Workbook

Sheet Cover
B2: Priced In: MarketAxess (MKTX)
B3: Reverse DCF, model v1.0. Inputs as of the Oct 13, 2026 close; model locked Oct 14, 2026 (commit 0735af0).
B4: Exchanges | US | reports in USD
B6: The question
B7: What revenue growth over the next five years does today's price imply, and is that more or less than the company has delivered and analysts expect?
B9: Answer
B10: Price at the lock ($) | C10: =Inputs!$C$6 -> 164.53538
B11: Implied 5-year revenue growth | C11: =Solver!$W$7 -> 0.084007684
B12: Anchor (history and analysts) | C12: =Inputs!$C$43 -> 0.057829158
B13: Gap (implied - anchor) | C13: =C11-C12 -> 0.026178525
B14: Verdict | C14: Deal price
B15: WACC | C15: =WACC!$C$37 -> 0.077507582
B16: Terminal growth | C16: =Inputs!$C$37 -> 0.0283
B17: Unlevered free-cash-flow margin | C17: =Inputs!$C$23 -> 0.22332563
B18: Your view of growth (Inputs, yellow) | C18: =Inputs!$C$45 -> 0.057829158
B19: Value per share at your view ($) | C19: =DCF!$C$41 -> 141.99835
B20: Upside or downside at your view | C20: =DCF!$C$43 -> -0.13697378
B22: Fit flag: Deal price
B23: ICE agreed on July 30, 2026 to buy MarketAxess for $167 a share in cash; the stock trades on the deal, not on growth.
B25: How to use this file
B26: 1. Change any blue cell on Inputs, History or WACC; everything recalculates, including the solver.
B27: 2. The Solver tab finds implied growth by bisection with formulas, so you never need Goal Seek. 40 steps narrow a 150-point range to well under 0.0001%.
B28: 3. Type your own growth view in the yellow cell on Inputs; DCF panel B and this page show what the stock is worth if you're right.
B29: 4. Check confirms this workbook matches the Python pipeline that runs the site.
B31: Colour key
B32: Typed input with a source | C32: 1234
B33: Formula | C33: =C32*2 -> 2468
B34: Link to another tab | C34: =Inputs!$C$12 -> 870.03
B35: Your view (edit this one) | C35: =Inputs!$C$45 -> 0.057829158
B37: Live site
B38: https://claude.ai/artifact/DS3n4CgaKxaSLzkXDsBKuK
B40: Built by Rohan Jayapalan. Not investment advice.

Sheet Inputs
B2: MarketAxess (MKTX): inputs
B3: Blue cells are typed inputs with a source. Black cells are formulas. Change a blue cell and every tab recalculates.
B5: Market and price
B6: Price per share at the lock ($) | C6: 164.53538 | E6: Market cap divided by shares from Stock Analysis at the Oct 13, 2026 close.
B7: Diluted shares outstanding (mm) | C7: 35.19 | E7: Stock Analysis statistics page, Oct 13, 2026.
B8: Market value of equity ($mm) | C8: =C6*C7 -> 5790 | E8: Price x shares.
B10: Trailing 12 months
B11: Revenue, reported ($mm) | C11: 870.03 | E11: Stock Analysis income statement, trailing 12 months.
B12: Revenue used in the model ($mm) | C12: =C11 -> 870.03 | E12: Same as reported.
B13: Free cash flow, reported (cash from operations - capex) ($mm) | C13: 194.3 | E13: Stock Analysis cash flow statement, trailing 12 months.
B14: Free cash flow before adjustments ($mm) | C14: =C13 -> 194.3 | E14: Same as reported.
B15: Less: adjustments ($mm) | C15: 0 | E15: None for this company.
B16: Free cash flow used ($mm) | C16: =C14-C15 -> 194.3
B17: Operating income ($mm) | C17: 357.17 | E17: Stock Analysis, trailing 12 months.
B18: Pretax income ($mm) | C18: 367.07 | E18: Stock Analysis, trailing 12 months.
B19: Interest proxy: operating income - pretax, floored at zero ($mm) | C19: =MAX(0,C17-C18) -> 0 | E19: Net interest and other non-operating costs. Adding it back (after tax) turns levered FCF into unlevered FCF.
B20: Tax rate | C20: 0.25 | E20: Statutory blend: 25% US (21% federal plus state), 26.5% Canada (federal plus Ontario).
B21: After-tax interest added back ($mm) | C21: =C19*(1-C20) -> 0
B22: Unlevered free cash flow ($mm) | C22: =C16+C21 -> 194.3
B23: Unlevered free-cash-flow margin | C23: =C22/C12 -> 0.22332563 | E23: Held flat for all 10 years in the model.
B24: EBITDA ($mm) | C24: 434.96 | E24: Stock Analysis, trailing 12 months.
B26: Balance sheet
B27: Total debt ($mm) | C27: 178.91 | E27: Stock Analysis balance sheet, latest quarter.
B28: Cash and equivalents ($mm) | C28: 346.31 | E28: Stock Analysis balance sheet, latest quarter.
B29: Net debt ($mm) | C29: =C27-C28 -> -167.4
B31: Rates
B32: 10-year US Treasury yield | C32: 0.0521 | E32: US Treasury daily par yield curve, Oct 13, 2026.
B33: 10-year TIPS real yield | C33: 0.0288 | E33: US Treasury daily real yield curve, Oct 13, 2026.
B34: Breakeven inflation | C34: =C32-C33 -> 0.0233 | E34: Nominal minus real: the market's inflation expectation.
B35: Risk-free rate used | C35: =C32 -> 0.0521
B36: Real growth added to inflation | C36: 0.005 | E36: Half a point of long-run real growth.
B37: Terminal growth | C37: =MIN(C34+C36,C35) -> 0.0283 | E37: Capped at the risk-free rate.
B38: Equity risk premium | C38: 0.0423 | E38: Damodaran implied equity risk premium, start of 2026.
B40: Growth anchor and verdict
B41: Past revenue growth (CAGR) | C41: =History!$C$12 -> 0.049858317 | E41: FY2021 to the 12 months ended June 2026
B42: Analysts' revenue growth forecast | C42: 0.0658 | E42: Analysts' 3-year revenue CAGR forecast (stockanalysis)
B43: Anchor (average of the two) | C43: =AVERAGE(C41:C42) -> 0.057829158 | E43: AVERAGE skips the n/a text when history isn't used.
B44: Verdict band (+/-) | C44: 0.03 | E44: Set before any backtest and never changed.
B45: Your view of 5-year revenue growth | C45: 0.057829158 | E45: Type your own view. It starts at the anchor. DCF panel B and the Cover show what the stock is worth at your view.
B46: Years at the solved growth rate | C46: 5 | E46: Model v1.0: 5 years at the growth rate, then a straight-line fade.
B47: Years of fade to terminal growth | C47: 5 | E47: Years 1 to 10 are on the Solver and DCF tabs; years past 10 grow at the terminal rate.

Sheet History
B2: MarketAxess (MKTX): revenue history
B3: Revenue from Stock Analysis income statements; the window is chosen so acquisitions and disposals don't count as growth.
B5: Fiscal year | C5: FY2021 | D5: FY2022 | E5: FY2023 | F5: FY2024 | G5: FY2025 | H5: TTM Jun-26
B6: Revenue ($mm) | C6: 698.95 | D6: 718.3 | E6: 752.55 | F6: 817.1 | G6: 846.27 | H6: 870.03
B7: Growth on the prior year | D7: =D6/C6-1 -> 0.027684384 | E7: =E6/D6-1 -> 0.047682027 | F7: =F6/E6-1 -> 0.085775032 | G7: =G6/F6-1 -> 0.035699425
B10: History window
B11: Start year | C11: FY2021 | E11: Years from start to TTM | G11: 4.5
B12: Revenue CAGR, start to TTM | C12: =(H6/INDEX(C6:H6,MATCH(C11,C5:H5,0)))^(1/G11)-1 -> 0.049858317 | I12: FY2021 to the 12 months ended June 2026
B15: Free-cash-flow margin history
B16: Fiscal year | C16: 2021 | D16: 2022 | E16: 2023 | F16: 2024 | G16: 2025
B17: (CFO - capex) / revenue | C17: 0.3786 | D17: 0.3844 | E17: 0.4311 | F17: 0.4593 | G17: 0.4419 | I17: SEC XBRL filings (NetCashProvidedByOperatingActivities, PaymentsToAcquirePropertyPlantAndEquipment, revenue tags).
B18: Plus today's interest add-back | C18: =C17+(Inputs!$C$23-Inputs!$C$16/Inputs!$C$12) -> 0.3786 | D18: =D17+(Inputs!$C$23-Inputs!$C$16/Inputs!$C$12) -> 0.3844 | E18: =E17+(Inputs!$C$23-Inputs!$C$16/Inputs!$C$12) -> 0.4311 | F18: =F17+(Inputs!$C$23-Inputs!$C$16/Inputs!$C$12) -> 0.4593 | G18: =G17+(Inputs!$C$23-Inputs!$C$16/Inputs!$C$12) -> 0.4419
B19: Range (the margin slider's shaded zone) | C19: =MIN(C18:G18) -> 0.3786 | D19: =MAX(C18:G18) -> 0.4593

Sheet WACC
B2: MarketAxess (MKTX): cost of capital
B3: Bottom-up beta: the median unlevered beta of the company's group, relevered for this company's debt.
B5: Peer | C5: Raw beta | D5: Debt ($mm) | E5: Equity ($mm) | F5: Tax rate | G5: Unlevered beta
B6: Intercontinental Exchange (ICE) | C6: 0.93718463 | D6: 20530 | E6: 87470 | F6: 0.25 | G6: =C6/(1+(1-F6)*D6/E6) -> 0.79690417 | H6: Raw betas: 60 monthly returns to Sep 2026 against the S&P 500 (S&P/TSX for TMX); Cboe uses Stock Analysis's 5-year beta. Debt and equity from Stock Analysis, Oct 13, 2026.
B7: CME Group (CME) | C7: 0.23986632 | D7: 3870 | E7: 99970 | F7: 0.25 | G7: =C7/(1+(1-F7)*D7/E7) -> 0.2330986
B8: Nasdaq (NDAQ) | C8: 0.99189493 | D8: 9320 | E8: 52250 | F8: 0.25 | G8: =C8/(1+(1-F8)*D8/E8) -> 0.87485669
B9: Cboe Global Markets (CBOE) | C9: 0.41 | D9: 1580 | E9: 30520 | F9: 0.25 | G9: =C9/(1+(1-F9)*D9/E9) -> 0.39467592
B10: TMX Group (X) | C10: 0.071228248 | D10: 2070 | E10: 15010 | F10: 0.265 | G10: =C10/(1+(1-F10)*D10/E10) -> 0.064672851
B11: Tradeweb (TW) | C11: 0.61179985 | D11: 150.34 | E11: 25740 | F11: 0.25 | G11: =C11/(1+(1-F11)*D11/E11) -> 0.60913153
B12: MarketAxess (MKTX) | C12: 0.79839643 | D12: 178.91 | E12: 5790 | F12: 0.25 | G12: =C12/(1+(1-F12)*D12/E12) -> 0.78031278
B14: Group median unlevered beta | C14: =MEDIAN(G6:G12) -> 0.60913153
B15: Debt ($mm) | C15: =Inputs!$C$27 -> 178.91
B16: Market value of equity ($mm) | C16: =Inputs!$C$8 -> 5790
B17: Tax rate | C17: =Inputs!$C$20 -> 0.25
B18: Relevered beta | C18: =WACC!$C$14*(1+(1-WACC!$C$17)*WACC!$C$15/WACC!$C$16) -> 0.62324807 | H18: Hamada: unlevered beta x (1 + (1 - tax) x debt / equity).
B19: Risk-free rate | C19: =Inputs!$C$35 -> 0.0521
B20: Equity risk premium | C20: =Inputs!$C$38 -> 0.0423
B21: Cost of equity | C21: =WACC!$C$19+WACC!$C$18*WACC!$C$20 -> 0.078463394 | H21: CAPM: risk-free + beta x premium.
B23: Debt-to-EBITDA spread table
B24: Debt / EBITDA below | C24: Spread
B25: 1 | C25: 0.01 | H25: Synthetic spread over the risk-free rate by leverage, a simplified version of Damodaran's ratings table; the last row covers anything at 4x or above.
B26: 2 | C26: 0.0125
B27: 3 | C27: 0.016
B28: 4 | C28: 0.02
B29: 99 | C29: 0.0275
B31: Debt / EBITDA | C31: =Inputs!$C$27/Inputs!$C$24 -> 0.41132518
B32: Credit spread | C32: =INDEX(C25:C29,COUNTIF(B25:B29,"<="&WACC!$C$31)+1) -> 0.01 | H32: First row whose limit is above this company's leverage.
B33: Pre-tax cost of debt | C33: =WACC!$C$19+WACC!$C$32 -> 0.0621
B34: After-tax cost of debt | C34: =WACC!$C$33*(1-WACC!$C$17) -> 0.046575
B35: Weight of debt | C35: =WACC!$C$15/(WACC!$C$15+WACC!$C$16) -> 0.029973647 | H35: Market-value weights.
B36: Weight of equity | C36: =1-WACC!$C$35 -> 0.97002635
B37: WACC | C37: =WACC!$C$36*WACC!$C$21+WACC!$C$35*WACC!$C$34 -> 0.077507582

Sheet Solver
A1: Solver: bisection for the growth rate that makes the model equal the price (replaces Goal Seek)
B2: Revenue | C2: =Inputs!$C$12 -> 870.03 | D2: Margin | E2: =Inputs!$C$23 -> 0.22332563 | F2: Debt | G2: =Inputs!$C$27 -> 178.91 | H2: Cash | I2: =Inputs!$C$28 -> 346.31 | J2: Shares | K2: =Inputs!$C$7 -> 35.19 | L2: Price | M2: =Inputs!$C$6 -> 164.53538 | N2: Years | O2: =Inputs!$C$46 -> 5 | P2: Fade | Q2: =Inputs!$C$47 -> 5
D3: Year | E3: 1 | F3: 2 | G3: 3 | H3: 4 | I3: 5 | J3: 6 | K3: 7 | L3: 8 | M3: 9 | N3: 10
A4: Each row tries the midpoint of the current range. If the value per share is above the price, the answer is lower, so the top of the range moves down; otherwise the bottom moves up.
A6: Base case: model WACC and terminal growth (40 steps) | E6: WACC | F6: =WACC!$C$37 -> 0.077507582 | G6: Terminal growth | I6: =Inputs!$C$37 -> 0.0283 | W6: Implied growth
A7: Step | B7: Low | C7: High | D7: Mid | E7: Rev Y1 | F7: Rev Y2 | G7: Rev Y3 | H7: Rev Y4 | I7: Rev Y5 | J7: Rev Y6 | K7: Rev Y7 | L7: Rev Y8 | M7: Rev Y9 | N7: Rev Y10 | O7: PV of FCF | P7: PV of TV | Q7: EV | R7: Equity | S7: Per share | T7: Value - price | W7: =$D$47 -> 0.084007684
A8: 1 | B8: -0.5 | C8: 1 | D8: =(B8+C8)/2 -> 0.25 | E8: =$C$2*(1+IF(E$3<=$O$2,$D8,$D8-($D8-$I$6)*MIN(E$3-$O$2,$Q$2)/$Q$2)) -> 1087.5375 | F8: =E8*(1+IF(F$3<=$O$2,$D8,$D8-($D8-$I$6)*MIN(F$3-$O$2,$Q$2)/$Q$2)) -> 1359.4219 | G8: =F8*(1+IF(G$3<=$O$2,$D8,$D8-($D8-$I$6)*MIN(G$3-$O$2,$Q$2)/$Q$2)) -> 1699.2773 | H8: =G8*(1+IF(H$3<=$O$2,$D8,$D8-($D8-$I$6)*MIN(H$3-$O$2,$Q$2)/$Q$2)) -> 2124.0967 | I8: =H8*(1+IF(I$3<=$O$2,$D8,$D8-($D8-$I$6)*MIN(I$3-$O$2,$Q$2)/$Q$2)) -> 2655.1208 | J8: =I8*(1+IF(J$3<=$O$2,$D8,$D8-($D8-$I$6)*MIN(J$3-$O$2,$Q$2)/$Q$2)) -> 3201.173 | K8: =J8*(1+IF(K$3<=$O$2,$D8,$D8-($D8-$I$6)*MIN(K$3-$O$2,$Q$2)/$Q$2)) -> 3717.5862 | L8: =K8*(1+IF(L$3<=$O$2,$D8,$D8-($D8-$I$6)*MIN(L$3-$O$2,$Q$2)/$Q$2)) -> 4152.4695 | M8: =L8*(1+IF(M$3<=$O$2,$D8,$D8-($D8-$I$6)*MIN(M$3-$O$2,$Q$2)/$Q$2)) -> 4454.1049 | N8: =M8*(1+IF(N$3<=$O$2,$D8,$D8-($D8-$I$6)*MIN(N$3-$O$2,$Q$2)/$Q$2)) -> 4580.156 | O8: =SUMPRODUCT(E8:N8,1/(1+$F$6)^$E$3:$N$3)*$E$2 -> 4002.814 | P8: =N8*$E$2*(1+$I$6)/($F$6-$I$6)/(1+$F$6)^$N$3 -> 10132.19 | Q8: =O8+P8 -> 14135.004 | R8: =Q8-$G$2+$I$2 -> 14302.404 | S8: =R8/$K$2 -> 406.43375 | T8: =S8-$M$2 -> 241.89837 | W8: =IF(OR(ABS(W7+0.5)<0.000001,ABS(W7-1)<0.000001),"Out of range","Solved") -> Solved
A9: 2 | B9: =IF(T8>0,B8,D8) -> -0.5 | C9: =IF(T8>0,D8,C8) -> 0.25 | D9: =(B9+C9)/2 -> -0.125 | E9: =$C$2*(1+IF(E$3<=$O$2,$D9,$D9-($D9-$I$6)*MIN(E$3-$O$2,$Q$2)/$Q$2)) -> 761.27625 | F9: =E9*(1+IF(F$3<=$O$2,$D9,$D9-($D9-$I$6)*MIN(F$3-$O$2,$Q$2)/$Q$2)) -> 666.11672 | G9: =F9*(1+IF(G$3<=$O$2,$D9,$D9-($D9-$I$6)*MIN(G$3-$O$2,$Q$2)/$Q$2)) -> 582.85213 | H9: =G9*(1+IF(H$3<=$O$2,$D9,$D9-($D9-$I$6)*MIN(H$3-$O$2,$Q$2)/$Q$2)) -> 509.99561 | I9: =H9*(1+IF(I$3<=$O$2,$D9,$D9-($D9-$I$6)*MIN(I$3-$O$2,$Q$2)/$Q$2)) -> 446.24616 | J9: =I9*(1+IF(J$3<=$O$2,$D9,$D9-($D9-$I$6)*MIN(J$3-$O$2,$Q$2)/$Q$2)) -> 404.1473 | K9: =J9*(1+IF(K$3<=$O$2,$D9,$D9-($D9-$I$6)*MIN(K$3-$O$2,$Q$2)/$Q$2)) -> 378.4112 | L9: =K9*(1+IF(L$3<=$O$2,$D9,$D9-($D9-$I$6)*MIN(L$3-$O$2,$Q$2)/$Q$2)) -> 365.91606 | M9: =L9*(1+IF(M$3<=$O$2,$D9,$D9-($D9-$I$6)*MIN(M$3-$O$2,$Q$2)/$Q$2)) -> 365.0525 | N9: =M9*(1+IF(N$3<=$O$2,$D9,$D9-($D9-$I$6)*MIN(N$3-$O$2,$Q$2)/$Q$2)) -> 375.38348 | O9: =SUMPRODUCT(E9:N9,1/(1+$F$6)^$E$3:$N$3)*$E$2 -> 777.20519 | P9: =N9*$E$2*(1+$I$6)/($F$6-$I$6)/(1+$F$6)^$N$3 -> 830.42076 | Q9: =O9+P9 -> 1607.6259 | R9: =Q9-$G$2+$I$2 -> 1775.0259 | S9: =R9/$K$2 -> 50.441203 | T9: =S9-$M$2 -> -114.09418
A10: 3 | B10: =IF(T9>0,B9,D9) -> -0.125 | C10: =IF(T9>0,D9,C9) -> 0.25 | D10: =(B10+C10)/2 -> 0.0625 | E10: =$C$2*(1+IF(E$3<=$O$2,$D10,$D10-($D10-$I$6)*MIN(E$3-$O$2,$Q$2)/$Q$2)) -> 924.40688 | F10: =E10*(1+IF(F$3<=$O$2,$D10,$D10-($D10-$I$6)*MIN(F$3-$O$2,$Q$2)/$Q$2)) -> 982.1823 | G10: =F10*(1+IF(G$3<=$O$2,$D10,$D10-($D10-$I$6)*MIN(G$3-$O$2,$Q$2)/$Q$2)) -> 1043.5687 | H10: =G10*(1+IF(H$3<=$O$2,$D10,$D10-($D10-$I$6)*MIN(H$3-$O$2,$Q$2)/$Q$2)) -> 1108.7917 | I10: =H10*(1+IF(I$3<=$O$2,$D10,$D10-($D10-$I$6)*MIN(I$3-$O$2,$Q$2)/$Q$2)) -> 1178.0912 | J10: =I10*(1+IF(J$3<=$O$2,$D10,$D10-($D10-$I$6)*MIN(J$3-$O$2,$Q$2)/$Q$2)) -> 1243.6638 | K10: =J10*(1+IF(K$3<=$O$2,$D10,$D10-($D10-$I$6)*MIN(K$3-$O$2,$Q$2)/$Q$2)) -> 1304.3794 | L10: =K10*(1+IF(L$3<=$O$2,$D10,$D10-($D10-$I$6)*MIN(L$3-$O$2,$Q$2)/$Q$2)) -> 1359.1373 | M10: =L10*(1+IF(M$3<=$O$2,$D10,$D10-($D10-$I$6)*MIN(M$3-$O$2,$Q$2)/$Q$2)) -> 1406.8974 | N10: =M10*(1+IF(N$3<=$O$2,$D10,$D10-($D10-$I$6)*MIN(N$3-$O$2,$Q$2)/$Q$2)) -> 1446.7126 | O10: =SUMPRODUCT(E10:N10,1/(1+$F$6)^$E$3:$N$3)*$E$2 -> 1762.5397 | P10: =N10*$E$2*(1+$I$6)/($F$6-$I$6)/(1+$F$6)^$N$3 -> 3200.4076 | Q10: =O10+P10 -> 4962.9473 | R10: =Q10-$G$2+$I$2 -> 5130.3473 | S10: =R10/$K$2 -> 145.78992 | T10: =S10-$M$2 -> -18.74546
A11: 4 | B11: =IF(T10>0,B10,D10) -> 0.0625 | C11: =IF(T10>0,D10,C10) -> 0.25 | D11: =(B11+C11)/2 -> 0.15625 | E11: =$C$2*(1+IF(E$3<=$O$2,$D11,$D11-($D11-$I$6)*MIN(E$3-$O$2,$Q$2)/$Q$2)) -> 1005.9722 | F11: =E11*(1+IF(F$3<=$O$2,$D11,$D11-($D11-$I$6)*MIN(F$3-$O$2,$Q$2)/$Q$2)) -> 1163.1553 | G11: =F11*(1+IF(G$3<=$O$2,$D11,$D11-($D11-$I$6)*MIN(G$3-$O$2,$Q$2)/$Q$2)) -> 1344.8984 | H11: =G11*(1+IF(H$3<=$O$2,$D11,$D11-($D11-$I$6)*MIN(H$3-$O$2,$Q$2)/$Q$2)) -> 1555.0387 | I11: =H11*(1+IF(I$3<=$O$2,$D11,$D11-($D11-$I$6)*MIN(I$3-$O$2,$Q$2)/$Q$2)) -> 1798.0135 | J11: =I11*(1+IF(J$3<=$O$2,$D11,$D11-($D11-$I$6)*MIN(J$3-$O$2,$Q$2)/$Q$2)) -> 2032.942 | K11: =J11*(1+IF(K$3<=$O$2,$D11,$D11-($D11-$I$6)*MIN(K$3-$O$2,$Q$2)/$Q$2)) -> 2246.5432 | L11: =K11*(1+IF(L$3<=$O$2,$D11,$D11-($D11-$I$6)*MIN(L$3-$O$2,$Q$2)/$Q$2)) -> 2425.0985 | M11: =L11*(1+IF(M$3<=$O$2,$D11,$D11-($D11-$I$6)*MIN(M$3-$O$2,$Q$2)/$Q$2)) -> 2555.787 | N11: =M11*(1+IF(N$3<=$O$2,$D11,$D11-($D11-$I$6)*MIN(N$3-$O$2,$Q$2)/$Q$2)) -> 2628.1158 | O11: =SUMPRODUCT(E11:N11,1/(1+$F$6)^$E$3:$N$3)*$E$2 -> 2661.8266 | P11: =N11*$E$2*(1+$I$6)/($F$6-$I$6)/(1+$F$6)^$N$3 -> 5813.8996 | Q11: =O11+P11 -> 8475.7262 | R11: =Q11-$G$2+$I$2 -> 8643.1262 | S11: =R11/$K$2 -> 245.61313 | T11: =S11-$M$2 -> 81.077754
A12: 5 | B12: =IF(T11>0,B11,D11) -> 0.0625 | C12: =IF(T11>0,D11,C11) -> 0.15625 | D12: =(B12+C12)/2 -> 0.109375 | E12: =$C$2*(1+IF(E$3<=$O$2,$D12,$D12-($D12-$I$6)*MIN(E$3-$O$2,$Q$2)/$Q$2)) -> 965.18953 | F12: =E12*(1+IF(F$3<=$O$2,$D12,$D12-($D12-$I$6)*MIN(F$3-$O$2,$Q$2)/$Q$2)) -> 1070.7571 | G12: =F12*(1+IF(G$3<=$O$2,$D12,$D12-($D12-$I$6)*MIN(G$3-$O$2,$Q$2)/$Q$2)) -> 1187.8712 | H12: =G12*(1+IF(H$3<=$O$2,$D12,$D12-($D12-$I$6)*MIN(H$3-$O$2,$Q$2)/$Q$2)) -> 1317.7946 | I12: =H12*(1+IF(I$3<=$O$2,$D12,$D12-($D12-$I$6)*MIN(I$3-$O$2,$Q$2)/$Q$2)) -> 1461.9284 | J12: =I12*(1+IF(J$3<=$O$2,$D12,$D12-($D12-$I$6)*MIN(J$3-$O$2,$Q$2)/$Q$2)) -> 1598.1216 | K12: =J12*(1+IF(K$3<=$O$2,$D12,$D12-($D12-$I$6)*MIN(K$3-$O$2,$Q$2)/$Q$2)) -> 1721.0891 | L12: =K12*(1+IF(L$3<=$O$2,$D12,$D12-($D12-$I$6)*MIN(L$3-$O$2,$Q$2)/$Q$2)) -> 1825.6109 | M12: =L12*(1+IF(M$3<=$O$2,$D12,$D12-($D12-$I$6)*MIN(M$3-$O$2,$Q$2)/$Q$2)) -> 1906.8779 | N12: =M12*(1+IF(N$3<=$O$2,$D12,$D12-($D12-$I$6)*MIN(N$3-$O$2,$Q$2)/$Q$2)) -> 1960.8426 | O12: =SUMPRODUCT(E12:N12,1/(1+$F$6)^$E$3:$N$3)*$E$2 -> 2166.6151 | P12: =N12*$E$2*(1+$I$6)/($F$6-$I$6)/(1+$F$6)^$N$3 -> 4337.7624 | Q12: =O12+P12 -> 6504.3775 | R12: =Q12-$G$2+$I$2 -> 6671.7775 | S12: =R12/$K$2 -> 189.59299 | T12: =S12-$M$2 -> 25.057615
A13: 6 | B13: =IF(T12>0,B12,D12) -> 0.0625 | C13: =IF(T12>0,D12,C12) -> 0.109375 | D13: =(B13+C13)/2 -> 0.0859375 | E13: =$C$2*(1+IF(E$3<=$O$2,$D13,$D13-($D13-$I$6)*MIN(E$3-$O$2,$Q$2)/$Q$2)) -> 944.7982 | F13: =E13*(1+IF(F$3<=$O$2,$D13,$D13-($D13-$I$6)*MIN(F$3-$O$2,$Q$2)/$Q$2)) -> 1025.9918 | G13: =F13*(1+IF(G$3<=$O$2,$D13,$D13-($D13-$I$6)*MIN(G$3-$O$2,$Q$2)/$Q$2)) -> 1114.163 | H13: =G13*(1+IF(H$3<=$O$2,$D13,$D13-($D13-$I$6)*MIN(H$3-$O$2,$Q$2)/$Q$2)) -> 1209.9113 | I13: =H13*(1+IF(I$3<=$O$2,$D13,$D13-($D13-$I$6)*MIN(I$3-$O$2,$Q$2)/$Q$2)) -> 1313.8881 | J13: =I13*(1+IF(J$3<=$O$2,$D13,$D13-($D13-$I$6)*MIN(J$3-$O$2,$Q$2)/$Q$2)) -> 1411.6545 | K13: =J13*(1+IF(K$3<=$O$2,$D13,$D13-($D13-$I$6)*MIN(K$3-$O$2,$Q$2)/$Q$2)) -> 1500.4229 | L13: =K13*(1+IF(L$3<=$O$2,$D13,$D13-($D13-$I$6)*MIN(L$3-$O$2,$Q$2)/$Q$2)) -> 1577.4771 | M13: =L13*(1+IF(M$3<=$O$2,$D13,$D13-($D13-$I$6)*MIN(M$3-$O$2,$Q$2)/$Q$2)) -> 1640.3041 | N13: =M13*(1+IF(N$3<=$O$2,$D13,$D13-($D13-$I$6)*MIN(N$3-$O$2,$Q$2)/$Q$2)) -> 1686.7247 | O13: =SUMPRODUCT(E13:N13,1/(1+$F$6)^$E$3:$N$3)*$E$2 -> 1954.2295 | P13: =N13*$E$2*(1+$I$6)/($F$6-$I$6)/(1+$F$6)^$N$3 -> 3731.3607 | Q13: =O13+P13 -> 5685.5902 | R13: =Q13-$G$2+$I$2 -> 5852.9902 | S13: =R13/$K$2 -> 166.32538 | T13: =S13-$M$2 -> 1.7900016
A14: 7 | B14: =IF(T13>0,B13,D13) -> 0.0625 | C14: =IF(T13>0,D13,C13) -> 0.0859375 | D14: =(B14+C14)/2 -> 0.07421875 | E14: =$C$2*(1+IF(E$3<=$O$2,$D14,$D14-($D14-$I$6)*MIN(E$3-$O$2,$Q$2)/$Q$2)) -> 934.60254 | F14: =E14*(1+IF(F$3<=$O$2,$D14,$D14-($D14-$I$6)*MIN(F$3-$O$2,$Q$2)/$Q$2)) -> 1003.9676 | G14: =F14*(1+IF(G$3<=$O$2,$D14,$D14-($D14-$I$6)*MIN(G$3-$O$2,$Q$2)/$Q$2)) -> 1078.4808 | H14: =G14*(1+IF(H$3<=$O$2,$D14,$D14-($D14-$I$6)*MIN(H$3-$O$2,$Q$2)/$Q$2)) -> 1158.5243 | I14: =H14*(1+IF(I$3<=$O$2,$D14,$D14-($D14-$I$6)*MIN(I$3-$O$2,$Q$2)/$Q$2)) -> 1244.5085 | J14: =I14*(1+IF(J$3<=$O$2,$D14,$D14-($D14-$I$6)*MIN(J$3-$O$2,$Q$2)/$Q$2)) -> 1325.4451 | K14: =J14*(1+IF(K$3<=$O$2,$D14,$D14-($D14-$I$6)*MIN(K$3-$O$2,$Q$2)/$Q$2)) -> 1399.4729 | L14: =K14*(1+IF(L$3<=$O$2,$D14,$D14-($D14-$I$6)*MIN(L$3-$O$2,$Q$2)/$Q$2)) -> 1464.7828 | M14: =L14*(1+IF(M$3<=$O$2,$D14,$D14-($D14-$I$6)*MIN(M$3-$O$2,$Q$2)/$Q$2)) -> 1519.6883 | N14: =M14*(1+IF(N$3<=$O$2,$D14,$D14-($D14-$I$6)*MIN(N$3-$O$2,$Q$2)/$Q$2)) -> 1562.6955 | O14: =SUMPRODUCT(E14:N14,1/(1+$F$6)^$E$3:$N$3)*$E$2 -> 1855.919 | P14: =N14*$E$2*(1+$I$6)/($F$6-$I$6)/(1+$F$6)^$N$3 -> 3456.9843 | Q14: =O14+P14 -> 5312.9032 | R14: =Q14-$G$2+$I$2 -> 5480.3032 | S14: =R14/$K$2 -> 155.73468 | T14: =S14-$M$2 -> -8.8007036
A15: 8 | B15: =IF(T14>0,B14,D14) -> 0.07421875 | C15: =IF(T14>0,D14,C14) -> 0.0859375 | D15: =(B15+C15)/2 -> 0.080078125 | E15: =$C$2*(1+IF(E$3<=$O$2,$D15,$D15-($D15-$I$6)*MIN(E$3-$O$2,$Q$2)/$Q$2)) -> 939.70037 | F15: =E15*(1+IF(F$3<=$O$2,$D15,$D15-($D15-$I$6)*MIN(F$3-$O$2,$Q$2)/$Q$2)) -> 1014.9498 | G15: =F15*(1+IF(G$3<=$O$2,$D15,$D15-($D15-$I$6)*MIN(G$3-$O$2,$Q$2)/$Q$2)) -> 1096.2251 | H15: =G15*(1+IF(H$3<=$O$2,$D15,$D15-($D15-$I$6)*MIN(H$3-$O$2,$Q$2)/$Q$2)) -> 1184.0087 | I15: =H15*(1+IF(I$3<=$O$2,$D15,$D15-($D15-$I$6)*MIN(I$3-$O$2,$Q$2)/$Q$2)) -> 1278.8219 | J15: =I15*(1+IF(J$3<=$O$2,$D15,$D15-($D15-$I$6)*MIN(J$3-$O$2,$Q$2)/$Q$2)) -> 1367.9846 | K15: =J15*(1+IF(K$3<=$O$2,$D15,$D15-($D15-$I$6)*MIN(K$3-$O$2,$Q$2)/$Q$2)) -> 1449.1976 | L15: =K15*(1+IF(L$3<=$O$2,$D15,$D15-($D15-$I$6)*MIN(L$3-$O$2,$Q$2)/$Q$2)) -> 1520.2246 | M15: =L15*(1+IF(M$3<=$O$2,$D15,$D15-($D15-$I$6)*MIN(M$3-$O$2,$Q$2)/$Q$2)) -> 1578.9898 | N15: =M15*(1+IF(N$3<=$O$2,$D15,$D15-($D15-$I$6)*MIN(N$3-$O$2,$Q$2)/$Q$2)) -> 1623.6752 | O15: =SUMPRODUCT(E15:N15,1/(1+$F$6)^$E$3:$N$3)*$E$2 -> 1904.443 | P15: =N15*$E$2*(1+$I$6)/($F$6-$I$6)/(1+$F$6)^$N$3 -> 3591.8831 | Q15: =O15+P15 -> 5496.3261 | R15: =Q15-$G$2+$I$2 -> 5663.7261 | S15: =R15/$K$2 -> 160.94703 | T15: =S15-$M$2 -> -3.5883452
A16: 9 | B16: =IF(T15>0,B15,D15) -> 0.080078125 | C16: =IF(T15>0,D15,C15) -> 0.0859375 | D16: =(B16+C16)/2 -> 0.083007812 | E16: =$C$2*(1+IF(E$3<=$O$2,$D16,$D16-($D16-$I$6)*MIN(E$3-$O$2,$Q$2)/$Q$2)) -> 942.24929 | F16: =E16*(1+IF(F$3<=$O$2,$D16,$D16-($D16-$I$6)*MIN(F$3-$O$2,$Q$2)/$Q$2)) -> 1020.4633 | G16: =F16*(1+IF(G$3<=$O$2,$D16,$D16-($D16-$I$6)*MIN(G$3-$O$2,$Q$2)/$Q$2)) -> 1105.1698 | H16: =G16*(1+IF(H$3<=$O$2,$D16,$D16-($D16-$I$6)*MIN(H$3-$O$2,$Q$2)/$Q$2)) -> 1196.9075 | I16: =H16*(1+IF(I$3<=$O$2,$D16,$D16-($D16-$I$6)*MIN(I$3-$O$2,$Q$2)/$Q$2)) -> 1296.2602 | J16: =I16*(1+IF(J$3<=$O$2,$D16,$D16-($D16-$I$6)*MIN(J$3-$O$2,$Q$2)/$Q$2)) -> 1389.6768 | K16: =J16*(1+IF(K$3<=$O$2,$D16,$D16-($D16-$I$6)*MIN(K$3-$O$2,$Q$2)/$Q$2)) -> 1474.6203 | L16: =K16*(1+IF(L$3<=$O$2,$D16,$D16-($D16-$I$6)*MIN(L$3-$O$2,$Q$2)/$Q$2)) -> 1548.6214 | M16: =L16*(1+IF(M$3<=$O$2,$D16,$D16-($D16-$I$6)*MIN(M$3-$O$2,$Q$2)/$Q$2)) -> 1609.3917 | N16: =M16*(1+IF(N$3<=$O$2,$D16,$D16-($D16-$I$6)*MIN(N$3-$O$2,$Q$2)/$Q$2)) -> 1654.9375 | O16: =SUMPRODUCT(E16:N16,1/(1+$F$6)^$E$3:$N$3)*$E$2 -> 1929.1766 | P16: =N16*$E$2*(1+$I$6)/($F$6-$I$6)/(1+$F$6)^$N$3 -> 3661.0413 | Q16: =O16+P16 -> 5590.2179 | R16: =Q16-$G$2+$I$2 -> 5757.6179 | S16: =R16/$K$2 -> 163.61517 | T16: =S16-$M$2 -> -0.92020749
A17: 10 | B17: =IF(T16>0,B16,D16) -> 0.083007812 | C17: =IF(T16>0,D16,C16) -> 0.0859375 | D17: =(B17+C17)/2 -> 0.084472656 | E17: =$C$2*(1+IF(E$3<=$O$2,$D17,$D17-($D17-$I$6)*MIN(E$3-$O$2,$Q$2)/$Q$2)) -> 943.52375 | F17: =E17*(1+IF(F$3<=$O$2,$D17,$D17-($D17-$I$6)*MIN(F$3-$O$2,$Q$2)/$Q$2)) -> 1023.2257 | G17: =F17*(1+IF(G$3<=$O$2,$D17,$D17-($D17-$I$6)*MIN(G$3-$O$2,$Q$2)/$Q$2)) -> 1109.6603 | H17: =G17*(1+IF(H$3<=$O$2,$D17,$D17-($D17-$I$6)*MIN(H$3-$O$2,$Q$2)/$Q$2)) -> 1203.3962 | I17: =H17*(1+IF(I$3<=$O$2,$D17,$D17-($D17-$I$6)*MIN(I$3-$O$2,$Q$2)/$Q$2)) -> 1305.0503 | J17: =I17*(1+IF(J$3<=$O$2,$D17,$D17-($D17-$I$6)*MIN(J$3-$O$2,$Q$2)/$Q$2)) -> 1400.6298 | K17: =J17*(1+IF(K$3<=$O$2,$D17,$D17-($D17-$I$6)*MIN(K$3-$O$2,$Q$2)/$Q$2)) -> 1487.4738 | L17: =K17*(1+IF(L$3<=$O$2,$D17,$D17-($D17-$I$6)*MIN(L$3-$O$2,$Q$2)/$Q$2)) -> 1562.9915 | M17: =L17*(1+IF(M$3<=$O$2,$D17,$D17-($D17-$I$6)*MIN(M$3-$O$2,$Q$2)/$Q$2)) -> 1624.7836 | N17: =M17*(1+IF(N$3<=$O$2,$D17,$D17-($D17-$I$6)*MIN(N$3-$O$2,$Q$2)/$Q$2)) -> 1670.765 | O17: =SUMPRODUCT(E17:N17,1/(1+$F$6)^$E$3:$N$3)*$E$2 -> 1941.6629 | P17: =N17*$E$2*(1+$I$6)/($F$6-$I$6)/(1+$F$6)^$N$3 -> 3696.0548 | Q17: =O17+P17 -> 5637.7177 | R17: =Q17-$G$2+$I$2 -> 5805.1177 | S17: =R17/$K$2 -> 164.96498 | T17: =S17-$M$2 -> 0.4296019
A18: 11 | B18: =IF(T17>0,B17,D17) -> 0.083007812 | C18: =IF(T17>0,D17,C17) -> 0.084472656 | D18: =(B18+C18)/2 -> 0.083740234 | E18: =$C$2*(1+IF(E$3<=$O$2,$D18,$D18-($D18-$I$6)*MIN(E$3-$O$2,$Q$2)/$Q$2)) -> 942.88652 | F18: =E18*(1+IF(F$3<=$O$2,$D18,$D18-($D18-$I$6)*MIN(F$3-$O$2,$Q$2)/$Q$2)) -> 1021.8441 | G18: =F18*(1+IF(G$3<=$O$2,$D18,$D18-($D18-$I$6)*MIN(G$3-$O$2,$Q$2)/$Q$2)) -> 1107.4135 | H18: =G18*(1+IF(H$3<=$O$2,$D18,$D18-($D18-$I$6)*MIN(H$3-$O$2,$Q$2)/$Q$2)) -> 1200.1486 | I18: =H18*(1+IF(I$3<=$O$2,$D18,$D18-($D18-$I$6)*MIN(I$3-$O$2,$Q$2)/$Q$2)) -> 1300.6493 | J18: =I18*(1+IF(J$3<=$O$2,$D18,$D18-($D18-$I$6)*MIN(J$3-$O$2,$Q$2)/$Q$2)) -> 1395.1443 | K18: =J18*(1+IF(K$3<=$O$2,$D18,$D18-($D18-$I$6)*MIN(K$3-$O$2,$Q$2)/$Q$2)) -> 1481.0352 | L18: =K18*(1+IF(L$3<=$O$2,$D18,$D18-($D18-$I$6)*MIN(L$3-$O$2,$Q$2)/$Q$2)) -> 1555.7921 | M18: =L18*(1+IF(M$3<=$O$2,$D18,$D18-($D18-$I$6)*MIN(M$3-$O$2,$Q$2)/$Q$2)) -> 1617.0717 | N18: =M18*(1+IF(N$3<=$O$2,$D18,$D18-($D18-$I$6)*MIN(N$3-$O$2,$Q$2)/$Q$2)) -> 1662.8348 | O18: =SUMPRODUCT(E18:N18,1/(1+$F$6)^$E$3:$N$3)*$E$2 -> 1935.4097 | P18: =N18*$E$2*(1+$I$6)/($F$6-$I$6)/(1+$F$6)^$N$3 -> 3678.5117 | Q18: =O18+P18 -> 5613.9214 | R18: =Q18-$G$2+$I$2 -> 5781.3214 | S18: =R18/$K$2 -> 164.28876 | T18: =S18-$M$2 -> -0.24662204
A19: 12 | B19: =IF(T18>0,B18,D18) -> 0.083740234 | C19: =IF(T18>0,D18,C18) -> 0.084472656 | D19: =(B19+C19)/2 -> 0.084106445 | E19: =$C$2*(1+IF(E$3<=$O$2,$D19,$D19-($D19-$I$6)*MIN(E$3-$O$2,$Q$2)/$Q$2)) -> 943.20513 | F19: =E19*(1+IF(F$3<=$O$2,$D19,$D19-($D19-$I$6)*MIN(F$3-$O$2,$Q$2)/$Q$2)) -> 1022.5348 | G19: =F19*(1+IF(G$3<=$O$2,$D19,$D19-($D19-$I$6)*MIN(G$3-$O$2,$Q$2)/$Q$2)) -> 1108.5365 | H19: =G19*(1+IF(H$3<=$O$2,$D19,$D19-($D19-$I$6)*MIN(H$3-$O$2,$Q$2)/$Q$2)) -> 1201.7716 | I19: =H19*(1+IF(I$3<=$O$2,$D19,$D19-($D19-$I$6)*MIN(I$3-$O$2,$Q$2)/$Q$2)) -> 1302.8483 | J19: =I19*(1+IF(J$3<=$O$2,$D19,$D19-($D19-$I$6)*MIN(J$3-$O$2,$Q$2)/$Q$2)) -> 1397.8848 | K19: =J19*(1+IF(K$3<=$O$2,$D19,$D19-($D19-$I$6)*MIN(K$3-$O$2,$Q$2)/$Q$2)) -> 1484.2515 | L19: =K19*(1+IF(L$3<=$O$2,$D19,$D19-($D19-$I$6)*MIN(L$3-$O$2,$Q$2)/$Q$2)) -> 1559.3882 | M19: =L19*(1+IF(M$3<=$O$2,$D19,$D19-($D19-$I$6)*MIN(M$3-$O$2,$Q$2)/$Q$2)) -> 1620.9236 | N19: =M19*(1+IF(N$3<=$O$2,$D19,$D19-($D19-$I$6)*MIN(N$3-$O$2,$Q$2)/$Q$2)) -> 1666.7958 | O19: =SUMPRODUCT(E19:N19,1/(1+$F$6)^$E$3:$N$3)*$E$2 -> 1938.5338 | P19: =N19*$E$2*(1+$I$6)/($F$6-$I$6)/(1+$F$6)^$N$3 -> 3687.2741 | Q19: =O19+P19 -> 5625.8079 | R19: =Q19-$G$2+$I$2 -> 5793.2079 | S19: =R19/$K$2 -> 164.62654 | T19: =S19-$M$2 -> 0.091159548
A20: 13 | B20: =IF(T19>0,B19,D19) -> 0.083740234 | C20: =IF(T19>0,D19,C19) -> 0.084106445 | D20: =(B20+C20)/2 -> 0.08392334 | E20: =$C$2*(1+IF(E$3<=$O$2,$D20,$D20-($D20-$I$6)*MIN(E$3-$O$2,$Q$2)/$Q$2)) -> 943.04582 | F20: =E20*(1+IF(F$3<=$O$2,$D20,$D20-($D20-$I$6)*MIN(F$3-$O$2,$Q$2)/$Q$2)) -> 1022.1894 | G20: =F20*(1+IF(G$3<=$O$2,$D20,$D20-($D20-$I$6)*MIN(G$3-$O$2,$Q$2)/$Q$2)) -> 1107.9749 | H20: =G20*(1+IF(H$3<=$O$2,$D20,$D20-($D20-$I$6)*MIN(H$3-$O$2,$Q$2)/$Q$2)) -> 1200.9599 | I20: =H20*(1+IF(I$3<=$O$2,$D20,$D20-($D20-$I$6)*MIN(I$3-$O$2,$Q$2)/$Q$2)) -> 1301.7484 | J20: =I20*(1+IF(J$3<=$O$2,$D20,$D20-($D20-$I$6)*MIN(J$3-$O$2,$Q$2)/$Q$2)) -> 1396.514 | K20: =J20*(1+IF(K$3<=$O$2,$D20,$D20-($D20-$I$6)*MIN(K$3-$O$2,$Q$2)/$Q$2)) -> 1482.6426 | L20: =K20*(1+IF(L$3<=$O$2,$D20,$D20-($D20-$I$6)*MIN(L$3-$O$2,$Q$2)/$Q$2)) -> 1557.5892 | M20: =L20*(1+IF(M$3<=$O$2,$D20,$D20-($D20-$I$6)*MIN(M$3-$O$2,$Q$2)/$Q$2)) -> 1618.9967 | N20: =M20*(1+IF(N$3<=$O$2,$D20,$D20-($D20-$I$6)*MIN(N$3-$O$2,$Q$2)/$Q$2)) -> 1664.8143 | O20: =SUMPRODUCT(E20:N20,1/(1+$F$6)^$E$3:$N$3)*$E$2 -> 1936.9711 | P20: =N20*$E$2*(1+$I$6)/($F$6-$I$6)/(1+$F$6)^$N$3 -> 3682.8906 | Q20: =O20+P20 -> 5619.8617 | R20: =Q20-$G$2+$I$2 -> 5787.2617 | S20: =R20/$K$2 -> 164.45757 | T20: =S20-$M$2 -> -0.077813771
... A47: 40 | B47: =IF(T46>0,B46,D46) -> 0.084007684 | C47: =IF(T46>0,D46,C46) -> 0.084007684 | D47: =(B47+C47)/2 -> 0.084007684 | E47: =$C$2*(1+IF(E$3<=$O$2,$D47,$D47-($D47-$I$6)*MIN(E$3-$O$2,$Q$2)/$Q$2)) -> 943.11921 | F47: =E47*(1+IF(F$3<=$O$2,$D47,$D47-($D47-$I$6)*MIN(F$3-$O$2,$Q$2)/$Q$2)) -> 1022.3485 | G47: =F47*(1+IF(G$3<=$O$2,$D47,$D47-($D47-$I$6)*MIN(G$3-$O$2,$Q$2)/$Q$2)) -> 1108.2336 | H47: =G47*(1+IF(H$3<=$O$2,$D47,$D47-($D47-$I$6)*MIN(H$3-$O$2,$Q$2)/$Q$2)) -> 1201.3337 | I47: =H47*(1+IF(I$3<=$O$2,$D47,$D47-($D47-$I$6)*MIN(I$3-$O$2,$Q$2)/$Q$2)) -> 1302.255 | J47: =I47*(1+IF(J$3<=$O$2,$D47,$D47-($D47-$I$6)*MIN(J$3-$O$2,$Q$2)/$Q$2)) -> 1397.1453 | K47: =J47*(1+IF(K$3<=$O$2,$D47,$D47-($D47-$I$6)*MIN(K$3-$O$2,$Q$2)/$Q$2)) -> 1483.3835 | L47: =K47*(1+IF(L$3<=$O$2,$D47,$D47-($D47-$I$6)*MIN(L$3-$O$2,$Q$2)/$Q$2)) -> 1558.4176 | M47: =L47*(1+IF(M$3<=$O$2,$D47,$D47-($D47-$I$6)*MIN(M$3-$O$2,$Q$2)/$Q$2)) -> 1619.884 | N47: =M47*(1+IF(N$3<=$O$2,$D47,$D47-($D47-$I$6)*MIN(N$3-$O$2,$Q$2)/$Q$2)) -> 1665.7267 | O47: =SUMPRODUCT(E47:N47,1/(1+$F$6)^$E$3:$N$3)*$E$2 -> 1937.6908 | P47: =N47*$E$2*(1+$I$6)/($F$6-$I$6)/(1+$F$6)^$N$3 -> 3684.9092 | Q47: =O47+P47 -> 5622.6 | R47: =Q47-$G$2+$I$2 -> 5790 | S47: =R47/$K$2 -> 164.53538 | T47: =S47-$M$2 -> -6.9223915e-10
A49: Grid block 2: row 1, column 1 of table A (24 steps) | E49: WACC | F49: =Sensitivity!$B$10 -> 0.067507582 | G49: Terminal growth | I49: =Sensitivity!$C$9 -> 0.0183
A50: Step | B50: Low | C50: High | D50: Mid | E50: Rev Y1 | F50: Rev Y2 | G50: Rev Y3 | H50: Rev Y4 | I50: Rev Y5 | J50: Rev Y6 | K50: Rev Y7 | L50: Rev Y8 | M50: Rev Y9 | N50: Rev Y10 | O50: PV of FCF | P50: PV of TV | Q50: EV | R50: Equity | S50: Per share | T50: Value - price
A51: 1 | B51: -0.5 | C51: 1 | D51: =(B51+C51)/2 -> 0.25 | E51: =$C$2*(1+IF(E$3<=$O$2,$D51,$D51-($D51-$I$49)*MIN(E$3-$O$2,$Q$2)/$Q$2)) -> 1087.5375 | F51: =E51*(1+IF(F$3<=$O$2,$D51,$D51-($D51-$I$49)*MIN(F$3-$O$2,$Q$2)/$Q$2)) -> 1359.4219 | G51: =F51*(1+IF(G$3<=$O$2,$D51,$D51-($D51-$I$49)*MIN(G$3-$O$2,$Q$2)/$Q$2)) -> 1699.2773 | H51: =G51*(1+IF(H$3<=$O$2,$D51,$D51-($D51-$I$49)*MIN(H$3-$O$2,$Q$2)/$Q$2)) -> 2124.0967 | I51: =H51*(1+IF(I$3<=$O$2,$D51,$D51-($D51-$I$49)*MIN(I$3-$O$2,$Q$2)/$Q$2)) -> 2655.1208 | J51: =I51*(1+IF(J$3<=$O$2,$D51,$D51-($D51-$I$49)*MIN(J$3-$O$2,$Q$2)/$Q$2)) -> 3195.8628 | K51: =J51*(1+IF(K$3<=$O$2,$D51,$D51-($D51-$I$49)*MIN(K$3-$O$2,$Q$2)/$Q$2)) -> 3698.6359 | L51: =K51*(1+IF(L$3<=$O$2,$D51,$D51-($D51-$I$49)*MIN(L$3-$O$2,$Q$2)/$Q$2)) -> 4109.1105 | M51: =L51*(1+IF(M$3<=$O$2,$D51,$D51-($D51-$I$49)*MIN(M$3-$O$2,$Q$2)/$Q$2)) -> 4374.7234 | N51: =M51*(1+IF(N$3<=$O$2,$D51,$D51-($D51-$I$49)*MIN(N$3-$O$2,$Q$2)/$Q$2)) -> 4454.7808 | O51: =SUMPRODUCT(E51:N51,1/(1+$F$49)^$E$3:$N$3)*$E$2 -> 4208.541 | P51: =N51*$E$2*(1+$I$49)/($F$49-$I$49)/(1+$F$49)^$N$3 -> 10712.7 | Q51: =O51+P51 -> 14921.241 | R51: =Q51-$G$2+$I$2 -> 15088.641 | S51: =R51/$K$2 -> 428.77639 | T51: =S51-$M$2 -> 264.24101
A52: 2 | B52: =IF(T51>0,B51,D51) -> -0.5 | C52: =IF(T51>0,D51,C51) -> 0.25 | D52: =(B52+C52)/2 -> -0.125 | E52: =$C$2*(1+IF(E$3<=$O$2,$D52,$D52-($D52-$I$49)*MIN(E$3-$O$2,$Q$2)/$Q$2)) -> 761.27625 | F52: =E52*(1+IF(F$3<=$O$2,$D52,$D52-($D52-$I$49)*MIN(F$3-$O$2,$Q$2)/$Q$2)) -> 666.11672 | G52: =F52*(1+IF(G$3<=$O$2,$D52,$D52-($D52-$I$49)*MIN(G$3-$O$2,$Q$2)/$Q$2)) -> 582.85213 | H52: =G52*(1+IF(H$3<=$O$2,$D52,$D52-($D52-$I$49)*MIN(H$3-$O$2,$Q$2)/$Q$2)) -> 509.99561 | I52: =H52*(1+IF(I$3<=$O$2,$D52,$D52-($D52-$I$49)*MIN(I$3-$O$2,$Q$2)/$Q$2)) -> 446.24616 | J52: =I52*(1+IF(J$3<=$O$2,$D52,$D52-($D52-$I$49)*MIN(J$3-$O$2,$Q$2)/$Q$2)) -> 403.25481 | K52: =J52*(1+IF(K$3<=$O$2,$D52,$D52-($D52-$I$49)*MIN(K$3-$O$2,$Q$2)/$Q$2)) -> 375.96252 | L52: =K52*(1+IF(L$3<=$O$2,$D52,$D52-($D52-$I$49)*MIN(L$3-$O$2,$Q$2)/$Q$2)) -> 361.29246 | M52: =L52*(1+IF(M$3<=$O$2,$D52,$D52-($D52-$I$49)*MIN(M$3-$O$2,$Q$2)/$Q$2)) -> 357.54947 | N52: =M52*(1+IF(N$3<=$O$2,$D52,$D52-($D52-$I$49)*MIN(N$3-$O$2,$Q$2)/$Q$2)) -> 364.09263 | O52: =SUMPRODUCT(E52:N52,1/(1+$F$49)^$E$3:$N$3)*$E$2 -> 804.90563 | P52: =N52*$E$2*(1+$I$49)/($F$49-$I$49)/(1+$F$49)^$N$3 -> 875.55714 | Q52: =O52+P52 -> 1680.4628 | R52: =Q52-$G$2+$I$2 -> 1847.8628 | S52: =R52/$K$2 -> 52.511019 | T52: =S52-$M$2 -> -112.02436
A53: 3 | B53: =IF(T52>0,B52,D52) -> -0.125 | C53: =IF(T52>0,D52,C52) -> 0.25 | D53: =(B53+C53)/2 -> 0.0625 | E53: =$C$2*(1+IF(E$3<=$O$2,$D53,$D53-($D53-$I$49)*MIN(E$3-$O$2,$Q$2)/$Q$2)) -> 924.40688 | F53: =E53*(1+IF(F$3<=$O$2,$D53,$D53-($D53-$I$49)*MIN(F$3-$O$2,$Q$2)/$Q$2)) -> 982.1823 | G53: =F53*(1+IF(G$3<=$O$2,$D53,$D53-($D53-$I$49)*MIN(G$3-$O$2,$Q$2)/$Q$2)) -> 1043.5687 | H53: =G53*(1+IF(H$3<=$O$2,$D53,$D53-($D53-$I$49)*MIN(H$3-$O$2,$Q$2)/$Q$2)) -> 1108.7917 | I53: =H53*(1+IF(I$3<=$O$2,$D53,$D53-($D53-$I$49)*MIN(I$3-$O$2,$Q$2)/$Q$2)) -> 1178.0912 | J53: =I53*(1+IF(J$3<=$O$2,$D53,$D53-($D53-$I$49)*MIN(J$3-$O$2,$Q$2)/$Q$2)) -> 1241.3076 | K53: =J53*(1+IF(K$3<=$O$2,$D53,$D53-($D53-$I$49)*MIN(K$3-$O$2,$Q$2)/$Q$2)) -> 1296.943 | L53: =K53*(1+IF(L$3<=$O$2,$D53,$D53-($D53-$I$49)*MIN(L$3-$O$2,$Q$2)/$Q$2)) -> 1343.607 | M53: =L53*(1+IF(M$3<=$O$2,$D53,$D53-($D53-$I$49)*MIN(M$3-$O$2,$Q$2)/$Q$2)) -> 1380.0725 | N53: =M53*(1+IF(N$3<=$O$2,$D53,$D53-($D53-$I$49)*MIN(N$3-$O$2,$Q$2)/$Q$2)) -> 1405.3278 | O53: =SUMPRODUCT(E53:N53,1/(1+$F$49)^$E$3:$N$3)*$E$2 -> 1841.0137 | P53: =N53*$E$2*(1+$I$49)/($F$49-$I$49)/(1+$F$49)^$N$3 -> 3379.4829 | Q53: =O53+P53 -> 5220.4966 | R53: =Q53-$G$2+$I$2 -> 5387.8966 | S53: =R53/$K$2 -> 153.10874 | T53: =S53-$M$2 -> -11.426638
A54: 4 | B54: =IF(T53>0,B53,D53) -> 0.0625 | C54: =IF(T53>0,D53,C53) -> 0.25 | D54: =(B54+C54)/2 -> 0.15625 | E54: =$C$2*(1+IF(E$3<=$O$2,$D54,$D54-($D54-$I$49)*MIN(E$3-$O$2,$Q$2)/$Q$2)) -> 1005.9722 | F54: =E54*(1+IF(F$3<=$O$2,$D54,$D54-($D54-$I$49)*MIN(F$3-$O$2,$Q$2)/$Q$2)) -> 1163.1553 | G54: =F54*(1+IF(G$3<=$O$2,$D54,$D54-($D54-$I$49)*MIN(G$3-$O$2,$Q$2)/$Q$2)) -> 1344.8984 | H54: =G54*(1+IF(H$3<=$O$2,$D54,$D54-($D54-$I$49)*MIN(H$3-$O$2,$Q$2)/$Q$2)) -> 1555.0387 | I54: =H54*(1+IF(I$3<=$O$2,$D54,$D54-($D54-$I$49)*MIN(I$3-$O$2,$Q$2)/$Q$2)) -> 1798.0135 | J54: =I54*(1+IF(J$3<=$O$2,$D54,$D54-($D54-$I$49)*MIN(J$3-$O$2,$Q$2)/$Q$2)) -> 2029.346 | K54: =J54*(1+IF(K$3<=$O$2,$D54,$D54-($D54-$I$49)*MIN(K$3-$O$2,$Q$2)/$Q$2)) -> 2234.452 | L54: =K54*(1+IF(L$3<=$O$2,$D54,$D54-($D54-$I$49)*MIN(L$3-$O$2,$Q$2)/$Q$2)) -> 2398.6395 | M54: =L54*(1+IF(M$3<=$O$2,$D54,$D54-($D54-$I$49)*MIN(M$3-$O$2,$Q$2)/$Q$2)) -> 2508.713 | N54: =M54*(1+IF(N$3<=$O$2,$D54,$D54-($D54-$I$49)*MIN(N$3-$O$2,$Q$2)/$Q$2)) -> 2554.6225 | O54: =SUMPRODUCT(E54:N54,1/(1+$F$49)^$E$3:$N$3)*$E$2 -> 2790.1988 | P54: =N54*$E$2*(1+$I$49)/($F$49-$I$49)/(1+$F$49)^$N$3 -> 6143.2663 | Q54: =O54+P54 -> 8933.4651 | R54: =Q54-$G$2+$I$2 -> 9100.8651 | S54: =R54/$K$2 -> 258.62077 | T54: =S54-$M$2 -> 94.085395
A55: 5 | B55: =IF(T54>0,B54,D54) -> 0.0625 | C55: =IF(T54>0,D54,C54) -> 0.15625 | D55: =(B55+C55)/2 -> 0.109375 | E55: =$C$2*(1+IF(E$3<=$O$2,$D55,$D55-($D55-$I$49)*MIN(E$3-$O$2,$Q$2)/$Q$2)) -> 965.18953 | F55: =E55*(1+IF(F$3<=$O$2,$D55,$D55-($D55-$I$49)*MIN(F$3-$O$2,$Q$2)/$Q$2)) -> 1070.7571 | G55: =F55*(1+IF(G$3<=$O$2,$D55,$D55-($D55-$I$49)*MIN(G$3-$O$2,$Q$2)/$Q$2)) -> 1187.8712 | H55: =G55*(1+IF(H$3<=$O$2,$D55,$D55-($D55-$I$49)*MIN(H$3-$O$2,$Q$2)/$Q$2)) -> 1317.7946 | I55: =H55*(1+IF(I$3<=$O$2,$D55,$D55-($D55-$I$49)*MIN(I$3-$O$2,$Q$2)/$Q$2)) -> 1461.9284 | J55: =I55*(1+IF(J$3<=$O$2,$D55,$D55-($D55-$I$49)*MIN(J$3-$O$2,$Q$2)/$Q$2)) -> 1595.1978 | K55: =J55*(1+IF(K$3<=$O$2,$D55,$D55-($D55-$I$49)*MIN(K$3-$O$2,$Q$2)/$Q$2)) -> 1711.5595 | L55: =K55*(1+IF(L$3<=$O$2,$D55,$D55-($D55-$I$49)*MIN(L$3-$O$2,$Q$2)/$Q$2)) -> 1805.2331 | M55: =L55*(1+IF(M$3<=$O$2,$D55,$D55-($D55-$I$49)*MIN(M$3-$O$2,$Q$2)/$Q$2)) -> 1871.1512 | N55: =M55*(1+IF(N$3<=$O$2,$D55,$D55-($D55-$I$49)*MIN(N$3-$O$2,$Q$2)/$Q$2)) -> 1905.3933 | O55: =SUMPRODUCT(E55:N55,1/(1+$F$49)^$E$3:$N$3)*$E$2 -> 2267.2397 | P55: =N55*$E$2*(1+$I$49)/($F$49-$I$49)/(1+$F$49)^$N$3 -> 4582.0227 | Q55: =O55+P55 -> 6849.2625 | R55: =Q55-$G$2+$I$2 -> 7016.6625 | S55: =R55/$K$2 -> 199.39365 | T55: =S55-$M$2 -> 34.858269
A56: 6 | B56: =IF(T55>0,B55,D55) -> 0.0625 | C56: =IF(T55>0,D55,C55) -> 0.109375 | D56: =(B56+C56)/2 -> 0.0859375 | E56: =$C$2*(1+IF(E$3<=$O$2,$D56,$D56-($D56-$I$49)*MIN(E$3-$O$2,$Q$2)/$Q$2)) -> 944.7982 | F56: =E56*(1+IF(F$3<=$O$2,$D56,$D56-($D56-$I$49)*MIN(F$3-$O$2,$Q$2)/$Q$2)) -> 1025.9918 | G56: =F56*(1+IF(G$3<=$O$2,$D56,$D56-($D56-$I$49)*MIN(G$3-$O$2,$Q$2)/$Q$2)) -> 1114.163 | H56: =G56*(1+IF(H$3<=$O$2,$D56,$D56-($D56-$I$49)*MIN(H$3-$O$2,$Q$2)/$Q$2)) -> 1209.9113 | I56: =H56*(1+IF(I$3<=$O$2,$D56,$D56-($D56-$I$49)*MIN(I$3-$O$2,$Q$2)/$Q$2)) -> 1313.8881 | J56: =I56*(1+IF(J$3<=$O$2,$D56,$D56-($D56-$I$49)*MIN(J$3-$O$2,$Q$2)/$Q$2)) -> 1409.0267 | K56: =J56*(1+IF(K$3<=$O$2,$D56,$D56-($D56-$I$49)*MIN(K$3-$O$2,$Q$2)/$Q$2)) -> 1491.9938 | L56: =K56*(1+IF(L$3<=$O$2,$D56,$D56-($D56-$I$49)*MIN(L$3-$O$2,$Q$2)/$Q$2)) -> 1559.6631 | M56: =L56*(1+IF(M$3<=$O$2,$D56,$D56-($D56-$I$49)*MIN(M$3-$O$2,$Q$2)/$Q$2)) -> 1609.3033 | N56: =M56*(1+IF(N$3<=$O$2,$D56,$D56-($D56-$I$49)*MIN(N$3-$O$2,$Q$2)/$Q$2)) -> 1638.7536 | O56: =SUMPRODUCT(E56:N56,1/(1+$F$49)^$E$3:$N$3)*$E$2 -> 2043.1473 | P56: =N56*$E$2*(1+$I$49)/($F$49-$I$49)/(1+$F$49)^$N$3 -> 3940.8169 | Q56: =O56+P56 -> 5983.9642 | R56: =Q56-$G$2+$I$2 -> 6151.3642 | S56: =R56/$K$2 -> 174.80433 | T56: =S56-$M$2 -> 10.268946
A57: 7 | B57: =IF(T56>0,B56,D56) -> 0.0625 | C57: =IF(T56>0,D56,C56) -> 0.0859375 | D57: =(B57+C57)/2 -> 0.07421875 | E57: =$C$2*(1+IF(E$3<=$O$2,$D57,$D57-($D57-$I$49)*MIN(E$3-$O$2,$Q$2)/$Q$2)) -> 934.60254 | F57: =E57*(1+IF(F$3<=$O$2,$D57,$D57-($D57-$I$49)*MIN(F$3-$O$2,$Q$2)/$Q$2)) -> 1003.9676 | G57: =F57*(1+IF(G$3<=$O$2,$D57,$D57-($D57-$I$49)*MIN(G$3-$O$2,$Q$2)/$Q$2)) -> 1078.4808 | H57: =G57*(1+IF(H$3<=$O$2,$D57,$D57-($D57-$I$49)*MIN(H$3-$O$2,$Q$2)/$Q$2)) -> 1158.5243 | I57: =H57*(1+IF(I$3<=$O$2,$D57,$D57-($D57-$I$49)*MIN(I$3-$O$2,$Q$2)/$Q$2)) -> 1244.5085 | J57: =I57*(1+IF(J$3<=$O$2,$D57,$D57-($D57-$I$49)*MIN(J$3-$O$2,$Q$2)/$Q$2)) -> 1322.9561 | K57: =J57*(1+IF(K$3<=$O$2,$D57,$D57-($D57-$I$49)*MIN(K$3-$O$2,$Q$2)/$Q$2)) -> 1391.553 | L57: =K57*(1+IF(L$3<=$O$2,$D57,$D57-($D57-$I$49)*MIN(L$3-$O$2,$Q$2)/$Q$2)) -> 1448.144 | M57: =L57*(1+IF(M$3<=$O$2,$D57,$D57-($D57-$I$49)*MIN(M$3-$O$2,$Q$2)/$Q$2)) -> 1490.8407 | N57: =M57*(1+IF(N$3<=$O$2,$D57,$D57-($D57-$I$49)*MIN(N$3-$O$2,$Q$2)/$Q$2)) -> 1518.1231 | O57: =SUMPRODUCT(E57:N57,1/(1+$F$49)^$E$3:$N$3)*$E$2 -> 1939.4649 | P57: =N57*$E$2*(1+$I$49)/($F$49-$I$49)/(1+$F$49)^$N$3 -> 3650.729 | Q57: =O57+P57 -> 5590.194 | R57: =Q57-$G$2+$I$2 -> 5757.594 | S57: =R57/$K$2 -> 163.61449 | T57: =S57-$M$2 -> -0.92088758
A58: 8 | B58: =IF(T57>0,B57,D57) -> 0.07421875 | C58: =IF(T57>0,D57,C57) -> 0.0859375 | D58: =(B58+C58)/2 -> 0.080078125 | E58: =$C$2*(1+IF(E$3<=$O$2,$D58,$D58-($D58-$I$49)*MIN(E$3-$O$2,$Q$2)/$Q$2)) -> 939.70037 | F58: =E58*(1+IF(F$3<=$O$2,$D58,$D58-($D58-$I$49)*MIN(F$3-$O$2,$Q$2)/$Q$2)) -> 1014.9498 | G58: =F58*(1+IF(G$3<=$O$2,$D58,$D58-($D58-$I$49)*MIN(G$3-$O$2,$Q$2)/$Q$2)) -> 1096.2251 | H58: =G58*(1+IF(H$3<=$O$2,$D58,$D58-($D58-$I$49)*MIN(H$3-$O$2,$Q$2)/$Q$2)) -> 1184.0087 | I58: =H58*(1+IF(I$3<=$O$2,$D58,$D58-($D58-$I$49)*MIN(I$3-$O$2,$Q$2)/$Q$2)) -> 1278.8219 | J58: =I58*(1+IF(J$3<=$O$2,$D58,$D58-($D58-$I$49)*MIN(J$3-$O$2,$Q$2)/$Q$2)) -> 1365.427 | K58: =J58*(1+IF(K$3<=$O$2,$D58,$D58-($D58-$I$49)*MIN(K$3-$O$2,$Q$2)/$Q$2)) -> 1441.0264 | L58: =K58*(1+IF(L$3<=$O$2,$D58,$D58-($D58-$I$49)*MIN(L$3-$O$2,$Q$2)/$Q$2)) -> 1503.0067 | M58: =L58*(1+IF(M$3<=$O$2,$D58,$D58-($D58-$I$49)*MIN(M$3-$O$2,$Q$2)/$Q$2)) -> 1549.0823 | N58: =M58*(1+IF(N$3<=$O$2,$D58,$D58-($D58-$I$49)*MIN(N$3-$O$2,$Q$2)/$Q$2)) -> 1577.4305 | O58: =SUMPRODUCT(E58:N58,1/(1+$F$49)^$E$3:$N$3)*$E$2 -> 1990.6365 | P58: =N58*$E$2*(1+$I$49)/($F$49-$I$49)/(1+$F$49)^$N$3 -> 3793.3495 | Q58: =O58+P58 -> 5783.9859 | R58: =Q58-$G$2+$I$2 -> 5951.3859 | S58: =R58/$K$2 -> 169.12151 | T58: =S58-$M$2 -> 4.5861309
A59: 9 | B59: =IF(T58>0,B58,D58) -> 0.07421875 | C59: =IF(T58>0,D58,C58) -> 0.080078125 | D59: =(B59+C59)/2 -> 0.077148438 | E59: =$C$2*(1+IF(E$3<=$O$2,$D59,$D59-($D59-$I$49)*MIN(E$3-$O$2,$Q$2)/$Q$2)) -> 937.15146 | F59: =E59*(1+IF(F$3<=$O$2,$D59,$D59-($D59-$I$49)*MIN(F$3-$O$2,$Q$2)/$Q$2)) -> 1009.4512 | G59: =F59*(1+IF(G$3<=$O$2,$D59,$D59-($D59-$I$49)*MIN(G$3-$O$2,$Q$2)/$Q$2)) -> 1087.3288 | H59: =G59*(1+IF(H$3<=$O$2,$D59,$D59-($D59-$I$49)*MIN(H$3-$O$2,$Q$2)/$Q$2)) -> 1171.2145 | I59: =H59*(1+IF(I$3<=$O$2,$D59,$D59-($D59-$I$49)*MIN(I$3-$O$2,$Q$2)/$Q$2)) -> 1261.5719 | J59: =I59*(1+IF(J$3<=$O$2,$D59,$D59-($D59-$I$49)*MIN(J$3-$O$2,$Q$2)/$Q$2)) -> 1344.0519 | K59: =J59*(1+IF(K$3<=$O$2,$D59,$D59-($D59-$I$49)*MIN(K$3-$O$2,$Q$2)/$Q$2)) -> 1416.1053 | L59: =K59*(1+IF(L$3<=$O$2,$D59,$D59-($D59-$I$49)*MIN(L$3-$O$2,$Q$2)/$Q$2)) -> 1475.3542 | M59: =L59*(1+IF(M$3<=$O$2,$D59,$D59-($D59-$I$49)*MIN(M$3-$O$2,$Q$2)/$Q$2)) -> 1519.7177 | N59: =M59*(1+IF(N$3<=$O$2,$D59,$D59-($D59-$I$49)*MIN(N$3-$O$2,$Q$2)/$Q$2)) -> 1547.5285 | O59: =SUMPRODUCT(E59:N59,1/(1+$F$49)^$E$3:$N$3)*$E$2 -> 1964.8853 | P59: =N59*$E$2*(1+$I$49)/($F$49-$I$49)/(1+$F$49)^$N$3 -> 3721.442 | Q59: =O59+P59 -> 5686.3273 | R59: =Q59-$G$2+$I$2 -> 5853.7273 | S59: =R59/$K$2 -> 166.34633 | T59: =S59-$M$2 -> 1.81095
A60: 10 | B60: =IF(T59>0,B59,D59) -> 0.07421875 | C60: =IF(T59>0,D59,C59) -> 0.077148438 | D60: =(B60+C60)/2 -> 0.075683594 | E60: =$C$2*(1+IF(E$3<=$O$2,$D60,$D60-($D60-$I$49)*MIN(E$3-$O$2,$Q$2)/$Q$2)) -> 935.877 | F60: =E60*(1+IF(F$3<=$O$2,$D60,$D60-($D60-$I$49)*MIN(F$3-$O$2,$Q$2)/$Q$2)) -> 1006.7075 | G60: =F60*(1+IF(G$3<=$O$2,$D60,$D60-($D60-$I$49)*MIN(G$3-$O$2,$Q$2)/$Q$2)) -> 1082.8988 | H60: =G60*(1+IF(H$3<=$O$2,$D60,$D60-($D60-$I$49)*MIN(H$3-$O$2,$Q$2)/$Q$2)) -> 1164.8564 | I60: =H60*(1+IF(I$3<=$O$2,$D60,$D60-($D60-$I$49)*MIN(I$3-$O$2,$Q$2)/$Q$2)) -> 1253.017 | J60: =I60*(1+IF(J$3<=$O$2,$D60,$D60-($D60-$I$49)*MIN(J$3-$O$2,$Q$2)/$Q$2)) -> 1333.4693 | K60: =J60*(1+IF(K$3<=$O$2,$D60,$D60-($D60-$I$49)*MIN(K$3-$O$2,$Q$2)/$Q$2)) -> 1403.7833 | L60: =K60*(1+IF(L$3<=$O$2,$D60,$D60-($D60-$I$49)*MIN(L$3-$O$2,$Q$2)/$Q$2)) -> 1461.6942 | M60: =L60*(1+IF(M$3<=$O$2,$D60,$D60-($D60-$I$49)*MIN(M$3-$O$2,$Q$2)/$Q$2)) -> 1505.2187 | N60: =M60*(1+IF(N$3<=$O$2,$D60,$D60-($D60-$I$49)*MIN(N$3-$O$2,$Q$2)/$Q$2)) -> 1532.7642 | O60: =SUMPRODUCT(E60:N60,1/(1+$F$49)^$E$3:$N$3)*$E$2 -> 1952.134 | P60: =N60*$E$2*(1+$I$49)/($F$49-$I$49)/(1+$F$49)^$N$3 -> 3685.9373 | Q60: =O60+P60 -> 5638.0713 | R60: =Q60-$G$2+$I$2 -> 5805.4713 | S60: =R60/$K$2 -> 164.97503 | T60: =S60-$M$2 -> 0.43965075
A61: 11 | B61: =IF(T60>0,B60,D60) -> 0.07421875 | C61: =IF(T60>0,D60,C60) -> 0.075683594 | D61: =(B61+C61)/2 -> 0.074951172 | E61: =$C$2*(1+IF(E$3<=$O$2,$D61,$D61-($D61-$I$49)*MIN(E$3-$O$2,$Q$2)/$Q$2)) -> 935.23977 | F61: =E61*(1+IF(F$3<=$O$2,$D61,$D61-($D61-$I$49)*MIN(F$3-$O$2,$Q$2)/$Q$2)) -> 1005.3371 | G61: =F61*(1+IF(G$3<=$O$2,$D61,$D61-($D61-$I$49)*MIN(G$3-$O$2,$Q$2)/$Q$2)) -> 1080.6883 | H61: =G61*(1+IF(H$3<=$O$2,$D61,$D61-($D61-$I$49)*MIN(H$3-$O$2,$Q$2)/$Q$2)) -> 1161.6871 | I61: =H61*(1+IF(I$3<=$O$2,$D61,$D61-($D61-$I$49)*MIN(I$3-$O$2,$Q$2)/$Q$2)) -> 1248.7569 | J61: =I61*(1+IF(J$3<=$O$2,$D61,$D61-($D61-$I$49)*MIN(J$3-$O$2,$Q$2)/$Q$2)) -> 1328.204 | K61: =J61*(1+IF(K$3<=$O$2,$D61,$D61-($D61-$I$49)*MIN(K$3-$O$2,$Q$2)/$Q$2)) -> 1397.6568 | L61: =K61*(1+IF(L$3<=$O$2,$D61,$D61-($D61-$I$49)*MIN(L$3-$O$2,$Q$2)/$Q$2)) -> 1454.9054 | M61: =L61*(1+IF(M$3<=$O$2,$D61,$D61-($D61-$I$49)*MIN(M$3-$O$2,$Q$2)/$Q$2)) -> 1498.0146 | N61: =M61*(1+IF(N$3<=$O$2,$D61,$D61-($D61-$I$49)*MIN(N$3-$O$2,$Q$2)/$Q$2)) -> 1525.4283 | O61: =SUMPRODUCT(E61:N61,1/(1+$F$49)^$E$3:$N$3)*$E$2 -> 1945.7892 | P61: =N61*$E$2*(1+$I$49)/($F$49-$I$49)/(1+$F$49)^$N$3 -> 3668.2963 | Q61: =O61+P61 -> 5614.0855 | R61: =Q61-$G$2+$I$2 -> 5781.4855 | S61: =R61/$K$2 -> 164.29342 | T61: =S61-$M$2 -> -0.24195887
A62: 12 | B62: =IF(T61>0,B61,D61) -> 0.074951172 | C62: =IF(T61>0,D61,C61) -> 0.075683594 | D62: =(B62+C62)/2 -> 0.075317383 | E62: =$C$2*(1+IF(E$3<=$O$2,$D62,$D62-($D62-$I$49)*MIN(E$3-$O$2,$Q$2)/$Q$2)) -> 935.55838 | F62: =E62*(1+IF(F$3<=$O$2,$D62,$D62-($D62-$I$49)*MIN(F$3-$O$2,$Q$2)/$Q$2)) -> 1006.0222 | G62: =F62*(1+IF(G$3<=$O$2,$D62,$D62-($D62-$I$49)*MIN(G$3-$O$2,$Q$2)/$Q$2)) -> 1081.7931 | H62: =G62*(1+IF(H$3<=$O$2,$D62,$D62-($D62-$I$49)*MIN(H$3-$O$2,$Q$2)/$Q$2)) -> 1163.271 | I62: =H62*(1+IF(I$3<=$O$2,$D62,$D62-($D62-$I$49)*MIN(I$3-$O$2,$Q$2)/$Q$2)) -> 1250.8855 | J62: =I62*(1+IF(J$3<=$O$2,$D62,$D62-($D62-$I$49)*MIN(J$3-$O$2,$Q$2)/$Q$2)) -> 1330.8345 | K62: =J62*(1+IF(K$3<=$O$2,$D62,$D62-($D62-$I$49)*MIN(K$3-$O$2,$Q$2)/$Q$2)) -> 1400.7172 | L62: =K62*(1+IF(L$3<=$O$2,$D62,$D62-($D62-$I$49)*MIN(L$3-$O$2,$Q$2)/$Q$2)) -> 1458.2964 | M62: =L62*(1+IF(M$3<=$O$2,$D62,$D62-($D62-$I$49)*MIN(M$3-$O$2,$Q$2)/$Q$2)) -> 1501.6129 | N62: =M62*(1+IF(N$3<=$O$2,$D62,$D62-($D62-$I$49)*MIN(N$3-$O$2,$Q$2)/$Q$2)) -> 1529.0924 | O62: =SUMPRODUCT(E62:N62,1/(1+$F$49)^$E$3:$N$3)*$E$2 -> 1948.959 | P62: =N62*$E$2*(1+$I$49)/($F$49-$I$49)/(1+$F$49)^$N$3 -> 3677.1075 | Q62: =O62+P62 -> 5626.0666 | R62: =Q62-$G$2+$I$2 -> 5793.4666 | S62: =R62/$K$2 -> 164.63389 | T62: =S62-$M$2 -> 0.098510246
A63: 13 | B63: =IF(T62>0,B62,D62) -> 0.074951172 | C63: =IF(T62>0,D62,C62) -> 0.075317383 | D63: =(B63+C63)/2 -> 0.075134277 | E63: =$C$2*(1+IF(E$3<=$O$2,$D63,$D63-($D63-$I$49)*MIN(E$3-$O$2,$Q$2)/$Q$2)) -> 935.39908 | F63: =E63*(1+IF(F$3<=$O$2,$D63,$D63-($D63-$I$49)*MIN(F$3-$O$2,$Q$2)/$Q$2)) -> 1005.6796 | G63: =F63*(1+IF(G$3<=$O$2,$D63,$D63-($D63-$I$49)*MIN(G$3-$O$2,$Q$2)/$Q$2)) -> 1081.2406 | H63: =G63*(1+IF(H$3<=$O$2,$D63,$D63-($D63-$I$49)*MIN(H$3-$O$2,$Q$2)/$Q$2)) -> 1162.4789 | I63: =H63*(1+IF(I$3<=$O$2,$D63,$D63-($D63-$I$49)*MIN(I$3-$O$2,$Q$2)/$Q$2)) -> 1249.8209 | J63: =I63*(1+IF(J$3<=$O$2,$D63,$D63-($D63-$I$49)*MIN(J$3-$O$2,$Q$2)/$Q$2)) -> 1329.5187 | K63: =J63*(1+IF(K$3<=$O$2,$D63,$D63-($D63-$I$49)*MIN(K$3-$O$2,$Q$2)/$Q$2)) -> 1399.1862 | L63: =K63*(1+IF(L$3<=$O$2,$D63,$D63-($D63-$I$49)*MIN(L$3-$O$2,$Q$2)/$Q$2)) -> 1456.6001 | M63: =L63*(1+IF(M$3<=$O$2,$D63,$D63-($D63-$I$49)*MIN(M$3-$O$2,$Q$2)/$Q$2)) -> 1499.8128 | N63: =M63*(1+IF(N$3<=$O$2,$D63,$D63-($D63-$I$49)*MIN(N$3-$O$2,$Q$2)/$Q$2)) -> 1527.2594 | O63: =SUMPRODUCT(E63:N63,1/(1+$F$49)^$E$3:$N$3)*$E$2 -> 1947.3735 | P63: =N63*$E$2*(1+$I$49)/($F$49-$I$49)/(1+$F$49)^$N$3 -> 3672.6996 | Q63: =O63+P63 -> 5620.0731 | R63: =Q63-$G$2+$I$2 -> 5787.4731 | S63: =R63/$K$2 -> 164.46357 | T63: =S63-$M$2 -> -0.071808162
... A74: 24 | B74: =IF(T73>0,B73,D73) -> 0.075211346 | C74: =IF(T73>0,D73,C73) -> 0.075211525 | D74: =(B74+C74)/2 -> 0.075211436 | E74: =$C$2*(1+IF(E$3<=$O$2,$D74,$D74-($D74-$I$49)*MIN(E$3-$O$2,$Q$2)/$Q$2)) -> 935.46621 | F74: =E74*(1+IF(F$3<=$O$2,$D74,$D74-($D74-$I$49)*MIN(F$3-$O$2,$Q$2)/$Q$2)) -> 1005.824 | G74: =F74*(1+IF(G$3<=$O$2,$D74,$D74-($D74-$I$49)*MIN(G$3-$O$2,$Q$2)/$Q$2)) -> 1081.4734 | H74: =G74*(1+IF(H$3<=$O$2,$D74,$D74-($D74-$I$49)*MIN(H$3-$O$2,$Q$2)/$Q$2)) -> 1162.8126 | I74: =H74*(1+IF(I$3<=$O$2,$D74,$D74-($D74-$I$49)*MIN(I$3-$O$2,$Q$2)/$Q$2)) -> 1250.2694 | J74: =I74*(1+IF(J$3<=$O$2,$D74,$D74-($D74-$I$49)*MIN(J$3-$O$2,$Q$2)/$Q$2)) -> 1330.073 | K74: =J74*(1+IF(K$3<=$O$2,$D74,$D74-($D74-$I$49)*MIN(K$3-$O$2,$Q$2)/$Q$2)) -> 1399.8312 | L74: =K74*(1+IF(L$3<=$O$2,$D74,$D74-($D74-$I$49)*MIN(L$3-$O$2,$Q$2)/$Q$2)) -> 1457.3147 | M74: =L74*(1+IF(M$3<=$O$2,$D74,$D74-($D74-$I$49)*MIN(M$3-$O$2,$Q$2)/$Q$2)) -> 1500.5711 | N74: =M74*(1+IF(N$3<=$O$2,$D74,$D74-($D74-$I$49)*MIN(N$3-$O$2,$Q$2)/$Q$2)) -> 1528.0315 | O74: =SUMPRODUCT(E74:N74,1/(1+$F$49)^$E$3:$N$3)*$E$2 -> 1948.0415 | P74: =N74*$E$2*(1+$I$49)/($F$49-$I$49)/(1+$F$49)^$N$3 -> 3674.5565 | Q74: =O74+P74 -> 5622.5979 | R74: =Q74-$G$2+$I$2 -> 5789.9979 | S74: =R74/$K$2 -> 164.53532 | T74: =S74-$M$2 -> -5.8700017e-05
A76: Grid block 3: row 1, column 2 of table A (24 steps) | E76: WACC | F76: =Sensitivity!$B$10 -> 0.067507582 | G76: Terminal growth | I76: =Sensitivity!$D$9 -> 0.0233
A77: Step | B77: Low | C77: High | D77: Mid | E77: Rev Y1 | F77: Rev Y2 | G77: Rev Y3 | H77: Rev Y4 | I77: Rev Y5 | J77: Rev Y6 | K77: Rev Y7 | L77: Rev Y8 | M77: Rev Y9 | N77: Rev Y10 | O77: PV of FCF | P77: PV of TV | Q77: EV | R77: Equity | S77: Per share | T77: Value - price
A78: 1 | B78: -0.5 | C78: 1 | D78: =(B78+C78)/2 -> 0.25 | E78: =$C$2*(1+IF(E$3<=$O$2,$D78,$D78-($D78-$I$76)*MIN(E$3-$O$2,$Q$2)/$Q$2)) -> 1087.5375 | F78: =E78*(1+IF(F$3<=$O$2,$D78,$D78-($D78-$I$76)*MIN(F$3-$O$2,$Q$2)/$Q$2)) -> 1359.4219 | G78: =F78*(1+IF(G$3<=$O$2,$D78,$D78-($D78-$I$76)*MIN(G$3-$O$2,$Q$2)/$Q$2)) -> 1699.2773 | H78: =G78*(1+IF(H$3<=$O$2,$D78,$D78-($D78-$I$76)*MIN(H$3-$O$2,$Q$2)/$Q$2)) -> 2124.0967 | I78: =H78*(1+IF(I$3<=$O$2,$D78,$D78-($D78-$I$76)*MIN(I$3-$O$2,$Q$2)/$Q$2)) -> 2655.1208 | J78: =I78*(1+IF(J$3<=$O$2,$D78,$D78-($D78-$I$76)*MIN(J$3-$O$2,$Q$2)/$Q$2)) -> 3198.5179 | K78: =J78*(1+IF(K$3<=$O$2,$D78,$D78-($D78-$I$76)*MIN(K$3-$O$2,$Q$2)/$Q$2)) -> 3708.1058 | L78: =K78*(1+IF(L$3<=$O$2,$D78,$D78-($D78-$I$76)*MIN(L$3-$O$2,$Q$2)/$Q$2)) -> 4130.7556 | M78: =L78*(1+IF(M$3<=$O$2,$D78,$D78-($D78-$I$76)*MIN(M$3-$O$2,$Q$2)/$Q$2)) -> 4414.2907 | N78: =M78*(1+IF(N$3<=$O$2,$D78,$D78-($D78-$I$76)*MIN(N$3-$O$2,$Q$2)/$Q$2)) -> 4517.1437 | O78: =SUMPRODUCT(E78:N78,1/(1+$F$76)^$E$3:$N$3)*$E$2 -> 4225.302 | P78: =N78*$E$2*(1+$I$76)/($F$76-$I$76)/(1+$F$76)^$N$3 -> 12150.636 | Q78: =O78+P78 -> 16375.938 | R78: =Q78-$G$2+$I$2 -> 16543.338 | S78: =R78/$K$2 -> 470.11475 | T78: =S78-$M$2 -> 305.57937
A79: 2 | B79: =IF(T78>0,B78,D78) -> -0.5 | C79: =IF(T78>0,D78,C78) -> 0.25 | D79: =(B79+C79)/2 -> -0.125 | E79: =$C$2*(1+IF(E$3<=$O$2,$D79,$D79-($D79-$I$76)*MIN(E$3-$O$2,$Q$2)/$Q$2)) -> 761.27625 | F79: =E79*(1+IF(F$3<=$O$2,$D79,$D79-($D79-$I$76)*MIN(F$3-$O$2,$Q$2)/$Q$2)) -> 666.11672 | G79: =F79*(1+IF(G$3<=$O$2,$D79,$D79-($D79-$I$76)*MIN(G$3-$O$2,$Q$2)/$Q$2)) -> 582.85213 | H79: =G79*(1+IF(H$3<=$O$2,$D79,$D79-($D79-$I$76)*MIN(H$3-$O$2,$Q$2)/$Q$2)) -> 509.99561 | I79: =H79*(1+IF(I$3<=$O$2,$D79,$D79-($D79-$I$76)*MIN(I$3-$O$2,$Q$2)/$Q$2)) -> 446.24616 | J79: =I79*(1+IF(J$3<=$O$2,$D79,$D79-($D79-$I$76)*MIN(J$3-$O$2,$Q$2)/$Q$2)) -> 403.70105 | K79: =J79*(1+IF(K$3<=$O$2,$D79,$D79-($D79-$I$76)*MIN(K$3-$O$2,$Q$2)/$Q$2)) -> 377.18597 | L79: =K79*(1+IF(L$3<=$O$2,$D79,$D79-($D79-$I$76)*MIN(L$3-$O$2,$Q$2)/$Q$2)) -> 363.59973 | M79: =L79*(1+IF(M$3<=$O$2,$D79,$D79-($D79-$I$76)*MIN(M$3-$O$2,$Q$2)/$Q$2)) -> 361.28723 | N79: =M79*(1+IF(N$3<=$O$2,$D79,$D79-($D79-$I$76)*MIN(N$3-$O$2,$Q$2)/$Q$2)) -> 369.70523 | O79: =SUMPRODUCT(E79:N79,1/(1+$F$76)^$E$3:$N$3)*$E$2 -> 806.56735 | P79: =N79*$E$2*(1+$I$76)/($F$76-$I$76)/(1+$F$76)^$N$3 -> 994.46772 | Q79: =O79+P79 -> 1801.0351 | R79: =Q79-$G$2+$I$2 -> 1968.4351 | S79: =R79/$K$2 -> 55.937342 | T79: =S79-$M$2 -> -108.59804
A80: 3 | B80: =IF(T79>0,B79,D79) -> -0.125 | C80: =IF(T79>0,D79,C79) -> 0.25 | D80: =(B80+C80)/2 -> 0.0625 | E80: =$C$2*(1+IF(E$3<=$O$2,$D80,$D80-($D80-$I$76)*MIN(E$3-$O$2,$Q$2)/$Q$2)) -> 924.40688 | F80: =E80*(1+IF(F$3<=$O$2,$D80,$D80-($D80-$I$76)*MIN(F$3-$O$2,$Q$2)/$Q$2)) -> 982.1823 | G80: =F80*(1+IF(G$3<=$O$2,$D80,$D80-($D80-$I$76)*MIN(G$3-$O$2,$Q$2)/$Q$2)) -> 1043.5687 | H80: =G80*(1+IF(H$3<=$O$2,$D80,$D80-($D80-$I$76)*MIN(H$3-$O$2,$Q$2)/$Q$2)) -> 1108.7917 | I80: =H80*(1+IF(I$3<=$O$2,$D80,$D80-($D80-$I$76)*MIN(I$3-$O$2,$Q$2)/$Q$2)) -> 1178.0912 | J80: =I80*(1+IF(J$3<=$O$2,$D80,$D80-($D80-$I$76)*MIN(J$3-$O$2,$Q$2)/$Q$2)) -> 1242.4857 | K80: =J80*(1+IF(K$3<=$O$2,$D80,$D80-($D80-$I$76)*MIN(K$3-$O$2,$Q$2)/$Q$2)) -> 1300.6589 | L80: =K80*(1+IF(L$3<=$O$2,$D80,$D80-($D80-$I$76)*MIN(L$3-$O$2,$Q$2)/$Q$2)) -> 1351.3586 | M80: =L80*(1+IF(M$3<=$O$2,$D80,$D80-($D80-$I$76)*MIN(M$3-$O$2,$Q$2)/$Q$2)) -> 1393.4399 | N80: =M80*(1+IF(N$3<=$O$2,$D80,$D80-($D80-$I$76)*MIN(N$3-$O$2,$Q$2)/$Q$2)) -> 1425.907 | O80: =SUMPRODUCT(E80:N80,1/(1+$F$76)^$E$3:$N$3)*$E$2 -> 1846.7929 | P80: =N80*$E$2*(1+$I$76)/($F$76-$I$76)/(1+$F$76)^$N$3 -> 3835.5381 | Q80: =O80+P80 -> 5682.3311 | R80: =Q80-$G$2+$I$2 -> 5849.7311 | S80: =R80/$K$2 -> 166.23277 | T80: =S80-$M$2 -> 1.6973873
A81: 4 | B81: =IF(T80>0,B80,D80) -> -0.125 | C81: =IF(T80>0,D80,C80) -> 0.0625 | D81: =(B81+C81)/2 -> -0.03125 | E81: =$C$2*(1+IF(E$3<=$O$2,$D81,$D81-($D81-$I$76)*MIN(E$3-$O$2,$Q$2)/$Q$2)) -> 842.84156 | F81: =E81*(1+IF(F$3<=$O$2,$D81,$D81-($D81-$I$76)*MIN(F$3-$O$2,$Q$2)/$Q$2)) -> 816.50276 | G81: =F81*(1+IF(G$3<=$O$2,$D81,$D81-($D81-$I$76)*MIN(G$3-$O$2,$Q$2)/$Q$2)) -> 790.98705 | H81: =G81*(1+IF(H$3<=$O$2,$D81,$D81-($D81-$I$76)*MIN(H$3-$O$2,$Q$2)/$Q$2)) -> 766.26871 | I81: =H81*(1+IF(I$3<=$O$2,$D81,$D81-($D81-$I$76)*MIN(I$3-$O$2,$Q$2)/$Q$2)) -> 742.32281 | J81: =I81*(1+IF(J$3<=$O$2,$D81,$D81-($D81-$I$76)*MIN(J$3-$O$2,$Q$2)/$Q$2)) -> 727.22396 | K81: =J81*(1+IF(K$3<=$O$2,$D81,$D81-($D81-$I$76)*MIN(K$3-$O$2,$Q$2)/$Q$2)) -> 720.36624 | L81: =K81*(1+IF(L$3<=$O$2,$D81,$D81-($D81-$I$76)*MIN(L$3-$O$2,$Q$2)/$Q$2)) -> 721.43238 | M81: =L81*(1+IF(M$3<=$O$2,$D81,$D81-($D81-$I$76)*MIN(M$3-$O$2,$Q$2)/$Q$2)) -> 730.37093 | N81: =M81*(1+IF(N$3<=$O$2,$D81,$D81-($D81-$I$76)*MIN(N$3-$O$2,$Q$2)/$Q$2)) -> 747.38857 | O81: =SUMPRODUCT(E81:N81,1/(1+$F$76)^$E$3:$N$3)*$E$2 -> 1217.4765 | P81: =N81*$E$2*(1+$I$76)/($F$76-$I$76)/(1+$F$76)^$N$3 -> 2010.3957 | Q81: =O81+P81 -> 3227.8723 | R81: =Q81-$G$2+$I$2 -> 3395.2723 | S81: =R81/$K$2 -> 96.484008 | T81: =S81-$M$2 -> -68.051371
A82: 5 | B82: =IF(T81>0,B81,D81) -> -0.03125 | C82: =IF(T81>0,D81,C81) -> 0.0625 | D82: =(B82+C82)/2 -> 0.015625 | E82: =$C$2*(1+IF(E$3<=$O$2,$D82,$D82-($D82-$I$76)*MIN(E$3-$O$2,$Q$2)/$Q$2)) -> 883.62422 | F82: =E82*(1+IF(F$3<=$O$2,$D82,$D82-($D82-$I$76)*MIN(F$3-$O$2,$Q$2)/$Q$2)) -> 897.43085 | G82: =F82*(1+IF(G$3<=$O$2,$D82,$D82-($D82-$I$76)*MIN(G$3-$O$2,$Q$2)/$Q$2)) -> 911.4532 | H82: =G82*(1+IF(H$3<=$O$2,$D82,$D82-($D82-$I$76)*MIN(H$3-$O$2,$Q$2)/$Q$2)) -> 925.69466 | I82: =H82*(1+IF(I$3<=$O$2,$D82,$D82-($D82-$I$76)*MIN(I$3-$O$2,$Q$2)/$Q$2)) -> 940.15864 | J82: =I82*(1+IF(J$3<=$O$2,$D82,$D82-($D82-$I$76)*MIN(J$3-$O$2,$Q$2)/$Q$2)) -> 956.29176 | K82: =J82*(1+IF(K$3<=$O$2,$D82,$D82-($D82-$I$76)*MIN(K$3-$O$2,$Q$2)/$Q$2)) -> 974.16964 | L82: =K82*(1+IF(L$3<=$O$2,$D82,$D82-($D82-$I$76)*MIN(L$3-$O$2,$Q$2)/$Q$2)) -> 993.87709 | M82: =L82*(1+IF(M$3<=$O$2,$D82,$D82-($D82-$I$76)*MIN(M$3-$O$2,$Q$2)/$Q$2)) -> 1015.5088 | N82: =M82*(1+IF(N$3<=$O$2,$D82,$D82-($D82-$I$76)*MIN(N$3-$O$2,$Q$2)/$Q$2)) -> 1039.1702 | O82: =SUMPRODUCT(E82:N82,1/(1+$F$76)^$E$3:$N$3)*$E$2 -> 1499.0745 | P82: =N82*$E$2*(1+$I$76)/($F$76-$I$76)/(1+$F$76)^$N$3 -> 2795.2572 | Q82: =O82+P82 -> 4294.3317 | R82: =Q82-$G$2+$I$2 -> 4461.7317 | S82: =R82/$K$2 -> 126.78976 | T82: =S82-$M$2 -> -37.745619
A83: 6 | B83: =IF(T82>0,B82,D82) -> 0.015625 | C83: =IF(T82>0,D82,C82) -> 0.0625 | D83: =(B83+C83)/2 -> 0.0390625 | E83: =$C$2*(1+IF(E$3<=$O$2,$D83,$D83-($D83-$I$76)*MIN(E$3-$O$2,$Q$2)/$Q$2)) -> 904.01555 | F83: =E83*(1+IF(F$3<=$O$2,$D83,$D83-($D83-$I$76)*MIN(F$3-$O$2,$Q$2)/$Q$2)) -> 939.32865 | G83: =F83*(1+IF(G$3<=$O$2,$D83,$D83-($D83-$I$76)*MIN(G$3-$O$2,$Q$2)/$Q$2)) -> 976.02118 | H83: =G83*(1+IF(H$3<=$O$2,$D83,$D83-($D83-$I$76)*MIN(H$3-$O$2,$Q$2)/$Q$2)) -> 1014.147 | I83: =H83*(1+IF(I$3<=$O$2,$D83,$D83-($D83-$I$76)*MIN(I$3-$O$2,$Q$2)/$Q$2)) -> 1053.7621 | J83: =I83*(1+IF(J$3<=$O$2,$D83,$D83-($D83-$I$76)*MIN(J$3-$O$2,$Q$2)/$Q$2)) -> 1091.6027 | K83: =J83*(1+IF(K$3<=$O$2,$D83,$D83-($D83-$I$76)*MIN(K$3-$O$2,$Q$2)/$Q$2)) -> 1127.3609 | L83: =K83*(1+IF(L$3<=$O$2,$D83,$D83-($D83-$I$76)*MIN(L$3-$O$2,$Q$2)/$Q$2)) -> 1160.7364 | M83: =L83*(1+IF(M$3<=$O$2,$D83,$D83-($D83-$I$76)*MIN(M$3-$O$2,$Q$2)/$Q$2)) -> 1191.4408 | N83: =M83*(1+IF(N$3<=$O$2,$D83,$D83-($D83-$I$76)*MIN(N$3-$O$2,$Q$2)/$Q$2)) -> 1219.2014 | O83: =SUMPRODUCT(E83:N83,1/(1+$F$76)^$E$3:$N$3)*$E$2 -> 1663.8339 | P83: =N83*$E$2*(1+$I$76)/($F$76-$I$76)/(1+$F$76)^$N$3 -> 3279.522 | Q83: =O83+P83 -> 4943.3559 | R83: =Q83-$G$2+$I$2 -> 5110.7559 | S83: =R83/$K$2 -> 145.23319 | T83: =S83-$M$2 -> -19.302192
A84: 7 | B84: =IF(T83>0,B83,D83) -> 0.0390625 | C84: =IF(T83>0,D83,C83) -> 0.0625 | D84: =(B84+C84)/2 -> 0.05078125 | E84: =$C$2*(1+IF(E$3<=$O$2,$D84,$D84-($D84-$I$76)*MIN(E$3-$O$2,$Q$2)/$Q$2)) -> 914.21121 | F84: =E84*(1+IF(F$3<=$O$2,$D84,$D84-($D84-$I$76)*MIN(F$3-$O$2,$Q$2)/$Q$2)) -> 960.636 | G84: =F84*(1+IF(G$3<=$O$2,$D84,$D84-($D84-$I$76)*MIN(G$3-$O$2,$Q$2)/$Q$2)) -> 1009.4183 | H84: =G84*(1+IF(H$3<=$O$2,$D84,$D84-($D84-$I$76)*MIN(H$3-$O$2,$Q$2)/$Q$2)) -> 1060.6778 | I84: =H84*(1+IF(I$3<=$O$2,$D84,$D84-($D84-$I$76)*MIN(I$3-$O$2,$Q$2)/$Q$2)) -> 1114.5404 | J84: =I84*(1+IF(J$3<=$O$2,$D84,$D84-($D84-$I$76)*MIN(J$3-$O$2,$Q$2)/$Q$2)) -> 1165.0123 | K84: =J84*(1+IF(K$3<=$O$2,$D84,$D84-($D84-$I$76)*MIN(K$3-$O$2,$Q$2)/$Q$2)) -> 1211.3667 | L84: =K84*(1+IF(L$3<=$O$2,$D84,$D84-($D84-$I$76)*MIN(L$3-$O$2,$Q$2)/$Q$2)) -> 1252.9075 | M84: =L84*(1+IF(M$3<=$O$2,$D84,$D84-($D84-$I$76)*MIN(M$3-$O$2,$Q$2)/$Q$2)) -> 1288.9865 | N84: =M84*(1+IF(N$3<=$O$2,$D84,$D84-($D84-$I$76)*MIN(N$3-$O$2,$Q$2)/$Q$2)) -> 1319.0199 | O84: =SUMPRODUCT(E84:N84,1/(1+$F$76)^$E$3:$N$3)*$E$2 -> 1752.9262 | P84: =N84*$E$2*(1+$I$76)/($F$76-$I$76)/(1+$F$76)^$N$3 -> 3548.0233 | Q84: =O84+P84 -> 5300.9494 | R84: =Q84-$G$2+$I$2 -> 5468.3494 | S84: =R84/$K$2 -> 155.39498 | T84: =S84-$M$2 -> -9.1403974
A85: 8 | B85: =IF(T84>0,B84,D84) -> 0.05078125 | C85: =IF(T84>0,D84,C84) -> 0.0625 | D85: =(B85+C85)/2 -> 0.056640625 | E85: =$C$2*(1+IF(E$3<=$O$2,$D85,$D85-($D85-$I$76)*MIN(E$3-$O$2,$Q$2)/$Q$2)) -> 919.30904 | F85: =E85*(1+IF(F$3<=$O$2,$D85,$D85-($D85-$I$76)*MIN(F$3-$O$2,$Q$2)/$Q$2)) -> 971.37928 | G85: =F85*(1+IF(G$3<=$O$2,$D85,$D85-($D85-$I$76)*MIN(G$3-$O$2,$Q$2)/$Q$2)) -> 1026.3988 | H85: =G85*(1+IF(H$3<=$O$2,$D85,$D85-($D85-$I$76)*MIN(H$3-$O$2,$Q$2)/$Q$2)) -> 1084.5347 | I85: =H85*(1+IF(I$3<=$O$2,$D85,$D85-($D85-$I$76)*MIN(I$3-$O$2,$Q$2)/$Q$2)) -> 1145.9634 | J85: =I85*(1+IF(J$3<=$O$2,$D85,$D85-($D85-$I$76)*MIN(J$3-$O$2,$Q$2)/$Q$2)) -> 1203.2301 | K85: =J85*(1+IF(K$3<=$O$2,$D85,$D85-($D85-$I$76)*MIN(K$3-$O$2,$Q$2)/$Q$2)) -> 1255.3352 | L85: =K85*(1+IF(L$3<=$O$2,$D85,$D85-($D85-$I$76)*MIN(L$3-$O$2,$Q$2)/$Q$2)) -> 1301.326 | M85: =L85*(1+IF(M$3<=$O$2,$D85,$D85-($D85-$I$76)*MIN(M$3-$O$2,$Q$2)/$Q$2)) -> 1340.3243 | N85: =M85*(1+IF(N$3<=$O$2,$D85,$D85-($D85-$I$76)*MIN(N$3-$O$2,$Q$2)/$Q$2)) -> 1371.5538 | O85: =SUMPRODUCT(E85:N85,1/(1+$F$76)^$E$3:$N$3)*$E$2 -> 1799.2482 | P85: =N85*$E$2*(1+$I$76)/($F$76-$I$76)/(1+$F$76)^$N$3 -> 3689.3338 | Q85: =O85+P85 -> 5488.582 | R85: =Q85-$G$2+$I$2 -> 5655.982 | S85: =R85/$K$2 -> 160.72697 | T85: =S85-$M$2 -> -3.8084118
A86: 9 | B86: =IF(T85>0,B85,D85) -> 0.056640625 | C86: =IF(T85>0,D85,C85) -> 0.0625 | D86: =(B86+C86)/2 -> 0.059570312 | E86: =$C$2*(1+IF(E$3<=$O$2,$D86,$D86-($D86-$I$76)*MIN(E$3-$O$2,$Q$2)/$Q$2)) -> 921.85796 | F86: =E86*(1+IF(F$3<=$O$2,$D86,$D86-($D86-$I$76)*MIN(F$3-$O$2,$Q$2)/$Q$2)) -> 976.77333 | G86: =F86*(1+IF(G$3<=$O$2,$D86,$D86-($D86-$I$76)*MIN(G$3-$O$2,$Q$2)/$Q$2)) -> 1034.96 | H86: =G86*(1+IF(H$3<=$O$2,$D86,$D86-($D86-$I$76)*MIN(H$3-$O$2,$Q$2)/$Q$2)) -> 1096.6129 | I86: =H86*(1+IF(I$3<=$O$2,$D86,$D86-($D86-$I$76)*MIN(I$3-$O$2,$Q$2)/$Q$2)) -> 1161.9385 | J86: =I86*(1+IF(J$3<=$O$2,$D86,$D86-($D86-$I$76)*MIN(J$3-$O$2,$Q$2)/$Q$2)) -> 1222.7267 | K86: =J86*(1+IF(K$3<=$O$2,$D86,$D86-($D86-$I$76)*MIN(K$3-$O$2,$Q$2)/$Q$2)) -> 1277.8255 | L86: =K86*(1+IF(L$3<=$O$2,$D86,$D86-($D86-$I$76)*MIN(L$3-$O$2,$Q$2)/$Q$2)) -> 1326.1377 | M86: =L86*(1+IF(M$3<=$O$2,$D86,$D86-($D86-$I$76)*MIN(M$3-$O$2,$Q$2)/$Q$2)) -> 1366.6566 | N86: =M86*(1+IF(N$3<=$O$2,$D86,$D86-($D86-$I$76)*MIN(N$3-$O$2,$Q$2)/$Q$2)) -> 1398.4997 | O86: =SUMPRODUCT(E86:N86,1/(1+$F$76)^$E$3:$N$3)*$E$2 -> 1822.8658 | P86: =N86*$E$2*(1+$I$76)/($F$76-$I$76)/(1+$F$76)^$N$3 -> 3761.8153 | Q86: =O86+P86 -> 5584.6811 | R86: =Q86-$G$2+$I$2 -> 5752.0811 | S86: =R86/$K$2 -> 163.45783 | T86: =S86-$M$2 -> -1.0775463
A87: 10 | B87: =IF(T86>0,B86,D86) -> 0.059570312 | C87: =IF(T86>0,D86,C86) -> 0.0625 | D87: =(B87+C87)/2 -> 0.061035156 | E87: =$C$2*(1+IF(E$3<=$O$2,$D87,$D87-($D87-$I$76)*MIN(E$3-$O$2,$Q$2)/$Q$2)) -> 923.13242 | F87: =E87*(1+IF(F$3<=$O$2,$D87,$D87-($D87-$I$76)*MIN(F$3-$O$2,$Q$2)/$Q$2)) -> 979.47595 | G87: =F87*(1+IF(G$3<=$O$2,$D87,$D87-($D87-$I$76)*MIN(G$3-$O$2,$Q$2)/$Q$2)) -> 1039.2584 | H87: =G87*(1+IF(H$3<=$O$2,$D87,$D87-($D87-$I$76)*MIN(H$3-$O$2,$Q$2)/$Q$2)) -> 1102.6897 | I87: =H87*(1+IF(I$3<=$O$2,$D87,$D87-($D87-$I$76)*MIN(I$3-$O$2,$Q$2)/$Q$2)) -> 1169.9926 | J87: =I87*(1+IF(J$3<=$O$2,$D87,$D87-($D87-$I$76)*MIN(J$3-$O$2,$Q$2)/$Q$2)) -> 1232.5733 | K87: =J87*(1+IF(K$3<=$O$2,$D87,$D87-($D87-$I$76)*MIN(K$3-$O$2,$Q$2)/$Q$2)) -> 1289.199 | L87: =K87*(1+IF(L$3<=$O$2,$D87,$D87-($D87-$I$76)*MIN(L$3-$O$2,$Q$2)/$Q$2)) -> 1338.6966 | M87: =L87*(1+IF(M$3<=$O$2,$D87,$D87-($D87-$I$76)*MIN(M$3-$O$2,$Q$2)/$Q$2)) -> 1379.9914 | N87: =M87*(1+IF(N$3<=$O$2,$D87,$D87-($D87-$I$76)*MIN(N$3-$O$2,$Q$2)/$Q$2)) -> 1412.1452 | O87: =SUMPRODUCT(E87:N87,1/(1+$F$76)^$E$3:$N$3)*$E$2 -> 1834.7905 | P87: =N87*$E$2*(1+$I$76)/($F$76-$I$76)/(1+$F$76)^$N$3 -> 3798.5204 | Q87: =O87+P87 -> 5633.3109 | R87: =Q87-$G$2+$I$2 -> 5800.7109 | S87: =R87/$K$2 -> 164.83975 | T87: =S87-$M$2 -> 0.3043732
A88: 11 | B88: =IF(T87>0,B87,D87) -> 0.059570312 | C88: =IF(T87>0,D87,C87) -> 0.061035156 | D88: =(B88+C88)/2 -> 0.060302734 | E88: =$C$2*(1+IF(E$3<=$O$2,$D88,$D88-($D88-$I$76)*MIN(E$3-$O$2,$Q$2)/$Q$2)) -> 922.49519 | F88: =E88*(1+IF(F$3<=$O$2,$D88,$D88-($D88-$I$76)*MIN(F$3-$O$2,$Q$2)/$Q$2)) -> 978.12417 | G88: =F88*(1+IF(G$3<=$O$2,$D88,$D88-($D88-$I$76)*MIN(G$3-$O$2,$Q$2)/$Q$2)) -> 1037.1077 | H88: =G88*(1+IF(H$3<=$O$2,$D88,$D88-($D88-$I$76)*MIN(H$3-$O$2,$Q$2)/$Q$2)) -> 1099.6482 | I88: =H88*(1+IF(I$3<=$O$2,$D88,$D88-($D88-$I$76)*MIN(I$3-$O$2,$Q$2)/$Q$2)) -> 1165.96 | J88: =I88*(1+IF(J$3<=$O$2,$D88,$D88-($D88-$I$76)*MIN(J$3-$O$2,$Q$2)/$Q$2)) -> 1227.6418 | K88: =J88*(1+IF(K$3<=$O$2,$D88,$D88-($D88-$I$76)*MIN(K$3-$O$2,$Q$2)/$Q$2)) -> 1283.5015 | L88: =K88*(1+IF(L$3<=$O$2,$D88,$D88-($D88-$I$76)*MIN(L$3-$O$2,$Q$2)/$Q$2)) -> 1332.4043 | M88: =L88*(1+IF(M$3<=$O$2,$D88,$D88-($D88-$I$76)*MIN(M$3-$O$2,$Q$2)/$Q$2)) -> 1373.3099 | N88: =M88*(1+IF(N$3<=$O$2,$D88,$D88-($D88-$I$76)*MIN(N$3-$O$2,$Q$2)/$Q$2)) -> 1405.308 | O88: =SUMPRODUCT(E88:N88,1/(1+$F$76)^$E$3:$N$3)*$E$2 -> 1828.8185 | P88: =N88*$E$2*(1+$I$76)/($F$76-$I$76)/(1+$F$76)^$N$3 -> 3780.1289 | Q88: =O88+P88 -> 5608.9474 | R88: =Q88-$G$2+$I$2 -> 5776.3474 | S88: =R88/$K$2 -> 164.14741 | T88: =S88-$M$2 -> -0.38796851
A89: 12 | B89: =IF(T88>0,B88,D88) -> 0.060302734 | C89: =IF(T88>0,D88,C88) -> 0.061035156 | D89: =(B89+C89)/2 -> 0.060668945 | E89: =$C$2*(1+IF(E$3<=$O$2,$D89,$D89-($D89-$I$76)*MIN(E$3-$O$2,$Q$2)/$Q$2)) -> 922.8138 | F89: =E89*(1+IF(F$3<=$O$2,$D89,$D89-($D89-$I$76)*MIN(F$3-$O$2,$Q$2)/$Q$2)) -> 978.79994 | G89: =F89*(1+IF(G$3<=$O$2,$D89,$D89-($D89-$I$76)*MIN(G$3-$O$2,$Q$2)/$Q$2)) -> 1038.1827 | H89: =G89*(1+IF(H$3<=$O$2,$D89,$D89-($D89-$I$76)*MIN(H$3-$O$2,$Q$2)/$Q$2)) -> 1101.1682 | I89: =H89*(1+IF(I$3<=$O$2,$D89,$D89-($D89-$I$76)*MIN(I$3-$O$2,$Q$2)/$Q$2)) -> 1167.9749 | J89: =I89*(1+IF(J$3<=$O$2,$D89,$D89-($D89-$I$76)*MIN(J$3-$O$2,$Q$2)/$Q$2)) -> 1230.1055 | K89: =J89*(1+IF(K$3<=$O$2,$D89,$D89-($D89-$I$76)*MIN(K$3-$O$2,$Q$2)/$Q$2)) -> 1286.3476 | L89: =K89*(1+IF(L$3<=$O$2,$D89,$D89-($D89-$I$76)*MIN(L$3-$O$2,$Q$2)/$Q$2)) -> 1335.5473 | M89: =L89*(1+IF(M$3<=$O$2,$D89,$D89-($D89-$I$76)*MIN(M$3-$O$2,$Q$2)/$Q$2)) -> 1376.6471 | N89: =M89*(1+IF(N$3<=$O$2,$D89,$D89-($D89-$I$76)*MIN(N$3-$O$2,$Q$2)/$Q$2)) -> 1408.723 | O89: =SUMPRODUCT(E89:N89,1/(1+$F$76)^$E$3:$N$3)*$E$2 -> 1831.802 | P89: =N89*$E$2*(1+$I$76)/($F$76-$I$76)/(1+$F$76)^$N$3 -> 3789.3149 | Q89: =O89+P89 -> 5621.117 | R89: =Q89-$G$2+$I$2 -> 5788.517 | S89: =R89/$K$2 -> 164.49324 | T89: =S89-$M$2 -> -0.042143753
A90: 13 | B90: =IF(T89>0,B89,D89) -> 0.060668945 | C90: =IF(T89>0,D89,C89) -> 0.061035156 | D90: =(B90+C90)/2 -> 0.060852051 | E90: =$C$2*(1+IF(E$3<=$O$2,$D90,$D90-($D90-$I$76)*MIN(E$3-$O$2,$Q$2)/$Q$2)) -> 922.97311 | F90: =E90*(1+IF(F$3<=$O$2,$D90,$D90-($D90-$I$76)*MIN(F$3-$O$2,$Q$2)/$Q$2)) -> 979.13792 | G90: =F90*(1+IF(G$3<=$O$2,$D90,$D90-($D90-$I$76)*MIN(G$3-$O$2,$Q$2)/$Q$2)) -> 1038.7205 | H90: =G90*(1+IF(H$3<=$O$2,$D90,$D90-($D90-$I$76)*MIN(H$3-$O$2,$Q$2)/$Q$2)) -> 1101.9287 | I90: =H90*(1+IF(I$3<=$O$2,$D90,$D90-($D90-$I$76)*MIN(I$3-$O$2,$Q$2)/$Q$2)) -> 1168.9834 | J90: =I90*(1+IF(J$3<=$O$2,$D90,$D90-($D90-$I$76)*MIN(J$3-$O$2,$Q$2)/$Q$2)) -> 1231.3389 | K90: =J90*(1+IF(K$3<=$O$2,$D90,$D90-($D90-$I$76)*MIN(K$3-$O$2,$Q$2)/$Q$2)) -> 1287.7726 | L90: =K90*(1+IF(L$3<=$O$2,$D90,$D90-($D90-$I$76)*MIN(L$3-$O$2,$Q$2)/$Q$2)) -> 1337.1211 | M90: =L90*(1+IF(M$3<=$O$2,$D90,$D90-($D90-$I$76)*MIN(M$3-$O$2,$Q$2)/$Q$2)) -> 1378.3184 | N90: =M90*(1+IF(N$3<=$O$2,$D90,$D90-($D90-$I$76)*MIN(N$3-$O$2,$Q$2)/$Q$2)) -> 1410.4332 | O90: =SUMPRODUCT(E90:N90,1/(1+$F$76)^$E$3:$N$3)*$E$2 -> 1833.2957 | P90: =N90*$E$2*(1+$I$76)/($F$76-$I$76)/(1+$F$76)^$N$3 -> 3793.9152 | Q90: =O90+P90 -> 5627.2109 | R90: =Q90-$G$2+$I$2 -> 5794.6109 | S90: =R90/$K$2 -> 164.66641 | T90: =S90-$M$2 -> 0.13102812
... A101: 24 | B101: =IF(T100>0,B100,D100) -> 0.06071347 | C101: =IF(T100>0,D100,C100) -> 0.060713649 | D101: =(B101+C101)/2 -> 0.060713559 | E101: =$C$2*(1+IF(E$3<=$O$2,$D101,$D101-($D101-$I$76)*MIN(E$3-$O$2,$Q$2)/$Q$2)) -> 922.85262 | F101: =E101*(1+IF(F$3<=$O$2,$D101,$D101-($D101-$I$76)*MIN(F$3-$O$2,$Q$2)/$Q$2)) -> 978.88229 | G101: =F101*(1+IF(G$3<=$O$2,$D101,$D101-($D101-$I$76)*MIN(G$3-$O$2,$Q$2)/$Q$2)) -> 1038.3137 | H101: =G101*(1+IF(H$3<=$O$2,$D101,$D101-($D101-$I$76)*MIN(H$3-$O$2,$Q$2)/$Q$2)) -> 1101.3534 | I101: =H101*(1+IF(I$3<=$O$2,$D101,$D101-($D101-$I$76)*MIN(I$3-$O$2,$Q$2)/$Q$2)) -> 1168.2205 | J101: =I101*(1+IF(J$3<=$O$2,$D101,$D101-($D101-$I$76)*MIN(J$3-$O$2,$Q$2)/$Q$2)) -> 1230.4059 | K101: =J101*(1+IF(K$3<=$O$2,$D101,$D101-($D101-$I$76)*MIN(K$3-$O$2,$Q$2)/$Q$2)) -> 1286.6947 | L101: =K101*(1+IF(L$3<=$O$2,$D101,$D101-($D101-$I$76)*MIN(L$3-$O$2,$Q$2)/$Q$2)) -> 1335.9306 | M101: =L101*(1+IF(M$3<=$O$2,$D101,$D101-($D101-$I$76)*MIN(M$3-$O$2,$Q$2)/$Q$2)) -> 1377.0541 | N101: =M101*(1+IF(N$3<=$O$2,$D101,$D101-($D101-$I$76)*MIN(N$3-$O$2,$Q$2)/$Q$2)) -> 1409.1395 | O101: =SUMPRODUCT(E101:N101,1/(1+$F$76)^$E$3:$N$3)*$E$2 -> 1832.1659 | P101: =N101*$E$2*(1+$I$76)/($F$76-$I$76)/(1+$F$76)^$N$3 -> 3790.4353 | Q101: =O101+P101 -> 5622.6012 | R101: =Q101-$G$2+$I$2 -> 5790.0012 | S101: =R101/$K$2 -> 164.53541 | T101: =S101-$M$2 -> 3.4028967e-05
A103: Grid block 4: row 1, column 3 of table A (24 steps) | E103: WACC | F103: =Sensitivity!$B$10 -> 0.067507582 | G103: Terminal growth | I103: =Sensitivity!$E$9 -> 0.0283
A104: Step | B104: Low | C104: High | D104: Mid | E104: Rev Y1 | F104: Rev Y2 | G104: Rev Y3 | H104: Rev Y4 | I104: Rev Y5 | J104: Rev Y6 | K104: Rev Y7 | L104: Rev Y8 | M104: Rev Y9 | N104: Rev Y10 | O104: PV of FCF | P104: PV of TV | Q104: EV | R104: Equity | S104: Per share | T104: Value - price
A105: 1 | B105: -0.5 | C105: 1 | D105: =(B105+C105)/2 -> 0.25 | E105: =$C$2*(1+IF(E$3<=$O$2,$D105,$D105-($D105-$I$103)*MIN(E$3-$O$2,$Q$2)/$Q$2)) -> 1087.5375 | F105: =E105*(1+IF(F$3<=$O$2,$D105,$D105-($D105-$I$103)*MIN(F$3-$O$2,$Q$2)/$Q$2)) -> 1359.4219 | G105: =F105*(1+IF(G$3<=$O$2,$D105,$D105-($D105-$I$103)*MIN(G$3-$O$2,$Q$2)/$Q$2)) -> 1699.2773 | H105: =G105*(1+IF(H$3<=$O$2,$D105,$D105-($D105-$I$103)*MIN(H$3-$O$2,$Q$2)/$Q$2)) -> 2124.0967 | I105: =H105*(1+IF(I$3<=$O$2,$D105,$D105-($D105-$I$103)*MIN(I$3-$O$2,$Q$2)/$Q$2)) -> 2655.1208 | J105: =I105*(1+IF(J$3<=$O$2,$D105,$D105-($D105-$I$103)*MIN(J$3-$O$2,$Q$2)/$Q$2)) -> 3201.173 | K105: =J105*(1+IF(K$3<=$O$2,$D105,$D105-($D105-$I$103)*MIN(K$3-$O$2,$Q$2)/$Q$2)) -> 3717.5862 | L105: =K105*(1+IF(L$3<=$O$2,$D105,$D105-($D105-$I$103)*MIN(L$3-$O$2,$Q$2)/$Q$2)) -> 4152.4695 | M105: =L105*(1+IF(M$3<=$O$2,$D105,$D105-($D105-$I$103)*MIN(M$3-$O$2,$Q$2)/$Q$2)) -> 4454.1049 | N105: =M105*(1+IF(N$3<=$O$2,$D105,$D105-($D105-$I$103)*MIN(N$3-$O$2,$Q$2)/$Q$2)) -> 4580.156 | O105: =SUMPRODUCT(E105:N105,1/(1+$F$103)^$E$3:$N$3)*$E$2 -> 4242.1798 | P105: =N105*$E$2*(1+$I$103)/($F$103-$I$103)/(1+$F$103)^$N$3 -> 13959.149 | Q105: =O105+P105 -> 18201.329 | R105: =Q105-$G$2+$I$2 -> 18368.729 | S105: =R105/$K$2 -> 521.98717 | T105: =S105-$M$2 -> 357.45179
A106: 2 | B106: =IF(T105>0,B105,D105) -> -0.5 | C106: =IF(T105>0,D105,C105) -> 0.25 | D106: =(B106+C106)/2 -> -0.125 | E106: =$C$2*(1+IF(E$3<=$O$2,$D106,$D106-($D106-$I$103)*MIN(E$3-$O$2,$Q$2)/$Q$2)) -> 761.27625 | F106: =E106*(1+IF(F$3<=$O$2,$D106,$D106-($D106-$I$103)*MIN(F$3-$O$2,$Q$2)/$Q$2)) -> 666.11672 | G106: =F106*(1+IF(G$3<=$O$2,$D106,$D106-($D106-$I$103)*MIN(G$3-$O$2,$Q$2)/$Q$2)) -> 582.85213 | H106: =G106*(1+IF(H$3<=$O$2,$D106,$D106-($D106-$I$103)*MIN(H$3-$O$2,$Q$2)/$Q$2)) -> 509.99561 | I106: =H106*(1+IF(I$3<=$O$2,$D106,$D106-($D106-$I$103)*MIN(I$3-$O$2,$Q$2)/$Q$2)) -> 446.24616 | J106: =I106*(1+IF(J$3<=$O$2,$D106,$D106-($D106-$I$103)*MIN(J$3-$O$2,$Q$2)/$Q$2)) -> 404.1473 | K106: =J106*(1+IF(K$3<=$O$2,$D106,$D106-($D106-$I$103)*MIN(K$3-$O$2,$Q$2)/$Q$2)) -> 378.4112 | L106: =K106*(1+IF(L$3<=$O$2,$D106,$D106-($D106-$I$103)*MIN(L$3-$O$2,$Q$2)/$Q$2)) -> 365.91606 | M106: =L106*(1+IF(M$3<=$O$2,$D106,$D106-($D106-$I$103)*MIN(M$3-$O$2,$Q$2)/$Q$2)) -> 365.0525 | N106: =M106*(1+IF(N$3<=$O$2,$D106,$D106-($D106-$I$103)*MIN(N$3-$O$2,$Q$2)/$Q$2)) -> 375.38348 | O106: =SUMPRODUCT(E106:N106,1/(1+$F$103)^$E$3:$N$3)*$E$2 -> 808.24157 | P106: =N106*$E$2*(1+$I$103)/($F$103-$I$103)/(1+$F$103)^$N$3 -> 1144.0732 | Q106: =O106+P106 -> 1952.3148 | R106: =Q106-$G$2+$I$2 -> 2119.7148 | S106: =R106/$K$2 -> 60.236283 | T106: =S106-$M$2 -> -104.2991
A107: 3 | B107: =IF(T106>0,B106,D106) -> -0.125 | C107: =IF(T106>0,D106,C106) -> 0.25 | D107: =(B107+C107)/2 -> 0.0625 | E107: =$C$2*(1+IF(E$3<=$O$2,$D107,$D107-($D107-$I$103)*MIN(E$3-$O$2,$Q$2)/$Q$2)) -> 924.40688 | F107: =E107*(1+IF(F$3<=$O$2,$D107,$D107-($D107-$I$103)*MIN(F$3-$O$2,$Q$2)/$Q$2)) -> 982.1823 | G107: =F107*(1+IF(G$3<=$O$2,$D107,$D107-($D107-$I$103)*MIN(G$3-$O$2,$Q$2)/$Q$2)) -> 1043.5687 | H107: =G107*(1+IF(H$3<=$O$2,$D107,$D107-($D107-$I$103)*MIN(H$3-$O$2,$Q$2)/$Q$2)) -> 1108.7917 | I107: =H107*(1+IF(I$3<=$O$2,$D107,$D107-($D107-$I$103)*MIN(I$3-$O$2,$Q$2)/$Q$2)) -> 1178.0912 | J107: =I107*(1+IF(J$3<=$O$2,$D107,$D107-($D107-$I$103)*MIN(J$3-$O$2,$Q$2)/$Q$2)) -> 1243.6638 | K107: =J107*(1+IF(K$3<=$O$2,$D107,$D107-($D107-$I$103)*MIN(K$3-$O$2,$Q$2)/$Q$2)) -> 1304.3794 | L107: =K107*(1+IF(L$3<=$O$2,$D107,$D107-($D107-$I$103)*MIN(L$3-$O$2,$Q$2)/$Q$2)) -> 1359.1373 | M107: =L107*(1+IF(M$3<=$O$2,$D107,$D107-($D107-$I$103)*MIN(M$3-$O$2,$Q$2)/$Q$2)) -> 1406.8974 | N107: =M107*(1+IF(N$3<=$O$2,$D107,$D107-($D107-$I$103)*MIN(N$3-$O$2,$Q$2)/$Q$2)) -> 1446.7126 | O107: =SUMPRODUCT(E107:N107,1/(1+$F$103)^$E$3:$N$3)*$E$2 -> 1852.6139 | P107: =N107*$E$2*(1+$I$103)/($F$103-$I$103)/(1+$F$103)^$N$3 -> 4409.2114 | Q107: =O107+P107 -> 6261.8253 | R107: =Q107-$G$2+$I$2 -> 6429.2253 | S107: =R107/$K$2 -> 182.70035 | T107: =S107-$M$2 -> 18.164971
A108: 4 | B108: =IF(T107>0,B107,D107) -> -0.125 | C108: =IF(T107>0,D107,C107) -> 0.0625 | D108: =(B108+C108)/2 -> -0.03125 | E108: =$C$2*(1+IF(E$3<=$O$2,$D108,$D108-($D108-$I$103)*MIN(E$3-$O$2,$Q$2)/$Q$2)) -> 842.84156 | F108: =E108*(1+IF(F$3<=$O$2,$D108,$D108-($D108-$I$103)*MIN(F$3-$O$2,$Q$2)/$Q$2)) -> 816.50276 | G108: =F108*(1+IF(G$3<=$O$2,$D108,$D108-($D108-$I$103)*MIN(G$3-$O$2,$Q$2)/$Q$2)) -> 790.98705 | H108: =G108*(1+IF(H$3<=$O$2,$D108,$D108-($D108-$I$103)*MIN(H$3-$O$2,$Q$2)/$Q$2)) -> 766.26871 | I108: =H108*(1+IF(I$3<=$O$2,$D108,$D108-($D108-$I$103)*MIN(I$3-$O$2,$Q$2)/$Q$2)) -> 742.32281 | J108: =I108*(1+IF(J$3<=$O$2,$D108,$D108-($D108-$I$103)*MIN(J$3-$O$2,$Q$2)/$Q$2)) -> 727.96629 | K108: =J108*(1+IF(K$3<=$O$2,$D108,$D108-($D108-$I$103)*MIN(K$3-$O$2,$Q$2)/$Q$2)) -> 722.5575 | L108: =K108*(1+IF(L$3<=$O$2,$D108,$D108-($D108-$I$103)*MIN(L$3-$O$2,$Q$2)/$Q$2)) -> 725.79455 | M108: =L108*(1+IF(M$3<=$O$2,$D108,$D108-($D108-$I$103)*MIN(M$3-$O$2,$Q$2)/$Q$2)) -> 737.69033 | N108: =M108*(1+IF(N$3<=$O$2,$D108,$D108-($D108-$I$103)*MIN(N$3-$O$2,$Q$2)/$Q$2)) -> 758.56696 | O108: =SUMPRODUCT(E108:N108,1/(1+$F$103)^$E$3:$N$3)*$E$2 -> 1220.6829 | P108: =N108*$E$2*(1+$I$103)/($F$103-$I$103)/(1+$F$103)^$N$3 -> 2311.9189 | Q108: =O108+P108 -> 3532.6018 | R108: =Q108-$G$2+$I$2 -> 3700.0018 | S108: =R108/$K$2 -> 105.14356 | T108: =S108-$M$2 -> -59.391821
A109: 5 | B109: =IF(T108>0,B108,D108) -> -0.03125 | C109: =IF(T108>0,D108,C108) -> 0.0625 | D109: =(B109+C109)/2 -> 0.015625 | E109: =$C$2*(1+IF(E$3<=$O$2,$D109,$D109-($D109-$I$103)*MIN(E$3-$O$2,$Q$2)/$Q$2)) -> 883.62422 | F109: =E109*(1+IF(F$3<=$O$2,$D109,$D109-($D109-$I$103)*MIN(F$3-$O$2,$Q$2)/$Q$2)) -> 897.43085 | G109: =F109*(1+IF(G$3<=$O$2,$D109,$D109-($D109-$I$103)*MIN(G$3-$O$2,$Q$2)/$Q$2)) -> 911.4532 | H109: =G109*(1+IF(H$3<=$O$2,$D109,$D109-($D109-$I$103)*MIN(H$3-$O$2,$Q$2)/$Q$2)) -> 925.69466 | I109: =H109*(1+IF(I$3<=$O$2,$D109,$D109-($D109-$I$103)*MIN(I$3-$O$2,$Q$2)/$Q$2)) -> 940.15864 | J109: =I109*(1+IF(J$3<=$O$2,$D109,$D109-($D109-$I$103)*MIN(J$3-$O$2,$Q$2)/$Q$2)) -> 957.23192 | K109: =J109*(1+IF(K$3<=$O$2,$D109,$D109-($D109-$I$103)*MIN(K$3-$O$2,$Q$2)/$Q$2)) -> 977.04184 | L109: =K109*(1+IF(L$3<=$O$2,$D109,$D109-($D109-$I$103)*MIN(L$3-$O$2,$Q$2)/$Q$2)) -> 999.73852 | M109: =L109*(1+IF(M$3<=$O$2,$D109,$D109-($D109-$I$103)*MIN(M$3-$O$2,$Q$2)/$Q$2)) -> 1025.4968 | N109: =M109*(1+IF(N$3<=$O$2,$D109,$D109-($D109-$I$103)*MIN(N$3-$O$2,$Q$2)/$Q$2)) -> 1054.5183 | O109: =SUMPRODUCT(E109:N109,1/(1+$F$103)^$E$3:$N$3)*$E$2 -> 1503.4211 | P109: =N109*$E$2*(1+$I$103)/($F$103-$I$103)/(1+$F$103)^$N$3 -> 3213.9033 | Q109: =O109+P109 -> 4717.3244 | R109: =Q109-$G$2+$I$2 -> 4884.7244 | S109: =R109/$K$2 -> 138.81001 | T109: =S109-$M$2 -> -25.725365
A110: 6 | B110: =IF(T109>0,B109,D109) -> 0.015625 | C110: =IF(T109>0,D109,C109) -> 0.0625 | D110: =(B110+C110)/2 -> 0.0390625 | E110: =$C$2*(1+IF(E$3<=$O$2,$D110,$D110-($D110-$I$103)*MIN(E$3-$O$2,$Q$2)/$Q$2)) -> 904.01555 | F110: =E110*(1+IF(F$3<=$O$2,$D110,$D110-($D110-$I$103)*MIN(F$3-$O$2,$Q$2)/$Q$2)) -> 939.32865 | G110: =F110*(1+IF(G$3<=$O$2,$D110,$D110-($D110-$I$103)*MIN(G$3-$O$2,$Q$2)/$Q$2)) -> 976.02118 | H110: =G110*(1+IF(H$3<=$O$2,$D110,$D110-($D110-$I$103)*MIN(H$3-$O$2,$Q$2)/$Q$2)) -> 1014.147 | I110: =H110*(1+IF(I$3<=$O$2,$D110,$D110-($D110-$I$103)*MIN(I$3-$O$2,$Q$2)/$Q$2)) -> 1053.7621 | J110: =I110*(1+IF(J$3<=$O$2,$D110,$D110-($D110-$I$103)*MIN(J$3-$O$2,$Q$2)/$Q$2)) -> 1092.6565 | K110: =J110*(1+IF(K$3<=$O$2,$D110,$D110-($D110-$I$103)*MIN(K$3-$O$2,$Q$2)/$Q$2)) -> 1130.6345 | L110: =K110*(1+IF(L$3<=$O$2,$D110,$D110-($D110-$I$103)*MIN(L$3-$O$2,$Q$2)/$Q$2)) -> 1167.4988 | M110: =L110*(1+IF(M$3<=$O$2,$D110,$D110-($D110-$I$103)*MIN(M$3-$O$2,$Q$2)/$Q$2)) -> 1203.0521 | N110: =M110*(1+IF(N$3<=$O$2,$D110,$D110-($D110-$I$103)*MIN(N$3-$O$2,$Q$2)/$Q$2)) -> 1237.0985 | O110: =SUMPRODUCT(E110:N110,1/(1+$F$103)^$E$3:$N$3)*$E$2 -> 1668.8714 | P110: =N110*$E$2*(1+$I$103)/($F$103-$I$103)/(1+$F$103)^$N$3 -> 3770.361 | Q110: =O110+P110 -> 5439.2323 | R110: =Q110-$G$2+$I$2 -> 5606.6323 | S110: =R110/$K$2 -> 159.32459 | T110: =S110-$M$2 -> -5.2107891
A111: 7 | B111: =IF(T110>0,B110,D110) -> 0.0390625 | C111: =IF(T110>0,D110,C110) -> 0.0625 | D111: =(B111+C111)/2 -> 0.05078125 | E111: =$C$2*(1+IF(E$3<=$O$2,$D111,$D111-($D111-$I$103)*MIN(E$3-$O$2,$Q$2)/$Q$2)) -> 914.21121 | F111: =E111*(1+IF(F$3<=$O$2,$D111,$D111-($D111-$I$103)*MIN(F$3-$O$2,$Q$2)/$Q$2)) -> 960.636 | G111: =F111*(1+IF(G$3<=$O$2,$D111,$D111-($D111-$I$103)*MIN(G$3-$O$2,$Q$2)/$Q$2)) -> 1009.4183 | H111: =G111*(1+IF(H$3<=$O$2,$D111,$D111-($D111-$I$103)*MIN(H$3-$O$2,$Q$2)/$Q$2)) -> 1060.6778 | I111: =H111*(1+IF(I$3<=$O$2,$D111,$D111-($D111-$I$103)*MIN(I$3-$O$2,$Q$2)/$Q$2)) -> 1114.5404 | J111: =I111*(1+IF(J$3<=$O$2,$D111,$D111-($D111-$I$103)*MIN(J$3-$O$2,$Q$2)/$Q$2)) -> 1166.1269 | K111: =J111*(1+IF(K$3<=$O$2,$D111,$D111-($D111-$I$103)*MIN(K$3-$O$2,$Q$2)/$Q$2)) -> 1214.8578 | L111: =K111*(1+IF(L$3<=$O$2,$D111,$D111-($D111-$I$103)*MIN(L$3-$O$2,$Q$2)/$Q$2)) -> 1260.1629 | M111: =L111*(1+IF(M$3<=$O$2,$D111,$D111-($D111-$I$103)*MIN(M$3-$O$2,$Q$2)/$Q$2)) -> 1301.4916 | N111: =M111*(1+IF(N$3<=$O$2,$D111,$D111-($D111-$I$103)*MIN(N$3-$O$2,$Q$2)/$Q$2)) -> 1338.3238 | O111: =SUMPRODUCT(E111:N111,1/(1+$F$103)^$E$3:$N$3)*$E$2 -> 1758.3432 | P111: =N111*$E$2*(1+$I$103)/($F$103-$I$103)/(1+$F$103)^$N$3 -> 4078.8699 | Q111: =O111+P111 -> 5837.2131 | R111: =Q111-$G$2+$I$2 -> 6004.6131 | S111: =R111/$K$2 -> 170.63407 | T111: =S111-$M$2 -> 6.0986949
A112: 8 | B112: =IF(T111>0,B111,D111) -> 0.0390625 | C112: =IF(T111>0,D111,C111) -> 0.05078125 | D112: =(B112+C112)/2 -> 0.044921875 | E112: =$C$2*(1+IF(E$3<=$O$2,$D112,$D112-($D112-$I$103)*MIN(E$3-$O$2,$Q$2)/$Q$2)) -> 909.11338 | F112: =E112*(1+IF(F$3<=$O$2,$D112,$D112-($D112-$I$103)*MIN(F$3-$O$2,$Q$2)/$Q$2)) -> 949.95246 | G112: =F112*(1+IF(G$3<=$O$2,$D112,$D112-($D112-$I$103)*MIN(G$3-$O$2,$Q$2)/$Q$2)) -> 992.6261 | H112: =G112*(1+IF(H$3<=$O$2,$D112,$D112-($D112-$I$103)*MIN(H$3-$O$2,$Q$2)/$Q$2)) -> 1037.2167 | I112: =H112*(1+IF(I$3<=$O$2,$D112,$D112-($D112-$I$103)*MIN(I$3-$O$2,$Q$2)/$Q$2)) -> 1083.8104 | J112: =I112*(1+IF(J$3<=$O$2,$D112,$D112-($D112-$I$103)*MIN(J$3-$O$2,$Q$2)/$Q$2)) -> 1128.8943 | K112: =J112*(1+IF(K$3<=$O$2,$D112,$D112-($D112-$I$103)*MIN(K$3-$O$2,$Q$2)/$Q$2)) -> 1172.1006 | L112: =K112*(1+IF(L$3<=$O$2,$D112,$D112-($D112-$I$103)*MIN(L$3-$O$2,$Q$2)/$Q$2)) -> 1213.064 | M112: =L112*(1+IF(M$3<=$O$2,$D112,$D112-($D112-$I$103)*MIN(M$3-$O$2,$Q$2)/$Q$2)) -> 1251.4264 | N112: =M112*(1+IF(N$3<=$O$2,$D112,$D112-($D112-$I$103)*MIN(N$3-$O$2,$Q$2)/$Q$2)) -> 1286.8418 | O112: =SUMPRODUCT(E112:N112,1/(1+$F$103)^$E$3:$N$3)*$E$2 -> 1713.0219 | P112: =N112*$E$2*(1+$I$103)/($F$103-$I$103)/(1+$F$103)^$N$3 -> 3921.9659 | Q112: =O112+P112 -> 5634.9878 | R112: =Q112-$G$2+$I$2 -> 5802.3878 | S112: =R112/$K$2 -> 164.88741 | T112: =S112-$M$2 -> 0.35202598
A113: 9 | B113: =IF(T112>0,B112,D112) -> 0.0390625 | C113: =IF(T112>0,D112,C112) -> 0.044921875 | D113: =(B113+C113)/2 -> 0.041992188 | E113: =$C$2*(1+IF(E$3<=$O$2,$D113,$D113-($D113-$I$103)*MIN(E$3-$O$2,$Q$2)/$Q$2)) -> 906.56446 | F113: =E113*(1+IF(F$3<=$O$2,$D113,$D113-($D113-$I$103)*MIN(F$3-$O$2,$Q$2)/$Q$2)) -> 944.63309 | G113: =F113*(1+IF(G$3<=$O$2,$D113,$D113-($D113-$I$103)*MIN(G$3-$O$2,$Q$2)/$Q$2)) -> 984.3003 | H113: =G113*(1+IF(H$3<=$O$2,$D113,$D113-($D113-$I$103)*MIN(H$3-$O$2,$Q$2)/$Q$2)) -> 1025.6332 | I113: =H113*(1+IF(I$3<=$O$2,$D113,$D113-($D113-$I$103)*MIN(I$3-$O$2,$Q$2)/$Q$2)) -> 1068.7018 | J113: =I113*(1+IF(J$3<=$O$2,$D113,$D113-($D113-$I$103)*MIN(J$3-$O$2,$Q$2)/$Q$2)) -> 1110.6524 | K113: =J113*(1+IF(K$3<=$O$2,$D113,$D113-($D113-$I$103)*MIN(K$3-$O$2,$Q$2)/$Q$2)) -> 1151.2082 | L113: =K113*(1+IF(L$3<=$O$2,$D113,$D113-($D113-$I$103)*MIN(L$3-$O$2,$Q$2)/$Q$2)) -> 1190.0924 | M113: =L113*(1+IF(M$3<=$O$2,$D113,$D113-($D113-$I$103)*MIN(M$3-$O$2,$Q$2)/$Q$2)) -> 1227.031 | N113: =M113*(1+IF(N$3<=$O$2,$D113,$D113-($D113-$I$103)*MIN(N$3-$O$2,$Q$2)/$Q$2)) -> 1261.756 | O113: =SUMPRODUCT(E113:N113,1/(1+$F$103)^$E$3:$N$3)*$E$2 -> 1690.8021 | P113: =N113*$E$2*(1+$I$103)/($F$103-$I$103)/(1+$F$103)^$N$3 -> 3845.5108 | Q113: =O113+P113 -> 5536.3128 | R113: =Q113-$G$2+$I$2 -> 5703.7128 | S113: =R113/$K$2 -> 162.08334 | T113: =S113-$M$2 -> -2.4520363
A114: 10 | B114: =IF(T113>0,B113,D113) -> 0.041992188 | C114: =IF(T113>0,D113,C113) -> 0.044921875 | D114: =(B114+C114)/2 -> 0.043457031 | E114: =$C$2*(1+IF(E$3<=$O$2,$D114,$D114-($D114-$I$103)*MIN(E$3-$O$2,$Q$2)/$Q$2)) -> 907.83892 | F114: =E114*(1+IF(F$3<=$O$2,$D114,$D114-($D114-$I$103)*MIN(F$3-$O$2,$Q$2)/$Q$2)) -> 947.29091 | G114: =F114*(1+IF(G$3<=$O$2,$D114,$D114-($D114-$I$103)*MIN(G$3-$O$2,$Q$2)/$Q$2)) -> 988.45736 | H114: =G114*(1+IF(H$3<=$O$2,$D114,$D114-($D114-$I$103)*MIN(H$3-$O$2,$Q$2)/$Q$2)) -> 1031.4128 | I114: =H114*(1+IF(I$3<=$O$2,$D114,$D114-($D114-$I$103)*MIN(I$3-$O$2,$Q$2)/$Q$2)) -> 1076.2349 | J114: =I114*(1+IF(J$3<=$O$2,$D114,$D114-($D114-$I$103)*MIN(J$3-$O$2,$Q$2)/$Q$2)) -> 1119.7424 | K114: =J114*(1+IF(K$3<=$O$2,$D114,$D114-($D114-$I$103)*MIN(K$3-$O$2,$Q$2)/$Q$2)) -> 1161.6143 | L114: =K114*(1+IF(L$3<=$O$2,$D114,$D114-($D114-$I$103)*MIN(L$3-$O$2,$Q$2)/$Q$2)) -> 1201.5306 | M114: =L114*(1+IF(M$3<=$O$2,$D114,$D114-($D114-$I$103)*MIN(M$3-$O$2,$Q$2)/$Q$2)) -> 1239.1763 | N114: =M114*(1+IF(N$3<=$O$2,$D114,$D114-($D114-$I$103)*MIN(N$3-$O$2,$Q$2)/$Q$2)) -> 1274.2449 | O114: =SUMPRODUCT(E114:N114,1/(1+$F$103)^$E$3:$N$3)*$E$2 -> 1701.8756 | P114: =N114*$E$2*(1+$I$103)/($F$103-$I$103)/(1+$F$103)^$N$3 -> 3883.574 | Q114: =O114+P114 -> 5585.4496 | R114: =Q114-$G$2+$I$2 -> 5752.8496 | S114: =R114/$K$2 -> 163.47967 | T114: =S114-$M$2 -> -1.0557094
A115: 11 | B115: =IF(T114>0,B114,D114) -> 0.043457031 | C115: =IF(T114>0,D114,C114) -> 0.044921875 | D115: =(B115+C115)/2 -> 0.044189453 | E115: =$C$2*(1+IF(E$3<=$O$2,$D115,$D115-($D115-$I$103)*MIN(E$3-$O$2,$Q$2)/$Q$2)) -> 908.47615 | F115: =E115*(1+IF(F$3<=$O$2,$D115,$D115-($D115-$I$103)*MIN(F$3-$O$2,$Q$2)/$Q$2)) -> 948.62121 | G115: =F115*(1+IF(G$3<=$O$2,$D115,$D115-($D115-$I$103)*MIN(G$3-$O$2,$Q$2)/$Q$2)) -> 990.54027 | H115: =G115*(1+IF(H$3<=$O$2,$D115,$D115-($D115-$I$103)*MIN(H$3-$O$2,$Q$2)/$Q$2)) -> 1034.3117 | I115: =H115*(1+IF(I$3<=$O$2,$D115,$D115-($D115-$I$103)*MIN(I$3-$O$2,$Q$2)/$Q$2)) -> 1080.0174 | J115: =I115*(1+IF(J$3<=$O$2,$D115,$D115-($D115-$I$103)*MIN(J$3-$O$2,$Q$2)/$Q$2)) -> 1124.3106 | K115: =J115*(1+IF(K$3<=$O$2,$D115,$D115-($D115-$I$103)*MIN(K$3-$O$2,$Q$2)/$Q$2)) -> 1166.8474 | L115: =K115*(1+IF(L$3<=$O$2,$D115,$D115-($D115-$I$103)*MIN(L$3-$O$2,$Q$2)/$Q$2)) -> 1207.2854 | M115: =L115*(1+IF(M$3<=$O$2,$D115,$D115-($D115-$I$103)*MIN(M$3-$O$2,$Q$2)/$Q$2)) -> 1245.2882 | N115: =M115*(1+IF(N$3<=$O$2,$D115,$D115-($D115-$I$103)*MIN(N$3-$O$2,$Q$2)/$Q$2)) -> 1280.5298 | O115: =SUMPRODUCT(E115:N115,1/(1+$F$103)^$E$3:$N$3)*$E$2 -> 1707.4396 | P115: =N115*$E$2*(1+$I$103)/($F$103-$I$103)/(1+$F$103)^$N$3 -> 3902.7287 | Q115: =O115+P115 -> 5610.1683 | R115: =Q115-$G$2+$I$2 -> 5777.5683 | S115: =R115/$K$2 -> 164.18211 | T115: =S115-$M$2 -> -0.35327287
A116: 12 | B116: =IF(T115>0,B115,D115) -> 0.044189453 | C116: =IF(T115>0,D115,C115) -> 0.044921875 | D116: =(B116+C116)/2 -> 0.044555664 | E116: =$C$2*(1+IF(E$3<=$O$2,$D116,$D116-($D116-$I$103)*MIN(E$3-$O$2,$Q$2)/$Q$2)) -> 908.79476 | F116: =E116*(1+IF(F$3<=$O$2,$D116,$D116-($D116-$I$103)*MIN(F$3-$O$2,$Q$2)/$Q$2)) -> 949.28672 | G116: =F116*(1+IF(G$3<=$O$2,$D116,$D116-($D116-$I$103)*MIN(G$3-$O$2,$Q$2)/$Q$2)) -> 991.58282 | H116: =G116*(1+IF(H$3<=$O$2,$D116,$D116-($D116-$I$103)*MIN(H$3-$O$2,$Q$2)/$Q$2)) -> 1035.7634 | I116: =H116*(1+IF(I$3<=$O$2,$D116,$D116-($D116-$I$103)*MIN(I$3-$O$2,$Q$2)/$Q$2)) -> 1081.9126 | J116: =I116*(1+IF(J$3<=$O$2,$D116,$D116-($D116-$I$103)*MIN(J$3-$O$2,$Q$2)/$Q$2)) -> 1126.6005 | K116: =J116*(1+IF(K$3<=$O$2,$D116,$D116-($D116-$I$103)*MIN(K$3-$O$2,$Q$2)/$Q$2)) -> 1169.4714 | L116: =K116*(1+IF(L$3<=$O$2,$D116,$D116-($D116-$I$103)*MIN(L$3-$O$2,$Q$2)/$Q$2)) -> 1210.1717 | M116: =L116*(1+IF(M$3<=$O$2,$D116,$D116-($D116-$I$103)*MIN(M$3-$O$2,$Q$2)/$Q$2)) -> 1248.354 | N116: =M116*(1+IF(N$3<=$O$2,$D116,$D116-($D116-$I$103)*MIN(N$3-$O$2,$Q$2)/$Q$2)) -> 1283.6824 | O116: =SUMPRODUCT(E116:N116,1/(1+$F$103)^$E$3:$N$3)*$E$2 -> 1710.2285 | P116: =N116*$E$2*(1+$I$103)/($F$103-$I$103)/(1+$F$103)^$N$3 -> 3912.337 | Q116: =O116+P116 -> 5622.5654 | R116: =Q116-$G$2+$I$2 -> 5789.9654 | S116: =R116/$K$2 -> 164.5344 | T116: =S116-$M$2 -> -0.00098187036
A117: 13 | B117: =IF(T116>0,B116,D116) -> 0.044555664 | C117: =IF(T116>0,D116,C116) -> 0.044921875 | D117: =(B117+C117)/2 -> 0.04473877 | E117: =$C$2*(1+IF(E$3<=$O$2,$D117,$D117-($D117-$I$103)*MIN(E$3-$O$2,$Q$2)/$Q$2)) -> 908.95407 | F117: =E117*(1+IF(F$3<=$O$2,$D117,$D117-($D117-$I$103)*MIN(F$3-$O$2,$Q$2)/$Q$2)) -> 949.61956 | G117: =F117*(1+IF(G$3<=$O$2,$D117,$D117-($D117-$I$103)*MIN(G$3-$O$2,$Q$2)/$Q$2)) -> 992.10437 | H117: =G117*(1+IF(H$3<=$O$2,$D117,$D117-($D117-$I$103)*MIN(H$3-$O$2,$Q$2)/$Q$2)) -> 1036.4899 | I117: =H117*(1+IF(I$3<=$O$2,$D117,$D117-($D117-$I$103)*MIN(I$3-$O$2,$Q$2)/$Q$2)) -> 1082.8612 | J117: =I117*(1+IF(J$3<=$O$2,$D117,$D117-($D117-$I$103)*MIN(J$3-$O$2,$Q$2)/$Q$2)) -> 1127.7469 | K117: =J117*(1+IF(K$3<=$O$2,$D117,$D117-($D117-$I$103)*MIN(K$3-$O$2,$Q$2)/$Q$2)) -> 1170.7854 | L117: =K117*(1+IF(L$3<=$O$2,$D117,$D117-($D117-$I$103)*MIN(L$3-$O$2,$Q$2)/$Q$2)) -> 1211.6171 | M117: =L117*(1+IF(M$3<=$O$2,$D117,$D117-($D117-$I$103)*MIN(M$3-$O$2,$Q$2)/$Q$2)) -> 1249.8894 | N117: =M117*(1+IF(N$3<=$O$2,$D117,$D117-($D117-$I$103)*MIN(N$3-$O$2,$Q$2)/$Q$2)) -> 1285.2612 | O117: =SUMPRODUCT(E117:N117,1/(1+$F$103)^$E$3:$N$3)*$E$2 -> 1711.6246 | P117: =N117*$E$2*(1+$I$103)/($F$103-$I$103)/(1+$F$103)^$N$3 -> 3917.1489 | Q117: =O117+P117 -> 5628.7735 | R117: =Q117-$G$2+$I$2 -> 5796.1735 | S117: =R117/$K$2 -> 164.71081 | T117: =S117-$M$2 -> 0.17543237
... A128: 24 | B128: =IF(T127>0,B127,D127) -> 0.044556558 | C128: =IF(T127>0,D127,C127) -> 0.044556737 | D128: =(B128+C128)/2 -> 0.044556648 | E128: =$C$2*(1+IF(E$3<=$O$2,$D128,$D128-($D128-$I$103)*MIN(E$3-$O$2,$Q$2)/$Q$2)) -> 908.79562 | F128: =E128*(1+IF(F$3<=$O$2,$D128,$D128-($D128-$I$103)*MIN(F$3-$O$2,$Q$2)/$Q$2)) -> 949.28851 | G128: =F128*(1+IF(G$3<=$O$2,$D128,$D128-($D128-$I$103)*MIN(G$3-$O$2,$Q$2)/$Q$2)) -> 991.58562 | H128: =G128*(1+IF(H$3<=$O$2,$D128,$D128-($D128-$I$103)*MIN(H$3-$O$2,$Q$2)/$Q$2)) -> 1035.7674 | I128: =H128*(1+IF(I$3<=$O$2,$D128,$D128-($D128-$I$103)*MIN(I$3-$O$2,$Q$2)/$Q$2)) -> 1081.9177 | J128: =I128*(1+IF(J$3<=$O$2,$D128,$D128-($D128-$I$103)*MIN(J$3-$O$2,$Q$2)/$Q$2)) -> 1126.6066 | K128: =J128*(1+IF(K$3<=$O$2,$D128,$D128-($D128-$I$103)*MIN(K$3-$O$2,$Q$2)/$Q$2)) -> 1169.4785 | L128: =K128*(1+IF(L$3<=$O$2,$D128,$D128-($D128-$I$103)*MIN(L$3-$O$2,$Q$2)/$Q$2)) -> 1210.1795 | M128: =L128*(1+IF(M$3<=$O$2,$D128,$D128-($D128-$I$103)*MIN(M$3-$O$2,$Q$2)/$Q$2)) -> 1248.3622 | N128: =M128*(1+IF(N$3<=$O$2,$D128,$D128-($D128-$I$103)*MIN(N$3-$O$2,$Q$2)/$Q$2)) -> 1283.6909 | O128: =SUMPRODUCT(E128:N128,1/(1+$F$103)^$E$3:$N$3)*$E$2 -> 1710.236 | P128: =N128*$E$2*(1+$I$103)/($F$103-$I$103)/(1+$F$103)^$N$3 -> 3912.3628 | Q128: =O128+P128 -> 5622.5988 | R128: =Q128-$G$2+$I$2 -> 5789.9988 | S128: =R128/$K$2 -> 164.53534 | T128: =S128-$M$2 -> -3.4811787e-05
A130: Grid block 5: row 1, column 4 of table A (24 steps) | E130: WACC | F130: =Sensitivity!$B$10 -> 0.067507582 | G130: Terminal growth | I130: =Sensitivity!$F$9 -> 0.0333
A131: Step | B131: Low | C131: High | D131: Mid | E131: Rev Y1 | F131: Rev Y2 | G131: Rev Y3 | H131: Rev Y4 | I131: Rev Y5 | J131: Rev Y6 | K131: Rev Y7 | L131: Rev Y8 | M131: Rev Y9 | N131: Rev Y10 | O131: PV of FCF | P131: PV of TV | Q131: EV | R131: Equity | S131: Per share | T131: Value - price
A132: 1 | B132: -0.5 | C132: 1 | D132: =(B132+C132)/2 -> 0.25 | E132: =$C$2*(1+IF(E$3<=$O$2,$D132,$D132-($D132-$I$130)*MIN(E$3-$O$2,$Q$2)/$Q$2)) -> 1087.5375 | F132: =E132*(1+IF(F$3<=$O$2,$D132,$D132-($D132-$I$130)*MIN(F$3-$O$2,$Q$2)/$Q$2)) -> 1359.4219 | G132: =F132*(1+IF(G$3<=$O$2,$D132,$D132-($D132-$I$130)*MIN(G$3-$O$2,$Q$2)/$Q$2)) -> 1699.2773 | H132: =G132*(1+IF(H$3<=$O$2,$D132,$D132-($D132-$I$130)*MIN(H$3-$O$2,$Q$2)/$Q$2)) -> 2124.0967 | I132: =H132*(1+IF(I$3<=$O$2,$D132,$D132-($D132-$I$130)*MIN(I$3-$O$2,$Q$2)/$Q$2)) -> 2655.1208 | J132: =I132*(1+IF(J$3<=$O$2,$D132,$D132-($D132-$I$130)*MIN(J$3-$O$2,$Q$2)/$Q$2)) -> 3203.8281 | K132: =J132*(1+IF(K$3<=$O$2,$D132,$D132-($D132-$I$130)*MIN(K$3-$O$2,$Q$2)/$Q$2)) -> 3727.0773 | L132: =K132*(1+IF(L$3<=$O$2,$D132,$D132-($D132-$I$130)*MIN(L$3-$O$2,$Q$2)/$Q$2)) -> 4174.2521 | M132: =L132*(1+IF(M$3<=$O$2,$D132,$D132-($D132-$I$130)*MIN(M$3-$O$2,$Q$2)/$Q$2)) -> 4494.1668 | N132: =M132*(1+IF(N$3<=$O$2,$D132,$D132-($D132-$I$130)*MIN(N$3-$O$2,$Q$2)/$Q$2)) -> 4643.8225 | O132: =SUMPRODUCT(E132:N132,1/(1+$F$130)^$E$3:$N$3)*$E$2 -> 4259.1749 | P132: =N132*$E$2*(1+$I$130)/($F$130-$I$130)/(1+$F$130)^$N$3 -> 16300.786 | Q132: =O132+P132 -> 20559.961 | R132: =Q132-$G$2+$I$2 -> 20727.361 | S132: =R132/$K$2 -> 589.01282 | T132: =S132-$M$2 -> 424.47744
A133: 2 | B133: =IF(T132>0,B132,D132) -> -0.5 | C133: =IF(T132>0,D132,C132) -> 0.25 | D133: =(B133+C133)/2 -> -0.125 | E133: =$C$2*(1+IF(E$3<=$O$2,$D133,$D133-($D133-$I$130)*MIN(E$3-$O$2,$Q$2)/$Q$2)) -> 761.27625 | F133: =E133*(1+IF(F$3<=$O$2,$D133,$D133-($D133-$I$130)*MIN(F$3-$O$2,$Q$2)/$Q$2)) -> 666.11672 | G133: =F133*(1+IF(G$3<=$O$2,$D133,$D133-($D133-$I$130)*MIN(G$3-$O$2,$Q$2)/$Q$2)) -> 582.85213 | H133: =G133*(1+IF(H$3<=$O$2,$D133,$D133-($D133-$I$130)*MIN(H$3-$O$2,$Q$2)/$Q$2)) -> 509.99561 | I133: =H133*(1+IF(I$3<=$O$2,$D133,$D133-($D133-$I$130)*MIN(I$3-$O$2,$Q$2)/$Q$2)) -> 446.24616 | J133: =I133*(1+IF(J$3<=$O$2,$D133,$D133-($D133-$I$130)*MIN(J$3-$O$2,$Q$2)/$Q$2)) -> 404.59354 | K133: =J133*(1+IF(K$3<=$O$2,$D133,$D133-($D133-$I$130)*MIN(K$3-$O$2,$Q$2)/$Q$2)) -> 379.63821 | L133: =K133*(1+IF(L$3<=$O$2,$D133,$D133-($D133-$I$130)*MIN(L$3-$O$2,$Q$2)/$Q$2)) -> 368.24148 | M133: =L133*(1+IF(M$3<=$O$2,$D133,$D133-($D133-$I$130)*MIN(M$3-$O$2,$Q$2)/$Q$2)) -> 368.84539 | N133: =M133*(1+IF(N$3<=$O$2,$D133,$D133-($D133-$I$130)*MIN(N$3-$O$2,$Q$2)/$Q$2)) -> 381.12794 | O133: =SUMPRODUCT(E133:N133,1/(1+$F$130)^$E$3:$N$3)*$E$2 -> 809.92837 | P133: =N133*$E$2*(1+$I$130)/($F$130-$I$130)/(1+$F$130)^$N$3 -> 1337.8386 | Q133: =O133+P133 -> 2147.767 | R133: =Q133-$G$2+$I$2 -> 2315.167 | S133: =R133/$K$2 -> 65.79048 | T133: =S133-$M$2 -> -98.744899
A134: 3 | B134: =IF(T133>0,B133,D133) -> -0.125 | C134: =IF(T133>0,D133,C133) -> 0.25 | D134: =(B134+C134)/2 -> 0.0625 | E134: =$C$2*(1+IF(E$3<=$O$2,$D134,$D134-($D134-$I$130)*MIN(E$3-$O$2,$Q$2)/$Q$2)) -> 924.40688 | F134: =E134*(1+IF(F$3<=$O$2,$D134,$D134-($D134-$I$130)*MIN(F$3-$O$2,$Q$2)/$Q$2)) -> 982.1823 | G134: =F134*(1+IF(G$3<=$O$2,$D134,$D134-($D134-$I$130)*MIN(G$3-$O$2,$Q$2)/$Q$2)) -> 1043.5687 | H134: =G134*(1+IF(H$3<=$O$2,$D134,$D134-($D134-$I$130)*MIN(H$3-$O$2,$Q$2)/$Q$2)) -> 1108.7917 | I134: =H134*(1+IF(I$3<=$O$2,$D134,$D134-($D134-$I$130)*MIN(I$3-$O$2,$Q$2)/$Q$2)) -> 1178.0912 | J134: =I134*(1+IF(J$3<=$O$2,$D134,$D134-($D134-$I$130)*MIN(J$3-$O$2,$Q$2)/$Q$2)) -> 1244.8419 | K134: =J134*(1+IF(K$3<=$O$2,$D134,$D134-($D134-$I$130)*MIN(K$3-$O$2,$Q$2)/$Q$2)) -> 1308.1047 | L134: =K134*(1+IF(L$3<=$O$2,$D134,$D134-($D134-$I$130)*MIN(L$3-$O$2,$Q$2)/$Q$2)) -> 1366.9433 | M134: =L134*(1+IF(M$3<=$O$2,$D134,$D134-($D134-$I$130)*MIN(M$3-$O$2,$Q$2)/$Q$2)) -> 1420.4455 | N134: =M134*(1+IF(N$3<=$O$2,$D134,$D134-($D134-$I$130)*MIN(N$3-$O$2,$Q$2)/$Q$2)) -> 1467.7463 | O134: =SUMPRODUCT(E134:N134,1/(1+$F$130)^$E$3:$N$3)*$E$2 -> 1858.4769 | P134: =N134*$E$2*(1+$I$130)/($F$130-$I$130)/(1+$F$130)^$N$3 -> 5152.0958 | Q134: =O134+P134 -> 7010.5727 | R134: =Q134-$G$2+$I$2 -> 7177.9727 | S134: =R134/$K$2 -> 203.97763 | T134: =S134-$M$2 -> 39.442249
A135: 4 | B135: =IF(T134>0,B134,D134) -> -0.125 | C135: =IF(T134>0,D134,C134) -> 0.0625 | D135: =(B135+C135)/2 -> -0.03125 | E135: =$C$2*(1+IF(E$3<=$O$2,$D135,$D135-($D135-$I$130)*MIN(E$3-$O$2,$Q$2)/$Q$2)) -> 842.84156 | F135: =E135*(1+IF(F$3<=$O$2,$D135,$D135-($D135-$I$130)*MIN(F$3-$O$2,$Q$2)/$Q$2)) -> 816.50276 | G135: =F135*(1+IF(G$3<=$O$2,$D135,$D135-($D135-$I$130)*MIN(G$3-$O$2,$Q$2)/$Q$2)) -> 790.98705 | H135: =G135*(1+IF(H$3<=$O$2,$D135,$D135-($D135-$I$130)*MIN(H$3-$O$2,$Q$2)/$Q$2)) -> 766.26871 | I135: =H135*(1+IF(I$3<=$O$2,$D135,$D135-($D135-$I$130)*MIN(I$3-$O$2,$Q$2)/$Q$2)) -> 742.32281 | J135: =I135*(1+IF(J$3<=$O$2,$D135,$D135-($D135-$I$130)*MIN(J$3-$O$2,$Q$2)/$Q$2)) -> 728.70861 | K135: =J135*(1+IF(K$3<=$O$2,$D135,$D135-($D135-$I$130)*MIN(K$3-$O$2,$Q$2)/$Q$2)) -> 724.75172 | L135: =K135*(1+IF(L$3<=$O$2,$D135,$D135-($D135-$I$130)*MIN(L$3-$O$2,$Q$2)/$Q$2)) -> 730.17286 | M135: =L135*(1+IF(M$3<=$O$2,$D135,$D135-($D135-$I$130)*MIN(M$3-$O$2,$Q$2)/$Q$2)) -> 745.06109 | N135: =M135*(1+IF(N$3<=$O$2,$D135,$D135-($D135-$I$130)*MIN(N$3-$O$2,$Q$2)/$Q$2)) -> 769.87162 | O135: =SUMPRODUCT(E135:N135,1/(1+$F$130)^$E$3:$N$3)*$E$2 -> 1223.913 | P135: =N135*$E$2*(1+$I$130)/($F$130-$I$130)/(1+$F$130)^$N$3 -> 2702.4101 | Q135: =O135+P135 -> 3926.3231 | R135: =Q135-$G$2+$I$2 -> 4093.7231 | S135: =R135/$K$2 -> 116.332 | T135: =S135-$M$2 -> -48.20338
A136: 5 | B136: =IF(T135>0,B135,D135) -> -0.03125 | C136: =IF(T135>0,D135,C135) -> 0.0625 | D136: =(B136+C136)/2 -> 0.015625 | E136: =$C$2*(1+IF(E$3<=$O$2,$D136,$D136-($D136-$I$130)*MIN(E$3-$O$2,$Q$2)/$Q$2)) -> 883.62422 | F136: =E136*(1+IF(F$3<=$O$2,$D136,$D136-($D136-$I$130)*MIN(F$3-$O$2,$Q$2)/$Q$2)) -> 897.43085 | G136: =F136*(1+IF(G$3<=$O$2,$D136,$D136-($D136-$I$130)*MIN(G$3-$O$2,$Q$2)/$Q$2)) -> 911.4532 | H136: =G136*(1+IF(H$3<=$O$2,$D136,$D136-($D136-$I$130)*MIN(H$3-$O$2,$Q$2)/$Q$2)) -> 925.69466 | I136: =H136*(1+IF(I$3<=$O$2,$D136,$D136-($D136-$I$130)*MIN(I$3-$O$2,$Q$2)/$Q$2)) -> 940.15864 | J136: =I136*(1+IF(J$3<=$O$2,$D136,$D136-($D136-$I$130)*MIN(J$3-$O$2,$Q$2)/$Q$2)) -> 958.17208 | K136: =J136*(1+IF(K$3<=$O$2,$D136,$D136-($D136-$I$130)*MIN(K$3-$O$2,$Q$2)/$Q$2)) -> 979.91779 | L136: =K136*(1+IF(L$3<=$O$2,$D136,$D136-($D136-$I$130)*MIN(L$3-$O$2,$Q$2)/$Q$2)) -> 1005.621 | M136: =L136*(1+IF(M$3<=$O$2,$D136,$D136-($D136-$I$130)*MIN(M$3-$O$2,$Q$2)/$Q$2)) -> 1035.5533 | N136: =M136*(1+IF(N$3<=$O$2,$D136,$D136-($D136-$I$130)*MIN(N$3-$O$2,$Q$2)/$Q$2)) -> 1070.0373 | O136: =SUMPRODUCT(E136:N136,1/(1+$F$130)^$E$3:$N$3)*$E$2 -> 1507.7995 | P136: =N136*$E$2*(1+$I$130)/($F$130-$I$130)/(1+$F$130)^$N$3 -> 3756.0542 | Q136: =O136+P136 -> 5263.8537 | R136: =Q136-$G$2+$I$2 -> 5431.2537 | S136: =R136/$K$2 -> 154.34083 | T136: =S136-$M$2 -> -10.194554
A137: 6 | B137: =IF(T136>0,B136,D136) -> 0.015625 | C137: =IF(T136>0,D136,C136) -> 0.0625 | D137: =(B137+C137)/2 -> 0.0390625 | E137: =$C$2*(1+IF(E$3<=$O$2,$D137,$D137-($D137-$I$130)*MIN(E$3-$O$2,$Q$2)/$Q$2)) -> 904.01555 | F137: =E137*(1+IF(F$3<=$O$2,$D137,$D137-($D137-$I$130)*MIN(F$3-$O$2,$Q$2)/$Q$2)) -> 939.32865 | G137: =F137*(1+IF(G$3<=$O$2,$D137,$D137-($D137-$I$130)*MIN(G$3-$O$2,$Q$2)/$Q$2)) -> 976.02118 | H137: =G137*(1+IF(H$3<=$O$2,$D137,$D137-($D137-$I$130)*MIN(H$3-$O$2,$Q$2)/$Q$2)) -> 1014.147 | I137: =H137*(1+IF(I$3<=$O$2,$D137,$D137-($D137-$I$130)*MIN(I$3-$O$2,$Q$2)/$Q$2)) -> 1053.7621 | J137: =I137*(1+IF(J$3<=$O$2,$D137,$D137-($D137-$I$130)*MIN(J$3-$O$2,$Q$2)/$Q$2)) -> 1093.7102 | K137: =J137*(1+IF(K$3<=$O$2,$D137,$D137-($D137-$I$130)*MIN(K$3-$O$2,$Q$2)/$Q$2)) -> 1133.9123 | L137: =K137*(1+IF(L$3<=$O$2,$D137,$D137-($D137-$I$130)*MIN(L$3-$O$2,$Q$2)/$Q$2)) -> 1174.2852 | M137: =L137*(1+IF(M$3<=$O$2,$D137,$D137-($D137-$I$130)*MIN(M$3-$O$2,$Q$2)/$Q$2)) -> 1214.7423 | N137: =M137*(1+IF(N$3<=$O$2,$D137,$D137-($D137-$I$130)*MIN(N$3-$O$2,$Q$2)/$Q$2)) -> 1255.1932 | O137: =SUMPRODUCT(E137:N137,1/(1+$F$130)^$E$3:$N$3)*$E$2 -> 1673.9453 | P137: =N137*$E$2*(1+$I$130)/($F$130-$I$130)/(1+$F$130)^$N$3 -> 4405.9902 | Q137: =O137+P137 -> 6079.9356 | R137: =Q137-$G$2+$I$2 -> 6247.3356 | S137: =R137/$K$2 -> 177.53156 | T137: =S137-$M$2 -> 12.99618
A138: 7 | B138: =IF(T137>0,B137,D137) -> 0.015625 | C138: =IF(T137>0,D137,C137) -> 0.0390625 | D138: =(B138+C138)/2 -> 0.02734375 | E138: =$C$2*(1+IF(E$3<=$O$2,$D138,$D138-($D138-$I$130)*MIN(E$3-$O$2,$Q$2)/$Q$2)) -> 893.81988 | F138: =E138*(1+IF(F$3<=$O$2,$D138,$D138-($D138-$I$130)*MIN(F$3-$O$2,$Q$2)/$Q$2)) -> 918.26027 | G138: =F138*(1+IF(G$3<=$O$2,$D138,$D138-($D138-$I$130)*MIN(G$3-$O$2,$Q$2)/$Q$2)) -> 943.36895 | H138: =G138*(1+IF(H$3<=$O$2,$D138,$D138-($D138-$I$130)*MIN(H$3-$O$2,$Q$2)/$Q$2)) -> 969.16419 | I138: =H138*(1+IF(I$3<=$O$2,$D138,$D138-($D138-$I$130)*MIN(I$3-$O$2,$Q$2)/$Q$2)) -> 995.66478 | J138: =I138*(1+IF(J$3<=$O$2,$D138,$D138-($D138-$I$130)*MIN(J$3-$O$2,$Q$2)/$Q$2)) -> 1024.0761 | K138: =J138*(1+IF(K$3<=$O$2,$D138,$D138-($D138-$I$130)*MIN(K$3-$O$2,$Q$2)/$Q$2)) -> 1054.518 | L138: =K138*(1+IF(L$3<=$O$2,$D138,$D138-($D138-$I$130)*MIN(L$3-$O$2,$Q$2)/$Q$2)) -> 1087.1211 | M138: =L138*(1+IF(M$3<=$O$2,$D138,$D138-($D138-$I$130)*MIN(M$3-$O$2,$Q$2)/$Q$2)) -> 1122.0272 | N138: =M138*(1+IF(N$3<=$O$2,$D138,$D138-($D138-$I$130)*MIN(N$3-$O$2,$Q$2)/$Q$2)) -> 1159.3907 | O138: =SUMPRODUCT(E138:N138,1/(1+$F$130)^$E$3:$N$3)*$E$2 -> 1588.6854 | P138: =N138*$E$2*(1+$I$130)/($F$130-$I$130)/(1+$F$130)^$N$3 -> 4069.7033 | Q138: =O138+P138 -> 5658.3886 | R138: =Q138-$G$2+$I$2 -> 5825.7886 | S138: =R138/$K$2 -> 165.55239 | T138: =S138-$M$2 -> 1.0170117
A139: 8 | B139: =IF(T138>0,B138,D138) -> 0.015625 | C139: =IF(T138>0,D138,C138) -> 0.02734375 | D139: =(B139+C139)/2 -> 0.021484375 | E139: =$C$2*(1+IF(E$3<=$O$2,$D139,$D139-($D139-$I$130)*MIN(E$3-$O$2,$Q$2)/$Q$2)) -> 888.72205 | F139: =E139*(1+IF(F$3<=$O$2,$D139,$D139-($D139-$I$130)*MIN(F$3-$O$2,$Q$2)/$Q$2)) -> 907.81569 | G139: =F139*(1+IF(G$3<=$O$2,$D139,$D139-($D139-$I$130)*MIN(G$3-$O$2,$Q$2)/$Q$2)) -> 927.31954 | H139: =G139*(1+IF(H$3<=$O$2,$D139,$D139-($D139-$I$130)*MIN(H$3-$O$2,$Q$2)/$Q$2)) -> 947.24242 | I139: =H139*(1+IF(I$3<=$O$2,$D139,$D139-($D139-$I$130)*MIN(I$3-$O$2,$Q$2)/$Q$2)) -> 967.59333 | J139: =I139*(1+IF(J$3<=$O$2,$D139,$D139-($D139-$I$130)*MIN(J$3-$O$2,$Q$2)/$Q$2)) -> 990.66802 | K139: =J139*(1+IF(K$3<=$O$2,$D139,$D139-($D139-$I$130)*MIN(K$3-$O$2,$Q$2)/$Q$2)) -> 1016.634 | L139: =K139*(1+IF(L$3<=$O$2,$D139,$D139-($D139-$I$130)*MIN(L$3-$O$2,$Q$2)/$Q$2)) -> 1045.6831 | M139: =L139*(1+IF(M$3<=$O$2,$D139,$D139-($D139-$I$130)*MIN(M$3-$O$2,$Q$2)/$Q$2)) -> 1078.0333 | N139: =M139*(1+IF(N$3<=$O$2,$D139,$D139-($D139-$I$130)*MIN(N$3-$O$2,$Q$2)/$Q$2)) -> 1113.9318 | O139: =SUMPRODUCT(E139:N139,1/(1+$F$130)^$E$3:$N$3)*$E$2 -> 1547.7091 | P139: =N139*$E$2*(1+$I$130)/($F$130-$I$130)/(1+$F$130)^$N$3 -> 3910.133 | Q139: =O139+P139 -> 5457.8421 | R139: =Q139-$G$2+$I$2 -> 5625.2421 | S139: =R139/$K$2 -> 159.85343 | T139: =S139-$M$2 -> -4.6819537
A140: 9 | B140: =IF(T139>0,B139,D139) -> 0.021484375 | C140: =IF(T139>0,D139,C139) -> 0.02734375 | D140: =(B140+C140)/2 -> 0.024414062 | E140: =$C$2*(1+IF(E$3<=$O$2,$D140,$D140-($D140-$I$130)*MIN(E$3-$O$2,$Q$2)/$Q$2)) -> 891.27097 | F140: =E140*(1+IF(F$3<=$O$2,$D140,$D140-($D140-$I$130)*MIN(F$3-$O$2,$Q$2)/$Q$2)) -> 913.03051 | G140: =F140*(1+IF(G$3<=$O$2,$D140,$D140-($D140-$I$130)*MIN(G$3-$O$2,$Q$2)/$Q$2)) -> 935.3213 | H140: =G140*(1+IF(H$3<=$O$2,$D140,$D140-($D140-$I$130)*MIN(H$3-$O$2,$Q$2)/$Q$2)) -> 958.15629 | I140: =H140*(1+IF(I$3<=$O$2,$D140,$D140-($D140-$I$130)*MIN(I$3-$O$2,$Q$2)/$Q$2)) -> 981.54878 | J140: =I140*(1+IF(J$3<=$O$2,$D140,$D140-($D140-$I$130)*MIN(J$3-$O$2,$Q$2)/$Q$2)) -> 1007.2568 | K140: =J140*(1+IF(K$3<=$O$2,$D140,$D140-($D140-$I$130)*MIN(K$3-$O$2,$Q$2)/$Q$2)) -> 1035.4282 | L140: =K140*(1+IF(L$3<=$O$2,$D140,$D140-($D140-$I$130)*MIN(L$3-$O$2,$Q$2)/$Q$2)) -> 1066.2276 | M140: =L140*(1+IF(M$3<=$O$2,$D140,$D140-($D140-$I$130)*MIN(M$3-$O$2,$Q$2)/$Q$2)) -> 1099.8381 | N140: =M140*(1+IF(N$3<=$O$2,$D140,$D140-($D140-$I$130)*MIN(N$3-$O$2,$Q$2)/$Q$2)) -> 1136.4627 | O140: =SUMPRODUCT(E140:N140,1/(1+$F$130)^$E$3:$N$3)*$E$2 -> 1568.0622 | P140: =N140*$E$2*(1+$I$130)/($F$130-$I$130)/(1+$F$130)^$N$3 -> 3989.2214 | Q140: =O140+P140 -> 5557.2836 | R140: =Q140-$G$2+$I$2 -> 5724.6836 | S140: =R140/$K$2 -> 162.67927 | T140: =S140-$M$2 -> -1.8561073
A141: 10 | B141: =IF(T140>0,B140,D140) -> 0.024414062 | C141: =IF(T140>0,D140,C140) -> 0.02734375 | D141: =(B141+C141)/2 -> 0.025878906 | E141: =$C$2*(1+IF(E$3<=$O$2,$D141,$D141-($D141-$I$130)*MIN(E$3-$O$2,$Q$2)/$Q$2)) -> 892.54542 | F141: =E141*(1+IF(F$3<=$O$2,$D141,$D141-($D141-$I$130)*MIN(F$3-$O$2,$Q$2)/$Q$2)) -> 915.64352 | G141: =F141*(1+IF(G$3<=$O$2,$D141,$D141-($D141-$I$130)*MIN(G$3-$O$2,$Q$2)/$Q$2)) -> 939.33938 | H141: =G141*(1+IF(H$3<=$O$2,$D141,$D141-($D141-$I$130)*MIN(H$3-$O$2,$Q$2)/$Q$2)) -> 963.64845 | I141: =H141*(1+IF(I$3<=$O$2,$D141,$D141-($D141-$I$130)*MIN(I$3-$O$2,$Q$2)/$Q$2)) -> 988.58662 | J141: =I141*(1+IF(J$3<=$O$2,$D141,$D141-($D141-$I$130)*MIN(J$3-$O$2,$Q$2)/$Q$2)) -> 1015.6374 | K141: =J141*(1+IF(K$3<=$O$2,$D141,$D141-($D141-$I$130)*MIN(K$3-$O$2,$Q$2)/$Q$2)) -> 1044.9359 | L141: =K141*(1+IF(L$3<=$O$2,$D141,$D141-($D141-$I$130)*MIN(L$3-$O$2,$Q$2)/$Q$2)) -> 1076.6304 | M141: =L141*(1+IF(M$3<=$O$2,$D141,$D141-($D141-$I$130)*MIN(M$3-$O$2,$Q$2)/$Q$2)) -> 1110.8843 | N141: =M141*(1+IF(N$3<=$O$2,$D141,$D141-($D141-$I$130)*MIN(N$3-$O$2,$Q$2)/$Q$2)) -> 1147.8767 | O141: =SUMPRODUCT(E141:N141,1/(1+$F$130)^$E$3:$N$3)*$E$2 -> 1578.3398 | P141: =N141*$E$2*(1+$I$130)/($F$130-$I$130)/(1+$F$130)^$N$3 -> 4029.2868 | Q141: =O141+P141 -> 5607.6267 | R141: =Q141-$G$2+$I$2 -> 5775.0267 | S141: =R141/$K$2 -> 164.10988 | T141: =S141-$M$2 -> -0.42549992
A142: 11 | B142: =IF(T141>0,B141,D141) -> 0.025878906 | C142: =IF(T141>0,D141,C141) -> 0.02734375 | D142: =(B142+C142)/2 -> 0.026611328 | E142: =$C$2*(1+IF(E$3<=$O$2,$D142,$D142-($D142-$I$130)*MIN(E$3-$O$2,$Q$2)/$Q$2)) -> 893.18265 | F142: =E142*(1+IF(F$3<=$O$2,$D142,$D142-($D142-$I$130)*MIN(F$3-$O$2,$Q$2)/$Q$2)) -> 916.95143 | G142: =F142*(1+IF(G$3<=$O$2,$D142,$D142-($D142-$I$130)*MIN(G$3-$O$2,$Q$2)/$Q$2)) -> 941.35273 | H142: =G142*(1+IF(H$3<=$O$2,$D142,$D142-($D142-$I$130)*MIN(H$3-$O$2,$Q$2)/$Q$2)) -> 966.40337 | I142: =H142*(1+IF(I$3<=$O$2,$D142,$D142-($D142-$I$130)*MIN(I$3-$O$2,$Q$2)/$Q$2)) -> 992.12065 | J142: =I142*(1+IF(J$3<=$O$2,$D142,$D142-($D142-$I$130)*MIN(J$3-$O$2,$Q$2)/$Q$2)) -> 1019.8495 | K142: =J142*(1+IF(K$3<=$O$2,$D142,$D142-($D142-$I$130)*MIN(K$3-$O$2,$Q$2)/$Q$2)) -> 1049.7176 | L142: =K142*(1+IF(L$3<=$O$2,$D142,$D142-($D142-$I$130)*MIN(L$3-$O$2,$Q$2)/$Q$2)) -> 1081.8647 | M142: =L142*(1+IF(M$3<=$O$2,$D142,$D142-($D142-$I$130)*MIN(M$3-$O$2,$Q$2)/$Q$2)) -> 1116.4436 | N142: =M142*(1+IF(N$3<=$O$2,$D142,$D142-($D142-$I$130)*MIN(N$3-$O$2,$Q$2)/$Q$2)) -> 1153.6211 | O142: =SUMPRODUCT(E142:N142,1/(1+$F$130)^$E$3:$N$3)*$E$2 -> 1583.5041 | P142: =N142*$E$2*(1+$I$130)/($F$130-$I$130)/(1+$F$130)^$N$3 -> 4049.451 | Q142: =O142+P142 -> 5632.9551 | R142: =Q142-$G$2+$I$2 -> 5800.3551 | S142: =R142/$K$2 -> 164.82964 | T142: =S142-$M$2 -> 0.29426246
A143: 12 | B143: =IF(T142>0,B142,D142) -> 0.025878906 | C143: =IF(T142>0,D142,C142) -> 0.026611328 | D143: =(B143+C143)/2 -> 0.026245117 | E143: =$C$2*(1+IF(E$3<=$O$2,$D143,$D143-($D143-$I$130)*MIN(E$3-$O$2,$Q$2)/$Q$2)) -> 892.86404 | F143: =E143*(1+IF(F$3<=$O$2,$D143,$D143-($D143-$I$130)*MIN(F$3-$O$2,$Q$2)/$Q$2)) -> 916.29736 | G143: =F143*(1+IF(G$3<=$O$2,$D143,$D143-($D143-$I$130)*MIN(G$3-$O$2,$Q$2)/$Q$2)) -> 940.34569 | H143: =G143*(1+IF(H$3<=$O$2,$D143,$D143-($D143-$I$130)*MIN(H$3-$O$2,$Q$2)/$Q$2)) -> 965.02518 | I143: =H143*(1+IF(I$3<=$O$2,$D143,$D143-($D143-$I$130)*MIN(I$3-$O$2,$Q$2)/$Q$2)) -> 990.35237 | J143: =I143*(1+IF(J$3<=$O$2,$D143,$D143-($D143-$I$130)*MIN(J$3-$O$2,$Q$2)/$Q$2)) -> 1017.7417 | K143: =J143*(1+IF(K$3<=$O$2,$D143,$D143-($D143-$I$130)*MIN(K$3-$O$2,$Q$2)/$Q$2)) -> 1047.3244 | L143: =K143*(1+IF(L$3<=$O$2,$D143,$D143-($D143-$I$130)*MIN(L$3-$O$2,$Q$2)/$Q$2)) -> 1079.2448 | M143: =L143*(1+IF(M$3<=$O$2,$D143,$D143-($D143-$I$130)*MIN(M$3-$O$2,$Q$2)/$Q$2)) -> 1113.6609 | N143: =M143*(1+IF(N$3<=$O$2,$D143,$D143-($D143-$I$130)*MIN(N$3-$O$2,$Q$2)/$Q$2)) -> 1150.7458 | O143: =SUMPRODUCT(E143:N143,1/(1+$F$130)^$E$3:$N$3)*$E$2 -> 1580.9198 | P143: =N143*$E$2*(1+$I$130)/($F$130-$I$130)/(1+$F$130)^$N$3 -> 4039.3579 | Q143: =O143+P143 -> 5620.2778 | R143: =Q143-$G$2+$I$2 -> 5787.6778 | S143: =R143/$K$2 -> 164.46939 | T143: =S143-$M$2 -> -0.065991414
A144: 13 | B144: =IF(T143>0,B143,D143) -> 0.026245117 | C144: =IF(T143>0,D143,C143) -> 0.026611328 | D144: =(B144+C144)/2 -> 0.026428223 | E144: =$C$2*(1+IF(E$3<=$O$2,$D144,$D144-($D144-$I$130)*MIN(E$3-$O$2,$Q$2)/$Q$2)) -> 893.02335 | F144: =E144*(1+IF(F$3<=$O$2,$D144,$D144-($D144-$I$130)*MIN(F$3-$O$2,$Q$2)/$Q$2)) -> 916.62437 | G144: =F144*(1+IF(G$3<=$O$2,$D144,$D144-($D144-$I$130)*MIN(G$3-$O$2,$Q$2)/$Q$2)) -> 940.84912 | H144: =G144*(1+IF(H$3<=$O$2,$D144,$D144-($D144-$I$130)*MIN(H$3-$O$2,$Q$2)/$Q$2)) -> 965.71409 | I144: =H144*(1+IF(I$3<=$O$2,$D144,$D144-($D144-$I$130)*MIN(I$3-$O$2,$Q$2)/$Q$2)) -> 991.2362 | J144: =I144*(1+IF(J$3<=$O$2,$D144,$D144-($D144-$I$130)*MIN(J$3-$O$2,$Q$2)/$Q$2)) -> 1018.7951 | K144: =J144*(1+IF(K$3<=$O$2,$D144,$D144-($D144-$I$130)*MIN(K$3-$O$2,$Q$2)/$Q$2)) -> 1048.5204 | L144: =K144*(1+IF(L$3<=$O$2,$D144,$D144-($D144-$I$130)*MIN(L$3-$O$2,$Q$2)/$Q$2)) -> 1080.5541 | M144: =L144*(1+IF(M$3<=$O$2,$D144,$D144-($D144-$I$130)*MIN(M$3-$O$2,$Q$2)/$Q$2)) -> 1115.0515 | N144: =M144*(1+IF(N$3<=$O$2,$D144,$D144-($D144-$I$130)*MIN(N$3-$O$2,$Q$2)/$Q$2)) -> 1152.1827 | O144: =SUMPRODUCT(E144:N144,1/(1+$F$130)^$E$3:$N$3)*$E$2 -> 1582.2114 | P144: =N144*$E$2*(1+$I$130)/($F$130-$I$130)/(1+$F$130)^$N$3 -> 4044.4017 | Q144: =O144+P144 -> 5626.6131 | R144: =Q144-$G$2+$I$2 -> 5794.0131 | S144: =R144/$K$2 -> 164.64942 | T144: =S144-$M$2 -> 0.11404227
... A155: 24 | B155: =IF(T154>0,B154,D154) -> 0.026312172 | C155: =IF(T154>0,D154,C154) -> 0.026312351 | D155: =(B155+C155)/2 -> 0.026312262 | E155: =$C$2*(1+IF(E$3<=$O$2,$D155,$D155-($D155-$I$130)*MIN(E$3-$O$2,$Q$2)/$Q$2)) -> 892.92246 | F155: =E155*(1+IF(F$3<=$O$2,$D155,$D155-($D155-$I$130)*MIN(F$3-$O$2,$Q$2)/$Q$2)) -> 916.41727 | G155: =F155*(1+IF(G$3<=$O$2,$D155,$D155-($D155-$I$130)*MIN(G$3-$O$2,$Q$2)/$Q$2)) -> 940.53028 | H155: =G155*(1+IF(H$3<=$O$2,$D155,$D155-($D155-$I$130)*MIN(H$3-$O$2,$Q$2)/$Q$2)) -> 965.27776 | I155: =H155*(1+IF(I$3<=$O$2,$D155,$D155-($D155-$I$130)*MIN(I$3-$O$2,$Q$2)/$Q$2)) -> 990.6764 | J155: =I155*(1+IF(J$3<=$O$2,$D155,$D155-($D155-$I$130)*MIN(J$3-$O$2,$Q$2)/$Q$2)) -> 1018.1279 | K155: =J155*(1+IF(K$3<=$O$2,$D155,$D155-($D155-$I$130)*MIN(K$3-$O$2,$Q$2)/$Q$2)) -> 1047.7629 | L155: =K155*(1+IF(L$3<=$O$2,$D155,$D155-($D155-$I$130)*MIN(L$3-$O$2,$Q$2)/$Q$2)) -> 1079.7248 | M155: =L155*(1+IF(M$3<=$O$2,$D155,$D155-($D155-$I$130)*MIN(M$3-$O$2,$Q$2)/$Q$2)) -> 1114.1706 | N155: =M155*(1+IF(N$3<=$O$2,$D155,$D155-($D155-$I$130)*MIN(N$3-$O$2,$Q$2)/$Q$2)) -> 1151.2725 | O155: =SUMPRODUCT(E155:N155,1/(1+$F$130)^$E$3:$N$3)*$E$2 -> 1581.3933 | P155: =N155*$E$2*(1+$I$130)/($F$130-$I$130)/(1+$F$130)^$N$3 -> 4041.2068 | Q155: =O155+P155 -> 5622.6002 | R155: =Q155-$G$2+$I$2 -> 5790.0002 | S155: =R155/$K$2 -> 164.53538 | T155: =S155-$M$2 -> 5.1505508e-06
A157: Grid block 6: row 1, column 5 of table A (24 steps) | E157: WACC | F157: =Sensitivity!$B$10 -> 0.067507582 | G157: Terminal growth | I157: =Sensitivity!$G$9 -> 0.0383
A158: Step | B158: Low | C158: High | D158: Mid | E158: Rev Y1 | F158: Rev Y2 | G158: Rev Y3 | H158: Rev Y4 | I158: Rev Y5 | J158: Rev Y6 | K158: Rev Y7 | L158: Rev Y8 | M158: Rev Y9 | N158: Rev Y10 | O158: PV of FCF | P158: PV of TV | Q158: EV | R158: Equity | S158: Per share | T158: Value - price
A159: 1 | B159: -0.5 | C159: 1 | D159: =(B159+C159)/2 -> 0.25 | E159: =$C$2*(1+IF(E$3<=$O$2,$D159,$D159-($D159-$I$157)*MIN(E$3-$O$2,$Q$2)/$Q$2)) -> 1087.5375 | F159: =E159*(1+IF(F$3<=$O$2,$D159,$D159-($D159-$I$157)*MIN(F$3-$O$2,$Q$2)/$Q$2)) -> 1359.4219 | G159: =F159*(1+IF(G$3<=$O$2,$D159,$D159-($D159-$I$157)*MIN(G$3-$O$2,$Q$2)/$Q$2)) -> 1699.2773 | H159: =G159*(1+IF(H$3<=$O$2,$D159,$D159-($D159-$I$157)*MIN(H$3-$O$2,$Q$2)/$Q$2)) -> 2124.0967 | I159: =H159*(1+IF(I$3<=$O$2,$D159,$D159-($D159-$I$157)*MIN(I$3-$O$2,$Q$2)/$Q$2)) -> 2655.1208 | J159: =I159*(1+IF(J$3<=$O$2,$D159,$D159-($D159-$I$157)*MIN(J$3-$O$2,$Q$2)/$Q$2)) -> 3206.4832 | K159: =J159*(1+IF(K$3<=$O$2,$D159,$D159-($D159-$I$157)*MIN(K$3-$O$2,$Q$2)/$Q$2)) -> 3736.5791 | L159: =K159*(1+IF(L$3<=$O$2,$D159,$D159-($D159-$I$157)*MIN(L$3-$O$2,$Q$2)/$Q$2)) -> 4196.1035 | M159: =L159*(1+IF(M$3<=$O$2,$D159,$D159-($D159-$I$157)*MIN(M$3-$O$2,$Q$2)/$Q$2)) -> 4534.4773 | N159: =M159*(1+IF(N$3<=$O$2,$D159,$D159-($D159-$I$157)*MIN(N$3-$O$2,$Q$2)/$Q$2)) -> 4708.1478 | O159: =SUMPRODUCT(E159:N159,1/(1+$F$157)^$E$3:$N$3)*$E$2 -> 4276.288 | P159: =N159*$E$2*(1+$I$157)/($F$157-$I$157)/(1+$F$157)^$N$3 -> 19449.401 | Q159: =O159+P159 -> 23725.689 | R159: =Q159-$G$2+$I$2 -> 23893.089 | S159: =R159/$K$2 -> 678.97382 | T159: =S159-$M$2 -> 514.43844
A160: 2 | B160: =IF(T159>0,B159,D159) -> -0.5 | C160: =IF(T159>0,D159,C159) -> 0.25 | D160: =(B160+C160)/2 -> -0.125 | E160: =$C$2*(1+IF(E$3<=$O$2,$D160,$D160-($D160-$I$157)*MIN(E$3-$O$2,$Q$2)/$Q$2)) -> 761.27625 | F160: =E160*(1+IF(F$3<=$O$2,$D160,$D160-($D160-$I$157)*MIN(F$3-$O$2,$Q$2)/$Q$2)) -> 666.11672 | G160: =F160*(1+IF(G$3<=$O$2,$D160,$D160-($D160-$I$157)*MIN(G$3-$O$2,$Q$2)/$Q$2)) -> 582.85213 | H160: =G160*(1+IF(H$3<=$O$2,$D160,$D160-($D160-$I$157)*MIN(H$3-$O$2,$Q$2)/$Q$2)) -> 509.99561 | I160: =H160*(1+IF(I$3<=$O$2,$D160,$D160-($D160-$I$157)*MIN(I$3-$O$2,$Q$2)/$Q$2)) -> 446.24616 | J160: =I160*(1+IF(J$3<=$O$2,$D160,$D160-($D160-$I$157)*MIN(J$3-$O$2,$Q$2)/$Q$2)) -> 405.03979 | K160: =J160*(1+IF(K$3<=$O$2,$D160,$D160-($D160-$I$157)*MIN(K$3-$O$2,$Q$2)/$Q$2)) -> 380.86702 | L160: =K160*(1+IF(L$3<=$O$2,$D160,$D160-($D160-$I$157)*MIN(L$3-$O$2,$Q$2)/$Q$2)) -> 370.57599 | M160: =L160*(1+IF(M$3<=$O$2,$D160,$D160-($D160-$I$157)*MIN(M$3-$O$2,$Q$2)/$Q$2)) -> 372.66604 | N160: =M160*(1+IF(N$3<=$O$2,$D160,$D160-($D160-$I$157)*MIN(N$3-$O$2,$Q$2)/$Q$2)) -> 386.93915 | O160: =SUMPRODUCT(E160:N160,1/(1+$F$157)^$E$3:$N$3)*$E$2 -> 811.62782 | P160: =N160*$E$2*(1+$I$157)/($F$157-$I$157)/(1+$F$157)^$N$3 -> 1598.4491 | Q160: =O160+P160 -> 2410.0769 | R160: =Q160-$G$2+$I$2 -> 2577.4769 | S160: =R160/$K$2 -> 73.244584 | T160: =S160-$M$2 -> -91.290796
A161: 3 | B161: =IF(T160>0,B160,D160) -> -0.125 | C161: =IF(T160>0,D160,C160) -> 0.25 | D161: =(B161+C161)/2 -> 0.0625 | E161: =$C$2*(1+IF(E$3<=$O$2,$D161,$D161-($D161-$I$157)*MIN(E$3-$O$2,$Q$2)/$Q$2)) -> 924.40688 | F161: =E161*(1+IF(F$3<=$O$2,$D161,$D161-($D161-$I$157)*MIN(F$3-$O$2,$Q$2)/$Q$2)) -> 982.1823 | G161: =F161*(1+IF(G$3<=$O$2,$D161,$D161-($D161-$I$157)*MIN(G$3-$O$2,$Q$2)/$Q$2)) -> 1043.5687 | H161: =G161*(1+IF(H$3<=$O$2,$D161,$D161-($D161-$I$157)*MIN(H$3-$O$2,$Q$2)/$Q$2)) -> 1108.7917 | I161: =H161*(1+IF(I$3<=$O$2,$D161,$D161-($D161-$I$157)*MIN(I$3-$O$2,$Q$2)/$Q$2)) -> 1178.0912 | J161: =I161*(1+IF(J$3<=$O$2,$D161,$D161-($D161-$I$157)*MIN(J$3-$O$2,$Q$2)/$Q$2)) -> 1246.02 | K161: =J161*(1+IF(K$3<=$O$2,$D161,$D161-($D161-$I$157)*MIN(K$3-$O$2,$Q$2)/$Q$2)) -> 1311.8347 | L161: =K161*(1+IF(L$3<=$O$2,$D161,$D161-($D161-$I$157)*MIN(L$3-$O$2,$Q$2)/$Q$2)) -> 1374.7766 | M161: =L161*(1+IF(M$3<=$O$2,$D161,$D161-($D161-$I$157)*MIN(M$3-$O$2,$Q$2)/$Q$2)) -> 1434.0844 | N161: =M161*(1+IF(N$3<=$O$2,$D161,$D161-($D161-$I$157)*MIN(N$3-$O$2,$Q$2)/$Q$2)) -> 1489.0099 | O161: =SUMPRODUCT(E161:N161,1/(1+$F$157)^$E$3:$N$3)*$E$2 -> 1864.3822 | P161: =N161*$E$2*(1+$I$157)/($F$157-$I$157)/(1+$F$157)^$N$3 -> 6151.1131 | Q161: =O161+P161 -> 8015.4953 | R161: =Q161-$G$2+$I$2 -> 8182.8953 | S161: =R161/$K$2 -> 232.53468 | T161: =S161-$M$2 -> 67.999299
A162: 4 | B162: =IF(T161>0,B161,D161) -> -0.125 | C162: =IF(T161>0,D161,C161) -> 0.0625 | D162: =(B162+C162)/2 -> -0.03125 | E162: =$C$2*(1+IF(E$3<=$O$2,$D162,$D162-($D162-$I$157)*MIN(E$3-$O$2,$Q$2)/$Q$2)) -> 842.84156 | F162: =E162*(1+IF(F$3<=$O$2,$D162,$D162-($D162-$I$157)*MIN(F$3-$O$2,$Q$2)/$Q$2)) -> 816.50276 | G162: =F162*(1+IF(G$3<=$O$2,$D162,$D162-($D162-$I$157)*MIN(G$3-$O$2,$Q$2)/$Q$2)) -> 790.98705 | H162: =G162*(1+IF(H$3<=$O$2,$D162,$D162-($D162-$I$157)*MIN(H$3-$O$2,$Q$2)/$Q$2)) -> 766.26871 | I162: =H162*(1+IF(I$3<=$O$2,$D162,$D162-($D162-$I$157)*MIN(I$3-$O$2,$Q$2)/$Q$2)) -> 742.32281 | J162: =I162*(1+IF(J$3<=$O$2,$D162,$D162-($D162-$I$157)*MIN(J$3-$O$2,$Q$2)/$Q$2)) -> 729.45093 | K162: =J162*(1+IF(K$3<=$O$2,$D162,$D162-($D162-$I$157)*MIN(K$3-$O$2,$Q$2)/$Q$2)) -> 726.94892 | L162: =K162*(1+IF(L$3<=$O$2,$D162,$D162-($D162-$I$157)*MIN(L$3-$O$2,$Q$2)/$Q$2)) -> 734.56734 | M162: =L162*(1+IF(M$3<=$O$2,$D162,$D162-($D162-$I$157)*MIN(M$3-$O$2,$Q$2)/$Q$2)) -> 752.48344 | N162: =M162*(1+IF(N$3<=$O$2,$D162,$D162-($D162-$I$157)*MIN(N$3-$O$2,$Q$2)/$Q$2)) -> 781.30355 | O162: =SUMPRODUCT(E162:N162,1/(1+$F$157)^$E$3:$N$3)*$E$2 -> 1227.1667 | P162: =N162*$E$2*(1+$I$157)/($F$157-$I$157)/(1+$F$157)^$N$3 -> 3227.572 | Q162: =O162+P162 -> 4454.7387 | R162: =Q162-$G$2+$I$2 -> 4622.1387 | S162: =R162/$K$2 -> 131.34807 | T162: =S162-$M$2 -> -33.187305
A163: 5 | B163: =IF(T162>0,B162,D162) -> -0.03125 | C163: =IF(T162>0,D162,C162) -> 0.0625 | D163: =(B163+C163)/2 -> 0.015625 | E163: =$C$2*(1+IF(E$3<=$O$2,$D163,$D163-($D163-$I$157)*MIN(E$3-$O$2,$Q$2)/$Q$2)) -> 883.62422 | F163: =E163*(1+IF(F$3<=$O$2,$D163,$D163-($D163-$I$157)*MIN(F$3-$O$2,$Q$2)/$Q$2)) -> 897.43085 | G163: =F163*(1+IF(G$3<=$O$2,$D163,$D163-($D163-$I$157)*MIN(G$3-$O$2,$Q$2)/$Q$2)) -> 911.4532 | H163: =G163*(1+IF(H$3<=$O$2,$D163,$D163-($D163-$I$157)*MIN(H$3-$O$2,$Q$2)/$Q$2)) -> 925.69466 | I163: =H163*(1+IF(I$3<=$O$2,$D163,$D163-($D163-$I$157)*MIN(I$3-$O$2,$Q$2)/$Q$2)) -> 940.15864 | J163: =I163*(1+IF(J$3<=$O$2,$D163,$D163-($D163-$I$157)*MIN(J$3-$O$2,$Q$2)/$Q$2)) -> 959.11224 | K163: =J163*(1+IF(K$3<=$O$2,$D163,$D163-($D163-$I$157)*MIN(K$3-$O$2,$Q$2)/$Q$2)) -> 982.79751 | L163: =K163*(1+IF(L$3<=$O$2,$D163,$D163-($D163-$I$157)*MIN(L$3-$O$2,$Q$2)/$Q$2)) -> 1011.5247 | M163: =L163*(1+IF(M$3<=$O$2,$D163,$D163-($D163-$I$157)*MIN(M$3-$O$2,$Q$2)/$Q$2)) -> 1045.6788 | N163: =M163*(1+IF(N$3<=$O$2,$D163,$D163-($D163-$I$157)*MIN(N$3-$O$2,$Q$2)/$Q$2)) -> 1085.7283 | O163: =SUMPRODUCT(E163:N163,1/(1+$F$157)^$E$3:$N$3)*$E$2 -> 1512.2097 | P163: =N163*$E$2*(1+$I$157)/($F$157-$I$157)/(1+$F$157)^$N$3 -> 4485.1534 | Q163: =O163+P163 -> 5997.3631 | R163: =Q163-$G$2+$I$2 -> 6164.7631 | S163: =R163/$K$2 -> 175.18508 | T163: =S163-$M$2 -> 10.649705
A164: 6 | B164: =IF(T163>0,B163,D163) -> -0.03125 | C164: =IF(T163>0,D163,C163) -> 0.015625 | D164: =(B164+C164)/2 -> -0.0078125 | E164: =$C$2*(1+IF(E$3<=$O$2,$D164,$D164-($D164-$I$157)*MIN(E$3-$O$2,$Q$2)/$Q$2)) -> 863.23289 | F164: =E164*(1+IF(F$3<=$O$2,$D164,$D164-($D164-$I$157)*MIN(F$3-$O$2,$Q$2)/$Q$2)) -> 856.48888 | G164: =F164*(1+IF(G$3<=$O$2,$D164,$D164-($D164-$I$157)*MIN(G$3-$O$2,$Q$2)/$Q$2)) -> 849.79756 | H164: =G164*(1+IF(H$3<=$O$2,$D164,$D164-($D164-$I$157)*MIN(H$3-$O$2,$Q$2)/$Q$2)) -> 843.15852 | I164: =H164*(1+IF(I$3<=$O$2,$D164,$D164-($D164-$I$157)*MIN(I$3-$O$2,$Q$2)/$Q$2)) -> 836.57134 | J164: =I164*(1+IF(J$3<=$O$2,$D164,$D164-($D164-$I$157)*MIN(J$3-$O$2,$Q$2)/$Q$2)) -> 837.75091 | K164: =J164*(1+IF(K$3<=$O$2,$D164,$D164-($D164-$I$157)*MIN(K$3-$O$2,$Q$2)/$Q$2)) -> 846.6583 | L164: =K164*(1+IF(L$3<=$O$2,$D164,$D164-($D164-$I$157)*MIN(L$3-$O$2,$Q$2)/$Q$2)) -> 863.4687 | M164: =L164*(1+IF(M$3<=$O$2,$D164,$D164-($D164-$I$157)*MIN(M$3-$O$2,$Q$2)/$Q$2)) -> 888.57621 | N164: =M164*(1+IF(N$3<=$O$2,$D164,$D164-($D164-$I$157)*MIN(N$3-$O$2,$Q$2)/$Q$2)) -> 922.60868 | O164: =SUMPRODUCT(E164:N164,1/(1+$F$157)^$E$3:$N$3)*$E$2 -> 1362.11 | P164: =N164*$E$2*(1+$I$157)/($F$157-$I$157)/(1+$F$157)^$N$3 -> 3811.3047 | Q164: =O164+P164 -> 5173.4147 | R164: =Q164-$G$2+$I$2 -> 5340.8147 | S164: =R164/$K$2 -> 151.77081 | T164: =S164-$M$2 -> -12.764573
A165: 7 | B165: =IF(T164>0,B164,D164) -> -0.0078125 | C165: =IF(T164>0,D164,C164) -> 0.015625 | D165: =(B165+C165)/2 -> 0.00390625 | E165: =$C$2*(1+IF(E$3<=$O$2,$D165,$D165-($D165-$I$157)*MIN(E$3-$O$2,$Q$2)/$Q$2)) -> 873.42855 | F165: =E165*(1+IF(F$3<=$O$2,$D165,$D165-($D165-$I$157)*MIN(F$3-$O$2,$Q$2)/$Q$2)) -> 876.84038 | G165: =F165*(1+IF(G$3<=$O$2,$D165,$D165-($D165-$I$157)*MIN(G$3-$O$2,$Q$2)/$Q$2)) -> 880.26554 | H165: =G165*(1+IF(H$3<=$O$2,$D165,$D165-($D165-$I$157)*MIN(H$3-$O$2,$Q$2)/$Q$2)) -> 883.70408 | I165: =H165*(1+IF(I$3<=$O$2,$D165,$D165-($D165-$I$157)*MIN(I$3-$O$2,$Q$2)/$Q$2)) -> 887.15605 | J165: =I165*(1+IF(J$3<=$O$2,$D165,$D165-($D165-$I$157)*MIN(J$3-$O$2,$Q$2)/$Q$2)) -> 896.72403 | K165: =J165*(1+IF(K$3<=$O$2,$D165,$D165-($D165-$I$157)*MIN(K$3-$O$2,$Q$2)/$Q$2)) -> 912.56354 | L165: =K165*(1+IF(L$3<=$O$2,$D165,$D165-($D165-$I$157)*MIN(L$3-$O$2,$Q$2)/$Q$2)) -> 934.96013 | M165: =L165*(1+IF(M$3<=$O$2,$D165,$D165-($D165-$I$157)*MIN(M$3-$O$2,$Q$2)/$Q$2)) -> 964.33774 | N165: =M165*(1+IF(N$3<=$O$2,$D165,$D165-($D165-$I$157)*MIN(N$3-$O$2,$Q$2)/$Q$2)) -> 1001.2719 | O165: =SUMPRODUCT(E165:N165,1/(1+$F$157)^$E$3:$N$3)*$E$2 -> 1435.1691 | P165: =N165*$E$2*(1+$I$157)/($F$157-$I$157)/(1+$F$157)^$N$3 -> 4136.2631 | Q165: =O165+P165 -> 5571.4322 | R165: =Q165-$G$2+$I$2 -> 5738.8322 | S165: =R165/$K$2 -> 163.08134 | T165: =S165-$M$2 -> -1.4540431
A166: 8 | B166: =IF(T165>0,B165,D165) -> 0.00390625 | C166: =IF(T165>0,D165,C165) -> 0.015625 | D166: =(B166+C166)/2 -> 0.009765625 | E166: =$C$2*(1+IF(E$3<=$O$2,$D166,$D166-($D166-$I$157)*MIN(E$3-$O$2,$Q$2)/$Q$2)) -> 878.52639 | F166: =E166*(1+IF(F$3<=$O$2,$D166,$D166-($D166-$I$157)*MIN(F$3-$O$2,$Q$2)/$Q$2)) -> 887.10575 | G166: =F166*(1+IF(G$3<=$O$2,$D166,$D166-($D166-$I$157)*MIN(G$3-$O$2,$Q$2)/$Q$2)) -> 895.76889 | H166: =G166*(1+IF(H$3<=$O$2,$D166,$D166-($D166-$I$157)*MIN(H$3-$O$2,$Q$2)/$Q$2)) -> 904.51663 | I166: =H166*(1+IF(I$3<=$O$2,$D166,$D166-($D166-$I$157)*MIN(I$3-$O$2,$Q$2)/$Q$2)) -> 913.3498 | J166: =I166*(1+IF(J$3<=$O$2,$D166,$D166-($D166-$I$157)*MIN(J$3-$O$2,$Q$2)/$Q$2)) -> 927.48161 | K166: =J166*(1+IF(K$3<=$O$2,$D166,$D166-($D166-$I$157)*MIN(K$3-$O$2,$Q$2)/$Q$2)) -> 947.12509 | L166: =K166*(1+IF(L$3<=$O$2,$D166,$D166-($D166-$I$157)*MIN(L$3-$O$2,$Q$2)/$Q$2)) -> 972.58973 | M166: =L166*(1+IF(M$3<=$O$2,$D166,$D166-($D166-$I$157)*MIN(M$3-$O$2,$Q$2)/$Q$2)) -> 1004.2895 | N166: =M166*(1+IF(N$3<=$O$2,$D166,$D166-($D166-$I$157)*MIN(N$3-$O$2,$Q$2)/$Q$2)) -> 1042.7538 | O166: =SUMPRODUCT(E166:N166,1/(1+$F$157)^$E$3:$N$3)*$E$2 -> 1473.1793 | P166: =N166*$E$2*(1+$I$157)/($F$157-$I$157)/(1+$F$157)^$N$3 -> 4307.6251 | Q166: =O166+P166 -> 5780.8044 | R166: =Q166-$G$2+$I$2 -> 5948.2044 | S166: =R166/$K$2 -> 169.0311 | T166: =S166-$M$2 -> 4.4957193
A167: 9 | B167: =IF(T166>0,B166,D166) -> 0.00390625 | C167: =IF(T166>0,D166,C166) -> 0.009765625 | D167: =(B167+C167)/2 -> 0.0068359375 | E167: =$C$2*(1+IF(E$3<=$O$2,$D167,$D167-($D167-$I$157)*MIN(E$3-$O$2,$Q$2)/$Q$2)) -> 875.97747 | F167: =E167*(1+IF(F$3<=$O$2,$D167,$D167-($D167-$I$157)*MIN(F$3-$O$2,$Q$2)/$Q$2)) -> 881.9656 | G167: =F167*(1+IF(G$3<=$O$2,$D167,$D167-($D167-$I$157)*MIN(G$3-$O$2,$Q$2)/$Q$2)) -> 887.99466 | H167: =G167*(1+IF(H$3<=$O$2,$D167,$D167-($D167-$I$157)*MIN(H$3-$O$2,$Q$2)/$Q$2)) -> 894.06494 | I167: =H167*(1+IF(I$3<=$O$2,$D167,$D167-($D167-$I$157)*MIN(I$3-$O$2,$Q$2)/$Q$2)) -> 900.17671 | J167: =I167*(1+IF(J$3<=$O$2,$D167,$D167-($D167-$I$157)*MIN(J$3-$O$2,$Q$2)/$Q$2)) -> 911.9949 | K167: =J167*(1+IF(K$3<=$O$2,$D167,$D167-($D167-$I$157)*MIN(K$3-$O$2,$Q$2)/$Q$2)) -> 929.70727 | L167: =K167*(1+IF(L$3<=$O$2,$D167,$D167-($D167-$I$157)*MIN(L$3-$O$2,$Q$2)/$Q$2)) -> 953.61411 | M167: =L167*(1+IF(M$3<=$O$2,$D167,$D167-($D167-$I$157)*MIN(M$3-$O$2,$Q$2)/$Q$2)) -> 984.13662 | N167: =M167*(1+IF(N$3<=$O$2,$D167,$D167-($D167-$I$157)*MIN(N$3-$O$2,$Q$2)/$Q$2)) -> 1021.829 | O167: =SUMPRODUCT(E167:N167,1/(1+$F$157)^$E$3:$N$3)*$E$2 -> 1454.0482 | P167: =N167*$E$2*(1+$I$157)/($F$157-$I$157)/(1+$F$157)^$N$3 -> 4221.185 | Q167: =O167+P167 -> 5675.2332 | R167: =Q167-$G$2+$I$2 -> 5842.6332 | S167: =R167/$K$2 -> 166.03107 | T167: =S167-$M$2 -> 1.4956859
A168: 10 | B168: =IF(T167>0,B167,D167) -> 0.00390625 | C168: =IF(T167>0,D167,C167) -> 0.0068359375 | D168: =(B168+C168)/2 -> 0.0053710938 | E168: =$C$2*(1+IF(E$3<=$O$2,$D168,$D168-($D168-$I$157)*MIN(E$3-$O$2,$Q$2)/$Q$2)) -> 874.70301 | F168: =E168*(1+IF(F$3<=$O$2,$D168,$D168-($D168-$I$157)*MIN(F$3-$O$2,$Q$2)/$Q$2)) -> 879.40112 | G168: =F168*(1+IF(G$3<=$O$2,$D168,$D168-($D168-$I$157)*MIN(G$3-$O$2,$Q$2)/$Q$2)) -> 884.12447 | H168: =G168*(1+IF(H$3<=$O$2,$D168,$D168-($D168-$I$157)*MIN(H$3-$O$2,$Q$2)/$Q$2)) -> 888.87319 | I168: =H168*(1+IF(I$3<=$O$2,$D168,$D168-($D168-$I$157)*MIN(I$3-$O$2,$Q$2)/$Q$2)) -> 893.64741 | J168: =I168*(1+IF(J$3<=$O$2,$D168,$D168-($D168-$I$157)*MIN(J$3-$O$2,$Q$2)/$Q$2)) -> 904.33264 | K168: =J168*(1+IF(K$3<=$O$2,$D168,$D168-($D168-$I$157)*MIN(K$3-$O$2,$Q$2)/$Q$2)) -> 921.10137 | L168: =K168*(1+IF(L$3<=$O$2,$D168,$D168-($D168-$I$157)*MIN(L$3-$O$2,$Q$2)/$Q$2)) -> 944.2472 | M168: =L168*(1+IF(M$3<=$O$2,$D168,$D168-($D168-$I$157)*MIN(M$3-$O$2,$Q$2)/$Q$2)) -> 974.19327 | N168: =M168*(1+IF(N$3<=$O$2,$D168,$D168-($D168-$I$157)*MIN(N$3-$O$2,$Q$2)/$Q$2)) -> 1011.5049 | O168: =SUMPRODUCT(E168:N168,1/(1+$F$157)^$E$3:$N$3)*$E$2 -> 1444.5774 | P168: =N168*$E$2*(1+$I$157)/($F$157-$I$157)/(1+$F$157)^$N$3 -> 4178.5357 | Q168: =O168+P168 -> 5623.1131 | R168: =Q168-$G$2+$I$2 -> 5790.5131 | S168: =R168/$K$2 -> 164.54996 | T168: =S168-$M$2 -> 0.01457981
A169: 11 | B169: =IF(T168>0,B168,D168) -> 0.00390625 | C169: =IF(T168>0,D168,C168) -> 0.0053710938 | D169: =(B169+C169)/2 -> 0.0046386719 | E169: =$C$2*(1+IF(E$3<=$O$2,$D169,$D169-($D169-$I$157)*MIN(E$3-$O$2,$Q$2)/$Q$2)) -> 874.06578 | F169: =E169*(1+IF(F$3<=$O$2,$D169,$D169-($D169-$I$157)*MIN(F$3-$O$2,$Q$2)/$Q$2)) -> 878.12029 | G169: =F169*(1+IF(G$3<=$O$2,$D169,$D169-($D169-$I$157)*MIN(G$3-$O$2,$Q$2)/$Q$2)) -> 882.1936 | H169: =G169*(1+IF(H$3<=$O$2,$D169,$D169-($D169-$I$157)*MIN(H$3-$O$2,$Q$2)/$Q$2)) -> 886.28581 | I169: =H169*(1+IF(I$3<=$O$2,$D169,$D169-($D169-$I$157)*MIN(I$3-$O$2,$Q$2)/$Q$2)) -> 890.397 | J169: =I169*(1+IF(J$3<=$O$2,$D169,$D169-($D169-$I$157)*MIN(J$3-$O$2,$Q$2)/$Q$2)) -> 900.52164 | K169: =J169*(1+IF(K$3<=$O$2,$D169,$D169-($D169-$I$157)*MIN(K$3-$O$2,$Q$2)/$Q$2)) -> 916.82397 | L169: =K169*(1+IF(L$3<=$O$2,$D169,$D169-($D169-$I$157)*MIN(L$3-$O$2,$Q$2)/$Q$2)) -> 939.59372 | M169: =L169*(1+IF(M$3<=$O$2,$D169,$D169-($D169-$I$157)*MIN(M$3-$O$2,$Q$2)/$Q$2)) -> 969.25457 | N169: =M169*(1+IF(N$3<=$O$2,$D169,$D169-($D169-$I$157)*MIN(N$3-$O$2,$Q$2)/$Q$2)) -> 1006.377 | O169: =SUMPRODUCT(E169:N169,1/(1+$F$157)^$E$3:$N$3)*$E$2 -> 1439.8655 | P169: =N169*$E$2*(1+$I$157)/($F$157-$I$157)/(1+$F$157)^$N$3 -> 4157.3525 | Q169: =O169+P169 -> 5597.2179 | R169: =Q169-$G$2+$I$2 -> 5764.6179 | S169: =R169/$K$2 -> 163.81409 | T169: =S169-$M$2 -> -0.72128626
A170: 12 | B170: =IF(T169>0,B169,D169) -> 0.0046386719 | C170: =IF(T169>0,D169,C169) -> 0.0053710938 | D170: =(B170+C170)/2 -> 0.0050048828 | E170: =$C$2*(1+IF(E$3<=$O$2,$D170,$D170-($D170-$I$157)*MIN(E$3-$O$2,$Q$2)/$Q$2)) -> 874.3844 | F170: =E170*(1+IF(F$3<=$O$2,$D170,$D170-($D170-$I$157)*MIN(F$3-$O$2,$Q$2)/$Q$2)) -> 878.76059 | G170: =F170*(1+IF(G$3<=$O$2,$D170,$D170-($D170-$I$157)*MIN(G$3-$O$2,$Q$2)/$Q$2)) -> 883.15868 | H170: =G170*(1+IF(H$3<=$O$2,$D170,$D170-($D170-$I$157)*MIN(H$3-$O$2,$Q$2)/$Q$2)) -> 887.57879 | I170: =H170*(1+IF(I$3<=$O$2,$D170,$D170-($D170-$I$157)*MIN(I$3-$O$2,$Q$2)/$Q$2)) -> 892.02102 | J170: =I170*(1+IF(J$3<=$O$2,$D170,$D170-($D170-$I$157)*MIN(J$3-$O$2,$Q$2)/$Q$2)) -> 902.42547 | K170: =J170*(1+IF(K$3<=$O$2,$D170,$D170-($D170-$I$157)*MIN(K$3-$O$2,$Q$2)/$Q$2)) -> 918.96054 | L170: =K170*(1+IF(L$3<=$O$2,$D170,$D170-($D170-$I$157)*MIN(L$3-$O$2,$Q$2)/$Q$2)) -> 941.91797 | M170: =L170*(1+IF(M$3<=$O$2,$D170,$D170-($D170-$I$157)*MIN(M$3-$O$2,$Q$2)/$Q$2)) -> 971.72118 | N170: =M170*(1+IF(N$3<=$O$2,$D170,$D170-($D170-$I$157)*MIN(N$3-$O$2,$Q$2)/$Q$2)) -> 1008.9381 | O170: =SUMPRODUCT(E170:N170,1/(1+$F$157)^$E$3:$N$3)*$E$2 -> 1442.2195 | P170: =N170*$E$2*(1+$I$157)/($F$157-$I$157)/(1+$F$157)^$N$3 -> 4167.9323 | Q170: =O170+P170 -> 5610.1518 | R170: =Q170-$G$2+$I$2 -> 5777.5518 | S170: =R170/$K$2 -> 164.18164 | T170: =S170-$M$2 -> -0.3537426
A171: 13 | B171: =IF(T170>0,B170,D170) -> 0.0050048828 | C171: =IF(T170>0,D170,C170) -> 0.0053710938 | D171: =(B171+C171)/2 -> 0.0051879883 | E171: =$C$2*(1+IF(E$3<=$O$2,$D171,$D171-($D171-$I$157)*MIN(E$3-$O$2,$Q$2)/$Q$2)) -> 874.54371 | F171: =E171*(1+IF(F$3<=$O$2,$D171,$D171-($D171-$I$157)*MIN(F$3-$O$2,$Q$2)/$Q$2)) -> 879.08083 | G171: =F171*(1+IF(G$3<=$O$2,$D171,$D171-($D171-$I$157)*MIN(G$3-$O$2,$Q$2)/$Q$2)) -> 883.64149 | H171: =G171*(1+IF(H$3<=$O$2,$D171,$D171-($D171-$I$157)*MIN(H$3-$O$2,$Q$2)/$Q$2)) -> 888.22581 | I171: =H171*(1+IF(I$3<=$O$2,$D171,$D171-($D171-$I$157)*MIN(I$3-$O$2,$Q$2)/$Q$2)) -> 892.83392 | J171: =I171*(1+IF(J$3<=$O$2,$D171,$D171-($D171-$I$157)*MIN(J$3-$O$2,$Q$2)/$Q$2)) -> 903.37863 | K171: =J171*(1+IF(K$3<=$O$2,$D171,$D171-($D171-$I$157)*MIN(K$3-$O$2,$Q$2)/$Q$2)) -> 920.03042 | L171: =K171*(1+IF(L$3<=$O$2,$D171,$D171-($D171-$I$157)*MIN(L$3-$O$2,$Q$2)/$Q$2)) -> 943.08197 | M171: =L171*(1+IF(M$3<=$O$2,$D171,$D171-($D171-$I$157)*MIN(M$3-$O$2,$Q$2)/$Q$2)) -> 972.95654 | N171: =M171*(1+IF(N$3<=$O$2,$D171,$D171-($D171-$I$157)*MIN(N$3-$O$2,$Q$2)/$Q$2)) -> 1010.2208 | O171: =SUMPRODUCT(E171:N171,1/(1+$F$157)^$E$3:$N$3)*$E$2 -> 1443.3979 | P171: =N171*$E$2*(1+$I$157)/($F$157-$I$157)/(1+$F$157)^$N$3 -> 4173.2311 | Q171: =O171+P171 -> 5616.629 | R171: =Q171-$G$2+$I$2 -> 5784.029 | S171: =R171/$K$2 -> 164.3657 | T171: =S171-$M$2 -> -0.16967883
... A182: 24 | B182: =IF(T181>0,B181,D181) -> 0.0053566098 | C182: =IF(T181>0,D181,C181) -> 0.0053567886 | D182: =(B182+C182)/2 -> 0.0053566992 | E182: =$C$2*(1+IF(E$3<=$O$2,$D182,$D182-($D182-$I$157)*MIN(E$3-$O$2,$Q$2)/$Q$2)) -> 874.69049 | F182: =E182*(1+IF(F$3<=$O$2,$D182,$D182-($D182-$I$157)*MIN(F$3-$O$2,$Q$2)/$Q$2)) -> 879.37594 | G182: =F182*(1+IF(G$3<=$O$2,$D182,$D182-($D182-$I$157)*MIN(G$3-$O$2,$Q$2)/$Q$2)) -> 884.0865 | H182: =G182*(1+IF(H$3<=$O$2,$D182,$D182-($D182-$I$157)*MIN(H$3-$O$2,$Q$2)/$Q$2)) -> 888.82228 | I182: =H182*(1+IF(I$3<=$O$2,$D182,$D182-($D182-$I$157)*MIN(I$3-$O$2,$Q$2)/$Q$2)) -> 893.58343 | J182: =I182*(1+IF(J$3<=$O$2,$D182,$D182-($D182-$I$157)*MIN(J$3-$O$2,$Q$2)/$Q$2)) -> 904.25761 | K182: =J182*(1+IF(K$3<=$O$2,$D182,$D182-($D182-$I$157)*MIN(K$3-$O$2,$Q$2)/$Q$2)) -> 921.01714 | L182: =K182*(1+IF(L$3<=$O$2,$D182,$D182-($D182-$I$157)*MIN(L$3-$O$2,$Q$2)/$Q$2)) -> 944.15556 | M182: =L182*(1+IF(M$3<=$O$2,$D182,$D182-($D182-$I$157)*MIN(M$3-$O$2,$Q$2)/$Q$2)) -> 974.09599 | N182: =M182*(1+IF(N$3<=$O$2,$D182,$D182-($D182-$I$157)*MIN(N$3-$O$2,$Q$2)/$Q$2)) -> 1011.4039 | O182: =SUMPRODUCT(E182:N182,1/(1+$F$157)^$E$3:$N$3)*$E$2 -> 1444.4846 | P182: =N182*$E$2*(1+$I$157)/($F$157-$I$157)/(1+$F$157)^$N$3 -> 4178.1185 | Q182: =O182+P182 -> 5622.6031 | R182: =Q182-$G$2+$I$2 -> 5790.0031 | S182: =R182/$K$2 -> 164.53547 | T182: =S182-$M$2 -> 8.7572344e-05
...

Sheet DCF
B2: MarketAxess (MKTX): discounted cash flow
B3: Panel A runs the model at the solved growth rate, so it should land on the price. Panel B runs it at your view.
B5: A. At the solved (implied) growth rate
B6: Year | C6: 1 | D6: 2 | E6: 3 | F6: 4 | G6: 5 | H6: 6 | I6: 7 | J6: 8 | K6: 9 | L6: 10
B7: Revenue growth | C7: =IF(C$6<=Inputs!$C$46,Solver!$W$7,Solver!$W$7-(Solver!$W$7-Inputs!$C$37)*MIN(C$6-Inputs!$C$46,Inputs!$C$47)/Inputs!$C$47) -> 0.084007684 | D7: =IF(D$6<=Inputs!$C$46,Solver!$W$7,Solver!$W$7-(Solver!$W$7-Inputs!$C$37)*MIN(D$6-Inputs!$C$46,Inputs!$C$47)/Inputs!$C$47) -> 0.084007684 | E7: =IF(E$6<=Inputs!$C$46,Solver!$W$7,Solver!$W$7-(Solver!$W$7-Inputs!$C$37)*MIN(E$6-Inputs!$C$46,Inputs!$C$47)/Inputs!$C$47) -> 0.084007684 | F7: =IF(F$6<=Inputs!$C$46,Solver!$W$7,Solver!$W$7-(Solver!$W$7-Inputs!$C$37)*MIN(F$6-Inputs!$C$46,Inputs!$C$47)/Inputs!$C$47) -> 0.084007684 | G7: =IF(G$6<=Inputs!$C$46,Solver!$W$7,Solver!$W$7-(Solver!$W$7-Inputs!$C$37)*MIN(G$6-Inputs!$C$46,Inputs!$C$47)/Inputs!$C$47) -> 0.084007684 | H7: =IF(H$6<=Inputs!$C$46,Solver!$W$7,Solver!$W$7-(Solver!$W$7-Inputs!$C$37)*MIN(H$6-Inputs!$C$46,Inputs!$C$47)/Inputs!$C$47) -> 0.072866147 | I7: =IF(I$6<=Inputs!$C$46,Solver!$W$7,Solver!$W$7-(Solver!$W$7-Inputs!$C$37)*MIN(I$6-Inputs!$C$46,Inputs!$C$47)/Inputs!$C$47) -> 0.06172461 | J7: =IF(J$6<=Inputs!$C$46,Solver!$W$7,Solver!$W$7-(Solver!$W$7-Inputs!$C$37)*MIN(J$6-Inputs!$C$46,Inputs!$C$47)/Inputs!$C$47) -> 0.050583074 | ... L7: =IF(L$6<=Inputs!$C$46,Solver!$W$7,Solver!$W$7-(Solver!$W$7-Inputs!$C$37)*MIN(L$6-Inputs!$C$46,Inputs!$C$47)/Inputs!$C$47) -> 0.0283
B8: Revenue ($mm) | C8: =Inputs!$C$12*(1+C7) -> 943.11921 | D8: =C8*(1+D7) -> 1022.3485 | E8: =D8*(1+E7) -> 1108.2336 | F8: =E8*(1+F7) -> 1201.3337 | G8: =F8*(1+G7) -> 1302.255 | H8: =G8*(1+H7) -> 1397.1453 | I8: =H8*(1+I7) -> 1483.3835 | J8: =I8*(1+J7) -> 1558.4176 | K8: =J8*(1+K7) -> 1619.884 | L8: =K8*(1+L7) -> 1665.7267
B9: Unlevered free cash flow ($mm) | C9: =C8*Inputs!$C$23 -> 210.62269 | D9: =D8*Inputs!$C$23 -> 228.31662 | E9: =E8*Inputs!$C$23 -> 247.49697 | F9: =F8*Inputs!$C$23 -> 268.28861 | G9: =G8*Inputs!$C$23 -> 290.82692 | H9: =H8*Inputs!$C$23 -> 312.01836 | I9: =I8*Inputs!$C$23 -> 331.27757 | J9: =J8*Inputs!$C$23 -> 348.03461 | ... L9: =L8*Inputs!$C$23 -> 371.99948
B10: Discount factor | C10: =1/(1+WACC!$C$37)^C$6 -> 0.92806772 | D10: =1/(1+WACC!$C$37)^D$6 -> 0.86130968 | E10: =1/(1+WACC!$C$37)^E$6 -> 0.79935371 | F10: =1/(1+WACC!$C$37)^F$6 -> 0.74185437 | G10: =1/(1+WACC!$C$37)^G$6 -> 0.68849109 | H10: =1/(1+WACC!$C$37)^H$6 -> 0.63896636 | I10: =1/(1+WACC!$C$37)^I$6 -> 0.59300405 | J10: =1/(1+WACC!$C$37)^J$6 -> 0.55034791 | ... L10: =1/(1+WACC!$C$37)^L$6 -> 0.47401998
B11: Present value ($mm) | C11: =C9*C10 -> 195.47212 | D11: =D9*D10 -> 196.65131 | E11: =E9*E10 -> 197.83762 | F11: =F9*F10 -> 199.03108 | G11: =G9*G10 -> 200.23174 | H11: =H9*H10 -> 199.36923 | I11: =I9*I10 -> 196.44894 | J11: =J9*J10 -> 191.54012 | ... L11: =L9*L10 -> 176.33519
B13: Sum of present values, years 1 to 10 | C13: =SUM(C11:L11) -> 1937.6908
B14: Terminal value at year 10 | C14: =L9*(1+Inputs!$C$37)/(WACC!$C$37-Inputs!$C$37) -> 7773.7424
B15: Present value of terminal value | C15: =C14*L10 -> 3684.9092
B16: Enterprise value | C16: =C13+C15 -> 5622.6
B17: Less: debt | C17: =-Inputs!$C$27 -> -178.91
B18: Plus: cash | C18: =Inputs!$C$28 -> 346.31
B19: Equity value | C19: =SUM(C16:C18) -> 5790
B20: Shares (mm) | C20: =Inputs!$C$7 -> 35.19
B21: Value per share ($) | C21: =C19/C20 -> 164.53538
B22: Price at the lock ($) | C22: =Inputs!$C$6 -> 164.53538
B23: Value / price - 1 | C23: =C21/C22-1 -> -4.2071902e-12
B24: Terminal value share of enterprise value | C24: =C15/C16 -> 0.6553746
B25: B. At your view of growth (Inputs tab, yellow cell)
B26: Year | C26: 1 | D26: 2 | E26: 3 | F26: 4 | G26: 5 | H26: 6 | I26: 7 | J26: 8 | K26: 9 | L26: 10
B27: Revenue growth | C27: =IF(C$26<=Inputs!$C$46,Inputs!$C$45,Inputs!$C$45-(Inputs!$C$45-Inputs!$C$37)*MIN(C$26-Inputs!$C$46,Inputs!$C$47)/Inputs!$C$47) -> 0.057829158 | D27: =IF(D$26<=Inputs!$C$46,Inputs!$C$45,Inputs!$C$45-(Inputs!$C$45-Inputs!$C$37)*MIN(D$26-Inputs!$C$46,Inputs!$C$47)/Inputs!$C$47) -> 0.057829158 | E27: =IF(E$26<=Inputs!$C$46,Inputs!$C$45,Inputs!$C$45-(Inputs!$C$45-Inputs!$C$37)*MIN(E$26-Inputs!$C$46,Inputs!$C$47)/Inputs!$C$47) -> 0.057829158 | F27: =IF(F$26<=Inputs!$C$46,Inputs!$C$45,Inputs!$C$45-(Inputs!$C$45-Inputs!$C$37)*MIN(F$26-Inputs!$C$46,Inputs!$C$47)/Inputs!$C$47) -> 0.057829158 | G27: =IF(G$26<=Inputs!$C$46,Inputs!$C$45,Inputs!$C$45-(Inputs!$C$45-Inputs!$C$37)*MIN(G$26-Inputs!$C$46,Inputs!$C$47)/Inputs!$C$47) -> 0.057829158 | H27: =IF(H$26<=Inputs!$C$46,Inputs!$C$45,Inputs!$C$45-(Inputs!$C$45-Inputs!$C$37)*MIN(H$26-Inputs!$C$46,Inputs!$C$47)/Inputs!$C$47) -> 0.051923327 | I27: =IF(I$26<=Inputs!$C$46,Inputs!$C$45,Inputs!$C$45-(Inputs!$C$45-Inputs!$C$37)*MIN(I$26-Inputs!$C$46,Inputs!$C$47)/Inputs!$C$47) -> 0.046017495 | J27: =IF(J$26<=Inputs!$C$46,Inputs!$C$45,Inputs!$C$45-(Inputs!$C$45-Inputs!$C$37)*MIN(J$26-Inputs!$C$46,Inputs!$C$47)/Inputs!$C$47) -> 0.040111663 | ... L27: =IF(L$26<=Inputs!$C$46,Inputs!$C$45,Inputs!$C$45-(Inputs!$C$45-Inputs!$C$37)*MIN(L$26-Inputs!$C$46,Inputs!$C$47)/Inputs!$C$47) -> 0.0283
B28: Revenue ($mm) | C28: =Inputs!$C$12*(1+C27) -> 920.3431 | D28: =C28*(1+D27) -> 973.56577 | E28: =D28*(1+E27) -> 1029.8663 | F28: =E28*(1+F27) -> 1089.4226 | G28: =F28*(1+G27) -> 1152.4229 | H28: =G28*(1+H27) -> 1212.2606 | I28: =H28*(1+I27) -> 1268.0458 | J28: =I28*(1+J27) -> 1318.9092 | K28: =J28*(1+K27) -> 1364.0236 | L28: =K28*(1+L27) -> 1402.6255
B29: Unlevered free cash flow ($mm) | C29: =C28*Inputs!$C$23 -> 205.53621 | D29: =D28*Inputs!$C$23 -> 217.42219 | E29: =E28*Inputs!$C$23 -> 229.99553 | F29: =F28*Inputs!$C$23 -> 243.29598 | G29: =G28*Inputs!$C$23 -> 257.36558 | H29: =H28*Inputs!$C$23 -> 270.72886 | I29: =I28*Inputs!$C$23 -> 283.18713 | J29: =J28*Inputs!$C$23 -> 294.54623 | ... L29: =L28*Inputs!$C$23 -> 313.24222
B30: Discount factor | C30: =1/(1+WACC!$C$37)^C$26 -> 0.92806772 | D30: =1/(1+WACC!$C$37)^D$26 -> 0.86130968 | E30: =1/(1+WACC!$C$37)^E$26 -> 0.79935371 | F30: =1/(1+WACC!$C$37)^F$26 -> 0.74185437 | G30: =1/(1+WACC!$C$37)^G$26 -> 0.68849109 | H30: =1/(1+WACC!$C$37)^H$26 -> 0.63896636 | I30: =1/(1+WACC!$C$37)^I$26 -> 0.59300405 | J30: =1/(1+WACC!$C$37)^J$26 -> 0.55034791 | ... L30: =1/(1+WACC!$C$37)^L$26 -> 0.47401998
B31: Present value ($mm) | C31: =C29*C30 -> 190.75152 | D31: =D29*D30 -> 187.26784 | E31: =E29*E30 -> 183.84778 | F31: =F29*F30 -> 180.49019 | G31: =G29*G30 -> 177.19391 | H31: =H29*H30 -> 172.98663 | I31: =I29*I30 -> 167.93111 | J31: =J29*J30 -> 162.1029 | ... L31: =L29*L30 -> 148.48307
B33: Sum of present values, years 1 to 10 | C33: =SUM(C31:L31) -> 1726.6434
B34: Terminal value at year 10 | C34: =L29*(1+Inputs!$C$37)/(WACC!$C$37-Inputs!$C$37) -> 6545.8809
B35: Present value of terminal value | C35: =C34*L30 -> 3102.8784
B36: Enterprise value | C36: =C33+C35 -> 4829.5218
B37: Less: debt | C37: =-Inputs!$C$27 -> -178.91
B38: Plus: cash | C38: =Inputs!$C$28 -> 346.31
B39: Equity value | C39: =SUM(C36:C38) -> 4996.9218
B40: Shares (mm) | C40: =Inputs!$C$7 -> 35.19
B41: Value per share ($) | C41: =C39/C40 -> 141.99835
B42: Price at the lock ($) | C42: =Inputs!$C$6 -> 164.53538
B43: Value / price - 1 | C43: =C41/C42-1 -> -0.13697378
B44: Terminal value share of enterprise value | C44: =C35/C36 -> 0.64248149

Sheet Sensitivity
B2: MarketAxess (MKTX): sensitivity
B3: Table A re-solves implied growth for each pair of inputs (Solver tab, blocks 2 to 26). Table B values the stock at a growth view.
B5: WACC step | C5: 0.005 | D5: Terminal-growth step | F5: 0.005
B6: Growth-view step | C6: 0.02
B8: A. Implied 5-year growth: WACC (rows) by terminal growth (columns)
C9: =Inputs!$C$37+(0-2)*$F$5 -> 0.0183 | D9: =Inputs!$C$37+(1-2)*$F$5 -> 0.0233 | E9: =Inputs!$C$37+(2-2)*$F$5 -> 0.0283 | F9: =Inputs!$C$37+(3-2)*$F$5 -> 0.0333 | G9: =Inputs!$C$37+(4-2)*$F$5 -> 0.0383
B10: =WACC!$C$37+(0-2)*$C$5 -> 0.067507582 | C10: =Solver!$D$74 -> 0.075211436 | D10: =Solver!$D$101 -> 0.060713559 | E10: =Solver!$D$128 -> 0.044556648 | F10: =Solver!$D$155 -> 0.026312262 | G10: =Solver!$D$182 -> 0.0053566992 | I10: Centre cell = the base case. Each step changes one input by the step size above.
B11: =WACC!$C$37+(1-2)*$C$5 -> 0.072507582 | C11: =Solver!$D$209 -> 0.092817277 | D11: =Solver!$D$236 -> 0.079610974 | E11: =Solver!$D$263 -> 0.065048009 | F11: =Solver!$D$290 -> 0.048819214 | G11: =Solver!$D$317 -> 0.030493826
B12: =WACC!$C$37+(2-2)*$C$5 -> 0.077507582 | C12: =Solver!$D$344 -> 0.10940674 | D12: =Solver!$D$371 -> 0.097273141 | E12: =Solver!$D$398 -> 0.084007651 | F12: =Solver!$D$425 -> 0.069379777 | G12: =Solver!$D$452 -> 0.053078741
B13: =WACC!$C$37+(3-2)*$C$5 -> 0.082507582 | C13: =Solver!$D$479 -> 0.12514272 | D13: =Solver!$D$506 -> 0.11391428 | E13: =Solver!$D$533 -> 0.10172614 | F13: =Solver!$D$560 -> 0.088401467 | G13: =Solver!$D$587 -> 0.073708504
B14: =WACC!$C$37+(4-2)*$C$5 -> 0.087507582 | C14: =Solver!$D$614 -> 0.14015165 | D14: =Solver!$D$641 -> 0.12969765 | E14: =Solver!$D$668 -> 0.11841896 | F14: =Solver!$D$695 -> 0.10617647 | G14: =Solver!$D$722 -> 0.0927926
B17: B. Value per share: WACC (rows) by your growth view (columns)
C18: =Inputs!$C$45+(0-2)*$C$6 -> 0.017829158 | D18: =Inputs!$C$45+(1-2)*$C$6 -> 0.037829158 | E18: =Inputs!$C$45+(2-2)*$C$6 -> 0.057829158 | F18: =Inputs!$C$45+(3-2)*$C$6 -> 0.077829158 | G18: =Inputs!$C$45+(4-2)*$C$6 -> 0.097829158
B19: =WACC!$C$37+(0-2)*$C$5 -> 0.067507582 | C19: =(SUMPRODUCT($C28:$L28,1/(1+$B19)^$C$27:$L$27)*Inputs!$C$23+$L28*Inputs!$C$23*(1+Inputs!$C$37)/($B19-Inputs!$C$37)/(1+$B19)^$L$27-Inputs!$C$27+Inputs!$C$28)/Inputs!$C$7 -> 140.62609 | D19: =(SUMPRODUCT($C29:$L29,1/(1+$B19)^$C$27:$L$27)*Inputs!$C$23+$L29*Inputs!$C$23*(1+Inputs!$C$37)/($B19-Inputs!$C$37)/(1+$B19)^$L$27-Inputs!$C$27+Inputs!$C$28)/Inputs!$C$7 -> 158.17661 | E19: =(SUMPRODUCT($C30:$L30,1/(1+$B19)^$C$27:$L$27)*Inputs!$C$23+$L30*Inputs!$C$23*(1+Inputs!$C$37)/($B19-Inputs!$C$37)/(1+$B19)^$L$27-Inputs!$C$27+Inputs!$C$28)/Inputs!$C$7 -> 177.79751 | F19: =(SUMPRODUCT($C31:$L31,1/(1+$B19)^$C$27:$L$27)*Inputs!$C$23+$L31*Inputs!$C$23*(1+Inputs!$C$37)/($B19-Inputs!$C$37)/(1+$B19)^$L$27-Inputs!$C$27+Inputs!$C$28)/Inputs!$C$7 -> 199.70017 | G19: =(SUMPRODUCT($C32:$L32,1/(1+$B19)^$C$27:$L$27)*Inputs!$C$23+$L32*Inputs!$C$23*(1+Inputs!$C$37)/($B19-Inputs!$C$37)/(1+$B19)^$L$27-Inputs!$C$27+Inputs!$C$28)/Inputs!$C$7 -> 224.11387 | I19: Compare with the price at the lock: $164.54.
B20: =WACC!$C$37+(1-2)*$C$5 -> 0.072507582 | C20: =(SUMPRODUCT($C28:$L28,1/(1+$B20)^$C$27:$L$27)*Inputs!$C$23+$L28*Inputs!$C$23*(1+Inputs!$C$37)/($B20-Inputs!$C$37)/(1+$B20)^$L$27-Inputs!$C$27+Inputs!$C$28)/Inputs!$C$7 -> 125.36573 | D20: =(SUMPRODUCT($C29:$L29,1/(1+$B20)^$C$27:$L$27)*Inputs!$C$23+$L29*Inputs!$C$23*(1+Inputs!$C$37)/($B20-Inputs!$C$37)/(1+$B20)^$L$27-Inputs!$C$27+Inputs!$C$28)/Inputs!$C$7 -> 140.71852 | E20: =(SUMPRODUCT($C30:$L30,1/(1+$B20)^$C$27:$L$27)*Inputs!$C$23+$L30*Inputs!$C$23*(1+Inputs!$C$37)/($B20-Inputs!$C$37)/(1+$B20)^$L$27-Inputs!$C$27+Inputs!$C$28)/Inputs!$C$7 -> 157.86878 | F20: =(SUMPRODUCT($C31:$L31,1/(1+$B20)^$C$27:$L$27)*Inputs!$C$23+$L31*Inputs!$C$23*(1+Inputs!$C$37)/($B20-Inputs!$C$37)/(1+$B20)^$L$27-Inputs!$C$27+Inputs!$C$28)/Inputs!$C$7 -> 176.99924 | G20: =(SUMPRODUCT($C32:$L32,1/(1+$B20)^$C$27:$L$27)*Inputs!$C$23+$L32*Inputs!$C$23*(1+Inputs!$C$37)/($B20-Inputs!$C$37)/(1+$B20)^$L$27-Inputs!$C$27+Inputs!$C$28)/Inputs!$C$7 -> 198.30808
B21: =WACC!$C$37+(2-2)*$C$5 -> 0.077507582 | C21: =(SUMPRODUCT($C28:$L28,1/(1+$B21)^$C$27:$L$27)*Inputs!$C$23+$L28*Inputs!$C$23*(1+Inputs!$C$37)/($B21-Inputs!$C$37)/(1+$B21)^$L$27-Inputs!$C$27+Inputs!$C$28)/Inputs!$C$7 -> 113.20414 | D21: =(SUMPRODUCT($C29:$L29,1/(1+$B21)^$C$27:$L$27)*Inputs!$C$23+$L29*Inputs!$C$23*(1+Inputs!$C$37)/($B21-Inputs!$C$37)/(1+$B21)^$L$27-Inputs!$C$27+Inputs!$C$28)/Inputs!$C$7 -> 126.81073 | E21: =(SUMPRODUCT($C30:$L30,1/(1+$B21)^$C$27:$L$27)*Inputs!$C$23+$L30*Inputs!$C$23*(1+Inputs!$C$37)/($B21-Inputs!$C$37)/(1+$B21)^$L$27-Inputs!$C$27+Inputs!$C$28)/Inputs!$C$7 -> 141.99835 | F21: =(SUMPRODUCT($C31:$L31,1/(1+$B21)^$C$27:$L$27)*Inputs!$C$23+$L31*Inputs!$C$23*(1+Inputs!$C$37)/($B21-Inputs!$C$37)/(1+$B21)^$L$27-Inputs!$C$27+Inputs!$C$28)/Inputs!$C$7 -> 158.92703 | G21: =(SUMPRODUCT($C32:$L32,1/(1+$B21)^$C$27:$L$27)*Inputs!$C$23+$L32*Inputs!$C$23*(1+Inputs!$C$37)/($B21-Inputs!$C$37)/(1+$B21)^$L$27-Inputs!$C$27+Inputs!$C$28)/Inputs!$C$7 -> 177.77032
B22: =WACC!$C$37+(3-2)*$C$5 -> 0.082507582 | C22: =(SUMPRODUCT($C28:$L28,1/(1+$B22)^$C$27:$L$27)*Inputs!$C$23+$L28*Inputs!$C$23*(1+Inputs!$C$37)/($B22-Inputs!$C$37)/(1+$B22)^$L$27-Inputs!$C$27+Inputs!$C$28)/Inputs!$C$7 -> 103.28393 | D22: =(SUMPRODUCT($C29:$L29,1/(1+$B22)^$C$27:$L$27)*Inputs!$C$23+$L29*Inputs!$C$23*(1+Inputs!$C$37)/($B22-Inputs!$C$37)/(1+$B22)^$L$27-Inputs!$C$27+Inputs!$C$28)/Inputs!$C$7 -> 115.47075 | E22: =(SUMPRODUCT($C30:$L30,1/(1+$B22)^$C$27:$L$27)*Inputs!$C$23+$L30*Inputs!$C$23*(1+Inputs!$C$37)/($B22-Inputs!$C$37)/(1+$B22)^$L$27-Inputs!$C$27+Inputs!$C$28)/Inputs!$C$7 -> 129.06297 | F22: =(SUMPRODUCT($C31:$L31,1/(1+$B22)^$C$27:$L$27)*Inputs!$C$23+$L31*Inputs!$C$23*(1+Inputs!$C$37)/($B22-Inputs!$C$37)/(1+$B22)^$L$27-Inputs!$C$27+Inputs!$C$28)/Inputs!$C$7 -> 144.20225 | G22: =(SUMPRODUCT($C32:$L32,1/(1+$B22)^$C$27:$L$27)*Inputs!$C$23+$L32*Inputs!$C$23*(1+Inputs!$C$37)/($B22-Inputs!$C$37)/(1+$B22)^$L$27-Inputs!$C$27+Inputs!$C$28)/Inputs!$C$7 -> 161.04215
B23: =WACC!$C$37+(4-2)*$C$5 -> 0.087507582 | C23: =(SUMPRODUCT($C28:$L28,1/(1+$B23)^$C$27:$L$27)*Inputs!$C$23+$L28*Inputs!$C$23*(1+Inputs!$C$37)/($B23-Inputs!$C$37)/(1+$B23)^$L$27-Inputs!$C$27+Inputs!$C$28)/Inputs!$C$7 -> 95.037306 | D23: =(SUMPRODUCT($C29:$L29,1/(1+$B23)^$C$27:$L$27)*Inputs!$C$23+$L29*Inputs!$C$23*(1+Inputs!$C$37)/($B23-Inputs!$C$37)/(1+$B23)^$L$27-Inputs!$C$27+Inputs!$C$28)/Inputs!$C$7 -> 106.04797 | E23: =(SUMPRODUCT($C30:$L30,1/(1+$B23)^$C$27:$L$27)*Inputs!$C$23+$L30*Inputs!$C$23*(1+Inputs!$C$37)/($B23-Inputs!$C$37)/(1+$B23)^$L$27-Inputs!$C$27+Inputs!$C$28)/Inputs!$C$7 -> 118.31885 | F23: =(SUMPRODUCT($C31:$L31,1/(1+$B23)^$C$27:$L$27)*Inputs!$C$23+$L31*Inputs!$C$23*(1+Inputs!$C$37)/($B23-Inputs!$C$37)/(1+$B23)^$L$27-Inputs!$C$27+Inputs!$C$28)/Inputs!$C$7 -> 131.97642 | G23: =(SUMPRODUCT($C32:$L32,1/(1+$B23)^$C$27:$L$27)*Inputs!$C$23+$L32*Inputs!$C$23*(1+Inputs!$C$37)/($B23-Inputs!$C$37)/(1+$B23)^$L$27-Inputs!$C$27+Inputs!$C$28)/Inputs!$C$7 -> 147.15778
B26: Helper: revenue paths for each growth view (years 1 to 10)
C27: 1 | D27: 2 | E27: 3 | F27: 4 | G27: 5 | H27: 6 | I27: 7 | J27: 8 | K27: 9 | L27: 10
B28: =C$18 -> 0.017829158 | C28: =Inputs!$C$12*(1+IF(C$27<=Inputs!$C$46,$B28,$B28-($B28-Inputs!$C$37)*MIN(C$27-Inputs!$C$46,Inputs!$C$47)/Inputs!$C$47)) -> 885.5419 | D28: =C28*(1+IF(D$27<=Inputs!$C$46,$B28,$B28-($B28-Inputs!$C$37)*MIN(D$27-Inputs!$C$46,Inputs!$C$47)/Inputs!$C$47)) -> 901.33037 | E28: =D28*(1+IF(E$27<=Inputs!$C$46,$B28,$B28-($B28-Inputs!$C$37)*MIN(E$27-Inputs!$C$46,Inputs!$C$47)/Inputs!$C$47)) -> 917.40033 | F28: =E28*(1+IF(F$27<=Inputs!$C$46,$B28,$B28-($B28-Inputs!$C$37)*MIN(F$27-Inputs!$C$46,Inputs!$C$47)/Inputs!$C$47)) -> 933.75681 | G28: =F28*(1+IF(G$27<=Inputs!$C$46,$B28,$B28-($B28-Inputs!$C$37)*MIN(G$27-Inputs!$C$46,Inputs!$C$47)/Inputs!$C$47)) -> 950.40491 | H28: =G28*(1+IF(H$27<=Inputs!$C$46,$B28,$B28-($B28-Inputs!$C$37)*MIN(H$27-Inputs!$C$46,Inputs!$C$47)/Inputs!$C$47)) -> 969.34013 | I28: =H28*(1+IF(I$27<=Inputs!$C$46,$B28,$B28-($B28-Inputs!$C$37)*MIN(I$27-Inputs!$C$46,Inputs!$C$47)/Inputs!$C$47)) -> 990.68257 | J28: =I28*(1+IF(J$27<=Inputs!$C$46,$B28,$B28-($B28-Inputs!$C$37)*MIN(J$27-Inputs!$C$46,Inputs!$C$47)/Inputs!$C$47)) -> 1014.5696 | K28: =J28*(1+IF(K$27<=Inputs!$C$46,$B28,$B28-($B28-Inputs!$C$37)*MIN(K$27-Inputs!$C$46,Inputs!$C$47)/Inputs!$C$47)) -> 1041.1572 | L28: =K28*(1+IF(L$27<=Inputs!$C$46,$B28,$B28-($B28-Inputs!$C$37)*MIN(L$27-Inputs!$C$46,Inputs!$C$47)/Inputs!$C$47)) -> 1070.622
B29: =D$18 -> 0.037829158 | C29: =Inputs!$C$12*(1+IF(C$27<=Inputs!$C$46,$B29,$B29-($B29-Inputs!$C$37)*MIN(C$27-Inputs!$C$46,Inputs!$C$47)/Inputs!$C$47)) -> 902.9425 | D29: =C29*(1+IF(D$27<=Inputs!$C$46,$B29,$B29-($B29-Inputs!$C$37)*MIN(D$27-Inputs!$C$46,Inputs!$C$47)/Inputs!$C$47)) -> 937.10006 | E29: =D29*(1+IF(E$27<=Inputs!$C$46,$B29,$B29-($B29-Inputs!$C$37)*MIN(E$27-Inputs!$C$46,Inputs!$C$47)/Inputs!$C$47)) -> 972.54976 | F29: =E29*(1+IF(F$27<=Inputs!$C$46,$B29,$B29-($B29-Inputs!$C$37)*MIN(F$27-Inputs!$C$46,Inputs!$C$47)/Inputs!$C$47)) -> 1009.3405 | G29: =F29*(1+IF(G$27<=Inputs!$C$46,$B29,$B29-($B29-Inputs!$C$37)*MIN(G$27-Inputs!$C$46,Inputs!$C$47)/Inputs!$C$47)) -> 1047.523 | H29: =G29*(1+IF(H$27<=Inputs!$C$46,$B29,$B29-($B29-Inputs!$C$37)*MIN(H$27-Inputs!$C$46,Inputs!$C$47)/Inputs!$C$47)) -> 1085.1535 | I29: =H29*(1+IF(I$27<=Inputs!$C$46,$B29,$B29-($B29-Inputs!$C$37)*MIN(I$27-Inputs!$C$46,Inputs!$C$47)/Inputs!$C$47)) -> 1122.0677 | J29: =I29*(1+IF(J$27<=Inputs!$C$46,$B29,$B29-($B29-Inputs!$C$37)*MIN(J$27-Inputs!$C$46,Inputs!$C$47)/Inputs!$C$47)) -> 1158.0992 | K29: =J29*(1+IF(K$27<=Inputs!$C$46,$B29,$B29-($B29-Inputs!$C$37)*MIN(K$27-Inputs!$C$46,Inputs!$C$47)/Inputs!$C$47)) -> 1193.0805 | L29: =K29*(1+IF(L$27<=Inputs!$C$46,$B29,$B29-($B29-Inputs!$C$37)*MIN(L$27-Inputs!$C$46,Inputs!$C$47)/Inputs!$C$47)) -> 1226.8447
B30: =E$18 -> 0.057829158 | C30: =Inputs!$C$12*(1+IF(C$27<=Inputs!$C$46,$B30,$B30-($B30-Inputs!$C$37)*MIN(C$27-Inputs!$C$46,Inputs!$C$47)/Inputs!$C$47)) -> 920.3431 | D30: =C30*(1+IF(D$27<=Inputs!$C$46,$B30,$B30-($B30-Inputs!$C$37)*MIN(D$27-Inputs!$C$46,Inputs!$C$47)/Inputs!$C$47)) -> 973.56577 | E30: =D30*(1+IF(E$27<=Inputs!$C$46,$B30,$B30-($B30-Inputs!$C$37)*MIN(E$27-Inputs!$C$46,Inputs!$C$47)/Inputs!$C$47)) -> 1029.8663 | F30: =E30*(1+IF(F$27<=Inputs!$C$46,$B30,$B30-($B30-Inputs!$C$37)*MIN(F$27-Inputs!$C$46,Inputs!$C$47)/Inputs!$C$47)) -> 1089.4226 | G30: =F30*(1+IF(G$27<=Inputs!$C$46,$B30,$B30-($B30-Inputs!$C$37)*MIN(G$27-Inputs!$C$46,Inputs!$C$47)/Inputs!$C$47)) -> 1152.4229 | H30: =G30*(1+IF(H$27<=Inputs!$C$46,$B30,$B30-($B30-Inputs!$C$37)*MIN(H$27-Inputs!$C$46,Inputs!$C$47)/Inputs!$C$47)) -> 1212.2606 | I30: =H30*(1+IF(I$27<=Inputs!$C$46,$B30,$B30-($B30-Inputs!$C$37)*MIN(I$27-Inputs!$C$46,Inputs!$C$47)/Inputs!$C$47)) -> 1268.0458 | J30: =I30*(1+IF(J$27<=Inputs!$C$46,$B30,$B30-($B30-Inputs!$C$37)*MIN(J$27-Inputs!$C$46,Inputs!$C$47)/Inputs!$C$47)) -> 1318.9092 | K30: =J30*(1+IF(K$27<=Inputs!$C$46,$B30,$B30-($B30-Inputs!$C$37)*MIN(K$27-Inputs!$C$46,Inputs!$C$47)/Inputs!$C$47)) -> 1364.0236 | L30: =K30*(1+IF(L$27<=Inputs!$C$46,$B30,$B30-($B30-Inputs!$C$37)*MIN(L$27-Inputs!$C$46,Inputs!$C$47)/Inputs!$C$47)) -> 1402.6255
B31: =F$18 -> 0.077829158 | C31: =Inputs!$C$12*(1+IF(C$27<=Inputs!$C$46,$B31,$B31-($B31-Inputs!$C$37)*MIN(C$27-Inputs!$C$46,Inputs!$C$47)/Inputs!$C$47)) -> 937.7437 | D31: =C31*(1+IF(D$27<=Inputs!$C$46,$B31,$B31-($B31-Inputs!$C$37)*MIN(D$27-Inputs!$C$46,Inputs!$C$47)/Inputs!$C$47)) -> 1010.7275 | E31: =D31*(1+IF(E$27<=Inputs!$C$46,$B31,$B31-($B31-Inputs!$C$37)*MIN(E$27-Inputs!$C$46,Inputs!$C$47)/Inputs!$C$47)) -> 1089.3916 | F31: =E31*(1+IF(F$27<=Inputs!$C$46,$B31,$B31-($B31-Inputs!$C$37)*MIN(F$27-Inputs!$C$46,Inputs!$C$47)/Inputs!$C$47)) -> 1174.178 | G31: =F31*(1+IF(G$27<=Inputs!$C$46,$B31,$B31-($B31-Inputs!$C$37)*MIN(G$27-Inputs!$C$46,Inputs!$C$47)/Inputs!$C$47)) -> 1265.5633 | H31: =G31*(1+IF(H$27<=Inputs!$C$46,$B31,$B31-($B31-Inputs!$C$37)*MIN(H$27-Inputs!$C$46,Inputs!$C$47)/Inputs!$C$47)) -> 1351.5246 | I31: =H31*(1+IF(I$27<=Inputs!$C$46,$B31,$B31-($B31-Inputs!$C$37)*MIN(I$27-Inputs!$C$46,Inputs!$C$47)/Inputs!$C$47)) -> 1429.9366 | J31: =I31*(1+IF(J$27<=Inputs!$C$46,$B31,$B31-($B31-Inputs!$C$37)*MIN(J$27-Inputs!$C$46,Inputs!$C$47)/Inputs!$C$47)) -> 1498.7333 | K31: =J31*(1+IF(K$27<=Inputs!$C$46,$B31,$B31-($B31-Inputs!$C$37)*MIN(K$27-Inputs!$C$46,Inputs!$C$47)/Inputs!$C$47)) -> 1555.9936 | L31: =K31*(1+IF(L$27<=Inputs!$C$46,$B31,$B31-($B31-Inputs!$C$37)*MIN(L$27-Inputs!$C$46,Inputs!$C$47)/Inputs!$C$47)) -> 1600.0282
B32: =G$18 -> 0.097829158 | C32: =Inputs!$C$12*(1+IF(C$27<=Inputs!$C$46,$B32,$B32-($B32-Inputs!$C$37)*MIN(C$27-Inputs!$C$46,Inputs!$C$47)/Inputs!$C$47)) -> 955.1443 | D32: =C32*(1+IF(D$27<=Inputs!$C$46,$B32,$B32-($B32-Inputs!$C$37)*MIN(D$27-Inputs!$C$46,Inputs!$C$47)/Inputs!$C$47)) -> 1048.5853 | E32: =D32*(1+IF(E$27<=Inputs!$C$46,$B32,$B32-($B32-Inputs!$C$37)*MIN(E$27-Inputs!$C$46,Inputs!$C$47)/Inputs!$C$47)) -> 1151.1675 | F32: =E32*(1+IF(F$27<=Inputs!$C$46,$B32,$B32-($B32-Inputs!$C$37)*MIN(F$27-Inputs!$C$46,Inputs!$C$47)/Inputs!$C$47)) -> 1263.7852 | G32: =F32*(1+IF(G$27<=Inputs!$C$46,$B32,$B32-($B32-Inputs!$C$37)*MIN(G$27-Inputs!$C$46,Inputs!$C$47)/Inputs!$C$47)) -> 1387.4203 | H32: =G32*(1+IF(H$27<=Inputs!$C$46,$B32,$B32-($B32-Inputs!$C$37)*MIN(H$27-Inputs!$C$46,Inputs!$C$47)/Inputs!$C$47)) -> 1503.8572 | I32: =H32*(1+IF(I$27<=Inputs!$C$46,$B32,$B32-($B32-Inputs!$C$37)*MIN(I$27-Inputs!$C$46,Inputs!$C$47)/Inputs!$C$47)) -> 1609.1535 | J32: =I32*(1+IF(J$27<=Inputs!$C$46,$B32,$B32-($B32-Inputs!$C$37)*MIN(J$27-Inputs!$C$46,Inputs!$C$47)/Inputs!$C$47)) -> 1699.4458 | K32: =J32*(1+IF(K$27<=Inputs!$C$46,$B32,$B32-($B32-Inputs!$C$37)*MIN(K$27-Inputs!$C$46,Inputs!$C$47)/Inputs!$C$47)) -> 1771.1723 | L32: =K32*(1+IF(L$27<=Inputs!$C$46,$B32,$B32-($B32-Inputs!$C$37)*MIN(L$27-Inputs!$C$46,Inputs!$C$47)/Inputs!$C$47)) -> 1821.2965

Sheet Check
B2: MarketAxess (MKTX): check against the Python pipeline
B3: Python values are typed in (blue) from the pipeline that runs the site. Each row passes if the two agree within the tolerance.
B5: Item | C5: This workbook | D5: Python pipeline | E5: Difference | F5: Result
B6: Unlevered free-cash-flow margin | C6: =Inputs!$C$23 -> 0.22332563 | D6: 0.22332563 | E6: =C6-D6 -> 2.4494558e-09 | F6: =IF(ABS(E6)<=0.00005,"Pass","Check") -> Pass
B7: Group median unlevered beta | C7: =WACC!$C$14 -> 0.60913153 | D7: 0.60913153 | E7: =C7-D7 -> -3.7891912e-13 | F7: =IF(ABS(E7)<=0.0005,"Pass","Check") -> Pass
B8: WACC | C8: =WACC!$C$37 -> 0.077507582 | D8: 0.07750758 | E8: =C8-D8 -> 2.0986394e-09 | F8: =IF(ABS(E8)<=0.00005,"Pass","Check") -> Pass
B9: Terminal growth | C9: =Inputs!$C$37 -> 0.0283 | D9: 0.0283 | E9: =C9-D9 -> 0 | F9: =IF(ABS(E9)<=0.00005,"Pass","Check") -> Pass
B10: Anchor | C10: =Inputs!$C$43 -> 0.057829158 | D10: 0.05782916 | E10: =C10-D10 -> -1.504494e-09 | F10: =IF(ABS(E10)<=0.00005,"Pass","Check") -> Pass
B11: Implied growth, base case | C11: =Solver!$W$7 -> 0.084007684 | D11: 0.0840077 | E11: =C11-D11 -> -1.6173742e-08 | F11: =IF(ABS(E11)<=0.00005,"Pass","Check") -> Pass
B12: Implied growth, WACC one point higher | C12: =Sensitivity!$E$14 -> 0.11841896 | D12: 0.11841896 | E12: =C12-D12 -> 1.763382e-09 | F12: =IF(ABS(E12)<=0.0002,"Pass","Check") -> Pass
B13: Value per share at the anchor ($) | C13: =DCF!$C$41 -> 141.99835 | D13: 141.99835 | E13: =C13-D13 -> -2.5467557e-09 | F13: =IF(ABS(E13)<=0.02,"Pass","Check") -> Pass
B14: Panel A value minus price ($) | C14: =DCF!$C$21-DCF!$C$22 -> -6.9223915e-10 | D14: 0 | E14: =C14-D14 -> -6.9223915e-10 | F14: =IF(ABS(E14)<=0.01,"Pass","Check") -> Pass | G14: Panel B on the DCF tab uses your view; with the yellow cell at the anchor it matches the pipeline.
B16: Overall | C16: =IF(COUNTIF(F6:F14,"Pass")=9,"All checks pass","Review") -> All checks pass
