Workbook

Sheet Cover
B2: Priced In: TMX Group (X)
B3: Reverse DCF, model v1.0. Inputs as of the Oct 13, 2026 close; model locked Oct 14, 2026 (commit 0735af0).
B4: Exchanges | Canada | reports in CAD
B6: The question
B7: What revenue growth over the next five years does today's price imply, and is that more or less than the company has delivered and analysts expect?
B9: Answer
B10: Price at the lock (C$) | C10: =Inputs!$C$6 -> 54.504521
B11: Implied 5-year revenue growth | C11: =Solver!$W$7 -> 0.013955097
B12: Anchor (history and analysts) | C12: =Inputs!$C$43 -> 0.1503
B13: Gap (implied - anchor) | C13: =C11-C12 -> -0.1363449
B14: Verdict | C14: =IF(C13>=Inputs!$C$44,"Expectations too high",IF(C13<=-Inputs!$C$44,"Expectations too low","About right")) -> Expectations too low
B15: WACC | C15: =WACC!$C$37 -> 0.063509306
B16: Terminal growth | C16: =Inputs!$C$37 -> 0.025
B17: Unlevered free-cash-flow margin | C17: =Inputs!$C$23 -> 0.35987135
B18: Your view of growth (Inputs, yellow) | C18: =Inputs!$C$45 -> 0.1503
B19: Value per share at your view (C$) | C19: =DCF!$C$41 -> 129.38595
B20: Upside or downside at your view | C20: =DCF!$C$43 -> 1.3738572
B22: Fit flag: History not comparable
B23: VettaFi was consolidated in 2024 and the Cboe Canada purchase is pending.
B25: How to use this file
B26: 1. Change any blue cell on Inputs, History or WACC; everything recalculates, including the solver.
B27: 2. The Solver tab finds implied growth by bisection with formulas, so you never need Goal Seek. 40 steps narrow a 150-point range to well under 0.0001%.
B28: 3. Type your own growth view in the yellow cell on Inputs; DCF panel B and this page show what the stock is worth if you're right.
B29: 4. Check confirms this workbook matches the Python pipeline that runs the site.
B31: Colour key
B32: Typed input with a source | C32: 1234
B33: Formula | C33: =C32*2 -> 2468
B34: Link to another tab | C34: =Inputs!$C$12 -> 1850
B35: Your view (edit this one) | C35: =Inputs!$C$45 -> 0.1503
B37: Live site
B38: https://claude.ai/artifact/DS3n4CgaKxaSLzkXDsBKuK
B40: Built by Rohan Jayapalan. Not investment advice.

Sheet Inputs
B2: TMX Group (X): inputs
B3: Blue cells are typed inputs with a source. Black cells are formulas. Change a blue cell and every tab recalculates.
B5: Market and price
B6: Price per share at the lock (C$) | C6: 54.504521 | E6: Market cap divided by shares from Stock Analysis at the Oct 13, 2026 close. The TSX close that day was C$53.22; the lock used C$54.50.
B7: Diluted shares outstanding (mm) | C7: 275.39 | E7: Stock Analysis statistics page, Oct 13, 2026.
B8: Market value of equity (C$mm) | C8: =C6*C7 -> 15010 | E8: Price x shares.
B10: Trailing 12 months
B11: Revenue, reported (C$mm) | C11: 1850 | E11: Stock Analysis income statement, trailing 12 months.
B12: Revenue used in the model (C$mm) | C12: =C11 -> 1850 | E12: Same as reported.
B13: Free cash flow, reported (cash from operations - capex) (C$mm) | C13: 659 | E13: Stock Analysis cash flow statement, trailing 12 months.
B14: Free cash flow before adjustments (C$mm) | C14: =C13 -> 659 | E14: Same as reported.
B15: Less: adjustments (C$mm) | C15: 0 | E15: None for this company.
B16: Free cash flow used (C$mm) | C16: =C14-C15 -> 659
B17: Operating income (C$mm) | C17: 893.8 | E17: Stock Analysis, trailing 12 months.
B18: Pretax income (C$mm) | C18: 884.6 | E18: Stock Analysis, trailing 12 months.
B19: Interest proxy: operating income - pretax, floored at zero (C$mm) | C19: =MAX(0,C17-C18) -> 9.2 | E19: Net interest and other non-operating costs. Adding it back (after tax) turns levered FCF into unlevered FCF.
B20: Tax rate | C20: 0.265 | E20: Statutory blend: 25% US (21% federal plus state), 26.5% Canada (federal plus Ontario).
B21: After-tax interest added back (C$mm) | C21: =C19*(1-C20) -> 6.762
B22: Unlevered free cash flow (C$mm) | C22: =C16+C21 -> 665.762
B23: Unlevered free-cash-flow margin | C23: =C22/C12 -> 0.35987135 | E23: Held flat for all 10 years in the model.
B24: EBITDA (C$mm) | C24: 1070 | E24: Stock Analysis, trailing 12 months.
B26: Balance sheet
B27: Total debt (C$mm) | C27: 2070 | E27: Stock Analysis balance sheet, latest quarter.
B28: Cash and equivalents (C$mm) | C28: 517.3 | E28: Stock Analysis balance sheet, latest quarter.
B29: Net debt (C$mm) | C29: =C27-C28 -> 1552.7
B31: Rates
B32: 10-year Government of Canada yield | C32: 0.0387 | E32: Bank of Canada Valet, Oct 13, 2026.
B33: Inflation target | C33: 0.02 | E33: Bank of Canada 2% target.
B34: Inflation used | C34: =C33 -> 0.02
B35: Risk-free rate used | C35: =C32 -> 0.0387
B36: Real growth added to inflation | C36: 0.005 | E36: Half a point of long-run real growth.
B37: Terminal growth | C37: =C34+C36 -> 0.025
B38: Equity risk premium | C38: 0.0423 | E38: Damodaran implied equity risk premium, start of 2026.
B40: Growth anchor and verdict
B41: Past revenue growth (CAGR) | C41: n/a | E41: Not used: past growth isn't comparable (see Cover).
B42: Analysts' revenue growth forecast | C42: 0.1503 | E42: Analysts' 3-year revenue CAGR forecast (stockanalysis)
B43: Anchor (average of the two) | C43: =AVERAGE(C41:C42) -> 0.1503 | E43: AVERAGE skips the n/a text when history isn't used.
B44: Verdict band (+/-) | C44: 0.03 | E44: Set before any backtest and never changed.
B45: Your view of 5-year revenue growth | C45: 0.1503 | E45: Type your own view. It starts at the anchor. DCF panel B and the Cover show what the stock is worth at your view.
B46: Years at the solved growth rate | C46: 5 | E46: Model v1.0: 5 years at the growth rate, then a straight-line fade.
B47: Years of fade to terminal growth | C47: 5 | E47: Years 1 to 10 are on the Solver and DCF tabs; years past 10 grow at the terminal rate.

Sheet History
B2: TMX Group (X): revenue history
B3: Revenue from Stock Analysis income statements; the window is chosen so acquisitions and disposals don't count as growth.
B5: Fiscal year | C5: FY2021 | D5: FY2022 | E5: FY2023 | F5: FY2024 | G5: FY2025 | H5: TTM Jun-26
B6: Revenue (C$mm) | C6: 980.7 | D6: 1115 | E6: 1194 | F6: 1460 | G6: 1717 | H6: 1852
B7: Growth on the prior year | D7: =D6/C6-1 -> 0.136943 | E7: =E6/D6-1 -> 0.070852018 | F7: =F6/E6-1 -> 0.22278057 | G7: =G6/F6-1 -> 0.1760274
B8: Source note: CAD; VettaFi consolidated 2024
B10: History window
B11: Not used for this company: VettaFi was consolidated in 2024 and the Cboe Canada purchase is pending.

Sheet WACC
B2: TMX Group (X): cost of capital
B3: Bottom-up beta: the median unlevered beta of the company's group, relevered for this company's debt.
B5: Peer | C5: Raw beta | D5: Debt ($mm) | E5: Equity ($mm) | F5: Tax rate | G5: Unlevered beta
B6: Intercontinental Exchange (ICE) | C6: 0.93718463 | D6: 20530 | E6: 87470 | F6: 0.25 | G6: =C6/(1+(1-F6)*D6/E6) -> 0.79690417 | H6: Raw betas: 60 monthly returns to Sep 2026 against the S&P 500 (S&P/TSX for TMX); Cboe uses Stock Analysis's 5-year beta. Debt and equity from Stock Analysis, Oct 13, 2026.
B7: CME Group (CME) | C7: 0.23986632 | D7: 3870 | E7: 99970 | F7: 0.25 | G7: =C7/(1+(1-F7)*D7/E7) -> 0.2330986
B8: Nasdaq (NDAQ) | C8: 0.99189493 | D8: 9320 | E8: 52250 | F8: 0.25 | G8: =C8/(1+(1-F8)*D8/E8) -> 0.87485669
B9: Cboe Global Markets (CBOE) | C9: 0.41 | D9: 1580 | E9: 30520 | F9: 0.25 | G9: =C9/(1+(1-F9)*D9/E9) -> 0.39467592
B10: TMX Group (X) | C10: 0.071228248 | D10: 2070 | E10: 15010 | F10: 0.265 | G10: =C10/(1+(1-F10)*D10/E10) -> 0.064672851
B11: Tradeweb (TW) | C11: 0.61179985 | D11: 150.34 | E11: 25740 | F11: 0.25 | G11: =C11/(1+(1-F11)*D11/E11) -> 0.60913153
B12: MarketAxess (MKTX) | C12: 0.79839643 | D12: 178.91 | E12: 5790 | F12: 0.25 | G12: =C12/(1+(1-F12)*D12/E12) -> 0.78031278
B14: Group median unlevered beta | C14: =MEDIAN(G6:G12) -> 0.60913153
B15: Debt (C$mm) | C15: =Inputs!$C$27 -> 2070
B16: Market value of equity (C$mm) | C16: =Inputs!$C$8 -> 15010
B17: Tax rate | C17: =Inputs!$C$20 -> 0.265
B18: Relevered beta | C18: =WACC!$C$14*(1+(1-WACC!$C$17)*WACC!$C$15/WACC!$C$16) -> 0.67087458 | H18: Hamada: unlevered beta x (1 + (1 - tax) x debt / equity).
B19: Risk-free rate | C19: =Inputs!$C$35 -> 0.0387
B20: Equity risk premium | C20: =Inputs!$C$38 -> 0.0423
B21: Cost of equity | C21: =WACC!$C$19+WACC!$C$18*WACC!$C$20 -> 0.067077995 | H21: CAPM: risk-free + beta x premium.
B23: Debt-to-EBITDA spread table
B24: Debt / EBITDA below | C24: Spread
B25: 1 | C25: 0.01 | H25: Synthetic spread over the risk-free rate by leverage, a simplified version of Damodaran's ratings table; the last row covers anything at 4x or above.
B26: 2 | C26: 0.0125
B27: 3 | C27: 0.016
B28: 4 | C28: 0.02
B29: 99 | C29: 0.0275
B31: Debt / EBITDA | C31: =Inputs!$C$27/Inputs!$C$24 -> 1.9345794
B32: Credit spread | C32: =INDEX(C25:C29,COUNTIF(B25:B29,"<="&WACC!$C$31)+1) -> 0.0125 | H32: First row whose limit is above this company's leverage.
B33: Pre-tax cost of debt | C33: =WACC!$C$19+WACC!$C$32 -> 0.0512
B34: After-tax cost of debt | C34: =WACC!$C$33*(1-WACC!$C$17) -> 0.037632
B35: Weight of debt | C35: =WACC!$C$15/(WACC!$C$15+WACC!$C$16) -> 0.12119438 | H35: Market-value weights.
B36: Weight of equity | C36: =1-WACC!$C$35 -> 0.87880562
B37: WACC | C37: =WACC!$C$36*WACC!$C$21+WACC!$C$35*WACC!$C$34 -> 0.063509306

Sheet Solver
A1: Solver: bisection for the growth rate that makes the model equal the price (replaces Goal Seek)
B2: Revenue | C2: =Inputs!$C$12 -> 1850 | D2: Margin | E2: =Inputs!$C$23 -> 0.35987135 | F2: Debt | G2: =Inputs!$C$27 -> 2070 | H2: Cash | I2: =Inputs!$C$28 -> 517.3 | J2: Shares | K2: =Inputs!$C$7 -> 275.39 | L2: Price | M2: =Inputs!$C$6 -> 54.504521 | N2: Years | O2: =Inputs!$C$46 -> 5 | P2: Fade | Q2: =Inputs!$C$47 -> 5
D3: Year | E3: 1 | F3: 2 | G3: 3 | H3: 4 | I3: 5 | J3: 6 | K3: 7 | L3: 8 | M3: 9 | N3: 10
A4: Each row tries the midpoint of the current range. If the value per share is above the price, the answer is lower, so the top of the range moves down; otherwise the bottom moves up.
A6: Base case: model WACC and terminal growth (40 steps) | E6: WACC | F6: =WACC!$C$37 -> 0.063509306 | G6: Terminal growth | I6: =Inputs!$C$37 -> 0.025 | W6: Implied growth
A7: Step | B7: Low | C7: High | D7: Mid | E7: Rev Y1 | F7: Rev Y2 | G7: Rev Y3 | H7: Rev Y4 | I7: Rev Y5 | J7: Rev Y6 | K7: Rev Y7 | L7: Rev Y8 | M7: Rev Y9 | N7: Rev Y10 | O7: PV of FCF | P7: PV of TV | Q7: EV | R7: Equity | S7: Per share | T7: Value - price | W7: =$D$47 -> 0.013955097
A8: 1 | B8: -0.5 | C8: 1 | D8: =(B8+C8)/2 -> 0.25 | E8: =$C$2*(1+IF(E$3<=$O$2,$D8,$D8-($D8-$I$6)*MIN(E$3-$O$2,$Q$2)/$Q$2)) -> 2312.5 | F8: =E8*(1+IF(F$3<=$O$2,$D8,$D8-($D8-$I$6)*MIN(F$3-$O$2,$Q$2)/$Q$2)) -> 2890.625 | G8: =F8*(1+IF(G$3<=$O$2,$D8,$D8-($D8-$I$6)*MIN(G$3-$O$2,$Q$2)/$Q$2)) -> 3613.2812 | H8: =G8*(1+IF(H$3<=$O$2,$D8,$D8-($D8-$I$6)*MIN(H$3-$O$2,$Q$2)/$Q$2)) -> 4516.6016 | I8: =H8*(1+IF(I$3<=$O$2,$D8,$D8-($D8-$I$6)*MIN(I$3-$O$2,$Q$2)/$Q$2)) -> 5645.752 | J8: =I8*(1+IF(J$3<=$O$2,$D8,$D8-($D8-$I$6)*MIN(J$3-$O$2,$Q$2)/$Q$2)) -> 6803.1311 | K8: =J8*(1+IF(K$3<=$O$2,$D8,$D8-($D8-$I$6)*MIN(K$3-$O$2,$Q$2)/$Q$2)) -> 7891.6321 | L8: =K8*(1+IF(L$3<=$O$2,$D8,$D8-($D8-$I$6)*MIN(L$3-$O$2,$Q$2)/$Q$2)) -> 8799.1698 | M8: =L8*(1+IF(M$3<=$O$2,$D8,$D8-($D8-$I$6)*MIN(M$3-$O$2,$Q$2)/$Q$2)) -> 9415.1117 | N8: =M8*(1+IF(N$3<=$O$2,$D8,$D8-($D8-$I$6)*MIN(N$3-$O$2,$Q$2)/$Q$2)) -> 9650.4894 | O8: =SUMPRODUCT(E8:N8,1/(1+$F$6)^$E$3:$N$3)*$E$2 -> 14842.543 | P8: =N8*$E$2*(1+$I$6)/($F$6-$I$6)/(1+$F$6)^$N$3 -> 49939.231 | Q8: =O8+P8 -> 64781.774 | R8: =Q8-$G$2+$I$2 -> 63229.074 | S8: =R8/$K$2 -> 229.59829 | T8: =S8-$M$2 -> 175.09377 | W8: =IF(OR(ABS(W7+0.5)<0.000001,ABS(W7-1)<0.000001),"Out of range","Solved") -> Solved
A9: 2 | B9: =IF(T8>0,B8,D8) -> -0.5 | C9: =IF(T8>0,D8,C8) -> 0.25 | D9: =(B9+C9)/2 -> -0.125 | E9: =$C$2*(1+IF(E$3<=$O$2,$D9,$D9-($D9-$I$6)*MIN(E$3-$O$2,$Q$2)/$Q$2)) -> 1618.75 | F9: =E9*(1+IF(F$3<=$O$2,$D9,$D9-($D9-$I$6)*MIN(F$3-$O$2,$Q$2)/$Q$2)) -> 1416.4062 | G9: =F9*(1+IF(G$3<=$O$2,$D9,$D9-($D9-$I$6)*MIN(G$3-$O$2,$Q$2)/$Q$2)) -> 1239.3555 | H9: =G9*(1+IF(H$3<=$O$2,$D9,$D9-($D9-$I$6)*MIN(H$3-$O$2,$Q$2)/$Q$2)) -> 1084.436 | I9: =H9*(1+IF(I$3<=$O$2,$D9,$D9-($D9-$I$6)*MIN(I$3-$O$2,$Q$2)/$Q$2)) -> 948.88153 | J9: =I9*(1+IF(J$3<=$O$2,$D9,$D9-($D9-$I$6)*MIN(J$3-$O$2,$Q$2)/$Q$2)) -> 858.73779 | K9: =J9*(1+IF(K$3<=$O$2,$D9,$D9-($D9-$I$6)*MIN(K$3-$O$2,$Q$2)/$Q$2)) -> 802.91983 | L9: =K9*(1+IF(L$3<=$O$2,$D9,$D9-($D9-$I$6)*MIN(L$3-$O$2,$Q$2)/$Q$2)) -> 774.81764 | M9: =L9*(1+IF(M$3<=$O$2,$D9,$D9-($D9-$I$6)*MIN(M$3-$O$2,$Q$2)/$Q$2)) -> 770.94355 | N9: =M9*(1+IF(N$3<=$O$2,$D9,$D9-($D9-$I$6)*MIN(N$3-$O$2,$Q$2)/$Q$2)) -> 790.21714 | O9: =SUMPRODUCT(E9:N9,1/(1+$F$6)^$E$3:$N$3)*$E$2 -> 2810.0149 | P9: =N9*$E$2*(1+$I$6)/($F$6-$I$6)/(1+$F$6)^$N$3 -> 4089.2056 | Q9: =O9+P9 -> 6899.2206 | R9: =Q9-$G$2+$I$2 -> 5346.5206 | S9: =R9/$K$2 -> 19.41436 | T9: =S9-$M$2 -> -35.090161
A10: 3 | B10: =IF(T9>0,B9,D9) -> -0.125 | C10: =IF(T9>0,D9,C9) -> 0.25 | D10: =(B10+C10)/2 -> 0.0625 | E10: =$C$2*(1+IF(E$3<=$O$2,$D10,$D10-($D10-$I$6)*MIN(E$3-$O$2,$Q$2)/$Q$2)) -> 1965.625 | F10: =E10*(1+IF(F$3<=$O$2,$D10,$D10-($D10-$I$6)*MIN(F$3-$O$2,$Q$2)/$Q$2)) -> 2088.4766 | G10: =F10*(1+IF(G$3<=$O$2,$D10,$D10-($D10-$I$6)*MIN(G$3-$O$2,$Q$2)/$Q$2)) -> 2219.0063 | H10: =G10*(1+IF(H$3<=$O$2,$D10,$D10-($D10-$I$6)*MIN(H$3-$O$2,$Q$2)/$Q$2)) -> 2357.6942 | I10: =H10*(1+IF(I$3<=$O$2,$D10,$D10-($D10-$I$6)*MIN(I$3-$O$2,$Q$2)/$Q$2)) -> 2505.0501 | J10: =I10*(1+IF(J$3<=$O$2,$D10,$D10-($D10-$I$6)*MIN(J$3-$O$2,$Q$2)/$Q$2)) -> 2642.8279 | K10: =J10*(1+IF(K$3<=$O$2,$D10,$D10-($D10-$I$6)*MIN(K$3-$O$2,$Q$2)/$Q$2)) -> 2768.3622 | L10: =K10*(1+IF(L$3<=$O$2,$D10,$D10-($D10-$I$6)*MIN(L$3-$O$2,$Q$2)/$Q$2)) -> 2879.0967 | M10: =L10*(1+IF(M$3<=$O$2,$D10,$D10-($D10-$I$6)*MIN(M$3-$O$2,$Q$2)/$Q$2)) -> 2972.6673 | N10: =M10*(1+IF(N$3<=$O$2,$D10,$D10-($D10-$I$6)*MIN(N$3-$O$2,$Q$2)/$Q$2)) -> 3046.984 | O10: =SUMPRODUCT(E10:N10,1/(1+$F$6)^$E$3:$N$3)*$E$2 -> 6464.1928 | P10: =N10*$E$2*(1+$I$6)/($F$6-$I$6)/(1+$F$6)^$N$3 -> 15767.494 | Q10: =O10+P10 -> 22231.687 | R10: =Q10-$G$2+$I$2 -> 20678.987 | S10: =R10/$K$2 -> 75.089826 | T10: =S10-$M$2 -> 20.585305
A11: 4 | B11: =IF(T10>0,B10,D10) -> -0.125 | C11: =IF(T10>0,D10,C10) -> 0.0625 | D11: =(B11+C11)/2 -> -0.03125 | E11: =$C$2*(1+IF(E$3<=$O$2,$D11,$D11-($D11-$I$6)*MIN(E$3-$O$2,$Q$2)/$Q$2)) -> 1792.1875 | F11: =E11*(1+IF(F$3<=$O$2,$D11,$D11-($D11-$I$6)*MIN(F$3-$O$2,$Q$2)/$Q$2)) -> 1736.1816 | G11: =F11*(1+IF(G$3<=$O$2,$D11,$D11-($D11-$I$6)*MIN(G$3-$O$2,$Q$2)/$Q$2)) -> 1681.926 | H11: =G11*(1+IF(H$3<=$O$2,$D11,$D11-($D11-$I$6)*MIN(H$3-$O$2,$Q$2)/$Q$2)) -> 1629.3658 | I11: =H11*(1+IF(I$3<=$O$2,$D11,$D11-($D11-$I$6)*MIN(I$3-$O$2,$Q$2)/$Q$2)) -> 1578.4481 | J11: =I11*(1+IF(J$3<=$O$2,$D11,$D11-($D11-$I$6)*MIN(J$3-$O$2,$Q$2)/$Q$2)) -> 1546.8791 | K11: =J11*(1+IF(K$3<=$O$2,$D11,$D11-($D11-$I$6)*MIN(K$3-$O$2,$Q$2)/$Q$2)) -> 1533.3439 | L11: =K11*(1+IF(L$3<=$O$2,$D11,$D11-($D11-$I$6)*MIN(L$3-$O$2,$Q$2)/$Q$2)) -> 1537.1773 | M11: =L11*(1+IF(M$3<=$O$2,$D11,$D11-($D11-$I$6)*MIN(M$3-$O$2,$Q$2)/$Q$2)) -> 1558.3135 | N11: =M11*(1+IF(N$3<=$O$2,$D11,$D11-($D11-$I$6)*MIN(N$3-$O$2,$Q$2)/$Q$2)) -> 1597.2713 | O11: =SUMPRODUCT(E11:N11,1/(1+$F$6)^$E$3:$N$3)*$E$2 -> 4251.9845 | P11: =N11*$E$2*(1+$I$6)/($F$6-$I$6)/(1+$F$6)^$N$3 -> 8265.5395 | Q11: =O11+P11 -> 12517.524 | R11: =Q11-$G$2+$I$2 -> 10964.824 | S11: =R11/$K$2 -> 39.815622 | T11: =S11-$M$2 -> -14.688899
A12: 5 | B12: =IF(T11>0,B11,D11) -> -0.03125 | C12: =IF(T11>0,D11,C11) -> 0.0625 | D12: =(B12+C12)/2 -> 0.015625 | E12: =$C$2*(1+IF(E$3<=$O$2,$D12,$D12-($D12-$I$6)*MIN(E$3-$O$2,$Q$2)/$Q$2)) -> 1878.9062 | F12: =E12*(1+IF(F$3<=$O$2,$D12,$D12-($D12-$I$6)*MIN(F$3-$O$2,$Q$2)/$Q$2)) -> 1908.2642 | G12: =F12*(1+IF(G$3<=$O$2,$D12,$D12-($D12-$I$6)*MIN(G$3-$O$2,$Q$2)/$Q$2)) -> 1938.0808 | H12: =G12*(1+IF(H$3<=$O$2,$D12,$D12-($D12-$I$6)*MIN(H$3-$O$2,$Q$2)/$Q$2)) -> 1968.3633 | I12: =H12*(1+IF(I$3<=$O$2,$D12,$D12-($D12-$I$6)*MIN(I$3-$O$2,$Q$2)/$Q$2)) -> 1999.119 | J12: =I12*(1+IF(J$3<=$O$2,$D12,$D12-($D12-$I$6)*MIN(J$3-$O$2,$Q$2)/$Q$2)) -> 2034.1036 | K12: =J12*(1+IF(K$3<=$O$2,$D12,$D12-($D12-$I$6)*MIN(K$3-$O$2,$Q$2)/$Q$2)) -> 2073.5143 | L12: =K12*(1+IF(L$3<=$O$2,$D12,$D12-($D12-$I$6)*MIN(L$3-$O$2,$Q$2)/$Q$2)) -> 2117.5765 | M12: =L12*(1+IF(M$3<=$O$2,$D12,$D12-($D12-$I$6)*MIN(M$3-$O$2,$Q$2)/$Q$2)) -> 2166.5455 | N12: =M12*(1+IF(N$3<=$O$2,$D12,$D12-($D12-$I$6)*MIN(N$3-$O$2,$Q$2)/$Q$2)) -> 2220.7091 | O12: =SUMPRODUCT(E12:N12,1/(1+$F$6)^$E$3:$N$3)*$E$2 -> 5241.4487 | P12: =N12*$E$2*(1+$I$6)/($F$6-$I$6)/(1+$F$6)^$N$3 -> 11491.697 | Q12: =O12+P12 -> 16733.146 | R12: =Q12-$G$2+$I$2 -> 15180.446 | S12: =R12/$K$2 -> 55.123447 | T12: =S12-$M$2 -> 0.61892602
A13: 6 | B13: =IF(T12>0,B12,D12) -> -0.03125 | C13: =IF(T12>0,D12,C12) -> 0.015625 | D13: =(B13+C13)/2 -> -0.0078125 | E13: =$C$2*(1+IF(E$3<=$O$2,$D13,$D13-($D13-$I$6)*MIN(E$3-$O$2,$Q$2)/$Q$2)) -> 1835.5469 | F13: =E13*(1+IF(F$3<=$O$2,$D13,$D13-($D13-$I$6)*MIN(F$3-$O$2,$Q$2)/$Q$2)) -> 1821.2067 | G13: =F13*(1+IF(G$3<=$O$2,$D13,$D13-($D13-$I$6)*MIN(G$3-$O$2,$Q$2)/$Q$2)) -> 1806.9785 | H13: =G13*(1+IF(H$3<=$O$2,$D13,$D13-($D13-$I$6)*MIN(H$3-$O$2,$Q$2)/$Q$2)) -> 1792.8615 | I13: =H13*(1+IF(I$3<=$O$2,$D13,$D13-($D13-$I$6)*MIN(I$3-$O$2,$Q$2)/$Q$2)) -> 1778.8547 | J13: =I13*(1+IF(J$3<=$O$2,$D13,$D13-($D13-$I$6)*MIN(J$3-$O$2,$Q$2)/$Q$2)) -> 1776.6312 | K13: =J13*(1+IF(K$3<=$O$2,$D13,$D13-($D13-$I$6)*MIN(K$3-$O$2,$Q$2)/$Q$2)) -> 1786.0695 | L13: =K13*(1+IF(L$3<=$O$2,$D13,$D13-($D13-$I$6)*MIN(L$3-$O$2,$Q$2)/$Q$2)) -> 1807.2791 | M13: =L13*(1+IF(M$3<=$O$2,$D13,$D13-($D13-$I$6)*MIN(M$3-$O$2,$Q$2)/$Q$2)) -> 1840.6008 | N13: =M13*(1+IF(N$3<=$O$2,$D13,$D13-($D13-$I$6)*MIN(N$3-$O$2,$Q$2)/$Q$2)) -> 1886.6158 | O13: =SUMPRODUCT(E13:N13,1/(1+$F$6)^$E$3:$N$3)*$E$2 -> 4720.3836 | P13: =N13*$E$2*(1+$I$6)/($F$6-$I$6)/(1+$F$6)^$N$3 -> 9762.8357 | Q13: =O13+P13 -> 14483.219 | R13: =Q13-$G$2+$I$2 -> 12930.519 | S13: =R13/$K$2 -> 46.953482 | T13: =S13-$M$2 -> -7.551039
A14: 7 | B14: =IF(T13>0,B13,D13) -> -0.0078125 | C14: =IF(T13>0,D13,C13) -> 0.015625 | D14: =(B14+C14)/2 -> 0.00390625 | E14: =$C$2*(1+IF(E$3<=$O$2,$D14,$D14-($D14-$I$6)*MIN(E$3-$O$2,$Q$2)/$Q$2)) -> 1857.2266 | F14: =E14*(1+IF(F$3<=$O$2,$D14,$D14-($D14-$I$6)*MIN(F$3-$O$2,$Q$2)/$Q$2)) -> 1864.4814 | G14: =F14*(1+IF(G$3<=$O$2,$D14,$D14-($D14-$I$6)*MIN(G$3-$O$2,$Q$2)/$Q$2)) -> 1871.7645 | H14: =G14*(1+IF(H$3<=$O$2,$D14,$D14-($D14-$I$6)*MIN(H$3-$O$2,$Q$2)/$Q$2)) -> 1879.0761 | I14: =H14*(1+IF(I$3<=$O$2,$D14,$D14-($D14-$I$6)*MIN(I$3-$O$2,$Q$2)/$Q$2)) -> 1886.4162 | J14: =I14*(1+IF(J$3<=$O$2,$D14,$D14-($D14-$I$6)*MIN(J$3-$O$2,$Q$2)/$Q$2)) -> 1901.7433 | K14: =J14*(1+IF(K$3<=$O$2,$D14,$D14-($D14-$I$6)*MIN(K$3-$O$2,$Q$2)/$Q$2)) -> 1925.218 | L14: =K14*(1+IF(L$3<=$O$2,$D14,$D14-($D14-$I$6)*MIN(L$3-$O$2,$Q$2)/$Q$2)) -> 1957.1044 | M14: =L14*(1+IF(M$3<=$O$2,$D14,$D14-($D14-$I$6)*MIN(M$3-$O$2,$Q$2)/$Q$2)) -> 1997.7755 | N14: =M14*(1+IF(N$3<=$O$2,$D14,$D14-($D14-$I$6)*MIN(N$3-$O$2,$Q$2)/$Q$2)) -> 2047.7199 | O14: =SUMPRODUCT(E14:N14,1/(1+$F$6)^$E$3:$N$3)*$E$2 -> 4973.9986 | P14: =N14*$E$2*(1+$I$6)/($F$6-$I$6)/(1+$F$6)^$N$3 -> 10596.515 | Q14: =O14+P14 -> 15570.513 | R14: =Q14-$G$2+$I$2 -> 14017.813 | S14: =R14/$K$2 -> 50.901679 | T14: =S14-$M$2 -> -3.6028415
A15: 8 | B15: =IF(T14>0,B14,D14) -> 0.00390625 | C15: =IF(T14>0,D14,C14) -> 0.015625 | D15: =(B15+C15)/2 -> 0.009765625 | E15: =$C$2*(1+IF(E$3<=$O$2,$D15,$D15-($D15-$I$6)*MIN(E$3-$O$2,$Q$2)/$Q$2)) -> 1868.0664 | F15: =E15*(1+IF(F$3<=$O$2,$D15,$D15-($D15-$I$6)*MIN(F$3-$O$2,$Q$2)/$Q$2)) -> 1886.3092 | G15: =F15*(1+IF(G$3<=$O$2,$D15,$D15-($D15-$I$6)*MIN(G$3-$O$2,$Q$2)/$Q$2)) -> 1904.7302 | H15: =G15*(1+IF(H$3<=$O$2,$D15,$D15-($D15-$I$6)*MIN(H$3-$O$2,$Q$2)/$Q$2)) -> 1923.3311 | I15: =H15*(1+IF(I$3<=$O$2,$D15,$D15-($D15-$I$6)*MIN(I$3-$O$2,$Q$2)/$Q$2)) -> 1942.1136 | J15: =I15*(1+IF(J$3<=$O$2,$D15,$D15-($D15-$I$6)*MIN(J$3-$O$2,$Q$2)/$Q$2)) -> 1966.997 | K15: =J15*(1+IF(K$3<=$O$2,$D15,$D15-($D15-$I$6)*MIN(K$3-$O$2,$Q$2)/$Q$2)) -> 1998.1923 | L15: =K15*(1+IF(L$3<=$O$2,$D15,$D15-($D15-$I$6)*MIN(L$3-$O$2,$Q$2)/$Q$2)) -> 2035.9706 | M15: =L15*(1+IF(M$3<=$O$2,$D15,$D15-($D15-$I$6)*MIN(M$3-$O$2,$Q$2)/$Q$2)) -> 2080.6666 | N15: =M15*(1+IF(N$3<=$O$2,$D15,$D15-($D15-$I$6)*MIN(N$3-$O$2,$Q$2)/$Q$2)) -> 2132.6832 | O15: =SUMPRODUCT(E15:N15,1/(1+$F$6)^$E$3:$N$3)*$E$2 -> 5105.9509 | P15: =N15*$E$2*(1+$I$6)/($F$6-$I$6)/(1+$F$6)^$N$3 -> 11036.182 | Q15: =O15+P15 -> 16142.133 | R15: =Q15-$G$2+$I$2 -> 14589.433 | S15: =R15/$K$2 -> 52.977352 | T15: =S15-$M$2 -> -1.5271686
A16: 9 | B16: =IF(T15>0,B15,D15) -> 0.009765625 | C16: =IF(T15>0,D15,C15) -> 0.015625 | D16: =(B16+C16)/2 -> 0.012695312 | E16: =$C$2*(1+IF(E$3<=$O$2,$D16,$D16-($D16-$I$6)*MIN(E$3-$O$2,$Q$2)/$Q$2)) -> 1873.4863 | F16: =E16*(1+IF(F$3<=$O$2,$D16,$D16-($D16-$I$6)*MIN(F$3-$O$2,$Q$2)/$Q$2)) -> 1897.2708 | G16: =F16*(1+IF(G$3<=$O$2,$D16,$D16-($D16-$I$6)*MIN(G$3-$O$2,$Q$2)/$Q$2)) -> 1921.3573 | H16: =G16*(1+IF(H$3<=$O$2,$D16,$D16-($D16-$I$6)*MIN(H$3-$O$2,$Q$2)/$Q$2)) -> 1945.7495 | I16: =H16*(1+IF(I$3<=$O$2,$D16,$D16-($D16-$I$6)*MIN(I$3-$O$2,$Q$2)/$Q$2)) -> 1970.4514 | J16: =I16*(1+IF(J$3<=$O$2,$D16,$D16-($D16-$I$6)*MIN(J$3-$O$2,$Q$2)/$Q$2)) -> 2000.3161 | K16: =J16*(1+IF(K$3<=$O$2,$D16,$D16-($D16-$I$6)*MIN(K$3-$O$2,$Q$2)/$Q$2)) -> 2035.556 | L16: =K16*(1+IF(L$3<=$O$2,$D16,$D16-($D16-$I$6)*MIN(L$3-$O$2,$Q$2)/$Q$2)) -> 2076.4261 | M16: =L16*(1+IF(M$3<=$O$2,$D16,$D16-($D16-$I$6)*MIN(M$3-$O$2,$Q$2)/$Q$2)) -> 2123.2268 | N16: =M16*(1+IF(N$3<=$O$2,$D16,$D16-($D16-$I$6)*MIN(N$3-$O$2,$Q$2)/$Q$2)) -> 2176.3075 | O16: =SUMPRODUCT(E16:N16,1/(1+$F$6)^$E$3:$N$3)*$E$2 -> 5173.2511 | P16: =N16*$E$2*(1+$I$6)/($F$6-$I$6)/(1+$F$6)^$N$3 -> 11261.929 | Q16: =O16+P16 -> 16435.18 | R16: =Q16-$G$2+$I$2 -> 14882.48 | S16: =R16/$K$2 -> 54.041467 | T16: =S16-$M$2 -> -0.46305361
A17: 10 | B17: =IF(T16>0,B16,D16) -> 0.012695312 | C17: =IF(T16>0,D16,C16) -> 0.015625 | D17: =(B17+C17)/2 -> 0.014160156 | E17: =$C$2*(1+IF(E$3<=$O$2,$D17,$D17-($D17-$I$6)*MIN(E$3-$O$2,$Q$2)/$Q$2)) -> 1876.1963 | F17: =E17*(1+IF(F$3<=$O$2,$D17,$D17-($D17-$I$6)*MIN(F$3-$O$2,$Q$2)/$Q$2)) -> 1902.7635 | G17: =F17*(1+IF(G$3<=$O$2,$D17,$D17-($D17-$I$6)*MIN(G$3-$O$2,$Q$2)/$Q$2)) -> 1929.707 | H17: =G17*(1+IF(H$3<=$O$2,$D17,$D17-($D17-$I$6)*MIN(H$3-$O$2,$Q$2)/$Q$2)) -> 1957.0319 | I17: =H17*(1+IF(I$3<=$O$2,$D17,$D17-($D17-$I$6)*MIN(I$3-$O$2,$Q$2)/$Q$2)) -> 1984.7438 | J17: =I17*(1+IF(J$3<=$O$2,$D17,$D17-($D17-$I$6)*MIN(J$3-$O$2,$Q$2)/$Q$2)) -> 2017.1509 | K17: =J17*(1+IF(K$3<=$O$2,$D17,$D17-($D17-$I$6)*MIN(K$3-$O$2,$Q$2)/$Q$2)) -> 2054.4603 | L17: =K17*(1+IF(L$3<=$O$2,$D17,$D17-($D17-$I$6)*MIN(L$3-$O$2,$Q$2)/$Q$2)) -> 2096.9138 | M17: =L17*(1+IF(M$3<=$O$2,$D17,$D17-($D17-$I$6)*MIN(M$3-$O$2,$Q$2)/$Q$2)) -> 2144.7906 | N17: =M17*(1+IF(N$3<=$O$2,$D17,$D17-($D17-$I$6)*MIN(N$3-$O$2,$Q$2)/$Q$2)) -> 2198.4104 | O17: =SUMPRODUCT(E17:N17,1/(1+$F$6)^$E$3:$N$3)*$E$2 -> 5207.237 | P17: =N17*$E$2*(1+$I$6)/($F$6-$I$6)/(1+$F$6)^$N$3 -> 11376.306 | Q17: =O17+P17 -> 16583.543 | R17: =Q17-$G$2+$I$2 -> 15030.843 | S17: =R17/$K$2 -> 54.580208 | T17: =S17-$M$2 -> 0.075686751
A18: 11 | B18: =IF(T17>0,B17,D17) -> 0.012695312 | C18: =IF(T17>0,D17,C17) -> 0.014160156 | D18: =(B18+C18)/2 -> 0.013427734 | E18: =$C$2*(1+IF(E$3<=$O$2,$D18,$D18-($D18-$I$6)*MIN(E$3-$O$2,$Q$2)/$Q$2)) -> 1874.8413 | F18: =E18*(1+IF(F$3<=$O$2,$D18,$D18-($D18-$I$6)*MIN(F$3-$O$2,$Q$2)/$Q$2)) -> 1900.0162 | G18: =F18*(1+IF(G$3<=$O$2,$D18,$D18-($D18-$I$6)*MIN(G$3-$O$2,$Q$2)/$Q$2)) -> 1925.5291 | H18: =G18*(1+IF(H$3<=$O$2,$D18,$D18-($D18-$I$6)*MIN(H$3-$O$2,$Q$2)/$Q$2)) -> 1951.3846 | I18: =H18*(1+IF(I$3<=$O$2,$D18,$D18-($D18-$I$6)*MIN(I$3-$O$2,$Q$2)/$Q$2)) -> 1977.5873 | J18: =I18*(1+IF(J$3<=$O$2,$D18,$D18-($D18-$I$6)*MIN(J$3-$O$2,$Q$2)/$Q$2)) -> 2008.7188 | K18: =J18*(1+IF(K$3<=$O$2,$D18,$D18-($D18-$I$6)*MIN(K$3-$O$2,$Q$2)/$Q$2)) -> 2044.9895 | L18: =K18*(1+IF(L$3<=$O$2,$D18,$D18-($D18-$I$6)*MIN(L$3-$O$2,$Q$2)/$Q$2)) -> 2086.6482 | M18: =L18*(1+IF(M$3<=$O$2,$D18,$D18-($D18-$I$6)*MIN(M$3-$O$2,$Q$2)/$Q$2)) -> 2133.985 | N18: =M18*(1+IF(N$3<=$O$2,$D18,$D18-($D18-$I$6)*MIN(N$3-$O$2,$Q$2)/$Q$2)) -> 2187.3346 | O18: =SUMPRODUCT(E18:N18,1/(1+$F$6)^$E$3:$N$3)*$E$2 -> 5190.2159 | P18: =N18*$E$2*(1+$I$6)/($F$6-$I$6)/(1+$F$6)^$N$3 -> 11318.991 | Q18: =O18+P18 -> 16509.207 | R18: =Q18-$G$2+$I$2 -> 14956.507 | S18: =R18/$K$2 -> 54.310277 | T18: =S18-$M$2 -> -0.19424374
A19: 12 | B19: =IF(T18>0,B18,D18) -> 0.013427734 | C19: =IF(T18>0,D18,C18) -> 0.014160156 | D19: =(B19+C19)/2 -> 0.013793945 | E19: =$C$2*(1+IF(E$3<=$O$2,$D19,$D19-($D19-$I$6)*MIN(E$3-$O$2,$Q$2)/$Q$2)) -> 1875.5188 | F19: =E19*(1+IF(F$3<=$O$2,$D19,$D19-($D19-$I$6)*MIN(F$3-$O$2,$Q$2)/$Q$2)) -> 1901.3896 | G19: =F19*(1+IF(G$3<=$O$2,$D19,$D19-($D19-$I$6)*MIN(G$3-$O$2,$Q$2)/$Q$2)) -> 1927.6173 | H19: =G19*(1+IF(H$3<=$O$2,$D19,$D19-($D19-$I$6)*MIN(H$3-$O$2,$Q$2)/$Q$2)) -> 1954.2067 | I19: =H19*(1+IF(I$3<=$O$2,$D19,$D19-($D19-$I$6)*MIN(I$3-$O$2,$Q$2)/$Q$2)) -> 1981.1629 | J19: =I19*(1+IF(J$3<=$O$2,$D19,$D19-($D19-$I$6)*MIN(J$3-$O$2,$Q$2)/$Q$2)) -> 2012.9312 | K19: =J19*(1+IF(K$3<=$O$2,$D19,$D19-($D19-$I$6)*MIN(K$3-$O$2,$Q$2)/$Q$2)) -> 2049.7203 | L19: =K19*(1+IF(L$3<=$O$2,$D19,$D19-($D19-$I$6)*MIN(L$3-$O$2,$Q$2)/$Q$2)) -> 2091.7756 | M19: =L19*(1+IF(M$3<=$O$2,$D19,$D19-($D19-$I$6)*MIN(M$3-$O$2,$Q$2)/$Q$2)) -> 2139.3818 | N19: =M19*(1+IF(N$3<=$O$2,$D19,$D19-($D19-$I$6)*MIN(N$3-$O$2,$Q$2)/$Q$2)) -> 2192.8664 | O19: =SUMPRODUCT(E19:N19,1/(1+$F$6)^$E$3:$N$3)*$E$2 -> 5198.7194 | P19: =N19*$E$2*(1+$I$6)/($F$6-$I$6)/(1+$F$6)^$N$3 -> 11347.617 | Q19: =O19+P19 -> 16546.337 | R19: =Q19-$G$2+$I$2 -> 14993.637 | S19: =R19/$K$2 -> 54.445102 | T19: =S19-$M$2 -> -0.059418826
A20: 13 | B20: =IF(T19>0,B19,D19) -> 0.013793945 | C20: =IF(T19>0,D19,C19) -> 0.014160156 | D20: =(B20+C20)/2 -> 0.013977051 | E20: =$C$2*(1+IF(E$3<=$O$2,$D20,$D20-($D20-$I$6)*MIN(E$3-$O$2,$Q$2)/$Q$2)) -> 1875.8575 | F20: =E20*(1+IF(F$3<=$O$2,$D20,$D20-($D20-$I$6)*MIN(F$3-$O$2,$Q$2)/$Q$2)) -> 1902.0765 | G20: =F20*(1+IF(G$3<=$O$2,$D20,$D20-($D20-$I$6)*MIN(G$3-$O$2,$Q$2)/$Q$2)) -> 1928.6619 | H20: =G20*(1+IF(H$3<=$O$2,$D20,$D20-($D20-$I$6)*MIN(H$3-$O$2,$Q$2)/$Q$2)) -> 1955.6189 | I20: =H20*(1+IF(I$3<=$O$2,$D20,$D20-($D20-$I$6)*MIN(I$3-$O$2,$Q$2)/$Q$2)) -> 1982.9527 | J20: =I20*(1+IF(J$3<=$O$2,$D20,$D20-($D20-$I$6)*MIN(J$3-$O$2,$Q$2)/$Q$2)) -> 2015.0401 | K20: =J20*(1+IF(K$3<=$O$2,$D20,$D20-($D20-$I$6)*MIN(K$3-$O$2,$Q$2)/$Q$2)) -> 2052.0891 | L20: =K20*(1+IF(L$3<=$O$2,$D20,$D20-($D20-$I$6)*MIN(L$3-$O$2,$Q$2)/$Q$2)) -> 2094.3433 | M20: =L20*(1+IF(M$3<=$O$2,$D20,$D20-($D20-$I$6)*MIN(M$3-$O$2,$Q$2)/$Q$2)) -> 2142.0847 | N20: =M20*(1+IF(N$3<=$O$2,$D20,$D20-($D20-$I$6)*MIN(N$3-$O$2,$Q$2)/$Q$2)) -> 2195.6369 | O20: =SUMPRODUCT(E20:N20,1/(1+$F$6)^$E$3:$N$3)*$E$2 -> 5202.9764 | P20: =N20*$E$2*(1+$I$6)/($F$6-$I$6)/(1+$F$6)^$N$3 -> 11361.954 | Q20: =O20+P20 -> 16564.93 | R20: =Q20-$G$2+$I$2 -> 15012.23 | S20: =R20/$K$2 -> 54.51262 | T20: =S20-$M$2 -> 0.0080988472
... A47: 40 | B47: =IF(T46>0,B46,D46) -> 0.013955097 | C47: =IF(T46>0,D46,C46) -> 0.013955097 | D47: =(B47+C47)/2 -> 0.013955097 | E47: =$C$2*(1+IF(E$3<=$O$2,$D47,$D47-($D47-$I$6)*MIN(E$3-$O$2,$Q$2)/$Q$2)) -> 1875.8169 | F47: =E47*(1+IF(F$3<=$O$2,$D47,$D47-($D47-$I$6)*MIN(F$3-$O$2,$Q$2)/$Q$2)) -> 1901.9941 | G47: =F47*(1+IF(G$3<=$O$2,$D47,$D47-($D47-$I$6)*MIN(G$3-$O$2,$Q$2)/$Q$2)) -> 1928.5366 | H47: =G47*(1+IF(H$3<=$O$2,$D47,$D47-($D47-$I$6)*MIN(H$3-$O$2,$Q$2)/$Q$2)) -> 1955.4496 | I47: =H47*(1+IF(I$3<=$O$2,$D47,$D47-($D47-$I$6)*MIN(I$3-$O$2,$Q$2)/$Q$2)) -> 1982.7381 | J47: =I47*(1+IF(J$3<=$O$2,$D47,$D47-($D47-$I$6)*MIN(J$3-$O$2,$Q$2)/$Q$2)) -> 2014.7872 | K47: =J47*(1+IF(K$3<=$O$2,$D47,$D47-($D47-$I$6)*MIN(K$3-$O$2,$Q$2)/$Q$2)) -> 2051.805 | L47: =K47*(1+IF(L$3<=$O$2,$D47,$D47-($D47-$I$6)*MIN(L$3-$O$2,$Q$2)/$Q$2)) -> 2094.0353 | M47: =L47*(1+IF(M$3<=$O$2,$D47,$D47-($D47-$I$6)*MIN(M$3-$O$2,$Q$2)/$Q$2)) -> 2141.7605 | N47: =M47*(1+IF(N$3<=$O$2,$D47,$D47-($D47-$I$6)*MIN(N$3-$O$2,$Q$2)/$Q$2)) -> 2195.3045 | O47: =SUMPRODUCT(E47:N47,1/(1+$F$6)^$E$3:$N$3)*$E$2 -> 5202.4659 | P47: =N47*$E$2*(1+$I$6)/($F$6-$I$6)/(1+$F$6)^$N$3 -> 11360.234 | Q47: =O47+P47 -> 16562.7 | R47: =Q47-$G$2+$I$2 -> 15010 | S47: =R47/$K$2 -> 54.504521 | T47: =S47-$M$2 -> -3.7296388e-10
A49: Grid block 2: row 1, column 1 of table A (24 steps) | E49: WACC | F49: =Sensitivity!$B$10 -> 0.053509306 | G49: Terminal growth | I49: =Sensitivity!$C$9 -> 0.015
A50: Step | B50: Low | C50: High | D50: Mid | E50: Rev Y1 | F50: Rev Y2 | G50: Rev Y3 | H50: Rev Y4 | I50: Rev Y5 | J50: Rev Y6 | K50: Rev Y7 | L50: Rev Y8 | M50: Rev Y9 | N50: Rev Y10 | O50: PV of FCF | P50: PV of TV | Q50: EV | R50: Equity | S50: Per share | T50: Value - price
A51: 1 | B51: -0.5 | C51: 1 | D51: =(B51+C51)/2 -> 0.25 | E51: =$C$2*(1+IF(E$3<=$O$2,$D51,$D51-($D51-$I$49)*MIN(E$3-$O$2,$Q$2)/$Q$2)) -> 2312.5 | F51: =E51*(1+IF(F$3<=$O$2,$D51,$D51-($D51-$I$49)*MIN(F$3-$O$2,$Q$2)/$Q$2)) -> 2890.625 | G51: =F51*(1+IF(G$3<=$O$2,$D51,$D51-($D51-$I$49)*MIN(G$3-$O$2,$Q$2)/$Q$2)) -> 3613.2812 | H51: =G51*(1+IF(H$3<=$O$2,$D51,$D51-($D51-$I$49)*MIN(H$3-$O$2,$Q$2)/$Q$2)) -> 4516.6016 | I51: =H51*(1+IF(I$3<=$O$2,$D51,$D51-($D51-$I$49)*MIN(I$3-$O$2,$Q$2)/$Q$2)) -> 5645.752 | J51: =I51*(1+IF(J$3<=$O$2,$D51,$D51-($D51-$I$49)*MIN(J$3-$O$2,$Q$2)/$Q$2)) -> 6791.8396 | K51: =J51*(1+IF(K$3<=$O$2,$D51,$D51-($D51-$I$49)*MIN(K$3-$O$2,$Q$2)/$Q$2)) -> 7851.3666 | L51: =K51*(1+IF(L$3<=$O$2,$D51,$D51-($D51-$I$49)*MIN(L$3-$O$2,$Q$2)/$Q$2)) -> 8707.1655 | M51: =L51*(1+IF(M$3<=$O$2,$D51,$D51-($D51-$I$49)*MIN(M$3-$O$2,$Q$2)/$Q$2)) -> 9247.0098 | N51: =M51*(1+IF(N$3<=$O$2,$D51,$D51-($D51-$I$49)*MIN(N$3-$O$2,$Q$2)/$Q$2)) -> 9385.7149 | O51: =SUMPRODUCT(E51:N51,1/(1+$F$49)^$E$3:$N$3)*$E$2 -> 15625.901 | P51: =N51*$E$2*(1+$I$49)/($F$49-$I$49)/(1+$F$49)^$N$3 -> 52860.495 | Q51: =O51+P51 -> 68486.397 | R51: =Q51-$G$2+$I$2 -> 66933.697 | S51: =R51/$K$2 -> 243.05057 | T51: =S51-$M$2 -> 188.54605
A52: 2 | B52: =IF(T51>0,B51,D51) -> -0.5 | C52: =IF(T51>0,D51,C51) -> 0.25 | D52: =(B52+C52)/2 -> -0.125 | E52: =$C$2*(1+IF(E$3<=$O$2,$D52,$D52-($D52-$I$49)*MIN(E$3-$O$2,$Q$2)/$Q$2)) -> 1618.75 | F52: =E52*(1+IF(F$3<=$O$2,$D52,$D52-($D52-$I$49)*MIN(F$3-$O$2,$Q$2)/$Q$2)) -> 1416.4062 | G52: =F52*(1+IF(G$3<=$O$2,$D52,$D52-($D52-$I$49)*MIN(G$3-$O$2,$Q$2)/$Q$2)) -> 1239.3555 | H52: =G52*(1+IF(H$3<=$O$2,$D52,$D52-($D52-$I$49)*MIN(H$3-$O$2,$Q$2)/$Q$2)) -> 1084.436 | I52: =H52*(1+IF(I$3<=$O$2,$D52,$D52-($D52-$I$49)*MIN(I$3-$O$2,$Q$2)/$Q$2)) -> 948.88153 | J52: =I52*(1+IF(J$3<=$O$2,$D52,$D52-($D52-$I$49)*MIN(J$3-$O$2,$Q$2)/$Q$2)) -> 856.84002 | K52: =J52*(1+IF(K$3<=$O$2,$D52,$D52-($D52-$I$49)*MIN(K$3-$O$2,$Q$2)/$Q$2)) -> 797.71806 | L52: =K52*(1+IF(L$3<=$O$2,$D52,$D52-($D52-$I$49)*MIN(L$3-$O$2,$Q$2)/$Q$2)) -> 765.01162 | M52: =L52*(1+IF(M$3<=$O$2,$D52,$D52-($D52-$I$49)*MIN(M$3-$O$2,$Q$2)/$Q$2)) -> 755.06647 | N52: =M52*(1+IF(N$3<=$O$2,$D52,$D52-($D52-$I$49)*MIN(N$3-$O$2,$Q$2)/$Q$2)) -> 766.39247 | O52: =SUMPRODUCT(E52:N52,1/(1+$F$49)^$E$3:$N$3)*$E$2 -> 2913.6063 | P52: =N52*$E$2*(1+$I$49)/($F$49-$I$49)/(1+$F$49)^$N$3 -> 4316.3345 | Q52: =O52+P52 -> 7229.9408 | R52: =Q52-$G$2+$I$2 -> 5677.2408 | S52: =R52/$K$2 -> 20.615276 | T52: =S52-$M$2 -> -33.889245
A53: 3 | B53: =IF(T52>0,B52,D52) -> -0.125 | C53: =IF(T52>0,D52,C52) -> 0.25 | D53: =(B53+C53)/2 -> 0.0625 | E53: =$C$2*(1+IF(E$3<=$O$2,$D53,$D53-($D53-$I$49)*MIN(E$3-$O$2,$Q$2)/$Q$2)) -> 1965.625 | F53: =E53*(1+IF(F$3<=$O$2,$D53,$D53-($D53-$I$49)*MIN(F$3-$O$2,$Q$2)/$Q$2)) -> 2088.4766 | G53: =F53*(1+IF(G$3<=$O$2,$D53,$D53-($D53-$I$49)*MIN(G$3-$O$2,$Q$2)/$Q$2)) -> 2219.0063 | H53: =G53*(1+IF(H$3<=$O$2,$D53,$D53-($D53-$I$49)*MIN(H$3-$O$2,$Q$2)/$Q$2)) -> 2357.6942 | I53: =H53*(1+IF(I$3<=$O$2,$D53,$D53-($D53-$I$49)*MIN(I$3-$O$2,$Q$2)/$Q$2)) -> 2505.0501 | J53: =I53*(1+IF(J$3<=$O$2,$D53,$D53-($D53-$I$49)*MIN(J$3-$O$2,$Q$2)/$Q$2)) -> 2637.8178 | K53: =J53*(1+IF(K$3<=$O$2,$D53,$D53-($D53-$I$49)*MIN(K$3-$O$2,$Q$2)/$Q$2)) -> 2752.5629 | L53: =K53*(1+IF(L$3<=$O$2,$D53,$D53-($D53-$I$49)*MIN(L$3-$O$2,$Q$2)/$Q$2)) -> 2846.15 | M53: =L53*(1+IF(M$3<=$O$2,$D53,$D53-($D53-$I$49)*MIN(M$3-$O$2,$Q$2)/$Q$2)) -> 2915.8807 | N53: =M53*(1+IF(N$3<=$O$2,$D53,$D53-($D53-$I$49)*MIN(N$3-$O$2,$Q$2)/$Q$2)) -> 2959.6189 | O53: =SUMPRODUCT(E53:N53,1/(1+$F$49)^$E$3:$N$3)*$E$2 -> 6760.8673 | P53: =N53*$E$2*(1+$I$49)/($F$49-$I$49)/(1+$F$49)^$N$3 -> 16668.62 | Q53: =O53+P53 -> 23429.488 | R53: =Q53-$G$2+$I$2 -> 21876.788 | S53: =R53/$K$2 -> 79.439296 | T53: =S53-$M$2 -> 24.934775
A54: 4 | B54: =IF(T53>0,B53,D53) -> -0.125 | C54: =IF(T53>0,D53,C53) -> 0.0625 | D54: =(B54+C54)/2 -> -0.03125 | E54: =$C$2*(1+IF(E$3<=$O$2,$D54,$D54-($D54-$I$49)*MIN(E$3-$O$2,$Q$2)/$Q$2)) -> 1792.1875 | F54: =E54*(1+IF(F$3<=$O$2,$D54,$D54-($D54-$I$49)*MIN(F$3-$O$2,$Q$2)/$Q$2)) -> 1736.1816 | G54: =F54*(1+IF(G$3<=$O$2,$D54,$D54-($D54-$I$49)*MIN(G$3-$O$2,$Q$2)/$Q$2)) -> 1681.926 | H54: =G54*(1+IF(H$3<=$O$2,$D54,$D54-($D54-$I$49)*MIN(H$3-$O$2,$Q$2)/$Q$2)) -> 1629.3658 | I54: =H54*(1+IF(I$3<=$O$2,$D54,$D54-($D54-$I$49)*MIN(I$3-$O$2,$Q$2)/$Q$2)) -> 1578.4481 | J54: =I54*(1+IF(J$3<=$O$2,$D54,$D54-($D54-$I$49)*MIN(J$3-$O$2,$Q$2)/$Q$2)) -> 1543.7222 | K54: =J54*(1+IF(K$3<=$O$2,$D54,$D54-($D54-$I$49)*MIN(K$3-$O$2,$Q$2)/$Q$2)) -> 1524.0398 | L54: =K54*(1+IF(L$3<=$O$2,$D54,$D54-($D54-$I$49)*MIN(L$3-$O$2,$Q$2)/$Q$2)) -> 1518.7056 | M54: =L54*(1+IF(M$3<=$O$2,$D54,$D54-($D54-$I$49)*MIN(M$3-$O$2,$Q$2)/$Q$2)) -> 1527.4382 | N54: =M54*(1+IF(N$3<=$O$2,$D54,$D54-($D54-$I$49)*MIN(N$3-$O$2,$Q$2)/$Q$2)) -> 1550.3498 | O54: =SUMPRODUCT(E54:N54,1/(1+$F$49)^$E$3:$N$3)*$E$2 -> 4428.9302 | P54: =N54*$E$2*(1+$I$49)/($F$49-$I$49)/(1+$F$49)^$N$3 -> 8731.5945 | Q54: =O54+P54 -> 13160.525 | R54: =Q54-$G$2+$I$2 -> 11607.825 | S54: =R54/$K$2 -> 42.150495 | T54: =S54-$M$2 -> -12.354026
A55: 5 | B55: =IF(T54>0,B54,D54) -> -0.03125 | C55: =IF(T54>0,D54,C54) -> 0.0625 | D55: =(B55+C55)/2 -> 0.015625 | E55: =$C$2*(1+IF(E$3<=$O$2,$D55,$D55-($D55-$I$49)*MIN(E$3-$O$2,$Q$2)/$Q$2)) -> 1878.9062 | F55: =E55*(1+IF(F$3<=$O$2,$D55,$D55-($D55-$I$49)*MIN(F$3-$O$2,$Q$2)/$Q$2)) -> 1908.2642 | G55: =F55*(1+IF(G$3<=$O$2,$D55,$D55-($D55-$I$49)*MIN(G$3-$O$2,$Q$2)/$Q$2)) -> 1938.0808 | H55: =G55*(1+IF(H$3<=$O$2,$D55,$D55-($D55-$I$49)*MIN(H$3-$O$2,$Q$2)/$Q$2)) -> 1968.3633 | I55: =H55*(1+IF(I$3<=$O$2,$D55,$D55-($D55-$I$49)*MIN(I$3-$O$2,$Q$2)/$Q$2)) -> 1999.119 | J55: =I55*(1+IF(J$3<=$O$2,$D55,$D55-($D55-$I$49)*MIN(J$3-$O$2,$Q$2)/$Q$2)) -> 2030.1053 | K55: =J55*(1+IF(K$3<=$O$2,$D55,$D55-($D55-$I$49)*MIN(K$3-$O$2,$Q$2)/$Q$2)) -> 2061.3182 | L55: =K55*(1+IF(L$3<=$O$2,$D55,$D55-($D55-$I$49)*MIN(L$3-$O$2,$Q$2)/$Q$2)) -> 2092.7533 | M55: =L55*(1+IF(M$3<=$O$2,$D55,$D55-($D55-$I$49)*MIN(M$3-$O$2,$Q$2)/$Q$2)) -> 2124.4062 | N55: =M55*(1+IF(N$3<=$O$2,$D55,$D55-($D55-$I$49)*MIN(N$3-$O$2,$Q$2)/$Q$2)) -> 2156.2723 | O55: =SUMPRODUCT(E55:N55,1/(1+$F$49)^$E$3:$N$3)*$E$2 -> 5471.1398 | P55: =N55*$E$2*(1+$I$49)/($F$49-$I$49)/(1+$F$49)^$N$3 -> 12144.16 | Q55: =O55+P55 -> 17615.299 | R55: =Q55-$G$2+$I$2 -> 16062.599 | S55: =R55/$K$2 -> 58.326735 | T55: =S55-$M$2 -> 3.8222139
A56: 6 | B56: =IF(T55>0,B55,D55) -> -0.03125 | C56: =IF(T55>0,D55,C55) -> 0.015625 | D56: =(B56+C56)/2 -> -0.0078125 | E56: =$C$2*(1+IF(E$3<=$O$2,$D56,$D56-($D56-$I$49)*MIN(E$3-$O$2,$Q$2)/$Q$2)) -> 1835.5469 | F56: =E56*(1+IF(F$3<=$O$2,$D56,$D56-($D56-$I$49)*MIN(F$3-$O$2,$Q$2)/$Q$2)) -> 1821.2067 | G56: =F56*(1+IF(G$3<=$O$2,$D56,$D56-($D56-$I$49)*MIN(G$3-$O$2,$Q$2)/$Q$2)) -> 1806.9785 | H56: =G56*(1+IF(H$3<=$O$2,$D56,$D56-($D56-$I$49)*MIN(H$3-$O$2,$Q$2)/$Q$2)) -> 1792.8615 | I56: =H56*(1+IF(I$3<=$O$2,$D56,$D56-($D56-$I$49)*MIN(I$3-$O$2,$Q$2)/$Q$2)) -> 1778.8547 | J56: =I56*(1+IF(J$3<=$O$2,$D56,$D56-($D56-$I$49)*MIN(J$3-$O$2,$Q$2)/$Q$2)) -> 1773.0735 | K56: =J56*(1+IF(K$3<=$O$2,$D56,$D56-($D56-$I$49)*MIN(K$3-$O$2,$Q$2)/$Q$2)) -> 1775.4006 | L56: =K56*(1+IF(L$3<=$O$2,$D56,$D56-($D56-$I$49)*MIN(L$3-$O$2,$Q$2)/$Q$2)) -> 1785.8311 | M56: =L56*(1+IF(M$3<=$O$2,$D56,$D56-($D56-$I$49)*MIN(M$3-$O$2,$Q$2)/$Q$2)) -> 1804.4707 | N56: =M56*(1+IF(N$3<=$O$2,$D56,$D56-($D56-$I$49)*MIN(N$3-$O$2,$Q$2)/$Q$2)) -> 1831.5378 | O56: =SUMPRODUCT(E56:N56,1/(1+$F$49)^$E$3:$N$3)*$E$2 -> 4922.1069 | P56: =N56*$E$2*(1+$I$49)/($F$49-$I$49)/(1+$F$49)^$N$3 -> 10315.25 | Q56: =O56+P56 -> 15237.357 | R56: =Q56-$G$2+$I$2 -> 13684.657 | S56: =R56/$K$2 -> 49.691916 | T56: =S56-$M$2 -> -4.8126053
A57: 7 | B57: =IF(T56>0,B56,D56) -> -0.0078125 | C57: =IF(T56>0,D56,C56) -> 0.015625 | D57: =(B57+C57)/2 -> 0.00390625 | E57: =$C$2*(1+IF(E$3<=$O$2,$D57,$D57-($D57-$I$49)*MIN(E$3-$O$2,$Q$2)/$Q$2)) -> 1857.2266 | F57: =E57*(1+IF(F$3<=$O$2,$D57,$D57-($D57-$I$49)*MIN(F$3-$O$2,$Q$2)/$Q$2)) -> 1864.4814 | G57: =F57*(1+IF(G$3<=$O$2,$D57,$D57-($D57-$I$49)*MIN(G$3-$O$2,$Q$2)/$Q$2)) -> 1871.7645 | H57: =G57*(1+IF(H$3<=$O$2,$D57,$D57-($D57-$I$49)*MIN(H$3-$O$2,$Q$2)/$Q$2)) -> 1879.0761 | I57: =H57*(1+IF(I$3<=$O$2,$D57,$D57-($D57-$I$49)*MIN(I$3-$O$2,$Q$2)/$Q$2)) -> 1886.4162 | J57: =I57*(1+IF(J$3<=$O$2,$D57,$D57-($D57-$I$49)*MIN(J$3-$O$2,$Q$2)/$Q$2)) -> 1897.9705 | K57: =J57*(1+IF(K$3<=$O$2,$D57,$D57-($D57-$I$49)*MIN(K$3-$O$2,$Q$2)/$Q$2)) -> 1913.8067 | L57: =K57*(1+IF(L$3<=$O$2,$D57,$D57-($D57-$I$49)*MIN(L$3-$O$2,$Q$2)/$Q$2)) -> 1934.0213 | M57: =L57*(1+IF(M$3<=$O$2,$D57,$D57-($D57-$I$49)*MIN(M$3-$O$2,$Q$2)/$Q$2)) -> 1958.7405 | N57: =M57*(1+IF(N$3<=$O$2,$D57,$D57-($D57-$I$49)*MIN(N$3-$O$2,$Q$2)/$Q$2)) -> 1988.1216 | O57: =SUMPRODUCT(E57:N57,1/(1+$F$49)^$E$3:$N$3)*$E$2 -> 5189.2852 | P57: =N57*$E$2*(1+$I$49)/($F$49-$I$49)/(1+$F$49)^$N$3 -> 11197.132 | Q57: =O57+P57 -> 16386.418 | R57: =Q57-$G$2+$I$2 -> 14833.718 | S57: =R57/$K$2 -> 53.864402 | T57: =S57-$M$2 -> -0.64011926
A58: 8 | B58: =IF(T57>0,B57,D57) -> 0.00390625 | C58: =IF(T57>0,D57,C57) -> 0.015625 | D58: =(B58+C58)/2 -> 0.009765625 | E58: =$C$2*(1+IF(E$3<=$O$2,$D58,$D58-($D58-$I$49)*MIN(E$3-$O$2,$Q$2)/$Q$2)) -> 1868.0664 | F58: =E58*(1+IF(F$3<=$O$2,$D58,$D58-($D58-$I$49)*MIN(F$3-$O$2,$Q$2)/$Q$2)) -> 1886.3092 | G58: =F58*(1+IF(G$3<=$O$2,$D58,$D58-($D58-$I$49)*MIN(G$3-$O$2,$Q$2)/$Q$2)) -> 1904.7302 | H58: =G58*(1+IF(H$3<=$O$2,$D58,$D58-($D58-$I$49)*MIN(H$3-$O$2,$Q$2)/$Q$2)) -> 1923.3311 | I58: =H58*(1+IF(I$3<=$O$2,$D58,$D58-($D58-$I$49)*MIN(I$3-$O$2,$Q$2)/$Q$2)) -> 1942.1136 | J58: =I58*(1+IF(J$3<=$O$2,$D58,$D58-($D58-$I$49)*MIN(J$3-$O$2,$Q$2)/$Q$2)) -> 1963.1127 | K58: =J58*(1+IF(K$3<=$O$2,$D58,$D58-($D58-$I$49)*MIN(K$3-$O$2,$Q$2)/$Q$2)) -> 1986.394 | L58: =K58*(1+IF(L$3<=$O$2,$D58,$D58-($D58-$I$49)*MIN(L$3-$O$2,$Q$2)/$Q$2)) -> 2012.0309 | M58: =L58*(1+IF(M$3<=$O$2,$D58,$D58-($D58-$I$49)*MIN(M$3-$O$2,$Q$2)/$Q$2)) -> 2040.1051 | N58: =M58*(1+IF(N$3<=$O$2,$D58,$D58-($D58-$I$49)*MIN(N$3-$O$2,$Q$2)/$Q$2)) -> 2070.7066 | O58: =SUMPRODUCT(E58:N58,1/(1+$F$49)^$E$3:$N$3)*$E$2 -> 5328.3318 | P58: =N58*$E$2*(1+$I$49)/($F$49-$I$49)/(1+$F$49)^$N$3 -> 11662.253 | Q58: =O58+P58 -> 16990.584 | R58: =Q58-$G$2+$I$2 -> 15437.884 | S58: =R58/$K$2 -> 56.05826 | T58: =S58-$M$2 -> 1.5537395
A59: 9 | B59: =IF(T58>0,B58,D58) -> 0.00390625 | C59: =IF(T58>0,D58,C58) -> 0.009765625 | D59: =(B59+C59)/2 -> 0.0068359375 | E59: =$C$2*(1+IF(E$3<=$O$2,$D59,$D59-($D59-$I$49)*MIN(E$3-$O$2,$Q$2)/$Q$2)) -> 1862.6465 | F59: =E59*(1+IF(F$3<=$O$2,$D59,$D59-($D59-$I$49)*MIN(F$3-$O$2,$Q$2)/$Q$2)) -> 1875.3794 | G59: =F59*(1+IF(G$3<=$O$2,$D59,$D59-($D59-$I$49)*MIN(G$3-$O$2,$Q$2)/$Q$2)) -> 1888.1994 | H59: =G59*(1+IF(H$3<=$O$2,$D59,$D59-($D59-$I$49)*MIN(H$3-$O$2,$Q$2)/$Q$2)) -> 1901.107 | I59: =H59*(1+IF(I$3<=$O$2,$D59,$D59-($D59-$I$49)*MIN(I$3-$O$2,$Q$2)/$Q$2)) -> 1914.1029 | J59: =I59*(1+IF(J$3<=$O$2,$D59,$D59-($D59-$I$49)*MIN(J$3-$O$2,$Q$2)/$Q$2)) -> 1930.3129 | K59: =J59*(1+IF(K$3<=$O$2,$D59,$D59-($D59-$I$49)*MIN(K$3-$O$2,$Q$2)/$Q$2)) -> 1949.8121 | L59: =K59*(1+IF(L$3<=$O$2,$D59,$D59-($D59-$I$49)*MIN(L$3-$O$2,$Q$2)/$Q$2)) -> 1972.6919 | M59: =L59*(1+IF(M$3<=$O$2,$D59,$D59-($D59-$I$49)*MIN(M$3-$O$2,$Q$2)/$Q$2)) -> 1999.0613 | N59: =M59*(1+IF(N$3<=$O$2,$D59,$D59-($D59-$I$49)*MIN(N$3-$O$2,$Q$2)/$Q$2)) -> 2029.0472 | O59: =SUMPRODUCT(E59:N59,1/(1+$F$49)^$E$3:$N$3)*$E$2 -> 5258.3442 | P59: =N59*$E$2*(1+$I$49)/($F$49-$I$49)/(1+$F$49)^$N$3 -> 11427.626 | Q59: =O59+P59 -> 16685.97 | R59: =Q59-$G$2+$I$2 -> 15133.27 | S59: =R59/$K$2 -> 54.952141 | T59: =S59-$M$2 -> 0.44761987
A60: 10 | B60: =IF(T59>0,B59,D59) -> 0.00390625 | C60: =IF(T59>0,D59,C59) -> 0.0068359375 | D60: =(B60+C60)/2 -> 0.0053710938 | E60: =$C$2*(1+IF(E$3<=$O$2,$D60,$D60-($D60-$I$49)*MIN(E$3-$O$2,$Q$2)/$Q$2)) -> 1859.9365 | F60: =E60*(1+IF(F$3<=$O$2,$D60,$D60-($D60-$I$49)*MIN(F$3-$O$2,$Q$2)/$Q$2)) -> 1869.9264 | G60: =F60*(1+IF(G$3<=$O$2,$D60,$D60-($D60-$I$49)*MIN(G$3-$O$2,$Q$2)/$Q$2)) -> 1879.97 | H60: =G60*(1+IF(H$3<=$O$2,$D60,$D60-($D60-$I$49)*MIN(H$3-$O$2,$Q$2)/$Q$2)) -> 1890.0675 | I60: =H60*(1+IF(I$3<=$O$2,$D60,$D60-($D60-$I$49)*MIN(I$3-$O$2,$Q$2)/$Q$2)) -> 1900.2192 | J60: =I60*(1+IF(J$3<=$O$2,$D60,$D60-($D60-$I$49)*MIN(J$3-$O$2,$Q$2)/$Q$2)) -> 1914.0849 | K60: =J60*(1+IF(K$3<=$O$2,$D60,$D60-($D60-$I$49)*MIN(K$3-$O$2,$Q$2)/$Q$2)) -> 1931.7378 | L60: =K60*(1+IF(L$3<=$O$2,$D60,$D60-($D60-$I$49)*MIN(L$3-$O$2,$Q$2)/$Q$2)) -> 1953.2737 | M60: =L60*(1+IF(M$3<=$O$2,$D60,$D60-($D60-$I$49)*MIN(M$3-$O$2,$Q$2)/$Q$2)) -> 1978.8112 | N60: =M60*(1+IF(N$3<=$O$2,$D60,$D60-($D60-$I$49)*MIN(N$3-$O$2,$Q$2)/$Q$2)) -> 2008.4934 | O60: =SUMPRODUCT(E60:N60,1/(1+$F$49)^$E$3:$N$3)*$E$2 -> 5223.6993 | P60: =N60*$E$2*(1+$I$49)/($F$49-$I$49)/(1+$F$49)^$N$3 -> 11311.866 | Q60: =O60+P60 -> 16535.566 | R60: =Q60-$G$2+$I$2 -> 14982.866 | S60: =R60/$K$2 -> 54.405991 | T60: =S60-$M$2 -> -0.098530353
A61: 11 | B61: =IF(T60>0,B60,D60) -> 0.0053710938 | C61: =IF(T60>0,D60,C60) -> 0.0068359375 | D61: =(B61+C61)/2 -> 0.0061035156 | E61: =$C$2*(1+IF(E$3<=$O$2,$D61,$D61-($D61-$I$49)*MIN(E$3-$O$2,$Q$2)/$Q$2)) -> 1861.2915 | F61: =E61*(1+IF(F$3<=$O$2,$D61,$D61-($D61-$I$49)*MIN(F$3-$O$2,$Q$2)/$Q$2)) -> 1872.6519 | G61: =F61*(1+IF(G$3<=$O$2,$D61,$D61-($D61-$I$49)*MIN(G$3-$O$2,$Q$2)/$Q$2)) -> 1884.0817 | H61: =G61*(1+IF(H$3<=$O$2,$D61,$D61-($D61-$I$49)*MIN(H$3-$O$2,$Q$2)/$Q$2)) -> 1895.5812 | I61: =H61*(1+IF(I$3<=$O$2,$D61,$D61-($D61-$I$49)*MIN(I$3-$O$2,$Q$2)/$Q$2)) -> 1907.1509 | J61: =I61*(1+IF(J$3<=$O$2,$D61,$D61-($D61-$I$49)*MIN(J$3-$O$2,$Q$2)/$Q$2)) -> 1922.1846 | K61: =J61*(1+IF(K$3<=$O$2,$D61,$D61-($D61-$I$49)*MIN(K$3-$O$2,$Q$2)/$Q$2)) -> 1940.757 | L61: =K61*(1+IF(L$3<=$O$2,$D61,$D61-($D61-$I$49)*MIN(L$3-$O$2,$Q$2)/$Q$2)) -> 1962.962 | M61: =L61*(1+IF(M$3<=$O$2,$D61,$D61-($D61-$I$49)*MIN(M$3-$O$2,$Q$2)/$Q$2)) -> 1988.9137 | N61: =M61*(1+IF(N$3<=$O$2,$D61,$D61-($D61-$I$49)*MIN(N$3-$O$2,$Q$2)/$Q$2)) -> 2018.7474 | O61: =SUMPRODUCT(E61:N61,1/(1+$F$49)^$E$3:$N$3)*$E$2 -> 5240.9928 | P61: =N61*$E$2*(1+$I$49)/($F$49-$I$49)/(1+$F$49)^$N$3 -> 11369.617 | Q61: =O61+P61 -> 16610.61 | R61: =Q61-$G$2+$I$2 -> 15057.91 | S61: =R61/$K$2 -> 54.678493 | T61: =S61-$M$2 -> 0.17397249
A62: 12 | B62: =IF(T61>0,B61,D61) -> 0.0053710938 | C62: =IF(T61>0,D61,C61) -> 0.0061035156 | D62: =(B62+C62)/2 -> 0.0057373047 | E62: =$C$2*(1+IF(E$3<=$O$2,$D62,$D62-($D62-$I$49)*MIN(E$3-$O$2,$Q$2)/$Q$2)) -> 1860.614 | F62: =E62*(1+IF(F$3<=$O$2,$D62,$D62-($D62-$I$49)*MIN(F$3-$O$2,$Q$2)/$Q$2)) -> 1871.2889 | G62: =F62*(1+IF(G$3<=$O$2,$D62,$D62-($D62-$I$49)*MIN(G$3-$O$2,$Q$2)/$Q$2)) -> 1882.0251 | H62: =G62*(1+IF(H$3<=$O$2,$D62,$D62-($D62-$I$49)*MIN(H$3-$O$2,$Q$2)/$Q$2)) -> 1892.8228 | I62: =H62*(1+IF(I$3<=$O$2,$D62,$D62-($D62-$I$49)*MIN(I$3-$O$2,$Q$2)/$Q$2)) -> 1903.6825 | J62: =I62*(1+IF(J$3<=$O$2,$D62,$D62-($D62-$I$49)*MIN(J$3-$O$2,$Q$2)/$Q$2)) -> 1918.1312 | K62: =J62*(1+IF(K$3<=$O$2,$D62,$D62-($D62-$I$49)*MIN(K$3-$O$2,$Q$2)/$Q$2)) -> 1936.2429 | L62: =K62*(1+IF(L$3<=$O$2,$D62,$D62-($D62-$I$49)*MIN(L$3-$O$2,$Q$2)/$Q$2)) -> 1958.1126 | M62: =L62*(1+IF(M$3<=$O$2,$D62,$D62-($D62-$I$49)*MIN(M$3-$O$2,$Q$2)/$Q$2)) -> 1983.8568 | N62: =M62*(1+IF(N$3<=$O$2,$D62,$D62-($D62-$I$49)*MIN(N$3-$O$2,$Q$2)/$Q$2)) -> 2013.6147 | O62: =SUMPRODUCT(E62:N62,1/(1+$F$49)^$E$3:$N$3)*$E$2 -> 5232.3389 | P62: =N62*$E$2*(1+$I$49)/($F$49-$I$49)/(1+$F$49)^$N$3 -> 11340.71 | Q62: =O62+P62 -> 16573.049 | R62: =Q62-$G$2+$I$2 -> 15020.349 | S62: =R62/$K$2 -> 54.542099 | T62: =S62-$M$2 -> 0.037578265
A63: 13 | B63: =IF(T62>0,B62,D62) -> 0.0053710938 | C63: =IF(T62>0,D62,C62) -> 0.0057373047 | D63: =(B63+C63)/2 -> 0.0055541992 | E63: =$C$2*(1+IF(E$3<=$O$2,$D63,$D63-($D63-$I$49)*MIN(E$3-$O$2,$Q$2)/$Q$2)) -> 1860.2753 | F63: =E63*(1+IF(F$3<=$O$2,$D63,$D63-($D63-$I$49)*MIN(F$3-$O$2,$Q$2)/$Q$2)) -> 1870.6076 | G63: =F63*(1+IF(G$3<=$O$2,$D63,$D63-($D63-$I$49)*MIN(G$3-$O$2,$Q$2)/$Q$2)) -> 1880.9973 | H63: =G63*(1+IF(H$3<=$O$2,$D63,$D63-($D63-$I$49)*MIN(H$3-$O$2,$Q$2)/$Q$2)) -> 1891.4448 | I63: =H63*(1+IF(I$3<=$O$2,$D63,$D63-($D63-$I$49)*MIN(I$3-$O$2,$Q$2)/$Q$2)) -> 1901.9502 | J63: =I63*(1+IF(J$3<=$O$2,$D63,$D63-($D63-$I$49)*MIN(J$3-$O$2,$Q$2)/$Q$2)) -> 1916.1071 | K63: =J63*(1+IF(K$3<=$O$2,$D63,$D63-($D63-$I$49)*MIN(K$3-$O$2,$Q$2)/$Q$2)) -> 1933.9892 | L63: =K63*(1+IF(L$3<=$O$2,$D63,$D63-($D63-$I$49)*MIN(L$3-$O$2,$Q$2)/$Q$2)) -> 1955.6918 | M63: =L63*(1+IF(M$3<=$O$2,$D63,$D63-($D63-$I$49)*MIN(M$3-$O$2,$Q$2)/$Q$2)) -> 1981.3326 | N63: =M63*(1+IF(N$3<=$O$2,$D63,$D63-($D63-$I$49)*MIN(N$3-$O$2,$Q$2)/$Q$2)) -> 2011.0526 | O63: =SUMPRODUCT(E63:N63,1/(1+$F$49)^$E$3:$N$3)*$E$2 -> 5228.0173 | P63: =N63*$E$2*(1+$I$49)/($F$49-$I$49)/(1+$F$49)^$N$3 -> 11326.28 | Q63: =O63+P63 -> 16554.297 | R63: =Q63-$G$2+$I$2 -> 15001.597 | S63: =R63/$K$2 -> 54.474009 | T63: =S63-$M$2 -> -0.030511712
... A74: 24 | B74: =IF(T73>0,B73,D73) -> 0.005636096 | C74: =IF(T73>0,D73,C73) -> 0.0056362748 | D74: =(B74+C74)/2 -> 0.0056361854 | E74: =$C$2*(1+IF(E$3<=$O$2,$D74,$D74-($D74-$I$49)*MIN(E$3-$O$2,$Q$2)/$Q$2)) -> 1860.4269 | F74: =E74*(1+IF(F$3<=$O$2,$D74,$D74-($D74-$I$49)*MIN(F$3-$O$2,$Q$2)/$Q$2)) -> 1870.9127 | G74: =F74*(1+IF(G$3<=$O$2,$D74,$D74-($D74-$I$49)*MIN(G$3-$O$2,$Q$2)/$Q$2)) -> 1881.4575 | H74: =G74*(1+IF(H$3<=$O$2,$D74,$D74-($D74-$I$49)*MIN(H$3-$O$2,$Q$2)/$Q$2)) -> 1892.0617 | I74: =H74*(1+IF(I$3<=$O$2,$D74,$D74-($D74-$I$49)*MIN(I$3-$O$2,$Q$2)/$Q$2)) -> 1902.7257 | J74: =I74*(1+IF(J$3<=$O$2,$D74,$D74-($D74-$I$49)*MIN(J$3-$O$2,$Q$2)/$Q$2)) -> 1917.0132 | K74: =J74*(1+IF(K$3<=$O$2,$D74,$D74-($D74-$I$49)*MIN(K$3-$O$2,$Q$2)/$Q$2)) -> 1934.9981 | L74: =K74*(1+IF(L$3<=$O$2,$D74,$D74-($D74-$I$49)*MIN(L$3-$O$2,$Q$2)/$Q$2)) -> 1956.7754 | M74: =L74*(1+IF(M$3<=$O$2,$D74,$D74-($D74-$I$49)*MIN(M$3-$O$2,$Q$2)/$Q$2)) -> 1982.4625 | N74: =M74*(1+IF(N$3<=$O$2,$D74,$D74-($D74-$I$49)*MIN(N$3-$O$2,$Q$2)/$Q$2)) -> 2012.1994 | O74: =SUMPRODUCT(E74:N74,1/(1+$F$49)^$E$3:$N$3)*$E$2 -> 5229.9518 | P74: =N74*$E$2*(1+$I$49)/($F$49-$I$49)/(1+$F$49)^$N$3 -> 11332.739 | Q74: =O74+P74 -> 16562.691 | R74: =Q74-$G$2+$I$2 -> 15009.991 | S74: =R74/$K$2 -> 54.504488 | T74: =S74-$M$2 -> -3.2981986e-05
A76: Grid block 3: row 1, column 2 of table A (24 steps) | E76: WACC | F76: =Sensitivity!$B$10 -> 0.053509306 | G76: Terminal growth | I76: =Sensitivity!$D$9 -> 0.02
A77: Step | B77: Low | C77: High | D77: Mid | E77: Rev Y1 | F77: Rev Y2 | G77: Rev Y3 | H77: Rev Y4 | I77: Rev Y5 | J77: Rev Y6 | K77: Rev Y7 | L77: Rev Y8 | M77: Rev Y9 | N77: Rev Y10 | O77: PV of FCF | P77: PV of TV | Q77: EV | R77: Equity | S77: Per share | T77: Value - price
A78: 1 | B78: -0.5 | C78: 1 | D78: =(B78+C78)/2 -> 0.25 | E78: =$C$2*(1+IF(E$3<=$O$2,$D78,$D78-($D78-$I$76)*MIN(E$3-$O$2,$Q$2)/$Q$2)) -> 2312.5 | F78: =E78*(1+IF(F$3<=$O$2,$D78,$D78-($D78-$I$76)*MIN(F$3-$O$2,$Q$2)/$Q$2)) -> 2890.625 | G78: =F78*(1+IF(G$3<=$O$2,$D78,$D78-($D78-$I$76)*MIN(G$3-$O$2,$Q$2)/$Q$2)) -> 3613.2812 | H78: =G78*(1+IF(H$3<=$O$2,$D78,$D78-($D78-$I$76)*MIN(H$3-$O$2,$Q$2)/$Q$2)) -> 4516.6016 | I78: =H78*(1+IF(I$3<=$O$2,$D78,$D78-($D78-$I$76)*MIN(I$3-$O$2,$Q$2)/$Q$2)) -> 5645.752 | J78: =I78*(1+IF(J$3<=$O$2,$D78,$D78-($D78-$I$76)*MIN(J$3-$O$2,$Q$2)/$Q$2)) -> 6797.4854 | K78: =J78*(1+IF(K$3<=$O$2,$D78,$D78-($D78-$I$76)*MIN(K$3-$O$2,$Q$2)/$Q$2)) -> 7871.488 | L78: =K78*(1+IF(L$3<=$O$2,$D78,$D78-($D78-$I$76)*MIN(L$3-$O$2,$Q$2)/$Q$2)) -> 8753.0947 | M78: =L78*(1+IF(M$3<=$O$2,$D78,$D78-($D78-$I$76)*MIN(M$3-$O$2,$Q$2)/$Q$2)) -> 9330.7989 | N78: =M78*(1+IF(N$3<=$O$2,$D78,$D78-($D78-$I$76)*MIN(N$3-$O$2,$Q$2)/$Q$2)) -> 9517.4149 | O78: =SUMPRODUCT(E78:N78,1/(1+$F$76)^$E$3:$N$3)*$E$2 -> 15690.311 | P78: =N78*$E$2*(1+$I$76)/($F$76-$I$76)/(1+$F$76)^$N$3 -> 61903.793 | Q78: =O78+P78 -> 77594.104 | R78: =Q78-$G$2+$I$2 -> 76041.404 | S78: =R78/$K$2 -> 276.1226 | T78: =S78-$M$2 -> 221.61808
A79: 2 | B79: =IF(T78>0,B78,D78) -> -0.5 | C79: =IF(T78>0,D78,C78) -> 0.25 | D79: =(B79+C79)/2 -> -0.125 | E79: =$C$2*(1+IF(E$3<=$O$2,$D79,$D79-($D79-$I$76)*MIN(E$3-$O$2,$Q$2)/$Q$2)) -> 1618.75 | F79: =E79*(1+IF(F$3<=$O$2,$D79,$D79-($D79-$I$76)*MIN(F$3-$O$2,$Q$2)/$Q$2)) -> 1416.4062 | G79: =F79*(1+IF(G$3<=$O$2,$D79,$D79-($D79-$I$76)*MIN(G$3-$O$2,$Q$2)/$Q$2)) -> 1239.3555 | H79: =G79*(1+IF(H$3<=$O$2,$D79,$D79-($D79-$I$76)*MIN(H$3-$O$2,$Q$2)/$Q$2)) -> 1084.436 | I79: =H79*(1+IF(I$3<=$O$2,$D79,$D79-($D79-$I$76)*MIN(I$3-$O$2,$Q$2)/$Q$2)) -> 948.88153 | J79: =I79*(1+IF(J$3<=$O$2,$D79,$D79-($D79-$I$76)*MIN(J$3-$O$2,$Q$2)/$Q$2)) -> 857.7889 | K79: =J79*(1+IF(K$3<=$O$2,$D79,$D79-($D79-$I$76)*MIN(K$3-$O$2,$Q$2)/$Q$2)) -> 800.31705 | L79: =K79*(1+IF(L$3<=$O$2,$D79,$D79-($D79-$I$76)*MIN(L$3-$O$2,$Q$2)/$Q$2)) -> 769.905 | M79: =L79*(1+IF(M$3<=$O$2,$D79,$D79-($D79-$I$76)*MIN(M$3-$O$2,$Q$2)/$Q$2)) -> 762.97585 | N79: =M79*(1+IF(N$3<=$O$2,$D79,$D79-($D79-$I$76)*MIN(N$3-$O$2,$Q$2)/$Q$2)) -> 778.23537 | O79: =SUMPRODUCT(E79:N79,1/(1+$F$76)^$E$3:$N$3)*$E$2 -> 2919.977 | P79: =N79*$E$2*(1+$I$76)/($F$76-$I$76)/(1+$F$76)^$N$3 -> 5061.8494 | Q79: =O79+P79 -> 7981.8265 | R79: =Q79-$G$2+$I$2 -> 6429.1265 | S79: =R79/$K$2 -> 23.345533 | T79: =S79-$M$2 -> -31.158987
A80: 3 | B80: =IF(T79>0,B79,D79) -> -0.125 | C80: =IF(T79>0,D79,C79) -> 0.25 | D80: =(B80+C80)/2 -> 0.0625 | E80: =$C$2*(1+IF(E$3<=$O$2,$D80,$D80-($D80-$I$76)*MIN(E$3-$O$2,$Q$2)/$Q$2)) -> 1965.625 | F80: =E80*(1+IF(F$3<=$O$2,$D80,$D80-($D80-$I$76)*MIN(F$3-$O$2,$Q$2)/$Q$2)) -> 2088.4766 | G80: =F80*(1+IF(G$3<=$O$2,$D80,$D80-($D80-$I$76)*MIN(G$3-$O$2,$Q$2)/$Q$2)) -> 2219.0063 | H80: =G80*(1+IF(H$3<=$O$2,$D80,$D80-($D80-$I$76)*MIN(H$3-$O$2,$Q$2)/$Q$2)) -> 2357.6942 | I80: =H80*(1+IF(I$3<=$O$2,$D80,$D80-($D80-$I$76)*MIN(I$3-$O$2,$Q$2)/$Q$2)) -> 2505.0501 | J80: =I80*(1+IF(J$3<=$O$2,$D80,$D80-($D80-$I$76)*MIN(J$3-$O$2,$Q$2)/$Q$2)) -> 2640.3228 | K80: =J80*(1+IF(K$3<=$O$2,$D80,$D80-($D80-$I$76)*MIN(K$3-$O$2,$Q$2)/$Q$2)) -> 2760.4575 | L80: =K80*(1+IF(L$3<=$O$2,$D80,$D80-($D80-$I$76)*MIN(L$3-$O$2,$Q$2)/$Q$2)) -> 2862.5945 | M80: =L80*(1+IF(M$3<=$O$2,$D80,$D80-($D80-$I$76)*MIN(M$3-$O$2,$Q$2)/$Q$2)) -> 2944.1784 | N80: =M80*(1+IF(N$3<=$O$2,$D80,$D80-($D80-$I$76)*MIN(N$3-$O$2,$Q$2)/$Q$2)) -> 3003.062 | O80: =SUMPRODUCT(E80:N80,1/(1+$F$76)^$E$3:$N$3)*$E$2 -> 6783.0522 | P80: =N80*$E$2*(1+$I$76)/($F$76-$I$76)/(1+$F$76)^$N$3 -> 19532.712 | Q80: =O80+P80 -> 26315.764 | R80: =Q80-$G$2+$I$2 -> 24763.064 | S80: =R80/$K$2 -> 89.919984 | T80: =S80-$M$2 -> 35.415463
A81: 4 | B81: =IF(T80>0,B80,D80) -> -0.125 | C81: =IF(T80>0,D80,C80) -> 0.0625 | D81: =(B81+C81)/2 -> -0.03125 | E81: =$C$2*(1+IF(E$3<=$O$2,$D81,$D81-($D81-$I$76)*MIN(E$3-$O$2,$Q$2)/$Q$2)) -> 1792.1875 | F81: =E81*(1+IF(F$3<=$O$2,$D81,$D81-($D81-$I$76)*MIN(F$3-$O$2,$Q$2)/$Q$2)) -> 1736.1816 | G81: =F81*(1+IF(G$3<=$O$2,$D81,$D81-($D81-$I$76)*MIN(G$3-$O$2,$Q$2)/$Q$2)) -> 1681.926 | H81: =G81*(1+IF(H$3<=$O$2,$D81,$D81-($D81-$I$76)*MIN(H$3-$O$2,$Q$2)/$Q$2)) -> 1629.3658 | I81: =H81*(1+IF(I$3<=$O$2,$D81,$D81-($D81-$I$76)*MIN(I$3-$O$2,$Q$2)/$Q$2)) -> 1578.4481 | J81: =I81*(1+IF(J$3<=$O$2,$D81,$D81-($D81-$I$76)*MIN(J$3-$O$2,$Q$2)/$Q$2)) -> 1545.3007 | K81: =J81*(1+IF(K$3<=$O$2,$D81,$D81-($D81-$I$76)*MIN(K$3-$O$2,$Q$2)/$Q$2)) -> 1528.6887 | L81: =K81*(1+IF(L$3<=$O$2,$D81,$D81-($D81-$I$76)*MIN(L$3-$O$2,$Q$2)/$Q$2)) -> 1527.9244 | M81: =L81*(1+IF(M$3<=$O$2,$D81,$D81-($D81-$I$76)*MIN(M$3-$O$2,$Q$2)/$Q$2)) -> 1542.8216 | N81: =M81*(1+IF(N$3<=$O$2,$D81,$D81-($D81-$I$76)*MIN(N$3-$O$2,$Q$2)/$Q$2)) -> 1573.6781 | O81: =SUMPRODUCT(E81:N81,1/(1+$F$76)^$E$3:$N$3)*$E$2 -> 4441.1413 | P81: =N81*$E$2*(1+$I$76)/($F$76-$I$76)/(1+$F$76)^$N$3 -> 10235.62 | Q81: =O81+P81 -> 14676.761 | R81: =Q81-$G$2+$I$2 -> 13124.061 | S81: =R81/$K$2 -> 47.656273 | T81: =S81-$M$2 -> -6.8482474
A82: 5 | B82: =IF(T81>0,B81,D81) -> -0.03125 | C82: =IF(T81>0,D81,C81) -> 0.0625 | D82: =(B82+C82)/2 -> 0.015625 | E82: =$C$2*(1+IF(E$3<=$O$2,$D82,$D82-($D82-$I$76)*MIN(E$3-$O$2,$Q$2)/$Q$2)) -> 1878.9062 | F82: =E82*(1+IF(F$3<=$O$2,$D82,$D82-($D82-$I$76)*MIN(F$3-$O$2,$Q$2)/$Q$2)) -> 1908.2642 | G82: =F82*(1+IF(G$3<=$O$2,$D82,$D82-($D82-$I$76)*MIN(G$3-$O$2,$Q$2)/$Q$2)) -> 1938.0808 | H82: =G82*(1+IF(H$3<=$O$2,$D82,$D82-($D82-$I$76)*MIN(H$3-$O$2,$Q$2)/$Q$2)) -> 1968.3633 | I82: =H82*(1+IF(I$3<=$O$2,$D82,$D82-($D82-$I$76)*MIN(I$3-$O$2,$Q$2)/$Q$2)) -> 1999.119 | J82: =I82*(1+IF(J$3<=$O$2,$D82,$D82-($D82-$I$76)*MIN(J$3-$O$2,$Q$2)/$Q$2)) -> 2032.1044 | K82: =J82*(1+IF(K$3<=$O$2,$D82,$D82-($D82-$I$76)*MIN(K$3-$O$2,$Q$2)/$Q$2)) -> 2067.4123 | L82: =K82*(1+IF(L$3<=$O$2,$D82,$D82-($D82-$I$76)*MIN(L$3-$O$2,$Q$2)/$Q$2)) -> 2105.1425 | M82: =L82*(1+IF(M$3<=$O$2,$D82,$D82-($D82-$I$76)*MIN(M$3-$O$2,$Q$2)/$Q$2)) -> 2145.4034 | N82: =M82*(1+IF(N$3<=$O$2,$D82,$D82-($D82-$I$76)*MIN(N$3-$O$2,$Q$2)/$Q$2)) -> 2188.3114 | O82: =SUMPRODUCT(E82:N82,1/(1+$F$76)^$E$3:$N$3)*$E$2 -> 5487.6998 | P82: =N82*$E$2*(1+$I$76)/($F$76-$I$76)/(1+$F$76)^$N$3 -> 14233.359 | Q82: =O82+P82 -> 19721.058 | R82: =Q82-$G$2+$I$2 -> 18168.358 | S82: =R82/$K$2 -> 65.973195 | T82: =S82-$M$2 -> 11.468675
A83: 6 | B83: =IF(T82>0,B82,D82) -> -0.03125 | C83: =IF(T82>0,D82,C82) -> 0.015625 | D83: =(B83+C83)/2 -> -0.0078125 | E83: =$C$2*(1+IF(E$3<=$O$2,$D83,$D83-($D83-$I$76)*MIN(E$3-$O$2,$Q$2)/$Q$2)) -> 1835.5469 | F83: =E83*(1+IF(F$3<=$O$2,$D83,$D83-($D83-$I$76)*MIN(F$3-$O$2,$Q$2)/$Q$2)) -> 1821.2067 | G83: =F83*(1+IF(G$3<=$O$2,$D83,$D83-($D83-$I$76)*MIN(G$3-$O$2,$Q$2)/$Q$2)) -> 1806.9785 | H83: =G83*(1+IF(H$3<=$O$2,$D83,$D83-($D83-$I$76)*MIN(H$3-$O$2,$Q$2)/$Q$2)) -> 1792.8615 | I83: =H83*(1+IF(I$3<=$O$2,$D83,$D83-($D83-$I$76)*MIN(I$3-$O$2,$Q$2)/$Q$2)) -> 1778.8547 | J83: =I83*(1+IF(J$3<=$O$2,$D83,$D83-($D83-$I$76)*MIN(J$3-$O$2,$Q$2)/$Q$2)) -> 1774.8523 | K83: =J83*(1+IF(K$3<=$O$2,$D83,$D83-($D83-$I$76)*MIN(K$3-$O$2,$Q$2)/$Q$2)) -> 1780.7315 | L83: =K83*(1+IF(L$3<=$O$2,$D83,$D83-($D83-$I$76)*MIN(L$3-$O$2,$Q$2)/$Q$2)) -> 1796.5355 | M83: =L83*(1+IF(M$3<=$O$2,$D83,$D83-($D83-$I$76)*MIN(M$3-$O$2,$Q$2)/$Q$2)) -> 1822.473 | N83: =M83*(1+IF(N$3<=$O$2,$D83,$D83-($D83-$I$76)*MIN(N$3-$O$2,$Q$2)/$Q$2)) -> 1858.9224 | O83: =SUMPRODUCT(E83:N83,1/(1+$F$76)^$E$3:$N$3)*$E$2 -> 4936.3498 | P83: =N83*$E$2*(1+$I$76)/($F$76-$I$76)/(1+$F$76)^$N$3 -> 12090.925 | Q83: =O83+P83 -> 17027.275 | R83: =Q83-$G$2+$I$2 -> 15474.575 | S83: =R83/$K$2 -> 56.191491 | T83: =S83-$M$2 -> 1.6869705
A84: 7 | B84: =IF(T83>0,B83,D83) -> -0.03125 | C84: =IF(T83>0,D83,C83) -> -0.0078125 | D84: =(B84+C84)/2 -> -0.01953125 | E84: =$C$2*(1+IF(E$3<=$O$2,$D84,$D84-($D84-$I$76)*MIN(E$3-$O$2,$Q$2)/$Q$2)) -> 1813.8672 | F84: =E84*(1+IF(F$3<=$O$2,$D84,$D84-($D84-$I$76)*MIN(F$3-$O$2,$Q$2)/$Q$2)) -> 1778.4401 | G84: =F84*(1+IF(G$3<=$O$2,$D84,$D84-($D84-$I$76)*MIN(G$3-$O$2,$Q$2)/$Q$2)) -> 1743.7049 | H84: =G84*(1+IF(H$3<=$O$2,$D84,$D84-($D84-$I$76)*MIN(H$3-$O$2,$Q$2)/$Q$2)) -> 1709.6482 | I84: =H84*(1+IF(I$3<=$O$2,$D84,$D84-($D84-$I$76)*MIN(I$3-$O$2,$Q$2)/$Q$2)) -> 1676.2566 | J84: =I84*(1+IF(J$3<=$O$2,$D84,$D84-($D84-$I$76)*MIN(J$3-$O$2,$Q$2)/$Q$2)) -> 1656.7701 | K84: =J84*(1+IF(K$3<=$O$2,$D84,$D84-($D84-$I$76)*MIN(K$3-$O$2,$Q$2)/$Q$2)) -> 1650.609 | L84: =K84*(1+IF(L$3<=$O$2,$D84,$D84-($D84-$I$76)*MIN(L$3-$O$2,$Q$2)/$Q$2)) -> 1657.521 | M84: =L84*(1+IF(M$3<=$O$2,$D84,$D84-($D84-$I$76)*MIN(M$3-$O$2,$Q$2)/$Q$2)) -> 1677.5666 | N84: =M84*(1+IF(N$3<=$O$2,$D84,$D84-($D84-$I$76)*MIN(N$3-$O$2,$Q$2)/$Q$2)) -> 1711.1179 | O84: =SUMPRODUCT(E84:N84,1/(1+$F$76)^$E$3:$N$3)*$E$2 -> 4682.0782 | P84: =N84*$E$2*(1+$I$76)/($F$76-$I$76)/(1+$F$76)^$N$3 -> 11129.565 | Q84: =O84+P84 -> 15811.643 | R84: =Q84-$G$2+$I$2 -> 14258.943 | S84: =R84/$K$2 -> 51.777274 | T84: =S84-$M$2 -> -2.727247
A85: 8 | B85: =IF(T84>0,B84,D84) -> -0.01953125 | C85: =IF(T84>0,D84,C84) -> -0.0078125 | D85: =(B85+C85)/2 -> -0.013671875 | E85: =$C$2*(1+IF(E$3<=$O$2,$D85,$D85-($D85-$I$76)*MIN(E$3-$O$2,$Q$2)/$Q$2)) -> 1824.707 | F85: =E85*(1+IF(F$3<=$O$2,$D85,$D85-($D85-$I$76)*MIN(F$3-$O$2,$Q$2)/$Q$2)) -> 1799.7599 | G85: =F85*(1+IF(G$3<=$O$2,$D85,$D85-($D85-$I$76)*MIN(G$3-$O$2,$Q$2)/$Q$2)) -> 1775.1538 | H85: =G85*(1+IF(H$3<=$O$2,$D85,$D85-($D85-$I$76)*MIN(H$3-$O$2,$Q$2)/$Q$2)) -> 1750.8841 | I85: =H85*(1+IF(I$3<=$O$2,$D85,$D85-($D85-$I$76)*MIN(I$3-$O$2,$Q$2)/$Q$2)) -> 1726.9462 | J85: =I85*(1+IF(J$3<=$O$2,$D85,$D85-($D85-$I$76)*MIN(J$3-$O$2,$Q$2)/$Q$2)) -> 1714.9655 | K85: =J85*(1+IF(K$3<=$O$2,$D85,$D85-($D85-$I$76)*MIN(K$3-$O$2,$Q$2)/$Q$2)) -> 1714.6172 | L85: =K85*(1+IF(L$3<=$O$2,$D85,$D85-($D85-$I$76)*MIN(L$3-$O$2,$Q$2)/$Q$2)) -> 1725.8158 | M85: =L85*(1+IF(M$3<=$O$2,$D85,$D85-($D85-$I$76)*MIN(M$3-$O$2,$Q$2)/$Q$2)) -> 1748.7098 | N85: =M85*(1+IF(N$3<=$O$2,$D85,$D85-($D85-$I$76)*MIN(N$3-$O$2,$Q$2)/$Q$2)) -> 1783.684 | O85: =SUMPRODUCT(E85:N85,1/(1+$F$76)^$E$3:$N$3)*$E$2 -> 4807.5046 | P85: =N85*$E$2*(1+$I$76)/($F$76-$I$76)/(1+$F$76)^$N$3 -> 11601.554 | Q85: =O85+P85 -> 16409.059 | R85: =Q85-$G$2+$I$2 -> 14856.359 | S85: =R85/$K$2 -> 53.946617 | T85: =S85-$M$2 -> -0.5579043
A86: 9 | B86: =IF(T85>0,B85,D85) -> -0.013671875 | C86: =IF(T85>0,D85,C85) -> -0.0078125 | D86: =(B86+C86)/2 -> -0.010742188 | E86: =$C$2*(1+IF(E$3<=$O$2,$D86,$D86-($D86-$I$76)*MIN(E$3-$O$2,$Q$2)/$Q$2)) -> 1830.127 | F86: =E86*(1+IF(F$3<=$O$2,$D86,$D86-($D86-$I$76)*MIN(F$3-$O$2,$Q$2)/$Q$2)) -> 1810.4674 | G86: =F86*(1+IF(G$3<=$O$2,$D86,$D86-($D86-$I$76)*MIN(G$3-$O$2,$Q$2)/$Q$2)) -> 1791.019 | H86: =G86*(1+IF(H$3<=$O$2,$D86,$D86-($D86-$I$76)*MIN(H$3-$O$2,$Q$2)/$Q$2)) -> 1771.7795 | I86: =H86*(1+IF(I$3<=$O$2,$D86,$D86-($D86-$I$76)*MIN(I$3-$O$2,$Q$2)/$Q$2)) -> 1752.7468 | J86: =I86*(1+IF(J$3<=$O$2,$D86,$D86-($D86-$I$76)*MIN(J$3-$O$2,$Q$2)/$Q$2)) -> 1744.6951 | K86: =J86*(1+IF(K$3<=$O$2,$D86,$D86-($D86-$I$76)*MIN(K$3-$O$2,$Q$2)/$Q$2)) -> 1747.4075 | L86: =K86*(1+IF(L$3<=$O$2,$D86,$D86-($D86-$I$76)*MIN(L$3-$O$2,$Q$2)/$Q$2)) -> 1760.868 | M86: =L86*(1+IF(M$3<=$O$2,$D86,$D86-($D86-$I$76)*MIN(M$3-$O$2,$Q$2)/$Q$2)) -> 1785.2588 | N86: =M86*(1+IF(N$3<=$O$2,$D86,$D86-($D86-$I$76)*MIN(N$3-$O$2,$Q$2)/$Q$2)) -> 1820.964 | O86: =SUMPRODUCT(E86:N86,1/(1+$F$76)^$E$3:$N$3)*$E$2 -> 4871.4944 | P86: =N86*$E$2*(1+$I$76)/($F$76-$I$76)/(1+$F$76)^$N$3 -> 11844.033 | Q86: =O86+P86 -> 16715.527 | R86: =Q86-$G$2+$I$2 -> 15162.827 | S86: =R86/$K$2 -> 55.05947 | T86: =S86-$M$2 -> 0.55494924
A87: 10 | B87: =IF(T86>0,B86,D86) -> -0.013671875 | C87: =IF(T86>0,D86,C86) -> -0.010742188 | D87: =(B87+C87)/2 -> -0.012207031 | E87: =$C$2*(1+IF(E$3<=$O$2,$D87,$D87-($D87-$I$76)*MIN(E$3-$O$2,$Q$2)/$Q$2)) -> 1827.417 | F87: =E87*(1+IF(F$3<=$O$2,$D87,$D87-($D87-$I$76)*MIN(F$3-$O$2,$Q$2)/$Q$2)) -> 1805.1097 | G87: =F87*(1+IF(G$3<=$O$2,$D87,$D87-($D87-$I$76)*MIN(G$3-$O$2,$Q$2)/$Q$2)) -> 1783.0746 | H87: =G87*(1+IF(H$3<=$O$2,$D87,$D87-($D87-$I$76)*MIN(H$3-$O$2,$Q$2)/$Q$2)) -> 1761.3086 | I87: =H87*(1+IF(I$3<=$O$2,$D87,$D87-($D87-$I$76)*MIN(I$3-$O$2,$Q$2)/$Q$2)) -> 1739.8082 | J87: =I87*(1+IF(J$3<=$O$2,$D87,$D87-($D87-$I$76)*MIN(J$3-$O$2,$Q$2)/$Q$2)) -> 1729.7771 | K87: =J87*(1+IF(K$3<=$O$2,$D87,$D87-($D87-$I$76)*MIN(K$3-$O$2,$Q$2)/$Q$2)) -> 1730.9461 | L87: =K87*(1+IF(L$3<=$O$2,$D87,$D87-($D87-$I$76)*MIN(L$3-$O$2,$Q$2)/$Q$2)) -> 1743.2656 | M87: =L87*(1+IF(M$3<=$O$2,$D87,$D87-($D87-$I$76)*MIN(M$3-$O$2,$Q$2)/$Q$2)) -> 1766.9018 | N87: =M87*(1+IF(N$3<=$O$2,$D87,$D87-($D87-$I$76)*MIN(N$3-$O$2,$Q$2)/$Q$2)) -> 1802.2398 | O87: =SUMPRODUCT(E87:N87,1/(1+$F$76)^$E$3:$N$3)*$E$2 -> 4839.392 | P87: =N87*$E$2*(1+$I$76)/($F$76-$I$76)/(1+$F$76)^$N$3 -> 11722.246 | Q87: =O87+P87 -> 16561.638 | R87: =Q87-$G$2+$I$2 -> 15008.938 | S87: =R87/$K$2 -> 54.500665 | T87: =S87-$M$2 -> -0.003855561
A88: 11 | B88: =IF(T87>0,B87,D87) -> -0.012207031 | C88: =IF(T87>0,D87,C87) -> -0.010742188 | D88: =(B88+C88)/2 -> -0.011474609 | E88: =$C$2*(1+IF(E$3<=$O$2,$D88,$D88-($D88-$I$76)*MIN(E$3-$O$2,$Q$2)/$Q$2)) -> 1828.772 | F88: =E88*(1+IF(F$3<=$O$2,$D88,$D88-($D88-$I$76)*MIN(F$3-$O$2,$Q$2)/$Q$2)) -> 1807.7875 | G88: =F88*(1+IF(G$3<=$O$2,$D88,$D88-($D88-$I$76)*MIN(G$3-$O$2,$Q$2)/$Q$2)) -> 1787.0439 | H88: =G88*(1+IF(H$3<=$O$2,$D88,$D88-($D88-$I$76)*MIN(H$3-$O$2,$Q$2)/$Q$2)) -> 1766.5382 | I88: =H88*(1+IF(I$3<=$O$2,$D88,$D88-($D88-$I$76)*MIN(I$3-$O$2,$Q$2)/$Q$2)) -> 1746.2679 | J88: =I88*(1+IF(J$3<=$O$2,$D88,$D88-($D88-$I$76)*MIN(J$3-$O$2,$Q$2)/$Q$2)) -> 1737.2228 | K88: =J88*(1+IF(K$3<=$O$2,$D88,$D88-($D88-$I$76)*MIN(K$3-$O$2,$Q$2)/$Q$2)) -> 1739.1602 | L88: =K88*(1+IF(L$3<=$O$2,$D88,$D88-($D88-$I$76)*MIN(L$3-$O$2,$Q$2)/$Q$2)) -> 1752.0476 | M88: =L88*(1+IF(M$3<=$O$2,$D88,$D88-($D88-$I$76)*MIN(M$3-$O$2,$Q$2)/$Q$2)) -> 1776.0596 | N88: =M88*(1+IF(N$3<=$O$2,$D88,$D88-($D88-$I$76)*MIN(N$3-$O$2,$Q$2)/$Q$2)) -> 1811.5808 | O88: =SUMPRODUCT(E88:N88,1/(1+$F$76)^$E$3:$N$3)*$E$2 -> 4855.4162 | P88: =N88*$E$2*(1+$I$76)/($F$76-$I$76)/(1+$F$76)^$N$3 -> 11783.002 | Q88: =O88+P88 -> 16638.419 | R88: =Q88-$G$2+$I$2 -> 15085.719 | S88: =R88/$K$2 -> 54.779471 | T88: =S88-$M$2 -> 0.2749501
A89: 12 | B89: =IF(T88>0,B88,D88) -> -0.012207031 | C89: =IF(T88>0,D88,C88) -> -0.011474609 | D89: =(B89+C89)/2 -> -0.01184082 | E89: =$C$2*(1+IF(E$3<=$O$2,$D89,$D89-($D89-$I$76)*MIN(E$3-$O$2,$Q$2)/$Q$2)) -> 1828.0945 | F89: =E89*(1+IF(F$3<=$O$2,$D89,$D89-($D89-$I$76)*MIN(F$3-$O$2,$Q$2)/$Q$2)) -> 1806.4483 | G89: =F89*(1+IF(G$3<=$O$2,$D89,$D89-($D89-$I$76)*MIN(G$3-$O$2,$Q$2)/$Q$2)) -> 1785.0585 | H89: =G89*(1+IF(H$3<=$O$2,$D89,$D89-($D89-$I$76)*MIN(H$3-$O$2,$Q$2)/$Q$2)) -> 1763.922 | I89: =H89*(1+IF(I$3<=$O$2,$D89,$D89-($D89-$I$76)*MIN(I$3-$O$2,$Q$2)/$Q$2)) -> 1743.0357 | J89: =I89*(1+IF(J$3<=$O$2,$D89,$D89-($D89-$I$76)*MIN(J$3-$O$2,$Q$2)/$Q$2)) -> 1733.4966 | K89: =J89*(1+IF(K$3<=$O$2,$D89,$D89-($D89-$I$76)*MIN(K$3-$O$2,$Q$2)/$Q$2)) -> 1735.049 | L89: =K89*(1+IF(L$3<=$O$2,$D89,$D89-($D89-$I$76)*MIN(L$3-$O$2,$Q$2)/$Q$2)) -> 1747.6518 | M89: =L89*(1+IF(M$3<=$O$2,$D89,$D89-($D89-$I$76)*MIN(M$3-$O$2,$Q$2)/$Q$2)) -> 1771.4755 | N89: =M89*(1+IF(N$3<=$O$2,$D89,$D89-($D89-$I$76)*MIN(N$3-$O$2,$Q$2)/$Q$2)) -> 1806.905 | O89: =SUMPRODUCT(E89:N89,1/(1+$F$76)^$E$3:$N$3)*$E$2 -> 4847.3973 | P89: =N89*$E$2*(1+$I$76)/($F$76-$I$76)/(1+$F$76)^$N$3 -> 11752.59 | Q89: =O89+P89 -> 16599.987 | R89: =Q89-$G$2+$I$2 -> 15047.287 | S89: =R89/$K$2 -> 54.639919 | T89: =S89-$M$2 -> 0.13539836
A90: 13 | B90: =IF(T89>0,B89,D89) -> -0.012207031 | C90: =IF(T89>0,D89,C89) -> -0.01184082 | D90: =(B90+C90)/2 -> -0.012023926 | E90: =$C$2*(1+IF(E$3<=$O$2,$D90,$D90-($D90-$I$76)*MIN(E$3-$O$2,$Q$2)/$Q$2)) -> 1827.7557 | F90: =E90*(1+IF(F$3<=$O$2,$D90,$D90-($D90-$I$76)*MIN(F$3-$O$2,$Q$2)/$Q$2)) -> 1805.7789 | G90: =F90*(1+IF(G$3<=$O$2,$D90,$D90-($D90-$I$76)*MIN(G$3-$O$2,$Q$2)/$Q$2)) -> 1784.0664 | H90: =G90*(1+IF(H$3<=$O$2,$D90,$D90-($D90-$I$76)*MIN(H$3-$O$2,$Q$2)/$Q$2)) -> 1762.6149 | I90: =H90*(1+IF(I$3<=$O$2,$D90,$D90-($D90-$I$76)*MIN(I$3-$O$2,$Q$2)/$Q$2)) -> 1741.4214 | J90: =I90*(1+IF(J$3<=$O$2,$D90,$D90-($D90-$I$76)*MIN(J$3-$O$2,$Q$2)/$Q$2)) -> 1731.6361 | K90: =J90*(1+IF(K$3<=$O$2,$D90,$D90-($D90-$I$76)*MIN(K$3-$O$2,$Q$2)/$Q$2)) -> 1732.9965 | L90: =K90*(1+IF(L$3<=$O$2,$D90,$D90-($D90-$I$76)*MIN(L$3-$O$2,$Q$2)/$Q$2)) -> 1745.4575 | M90: =L90*(1+IF(M$3<=$O$2,$D90,$D90-($D90-$I$76)*MIN(M$3-$O$2,$Q$2)/$Q$2)) -> 1769.1874 | N90: =M90*(1+IF(N$3<=$O$2,$D90,$D90-($D90-$I$76)*MIN(N$3-$O$2,$Q$2)/$Q$2)) -> 1804.5711 | O90: =SUMPRODUCT(E90:N90,1/(1+$F$76)^$E$3:$N$3)*$E$2 -> 4843.393 | P90: =N90*$E$2*(1+$I$76)/($F$76-$I$76)/(1+$F$76)^$N$3 -> 11737.41 | Q90: =O90+P90 -> 16580.803 | R90: =Q90-$G$2+$I$2 -> 15028.103 | S90: =R90/$K$2 -> 54.570255 | T90: =S90-$M$2 -> 0.06573421
... A101: 24 | B101: =IF(T100>0,B100,D100) -> -0.012197018 | C101: =IF(T100>0,D100,C100) -> -0.012196839 | D101: =(B101+C101)/2 -> -0.012196928 | E101: =$C$2*(1+IF(E$3<=$O$2,$D101,$D101-($D101-$I$76)*MIN(E$3-$O$2,$Q$2)/$Q$2)) -> 1827.4357 | F101: =E101*(1+IF(F$3<=$O$2,$D101,$D101-($D101-$I$76)*MIN(F$3-$O$2,$Q$2)/$Q$2)) -> 1805.1466 | G101: =F101*(1+IF(G$3<=$O$2,$D101,$D101-($D101-$I$76)*MIN(G$3-$O$2,$Q$2)/$Q$2)) -> 1783.1293 | H101: =G101*(1+IF(H$3<=$O$2,$D101,$D101-($D101-$I$76)*MIN(H$3-$O$2,$Q$2)/$Q$2)) -> 1761.3806 | I101: =H101*(1+IF(I$3<=$O$2,$D101,$D101-($D101-$I$76)*MIN(I$3-$O$2,$Q$2)/$Q$2)) -> 1739.8972 | J101: =I101*(1+IF(J$3<=$O$2,$D101,$D101-($D101-$I$76)*MIN(J$3-$O$2,$Q$2)/$Q$2)) -> 1729.8797 | K101: =J101*(1+IF(K$3<=$O$2,$D101,$D101-($D101-$I$76)*MIN(K$3-$O$2,$Q$2)/$Q$2)) -> 1731.0592 | L101: =K101*(1+IF(L$3<=$O$2,$D101,$D101-($D101-$I$76)*MIN(L$3-$O$2,$Q$2)/$Q$2)) -> 1743.3864 | M101: =L101*(1+IF(M$3<=$O$2,$D101,$D101-($D101-$I$76)*MIN(M$3-$O$2,$Q$2)/$Q$2)) -> 1767.0278 | N101: =M101*(1+IF(N$3<=$O$2,$D101,$D101-($D101-$I$76)*MIN(N$3-$O$2,$Q$2)/$Q$2)) -> 1802.3684 | O101: =SUMPRODUCT(E101:N101,1/(1+$F$76)^$E$3:$N$3)*$E$2 -> 4839.6126 | P101: =N101*$E$2*(1+$I$76)/($F$76-$I$76)/(1+$F$76)^$N$3 -> 11723.082 | Q101: =O101+P101 -> 16562.695 | R101: =Q101-$G$2+$I$2 -> 15009.995 | S101: =R101/$K$2 -> 54.504503 | T101: =S101-$M$2 -> -1.7828704e-05
A103: Grid block 4: row 1, column 3 of table A (24 steps) | E103: WACC | F103: =Sensitivity!$B$10 -> 0.053509306 | G103: Terminal growth | I103: =Sensitivity!$E$9 -> 0.025
A104: Step | B104: Low | C104: High | D104: Mid | E104: Rev Y1 | F104: Rev Y2 | G104: Rev Y3 | H104: Rev Y4 | I104: Rev Y5 | J104: Rev Y6 | K104: Rev Y7 | L104: Rev Y8 | M104: Rev Y9 | N104: Rev Y10 | O104: PV of FCF | P104: PV of TV | Q104: EV | R104: Equity | S104: Per share | T104: Value - price
A105: 1 | B105: -0.5 | C105: 1 | D105: =(B105+C105)/2 -> 0.25 | E105: =$C$2*(1+IF(E$3<=$O$2,$D105,$D105-($D105-$I$103)*MIN(E$3-$O$2,$Q$2)/$Q$2)) -> 2312.5 | F105: =E105*(1+IF(F$3<=$O$2,$D105,$D105-($D105-$I$103)*MIN(F$3-$O$2,$Q$2)/$Q$2)) -> 2890.625 | G105: =F105*(1+IF(G$3<=$O$2,$D105,$D105-($D105-$I$103)*MIN(G$3-$O$2,$Q$2)/$Q$2)) -> 3613.2812 | H105: =G105*(1+IF(H$3<=$O$2,$D105,$D105-($D105-$I$103)*MIN(H$3-$O$2,$Q$2)/$Q$2)) -> 4516.6016 | I105: =H105*(1+IF(I$3<=$O$2,$D105,$D105-($D105-$I$103)*MIN(I$3-$O$2,$Q$2)/$Q$2)) -> 5645.752 | J105: =I105*(1+IF(J$3<=$O$2,$D105,$D105-($D105-$I$103)*MIN(J$3-$O$2,$Q$2)/$Q$2)) -> 6803.1311 | K105: =J105*(1+IF(K$3<=$O$2,$D105,$D105-($D105-$I$103)*MIN(K$3-$O$2,$Q$2)/$Q$2)) -> 7891.6321 | L105: =K105*(1+IF(L$3<=$O$2,$D105,$D105-($D105-$I$103)*MIN(L$3-$O$2,$Q$2)/$Q$2)) -> 8799.1698 | M105: =L105*(1+IF(M$3<=$O$2,$D105,$D105-($D105-$I$103)*MIN(M$3-$O$2,$Q$2)/$Q$2)) -> 9415.1117 | N105: =M105*(1+IF(N$3<=$O$2,$D105,$D105-($D105-$I$103)*MIN(N$3-$O$2,$Q$2)/$Q$2)) -> 9650.4894 | O105: =SUMPRODUCT(E105:N105,1/(1+$F$103)^$E$3:$N$3)*$E$2 -> 15755.173 | P105: =N105*$E$2*(1+$I$103)/($F$103-$I$103)/(1+$F$103)^$N$3 -> 74139.573 | Q105: =O105+P105 -> 89894.745 | R105: =Q105-$G$2+$I$2 -> 88342.045 | S105: =R105/$K$2 -> 320.78886 | T105: =S105-$M$2 -> 266.28434
A106: 2 | B106: =IF(T105>0,B105,D105) -> -0.5 | C106: =IF(T105>0,D105,C105) -> 0.25 | D106: =(B106+C106)/2 -> -0.125 | E106: =$C$2*(1+IF(E$3<=$O$2,$D106,$D106-($D106-$I$103)*MIN(E$3-$O$2,$Q$2)/$Q$2)) -> 1618.75 | F106: =E106*(1+IF(F$3<=$O$2,$D106,$D106-($D106-$I$103)*MIN(F$3-$O$2,$Q$2)/$Q$2)) -> 1416.4062 | G106: =F106*(1+IF(G$3<=$O$2,$D106,$D106-($D106-$I$103)*MIN(G$3-$O$2,$Q$2)/$Q$2)) -> 1239.3555 | H106: =G106*(1+IF(H$3<=$O$2,$D106,$D106-($D106-$I$103)*MIN(H$3-$O$2,$Q$2)/$Q$2)) -> 1084.436 | I106: =H106*(1+IF(I$3<=$O$2,$D106,$D106-($D106-$I$103)*MIN(I$3-$O$2,$Q$2)/$Q$2)) -> 948.88153 | J106: =I106*(1+IF(J$3<=$O$2,$D106,$D106-($D106-$I$103)*MIN(J$3-$O$2,$Q$2)/$Q$2)) -> 858.73779 | K106: =J106*(1+IF(K$3<=$O$2,$D106,$D106-($D106-$I$103)*MIN(K$3-$O$2,$Q$2)/$Q$2)) -> 802.91983 | L106: =K106*(1+IF(L$3<=$O$2,$D106,$D106-($D106-$I$103)*MIN(L$3-$O$2,$Q$2)/$Q$2)) -> 774.81764 | M106: =L106*(1+IF(M$3<=$O$2,$D106,$D106-($D106-$I$103)*MIN(M$3-$O$2,$Q$2)/$Q$2)) -> 770.94355 | N106: =M106*(1+IF(N$3<=$O$2,$D106,$D106-($D106-$I$103)*MIN(N$3-$O$2,$Q$2)/$Q$2)) -> 790.21714 | O106: =SUMPRODUCT(E106:N106,1/(1+$F$103)^$E$3:$N$3)*$E$2 -> 2926.3961 | P106: =N106*$E$2*(1+$I$103)/($F$103-$I$103)/(1+$F$103)^$N$3 -> 6070.8176 | Q106: =O106+P106 -> 8997.2136 | R106: =Q106-$G$2+$I$2 -> 7444.5136 | S106: =R106/$K$2 -> 27.032621 | T106: =S106-$M$2 -> -27.471899
A107: 3 | B107: =IF(T106>0,B106,D106) -> -0.125 | C107: =IF(T106>0,D106,C106) -> 0.25 | D107: =(B107+C107)/2 -> 0.0625 | E107: =$C$2*(1+IF(E$3<=$O$2,$D107,$D107-($D107-$I$103)*MIN(E$3-$O$2,$Q$2)/$Q$2)) -> 1965.625 | F107: =E107*(1+IF(F$3<=$O$2,$D107,$D107-($D107-$I$103)*MIN(F$3-$O$2,$Q$2)/$Q$2)) -> 2088.4766 | G107: =F107*(1+IF(G$3<=$O$2,$D107,$D107-($D107-$I$103)*MIN(G$3-$O$2,$Q$2)/$Q$2)) -> 2219.0063 | H107: =G107*(1+IF(H$3<=$O$2,$D107,$D107-($D107-$I$103)*MIN(H$3-$O$2,$Q$2)/$Q$2)) -> 2357.6942 | I107: =H107*(1+IF(I$3<=$O$2,$D107,$D107-($D107-$I$103)*MIN(I$3-$O$2,$Q$2)/$Q$2)) -> 2505.0501 | J107: =I107*(1+IF(J$3<=$O$2,$D107,$D107-($D107-$I$103)*MIN(J$3-$O$2,$Q$2)/$Q$2)) -> 2642.8279 | K107: =J107*(1+IF(K$3<=$O$2,$D107,$D107-($D107-$I$103)*MIN(K$3-$O$2,$Q$2)/$Q$2)) -> 2768.3622 | L107: =K107*(1+IF(L$3<=$O$2,$D107,$D107-($D107-$I$103)*MIN(L$3-$O$2,$Q$2)/$Q$2)) -> 2879.0967 | M107: =L107*(1+IF(M$3<=$O$2,$D107,$D107-($D107-$I$103)*MIN(M$3-$O$2,$Q$2)/$Q$2)) -> 2972.6673 | N107: =M107*(1+IF(N$3<=$O$2,$D107,$D107-($D107-$I$103)*MIN(N$3-$O$2,$Q$2)/$Q$2)) -> 3046.984 | O107: =SUMPRODUCT(E107:N107,1/(1+$F$103)^$E$3:$N$3)*$E$2 -> 6805.3988 | P107: =N107*$E$2*(1+$I$103)/($F$103-$I$103)/(1+$F$103)^$N$3 -> 23408.356 | Q107: =O107+P107 -> 30213.755 | R107: =Q107-$G$2+$I$2 -> 28661.055 | S107: =R107/$K$2 -> 104.07442 | T107: =S107-$M$2 -> 49.569901
A108: 4 | B108: =IF(T107>0,B107,D107) -> -0.125 | C108: =IF(T107>0,D107,C107) -> 0.0625 | D108: =(B108+C108)/2 -> -0.03125 | E108: =$C$2*(1+IF(E$3<=$O$2,$D108,$D108-($D108-$I$103)*MIN(E$3-$O$2,$Q$2)/$Q$2)) -> 1792.1875 | F108: =E108*(1+IF(F$3<=$O$2,$D108,$D108-($D108-$I$103)*MIN(F$3-$O$2,$Q$2)/$Q$2)) -> 1736.1816 | G108: =F108*(1+IF(G$3<=$O$2,$D108,$D108-($D108-$I$103)*MIN(G$3-$O$2,$Q$2)/$Q$2)) -> 1681.926 | H108: =G108*(1+IF(H$3<=$O$2,$D108,$D108-($D108-$I$103)*MIN(H$3-$O$2,$Q$2)/$Q$2)) -> 1629.3658 | I108: =H108*(1+IF(I$3<=$O$2,$D108,$D108-($D108-$I$103)*MIN(I$3-$O$2,$Q$2)/$Q$2)) -> 1578.4481 | J108: =I108*(1+IF(J$3<=$O$2,$D108,$D108-($D108-$I$103)*MIN(J$3-$O$2,$Q$2)/$Q$2)) -> 1546.8791 | K108: =J108*(1+IF(K$3<=$O$2,$D108,$D108-($D108-$I$103)*MIN(K$3-$O$2,$Q$2)/$Q$2)) -> 1533.3439 | L108: =K108*(1+IF(L$3<=$O$2,$D108,$D108-($D108-$I$103)*MIN(L$3-$O$2,$Q$2)/$Q$2)) -> 1537.1773 | M108: =L108*(1+IF(M$3<=$O$2,$D108,$D108-($D108-$I$103)*MIN(M$3-$O$2,$Q$2)/$Q$2)) -> 1558.3135 | N108: =M108*(1+IF(N$3<=$O$2,$D108,$D108-($D108-$I$103)*MIN(N$3-$O$2,$Q$2)/$Q$2)) -> 1597.2713 | O108: =SUMPRODUCT(E108:N108,1/(1+$F$103)^$E$3:$N$3)*$E$2 -> 4453.4432 | P108: =N108*$E$2*(1+$I$103)/($F$103-$I$103)/(1+$F$103)^$N$3 -> 12270.985 | Q108: =O108+P108 -> 16724.428 | R108: =Q108-$G$2+$I$2 -> 15171.728 | S108: =R108/$K$2 -> 55.091792 | T108: =S108-$M$2 -> 0.5872707
A109: 5 | B109: =IF(T108>0,B108,D108) -> -0.125 | C109: =IF(T108>0,D108,C108) -> -0.03125 | D109: =(B109+C109)/2 -> -0.078125 | E109: =$C$2*(1+IF(E$3<=$O$2,$D109,$D109-($D109-$I$103)*MIN(E$3-$O$2,$Q$2)/$Q$2)) -> 1705.4688 | F109: =E109*(1+IF(F$3<=$O$2,$D109,$D109-($D109-$I$103)*MIN(F$3-$O$2,$Q$2)/$Q$2)) -> 1572.229 | G109: =F109*(1+IF(G$3<=$O$2,$D109,$D109-($D109-$I$103)*MIN(G$3-$O$2,$Q$2)/$Q$2)) -> 1449.3986 | H109: =G109*(1+IF(H$3<=$O$2,$D109,$D109-($D109-$I$103)*MIN(H$3-$O$2,$Q$2)/$Q$2)) -> 1336.1643 | I109: =H109*(1+IF(I$3<=$O$2,$D109,$D109-($D109-$I$103)*MIN(I$3-$O$2,$Q$2)/$Q$2)) -> 1231.7765 | J109: =I109*(1+IF(J$3<=$O$2,$D109,$D109-($D109-$I$103)*MIN(J$3-$O$2,$Q$2)/$Q$2)) -> 1160.9494 | K109: =J109*(1+IF(K$3<=$O$2,$D109,$D109-($D109-$I$103)*MIN(K$3-$O$2,$Q$2)/$Q$2)) -> 1118.1394 | L109: =K109*(1+IF(L$3<=$O$2,$D109,$D109-($D109-$I$103)*MIN(L$3-$O$2,$Q$2)/$Q$2)) -> 1099.9696 | M109: =L109*(1+IF(M$3<=$O$2,$D109,$D109-($D109-$I$103)*MIN(M$3-$O$2,$Q$2)/$Q$2)) -> 1104.782 | N109: =M109*(1+IF(N$3<=$O$2,$D109,$D109-($D109-$I$103)*MIN(N$3-$O$2,$Q$2)/$Q$2)) -> 1132.4015 | O109: =SUMPRODUCT(E109:N109,1/(1+$F$103)^$E$3:$N$3)*$E$2 -> 3606.8646 | P109: =N109*$E$2*(1+$I$103)/($F$103-$I$103)/(1+$F$103)^$N$3 -> 8699.6379 | Q109: =O109+P109 -> 12306.502 | R109: =Q109-$G$2+$I$2 -> 10753.802 | S109: =R109/$K$2 -> 39.049357 | T109: =S109-$M$2 -> -15.455164
A110: 6 | B110: =IF(T109>0,B109,D109) -> -0.078125 | C110: =IF(T109>0,D109,C109) -> -0.03125 | D110: =(B110+C110)/2 -> -0.0546875 | E110: =$C$2*(1+IF(E$3<=$O$2,$D110,$D110-($D110-$I$103)*MIN(E$3-$O$2,$Q$2)/$Q$2)) -> 1748.8281 | F110: =E110*(1+IF(F$3<=$O$2,$D110,$D110-($D110-$I$103)*MIN(F$3-$O$2,$Q$2)/$Q$2)) -> 1653.1891 | G110: =F110*(1+IF(G$3<=$O$2,$D110,$D110-($D110-$I$103)*MIN(G$3-$O$2,$Q$2)/$Q$2)) -> 1562.7803 | H110: =G110*(1+IF(H$3<=$O$2,$D110,$D110-($D110-$I$103)*MIN(H$3-$O$2,$Q$2)/$Q$2)) -> 1477.3158 | I110: =H110*(1+IF(I$3<=$O$2,$D110,$D110-($D110-$I$103)*MIN(I$3-$O$2,$Q$2)/$Q$2)) -> 1396.5251 | J110: =I110*(1+IF(J$3<=$O$2,$D110,$D110-($D110-$I$103)*MIN(J$3-$O$2,$Q$2)/$Q$2)) -> 1342.4097 | K110: =J110*(1+IF(K$3<=$O$2,$D110,$D110-($D110-$I$103)*MIN(K$3-$O$2,$Q$2)/$Q$2)) -> 1311.786 | L110: =K110*(1+IF(L$3<=$O$2,$D110,$D110-($D110-$I$103)*MIN(L$3-$O$2,$Q$2)/$Q$2)) -> 1302.7675 | M110: =L110*(1+IF(M$3<=$O$2,$D110,$D110-($D110-$I$103)*MIN(M$3-$O$2,$Q$2)/$Q$2)) -> 1314.5738 | N110: =M110*(1+IF(N$3<=$O$2,$D110,$D110-($D110-$I$103)*MIN(N$3-$O$2,$Q$2)/$Q$2)) -> 1347.4381 | O110: =SUMPRODUCT(E110:N110,1/(1+$F$103)^$E$3:$N$3)*$E$2 -> 4007.1618 | P110: =N110*$E$2*(1+$I$103)/($F$103-$I$103)/(1+$F$103)^$N$3 -> 10351.65 | Q110: =O110+P110 -> 14358.812 | R110: =Q110-$G$2+$I$2 -> 12806.112 | S110: =R110/$K$2 -> 46.501731 | T110: =S110-$M$2 -> -8.0027899
A111: 7 | B111: =IF(T110>0,B110,D110) -> -0.0546875 | C111: =IF(T110>0,D110,C110) -> -0.03125 | D111: =(B111+C111)/2 -> -0.04296875 | E111: =$C$2*(1+IF(E$3<=$O$2,$D111,$D111-($D111-$I$103)*MIN(E$3-$O$2,$Q$2)/$Q$2)) -> 1770.5078 | F111: =E111*(1+IF(F$3<=$O$2,$D111,$D111-($D111-$I$103)*MIN(F$3-$O$2,$Q$2)/$Q$2)) -> 1694.4313 | G111: =F111*(1+IF(G$3<=$O$2,$D111,$D111-($D111-$I$103)*MIN(G$3-$O$2,$Q$2)/$Q$2)) -> 1621.6237 | H111: =G111*(1+IF(H$3<=$O$2,$D111,$D111-($D111-$I$103)*MIN(H$3-$O$2,$Q$2)/$Q$2)) -> 1551.9446 | I111: =H111*(1+IF(I$3<=$O$2,$D111,$D111-($D111-$I$103)*MIN(I$3-$O$2,$Q$2)/$Q$2)) -> 1485.2594 | J111: =I111*(1+IF(J$3<=$O$2,$D111,$D111-($D111-$I$103)*MIN(J$3-$O$2,$Q$2)/$Q$2)) -> 1441.63 | K111: =J111*(1+IF(K$3<=$O$2,$D111,$D111-($D111-$I$103)*MIN(K$3-$O$2,$Q$2)/$Q$2)) -> 1418.8792 | L111: =K111*(1+IF(L$3<=$O$2,$D111,$D111-($D111-$I$103)*MIN(L$3-$O$2,$Q$2)/$Q$2)) -> 1415.7754 | M111: =L111*(1+IF(M$3<=$O$2,$D111,$D111-($D111-$I$103)*MIN(M$3-$O$2,$Q$2)/$Q$2)) -> 1431.9241 | N111: =M111*(1+IF(N$3<=$O$2,$D111,$D111-($D111-$I$103)*MIN(N$3-$O$2,$Q$2)/$Q$2)) -> 1467.7222 | O111: =SUMPRODUCT(E111:N111,1/(1+$F$103)^$E$3:$N$3)*$E$2 -> 4224.2532 | P111: =N111*$E$2*(1+$I$103)/($F$103-$I$103)/(1+$F$103)^$N$3 -> 11275.728 | Q111: =O111+P111 -> 15499.982 | R111: =Q111-$G$2+$I$2 -> 13947.282 | S111: =R111/$K$2 -> 50.645563 | T111: =S111-$M$2 -> -3.8589576
A112: 8 | B112: =IF(T111>0,B111,D111) -> -0.04296875 | C112: =IF(T111>0,D111,C111) -> -0.03125 | D112: =(B112+C112)/2 -> -0.037109375 | E112: =$C$2*(1+IF(E$3<=$O$2,$D112,$D112-($D112-$I$103)*MIN(E$3-$O$2,$Q$2)/$Q$2)) -> 1781.3477 | F112: =E112*(1+IF(F$3<=$O$2,$D112,$D112-($D112-$I$103)*MIN(F$3-$O$2,$Q$2)/$Q$2)) -> 1715.243 | G112: =F112*(1+IF(G$3<=$O$2,$D112,$D112-($D112-$I$103)*MIN(G$3-$O$2,$Q$2)/$Q$2)) -> 1651.5914 | H112: =G112*(1+IF(H$3<=$O$2,$D112,$D112-($D112-$I$103)*MIN(H$3-$O$2,$Q$2)/$Q$2)) -> 1590.3018 | I112: =H112*(1+IF(I$3<=$O$2,$D112,$D112-($D112-$I$103)*MIN(I$3-$O$2,$Q$2)/$Q$2)) -> 1531.2867 | J112: =I112*(1+IF(J$3<=$O$2,$D112,$D112-($D112-$I$103)*MIN(J$3-$O$2,$Q$2)/$Q$2)) -> 1493.4831 | K112: =J112*(1+IF(K$3<=$O$2,$D112,$D112-($D112-$I$103)*MIN(K$3-$O$2,$Q$2)/$Q$2)) -> 1475.1646 | L112: =K112*(1+IF(L$3<=$O$2,$D112,$D112-($D112-$I$103)*MIN(L$3-$O$2,$Q$2)/$Q$2)) -> 1475.3951 | M112: =L112*(1+IF(M$3<=$O$2,$D112,$D112-($D112-$I$103)*MIN(M$3-$O$2,$Q$2)/$Q$2)) -> 1493.9528 | N112: =M112*(1+IF(N$3<=$O$2,$D112,$D112-($D112-$I$103)*MIN(N$3-$O$2,$Q$2)/$Q$2)) -> 1531.3016 | O112: =SUMPRODUCT(E112:N112,1/(1+$F$103)^$E$3:$N$3)*$E$2 -> 4337.2967 | P112: =N112*$E$2*(1+$I$103)/($F$103-$I$103)/(1+$F$103)^$N$3 -> 11764.175 | Q112: =O112+P112 -> 16101.472 | R112: =Q112-$G$2+$I$2 -> 14548.772 | S112: =R112/$K$2 -> 52.829702 | T112: =S112-$M$2 -> -1.6748185
A113: 9 | B113: =IF(T112>0,B112,D112) -> -0.037109375 | C113: =IF(T112>0,D112,C112) -> -0.03125 | D113: =(B113+C113)/2 -> -0.034179688 | E113: =$C$2*(1+IF(E$3<=$O$2,$D113,$D113-($D113-$I$103)*MIN(E$3-$O$2,$Q$2)/$Q$2)) -> 1786.7676 | F113: =E113*(1+IF(F$3<=$O$2,$D113,$D113-($D113-$I$103)*MIN(F$3-$O$2,$Q$2)/$Q$2)) -> 1725.6964 | G113: =F113*(1+IF(G$3<=$O$2,$D113,$D113-($D113-$I$103)*MIN(G$3-$O$2,$Q$2)/$Q$2)) -> 1666.7127 | H113: =G113*(1+IF(H$3<=$O$2,$D113,$D113-($D113-$I$103)*MIN(H$3-$O$2,$Q$2)/$Q$2)) -> 1609.7449 | I113: =H113*(1+IF(I$3<=$O$2,$D113,$D113-($D113-$I$103)*MIN(I$3-$O$2,$Q$2)/$Q$2)) -> 1554.7244 | J113: =I113*(1+IF(J$3<=$O$2,$D113,$D113-($D113-$I$103)*MIN(J$3-$O$2,$Q$2)/$Q$2)) -> 1519.986 | K113: =J113*(1+IF(K$3<=$O$2,$D113,$D113-($D113-$I$103)*MIN(K$3-$O$2,$Q$2)/$Q$2)) -> 1504.0143 | L113: =K113*(1+IF(L$3<=$O$2,$D113,$D113-($D113-$I$103)*MIN(L$3-$O$2,$Q$2)/$Q$2)) -> 1506.0118 | M113: =L113*(1+IF(M$3<=$O$2,$D113,$D113-($D113-$I$103)*MIN(M$3-$O$2,$Q$2)/$Q$2)) -> 1525.837 | N113: =M113*(1+IF(N$3<=$O$2,$D113,$D113-($D113-$I$103)*MIN(N$3-$O$2,$Q$2)/$Q$2)) -> 1563.9829 | O113: =SUMPRODUCT(E113:N113,1/(1+$F$103)^$E$3:$N$3)*$E$2 -> 4394.9771 | P113: =N113*$E$2*(1+$I$103)/($F$103-$I$103)/(1+$F$103)^$N$3 -> 12015.248 | Q113: =O113+P113 -> 16410.225 | R113: =Q113-$G$2+$I$2 -> 14857.525 | S113: =R113/$K$2 -> 53.950853 | T113: =S113-$M$2 -> -0.553668
A114: 10 | B114: =IF(T113>0,B113,D113) -> -0.034179688 | C114: =IF(T113>0,D113,C113) -> -0.03125 | D114: =(B114+C114)/2 -> -0.032714844 | E114: =$C$2*(1+IF(E$3<=$O$2,$D114,$D114-($D114-$I$103)*MIN(E$3-$O$2,$Q$2)/$Q$2)) -> 1789.4775 | F114: =E114*(1+IF(F$3<=$O$2,$D114,$D114-($D114-$I$103)*MIN(F$3-$O$2,$Q$2)/$Q$2)) -> 1730.9351 | G114: =F114*(1+IF(G$3<=$O$2,$D114,$D114-($D114-$I$103)*MIN(G$3-$O$2,$Q$2)/$Q$2)) -> 1674.3078 | H114: =G114*(1+IF(H$3<=$O$2,$D114,$D114-($D114-$I$103)*MIN(H$3-$O$2,$Q$2)/$Q$2)) -> 1619.5331 | I114: =H114*(1+IF(I$3<=$O$2,$D114,$D114-($D114-$I$103)*MIN(I$3-$O$2,$Q$2)/$Q$2)) -> 1566.5503 | J114: =I114*(1+IF(J$3<=$O$2,$D114,$D114-($D114-$I$103)*MIN(J$3-$O$2,$Q$2)/$Q$2)) -> 1533.3835 | K114: =J114*(1+IF(K$3<=$O$2,$D114,$D114-($D114-$I$103)*MIN(K$3-$O$2,$Q$2)/$Q$2)) -> 1518.6187 | L114: =K114*(1+IF(L$3<=$O$2,$D114,$D114-($D114-$I$103)*MIN(L$3-$O$2,$Q$2)/$Q$2)) -> 1521.5254 | M114: =L114*(1+IF(M$3<=$O$2,$D114,$D114-($D114-$I$103)*MIN(M$3-$O$2,$Q$2)/$Q$2)) -> 1542.0006 | N114: =M114*(1+IF(N$3<=$O$2,$D114,$D114-($D114-$I$103)*MIN(N$3-$O$2,$Q$2)/$Q$2)) -> 1580.5507 | O114: =SUMPRODUCT(E114:N114,1/(1+$F$103)^$E$3:$N$3)*$E$2 -> 4424.1113 | P114: =N114*$E$2*(1+$I$103)/($F$103-$I$103)/(1+$F$103)^$N$3 -> 12142.529 | Q114: =O114+P114 -> 16566.641 | R114: =Q114-$G$2+$I$2 -> 15013.941 | S114: =R114/$K$2 -> 54.51883 | T114: =S114-$M$2 -> 0.014308824
A115: 11 | B115: =IF(T114>0,B114,D114) -> -0.034179688 | C115: =IF(T114>0,D114,C114) -> -0.032714844 | D115: =(B115+C115)/2 -> -0.033447266 | E115: =$C$2*(1+IF(E$3<=$O$2,$D115,$D115-($D115-$I$103)*MIN(E$3-$O$2,$Q$2)/$Q$2)) -> 1788.1226 | F115: =E115*(1+IF(F$3<=$O$2,$D115,$D115-($D115-$I$103)*MIN(F$3-$O$2,$Q$2)/$Q$2)) -> 1728.3147 | G115: =F115*(1+IF(G$3<=$O$2,$D115,$D115-($D115-$I$103)*MIN(G$3-$O$2,$Q$2)/$Q$2)) -> 1670.5073 | H115: =G115*(1+IF(H$3<=$O$2,$D115,$D115-($D115-$I$103)*MIN(H$3-$O$2,$Q$2)/$Q$2)) -> 1614.6334 | I115: =H115*(1+IF(I$3<=$O$2,$D115,$D115-($D115-$I$103)*MIN(I$3-$O$2,$Q$2)/$Q$2)) -> 1560.6284 | J115: =I115*(1+IF(J$3<=$O$2,$D115,$D115-($D115-$I$103)*MIN(J$3-$O$2,$Q$2)/$Q$2)) -> 1526.6725 | K115: =J115*(1+IF(K$3<=$O$2,$D115,$D115-($D115-$I$103)*MIN(K$3-$O$2,$Q$2)/$Q$2)) -> 1511.3014 | L115: =K115*(1+IF(L$3<=$O$2,$D115,$D115-($D115-$I$103)*MIN(L$3-$O$2,$Q$2)/$Q$2)) -> 1513.7514 | M115: =L115*(1+IF(M$3<=$O$2,$D115,$D115-($D115-$I$103)*MIN(M$3-$O$2,$Q$2)/$Q$2)) -> 1533.9002 | N115: =M115*(1+IF(N$3<=$O$2,$D115,$D115-($D115-$I$103)*MIN(N$3-$O$2,$Q$2)/$Q$2)) -> 1572.2477 | O115: =SUMPRODUCT(E115:N115,1/(1+$F$103)^$E$3:$N$3)*$E$2 -> 4409.5195 | P115: =N115*$E$2*(1+$I$103)/($F$103-$I$103)/(1+$F$103)^$N$3 -> 12078.742 | Q115: =O115+P115 -> 16488.262 | R115: =Q115-$G$2+$I$2 -> 14935.562 | S115: =R115/$K$2 -> 54.234221 | T115: =S115-$M$2 -> -0.27030034
A116: 12 | B116: =IF(T115>0,B115,D115) -> -0.033447266 | C116: =IF(T115>0,D115,C115) -> -0.032714844 | D116: =(B116+C116)/2 -> -0.033081055 | E116: =$C$2*(1+IF(E$3<=$O$2,$D116,$D116-($D116-$I$103)*MIN(E$3-$O$2,$Q$2)/$Q$2)) -> 1788.8 | F116: =E116*(1+IF(F$3<=$O$2,$D116,$D116-($D116-$I$103)*MIN(F$3-$O$2,$Q$2)/$Q$2)) -> 1729.6247 | G116: =F116*(1+IF(G$3<=$O$2,$D116,$D116-($D116-$I$103)*MIN(G$3-$O$2,$Q$2)/$Q$2)) -> 1672.4068 | H116: =G116*(1+IF(H$3<=$O$2,$D116,$D116-($D116-$I$103)*MIN(H$3-$O$2,$Q$2)/$Q$2)) -> 1617.0819 | I116: =H116*(1+IF(I$3<=$O$2,$D116,$D116-($D116-$I$103)*MIN(I$3-$O$2,$Q$2)/$Q$2)) -> 1563.5871 | J116: =I116*(1+IF(J$3<=$O$2,$D116,$D116-($D116-$I$103)*MIN(J$3-$O$2,$Q$2)/$Q$2)) -> 1530.0249 | K116: =J116*(1+IF(K$3<=$O$2,$D116,$D116-($D116-$I$103)*MIN(K$3-$O$2,$Q$2)/$Q$2)) -> 1514.9563 | L116: =K116*(1+IF(L$3<=$O$2,$D116,$D116-($D116-$I$103)*MIN(L$3-$O$2,$Q$2)/$Q$2)) -> 1517.6341 | M116: =L116*(1+IF(M$3<=$O$2,$D116,$D116-($D116-$I$103)*MIN(M$3-$O$2,$Q$2)/$Q$2)) -> 1537.9458 | N116: =M116*(1+IF(N$3<=$O$2,$D116,$D116-($D116-$I$103)*MIN(N$3-$O$2,$Q$2)/$Q$2)) -> 1576.3944 | O116: =SUMPRODUCT(E116:N116,1/(1+$F$103)^$E$3:$N$3)*$E$2 -> 4416.8093 | P116: =N116*$E$2*(1+$I$103)/($F$103-$I$103)/(1+$F$103)^$N$3 -> 12110.599 | Q116: =O116+P116 -> 16527.408 | R116: =Q116-$G$2+$I$2 -> 14974.708 | S116: =R116/$K$2 -> 54.37637 | T116: =S116-$M$2 -> -0.12815124
A117: 13 | B117: =IF(T116>0,B116,D116) -> -0.033081055 | C117: =IF(T116>0,D116,C116) -> -0.032714844 | D117: =(B117+C117)/2 -> -0.032897949 | E117: =$C$2*(1+IF(E$3<=$O$2,$D117,$D117-($D117-$I$103)*MIN(E$3-$O$2,$Q$2)/$Q$2)) -> 1789.1388 | F117: =E117*(1+IF(F$3<=$O$2,$D117,$D117-($D117-$I$103)*MIN(F$3-$O$2,$Q$2)/$Q$2)) -> 1730.2798 | G117: =F117*(1+IF(G$3<=$O$2,$D117,$D117-($D117-$I$103)*MIN(G$3-$O$2,$Q$2)/$Q$2)) -> 1673.3571 | H117: =G117*(1+IF(H$3<=$O$2,$D117,$D117-($D117-$I$103)*MIN(H$3-$O$2,$Q$2)/$Q$2)) -> 1618.3071 | I117: =H117*(1+IF(I$3<=$O$2,$D117,$D117-($D117-$I$103)*MIN(I$3-$O$2,$Q$2)/$Q$2)) -> 1565.0681 | J117: =I117*(1+IF(J$3<=$O$2,$D117,$D117-($D117-$I$103)*MIN(J$3-$O$2,$Q$2)/$Q$2)) -> 1531.7035 | K117: =J117*(1+IF(K$3<=$O$2,$D117,$D117-($D117-$I$103)*MIN(K$3-$O$2,$Q$2)/$Q$2)) -> 1516.7865 | L117: =K117*(1+IF(L$3<=$O$2,$D117,$D117-($D117-$I$103)*MIN(L$3-$O$2,$Q$2)/$Q$2)) -> 1519.5787 | M117: =L117*(1+IF(M$3<=$O$2,$D117,$D117-($D117-$I$103)*MIN(M$3-$O$2,$Q$2)/$Q$2)) -> 1539.972 | N117: =M117*(1+IF(N$3<=$O$2,$D117,$D117-($D117-$I$103)*MIN(N$3-$O$2,$Q$2)/$Q$2)) -> 1578.4713 | O117: =SUMPRODUCT(E117:N117,1/(1+$F$103)^$E$3:$N$3)*$E$2 -> 4420.4587 | P117: =N117*$E$2*(1+$I$103)/($F$103-$I$103)/(1+$F$103)^$N$3 -> 12126.555 | Q117: =O117+P117 -> 16547.014 | R117: =Q117-$G$2+$I$2 -> 14994.314 | S117: =R117/$K$2 -> 54.447561 | T117: =S117-$M$2 -> -0.056960116
... A128: 24 | B128: =IF(T127>0,B127,D127) -> -0.032751679 | C128: =IF(T127>0,D127,C127) -> -0.032751501 | D128: =(B128+C128)/2 -> -0.03275159 | E128: =$C$2*(1+IF(E$3<=$O$2,$D128,$D128-($D128-$I$103)*MIN(E$3-$O$2,$Q$2)/$Q$2)) -> 1789.4096 | F128: =E128*(1+IF(F$3<=$O$2,$D128,$D128-($D128-$I$103)*MIN(F$3-$O$2,$Q$2)/$Q$2)) -> 1730.8036 | G128: =F128*(1+IF(G$3<=$O$2,$D128,$D128-($D128-$I$103)*MIN(G$3-$O$2,$Q$2)/$Q$2)) -> 1674.117 | H128: =G128*(1+IF(H$3<=$O$2,$D128,$D128-($D128-$I$103)*MIN(H$3-$O$2,$Q$2)/$Q$2)) -> 1619.287 | I128: =H128*(1+IF(I$3<=$O$2,$D128,$D128-($D128-$I$103)*MIN(I$3-$O$2,$Q$2)/$Q$2)) -> 1566.2528 | J128: =I128*(1+IF(J$3<=$O$2,$D128,$D128-($D128-$I$103)*MIN(J$3-$O$2,$Q$2)/$Q$2)) -> 1533.0462 | K128: =J128*(1+IF(K$3<=$O$2,$D128,$D128-($D128-$I$103)*MIN(K$3-$O$2,$Q$2)/$Q$2)) -> 1518.2509 | L128: =K128*(1+IF(L$3<=$O$2,$D128,$D128-($D128-$I$103)*MIN(L$3-$O$2,$Q$2)/$Q$2)) -> 1521.1346 | M128: =L128*(1+IF(M$3<=$O$2,$D128,$D128-($D128-$I$103)*MIN(M$3-$O$2,$Q$2)/$Q$2)) -> 1541.5933 | N128: =M128*(1+IF(N$3<=$O$2,$D128,$D128-($D128-$I$103)*MIN(N$3-$O$2,$Q$2)/$Q$2)) -> 1580.1332 | O128: =SUMPRODUCT(E128:N128,1/(1+$F$103)^$E$3:$N$3)*$E$2 -> 4423.378 | P128: =N128*$E$2*(1+$I$103)/($F$103-$I$103)/(1+$F$103)^$N$3 -> 12139.322 | Q128: =O128+P128 -> 16562.7 | R128: =Q128-$G$2+$I$2 -> 15010 | S128: =R128/$K$2 -> 54.504521 | T128: =S128-$M$2 -> 7.1863568e-08
A130: Grid block 5: row 1, column 4 of table A (24 steps) | E130: WACC | F130: =Sensitivity!$B$10 -> 0.053509306 | G130: Terminal growth | I130: =Sensitivity!$F$9 -> 0.03
A131: Step | B131: Low | C131: High | D131: Mid | E131: Rev Y1 | F131: Rev Y2 | G131: Rev Y3 | H131: Rev Y4 | I131: Rev Y5 | J131: Rev Y6 | K131: Rev Y7 | L131: Rev Y8 | M131: Rev Y9 | N131: Rev Y10 | O131: PV of FCF | P131: PV of TV | Q131: EV | R131: Equity | S131: Per share | T131: Value - price
A132: 1 | B132: -0.5 | C132: 1 | D132: =(B132+C132)/2 -> 0.25 | E132: =$C$2*(1+IF(E$3<=$O$2,$D132,$D132-($D132-$I$130)*MIN(E$3-$O$2,$Q$2)/$Q$2)) -> 2312.5 | F132: =E132*(1+IF(F$3<=$O$2,$D132,$D132-($D132-$I$130)*MIN(F$3-$O$2,$Q$2)/$Q$2)) -> 2890.625 | G132: =F132*(1+IF(G$3<=$O$2,$D132,$D132-($D132-$I$130)*MIN(G$3-$O$2,$Q$2)/$Q$2)) -> 3613.2812 | H132: =G132*(1+IF(H$3<=$O$2,$D132,$D132-($D132-$I$130)*MIN(H$3-$O$2,$Q$2)/$Q$2)) -> 4516.6016 | I132: =H132*(1+IF(I$3<=$O$2,$D132,$D132-($D132-$I$130)*MIN(I$3-$O$2,$Q$2)/$Q$2)) -> 5645.752 | J132: =I132*(1+IF(J$3<=$O$2,$D132,$D132-($D132-$I$130)*MIN(J$3-$O$2,$Q$2)/$Q$2)) -> 6808.7769 | K132: =J132*(1+IF(K$3<=$O$2,$D132,$D132-($D132-$I$130)*MIN(K$3-$O$2,$Q$2)/$Q$2)) -> 7911.7987 | L132: =K132*(1+IF(L$3<=$O$2,$D132,$D132-($D132-$I$130)*MIN(L$3-$O$2,$Q$2)/$Q$2)) -> 8845.391 | M132: =L132*(1+IF(M$3<=$O$2,$D132,$D132-($D132-$I$130)*MIN(M$3-$O$2,$Q$2)/$Q$2)) -> 9499.9499 | N132: =M132*(1+IF(N$3<=$O$2,$D132,$D132-($D132-$I$130)*MIN(N$3-$O$2,$Q$2)/$Q$2)) -> 9784.9484 | O132: =SUMPRODUCT(E132:N132,1/(1+$F$130)^$E$3:$N$3)*$E$2 -> 15820.488 | P132: =N132*$E$2*(1+$I$130)/($F$130-$I$130)/(1+$F$130)^$N$3 -> 91605.062 | Q132: =O132+P132 -> 107425.55 | R132: =Q132-$G$2+$I$2 -> 105872.85 | S132: =R132/$K$2 -> 384.44697 | T132: =S132-$M$2 -> 329.94245
A133: 2 | B133: =IF(T132>0,B132,D132) -> -0.5 | C133: =IF(T132>0,D132,C132) -> 0.25 | D133: =(B133+C133)/2 -> -0.125 | E133: =$C$2*(1+IF(E$3<=$O$2,$D133,$D133-($D133-$I$130)*MIN(E$3-$O$2,$Q$2)/$Q$2)) -> 1618.75 | F133: =E133*(1+IF(F$3<=$O$2,$D133,$D133-($D133-$I$130)*MIN(F$3-$O$2,$Q$2)/$Q$2)) -> 1416.4062 | G133: =F133*(1+IF(G$3<=$O$2,$D133,$D133-($D133-$I$130)*MIN(G$3-$O$2,$Q$2)/$Q$2)) -> 1239.3555 | H133: =G133*(1+IF(H$3<=$O$2,$D133,$D133-($D133-$I$130)*MIN(H$3-$O$2,$Q$2)/$Q$2)) -> 1084.436 | I133: =H133*(1+IF(I$3<=$O$2,$D133,$D133-($D133-$I$130)*MIN(I$3-$O$2,$Q$2)/$Q$2)) -> 948.88153 | J133: =I133*(1+IF(J$3<=$O$2,$D133,$D133-($D133-$I$130)*MIN(J$3-$O$2,$Q$2)/$Q$2)) -> 859.68667 | K133: =J133*(1+IF(K$3<=$O$2,$D133,$D133-($D133-$I$130)*MIN(K$3-$O$2,$Q$2)/$Q$2)) -> 805.52641 | L133: =K133*(1+IF(L$3<=$O$2,$D133,$D133-($D133-$I$130)*MIN(L$3-$O$2,$Q$2)/$Q$2)) -> 779.74956 | M133: =L133*(1+IF(M$3<=$O$2,$D133,$D133-($D133-$I$130)*MIN(M$3-$O$2,$Q$2)/$Q$2)) -> 778.96981 | N133: =M133*(1+IF(N$3<=$O$2,$D133,$D133-($D133-$I$130)*MIN(N$3-$O$2,$Q$2)/$Q$2)) -> 802.33891 | O133: =SUMPRODUCT(E133:N133,1/(1+$F$130)^$E$3:$N$3)*$E$2 -> 2932.8637 | P133: =N133*$E$2*(1+$I$130)/($F$130-$I$130)/(1+$F$130)^$N$3 -> 7511.3637 | Q133: =O133+P133 -> 10444.227 | R133: =Q133-$G$2+$I$2 -> 8891.5274 | S133: =R133/$K$2 -> 32.287038 | T133: =S133-$M$2 -> -22.217483
A134: 3 | B134: =IF(T133>0,B133,D133) -> -0.125 | C134: =IF(T133>0,D133,C133) -> 0.25 | D134: =(B134+C134)/2 -> 0.0625 | E134: =$C$2*(1+IF(E$3<=$O$2,$D134,$D134-($D134-$I$130)*MIN(E$3-$O$2,$Q$2)/$Q$2)) -> 1965.625 | F134: =E134*(1+IF(F$3<=$O$2,$D134,$D134-($D134-$I$130)*MIN(F$3-$O$2,$Q$2)/$Q$2)) -> 2088.4766 | G134: =F134*(1+IF(G$3<=$O$2,$D134,$D134-($D134-$I$130)*MIN(G$3-$O$2,$Q$2)/$Q$2)) -> 2219.0063 | H134: =G134*(1+IF(H$3<=$O$2,$D134,$D134-($D134-$I$130)*MIN(H$3-$O$2,$Q$2)/$Q$2)) -> 2357.6942 | I134: =H134*(1+IF(I$3<=$O$2,$D134,$D134-($D134-$I$130)*MIN(I$3-$O$2,$Q$2)/$Q$2)) -> 2505.0501 | J134: =I134*(1+IF(J$3<=$O$2,$D134,$D134-($D134-$I$130)*MIN(J$3-$O$2,$Q$2)/$Q$2)) -> 2645.3329 | K134: =J134*(1+IF(K$3<=$O$2,$D134,$D134-($D134-$I$130)*MIN(K$3-$O$2,$Q$2)/$Q$2)) -> 2776.2769 | L134: =K134*(1+IF(L$3<=$O$2,$D134,$D134-($D134-$I$130)*MIN(L$3-$O$2,$Q$2)/$Q$2)) -> 2895.6568 | M134: =L134*(1+IF(M$3<=$O$2,$D134,$D134-($D134-$I$130)*MIN(M$3-$O$2,$Q$2)/$Q$2)) -> 3001.3483 | N134: =M134*(1+IF(N$3<=$O$2,$D134,$D134-($D134-$I$130)*MIN(N$3-$O$2,$Q$2)/$Q$2)) -> 3091.3888 | O134: =SUMPRODUCT(E134:N134,1/(1+$F$130)^$E$3:$N$3)*$E$2 -> 6827.9079 | P134: =N134*$E$2*(1+$I$130)/($F$130-$I$130)/(1+$F$130)^$N$3 -> 28941.068 | Q134: =O134+P134 -> 35768.976 | R134: =Q134-$G$2+$I$2 -> 34216.276 | S134: =R134/$K$2 -> 124.24662 | T134: =S134-$M$2 -> 69.742098
A135: 4 | B135: =IF(T134>0,B134,D134) -> -0.125 | C135: =IF(T134>0,D134,C134) -> 0.0625 | D135: =(B135+C135)/2 -> -0.03125 | E135: =$C$2*(1+IF(E$3<=$O$2,$D135,$D135-($D135-$I$130)*MIN(E$3-$O$2,$Q$2)/$Q$2)) -> 1792.1875 | F135: =E135*(1+IF(F$3<=$O$2,$D135,$D135-($D135-$I$130)*MIN(F$3-$O$2,$Q$2)/$Q$2)) -> 1736.1816 | G135: =F135*(1+IF(G$3<=$O$2,$D135,$D135-($D135-$I$130)*MIN(G$3-$O$2,$Q$2)/$Q$2)) -> 1681.926 | H135: =G135*(1+IF(H$3<=$O$2,$D135,$D135-($D135-$I$130)*MIN(H$3-$O$2,$Q$2)/$Q$2)) -> 1629.3658 | I135: =H135*(1+IF(I$3<=$O$2,$D135,$D135-($D135-$I$130)*MIN(I$3-$O$2,$Q$2)/$Q$2)) -> 1578.4481 | J135: =I135*(1+IF(J$3<=$O$2,$D135,$D135-($D135-$I$130)*MIN(J$3-$O$2,$Q$2)/$Q$2)) -> 1548.4576 | K135: =J135*(1+IF(K$3<=$O$2,$D135,$D135-($D135-$I$130)*MIN(K$3-$O$2,$Q$2)/$Q$2)) -> 1538.0055 | L135: =K135*(1+IF(L$3<=$O$2,$D135,$D135-($D135-$I$130)*MIN(L$3-$O$2,$Q$2)/$Q$2)) -> 1546.4645 | M135: =L135*(1+IF(M$3<=$O$2,$D135,$D135-($D135-$I$130)*MIN(M$3-$O$2,$Q$2)/$Q$2)) -> 1573.9143 | N135: =M135*(1+IF(N$3<=$O$2,$D135,$D135-($D135-$I$130)*MIN(N$3-$O$2,$Q$2)/$Q$2)) -> 1621.1317 | O135: =SUMPRODUCT(E135:N135,1/(1+$F$130)^$E$3:$N$3)*$E$2 -> 4465.8363 | P135: =N135*$E$2*(1+$I$130)/($F$130-$I$130)/(1+$F$130)^$N$3 -> 15176.766 | Q135: =O135+P135 -> 19642.602 | R135: =Q135-$G$2+$I$2 -> 18089.902 | S135: =R135/$K$2 -> 65.688305 | T135: =S135-$M$2 -> 11.183784
A136: 5 | B136: =IF(T135>0,B135,D135) -> -0.125 | C136: =IF(T135>0,D135,C135) -> -0.03125 | D136: =(B136+C136)/2 -> -0.078125 | E136: =$C$2*(1+IF(E$3<=$O$2,$D136,$D136-($D136-$I$130)*MIN(E$3-$O$2,$Q$2)/$Q$2)) -> 1705.4688 | F136: =E136*(1+IF(F$3<=$O$2,$D136,$D136-($D136-$I$130)*MIN(F$3-$O$2,$Q$2)/$Q$2)) -> 1572.229 | G136: =F136*(1+IF(G$3<=$O$2,$D136,$D136-($D136-$I$130)*MIN(G$3-$O$2,$Q$2)/$Q$2)) -> 1449.3986 | H136: =G136*(1+IF(H$3<=$O$2,$D136,$D136-($D136-$I$130)*MIN(H$3-$O$2,$Q$2)/$Q$2)) -> 1336.1643 | I136: =H136*(1+IF(I$3<=$O$2,$D136,$D136-($D136-$I$130)*MIN(I$3-$O$2,$Q$2)/$Q$2)) -> 1231.7765 | J136: =I136*(1+IF(J$3<=$O$2,$D136,$D136-($D136-$I$130)*MIN(J$3-$O$2,$Q$2)/$Q$2)) -> 1162.1811 | K136: =J136*(1+IF(K$3<=$O$2,$D136,$D136-($D136-$I$130)*MIN(K$3-$O$2,$Q$2)/$Q$2)) -> 1121.6501 | L136: =K136*(1+IF(L$3<=$O$2,$D136,$D136-($D136-$I$130)*MIN(L$3-$O$2,$Q$2)/$Q$2)) -> 1106.7882 | M136: =L136*(1+IF(M$3<=$O$2,$D136,$D136-($D136-$I$130)*MIN(M$3-$O$2,$Q$2)/$Q$2)) -> 1116.0576 | N136: =M136*(1+IF(N$3<=$O$2,$D136,$D136-($D136-$I$130)*MIN(N$3-$O$2,$Q$2)/$Q$2)) -> 1149.5393 | O136: =SUMPRODUCT(E136:N136,1/(1+$F$130)^$E$3:$N$3)*$E$2 -> 3615.8833 | P136: =N136*$E$2*(1+$I$130)/($F$130-$I$130)/(1+$F$130)^$N$3 -> 10761.796 | Q136: =O136+P136 -> 14377.679 | R136: =Q136-$G$2+$I$2 -> 12824.979 | S136: =R136/$K$2 -> 46.570243 | T136: =S136-$M$2 -> -7.9342777
A137: 6 | B137: =IF(T136>0,B136,D136) -> -0.078125 | C137: =IF(T136>0,D136,C136) -> -0.03125 | D137: =(B137+C137)/2 -> -0.0546875 | E137: =$C$2*(1+IF(E$3<=$O$2,$D137,$D137-($D137-$I$130)*MIN(E$3-$O$2,$Q$2)/$Q$2)) -> 1748.8281 | F137: =E137*(1+IF(F$3<=$O$2,$D137,$D137-($D137-$I$130)*MIN(F$3-$O$2,$Q$2)/$Q$2)) -> 1653.1891 | G137: =F137*(1+IF(G$3<=$O$2,$D137,$D137-($D137-$I$130)*MIN(G$3-$O$2,$Q$2)/$Q$2)) -> 1562.7803 | H137: =G137*(1+IF(H$3<=$O$2,$D137,$D137-($D137-$I$130)*MIN(H$3-$O$2,$Q$2)/$Q$2)) -> 1477.3158 | I137: =H137*(1+IF(I$3<=$O$2,$D137,$D137-($D137-$I$130)*MIN(I$3-$O$2,$Q$2)/$Q$2)) -> 1396.5251 | J137: =I137*(1+IF(J$3<=$O$2,$D137,$D137-($D137-$I$130)*MIN(J$3-$O$2,$Q$2)/$Q$2)) -> 1343.8062 | K137: =J137*(1+IF(K$3<=$O$2,$D137,$D137-($D137-$I$130)*MIN(K$3-$O$2,$Q$2)/$Q$2)) -> 1315.8383 | L137: =K137*(1+IF(L$3<=$O$2,$D137,$D137-($D137-$I$130)*MIN(L$3-$O$2,$Q$2)/$Q$2)) -> 1310.7394 | M137: =L137*(1+IF(M$3<=$O$2,$D137,$D137-($D137-$I$130)*MIN(M$3-$O$2,$Q$2)/$Q$2)) -> 1327.8609 | N137: =M137*(1+IF(N$3<=$O$2,$D137,$D137-($D137-$I$130)*MIN(N$3-$O$2,$Q$2)/$Q$2)) -> 1367.6968 | O137: =SUMPRODUCT(E137:N137,1/(1+$F$130)^$E$3:$N$3)*$E$2 -> 4017.7525 | P137: =N137*$E$2*(1+$I$130)/($F$130-$I$130)/(1+$F$130)^$N$3 -> 12804.15 | Q137: =O137+P137 -> 16821.902 | R137: =Q137-$G$2+$I$2 -> 15269.202 | S137: =R137/$K$2 -> 55.445741 | T137: =S137-$M$2 -> 0.94121964
A138: 7 | B138: =IF(T137>0,B137,D137) -> -0.078125 | C138: =IF(T137>0,D137,C137) -> -0.0546875 | D138: =(B138+C138)/2 -> -0.06640625 | E138: =$C$2*(1+IF(E$3<=$O$2,$D138,$D138-($D138-$I$130)*MIN(E$3-$O$2,$Q$2)/$Q$2)) -> 1727.1484 | F138: =E138*(1+IF(F$3<=$O$2,$D138,$D138-($D138-$I$130)*MIN(F$3-$O$2,$Q$2)/$Q$2)) -> 1612.455 | G138: =F138*(1+IF(G$3<=$O$2,$D138,$D138-($D138-$I$130)*MIN(G$3-$O$2,$Q$2)/$Q$2)) -> 1505.3779 | H138: =G138*(1+IF(H$3<=$O$2,$D138,$D138-($D138-$I$130)*MIN(H$3-$O$2,$Q$2)/$Q$2)) -> 1405.4114 | I138: =H138*(1+IF(I$3<=$O$2,$D138,$D138-($D138-$I$130)*MIN(I$3-$O$2,$Q$2)/$Q$2)) -> 1312.0833 | J138: =I138*(1+IF(J$3<=$O$2,$D138,$D138-($D138-$I$130)*MIN(J$3-$O$2,$Q$2)/$Q$2)) -> 1250.2514 | K138: =J138*(1+IF(K$3<=$O$2,$D138,$D138-($D138-$I$130)*MIN(K$3-$O$2,$Q$2)/$Q$2)) -> 1215.4397 | L138: =K138*(1+IF(L$3<=$O$2,$D138,$D138-($D138-$I$130)*MIN(L$3-$O$2,$Q$2)/$Q$2)) -> 1205.0325 | M138: =L138*(1+IF(M$3<=$O$2,$D138,$D138-($D138-$I$130)*MIN(M$3-$O$2,$Q$2)/$Q$2)) -> 1217.9489 | N138: =M138*(1+IF(N$3<=$O$2,$D138,$D138-($D138-$I$130)*MIN(N$3-$O$2,$Q$2)/$Q$2)) -> 1254.4874 | O138: =SUMPRODUCT(E138:N138,1/(1+$F$130)^$E$3:$N$3)*$E$2 -> 3811.3373 | P138: =N138*$E$2*(1+$I$130)/($F$130-$I$130)/(1+$F$130)^$N$3 -> 11744.303 | Q138: =O138+P138 -> 15555.64 | R138: =Q138-$G$2+$I$2 -> 14002.94 | S138: =R138/$K$2 -> 50.847671 | T138: =S138-$M$2 -> -3.6568503
A139: 8 | B139: =IF(T138>0,B138,D138) -> -0.06640625 | C139: =IF(T138>0,D138,C138) -> -0.0546875 | D139: =(B139+C139)/2 -> -0.060546875 | E139: =$C$2*(1+IF(E$3<=$O$2,$D139,$D139-($D139-$I$130)*MIN(E$3-$O$2,$Q$2)/$Q$2)) -> 1737.9883 | F139: =E139*(1+IF(F$3<=$O$2,$D139,$D139-($D139-$I$130)*MIN(F$3-$O$2,$Q$2)/$Q$2)) -> 1632.7585 | G139: =F139*(1+IF(G$3<=$O$2,$D139,$D139-($D139-$I$130)*MIN(G$3-$O$2,$Q$2)/$Q$2)) -> 1533.9001 | H139: =G139*(1+IF(H$3<=$O$2,$D139,$D139-($D139-$I$130)*MIN(H$3-$O$2,$Q$2)/$Q$2)) -> 1441.0272 | I139: =H139*(1+IF(I$3<=$O$2,$D139,$D139-($D139-$I$130)*MIN(I$3-$O$2,$Q$2)/$Q$2)) -> 1353.7775 | J139: =I139*(1+IF(J$3<=$O$2,$D139,$D139-($D139-$I$130)*MIN(J$3-$O$2,$Q$2)/$Q$2)) -> 1296.3266 | K139: =J139*(1+IF(K$3<=$O$2,$D139,$D139-($D139-$I$130)*MIN(K$3-$O$2,$Q$2)/$Q$2)) -> 1264.7894 | L139: =K139*(1+IF(L$3<=$O$2,$D139,$D139-($D139-$I$130)*MIN(L$3-$O$2,$Q$2)/$Q$2)) -> 1256.924 | M139: =L139*(1+IF(M$3<=$O$2,$D139,$D139-($D139-$I$130)*MIN(M$3-$O$2,$Q$2)/$Q$2)) -> 1271.8696 | N139: =M139*(1+IF(N$3<=$O$2,$D139,$D139-($D139-$I$130)*MIN(N$3-$O$2,$Q$2)/$Q$2)) -> 1310.0257 | O139: =SUMPRODUCT(E139:N139,1/(1+$F$130)^$E$3:$N$3)*$E$2 -> 3913.1388 | P139: =N139*$E$2*(1+$I$130)/($F$130-$I$130)/(1+$F$130)^$N$3 -> 12264.243 | Q139: =O139+P139 -> 16177.382 | R139: =Q139-$G$2+$I$2 -> 14624.682 | S139: =R139/$K$2 -> 53.105349 | T139: =S139-$M$2 -> -1.3991723
A140: 9 | B140: =IF(T139>0,B139,D139) -> -0.060546875 | C140: =IF(T139>0,D139,C139) -> -0.0546875 | D140: =(B140+C140)/2 -> -0.057617188 | E140: =$C$2*(1+IF(E$3<=$O$2,$D140,$D140-($D140-$I$130)*MIN(E$3-$O$2,$Q$2)/$Q$2)) -> 1743.4082 | F140: =E140*(1+IF(F$3<=$O$2,$D140,$D140-($D140-$I$130)*MIN(F$3-$O$2,$Q$2)/$Q$2)) -> 1642.9579 | G140: =F140*(1+IF(G$3<=$O$2,$D140,$D140-($D140-$I$130)*MIN(G$3-$O$2,$Q$2)/$Q$2)) -> 1548.2953 | H140: =G140*(1+IF(H$3<=$O$2,$D140,$D140-($D140-$I$130)*MIN(H$3-$O$2,$Q$2)/$Q$2)) -> 1459.0869 | I140: =H140*(1+IF(I$3<=$O$2,$D140,$D140-($D140-$I$130)*MIN(I$3-$O$2,$Q$2)/$Q$2)) -> 1375.0184 | J140: =I140*(1+IF(J$3<=$O$2,$D140,$D140-($D140-$I$130)*MIN(J$3-$O$2,$Q$2)/$Q$2)) -> 1319.8888 | K140: =J140*(1+IF(K$3<=$O$2,$D140,$D140-($D140-$I$130)*MIN(K$3-$O$2,$Q$2)/$Q$2)) -> 1290.0985 | L140: =K140*(1+IF(L$3<=$O$2,$D140,$D140-($D140-$I$130)*MIN(L$3-$O$2,$Q$2)/$Q$2)) -> 1283.5875 | M140: =L140*(1+IF(M$3<=$O$2,$D140,$D140-($D140-$I$130)*MIN(M$3-$O$2,$Q$2)/$Q$2)) -> 1299.6023 | N140: =M140*(1+IF(N$3<=$O$2,$D140,$D140-($D140-$I$130)*MIN(N$3-$O$2,$Q$2)/$Q$2)) -> 1338.5903 | O140: =SUMPRODUCT(E140:N140,1/(1+$F$130)^$E$3:$N$3)*$E$2 -> 3965.0895 | P140: =N140*$E$2*(1+$I$130)/($F$130-$I$130)/(1+$F$130)^$N$3 -> 12531.66 | Q140: =O140+P140 -> 16496.75 | R140: =Q140-$G$2+$I$2 -> 14944.05 | S140: =R140/$K$2 -> 54.265042 | T140: =S140-$M$2 -> -0.23947893
A141: 10 | B141: =IF(T140>0,B140,D140) -> -0.057617188 | C141: =IF(T140>0,D140,C140) -> -0.0546875 | D141: =(B141+C141)/2 -> -0.056152344 | E141: =$C$2*(1+IF(E$3<=$O$2,$D141,$D141-($D141-$I$130)*MIN(E$3-$O$2,$Q$2)/$Q$2)) -> 1746.1182 | F141: =E141*(1+IF(F$3<=$O$2,$D141,$D141-($D141-$I$130)*MIN(F$3-$O$2,$Q$2)/$Q$2)) -> 1648.0695 | G141: =F141*(1+IF(G$3<=$O$2,$D141,$D141-($D141-$I$130)*MIN(G$3-$O$2,$Q$2)/$Q$2)) -> 1555.5266 | H141: =G141*(1+IF(H$3<=$O$2,$D141,$D141-($D141-$I$130)*MIN(H$3-$O$2,$Q$2)/$Q$2)) -> 1468.1801 | I141: =H141*(1+IF(I$3<=$O$2,$D141,$D141-($D141-$I$130)*MIN(I$3-$O$2,$Q$2)/$Q$2)) -> 1385.7384 | J141: =I141*(1+IF(J$3<=$O$2,$D141,$D141-($D141-$I$130)*MIN(J$3-$O$2,$Q$2)/$Q$2)) -> 1331.8028 | K141: =J141*(1+IF(K$3<=$O$2,$D141,$D141-($D141-$I$130)*MIN(K$3-$O$2,$Q$2)/$Q$2)) -> 1302.9141 | L141: =K141*(1+IF(L$3<=$O$2,$D141,$D141-($D141-$I$130)*MIN(L$3-$O$2,$Q$2)/$Q$2)) -> 1297.1019 | M141: =L141*(1+IF(M$3<=$O$2,$D141,$D141-($D141-$I$130)*MIN(M$3-$O$2,$Q$2)/$Q$2)) -> 1313.6653 | N141: =M141*(1+IF(N$3<=$O$2,$D141,$D141-($D141-$I$130)*MIN(N$3-$O$2,$Q$2)/$Q$2)) -> 1353.0753 | O141: =SUMPRODUCT(E141:N141,1/(1+$F$130)^$E$3:$N$3)*$E$2 -> 3991.3314 | P141: =N141*$E$2*(1+$I$130)/($F$130-$I$130)/(1+$F$130)^$N$3 -> 12667.266 | Q141: =O141+P141 -> 16658.597 | R141: =Q141-$G$2+$I$2 -> 15105.897 | S141: =R141/$K$2 -> 54.852745 | T141: =S141-$M$2 -> 0.34822406
A142: 11 | B142: =IF(T141>0,B141,D141) -> -0.057617188 | C142: =IF(T141>0,D141,C141) -> -0.056152344 | D142: =(B142+C142)/2 -> -0.056884766 | E142: =$C$2*(1+IF(E$3<=$O$2,$D142,$D142-($D142-$I$130)*MIN(E$3-$O$2,$Q$2)/$Q$2)) -> 1744.7632 | F142: =E142*(1+IF(F$3<=$O$2,$D142,$D142-($D142-$I$130)*MIN(F$3-$O$2,$Q$2)/$Q$2)) -> 1645.5127 | G142: =F142*(1+IF(G$3<=$O$2,$D142,$D142-($D142-$I$130)*MIN(G$3-$O$2,$Q$2)/$Q$2)) -> 1551.9081 | H142: =G142*(1+IF(H$3<=$O$2,$D142,$D142-($D142-$I$130)*MIN(H$3-$O$2,$Q$2)/$Q$2)) -> 1463.6282 | I142: =H142*(1+IF(I$3<=$O$2,$D142,$D142-($D142-$I$130)*MIN(I$3-$O$2,$Q$2)/$Q$2)) -> 1380.3701 | J142: =I142*(1+IF(J$3<=$O$2,$D142,$D142-($D142-$I$130)*MIN(J$3-$O$2,$Q$2)/$Q$2)) -> 1325.8347 | K142: =J142*(1+IF(K$3<=$O$2,$D142,$D142-($D142-$I$130)*MIN(K$3-$O$2,$Q$2)/$Q$2)) -> 1296.4928 | L142: =K142*(1+IF(L$3<=$O$2,$D142,$D142-($D142-$I$130)*MIN(L$3-$O$2,$Q$2)/$Q$2)) -> 1290.3294 | M142: =L142*(1+IF(M$3<=$O$2,$D142,$D142-($D142-$I$130)*MIN(M$3-$O$2,$Q$2)/$Q$2)) -> 1306.6173 | N142: =M142*(1+IF(N$3<=$O$2,$D142,$D142-($D142-$I$130)*MIN(N$3-$O$2,$Q$2)/$Q$2)) -> 1345.8158 | O142: =SUMPRODUCT(E142:N142,1/(1+$F$130)^$E$3:$N$3)*$E$2 -> 3978.1881 | P142: =N142*$E$2*(1+$I$130)/($F$130-$I$130)/(1+$F$130)^$N$3 -> 12599.304 | Q142: =O142+P142 -> 16577.492 | R142: =Q142-$G$2+$I$2 -> 15024.792 | S142: =R142/$K$2 -> 54.558234 | T142: =S142-$M$2 -> 0.053713582
A143: 12 | B143: =IF(T142>0,B142,D142) -> -0.057617188 | C143: =IF(T142>0,D142,C142) -> -0.056884766 | D143: =(B143+C143)/2 -> -0.057250977 | E143: =$C$2*(1+IF(E$3<=$O$2,$D143,$D143-($D143-$I$130)*MIN(E$3-$O$2,$Q$2)/$Q$2)) -> 1744.0857 | F143: =E143*(1+IF(F$3<=$O$2,$D143,$D143-($D143-$I$130)*MIN(F$3-$O$2,$Q$2)/$Q$2)) -> 1644.2351 | G143: =F143*(1+IF(G$3<=$O$2,$D143,$D143-($D143-$I$130)*MIN(G$3-$O$2,$Q$2)/$Q$2)) -> 1550.101 | H143: =G143*(1+IF(H$3<=$O$2,$D143,$D143-($D143-$I$130)*MIN(H$3-$O$2,$Q$2)/$Q$2)) -> 1461.3562 | I143: =H143*(1+IF(I$3<=$O$2,$D143,$D143-($D143-$I$130)*MIN(I$3-$O$2,$Q$2)/$Q$2)) -> 1377.6922 | J143: =I143*(1+IF(J$3<=$O$2,$D143,$D143-($D143-$I$130)*MIN(J$3-$O$2,$Q$2)/$Q$2)) -> 1322.8589 | K143: =J143*(1+IF(K$3<=$O$2,$D143,$D143-($D143-$I$130)*MIN(K$3-$O$2,$Q$2)/$Q$2)) -> 1293.2923 | L143: =K143*(1+IF(L$3<=$O$2,$D143,$D143-($D143-$I$130)*MIN(L$3-$O$2,$Q$2)/$Q$2)) -> 1286.9546 | M143: =L143*(1+IF(M$3<=$O$2,$D143,$D143-($D143-$I$130)*MIN(M$3-$O$2,$Q$2)/$Q$2)) -> 1303.1056 | N143: =M143*(1+IF(N$3<=$O$2,$D143,$D143-($D143-$I$130)*MIN(N$3-$O$2,$Q$2)/$Q$2)) -> 1342.1988 | O143: =SUMPRODUCT(E143:N143,1/(1+$F$130)^$E$3:$N$3)*$E$2 -> 3971.6332 | P143: =N143*$E$2*(1+$I$130)/($F$130-$I$130)/(1+$F$130)^$N$3 -> 12565.443 | Q143: =O143+P143 -> 16537.076 | R143: =Q143-$G$2+$I$2 -> 14984.376 | S143: =R143/$K$2 -> 54.411474 | T143: =S143-$M$2 -> -0.093047096
A144: 13 | B144: =IF(T143>0,B143,D143) -> -0.057250977 | C144: =IF(T143>0,D143,C143) -> -0.056884766 | D144: =(B144+C144)/2 -> -0.057067871 | E144: =$C$2*(1+IF(E$3<=$O$2,$D144,$D144-($D144-$I$130)*MIN(E$3-$O$2,$Q$2)/$Q$2)) -> 1744.4244 | F144: =E144*(1+IF(F$3<=$O$2,$D144,$D144-($D144-$I$130)*MIN(F$3-$O$2,$Q$2)/$Q$2)) -> 1644.8738 | G144: =F144*(1+IF(G$3<=$O$2,$D144,$D144-($D144-$I$130)*MIN(G$3-$O$2,$Q$2)/$Q$2)) -> 1551.0044 | H144: =G144*(1+IF(H$3<=$O$2,$D144,$D144-($D144-$I$130)*MIN(H$3-$O$2,$Q$2)/$Q$2)) -> 1462.4919 | I144: =H144*(1+IF(I$3<=$O$2,$D144,$D144-($D144-$I$130)*MIN(I$3-$O$2,$Q$2)/$Q$2)) -> 1379.0306 | J144: =I144*(1+IF(J$3<=$O$2,$D144,$D144-($D144-$I$130)*MIN(J$3-$O$2,$Q$2)/$Q$2)) -> 1324.3461 | K144: =J144*(1+IF(K$3<=$O$2,$D144,$D144-($D144-$I$130)*MIN(K$3-$O$2,$Q$2)/$Q$2)) -> 1294.8917 | L144: =K144*(1+IF(L$3<=$O$2,$D144,$D144-($D144-$I$130)*MIN(L$3-$O$2,$Q$2)/$Q$2)) -> 1288.641 | M144: =L144*(1+IF(M$3<=$O$2,$D144,$D144-($D144-$I$130)*MIN(M$3-$O$2,$Q$2)/$Q$2)) -> 1304.8604 | N144: =M144*(1+IF(N$3<=$O$2,$D144,$D144-($D144-$I$130)*MIN(N$3-$O$2,$Q$2)/$Q$2)) -> 1344.0062 | O144: =SUMPRODUCT(E144:N144,1/(1+$F$130)^$E$3:$N$3)*$E$2 -> 3974.9093 | P144: =N144*$E$2*(1+$I$130)/($F$130-$I$130)/(1+$F$130)^$N$3 -> 12582.363 | Q144: =O144+P144 -> 16557.273 | R144: =Q144-$G$2+$I$2 -> 15004.573 | S144: =R144/$K$2 -> 54.484813 | T144: =S144-$M$2 -> -0.019707903
... A155: 24 | B155: =IF(T154>0,B154,D154) -> -0.057018876 | C155: =IF(T154>0,D154,C154) -> -0.057018697 | D155: =(B155+C155)/2 -> -0.057018787 | E155: =$C$2*(1+IF(E$3<=$O$2,$D155,$D155-($D155-$I$130)*MIN(E$3-$O$2,$Q$2)/$Q$2)) -> 1744.5152 | F155: =E155*(1+IF(F$3<=$O$2,$D155,$D155-($D155-$I$130)*MIN(F$3-$O$2,$Q$2)/$Q$2)) -> 1645.0451 | G155: =F155*(1+IF(G$3<=$O$2,$D155,$D155-($D155-$I$130)*MIN(G$3-$O$2,$Q$2)/$Q$2)) -> 1551.2466 | H155: =G155*(1+IF(H$3<=$O$2,$D155,$D155-($D155-$I$130)*MIN(H$3-$O$2,$Q$2)/$Q$2)) -> 1462.7964 | I155: =H155*(1+IF(I$3<=$O$2,$D155,$D155-($D155-$I$130)*MIN(I$3-$O$2,$Q$2)/$Q$2)) -> 1379.3895 | J155: =I155*(1+IF(J$3<=$O$2,$D155,$D155-($D155-$I$130)*MIN(J$3-$O$2,$Q$2)/$Q$2)) -> 1324.745 | K155: =J155*(1+IF(K$3<=$O$2,$D155,$D155-($D155-$I$130)*MIN(K$3-$O$2,$Q$2)/$Q$2)) -> 1295.3207 | L155: =K155*(1+IF(L$3<=$O$2,$D155,$D155-($D155-$I$130)*MIN(L$3-$O$2,$Q$2)/$Q$2)) -> 1289.0934 | M155: =L155*(1+IF(M$3<=$O$2,$D155,$D155-($D155-$I$130)*MIN(M$3-$O$2,$Q$2)/$Q$2)) -> 1305.3312 | N155: =M155*(1+IF(N$3<=$O$2,$D155,$D155-($D155-$I$130)*MIN(N$3-$O$2,$Q$2)/$Q$2)) -> 1344.4911 | O155: =SUMPRODUCT(E155:N155,1/(1+$F$130)^$E$3:$N$3)*$E$2 -> 3975.788 | P155: =N155*$E$2*(1+$I$130)/($F$130-$I$130)/(1+$F$130)^$N$3 -> 12586.903 | Q155: =O155+P155 -> 16562.691 | R155: =Q155-$G$2+$I$2 -> 15009.991 | S155: =R155/$K$2 -> 54.504487 | T155: =S155-$M$2 -> -3.4145718e-05
A157: Grid block 6: row 1, column 5 of table A (24 steps) | E157: WACC | F157: =Sensitivity!$B$10 -> 0.053509306 | G157: Terminal growth | I157: =Sensitivity!$G$9 -> 0.035
A158: Step | B158: Low | C158: High | D158: Mid | E158: Rev Y1 | F158: Rev Y2 | G158: Rev Y3 | H158: Rev Y4 | I158: Rev Y5 | J158: Rev Y6 | K158: Rev Y7 | L158: Rev Y8 | M158: Rev Y9 | N158: Rev Y10 | O158: PV of FCF | P158: PV of TV | Q158: EV | R158: Equity | S158: Per share | T158: Value - price
A159: 1 | B159: -0.5 | C159: 1 | D159: =(B159+C159)/2 -> 0.25 | E159: =$C$2*(1+IF(E$3<=$O$2,$D159,$D159-($D159-$I$157)*MIN(E$3-$O$2,$Q$2)/$Q$2)) -> 2312.5 | F159: =E159*(1+IF(F$3<=$O$2,$D159,$D159-($D159-$I$157)*MIN(F$3-$O$2,$Q$2)/$Q$2)) -> 2890.625 | G159: =F159*(1+IF(G$3<=$O$2,$D159,$D159-($D159-$I$157)*MIN(G$3-$O$2,$Q$2)/$Q$2)) -> 3613.2812 | H159: =G159*(1+IF(H$3<=$O$2,$D159,$D159-($D159-$I$157)*MIN(H$3-$O$2,$Q$2)/$Q$2)) -> 4516.6016 | I159: =H159*(1+IF(I$3<=$O$2,$D159,$D159-($D159-$I$157)*MIN(I$3-$O$2,$Q$2)/$Q$2)) -> 5645.752 | J159: =I159*(1+IF(J$3<=$O$2,$D159,$D159-($D159-$I$157)*MIN(J$3-$O$2,$Q$2)/$Q$2)) -> 6814.4226 | K159: =J159*(1+IF(K$3<=$O$2,$D159,$D159-($D159-$I$157)*MIN(K$3-$O$2,$Q$2)/$Q$2)) -> 7931.9879 | L159: =K159*(1+IF(L$3<=$O$2,$D159,$D159-($D159-$I$157)*MIN(L$3-$O$2,$Q$2)/$Q$2)) -> 8891.7585 | M159: =L159*(1+IF(M$3<=$O$2,$D159,$D159-($D159-$I$157)*MIN(M$3-$O$2,$Q$2)/$Q$2)) -> 9585.3156 | N159: =M159*(1+IF(N$3<=$O$2,$D159,$D159-($D159-$I$157)*MIN(N$3-$O$2,$Q$2)/$Q$2)) -> 9920.8017 | O159: =SUMPRODUCT(E159:N159,1/(1+$F$157)^$E$3:$N$3)*$E$2 -> 15886.261 | P159: =N159*$E$2*(1+$I$157)/($F$157-$I$157)/(1+$F$157)^$N$3 -> 118538.79 | Q159: =O159+P159 -> 134425.06 | R159: =Q159-$G$2+$I$2 -> 132872.36 | S159: =R159/$K$2 -> 482.48795 | T159: =S159-$M$2 -> 427.98342
A160: 2 | B160: =IF(T159>0,B159,D159) -> -0.5 | C160: =IF(T159>0,D159,C159) -> 0.25 | D160: =(B160+C160)/2 -> -0.125 | E160: =$C$2*(1+IF(E$3<=$O$2,$D160,$D160-($D160-$I$157)*MIN(E$3-$O$2,$Q$2)/$Q$2)) -> 1618.75 | F160: =E160*(1+IF(F$3<=$O$2,$D160,$D160-($D160-$I$157)*MIN(F$3-$O$2,$Q$2)/$Q$2)) -> 1416.4062 | G160: =F160*(1+IF(G$3<=$O$2,$D160,$D160-($D160-$I$157)*MIN(G$3-$O$2,$Q$2)/$Q$2)) -> 1239.3555 | H160: =G160*(1+IF(H$3<=$O$2,$D160,$D160-($D160-$I$157)*MIN(H$3-$O$2,$Q$2)/$Q$2)) -> 1084.436 | I160: =H160*(1+IF(I$3<=$O$2,$D160,$D160-($D160-$I$157)*MIN(I$3-$O$2,$Q$2)/$Q$2)) -> 948.88153 | J160: =I160*(1+IF(J$3<=$O$2,$D160,$D160-($D160-$I$157)*MIN(J$3-$O$2,$Q$2)/$Q$2)) -> 860.63555 | K160: =J160*(1+IF(K$3<=$O$2,$D160,$D160-($D160-$I$157)*MIN(K$3-$O$2,$Q$2)/$Q$2)) -> 808.13678 | L160: =K160*(1+IF(L$3<=$O$2,$D160,$D160-($D160-$I$157)*MIN(L$3-$O$2,$Q$2)/$Q$2)) -> 784.70081 | M160: =L160*(1+IF(M$3<=$O$2,$D160,$D160-($D160-$I$157)*MIN(M$3-$O$2,$Q$2)/$Q$2)) -> 787.05492 | N160: =M160*(1+IF(N$3<=$O$2,$D160,$D160-($D160-$I$157)*MIN(N$3-$O$2,$Q$2)/$Q$2)) -> 814.60184 | O160: =SUMPRODUCT(E160:N160,1/(1+$F$157)^$E$3:$N$3)*$E$2 -> 2939.3803 | P160: =N160*$E$2*(1+$I$157)/($F$157-$I$157)/(1+$F$157)^$N$3 -> 9733.2779 | Q160: =O160+P160 -> 12672.658 | R160: =Q160-$G$2+$I$2 -> 11119.958 | S160: =R160/$K$2 -> 40.378947 | T160: =S160-$M$2 -> -14.125574
A161: 3 | B161: =IF(T160>0,B160,D160) -> -0.125 | C161: =IF(T160>0,D160,C160) -> 0.25 | D161: =(B161+C161)/2 -> 0.0625 | E161: =$C$2*(1+IF(E$3<=$O$2,$D161,$D161-($D161-$I$157)*MIN(E$3-$O$2,$Q$2)/$Q$2)) -> 1965.625 | F161: =E161*(1+IF(F$3<=$O$2,$D161,$D161-($D161-$I$157)*MIN(F$3-$O$2,$Q$2)/$Q$2)) -> 2088.4766 | G161: =F161*(1+IF(G$3<=$O$2,$D161,$D161-($D161-$I$157)*MIN(G$3-$O$2,$Q$2)/$Q$2)) -> 2219.0063 | H161: =G161*(1+IF(H$3<=$O$2,$D161,$D161-($D161-$I$157)*MIN(H$3-$O$2,$Q$2)/$Q$2)) -> 2357.6942 | I161: =H161*(1+IF(I$3<=$O$2,$D161,$D161-($D161-$I$157)*MIN(I$3-$O$2,$Q$2)/$Q$2)) -> 2505.0501 | J161: =I161*(1+IF(J$3<=$O$2,$D161,$D161-($D161-$I$157)*MIN(J$3-$O$2,$Q$2)/$Q$2)) -> 2647.838 | K161: =J161*(1+IF(K$3<=$O$2,$D161,$D161-($D161-$I$157)*MIN(K$3-$O$2,$Q$2)/$Q$2)) -> 2784.2016 | L161: =K161*(1+IF(L$3<=$O$2,$D161,$D161-($D161-$I$157)*MIN(L$3-$O$2,$Q$2)/$Q$2)) -> 2912.2749 | M161: =L161*(1+IF(M$3<=$O$2,$D161,$D161-($D161-$I$157)*MIN(M$3-$O$2,$Q$2)/$Q$2)) -> 3030.2221 | N161: =M161*(1+IF(N$3<=$O$2,$D161,$D161-($D161-$I$157)*MIN(N$3-$O$2,$Q$2)/$Q$2)) -> 3136.2798 | O161: =SUMPRODUCT(E161:N161,1/(1+$F$157)^$E$3:$N$3)*$E$2 -> 6850.5806 | P161: =N161*$E$2*(1+$I$157)/($F$157-$I$157)/(1+$F$157)^$N$3 -> 37473.87 | Q161: =O161+P161 -> 44324.45 | R161: =Q161-$G$2+$I$2 -> 42771.75 | S161: =R161/$K$2 -> 155.31337 | T161: =S161-$M$2 -> 100.80885
A162: 4 | B162: =IF(T161>0,B161,D161) -> -0.125 | C162: =IF(T161>0,D161,C161) -> 0.0625 | D162: =(B162+C162)/2 -> -0.03125 | E162: =$C$2*(1+IF(E$3<=$O$2,$D162,$D162-($D162-$I$157)*MIN(E$3-$O$2,$Q$2)/$Q$2)) -> 1792.1875 | F162: =E162*(1+IF(F$3<=$O$2,$D162,$D162-($D162-$I$157)*MIN(F$3-$O$2,$Q$2)/$Q$2)) -> 1736.1816 | G162: =F162*(1+IF(G$3<=$O$2,$D162,$D162-($D162-$I$157)*MIN(G$3-$O$2,$Q$2)/$Q$2)) -> 1681.926 | H162: =G162*(1+IF(H$3<=$O$2,$D162,$D162-($D162-$I$157)*MIN(H$3-$O$2,$Q$2)/$Q$2)) -> 1629.3658 | I162: =H162*(1+IF(I$3<=$O$2,$D162,$D162-($D162-$I$157)*MIN(I$3-$O$2,$Q$2)/$Q$2)) -> 1578.4481 | J162: =I162*(1+IF(J$3<=$O$2,$D162,$D162-($D162-$I$157)*MIN(J$3-$O$2,$Q$2)/$Q$2)) -> 1550.036 | K162: =J162*(1+IF(K$3<=$O$2,$D162,$D162-($D162-$I$157)*MIN(K$3-$O$2,$Q$2)/$Q$2)) -> 1542.6734 | L162: =K162*(1+IF(L$3<=$O$2,$D162,$D162-($D162-$I$157)*MIN(L$3-$O$2,$Q$2)/$Q$2)) -> 1555.7861 | M162: =L162*(1+IF(M$3<=$O$2,$D162,$D162-($D162-$I$157)*MIN(M$3-$O$2,$Q$2)/$Q$2)) -> 1589.6244 | N162: =M162*(1+IF(N$3<=$O$2,$D162,$D162-($D162-$I$157)*MIN(N$3-$O$2,$Q$2)/$Q$2)) -> 1645.2613 | O162: =SUMPRODUCT(E162:N162,1/(1+$F$157)^$E$3:$N$3)*$E$2 -> 4478.3214 | P162: =N162*$E$2*(1+$I$157)/($F$157-$I$157)/(1+$F$157)^$N$3 -> 19658.42 | Q162: =O162+P162 -> 24136.742 | R162: =Q162-$G$2+$I$2 -> 22584.042 | S162: =R162/$K$2 -> 82.007486 | T162: =S162-$M$2 -> 27.502965
A163: 5 | B163: =IF(T162>0,B162,D162) -> -0.125 | C163: =IF(T162>0,D162,C162) -> -0.03125 | D163: =(B163+C163)/2 -> -0.078125 | E163: =$C$2*(1+IF(E$3<=$O$2,$D163,$D163-($D163-$I$157)*MIN(E$3-$O$2,$Q$2)/$Q$2)) -> 1705.4688 | F163: =E163*(1+IF(F$3<=$O$2,$D163,$D163-($D163-$I$157)*MIN(F$3-$O$2,$Q$2)/$Q$2)) -> 1572.229 | G163: =F163*(1+IF(G$3<=$O$2,$D163,$D163-($D163-$I$157)*MIN(G$3-$O$2,$Q$2)/$Q$2)) -> 1449.3986 | H163: =G163*(1+IF(H$3<=$O$2,$D163,$D163-($D163-$I$157)*MIN(H$3-$O$2,$Q$2)/$Q$2)) -> 1336.1643 | I163: =H163*(1+IF(I$3<=$O$2,$D163,$D163-($D163-$I$157)*MIN(I$3-$O$2,$Q$2)/$Q$2)) -> 1231.7765 | J163: =I163*(1+IF(J$3<=$O$2,$D163,$D163-($D163-$I$157)*MIN(J$3-$O$2,$Q$2)/$Q$2)) -> 1163.4129 | K163: =J163*(1+IF(K$3<=$O$2,$D163,$D163-($D163-$I$157)*MIN(K$3-$O$2,$Q$2)/$Q$2)) -> 1125.1657 | L163: =K163*(1+IF(L$3<=$O$2,$D163,$D163-($D163-$I$157)*MIN(L$3-$O$2,$Q$2)/$Q$2)) -> 1113.6328 | M163: =L163*(1+IF(M$3<=$O$2,$D163,$D163-($D163-$I$157)*MIN(M$3-$O$2,$Q$2)/$Q$2)) -> 1127.414 | N163: =M163*(1+IF(N$3<=$O$2,$D163,$D163-($D163-$I$157)*MIN(N$3-$O$2,$Q$2)/$Q$2)) -> 1166.8735 | O163: =SUMPRODUCT(E163:N163,1/(1+$F$157)^$E$3:$N$3)*$E$2 -> 3624.9696 | P163: =N163*$E$2*(1+$I$157)/($F$157-$I$157)/(1+$F$157)^$N$3 -> 13942.399 | Q163: =O163+P163 -> 17567.368 | R163: =Q163-$G$2+$I$2 -> 16014.668 | S163: =R163/$K$2 -> 58.152687 | T163: =S163-$M$2 -> 3.6481657
A164: 6 | B164: =IF(T163>0,B163,D163) -> -0.125 | C164: =IF(T163>0,D163,C163) -> -0.078125 | D164: =(B164+C164)/2 -> -0.1015625 | E164: =$C$2*(1+IF(E$3<=$O$2,$D164,$D164-($D164-$I$157)*MIN(E$3-$O$2,$Q$2)/$Q$2)) -> 1662.1094 | F164: =E164*(1+IF(F$3<=$O$2,$D164,$D164-($D164-$I$157)*MIN(F$3-$O$2,$Q$2)/$Q$2)) -> 1493.3014 | G164: =F164*(1+IF(G$3<=$O$2,$D164,$D164-($D164-$I$157)*MIN(G$3-$O$2,$Q$2)/$Q$2)) -> 1341.638 | H164: =G164*(1+IF(H$3<=$O$2,$D164,$D164-($D164-$I$157)*MIN(H$3-$O$2,$Q$2)/$Q$2)) -> 1205.3779 | I164: =H164*(1+IF(I$3<=$O$2,$D164,$D164-($D164-$I$157)*MIN(I$3-$O$2,$Q$2)/$Q$2)) -> 1082.9567 | J164: =I164*(1+IF(J$3<=$O$2,$D164,$D164-($D164-$I$157)*MIN(J$3-$O$2,$Q$2)/$Q$2)) -> 1002.5471 | K164: =J164*(1+IF(K$3<=$O$2,$D164,$D164-($D164-$I$157)*MIN(K$3-$O$2,$Q$2)/$Q$2)) -> 955.49008 | L164: =K164*(1+IF(L$3<=$O$2,$D164,$D164-($D164-$I$157)*MIN(L$3-$O$2,$Q$2)/$Q$2)) -> 936.73859 | M164: =L164*(1+IF(M$3<=$O$2,$D164,$D164-($D164-$I$157)*MIN(M$3-$O$2,$Q$2)/$Q$2)) -> 943.93977 | N164: =M164*(1+IF(N$3<=$O$2,$D164,$D164-($D164-$I$157)*MIN(N$3-$O$2,$Q$2)/$Q$2)) -> 976.97766 | O164: =SUMPRODUCT(E164:N164,1/(1+$F$157)^$E$3:$N$3)*$E$2 -> 3263.3564 | P164: =N164*$E$2*(1+$I$157)/($F$157-$I$157)/(1+$F$157)^$N$3 -> 11673.427 | Q164: =O164+P164 -> 14936.783 | R164: =Q164-$G$2+$I$2 -> 13384.083 | S164: =R164/$K$2 -> 48.60047 | T164: =S164-$M$2 -> -5.9040511
A165: 7 | B165: =IF(T164>0,B164,D164) -> -0.1015625 | C165: =IF(T164>0,D164,C164) -> -0.078125 | D165: =(B165+C165)/2 -> -0.08984375 | E165: =$C$2*(1+IF(E$3<=$O$2,$D165,$D165-($D165-$I$157)*MIN(E$3-$O$2,$Q$2)/$Q$2)) -> 1683.7891 | F165: =E165*(1+IF(F$3<=$O$2,$D165,$D165-($D165-$I$157)*MIN(F$3-$O$2,$Q$2)/$Q$2)) -> 1532.5111 | G165: =F165*(1+IF(G$3<=$O$2,$D165,$D165-($D165-$I$157)*MIN(G$3-$O$2,$Q$2)/$Q$2)) -> 1394.8246 | H165: =G165*(1+IF(H$3<=$O$2,$D165,$D165-($D165-$I$157)*MIN(H$3-$O$2,$Q$2)/$Q$2)) -> 1269.5083 | I165: =H165*(1+IF(I$3<=$O$2,$D165,$D165-($D165-$I$157)*MIN(I$3-$O$2,$Q$2)/$Q$2)) -> 1155.4509 | J165: =I165*(1+IF(J$3<=$O$2,$D165,$D165-($D165-$I$157)*MIN(J$3-$O$2,$Q$2)/$Q$2)) -> 1080.4911 | K165: =J165*(1+IF(K$3<=$O$2,$D165,$D165-($D165-$I$157)*MIN(K$3-$O$2,$Q$2)/$Q$2)) -> 1037.3727 | L165: =K165*(1+IF(L$3<=$O$2,$D165,$D165-($D165-$I$157)*MIN(L$3-$O$2,$Q$2)/$Q$2)) -> 1021.877 | M165: =L165*(1+IF(M$3<=$O$2,$D165,$D165-($D165-$I$157)*MIN(M$3-$O$2,$Q$2)/$Q$2)) -> 1032.1277 | N165: =M165*(1+IF(N$3<=$O$2,$D165,$D165-($D165-$I$157)*MIN(N$3-$O$2,$Q$2)/$Q$2)) -> 1068.2521 | O165: =SUMPRODUCT(E165:N165,1/(1+$F$157)^$E$3:$N$3)*$E$2 -> 3439.2049 | P165: =N165*$E$2*(1+$I$157)/($F$157-$I$157)/(1+$F$157)^$N$3 -> 12764.021 | Q165: =O165+P165 -> 16203.226 | R165: =Q165-$G$2+$I$2 -> 14650.526 | S165: =R165/$K$2 -> 53.199193 | T165: =S165-$M$2 -> -1.3053283
A166: 8 | B166: =IF(T165>0,B165,D165) -> -0.08984375 | C166: =IF(T165>0,D165,C165) -> -0.078125 | D166: =(B166+C166)/2 -> -0.083984375 | E166: =$C$2*(1+IF(E$3<=$O$2,$D166,$D166-($D166-$I$157)*MIN(E$3-$O$2,$Q$2)/$Q$2)) -> 1694.6289 | F166: =E166*(1+IF(F$3<=$O$2,$D166,$D166-($D166-$I$157)*MIN(F$3-$O$2,$Q$2)/$Q$2)) -> 1552.3066 | G166: =F166*(1+IF(G$3<=$O$2,$D166,$D166-($D166-$I$157)*MIN(G$3-$O$2,$Q$2)/$Q$2)) -> 1421.9371 | H166: =G166*(1+IF(H$3<=$O$2,$D166,$D166-($D166-$I$157)*MIN(H$3-$O$2,$Q$2)/$Q$2)) -> 1302.5166 | I166: =H166*(1+IF(I$3<=$O$2,$D166,$D166-($D166-$I$157)*MIN(I$3-$O$2,$Q$2)/$Q$2)) -> 1193.1255 | J166: =I166*(1+IF(J$3<=$O$2,$D166,$D166-($D166-$I$157)*MIN(J$3-$O$2,$Q$2)/$Q$2)) -> 1121.3143 | K166: =J166*(1+IF(K$3<=$O$2,$D166,$D166-($D166-$I$157)*MIN(K$3-$O$2,$Q$2)/$Q$2)) -> 1080.509 | L166: =K166*(1+IF(L$3<=$O$2,$D166,$D166-($D166-$I$157)*MIN(L$3-$O$2,$Q$2)/$Q$2)) -> 1066.9013 | M166: =L166*(1+IF(M$3<=$O$2,$D166,$D166-($D166-$I$157)*MIN(M$3-$O$2,$Q$2)/$Q$2)) -> 1078.8539 | N166: =M166*(1+IF(N$3<=$O$2,$D166,$D166-($D166-$I$157)*MIN(N$3-$O$2,$Q$2)/$Q$2)) -> 1116.6138 | O166: =SUMPRODUCT(E166:N166,1/(1+$F$157)^$E$3:$N$3)*$E$2 -> 3530.8148 | P166: =N166*$E$2*(1+$I$157)/($F$157-$I$157)/(1+$F$157)^$N$3 -> 13341.871 | Q166: =O166+P166 -> 16872.686 | R166: =Q166-$G$2+$I$2 -> 15319.986 | S166: =R166/$K$2 -> 55.630145 | T166: =S166-$M$2 -> 1.125624
A167: 9 | B167: =IF(T166>0,B166,D166) -> -0.08984375 | C167: =IF(T166>0,D166,C166) -> -0.083984375 | D167: =(B167+C167)/2 -> -0.086914062 | E167: =$C$2*(1+IF(E$3<=$O$2,$D167,$D167-($D167-$I$157)*MIN(E$3-$O$2,$Q$2)/$Q$2)) -> 1689.209 | F167: =E167*(1+IF(F$3<=$O$2,$D167,$D167-($D167-$I$157)*MIN(F$3-$O$2,$Q$2)/$Q$2)) -> 1542.393 | G167: =F167*(1+IF(G$3<=$O$2,$D167,$D167-($D167-$I$157)*MIN(G$3-$O$2,$Q$2)/$Q$2)) -> 1408.3373 | H167: =G167*(1+IF(H$3<=$O$2,$D167,$D167-($D167-$I$157)*MIN(H$3-$O$2,$Q$2)/$Q$2)) -> 1285.933 | I167: =H167*(1+IF(I$3<=$O$2,$D167,$D167-($D167-$I$157)*MIN(I$3-$O$2,$Q$2)/$Q$2)) -> 1174.1673 | J167: =I167*(1+IF(J$3<=$O$2,$D167,$D167-($D167-$I$157)*MIN(J$3-$O$2,$Q$2)/$Q$2)) -> 1100.7452 | K167: =J167*(1+IF(K$3<=$O$2,$D167,$D167-($D167-$I$157)*MIN(K$3-$O$2,$Q$2)/$Q$2)) -> 1058.7535 | L167: =K167*(1+IF(L$3<=$O$2,$D167,$D167-($D167-$I$157)*MIN(L$3-$O$2,$Q$2)/$Q$2)) -> 1044.1791 | M167: =L167*(1+IF(M$3<=$O$2,$D167,$D167-($D167-$I$157)*MIN(M$3-$O$2,$Q$2)/$Q$2)) -> 1055.2653 | N167: =M167*(1+IF(N$3<=$O$2,$D167,$D167-($D167-$I$157)*MIN(N$3-$O$2,$Q$2)/$Q$2)) -> 1092.1996 | O167: =SUMPRODUCT(E167:N167,1/(1+$F$157)^$E$3:$N$3)*$E$2 -> 3484.6959 | P167: =N167*$E$2*(1+$I$157)/($F$157-$I$157)/(1+$F$157)^$N$3 -> 13050.158 | Q167: =O167+P167 -> 16534.853 | R167: =Q167-$G$2+$I$2 -> 14982.153 | S167: =R167/$K$2 -> 54.403404 | T167: =S167-$M$2 -> -0.10111668
A168: 10 | B168: =IF(T167>0,B167,D167) -> -0.086914062 | C168: =IF(T167>0,D167,C167) -> -0.083984375 | D168: =(B168+C168)/2 -> -0.085449219 | E168: =$C$2*(1+IF(E$3<=$O$2,$D168,$D168-($D168-$I$157)*MIN(E$3-$O$2,$Q$2)/$Q$2)) -> 1691.9189 | F168: =E168*(1+IF(F$3<=$O$2,$D168,$D168-($D168-$I$157)*MIN(F$3-$O$2,$Q$2)/$Q$2)) -> 1547.3458 | G168: =F168*(1+IF(G$3<=$O$2,$D168,$D168-($D168-$I$157)*MIN(G$3-$O$2,$Q$2)/$Q$2)) -> 1415.1263 | H168: =G168*(1+IF(H$3<=$O$2,$D168,$D168-($D168-$I$157)*MIN(H$3-$O$2,$Q$2)/$Q$2)) -> 1294.2049 | I168: =H168*(1+IF(I$3<=$O$2,$D168,$D168-($D168-$I$157)*MIN(I$3-$O$2,$Q$2)/$Q$2)) -> 1183.6161 | J168: =I168*(1+IF(J$3<=$O$2,$D168,$D168-($D168-$I$157)*MIN(J$3-$O$2,$Q$2)/$Q$2)) -> 1110.9901 | K168: =J168*(1+IF(K$3<=$O$2,$D168,$D168-($D168-$I$157)*MIN(K$3-$O$2,$Q$2)/$Q$2)) -> 1069.584 | L168: =K168*(1+IF(L$3<=$O$2,$D168,$D168-($D168-$I$157)*MIN(L$3-$O$2,$Q$2)/$Q$2)) -> 1055.4873 | M168: =L168*(1+IF(M$3<=$O$2,$D168,$D168-($D168-$I$157)*MIN(M$3-$O$2,$Q$2)/$Q$2)) -> 1067.0028 | N168: =M168*(1+IF(N$3<=$O$2,$D168,$D168-($D168-$I$157)*MIN(N$3-$O$2,$Q$2)/$Q$2)) -> 1104.3479 | O168: =SUMPRODUCT(E168:N168,1/(1+$F$157)^$E$3:$N$3)*$E$2 -> 3507.6763 | P168: =N168*$E$2*(1+$I$157)/($F$157-$I$157)/(1+$F$157)^$N$3 -> 13195.311 | Q168: =O168+P168 -> 16702.988 | R168: =Q168-$G$2+$I$2 -> 15150.288 | S168: =R168/$K$2 -> 55.013936 | T168: =S168-$M$2 -> 0.50941472
A169: 11 | B169: =IF(T168>0,B168,D168) -> -0.086914062 | C169: =IF(T168>0,D168,C168) -> -0.085449219 | D169: =(B169+C169)/2 -> -0.086181641 | E169: =$C$2*(1+IF(E$3<=$O$2,$D169,$D169-($D169-$I$157)*MIN(E$3-$O$2,$Q$2)/$Q$2)) -> 1690.564 | F169: =E169*(1+IF(F$3<=$O$2,$D169,$D169-($D169-$I$157)*MIN(F$3-$O$2,$Q$2)/$Q$2)) -> 1544.8684 | G169: =F169*(1+IF(G$3<=$O$2,$D169,$D169-($D169-$I$157)*MIN(G$3-$O$2,$Q$2)/$Q$2)) -> 1411.7291 | H169: =G169*(1+IF(H$3<=$O$2,$D169,$D169-($D169-$I$157)*MIN(H$3-$O$2,$Q$2)/$Q$2)) -> 1290.064 | I169: =H169*(1+IF(I$3<=$O$2,$D169,$D169-($D169-$I$157)*MIN(I$3-$O$2,$Q$2)/$Q$2)) -> 1178.8841 | J169: =I169*(1+IF(J$3<=$O$2,$D169,$D169-($D169-$I$157)*MIN(J$3-$O$2,$Q$2)/$Q$2)) -> 1105.8578 | K169: =J169*(1+IF(K$3<=$O$2,$D169,$D169-($D169-$I$157)*MIN(K$3-$O$2,$Q$2)/$Q$2)) -> 1064.157 | L169: =K169*(1+IF(L$3<=$O$2,$D169,$D169-($D169-$I$157)*MIN(L$3-$O$2,$Q$2)/$Q$2)) -> 1049.82 | M169: =L169*(1+IF(M$3<=$O$2,$D169,$D169-($D169-$I$157)*MIN(M$3-$O$2,$Q$2)/$Q$2)) -> 1061.1199 | N169: =M169*(1+IF(N$3<=$O$2,$D169,$D169-($D169-$I$157)*MIN(N$3-$O$2,$Q$2)/$Q$2)) -> 1098.2591 | O169: =SUMPRODUCT(E169:N169,1/(1+$F$157)^$E$3:$N$3)*$E$2 -> 3496.1664 | P169: =N169*$E$2*(1+$I$157)/($F$157-$I$157)/(1+$F$157)^$N$3 -> 13122.56 | Q169: =O169+P169 -> 16618.726 | R169: =Q169-$G$2+$I$2 -> 15066.026 | S169: =R169/$K$2 -> 54.707963 | T169: =S169-$M$2 -> 0.20344214
A170: 12 | B170: =IF(T169>0,B169,D169) -> -0.086914062 | C170: =IF(T169>0,D169,C169) -> -0.086181641 | D170: =(B170+C170)/2 -> -0.086547852 | E170: =$C$2*(1+IF(E$3<=$O$2,$D170,$D170-($D170-$I$157)*MIN(E$3-$O$2,$Q$2)/$Q$2)) -> 1689.8865 | F170: =E170*(1+IF(F$3<=$O$2,$D170,$D170-($D170-$I$157)*MIN(F$3-$O$2,$Q$2)/$Q$2)) -> 1543.6304 | G170: =F170*(1+IF(G$3<=$O$2,$D170,$D170-($D170-$I$157)*MIN(G$3-$O$2,$Q$2)/$Q$2)) -> 1410.0325 | H170: =G170*(1+IF(H$3<=$O$2,$D170,$D170-($D170-$I$157)*MIN(H$3-$O$2,$Q$2)/$Q$2)) -> 1287.9972 | I170: =H170*(1+IF(I$3<=$O$2,$D170,$D170-($D170-$I$157)*MIN(I$3-$O$2,$Q$2)/$Q$2)) -> 1176.5239 | J170: =I170*(1+IF(J$3<=$O$2,$D170,$D170-($D170-$I$157)*MIN(J$3-$O$2,$Q$2)/$Q$2)) -> 1103.299 | K170: =J170*(1+IF(K$3<=$O$2,$D170,$D170-($D170-$I$157)*MIN(K$3-$O$2,$Q$2)/$Q$2)) -> 1061.4523 | L170: =K170*(1+IF(L$3<=$O$2,$D170,$D170-($D170-$I$157)*MIN(L$3-$O$2,$Q$2)/$Q$2)) -> 1046.9963 | M170: =L170*(1+IF(M$3<=$O$2,$D170,$D170-($D170-$I$157)*MIN(M$3-$O$2,$Q$2)/$Q$2)) -> 1058.1891 | N170: =M170*(1+IF(N$3<=$O$2,$D170,$D170-($D170-$I$157)*MIN(N$3-$O$2,$Q$2)/$Q$2)) -> 1095.2257 | O170: =SUMPRODUCT(E170:N170,1/(1+$F$157)^$E$3:$N$3)*$E$2 -> 3490.4262 | P170: =N170*$E$2*(1+$I$157)/($F$157-$I$157)/(1+$F$157)^$N$3 -> 13086.315 | Q170: =O170+P170 -> 16576.741 | R170: =Q170-$G$2+$I$2 -> 15024.041 | S170: =R170/$K$2 -> 54.555507 | T170: =S170-$M$2 -> 0.050986371
A171: 13 | B171: =IF(T170>0,B170,D170) -> -0.086914062 | C171: =IF(T170>0,D170,C170) -> -0.086547852 | D171: =(B171+C171)/2 -> -0.086730957 | E171: =$C$2*(1+IF(E$3<=$O$2,$D171,$D171-($D171-$I$157)*MIN(E$3-$O$2,$Q$2)/$Q$2)) -> 1689.5477 | F171: =E171*(1+IF(F$3<=$O$2,$D171,$D171-($D171-$I$157)*MIN(F$3-$O$2,$Q$2)/$Q$2)) -> 1543.0116 | G171: =F171*(1+IF(G$3<=$O$2,$D171,$D171-($D171-$I$157)*MIN(G$3-$O$2,$Q$2)/$Q$2)) -> 1409.1848 | H171: =G171*(1+IF(H$3<=$O$2,$D171,$D171-($D171-$I$157)*MIN(H$3-$O$2,$Q$2)/$Q$2)) -> 1286.9648 | I171: =H171*(1+IF(I$3<=$O$2,$D171,$D171-($D171-$I$157)*MIN(I$3-$O$2,$Q$2)/$Q$2)) -> 1175.3451 | J171: =I171*(1+IF(J$3<=$O$2,$D171,$D171-($D171-$I$157)*MIN(J$3-$O$2,$Q$2)/$Q$2)) -> 1102.0215 | K171: =J171*(1+IF(K$3<=$O$2,$D171,$D171-($D171-$I$157)*MIN(K$3-$O$2,$Q$2)/$Q$2)) -> 1060.1022 | L171: =K171*(1+IF(L$3<=$O$2,$D171,$D171-($D171-$I$157)*MIN(L$3-$O$2,$Q$2)/$Q$2)) -> 1045.5868 | M171: =L171*(1+IF(M$3<=$O$2,$D171,$D171-($D171-$I$157)*MIN(M$3-$O$2,$Q$2)/$Q$2)) -> 1056.7263 | N171: =M171*(1+IF(N$3<=$O$2,$D171,$D171-($D171-$I$157)*MIN(N$3-$O$2,$Q$2)/$Q$2)) -> 1093.7118 | O171: =SUMPRODUCT(E171:N171,1/(1+$F$157)^$E$3:$N$3)*$E$2 -> 3487.5598 | P171: =N171*$E$2*(1+$I$157)/($F$157-$I$157)/(1+$F$157)^$N$3 -> 13068.225 | Q171: =O171+P171 -> 16555.785 | R171: =Q171-$G$2+$I$2 -> 15003.085 | S171: =R171/$K$2 -> 54.479412 | T171: =S171-$M$2 -> -0.0251092
... A182: 24 | B182: =IF(T181>0,B181,D181) -> -0.086670518 | C182: =IF(T181>0,D181,C181) -> -0.086670339 | D182: =(B182+C182)/2 -> -0.086670429 | E182: =$C$2*(1+IF(E$3<=$O$2,$D182,$D182-($D182-$I$157)*MIN(E$3-$O$2,$Q$2)/$Q$2)) -> 1689.6597 | F182: =E182*(1+IF(F$3<=$O$2,$D182,$D182-($D182-$I$157)*MIN(F$3-$O$2,$Q$2)/$Q$2)) -> 1543.2162 | G182: =F182*(1+IF(G$3<=$O$2,$D182,$D182-($D182-$I$157)*MIN(G$3-$O$2,$Q$2)/$Q$2)) -> 1409.465 | H182: =G182*(1+IF(H$3<=$O$2,$D182,$D182-($D182-$I$157)*MIN(H$3-$O$2,$Q$2)/$Q$2)) -> 1287.306 | I182: =H182*(1+IF(I$3<=$O$2,$D182,$D182-($D182-$I$157)*MIN(I$3-$O$2,$Q$2)/$Q$2)) -> 1175.7347 | J182: =I182*(1+IF(J$3<=$O$2,$D182,$D182-($D182-$I$157)*MIN(J$3-$O$2,$Q$2)/$Q$2)) -> 1102.4437 | K182: =J182*(1+IF(K$3<=$O$2,$D182,$D182-($D182-$I$157)*MIN(K$3-$O$2,$Q$2)/$Q$2)) -> 1060.5483 | L182: =K182*(1+IF(L$3<=$O$2,$D182,$D182-($D182-$I$157)*MIN(L$3-$O$2,$Q$2)/$Q$2)) -> 1046.0526 | M182: =L182*(1+IF(M$3<=$O$2,$D182,$D182-($D182-$I$157)*MIN(M$3-$O$2,$Q$2)/$Q$2)) -> 1057.2097 | N182: =M182*(1+IF(N$3<=$O$2,$D182,$D182-($D182-$I$157)*MIN(N$3-$O$2,$Q$2)/$Q$2)) -> 1094.212 | O182: =SUMPRODUCT(E182:N182,1/(1+$F$157)^$E$3:$N$3)*$E$2 -> 3488.5071 | P182: =N182*$E$2*(1+$I$157)/($F$157-$I$157)/(1+$F$157)^$N$3 -> 13074.203 | Q182: =O182+P182 -> 16562.71 | R182: =Q182-$G$2+$I$2 -> 15010.01 | S182: =R182/$K$2 -> 54.504557 | T182: =S182-$M$2 -> 3.5687734e-05
...

Sheet DCF
B2: TMX Group (X): discounted cash flow
B3: Panel A runs the model at the solved growth rate, so it should land on the price. Panel B runs it at your view.
B5: A. At the solved (implied) growth rate
B6: Year | C6: 1 | D6: 2 | E6: 3 | F6: 4 | G6: 5 | H6: 6 | I6: 7 | J6: 8 | K6: 9 | L6: 10
B7: Revenue growth | C7: =IF(C$6<=Inputs!$C$46,Solver!$W$7,Solver!$W$7-(Solver!$W$7-Inputs!$C$37)*MIN(C$6-Inputs!$C$46,Inputs!$C$47)/Inputs!$C$47) -> 0.013955097 | D7: =IF(D$6<=Inputs!$C$46,Solver!$W$7,Solver!$W$7-(Solver!$W$7-Inputs!$C$37)*MIN(D$6-Inputs!$C$46,Inputs!$C$47)/Inputs!$C$47) -> 0.013955097 | E7: =IF(E$6<=Inputs!$C$46,Solver!$W$7,Solver!$W$7-(Solver!$W$7-Inputs!$C$37)*MIN(E$6-Inputs!$C$46,Inputs!$C$47)/Inputs!$C$47) -> 0.013955097 | F7: =IF(F$6<=Inputs!$C$46,Solver!$W$7,Solver!$W$7-(Solver!$W$7-Inputs!$C$37)*MIN(F$6-Inputs!$C$46,Inputs!$C$47)/Inputs!$C$47) -> 0.013955097 | G7: =IF(G$6<=Inputs!$C$46,Solver!$W$7,Solver!$W$7-(Solver!$W$7-Inputs!$C$37)*MIN(G$6-Inputs!$C$46,Inputs!$C$47)/Inputs!$C$47) -> 0.013955097 | H7: =IF(H$6<=Inputs!$C$46,Solver!$W$7,Solver!$W$7-(Solver!$W$7-Inputs!$C$37)*MIN(H$6-Inputs!$C$46,Inputs!$C$47)/Inputs!$C$47) -> 0.016164078 | I7: =IF(I$6<=Inputs!$C$46,Solver!$W$7,Solver!$W$7-(Solver!$W$7-Inputs!$C$37)*MIN(I$6-Inputs!$C$46,Inputs!$C$47)/Inputs!$C$47) -> 0.018373058 | J7: =IF(J$6<=Inputs!$C$46,Solver!$W$7,Solver!$W$7-(Solver!$W$7-Inputs!$C$37)*MIN(J$6-Inputs!$C$46,Inputs!$C$47)/Inputs!$C$47) -> 0.020582039 | ... L7: =IF(L$6<=Inputs!$C$46,Solver!$W$7,Solver!$W$7-(Solver!$W$7-Inputs!$C$37)*MIN(L$6-Inputs!$C$46,Inputs!$C$47)/Inputs!$C$47) -> 0.025
B8: Revenue (C$mm) | C8: =Inputs!$C$12*(1+C7) -> 1875.8169 | D8: =C8*(1+D7) -> 1901.9941 | E8: =D8*(1+E7) -> 1928.5366 | F8: =E8*(1+F7) -> 1955.4496 | G8: =F8*(1+G7) -> 1982.7381 | H8: =G8*(1+H7) -> 2014.7872 | I8: =H8*(1+I7) -> 2051.805 | J8: =I8*(1+J7) -> 2094.0353 | K8: =J8*(1+K7) -> 2141.7605 | L8: =K8*(1+L7) -> 2195.3045
B9: Unlevered free cash flow (C$mm) | C9: =C8*Inputs!$C$23 -> 675.05277 | D9: =D8*Inputs!$C$23 -> 684.4732 | E9: =E8*Inputs!$C$23 -> 694.02509 | F9: =F8*Inputs!$C$23 -> 703.71028 | G9: =G8*Inputs!$C$23 -> 713.53062 | H9: =H8*Inputs!$C$23 -> 725.06419 | I9: =I8*Inputs!$C$23 -> 738.38583 | J9: =J8*Inputs!$C$23 -> 753.58332 | ... L9: =L8*Inputs!$C$23 -> 790.02721
B10: Discount factor | C10: =1/(1+WACC!$C$37)^C$6 -> 0.94028326 | D10: =1/(1+WACC!$C$37)^D$6 -> 0.88413261 | E10: =1/(1+WACC!$C$37)^E$6 -> 0.8313351 | F10: =1/(1+WACC!$C$37)^F$6 -> 0.78169048 | G10: =1/(1+WACC!$C$37)^G$6 -> 0.73501047 | H10: =1/(1+WACC!$C$37)^H$6 -> 0.69111805 | I10: =1/(1+WACC!$C$37)^I$6 -> 0.64984673 | J10: =1/(1+WACC!$C$37)^J$6 -> 0.61104001 | ... L10: =1/(1+WACC!$C$37)^L$6 -> 0.5402404
B11: Present value (C$mm) | C11: =C9*C10 -> 634.74082 | D11: =D9*D10 -> 605.16508 | E11: =E9*E10 -> 576.96742 | F11: =F9*F10 -> 550.08362 | G11: =G9*G10 -> 524.45248 | H11: =H9*H10 -> 501.10495 | I11: =I9*I10 -> 479.83762 | J11: =J9*J10 -> 460.46956 | ... L11: =L9*L10 -> 426.80461
B13: Sum of present values, years 1 to 10 | C13: =SUM(C11:L11) -> 5202.4659
B14: Terminal value at year 10 | C14: =L9*(1+Inputs!$C$37)/(WACC!$C$37-Inputs!$C$37) -> 21028.109
B15: Present value of terminal value | C15: =C14*L10 -> 11360.234
B16: Enterprise value | C16: =C13+C15 -> 16562.7
B17: Less: debt | C17: =-Inputs!$C$27 -> -2070
B18: Plus: cash | C18: =Inputs!$C$28 -> 517.3
B19: Equity value | C19: =SUM(C16:C18) -> 15010
B20: Shares (mm) | C20: =Inputs!$C$7 -> 275.39
B21: Value per share (C$) | C21: =C19/C20 -> 54.504521
B22: Price at the lock (C$) | C22: =Inputs!$C$6 -> 54.504521
B23: Value / price - 1 | C23: =C21/C22-1 -> -6.8428596e-12
B24: Terminal value share of enterprise value | C24: =C15/C16 -> 0.68589265
B25: B. At your view of growth (Inputs tab, yellow cell)
B26: Year | C26: 1 | D26: 2 | E26: 3 | F26: 4 | G26: 5 | H26: 6 | I26: 7 | J26: 8 | K26: 9 | L26: 10
B27: Revenue growth | C27: =IF(C$26<=Inputs!$C$46,Inputs!$C$45,Inputs!$C$45-(Inputs!$C$45-Inputs!$C$37)*MIN(C$26-Inputs!$C$46,Inputs!$C$47)/Inputs!$C$47) -> 0.1503 | D27: =IF(D$26<=Inputs!$C$46,Inputs!$C$45,Inputs!$C$45-(Inputs!$C$45-Inputs!$C$37)*MIN(D$26-Inputs!$C$46,Inputs!$C$47)/Inputs!$C$47) -> 0.1503 | E27: =IF(E$26<=Inputs!$C$46,Inputs!$C$45,Inputs!$C$45-(Inputs!$C$45-Inputs!$C$37)*MIN(E$26-Inputs!$C$46,Inputs!$C$47)/Inputs!$C$47) -> 0.1503 | F27: =IF(F$26<=Inputs!$C$46,Inputs!$C$45,Inputs!$C$45-(Inputs!$C$45-Inputs!$C$37)*MIN(F$26-Inputs!$C$46,Inputs!$C$47)/Inputs!$C$47) -> 0.1503 | G27: =IF(G$26<=Inputs!$C$46,Inputs!$C$45,Inputs!$C$45-(Inputs!$C$45-Inputs!$C$37)*MIN(G$26-Inputs!$C$46,Inputs!$C$47)/Inputs!$C$47) -> 0.1503 | H27: =IF(H$26<=Inputs!$C$46,Inputs!$C$45,Inputs!$C$45-(Inputs!$C$45-Inputs!$C$37)*MIN(H$26-Inputs!$C$46,Inputs!$C$47)/Inputs!$C$47) -> 0.12524 | I27: =IF(I$26<=Inputs!$C$46,Inputs!$C$45,Inputs!$C$45-(Inputs!$C$45-Inputs!$C$37)*MIN(I$26-Inputs!$C$46,Inputs!$C$47)/Inputs!$C$47) -> 0.10018 | J27: =IF(J$26<=Inputs!$C$46,Inputs!$C$45,Inputs!$C$45-(Inputs!$C$45-Inputs!$C$37)*MIN(J$26-Inputs!$C$46,Inputs!$C$47)/Inputs!$C$47) -> 0.07512 | ... L27: =IF(L$26<=Inputs!$C$46,Inputs!$C$45,Inputs!$C$45-(Inputs!$C$45-Inputs!$C$37)*MIN(L$26-Inputs!$C$46,Inputs!$C$47)/Inputs!$C$47) -> 0.025
B28: Revenue (C$mm) | C28: =Inputs!$C$12*(1+C27) -> 2128.055 | D28: =C28*(1+D27) -> 2447.9017 | E28: =D28*(1+E27) -> 2815.8213 | F28: =E28*(1+F27) -> 3239.0392 | G28: =F28*(1+G27) -> 3725.8668 | H28: =G28*(1+H27) -> 4192.4944 | I28: =H28*(1+I27) -> 4612.4985 | J28: =I28*(1+J27) -> 4958.9894 | K28: =J28*(1+K27) -> 5207.2364 | L28: =K28*(1+L27) -> 5337.4173
B29: Unlevered free cash flow (C$mm) | C29: =C28*Inputs!$C$23 -> 765.82603 | D29: =D28*Inputs!$C$23 -> 880.92968 | E29: =E28*Inputs!$C$23 -> 1013.3334 | F29: =F28*Inputs!$C$23 -> 1165.6374 | G29: =G28*Inputs!$C$23 -> 1340.8327 | H29: =H28*Inputs!$C$23 -> 1508.7586 | I29: =I28*Inputs!$C$23 -> 1659.9061 | J29: =J28*Inputs!$C$23 -> 1784.5982 | ... L29: =L28*Inputs!$C$23 -> 1920.7836
B30: Discount factor | C30: =1/(1+WACC!$C$37)^C$26 -> 0.94028326 | D30: =1/(1+WACC!$C$37)^D$26 -> 0.88413261 | E30: =1/(1+WACC!$C$37)^E$26 -> 0.8313351 | F30: =1/(1+WACC!$C$37)^F$26 -> 0.78169048 | G30: =1/(1+WACC!$C$37)^G$26 -> 0.73501047 | H30: =1/(1+WACC!$C$37)^H$26 -> 0.69111805 | I30: =1/(1+WACC!$C$37)^I$26 -> 0.64984673 | J30: =1/(1+WACC!$C$37)^J$26 -> 0.61104001 | ... L30: =1/(1+WACC!$C$37)^L$26 -> 0.5402404
B31: Present value (C$mm) | C31: =C29*C30 -> 720.0934 | D31: =D29*D30 -> 778.85866 | E31: =E29*E30 -> 842.41963 | F31: =F29*F30 -> 911.16768 | G31: =G29*G30 -> 985.5261 | H31: =H29*H30 -> 1042.7303 | I31: =I29*I30 -> 1078.6845 | J31: =J29*J30 -> 1090.4609 | ... L31: =L29*L30 -> 1037.6849
B33: Sum of present values, years 1 to 10 | C33: =SUM(C31:L31) -> 9564.2968
B34: Terminal value at year 10 | C34: =L29*(1+Inputs!$C$37)/(WACC!$C$37-Inputs!$C$37) -> 51125.387
B35: Present value of terminal value | C35: =C34*L30 -> 27619.999
B36: Enterprise value | C36: =C33+C35 -> 37184.296
B37: Less: debt | C37: =-Inputs!$C$27 -> -2070
B38: Plus: cash | C38: =Inputs!$C$28 -> 517.3
B39: Equity value | C39: =SUM(C36:C38) -> 35631.596
B40: Shares (mm) | C40: =Inputs!$C$7 -> 275.39
B41: Value per share (C$) | C41: =C39/C40 -> 129.38595
B42: Price at the lock (C$) | C42: =Inputs!$C$6 -> 54.504521
B43: Value / price - 1 | C43: =C41/C42-1 -> 1.3738572
B44: Terminal value share of enterprise value | C44: =C35/C36 -> 0.74278667

Sheet Sensitivity
B2: TMX Group (X): sensitivity
B3: Table A re-solves implied growth for each pair of inputs (Solver tab, blocks 2 to 26). Table B values the stock at a growth view.
B5: WACC step | C5: 0.005 | D5: Terminal-growth step | F5: 0.005
B6: Growth-view step | C6: 0.02
B8: A. Implied 5-year growth: WACC (rows) by terminal growth (columns)
C9: =Inputs!$C$37+(0-2)*$F$5 -> 0.015 | D9: =Inputs!$C$37+(1-2)*$F$5 -> 0.02 | E9: =Inputs!$C$37+(2-2)*$F$5 -> 0.025 | F9: =Inputs!$C$37+(3-2)*$F$5 -> 0.03 | G9: =Inputs!$C$37+(4-2)*$F$5 -> 0.035
B10: =WACC!$C$37+(0-2)*$C$5 -> 0.053509306 | C10: =Solver!$D$74 -> 0.0056361854 | D10: =Solver!$D$101 -> -0.012196928 | E10: =Solver!$D$128 -> -0.03275159 | F10: =Solver!$D$155 -> -0.057018787 | G10: =Solver!$D$182 -> -0.086670429 | I10: Centre cell = the base case. Each step changes one input by the step size above.
B11: =WACC!$C$37+(1-2)*$C$5 -> 0.058509306 | C11: =Solver!$D$209 -> 0.025617391 | D11: =Solver!$D$236 -> 0.0097970068 | E11: =Solver!$D$263 -> -0.0081165731 | F11: =Solver!$D$290 -> -0.028763145 | G11: =Solver!$D$317 -> -0.053138167
B12: =WACC!$C$37+(2-2)*$C$5 -> 0.063509306 | C12: =Solver!$D$344 -> 0.044075459 | D12: =Solver!$D$371 -> 0.029846877 | E12: =Solver!$D$398 -> 0.013955146 | F12: =Solver!$D$425 -> -0.0040389001 | G12: =Solver!$D$452 -> -0.024777561
B13: =WACC!$C$37+(3-2)*$C$5 -> 0.068509306 | C13: =Solver!$D$479 -> 0.061303288 | D13: =Solver!$D$506 -> 0.048366457 | E13: =Solver!$D$533 -> 0.034073681 | F13: =Solver!$D$560 -> 0.018110424 | G13: =Solver!$D$587 -> 3.6090612e-05
B14: =WACC!$C$37+(4-2)*$C$5 -> 0.073509306 | C14: =Solver!$D$614 -> 0.07751742 | D14: =Solver!$D$641 -> 0.065650076 | E14: =Solver!$D$668 -> 0.052654773 | F14: =Solver!$D$695 -> 0.038297623 | G14: =Solver!$D$722 -> 0.02226302
B17: B. Value per share: WACC (rows) by your growth view (columns)
C18: =Inputs!$C$45+(0-2)*$C$6 -> 0.1103 | D18: =Inputs!$C$45+(1-2)*$C$6 -> 0.1303 | E18: =Inputs!$C$45+(2-2)*$C$6 -> 0.1503 | F18: =Inputs!$C$45+(3-2)*$C$6 -> 0.1703 | G18: =Inputs!$C$45+(4-2)*$C$6 -> 0.1903
B19: =WACC!$C$37+(0-2)*$C$5 -> 0.053509306 | C19: =(SUMPRODUCT($C28:$L28,1/(1+$B19)^$C$27:$L$27)*Inputs!$C$23+$L28*Inputs!$C$23*(1+Inputs!$C$37)/($B19-Inputs!$C$37)/(1+$B19)^$L$27-Inputs!$C$27+Inputs!$C$28)/Inputs!$C$7 -> 140.93235 | D19: =(SUMPRODUCT($C29:$L29,1/(1+$B19)^$C$27:$L$27)*Inputs!$C$23+$L29*Inputs!$C$23*(1+Inputs!$C$37)/($B19-Inputs!$C$37)/(1+$B19)^$L$27-Inputs!$C$27+Inputs!$C$28)/Inputs!$C$7 -> 159.4188 | E19: =(SUMPRODUCT($C30:$L30,1/(1+$B19)^$C$27:$L$27)*Inputs!$C$23+$L30*Inputs!$C$23*(1+Inputs!$C$37)/($B19-Inputs!$C$37)/(1+$B19)^$L$27-Inputs!$C$27+Inputs!$C$28)/Inputs!$C$7 -> 179.97507 | F19: =(SUMPRODUCT($C31:$L31,1/(1+$B19)^$C$27:$L$27)*Inputs!$C$23+$L31*Inputs!$C$23*(1+Inputs!$C$37)/($B19-Inputs!$C$37)/(1+$B19)^$L$27-Inputs!$C$27+Inputs!$C$28)/Inputs!$C$7 -> 202.79967 | G19: =(SUMPRODUCT($C32:$L32,1/(1+$B19)^$C$27:$L$27)*Inputs!$C$23+$L32*Inputs!$C$23*(1+Inputs!$C$37)/($B19-Inputs!$C$37)/(1+$B19)^$L$27-Inputs!$C$27+Inputs!$C$28)/Inputs!$C$7 -> 228.10696 | I19: Compare with the price at the lock: C$54.50.
B20: =WACC!$C$37+(1-2)*$C$5 -> 0.058509306 | C20: =(SUMPRODUCT($C28:$L28,1/(1+$B20)^$C$27:$L$27)*Inputs!$C$23+$L28*Inputs!$C$23*(1+Inputs!$C$37)/($B20-Inputs!$C$37)/(1+$B20)^$L$27-Inputs!$C$27+Inputs!$C$28)/Inputs!$C$7 -> 118.25984 | D20: =(SUMPRODUCT($C29:$L29,1/(1+$B20)^$C$27:$L$27)*Inputs!$C$23+$L29*Inputs!$C$23*(1+Inputs!$C$37)/($B20-Inputs!$C$37)/(1+$B20)^$L$27-Inputs!$C$27+Inputs!$C$28)/Inputs!$C$7 -> 133.71335 | E20: =(SUMPRODUCT($C30:$L30,1/(1+$B20)^$C$27:$L$27)*Inputs!$C$23+$L30*Inputs!$C$23*(1+Inputs!$C$37)/($B20-Inputs!$C$37)/(1+$B20)^$L$27-Inputs!$C$27+Inputs!$C$28)/Inputs!$C$7 -> 150.88693 | F20: =(SUMPRODUCT($C31:$L31,1/(1+$B20)^$C$27:$L$27)*Inputs!$C$23+$L31*Inputs!$C$23*(1+Inputs!$C$37)/($B20-Inputs!$C$37)/(1+$B20)^$L$27-Inputs!$C$27+Inputs!$C$28)/Inputs!$C$7 -> 169.94498 | G20: =(SUMPRODUCT($C32:$L32,1/(1+$B20)^$C$27:$L$27)*Inputs!$C$23+$L32*Inputs!$C$23*(1+Inputs!$C$37)/($B20-Inputs!$C$37)/(1+$B20)^$L$27-Inputs!$C$27+Inputs!$C$28)/Inputs!$C$7 -> 191.06495
B21: =WACC!$C$37+(2-2)*$C$5 -> 0.063509306 | C21: =(SUMPRODUCT($C28:$L28,1/(1+$B21)^$C$27:$L$27)*Inputs!$C$23+$L28*Inputs!$C$23*(1+Inputs!$C$37)/($B21-Inputs!$C$37)/(1+$B21)^$L$27-Inputs!$C$27+Inputs!$C$28)/Inputs!$C$7 -> 101.49391 | D21: =(SUMPRODUCT($C29:$L29,1/(1+$B21)^$C$27:$L$27)*Inputs!$C$23+$L29*Inputs!$C$23*(1+Inputs!$C$37)/($B21-Inputs!$C$37)/(1+$B21)^$L$27-Inputs!$C$27+Inputs!$C$28)/Inputs!$C$7 -> 114.70881 | E21: =(SUMPRODUCT($C30:$L30,1/(1+$B21)^$C$27:$L$27)*Inputs!$C$23+$L30*Inputs!$C$23*(1+Inputs!$C$37)/($B21-Inputs!$C$37)/(1+$B21)^$L$27-Inputs!$C$27+Inputs!$C$28)/Inputs!$C$7 -> 129.38595 | F21: =(SUMPRODUCT($C31:$L31,1/(1+$B21)^$C$27:$L$27)*Inputs!$C$23+$L31*Inputs!$C$23*(1+Inputs!$C$37)/($B21-Inputs!$C$37)/(1+$B21)^$L$27-Inputs!$C$27+Inputs!$C$28)/Inputs!$C$7 -> 145.66459 | G21: =(SUMPRODUCT($C32:$L32,1/(1+$B21)^$C$27:$L$27)*Inputs!$C$23+$L32*Inputs!$C$23*(1+Inputs!$C$37)/($B21-Inputs!$C$37)/(1+$B21)^$L$27-Inputs!$C$27+Inputs!$C$28)/Inputs!$C$7 -> 163.69502
B22: =WACC!$C$37+(3-2)*$C$5 -> 0.068509306 | C22: =(SUMPRODUCT($C28:$L28,1/(1+$B22)^$C$27:$L$27)*Inputs!$C$23+$L28*Inputs!$C$23*(1+Inputs!$C$37)/($B22-Inputs!$C$37)/(1+$B22)^$L$27-Inputs!$C$27+Inputs!$C$28)/Inputs!$C$7 -> 88.597666 | D22: =(SUMPRODUCT($C29:$L29,1/(1+$B22)^$C$27:$L$27)*Inputs!$C$23+$L29*Inputs!$C$23*(1+Inputs!$C$37)/($B22-Inputs!$C$37)/(1+$B22)^$L$27-Inputs!$C$27+Inputs!$C$28)/Inputs!$C$7 -> 100.09422 | E22: =(SUMPRODUCT($C30:$L30,1/(1+$B22)^$C$27:$L$27)*Inputs!$C$23+$L30*Inputs!$C$23*(1+Inputs!$C$37)/($B22-Inputs!$C$37)/(1+$B22)^$L$27-Inputs!$C$27+Inputs!$C$28)/Inputs!$C$7 -> 112.85538 | F22: =(SUMPRODUCT($C31:$L31,1/(1+$B22)^$C$27:$L$27)*Inputs!$C$23+$L31*Inputs!$C$23*(1+Inputs!$C$37)/($B22-Inputs!$C$37)/(1+$B22)^$L$27-Inputs!$C$27+Inputs!$C$28)/Inputs!$C$7 -> 127.00115 | G22: =(SUMPRODUCT($C32:$L32,1/(1+$B22)^$C$27:$L$27)*Inputs!$C$23+$L32*Inputs!$C$23*(1+Inputs!$C$37)/($B22-Inputs!$C$37)/(1+$B22)^$L$27-Inputs!$C$27+Inputs!$C$28)/Inputs!$C$7 -> 142.66103
B23: =WACC!$C$37+(4-2)*$C$5 -> 0.073509306 | C23: =(SUMPRODUCT($C28:$L28,1/(1+$B23)^$C$27:$L$27)*Inputs!$C$23+$L28*Inputs!$C$23*(1+Inputs!$C$37)/($B23-Inputs!$C$37)/(1+$B23)^$L$27-Inputs!$C$27+Inputs!$C$28)/Inputs!$C$7 -> 78.374031 | D23: =(SUMPRODUCT($C29:$L29,1/(1+$B23)^$C$27:$L$27)*Inputs!$C$23+$L29*Inputs!$C$23*(1+Inputs!$C$37)/($B23-Inputs!$C$37)/(1+$B23)^$L$27-Inputs!$C$27+Inputs!$C$28)/Inputs!$C$7 -> 88.511456 | E23: =(SUMPRODUCT($C30:$L30,1/(1+$B23)^$C$27:$L$27)*Inputs!$C$23+$L30*Inputs!$C$23*(1+Inputs!$C$37)/($B23-Inputs!$C$37)/(1+$B23)^$L$27-Inputs!$C$27+Inputs!$C$28)/Inputs!$C$7 -> 99.757398 | F23: =(SUMPRODUCT($C31:$L31,1/(1+$B23)^$C$27:$L$27)*Inputs!$C$23+$L31*Inputs!$C$23*(1+Inputs!$C$37)/($B23-Inputs!$C$37)/(1+$B23)^$L$27-Inputs!$C$27+Inputs!$C$28)/Inputs!$C$7 -> 112.21667 | G23: =(SUMPRODUCT($C32:$L32,1/(1+$B23)^$C$27:$L$27)*Inputs!$C$23+$L32*Inputs!$C$23*(1+Inputs!$C$37)/($B23-Inputs!$C$37)/(1+$B23)^$L$27-Inputs!$C$27+Inputs!$C$28)/Inputs!$C$7 -> 126.00237
B26: Helper: revenue paths for each growth view (years 1 to 10)
C27: 1 | D27: 2 | E27: 3 | F27: 4 | G27: 5 | H27: 6 | I27: 7 | J27: 8 | K27: 9 | L27: 10
B28: =C$18 -> 0.1103 | C28: =Inputs!$C$12*(1+IF(C$27<=Inputs!$C$46,$B28,$B28-($B28-Inputs!$C$37)*MIN(C$27-Inputs!$C$46,Inputs!$C$47)/Inputs!$C$47)) -> 2054.055 | D28: =C28*(1+IF(D$27<=Inputs!$C$46,$B28,$B28-($B28-Inputs!$C$37)*MIN(D$27-Inputs!$C$46,Inputs!$C$47)/Inputs!$C$47)) -> 2280.6173 | E28: =D28*(1+IF(E$27<=Inputs!$C$46,$B28,$B28-($B28-Inputs!$C$37)*MIN(E$27-Inputs!$C$46,Inputs!$C$47)/Inputs!$C$47)) -> 2532.1694 | F28: =E28*(1+IF(F$27<=Inputs!$C$46,$B28,$B28-($B28-Inputs!$C$37)*MIN(F$27-Inputs!$C$46,Inputs!$C$47)/Inputs!$C$47)) -> 2811.4676 | G28: =F28*(1+IF(G$27<=Inputs!$C$46,$B28,$B28-($B28-Inputs!$C$37)*MIN(G$27-Inputs!$C$46,Inputs!$C$47)/Inputs!$C$47)) -> 3121.5725 | H28: =G28*(1+IF(H$27<=Inputs!$C$46,$B28,$B28-($B28-Inputs!$C$37)*MIN(H$27-Inputs!$C$46,Inputs!$C$47)/Inputs!$C$47)) -> 3412.6279 | I28: =H28*(1+IF(I$27<=Inputs!$C$46,$B28,$B28-($B28-Inputs!$C$37)*MIN(I$27-Inputs!$C$46,Inputs!$C$47)/Inputs!$C$47)) -> 3672.6019 | J28: =I28*(1+IF(J$27<=Inputs!$C$46,$B28,$B28-($B28-Inputs!$C$37)*MIN(J$27-Inputs!$C$46,Inputs!$C$47)/Inputs!$C$47)) -> 3889.7262 | K28: =J28*(1+IF(K$27<=Inputs!$C$46,$B28,$B28-($B28-Inputs!$C$37)*MIN(K$27-Inputs!$C$46,Inputs!$C$47)/Inputs!$C$47)) -> 4053.328 | L28: =K28*(1+IF(L$27<=Inputs!$C$46,$B28,$B28-($B28-Inputs!$C$37)*MIN(L$27-Inputs!$C$46,Inputs!$C$47)/Inputs!$C$47)) -> 4154.6612
B29: =D$18 -> 0.1303 | C29: =Inputs!$C$12*(1+IF(C$27<=Inputs!$C$46,$B29,$B29-($B29-Inputs!$C$37)*MIN(C$27-Inputs!$C$46,Inputs!$C$47)/Inputs!$C$47)) -> 2091.055 | D29: =C29*(1+IF(D$27<=Inputs!$C$46,$B29,$B29-($B29-Inputs!$C$37)*MIN(D$27-Inputs!$C$46,Inputs!$C$47)/Inputs!$C$47)) -> 2363.5195 | E29: =D29*(1+IF(E$27<=Inputs!$C$46,$B29,$B29-($B29-Inputs!$C$37)*MIN(E$27-Inputs!$C$46,Inputs!$C$47)/Inputs!$C$47)) -> 2671.4861 | F29: =E29*(1+IF(F$27<=Inputs!$C$46,$B29,$B29-($B29-Inputs!$C$37)*MIN(F$27-Inputs!$C$46,Inputs!$C$47)/Inputs!$C$47)) -> 3019.5807 | G29: =F29*(1+IF(G$27<=Inputs!$C$46,$B29,$B29-($B29-Inputs!$C$37)*MIN(G$27-Inputs!$C$46,Inputs!$C$47)/Inputs!$C$47)) -> 3413.032 | H29: =G29*(1+IF(H$27<=Inputs!$C$46,$B29,$B29-($B29-Inputs!$C$37)*MIN(H$27-Inputs!$C$46,Inputs!$C$47)/Inputs!$C$47)) -> 3785.8717 | I29: =H29*(1+IF(I$27<=Inputs!$C$46,$B29,$B29-($B29-Inputs!$C$37)*MIN(I$27-Inputs!$C$46,Inputs!$C$47)/Inputs!$C$47)) -> 4119.7098 | J29: =I29*(1+IF(J$27<=Inputs!$C$46,$B29,$B29-($B29-Inputs!$C$37)*MIN(J$27-Inputs!$C$46,Inputs!$C$47)/Inputs!$C$47)) -> 4396.2248 | K29: =J29*(1+IF(K$27<=Inputs!$C$46,$B29,$B29-($B29-Inputs!$C$37)*MIN(K$27-Inputs!$C$46,Inputs!$C$47)/Inputs!$C$47)) -> 4598.7149 | L29: =K29*(1+IF(L$27<=Inputs!$C$46,$B29,$B29-($B29-Inputs!$C$37)*MIN(L$27-Inputs!$C$46,Inputs!$C$47)/Inputs!$C$47)) -> 4713.6827
B30: =E$18 -> 0.1503 | C30: =Inputs!$C$12*(1+IF(C$27<=Inputs!$C$46,$B30,$B30-($B30-Inputs!$C$37)*MIN(C$27-Inputs!$C$46,Inputs!$C$47)/Inputs!$C$47)) -> 2128.055 | D30: =C30*(1+IF(D$27<=Inputs!$C$46,$B30,$B30-($B30-Inputs!$C$37)*MIN(D$27-Inputs!$C$46,Inputs!$C$47)/Inputs!$C$47)) -> 2447.9017 | E30: =D30*(1+IF(E$27<=Inputs!$C$46,$B30,$B30-($B30-Inputs!$C$37)*MIN(E$27-Inputs!$C$46,Inputs!$C$47)/Inputs!$C$47)) -> 2815.8213 | F30: =E30*(1+IF(F$27<=Inputs!$C$46,$B30,$B30-($B30-Inputs!$C$37)*MIN(F$27-Inputs!$C$46,Inputs!$C$47)/Inputs!$C$47)) -> 3239.0392 | G30: =F30*(1+IF(G$27<=Inputs!$C$46,$B30,$B30-($B30-Inputs!$C$37)*MIN(G$27-Inputs!$C$46,Inputs!$C$47)/Inputs!$C$47)) -> 3725.8668 | H30: =G30*(1+IF(H$27<=Inputs!$C$46,$B30,$B30-($B30-Inputs!$C$37)*MIN(H$27-Inputs!$C$46,Inputs!$C$47)/Inputs!$C$47)) -> 4192.4944 | I30: =H30*(1+IF(I$27<=Inputs!$C$46,$B30,$B30-($B30-Inputs!$C$37)*MIN(I$27-Inputs!$C$46,Inputs!$C$47)/Inputs!$C$47)) -> 4612.4985 | J30: =I30*(1+IF(J$27<=Inputs!$C$46,$B30,$B30-($B30-Inputs!$C$37)*MIN(J$27-Inputs!$C$46,Inputs!$C$47)/Inputs!$C$47)) -> 4958.9894 | K30: =J30*(1+IF(K$27<=Inputs!$C$46,$B30,$B30-($B30-Inputs!$C$37)*MIN(K$27-Inputs!$C$46,Inputs!$C$47)/Inputs!$C$47)) -> 5207.2364 | L30: =K30*(1+IF(L$27<=Inputs!$C$46,$B30,$B30-($B30-Inputs!$C$37)*MIN(L$27-Inputs!$C$46,Inputs!$C$47)/Inputs!$C$47)) -> 5337.4173
B31: =F$18 -> 0.1703 | C31: =Inputs!$C$12*(1+IF(C$27<=Inputs!$C$46,$B31,$B31-($B31-Inputs!$C$37)*MIN(C$27-Inputs!$C$46,Inputs!$C$47)/Inputs!$C$47)) -> 2165.055 | D31: =C31*(1+IF(D$27<=Inputs!$C$46,$B31,$B31-($B31-Inputs!$C$37)*MIN(D$27-Inputs!$C$46,Inputs!$C$47)/Inputs!$C$47)) -> 2533.7639 | E31: =D31*(1+IF(E$27<=Inputs!$C$46,$B31,$B31-($B31-Inputs!$C$37)*MIN(E$27-Inputs!$C$46,Inputs!$C$47)/Inputs!$C$47)) -> 2965.2639 | F31: =E31*(1+IF(F$27<=Inputs!$C$46,$B31,$B31-($B31-Inputs!$C$37)*MIN(F$27-Inputs!$C$46,Inputs!$C$47)/Inputs!$C$47)) -> 3470.2483 | G31: =F31*(1+IF(G$27<=Inputs!$C$46,$B31,$B31-($B31-Inputs!$C$37)*MIN(G$27-Inputs!$C$46,Inputs!$C$47)/Inputs!$C$47)) -> 4061.2316 | H31: =G31*(1+IF(H$27<=Inputs!$C$46,$B31,$B31-($B31-Inputs!$C$37)*MIN(H$27-Inputs!$C$46,Inputs!$C$47)/Inputs!$C$47)) -> 4634.8399 | I31: =H31*(1+IF(I$27<=Inputs!$C$46,$B31,$B31-($B31-Inputs!$C$37)*MIN(I$27-Inputs!$C$46,Inputs!$C$47)/Inputs!$C$47)) -> 5154.7763 | J31: =I31*(1+IF(J$27<=Inputs!$C$46,$B31,$B31-($B31-Inputs!$C$37)*MIN(J$27-Inputs!$C$46,Inputs!$C$47)/Inputs!$C$47)) -> 5583.2413 | K31: =J31*(1+IF(K$27<=Inputs!$C$46,$B31,$B31-($B31-Inputs!$C$37)*MIN(K$27-Inputs!$C$46,Inputs!$C$47)/Inputs!$C$47)) -> 5885.0713 | L31: =K31*(1+IF(L$27<=Inputs!$C$46,$B31,$B31-($B31-Inputs!$C$37)*MIN(L$27-Inputs!$C$46,Inputs!$C$47)/Inputs!$C$47)) -> 6032.1981
B32: =G$18 -> 0.1903 | C32: =Inputs!$C$12*(1+IF(C$27<=Inputs!$C$46,$B32,$B32-($B32-Inputs!$C$37)*MIN(C$27-Inputs!$C$46,Inputs!$C$47)/Inputs!$C$47)) -> 2202.055 | D32: =C32*(1+IF(D$27<=Inputs!$C$46,$B32,$B32-($B32-Inputs!$C$37)*MIN(D$27-Inputs!$C$46,Inputs!$C$47)/Inputs!$C$47)) -> 2621.1061 | E32: =D32*(1+IF(E$27<=Inputs!$C$46,$B32,$B32-($B32-Inputs!$C$37)*MIN(E$27-Inputs!$C$46,Inputs!$C$47)/Inputs!$C$47)) -> 3119.9026 | F32: =E32*(1+IF(F$27<=Inputs!$C$46,$B32,$B32-($B32-Inputs!$C$37)*MIN(F$27-Inputs!$C$46,Inputs!$C$47)/Inputs!$C$47)) -> 3713.62 | G32: =F32*(1+IF(G$27<=Inputs!$C$46,$B32,$B32-($B32-Inputs!$C$37)*MIN(G$27-Inputs!$C$46,Inputs!$C$47)/Inputs!$C$47)) -> 4420.3219 | H32: =G32*(1+IF(H$27<=Inputs!$C$46,$B32,$B32-($B32-Inputs!$C$37)*MIN(H$27-Inputs!$C$46,Inputs!$C$47)/Inputs!$C$47)) -> 5115.3733 | I32: =H32*(1+IF(I$27<=Inputs!$C$46,$B32,$B32-($B32-Inputs!$C$37)*MIN(I$27-Inputs!$C$46,Inputs!$C$47)/Inputs!$C$47)) -> 5750.6004 | J32: =I32*(1+IF(J$27<=Inputs!$C$46,$B32,$B32-($B32-Inputs!$C$37)*MIN(J$27-Inputs!$C$46,Inputs!$C$47)/Inputs!$C$47)) -> 6274.5951 | K32: =J32*(1+IF(K$27<=Inputs!$C$46,$B32,$B32-($B32-Inputs!$C$37)*MIN(K$27-Inputs!$C$46,Inputs!$C$47)/Inputs!$C$47)) -> 6638.8981 | L32: =K32*(1+IF(L$27<=Inputs!$C$46,$B32,$B32-($B32-Inputs!$C$37)*MIN(L$27-Inputs!$C$46,Inputs!$C$47)/Inputs!$C$47)) -> 6804.8705

Sheet Check
B2: TMX Group (X): check against the Python pipeline
B3: Python values are typed in (blue) from the pipeline that runs the site. Each row passes if the two agree within the tolerance.
B5: Item | C5: This workbook | D5: Python pipeline | E5: Difference | F5: Result
B6: Unlevered free-cash-flow margin | C6: =Inputs!$C$23 -> 0.35987135 | D6: 0.35987135 | E6: =C6-D6 -> 1.3513514e-09 | F6: =IF(ABS(E6)<=0.00005,"Pass","Check") -> Pass
B7: Group median unlevered beta | C7: =WACC!$C$14 -> 0.60913153 | D7: 0.60913153 | E7: =C7-D7 -> -3.7891912e-13 | F7: =IF(ABS(E7)<=0.0005,"Pass","Check") -> Pass
B8: WACC | C8: =WACC!$C$37 -> 0.063509306 | D8: 0.06350931 | E8: =C8-D8 -> -4.3584779e-09 | F8: =IF(ABS(E8)<=0.00005,"Pass","Check") -> Pass
B9: Terminal growth | C9: =Inputs!$C$37 -> 0.025 | D9: 0.025 | E9: =C9-D9 -> 0 | F9: =IF(ABS(E9)<=0.00005,"Pass","Check") -> Pass
B10: Anchor | C10: =Inputs!$C$43 -> 0.1503 | D10: 0.1503 | E10: =C10-D10 -> 0 | F10: =IF(ABS(E10)<=0.00005,"Pass","Check") -> Pass
B11: Implied growth, base case | C11: =Solver!$W$7 -> 0.013955097 | D11: 0.0139551 | E11: =C11-D11 -> -2.9524716e-09 | F11: =IF(ABS(E11)<=0.00005,"Pass","Check") -> Pass
B12: Implied growth, WACC one point higher | C12: =Sensitivity!$E$14 -> 0.052654773 | D12: 0.05265473 | E12: =C12-D12 -> 4.2996902e-08 | F12: =IF(ABS(E12)<=0.0002,"Pass","Check") -> Pass
B13: Value per share at the anchor (C$) | C13: =DCF!$C$41 -> 129.38595 | D13: 129.38595 | E13: =C13-D13 -> 1.4363479e-09 | F13: =IF(ABS(E13)<=0.02,"Pass","Check") -> Pass
B14: Panel A value minus price (C$) | C14: =DCF!$C$21-DCF!$C$22 -> -3.7296388e-10 | D14: 0 | E14: =C14-D14 -> -3.7296388e-10 | F14: =IF(ABS(E14)<=0.01,"Pass","Check") -> Pass | G14: Panel B on the DCF tab uses your view; with the yellow cell at the anchor it matches the pipeline.
B16: Overall | C16: =IF(COUNTIF(F6:F14,"Pass")=9,"All checks pass","Review") -> All checks pass
