Workbook

Sheet Cover
B2: Priced In: Verisk (VRSK)
B3: Reverse DCF, model v1.0. Inputs as of the Oct 13, 2026 close; model locked Oct 14, 2026 (commit 0735af0).
B4: Data and software | US | reports in USD
B6: The question
B7: What revenue growth over the next five years does today's price imply, and is that more or less than the company has delivered and analysts expect?
B9: Answer
B10: Price at the lock ($) | C10: =Inputs!$C$6 -> 176.62876
B11: Implied 5-year revenue growth | C11: =Solver!$W$7 -> 0.02636698
B12: Anchor (history and analysts) | C12: =Inputs!$C$43 -> 0.062755445
B13: Gap (implied - anchor) | C13: =C11-C12 -> -0.036388465
B14: Verdict | C14: =IF(C13>=Inputs!$C$44,"Expectations too high",IF(C13<=-Inputs!$C$44,"Expectations too low","About right")) -> Expectations too low
B15: WACC | C15: =WACC!$C$35 -> 0.081941394
B16: Terminal growth | C16: =Inputs!$C$37 -> 0.0283
B17: Unlevered free-cash-flow margin | C17: =Inputs!$C$23 -> 0.45461783
B18: Your view of growth (Inputs, yellow) | C18: =Inputs!$C$45 -> 0.062755445
B19: Value per share at your view ($) | C19: =DCF!$C$41 -> 225.52226
B20: Upside or downside at your view | C20: =DCF!$C$43 -> 0.27681502
B25: How to use this file
B26: 1. Change any blue cell on Inputs, History or WACC; everything recalculates, including the solver.
B27: 2. The Solver tab finds implied growth by bisection with formulas, so you never need Goal Seek. 40 steps narrow a 150-point range to well under 0.0001%.
B28: 3. Type your own growth view in the yellow cell on Inputs; DCF panel B and this page show what the stock is worth if you're right.
B29: 4. Check confirms this workbook matches the Python pipeline that runs the site.
B31: Colour key
B32: Typed input with a source | C32: 1234
B33: Formula | C33: =C32*2 -> 2468
B34: Link to another tab | C34: =Inputs!$C$12 -> 3140
B35: Your view (edit this one) | C35: =Inputs!$C$45 -> 0.062755445
B37: Live site
B38: https://claude.ai/artifact/DS3n4CgaKxaSLzkXDsBKuK
B40: Built by Rohan Jayapalan. Not investment advice.

Sheet Inputs
B2: Verisk (VRSK): inputs
B3: Blue cells are typed inputs with a source. Black cells are formulas. Change a blue cell and every tab recalculates.
B5: Market and price
B6: Price per share at the lock ($) | C6: 176.62876 | E6: Market cap divided by shares from Stock Analysis at the Oct 13, 2026 close.
B7: Diluted shares outstanding (mm) | C7: 130.16 | E7: Stock Analysis statistics page, Oct 13, 2026.
B8: Market value of equity ($mm) | C8: =C6*C7 -> 22990 | E8: Price x shares.
B10: Trailing 12 months
B11: Revenue, reported ($mm) | C11: 3140 | E11: Stock Analysis income statement, trailing 12 months.
B12: Revenue used in the model ($mm) | C12: =C11 -> 3140 | E12: Same as reported.
B13: Free cash flow, reported (cash from operations - capex) ($mm) | C13: 1240 | E13: Stock Analysis cash flow statement, trailing 12 months.
B14: Free cash flow before adjustments ($mm) | C14: =C13 -> 1240 | E14: Same as reported.
B15: Less: adjustments ($mm) | C15: 0 | E15: None for this company.
B16: Free cash flow used ($mm) | C16: =C14-C15 -> 1240
B17: Operating income ($mm) | C17: 1410 | E17: Stock Analysis, trailing 12 months.
B18: Pretax income ($mm) | C18: 1160 | E18: Stock Analysis, trailing 12 months.
B19: Interest proxy: operating income - pretax, floored at zero ($mm) | C19: =MAX(0,C17-C18) -> 250 | E19: Net interest and other non-operating costs. Adding it back (after tax) turns levered FCF into unlevered FCF.
B20: Tax rate | C20: 0.25 | E20: Statutory blend: 25% US (21% federal plus state), 26.5% Canada (federal plus Ontario).
B21: After-tax interest added back ($mm) | C21: =C19*(1-C20) -> 187.5
B22: Unlevered free cash flow ($mm) | C22: =C16+C21 -> 1427.5
B23: Unlevered free-cash-flow margin | C23: =C22/C12 -> 0.45461783 | E23: Held flat for all 10 years in the model.
B24: EBITDA ($mm) | C24: 1520 | E24: Stock Analysis, trailing 12 months.
B26: Balance sheet
B27: Total debt ($mm) | C27: 4620 | E27: Stock Analysis balance sheet, latest quarter.
B28: Cash and equivalents ($mm) | C28: 552.2 | E28: Stock Analysis balance sheet, latest quarter.
B29: Net debt ($mm) | C29: =C27-C28 -> 4067.8
B31: Rates
B32: 10-year US Treasury yield | C32: 0.0521 | E32: US Treasury daily par yield curve, Oct 13, 2026.
B33: 10-year TIPS real yield | C33: 0.0288 | E33: US Treasury daily real yield curve, Oct 13, 2026.
B34: Breakeven inflation | C34: =C32-C33 -> 0.0233 | E34: Nominal minus real: the market's inflation expectation.
B35: Risk-free rate used | C35: =C32 -> 0.0521
B36: Real growth added to inflation | C36: 0.005 | E36: Half a point of long-run real growth.
B37: Terminal growth | C37: =MIN(C34+C36,C35) -> 0.0283 | E37: Capped at the risk-free rate.
B38: Equity risk premium | C38: 0.0423 | E38: Damodaran implied equity risk premium, start of 2026.
B40: Growth anchor and verdict
B41: Past revenue growth (CAGR) | C41: =History!$C$12 -> 0.06471089 | E41: FY2023 to the 12 months ended June 2026
B42: Analysts' revenue growth forecast | C42: 0.0608 | E42: Analysts' 3-year revenue CAGR forecast (stockanalysis)
B43: Anchor (average of the two) | C43: =AVERAGE(C41:C42) -> 0.062755445 | E43: AVERAGE skips the n/a text when history isn't used.
B44: Verdict band (+/-) | C44: 0.03 | E44: Set before any backtest and never changed.
B45: Your view of 5-year revenue growth | C45: 0.062755445 | E45: Type your own view. It starts at the anchor. DCF panel B and the Cover show what the stock is worth at your view.
B46: Years at the solved growth rate | C46: 5 | E46: Model v1.0: 5 years at the growth rate, then a straight-line fade.
B47: Years of fade to terminal growth | C47: 5 | E47: Years 1 to 10 are on the Solver and DCF tabs; years past 10 grow at the terminal rate.

Sheet History
B2: Verisk (VRSK): revenue history
B3: Revenue from Stock Analysis income statements; the window is chosen so acquisitions and disposals don't count as growth.
B5: Fiscal year | C5: FY2021 | D5: FY2022 | E5: FY2023 | F5: FY2024 | G5: FY2025 | H5: TTM Jun-26
B6: Revenue ($mm) | C6: 2463 | D6: 2497 | E6: 2681 | F6: 2882 | G6: 3073 | H6: 3136
B7: Growth on the prior year | D7: =D6/C6-1 -> 0.013804304 | E7: =E6/D6-1 -> 0.073688426 | F7: =F6/E6-1 -> 0.074972025 | G7: =G6/F6-1 -> 0.066273421
B8: Source note: divestitures reduce reported history
B10: History window
B11: Start year | C11: FY2023 | E11: Years from start to TTM | G11: 2.5
B12: Revenue CAGR, start to TTM | C12: =(H6/INDEX(C6:H6,MATCH(C11,C5:H5,0)))^(1/G11)-1 -> 0.06471089 | I12: FY2023 to the 12 months ended June 2026. Starts after Verisk sold its non-insurance units so the window is like for like.

Sheet WACC
B2: Verisk (VRSK): cost of capital
B3: Bottom-up beta: the median unlevered beta of the company's group, relevered for this company's debt.
B5: Peer | C5: Raw beta | D5: Debt ($mm) | E5: Equity ($mm) | F5: Tax rate | G5: Unlevered beta
B6: FactSet (FDS) | C6: 0.76933023 | D6: 1540 | E6: 10290 | F6: 0.25 | G6: =C6/(1+(1-F6)*D6/E6) -> 0.6916914 | H6: Raw betas: 60 monthly returns to Sep 2026 against the S&P 500 (S&P/TSX for TMX); Cboe uses Stock Analysis's 5-year beta. Debt and equity from Stock Analysis, Oct 13, 2026.
B7: Thomson Reuters (TRI) | C7: 0.76655834 | D7: 3210 | E7: 45600 | F7: 0.25 | G7: =C7/(1+(1-F7)*D7/E7) -> 0.72811666
B8: Broadridge (BR) | C8: 0.92313471 | D8: 3520 | E8: 19020 | F8: 0.25 | G8: =C8/(1+(1-F8)*D8/E8) -> 0.81061968
B9: SS&C Technologies (SSNC) | C9: 1.0872965 | D9: 7780 | E9: 19010 | F9: 0.25 | G9: =C9/(1+(1-F9)*D9/E9) -> 0.83193826
B10: Verisk (VRSK) | C10: 0.68789784 | D10: 4620 | E10: 22990 | F10: 0.25 | G10: =C10/(1+(1-F10)*D10/E10) -> 0.59779896
B12: Group median unlevered beta | C12: =MEDIAN(G6:G10) -> 0.72811666
B13: Debt ($mm) | C13: =Inputs!$C$27 -> 4620
B14: Market value of equity ($mm) | C14: =Inputs!$C$8 -> 22990
B15: Tax rate | C15: =Inputs!$C$20 -> 0.25
B16: Relevered beta | C16: =WACC!$C$12*(1+(1-WACC!$C$15)*WACC!$C$13/WACC!$C$14) -> 0.83785673 | H16: Hamada: unlevered beta x (1 + (1 - tax) x debt / equity).
B17: Risk-free rate | C17: =Inputs!$C$35 -> 0.0521
B18: Equity risk premium | C18: =Inputs!$C$38 -> 0.0423
B19: Cost of equity | C19: =WACC!$C$17+WACC!$C$16*WACC!$C$18 -> 0.08754134 | H19: CAPM: risk-free + beta x premium.
B21: Debt-to-EBITDA spread table
B22: Debt / EBITDA below | C22: Spread
B23: 1 | C23: 0.01 | H23: Synthetic spread over the risk-free rate by leverage, a simplified version of Damodaran's ratings table; the last row covers anything at 4x or above.
B24: 2 | C24: 0.0125
B25: 3 | C25: 0.016
B26: 4 | C26: 0.02
B27: 99 | C27: 0.0275
B29: Debt / EBITDA | C29: =Inputs!$C$27/Inputs!$C$24 -> 3.0394737
B30: Credit spread | C30: =INDEX(C23:C27,COUNTIF(B23:B27,"<="&WACC!$C$29)+1) -> 0.02 | H30: First row whose limit is above this company's leverage.
B31: Pre-tax cost of debt | C31: =WACC!$C$17+WACC!$C$30 -> 0.0721
B32: After-tax cost of debt | C32: =WACC!$C$31*(1-WACC!$C$15) -> 0.054075
B33: Weight of debt | C33: =WACC!$C$13/(WACC!$C$13+WACC!$C$14) -> 0.16733068 | H33: Market-value weights.
B34: Weight of equity | C34: =1-WACC!$C$33 -> 0.83266932
B35: WACC | C35: =WACC!$C$34*WACC!$C$19+WACC!$C$33*WACC!$C$32 -> 0.081941394

Sheet Solver
A1: Solver: bisection for the growth rate that makes the model equal the price (replaces Goal Seek)
B2: Revenue | C2: =Inputs!$C$12 -> 3140 | D2: Margin | E2: =Inputs!$C$23 -> 0.45461783 | F2: Debt | G2: =Inputs!$C$27 -> 4620 | H2: Cash | I2: =Inputs!$C$28 -> 552.2 | J2: Shares | K2: =Inputs!$C$7 -> 130.16 | L2: Price | M2: =Inputs!$C$6 -> 176.62876 | N2: Years | O2: =Inputs!$C$46 -> 5 | P2: Fade | Q2: =Inputs!$C$47 -> 5
D3: Year | E3: 1 | F3: 2 | G3: 3 | H3: 4 | I3: 5 | J3: 6 | K3: 7 | L3: 8 | M3: 9 | N3: 10
A4: Each row tries the midpoint of the current range. If the value per share is above the price, the answer is lower, so the top of the range moves down; otherwise the bottom moves up.
A6: Base case: model WACC and terminal growth (40 steps) | E6: WACC | F6: =WACC!$C$35 -> 0.081941394 | G6: Terminal growth | I6: =Inputs!$C$37 -> 0.0283 | W6: Implied growth
A7: Step | B7: Low | C7: High | D7: Mid | E7: Rev Y1 | F7: Rev Y2 | G7: Rev Y3 | H7: Rev Y4 | I7: Rev Y5 | J7: Rev Y6 | K7: Rev Y7 | L7: Rev Y8 | M7: Rev Y9 | N7: Rev Y10 | O7: PV of FCF | P7: PV of TV | Q7: EV | R7: Equity | S7: Per share | T7: Value - price | W7: =$D$47 -> 0.02636698
A8: 1 | B8: -0.5 | C8: 1 | D8: =(B8+C8)/2 -> 0.25 | E8: =$C$2*(1+IF(E$3<=$O$2,$D8,$D8-($D8-$I$6)*MIN(E$3-$O$2,$Q$2)/$Q$2)) -> 3925 | F8: =E8*(1+IF(F$3<=$O$2,$D8,$D8-($D8-$I$6)*MIN(F$3-$O$2,$Q$2)/$Q$2)) -> 4906.25 | G8: =F8*(1+IF(G$3<=$O$2,$D8,$D8-($D8-$I$6)*MIN(G$3-$O$2,$Q$2)/$Q$2)) -> 6132.8125 | H8: =G8*(1+IF(H$3<=$O$2,$D8,$D8-($D8-$I$6)*MIN(H$3-$O$2,$Q$2)/$Q$2)) -> 7666.0156 | I8: =H8*(1+IF(I$3<=$O$2,$D8,$D8-($D8-$I$6)*MIN(I$3-$O$2,$Q$2)/$Q$2)) -> 9582.5195 | J8: =I8*(1+IF(J$3<=$O$2,$D8,$D8-($D8-$I$6)*MIN(J$3-$O$2,$Q$2)/$Q$2)) -> 11553.26 | K8: =J8*(1+IF(K$3<=$O$2,$D8,$D8-($D8-$I$6)*MIN(K$3-$O$2,$Q$2)/$Q$2)) -> 13417.032 | L8: =K8*(1+IF(L$3<=$O$2,$D8,$D8-($D8-$I$6)*MIN(L$3-$O$2,$Q$2)/$Q$2)) -> 14986.557 | M8: =L8*(1+IF(M$3<=$O$2,$D8,$D8-($D8-$I$6)*MIN(M$3-$O$2,$Q$2)/$Q$2)) -> 16075.18 | N8: =M8*(1+IF(N$3<=$O$2,$D8,$D8-($D8-$I$6)*MIN(N$3-$O$2,$Q$2)/$Q$2)) -> 16530.108 | O8: =SUMPRODUCT(E8:N8,1/(1+$F$6)^$E$3:$N$3)*$E$2 -> 28671.256 | P8: =N8*$E$2*(1+$I$6)/($F$6-$I$6)/(1+$F$6)^$N$3 -> 65539.718 | Q8: =O8+P8 -> 94210.974 | R8: =Q8-$G$2+$I$2 -> 90143.174 | S8: =R8/$K$2 -> 692.55665 | T8: =S8-$M$2 -> 515.92789 | W8: =IF(OR(ABS(W7+0.5)<0.000001,ABS(W7-1)<0.000001),"Out of range","Solved") -> Solved
A9: 2 | B9: =IF(T8>0,B8,D8) -> -0.5 | C9: =IF(T8>0,D8,C8) -> 0.25 | D9: =(B9+C9)/2 -> -0.125 | E9: =$C$2*(1+IF(E$3<=$O$2,$D9,$D9-($D9-$I$6)*MIN(E$3-$O$2,$Q$2)/$Q$2)) -> 2747.5 | F9: =E9*(1+IF(F$3<=$O$2,$D9,$D9-($D9-$I$6)*MIN(F$3-$O$2,$Q$2)/$Q$2)) -> 2404.0625 | G9: =F9*(1+IF(G$3<=$O$2,$D9,$D9-($D9-$I$6)*MIN(G$3-$O$2,$Q$2)/$Q$2)) -> 2103.5547 | H9: =G9*(1+IF(H$3<=$O$2,$D9,$D9-($D9-$I$6)*MIN(H$3-$O$2,$Q$2)/$Q$2)) -> 1840.6104 | I9: =H9*(1+IF(I$3<=$O$2,$D9,$D9-($D9-$I$6)*MIN(I$3-$O$2,$Q$2)/$Q$2)) -> 1610.5341 | J9: =I9*(1+IF(J$3<=$O$2,$D9,$D9-($D9-$I$6)*MIN(J$3-$O$2,$Q$2)/$Q$2)) -> 1458.5963 | K9: =J9*(1+IF(K$3<=$O$2,$D9,$D9-($D9-$I$6)*MIN(K$3-$O$2,$Q$2)/$Q$2)) -> 1365.7129 | L9: =K9*(1+IF(L$3<=$O$2,$D9,$D9-($D9-$I$6)*MIN(L$3-$O$2,$Q$2)/$Q$2)) -> 1320.617 | M9: =L9*(1+IF(M$3<=$O$2,$D9,$D9-($D9-$I$6)*MIN(M$3-$O$2,$Q$2)/$Q$2)) -> 1317.5004 | N9: =M9*(1+IF(N$3<=$O$2,$D9,$D9-($D9-$I$6)*MIN(N$3-$O$2,$Q$2)/$Q$2)) -> 1354.7856 | O9: =SUMPRODUCT(E9:N9,1/(1+$F$6)^$E$3:$N$3)*$E$2 -> 5613.6018 | P9: =N9*$E$2*(1+$I$6)/($F$6-$I$6)/(1+$F$6)^$N$3 -> 5371.548 | Q9: =O9+P9 -> 10985.15 | R9: =Q9-$G$2+$I$2 -> 6917.3498 | S9: =R9/$K$2 -> 53.144974 | T9: =S9-$M$2 -> -123.48379
A10: 3 | B10: =IF(T9>0,B9,D9) -> -0.125 | C10: =IF(T9>0,D9,C9) -> 0.25 | D10: =(B10+C10)/2 -> 0.0625 | E10: =$C$2*(1+IF(E$3<=$O$2,$D10,$D10-($D10-$I$6)*MIN(E$3-$O$2,$Q$2)/$Q$2)) -> 3336.25 | F10: =E10*(1+IF(F$3<=$O$2,$D10,$D10-($D10-$I$6)*MIN(F$3-$O$2,$Q$2)/$Q$2)) -> 3544.7656 | G10: =F10*(1+IF(G$3<=$O$2,$D10,$D10-($D10-$I$6)*MIN(G$3-$O$2,$Q$2)/$Q$2)) -> 3766.3135 | H10: =G10*(1+IF(H$3<=$O$2,$D10,$D10-($D10-$I$6)*MIN(H$3-$O$2,$Q$2)/$Q$2)) -> 4001.7081 | I10: =H10*(1+IF(I$3<=$O$2,$D10,$D10-($D10-$I$6)*MIN(I$3-$O$2,$Q$2)/$Q$2)) -> 4251.8148 | J10: =I10*(1+IF(J$3<=$O$2,$D10,$D10-($D10-$I$6)*MIN(J$3-$O$2,$Q$2)/$Q$2)) -> 4488.4708 | K10: =J10*(1+IF(K$3<=$O$2,$D10,$D10-($D10-$I$6)*MIN(K$3-$O$2,$Q$2)/$Q$2)) -> 4707.598 | L10: =K10*(1+IF(L$3<=$O$2,$D10,$D10-($D10-$I$6)*MIN(L$3-$O$2,$Q$2)/$Q$2)) -> 4905.2229 | M10: =L10*(1+IF(M$3<=$O$2,$D10,$D10-($D10-$I$6)*MIN(M$3-$O$2,$Q$2)/$Q$2)) -> 5077.5925 | N10: =M10*(1+IF(N$3<=$O$2,$D10,$D10-($D10-$I$6)*MIN(N$3-$O$2,$Q$2)/$Q$2)) -> 5221.2883 | O10: =SUMPRODUCT(E10:N10,1/(1+$F$6)^$E$3:$N$3)*$E$2 -> 12670.862 | P10: =N10*$E$2*(1+$I$6)/($F$6-$I$6)/(1+$F$6)^$N$3 -> 20701.726 | Q10: =O10+P10 -> 33372.588 | R10: =Q10-$G$2+$I$2 -> 29304.788 | S10: =R10/$K$2 -> 225.14434 | T10: =S10-$M$2 -> 48.51558
A11: 4 | B11: =IF(T10>0,B10,D10) -> -0.125 | C11: =IF(T10>0,D10,C10) -> 0.0625 | D11: =(B11+C11)/2 -> -0.03125 | E11: =$C$2*(1+IF(E$3<=$O$2,$D11,$D11-($D11-$I$6)*MIN(E$3-$O$2,$Q$2)/$Q$2)) -> 3041.875 | F11: =E11*(1+IF(F$3<=$O$2,$D11,$D11-($D11-$I$6)*MIN(F$3-$O$2,$Q$2)/$Q$2)) -> 2946.8164 | G11: =F11*(1+IF(G$3<=$O$2,$D11,$D11-($D11-$I$6)*MIN(G$3-$O$2,$Q$2)/$Q$2)) -> 2854.7284 | H11: =G11*(1+IF(H$3<=$O$2,$D11,$D11-($D11-$I$6)*MIN(H$3-$O$2,$Q$2)/$Q$2)) -> 2765.5181 | I11: =H11*(1+IF(I$3<=$O$2,$D11,$D11-($D11-$I$6)*MIN(I$3-$O$2,$Q$2)/$Q$2)) -> 2679.0957 | J11: =I11*(1+IF(J$3<=$O$2,$D11,$D11-($D11-$I$6)*MIN(J$3-$O$2,$Q$2)/$Q$2)) -> 2627.282 | K11: =J11*(1+IF(K$3<=$O$2,$D11,$D11-($D11-$I$6)*MIN(K$3-$O$2,$Q$2)/$Q$2)) -> 2607.7613 | L11: =K11*(1+IF(L$3<=$O$2,$D11,$D11-($D11-$I$6)*MIN(L$3-$O$2,$Q$2)/$Q$2)) -> 2619.444 | M11: =L11*(1+IF(M$3<=$O$2,$D11,$D11-($D11-$I$6)*MIN(M$3-$O$2,$Q$2)/$Q$2)) -> 2662.3767 | N11: =M11*(1+IF(N$3<=$O$2,$D11,$D11-($D11-$I$6)*MIN(N$3-$O$2,$Q$2)/$Q$2)) -> 2737.722 | O11: =SUMPRODUCT(E11:N11,1/(1+$F$6)^$E$3:$N$3)*$E$2 -> 8410.2529 | P11: =N11*$E$2*(1+$I$6)/($F$6-$I$6)/(1+$F$6)^$N$3 -> 10854.71 | Q11: =O11+P11 -> 19264.963 | R11: =Q11-$G$2+$I$2 -> 15197.163 | S11: =R11/$K$2 -> 116.75755 | T11: =S11-$M$2 -> -59.871213
A12: 5 | B12: =IF(T11>0,B11,D11) -> -0.03125 | C12: =IF(T11>0,D11,C11) -> 0.0625 | D12: =(B12+C12)/2 -> 0.015625 | E12: =$C$2*(1+IF(E$3<=$O$2,$D12,$D12-($D12-$I$6)*MIN(E$3-$O$2,$Q$2)/$Q$2)) -> 3189.0625 | F12: =E12*(1+IF(F$3<=$O$2,$D12,$D12-($D12-$I$6)*MIN(F$3-$O$2,$Q$2)/$Q$2)) -> 3238.8916 | G12: =F12*(1+IF(G$3<=$O$2,$D12,$D12-($D12-$I$6)*MIN(G$3-$O$2,$Q$2)/$Q$2)) -> 3289.4993 | H12: =G12*(1+IF(H$3<=$O$2,$D12,$D12-($D12-$I$6)*MIN(H$3-$O$2,$Q$2)/$Q$2)) -> 3340.8977 | I12: =H12*(1+IF(I$3<=$O$2,$D12,$D12-($D12-$I$6)*MIN(I$3-$O$2,$Q$2)/$Q$2)) -> 3393.0992 | J12: =I12*(1+IF(J$3<=$O$2,$D12,$D12-($D12-$I$6)*MIN(J$3-$O$2,$Q$2)/$Q$2)) -> 3454.7179 | K12: =J12*(1+IF(K$3<=$O$2,$D12,$D12-($D12-$I$6)*MIN(K$3-$O$2,$Q$2)/$Q$2)) -> 3526.2133 | L12: =K12*(1+IF(L$3<=$O$2,$D12,$D12-($D12-$I$6)*MIN(L$3-$O$2,$Q$2)/$Q$2)) -> 3608.1272 | M12: =L12*(1+IF(M$3<=$O$2,$D12,$D12-($D12-$I$6)*MIN(M$3-$O$2,$Q$2)/$Q$2)) -> 3701.0906 | N12: =M12*(1+IF(N$3<=$O$2,$D12,$D12-($D12-$I$6)*MIN(N$3-$O$2,$Q$2)/$Q$2)) -> 3805.8315 | O12: =SUMPRODUCT(E12:N12,1/(1+$F$6)^$E$3:$N$3)*$E$2 -> 10319.249 | P12: =N12*$E$2*(1+$I$6)/($F$6-$I$6)/(1+$F$6)^$N$3 -> 15089.625 | Q12: =O12+P12 -> 25408.873 | R12: =Q12-$G$2+$I$2 -> 21341.073 | S12: =R12/$K$2 -> 163.96031 | T12: =S12-$M$2 -> -12.668459
A13: 6 | B13: =IF(T12>0,B12,D12) -> 0.015625 | C13: =IF(T12>0,D12,C12) -> 0.0625 | D13: =(B13+C13)/2 -> 0.0390625 | E13: =$C$2*(1+IF(E$3<=$O$2,$D13,$D13-($D13-$I$6)*MIN(E$3-$O$2,$Q$2)/$Q$2)) -> 3262.6562 | F13: =E13*(1+IF(F$3<=$O$2,$D13,$D13-($D13-$I$6)*MIN(F$3-$O$2,$Q$2)/$Q$2)) -> 3390.1038 | G13: =F13*(1+IF(G$3<=$O$2,$D13,$D13-($D13-$I$6)*MIN(G$3-$O$2,$Q$2)/$Q$2)) -> 3522.5297 | H13: =G13*(1+IF(H$3<=$O$2,$D13,$D13-($D13-$I$6)*MIN(H$3-$O$2,$Q$2)/$Q$2)) -> 3660.1285 | I13: =H13*(1+IF(I$3<=$O$2,$D13,$D13-($D13-$I$6)*MIN(I$3-$O$2,$Q$2)/$Q$2)) -> 3803.1023 | J13: =I13*(1+IF(J$3<=$O$2,$D13,$D13-($D13-$I$6)*MIN(J$3-$O$2,$Q$2)/$Q$2)) -> 3943.4748 | K13: =J13*(1+IF(K$3<=$O$2,$D13,$D13-($D13-$I$6)*MIN(K$3-$O$2,$Q$2)/$Q$2)) -> 4080.5401 | L13: =K13*(1+IF(L$3<=$O$2,$D13,$D13-($D13-$I$6)*MIN(L$3-$O$2,$Q$2)/$Q$2)) -> 4213.5861 | M13: =L13*(1+IF(M$3<=$O$2,$D13,$D13-($D13-$I$6)*MIN(M$3-$O$2,$Q$2)/$Q$2)) -> 4341.9003 | N13: =M13*(1+IF(N$3<=$O$2,$D13,$D13-($D13-$I$6)*MIN(N$3-$O$2,$Q$2)/$Q$2)) -> 4464.7761 | O13: =SUMPRODUCT(E13:N13,1/(1+$F$6)^$E$3:$N$3)*$E$2 -> 11434.179 | P13: =N13*$E$2*(1+$I$6)/($F$6-$I$6)/(1+$F$6)^$N$3 -> 17702.254 | Q13: =O13+P13 -> 29136.433 | R13: =Q13-$G$2+$I$2 -> 25068.633 | S13: =R13/$K$2 -> 192.5986 | T13: =S13-$M$2 -> 15.969831
A14: 7 | B14: =IF(T13>0,B13,D13) -> 0.015625 | C14: =IF(T13>0,D13,C13) -> 0.0390625 | D14: =(B14+C14)/2 -> 0.02734375 | E14: =$C$2*(1+IF(E$3<=$O$2,$D14,$D14-($D14-$I$6)*MIN(E$3-$O$2,$Q$2)/$Q$2)) -> 3225.8594 | F14: =E14*(1+IF(F$3<=$O$2,$D14,$D14-($D14-$I$6)*MIN(F$3-$O$2,$Q$2)/$Q$2)) -> 3314.0665 | G14: =F14*(1+IF(G$3<=$O$2,$D14,$D14-($D14-$I$6)*MIN(G$3-$O$2,$Q$2)/$Q$2)) -> 3404.6855 | H14: =G14*(1+IF(H$3<=$O$2,$D14,$D14-($D14-$I$6)*MIN(H$3-$O$2,$Q$2)/$Q$2)) -> 3497.7823 | I14: =H14*(1+IF(I$3<=$O$2,$D14,$D14-($D14-$I$6)*MIN(I$3-$O$2,$Q$2)/$Q$2)) -> 3593.4248 | J14: =I14*(1+IF(J$3<=$O$2,$D14,$D14-($D14-$I$6)*MIN(J$3-$O$2,$Q$2)/$Q$2)) -> 3692.3698 | K14: =J14*(1+IF(K$3<=$O$2,$D14,$D14-($D14-$I$6)*MIN(K$3-$O$2,$Q$2)/$Q$2)) -> 3794.7453 | L14: =K14*(1+IF(L$3<=$O$2,$D14,$D14-($D14-$I$6)*MIN(L$3-$O$2,$Q$2)/$Q$2)) -> 3900.6851 | M14: =L14*(1+IF(M$3<=$O$2,$D14,$D14-($D14-$I$6)*MIN(M$3-$O$2,$Q$2)/$Q$2)) -> 4010.3285 | N14: =M14*(1+IF(N$3<=$O$2,$D14,$D14-($D14-$I$6)*MIN(N$3-$O$2,$Q$2)/$Q$2)) -> 4123.8208 | O14: =SUMPRODUCT(E14:N14,1/(1+$F$6)^$E$3:$N$3)*$E$2 -> 10862.226 | P14: =N14*$E$2*(1+$I$6)/($F$6-$I$6)/(1+$F$6)^$N$3 -> 16350.411 | Q14: =O14+P14 -> 27212.637 | R14: =Q14-$G$2+$I$2 -> 23144.837 | S14: =R14/$K$2 -> 177.81835 | T14: =S14-$M$2 -> 1.1895862
A15: 8 | B15: =IF(T14>0,B14,D14) -> 0.015625 | C15: =IF(T14>0,D14,C14) -> 0.02734375 | D15: =(B15+C15)/2 -> 0.021484375 | E15: =$C$2*(1+IF(E$3<=$O$2,$D15,$D15-($D15-$I$6)*MIN(E$3-$O$2,$Q$2)/$Q$2)) -> 3207.4609 | F15: =E15*(1+IF(F$3<=$O$2,$D15,$D15-($D15-$I$6)*MIN(F$3-$O$2,$Q$2)/$Q$2)) -> 3276.3712 | G15: =F15*(1+IF(G$3<=$O$2,$D15,$D15-($D15-$I$6)*MIN(G$3-$O$2,$Q$2)/$Q$2)) -> 3346.762 | H15: =G15*(1+IF(H$3<=$O$2,$D15,$D15-($D15-$I$6)*MIN(H$3-$O$2,$Q$2)/$Q$2)) -> 3418.6651 | I15: =H15*(1+IF(I$3<=$O$2,$D15,$D15-($D15-$I$6)*MIN(I$3-$O$2,$Q$2)/$Q$2)) -> 3492.113 | J15: =I15*(1+IF(J$3<=$O$2,$D15,$D15-($D15-$I$6)*MIN(J$3-$O$2,$Q$2)/$Q$2)) -> 3571.899 | K15: =J15*(1+IF(K$3<=$O$2,$D15,$D15-($D15-$I$6)*MIN(K$3-$O$2,$Q$2)/$Q$2)) -> 3658.377 | L15: =K15*(1+IF(L$3<=$O$2,$D15,$D15-($D15-$I$6)*MIN(L$3-$O$2,$Q$2)/$Q$2)) -> 3751.9354 | M15: =L15*(1+IF(M$3<=$O$2,$D15,$D15-($D15-$I$6)*MIN(M$3-$O$2,$Q$2)/$Q$2)) -> 3853.0008 | N15: =M15*(1+IF(N$3<=$O$2,$D15,$D15-($D15-$I$6)*MIN(N$3-$O$2,$Q$2)/$Q$2)) -> 3962.0407 | O15: =SUMPRODUCT(E15:N15,1/(1+$F$6)^$E$3:$N$3)*$E$2 -> 10587.203 | P15: =N15*$E$2*(1+$I$6)/($F$6-$I$6)/(1+$F$6)^$N$3 -> 15708.974 | Q15: =O15+P15 -> 26296.177 | R15: =Q15-$G$2+$I$2 -> 22228.377 | S15: =R15/$K$2 -> 170.77733 | T15: =S15-$M$2 -> -5.8514374
A16: 9 | B16: =IF(T15>0,B15,D15) -> 0.021484375 | C16: =IF(T15>0,D15,C15) -> 0.02734375 | D16: =(B16+C16)/2 -> 0.024414062 | E16: =$C$2*(1+IF(E$3<=$O$2,$D16,$D16-($D16-$I$6)*MIN(E$3-$O$2,$Q$2)/$Q$2)) -> 3216.6602 | F16: =E16*(1+IF(F$3<=$O$2,$D16,$D16-($D16-$I$6)*MIN(F$3-$O$2,$Q$2)/$Q$2)) -> 3295.1919 | G16: =F16*(1+IF(G$3<=$O$2,$D16,$D16-($D16-$I$6)*MIN(G$3-$O$2,$Q$2)/$Q$2)) -> 3375.6409 | H16: =G16*(1+IF(H$3<=$O$2,$D16,$D16-($D16-$I$6)*MIN(H$3-$O$2,$Q$2)/$Q$2)) -> 3458.054 | I16: =H16*(1+IF(I$3<=$O$2,$D16,$D16-($D16-$I$6)*MIN(I$3-$O$2,$Q$2)/$Q$2)) -> 3542.4792 | J16: =I16*(1+IF(J$3<=$O$2,$D16,$D16-($D16-$I$6)*MIN(J$3-$O$2,$Q$2)/$Q$2)) -> 3631.7187 | K16: =J16*(1+IF(K$3<=$O$2,$D16,$D16-($D16-$I$6)*MIN(K$3-$O$2,$Q$2)/$Q$2)) -> 3726.0287 | L16: =K16*(1+IF(L$3<=$O$2,$D16,$D16-($D16-$I$6)*MIN(L$3-$O$2,$Q$2)/$Q$2)) -> 3825.6837 | M16: =L16*(1+IF(M$3<=$O$2,$D16,$D16-($D16-$I$6)*MIN(M$3-$O$2,$Q$2)/$Q$2)) -> 3930.9773 | N16: =M16*(1+IF(N$3<=$O$2,$D16,$D16-($D16-$I$6)*MIN(N$3-$O$2,$Q$2)/$Q$2)) -> 4042.2239 | O16: =SUMPRODUCT(E16:N16,1/(1+$F$6)^$E$3:$N$3)*$E$2 -> 10723.82 | P16: =N16*$E$2*(1+$I$6)/($F$6-$I$6)/(1+$F$6)^$N$3 -> 16026.89 | Q16: =O16+P16 -> 26750.71 | R16: =Q16-$G$2+$I$2 -> 22682.91 | S16: =R16/$K$2 -> 174.26944 | T16: =S16-$M$2 -> -2.3593289
A17: 10 | B17: =IF(T16>0,B16,D16) -> 0.024414062 | C17: =IF(T16>0,D16,C16) -> 0.02734375 | D17: =(B17+C17)/2 -> 0.025878906 | E17: =$C$2*(1+IF(E$3<=$O$2,$D17,$D17-($D17-$I$6)*MIN(E$3-$O$2,$Q$2)/$Q$2)) -> 3221.2598 | F17: =E17*(1+IF(F$3<=$O$2,$D17,$D17-($D17-$I$6)*MIN(F$3-$O$2,$Q$2)/$Q$2)) -> 3304.6224 | G17: =F17*(1+IF(G$3<=$O$2,$D17,$D17-($D17-$I$6)*MIN(G$3-$O$2,$Q$2)/$Q$2)) -> 3390.1425 | H17: =G17*(1+IF(H$3<=$O$2,$D17,$D17-($D17-$I$6)*MIN(H$3-$O$2,$Q$2)/$Q$2)) -> 3477.8756 | I17: =H17*(1+IF(I$3<=$O$2,$D17,$D17-($D17-$I$6)*MIN(I$3-$O$2,$Q$2)/$Q$2)) -> 3567.8793 | J17: =I17*(1+IF(J$3<=$O$2,$D17,$D17-($D17-$I$6)*MIN(J$3-$O$2,$Q$2)/$Q$2)) -> 3661.9397 | K17: =J17*(1+IF(K$3<=$O$2,$D17,$D17-($D17-$I$6)*MIN(K$3-$O$2,$Q$2)/$Q$2)) -> 3760.2531 | L17: =K17*(1+IF(L$3<=$O$2,$D17,$D17-($D17-$I$6)*MIN(L$3-$O$2,$Q$2)/$Q$2)) -> 3863.0266 | M17: =L17*(1+IF(M$3<=$O$2,$D17,$D17-($D17-$I$6)*MIN(M$3-$O$2,$Q$2)/$Q$2)) -> 3970.4798 | N17: =M17*(1+IF(N$3<=$O$2,$D17,$D17-($D17-$I$6)*MIN(N$3-$O$2,$Q$2)/$Q$2)) -> 4082.8443 | O17: =SUMPRODUCT(E17:N17,1/(1+$F$6)^$E$3:$N$3)*$E$2 -> 10792.798 | P17: =N17*$E$2*(1+$I$6)/($F$6-$I$6)/(1+$F$6)^$N$3 -> 16187.944 | Q17: =O17+P17 -> 26980.742 | R17: =Q17-$G$2+$I$2 -> 22912.942 | S17: =R17/$K$2 -> 176.03674 | T17: =S17-$M$2 -> -0.59202311
A18: 11 | B18: =IF(T17>0,B17,D17) -> 0.025878906 | C18: =IF(T17>0,D17,C17) -> 0.02734375 | D18: =(B18+C18)/2 -> 0.026611328 | E18: =$C$2*(1+IF(E$3<=$O$2,$D18,$D18-($D18-$I$6)*MIN(E$3-$O$2,$Q$2)/$Q$2)) -> 3223.5596 | F18: =E18*(1+IF(F$3<=$O$2,$D18,$D18-($D18-$I$6)*MIN(F$3-$O$2,$Q$2)/$Q$2)) -> 3309.3428 | G18: =F18*(1+IF(G$3<=$O$2,$D18,$D18-($D18-$I$6)*MIN(G$3-$O$2,$Q$2)/$Q$2)) -> 3397.4088 | H18: =G18*(1+IF(H$3<=$O$2,$D18,$D18-($D18-$I$6)*MIN(H$3-$O$2,$Q$2)/$Q$2)) -> 3487.8183 | I18: =H18*(1+IF(I$3<=$O$2,$D18,$D18-($D18-$I$6)*MIN(I$3-$O$2,$Q$2)/$Q$2)) -> 3580.6338 | J18: =I18*(1+IF(J$3<=$O$2,$D18,$D18-($D18-$I$6)*MIN(J$3-$O$2,$Q$2)/$Q$2)) -> 3677.1285 | K18: =J18*(1+IF(K$3<=$O$2,$D18,$D18-($D18-$I$6)*MIN(K$3-$O$2,$Q$2)/$Q$2)) -> 3777.4656 | L18: =K18*(1+IF(L$3<=$O$2,$D18,$D18-($D18-$I$6)*MIN(L$3-$O$2,$Q$2)/$Q$2)) -> 3881.8163 | M18: =L18*(1+IF(M$3<=$O$2,$D18,$D18-($D18-$I$6)*MIN(M$3-$O$2,$Q$2)/$Q$2)) -> 3990.3607 | N18: =M18*(1+IF(N$3<=$O$2,$D18,$D18-($D18-$I$6)*MIN(N$3-$O$2,$Q$2)/$Q$2)) -> 4103.2879 | O18: =SUMPRODUCT(E18:N18,1/(1+$F$6)^$E$3:$N$3)*$E$2 -> 10827.456 | P18: =N18*$E$2*(1+$I$6)/($F$6-$I$6)/(1+$F$6)^$N$3 -> 16269 | Q18: =O18+P18 -> 27096.456 | R18: =Q18-$G$2+$I$2 -> 23028.656 | S18: =R18/$K$2 -> 176.92575 | T18: =S18-$M$2 -> 0.29698721
A19: 12 | B19: =IF(T18>0,B18,D18) -> 0.025878906 | C19: =IF(T18>0,D18,C18) -> 0.026611328 | D19: =(B19+C19)/2 -> 0.026245117 | E19: =$C$2*(1+IF(E$3<=$O$2,$D19,$D19-($D19-$I$6)*MIN(E$3-$O$2,$Q$2)/$Q$2)) -> 3222.4097 | F19: =E19*(1+IF(F$3<=$O$2,$D19,$D19-($D19-$I$6)*MIN(F$3-$O$2,$Q$2)/$Q$2)) -> 3306.9822 | G19: =F19*(1+IF(G$3<=$O$2,$D19,$D19-($D19-$I$6)*MIN(G$3-$O$2,$Q$2)/$Q$2)) -> 3393.7743 | H19: =G19*(1+IF(H$3<=$O$2,$D19,$D19-($D19-$I$6)*MIN(H$3-$O$2,$Q$2)/$Q$2)) -> 3482.8443 | I19: =H19*(1+IF(I$3<=$O$2,$D19,$D19-($D19-$I$6)*MIN(I$3-$O$2,$Q$2)/$Q$2)) -> 3574.252 | J19: =I19*(1+IF(J$3<=$O$2,$D19,$D19-($D19-$I$6)*MIN(J$3-$O$2,$Q$2)/$Q$2)) -> 3669.5276 | K19: =J19*(1+IF(K$3<=$O$2,$D19,$D19-($D19-$I$6)*MIN(K$3-$O$2,$Q$2)/$Q$2)) -> 3768.8509 | L19: =K19*(1+IF(L$3<=$O$2,$D19,$D19-($D19-$I$6)*MIN(L$3-$O$2,$Q$2)/$Q$2)) -> 3872.4116 | M19: =L19*(1+IF(M$3<=$O$2,$D19,$D19-($D19-$I$6)*MIN(M$3-$O$2,$Q$2)/$Q$2)) -> 3980.4094 | N19: =M19*(1+IF(N$3<=$O$2,$D19,$D19-($D19-$I$6)*MIN(N$3-$O$2,$Q$2)/$Q$2)) -> 4093.055 | O19: =SUMPRODUCT(E19:N19,1/(1+$F$6)^$E$3:$N$3)*$E$2 -> 10810.113 | P19: =N19*$E$2*(1+$I$6)/($F$6-$I$6)/(1+$F$6)^$N$3 -> 16228.428 | Q19: =O19+P19 -> 27038.541 | R19: =Q19-$G$2+$I$2 -> 22970.741 | S19: =R19/$K$2 -> 176.4808 | T19: =S19-$M$2 -> -0.14796573
A20: 13 | B20: =IF(T19>0,B19,D19) -> 0.026245117 | C20: =IF(T19>0,D19,C19) -> 0.026611328 | D20: =(B20+C20)/2 -> 0.026428223 | E20: =$C$2*(1+IF(E$3<=$O$2,$D20,$D20-($D20-$I$6)*MIN(E$3-$O$2,$Q$2)/$Q$2)) -> 3222.9846 | F20: =E20*(1+IF(F$3<=$O$2,$D20,$D20-($D20-$I$6)*MIN(F$3-$O$2,$Q$2)/$Q$2)) -> 3308.1624 | G20: =F20*(1+IF(G$3<=$O$2,$D20,$D20-($D20-$I$6)*MIN(G$3-$O$2,$Q$2)/$Q$2)) -> 3395.5912 | H20: =G20*(1+IF(H$3<=$O$2,$D20,$D20-($D20-$I$6)*MIN(H$3-$O$2,$Q$2)/$Q$2)) -> 3485.3307 | I20: =H20*(1+IF(I$3<=$O$2,$D20,$D20-($D20-$I$6)*MIN(I$3-$O$2,$Q$2)/$Q$2)) -> 3577.4418 | J20: =I20*(1+IF(J$3<=$O$2,$D20,$D20-($D20-$I$6)*MIN(J$3-$O$2,$Q$2)/$Q$2)) -> 3673.3264 | K20: =J20*(1+IF(K$3<=$O$2,$D20,$D20-($D20-$I$6)*MIN(K$3-$O$2,$Q$2)/$Q$2)) -> 3773.1562 | L20: =K20*(1+IF(L$3<=$O$2,$D20,$D20-($D20-$I$6)*MIN(L$3-$O$2,$Q$2)/$Q$2)) -> 3877.1115 | M20: =L20*(1+IF(M$3<=$O$2,$D20,$D20-($D20-$I$6)*MIN(M$3-$O$2,$Q$2)/$Q$2)) -> 3985.3823 | N20: =M20*(1+IF(N$3<=$O$2,$D20,$D20-($D20-$I$6)*MIN(N$3-$O$2,$Q$2)/$Q$2)) -> 4098.1686 | O20: =SUMPRODUCT(E20:N20,1/(1+$F$6)^$E$3:$N$3)*$E$2 -> 10818.781 | P20: =N20*$E$2*(1+$I$6)/($F$6-$I$6)/(1+$F$6)^$N$3 -> 16248.703 | Q20: =O20+P20 -> 27067.484 | R20: =Q20-$G$2+$I$2 -> 22999.684 | S20: =R20/$K$2 -> 176.70316 | T20: =S20-$M$2 -> 0.07439869
... A47: 40 | B47: =IF(T46>0,B46,D46) -> 0.02636698 | C47: =IF(T46>0,D46,C46) -> 0.02636698 | D47: =(B47+C47)/2 -> 0.02636698 | E47: =$C$2*(1+IF(E$3<=$O$2,$D47,$D47-($D47-$I$6)*MIN(E$3-$O$2,$Q$2)/$Q$2)) -> 3222.7923 | F47: =E47*(1+IF(F$3<=$O$2,$D47,$D47-($D47-$I$6)*MIN(F$3-$O$2,$Q$2)/$Q$2)) -> 3307.7676 | G47: =F47*(1+IF(G$3<=$O$2,$D47,$D47-($D47-$I$6)*MIN(G$3-$O$2,$Q$2)/$Q$2)) -> 3394.9835 | H47: =G47*(1+IF(H$3<=$O$2,$D47,$D47-($D47-$I$6)*MIN(H$3-$O$2,$Q$2)/$Q$2)) -> 3484.4989 | I47: =H47*(1+IF(I$3<=$O$2,$D47,$D47-($D47-$I$6)*MIN(I$3-$O$2,$Q$2)/$Q$2)) -> 3576.3746 | J47: =I47*(1+IF(J$3<=$O$2,$D47,$D47-($D47-$I$6)*MIN(J$3-$O$2,$Q$2)/$Q$2)) -> 3672.0555 | K47: =J47*(1+IF(K$3<=$O$2,$D47,$D47-($D47-$I$6)*MIN(K$3-$O$2,$Q$2)/$Q$2)) -> 3771.7157 | L47: =K47*(1+IF(L$3<=$O$2,$D47,$D47-($D47-$I$6)*MIN(L$3-$O$2,$Q$2)/$Q$2)) -> 3875.539 | M47: =L47*(1+IF(M$3<=$O$2,$D47,$D47-($D47-$I$6)*MIN(M$3-$O$2,$Q$2)/$Q$2)) -> 3983.7184 | N47: =M47*(1+IF(N$3<=$O$2,$D47,$D47-($D47-$I$6)*MIN(N$3-$O$2,$Q$2)/$Q$2)) -> 4096.4577 | O47: =SUMPRODUCT(E47:N47,1/(1+$F$6)^$E$3:$N$3)*$E$2 -> 10815.881 | P47: =N47*$E$2*(1+$I$6)/($F$6-$I$6)/(1+$F$6)^$N$3 -> 16241.919 | Q47: =O47+P47 -> 27057.8 | R47: =Q47-$G$2+$I$2 -> 22990 | S47: =R47/$K$2 -> 176.62876 | T47: =S47-$M$2 -> 1.520533e-09
A49: Grid block 2: row 1, column 1 of table A (24 steps) | E49: WACC | F49: =Sensitivity!$B$10 -> 0.071941394 | G49: Terminal growth | I49: =Sensitivity!$C$9 -> 0.0183
A50: Step | B50: Low | C50: High | D50: Mid | E50: Rev Y1 | F50: Rev Y2 | G50: Rev Y3 | H50: Rev Y4 | I50: Rev Y5 | J50: Rev Y6 | K50: Rev Y7 | L50: Rev Y8 | M50: Rev Y9 | N50: Rev Y10 | O50: PV of FCF | P50: PV of TV | Q50: EV | R50: Equity | S50: Per share | T50: Value - price
A51: 1 | B51: -0.5 | C51: 1 | D51: =(B51+C51)/2 -> 0.25 | E51: =$C$2*(1+IF(E$3<=$O$2,$D51,$D51-($D51-$I$49)*MIN(E$3-$O$2,$Q$2)/$Q$2)) -> 3925 | F51: =E51*(1+IF(F$3<=$O$2,$D51,$D51-($D51-$I$49)*MIN(F$3-$O$2,$Q$2)/$Q$2)) -> 4906.25 | G51: =F51*(1+IF(G$3<=$O$2,$D51,$D51-($D51-$I$49)*MIN(G$3-$O$2,$Q$2)/$Q$2)) -> 6132.8125 | H51: =G51*(1+IF(H$3<=$O$2,$D51,$D51-($D51-$I$49)*MIN(H$3-$O$2,$Q$2)/$Q$2)) -> 7666.0156 | I51: =H51*(1+IF(I$3<=$O$2,$D51,$D51-($D51-$I$49)*MIN(I$3-$O$2,$Q$2)/$Q$2)) -> 9582.5195 | J51: =I51*(1+IF(J$3<=$O$2,$D51,$D51-($D51-$I$49)*MIN(J$3-$O$2,$Q$2)/$Q$2)) -> 11534.095 | K51: =J51*(1+IF(K$3<=$O$2,$D51,$D51-($D51-$I$49)*MIN(K$3-$O$2,$Q$2)/$Q$2)) -> 13348.639 | L51: =K51*(1+IF(L$3<=$O$2,$D51,$D51-($D51-$I$49)*MIN(L$3-$O$2,$Q$2)/$Q$2)) -> 14830.071 | M51: =L51*(1+IF(M$3<=$O$2,$D51,$D51-($D51-$I$49)*MIN(M$3-$O$2,$Q$2)/$Q$2)) -> 15788.687 | N51: =M51*(1+IF(N$3<=$O$2,$D51,$D51-($D51-$I$49)*MIN(N$3-$O$2,$Q$2)/$Q$2)) -> 16077.62 | O51: =SUMPRODUCT(E51:N51,1/(1+$F$49)^$E$3:$N$3)*$E$2 -> 30132.018 | P51: =N51*$E$2*(1+$I$49)/($F$49-$I$49)/(1+$F$49)^$N$3 -> 69268.135 | Q51: =O51+P51 -> 99400.153 | R51: =Q51-$G$2+$I$2 -> 95332.353 | S51: =R51/$K$2 -> 732.42435 | T51: =S51-$M$2 -> 555.79558
A52: 2 | B52: =IF(T51>0,B51,D51) -> -0.5 | C52: =IF(T51>0,D51,C51) -> 0.25 | D52: =(B52+C52)/2 -> -0.125 | E52: =$C$2*(1+IF(E$3<=$O$2,$D52,$D52-($D52-$I$49)*MIN(E$3-$O$2,$Q$2)/$Q$2)) -> 2747.5 | F52: =E52*(1+IF(F$3<=$O$2,$D52,$D52-($D52-$I$49)*MIN(F$3-$O$2,$Q$2)/$Q$2)) -> 2404.0625 | G52: =F52*(1+IF(G$3<=$O$2,$D52,$D52-($D52-$I$49)*MIN(G$3-$O$2,$Q$2)/$Q$2)) -> 2103.5547 | H52: =G52*(1+IF(H$3<=$O$2,$D52,$D52-($D52-$I$49)*MIN(H$3-$O$2,$Q$2)/$Q$2)) -> 1840.6104 | I52: =H52*(1+IF(I$3<=$O$2,$D52,$D52-($D52-$I$49)*MIN(I$3-$O$2,$Q$2)/$Q$2)) -> 1610.5341 | J52: =I52*(1+IF(J$3<=$O$2,$D52,$D52-($D52-$I$49)*MIN(J$3-$O$2,$Q$2)/$Q$2)) -> 1455.3752 | K52: =J52*(1+IF(K$3<=$O$2,$D52,$D52-($D52-$I$49)*MIN(K$3-$O$2,$Q$2)/$Q$2)) -> 1356.8754 | L52: =K52*(1+IF(L$3<=$O$2,$D52,$D52-($D52-$I$49)*MIN(L$3-$O$2,$Q$2)/$Q$2)) -> 1303.9301 | M52: =L52*(1+IF(M$3<=$O$2,$D52,$D52-($D52-$I$49)*MIN(M$3-$O$2,$Q$2)/$Q$2)) -> 1290.4214 | N52: =M52*(1+IF(N$3<=$O$2,$D52,$D52-($D52-$I$49)*MIN(N$3-$O$2,$Q$2)/$Q$2)) -> 1314.0361 | O52: =SUMPRODUCT(E52:N52,1/(1+$F$49)^$E$3:$N$3)*$E$2 -> 5811.4859 | P52: =N52*$E$2*(1+$I$49)/($F$49-$I$49)/(1+$F$49)^$N$3 -> 5661.3374 | Q52: =O52+P52 -> 11472.823 | R52: =Q52-$G$2+$I$2 -> 7405.0233 | S52: =R52/$K$2 -> 56.891697 | T52: =S52-$M$2 -> -119.73707
A53: 3 | B53: =IF(T52>0,B52,D52) -> -0.125 | C53: =IF(T52>0,D52,C52) -> 0.25 | D53: =(B53+C53)/2 -> 0.0625 | E53: =$C$2*(1+IF(E$3<=$O$2,$D53,$D53-($D53-$I$49)*MIN(E$3-$O$2,$Q$2)/$Q$2)) -> 3336.25 | F53: =E53*(1+IF(F$3<=$O$2,$D53,$D53-($D53-$I$49)*MIN(F$3-$O$2,$Q$2)/$Q$2)) -> 3544.7656 | G53: =F53*(1+IF(G$3<=$O$2,$D53,$D53-($D53-$I$49)*MIN(G$3-$O$2,$Q$2)/$Q$2)) -> 3766.3135 | H53: =G53*(1+IF(H$3<=$O$2,$D53,$D53-($D53-$I$49)*MIN(H$3-$O$2,$Q$2)/$Q$2)) -> 4001.7081 | I53: =H53*(1+IF(I$3<=$O$2,$D53,$D53-($D53-$I$49)*MIN(I$3-$O$2,$Q$2)/$Q$2)) -> 4251.8148 | J53: =I53*(1+IF(J$3<=$O$2,$D53,$D53-($D53-$I$49)*MIN(J$3-$O$2,$Q$2)/$Q$2)) -> 4479.9672 | K53: =J53*(1+IF(K$3<=$O$2,$D53,$D53-($D53-$I$49)*MIN(K$3-$O$2,$Q$2)/$Q$2)) -> 4680.7593 | L53: =K53*(1+IF(L$3<=$O$2,$D53,$D53-($D53-$I$49)*MIN(L$3-$O$2,$Q$2)/$Q$2)) -> 4849.1731 | M53: =L53*(1+IF(M$3<=$O$2,$D53,$D53-($D53-$I$49)*MIN(M$3-$O$2,$Q$2)/$Q$2)) -> 4980.7796 | N53: =M53*(1+IF(N$3<=$O$2,$D53,$D53-($D53-$I$49)*MIN(N$3-$O$2,$Q$2)/$Q$2)) -> 5071.9279 | O53: =SUMPRODUCT(E53:N53,1/(1+$F$49)^$E$3:$N$3)*$E$2 -> 13229.414 | P53: =N53*$E$2*(1+$I$49)/($F$49-$I$49)/(1+$F$49)^$N$3 -> 21851.679 | Q53: =O53+P53 -> 35081.093 | R53: =Q53-$G$2+$I$2 -> 31013.293 | S53: =R53/$K$2 -> 238.27053 | T53: =S53-$M$2 -> 61.641768
A54: 4 | B54: =IF(T53>0,B53,D53) -> -0.125 | C54: =IF(T53>0,D53,C53) -> 0.0625 | D54: =(B54+C54)/2 -> -0.03125 | E54: =$C$2*(1+IF(E$3<=$O$2,$D54,$D54-($D54-$I$49)*MIN(E$3-$O$2,$Q$2)/$Q$2)) -> 3041.875 | F54: =E54*(1+IF(F$3<=$O$2,$D54,$D54-($D54-$I$49)*MIN(F$3-$O$2,$Q$2)/$Q$2)) -> 2946.8164 | G54: =F54*(1+IF(G$3<=$O$2,$D54,$D54-($D54-$I$49)*MIN(G$3-$O$2,$Q$2)/$Q$2)) -> 2854.7284 | H54: =G54*(1+IF(H$3<=$O$2,$D54,$D54-($D54-$I$49)*MIN(H$3-$O$2,$Q$2)/$Q$2)) -> 2765.5181 | I54: =H54*(1+IF(I$3<=$O$2,$D54,$D54-($D54-$I$49)*MIN(I$3-$O$2,$Q$2)/$Q$2)) -> 2679.0957 | J54: =I54*(1+IF(J$3<=$O$2,$D54,$D54-($D54-$I$49)*MIN(J$3-$O$2,$Q$2)/$Q$2)) -> 2621.9238 | K54: =J54*(1+IF(K$3<=$O$2,$D54,$D54-($D54-$I$49)*MIN(K$3-$O$2,$Q$2)/$Q$2)) -> 2591.9552 | L54: =K54*(1+IF(L$3<=$O$2,$D54,$D54-($D54-$I$49)*MIN(L$3-$O$2,$Q$2)/$Q$2)) -> 2588.0154 | M54: =L54*(1+IF(M$3<=$O$2,$D54,$D54-($D54-$I$49)*MIN(M$3-$O$2,$Q$2)/$Q$2)) -> 2609.7289 | N54: =M54*(1+IF(N$3<=$O$2,$D54,$D54-($D54-$I$49)*MIN(N$3-$O$2,$Q$2)/$Q$2)) -> 2657.4869 | O54: =SUMPRODUCT(E54:N54,1/(1+$F$49)^$E$3:$N$3)*$E$2 -> 8745.5678 | P54: =N54*$E$2*(1+$I$49)/($F$49-$I$49)/(1+$F$49)^$N$3 -> 11449.404 | Q54: =O54+P54 -> 20194.971 | R54: =Q54-$G$2+$I$2 -> 16127.171 | S54: =R54/$K$2 -> 123.90267 | T54: =S54-$M$2 -> -52.726095
A55: 5 | B55: =IF(T54>0,B54,D54) -> -0.03125 | C55: =IF(T54>0,D54,C54) -> 0.0625 | D55: =(B55+C55)/2 -> 0.015625 | E55: =$C$2*(1+IF(E$3<=$O$2,$D55,$D55-($D55-$I$49)*MIN(E$3-$O$2,$Q$2)/$Q$2)) -> 3189.0625 | F55: =E55*(1+IF(F$3<=$O$2,$D55,$D55-($D55-$I$49)*MIN(F$3-$O$2,$Q$2)/$Q$2)) -> 3238.8916 | G55: =F55*(1+IF(G$3<=$O$2,$D55,$D55-($D55-$I$49)*MIN(G$3-$O$2,$Q$2)/$Q$2)) -> 3289.4993 | H55: =G55*(1+IF(H$3<=$O$2,$D55,$D55-($D55-$I$49)*MIN(H$3-$O$2,$Q$2)/$Q$2)) -> 3340.8977 | I55: =H55*(1+IF(I$3<=$O$2,$D55,$D55-($D55-$I$49)*MIN(I$3-$O$2,$Q$2)/$Q$2)) -> 3393.0992 | J55: =I55*(1+IF(J$3<=$O$2,$D55,$D55-($D55-$I$49)*MIN(J$3-$O$2,$Q$2)/$Q$2)) -> 3447.9317 | K55: =J55*(1+IF(K$3<=$O$2,$D55,$D55-($D55-$I$49)*MIN(K$3-$O$2,$Q$2)/$Q$2)) -> 3505.4949 | L55: =K55*(1+IF(L$3<=$O$2,$D55,$D55-($D55-$I$49)*MIN(L$3-$O$2,$Q$2)/$Q$2)) -> 3565.8946 | M55: =L55*(1+IF(M$3<=$O$2,$D55,$D55-($D55-$I$49)*MIN(M$3-$O$2,$Q$2)/$Q$2)) -> 3629.2427 | N55: =M55*(1+IF(N$3<=$O$2,$D55,$D55-($D55-$I$49)*MIN(N$3-$O$2,$Q$2)/$Q$2)) -> 3695.6579 | O55: =SUMPRODUCT(E55:N55,1/(1+$F$49)^$E$3:$N$3)*$E$2 -> 10753.028 | P55: =N55*$E$2*(1+$I$49)/($F$49-$I$49)/(1+$F$49)^$N$3 -> 15922.215 | Q55: =O55+P55 -> 26675.243 | R55: =Q55-$G$2+$I$2 -> 22607.443 | S55: =R55/$K$2 -> 173.68964 | T55: =S55-$M$2 -> -2.9391283
A56: 6 | B56: =IF(T55>0,B55,D55) -> 0.015625 | C56: =IF(T55>0,D55,C55) -> 0.0625 | D56: =(B56+C56)/2 -> 0.0390625 | E56: =$C$2*(1+IF(E$3<=$O$2,$D56,$D56-($D56-$I$49)*MIN(E$3-$O$2,$Q$2)/$Q$2)) -> 3262.6562 | F56: =E56*(1+IF(F$3<=$O$2,$D56,$D56-($D56-$I$49)*MIN(F$3-$O$2,$Q$2)/$Q$2)) -> 3390.1038 | G56: =F56*(1+IF(G$3<=$O$2,$D56,$D56-($D56-$I$49)*MIN(G$3-$O$2,$Q$2)/$Q$2)) -> 3522.5297 | H56: =G56*(1+IF(H$3<=$O$2,$D56,$D56-($D56-$I$49)*MIN(H$3-$O$2,$Q$2)/$Q$2)) -> 3660.1285 | I56: =H56*(1+IF(I$3<=$O$2,$D56,$D56-($D56-$I$49)*MIN(I$3-$O$2,$Q$2)/$Q$2)) -> 3803.1023 | J56: =I56*(1+IF(J$3<=$O$2,$D56,$D56-($D56-$I$49)*MIN(J$3-$O$2,$Q$2)/$Q$2)) -> 3935.8686 | K56: =J56*(1+IF(K$3<=$O$2,$D56,$D56-($D56-$I$49)*MIN(K$3-$O$2,$Q$2)/$Q$2)) -> 4056.9261 | L56: =K56*(1+IF(L$3<=$O$2,$D56,$D56-($D56-$I$49)*MIN(L$3-$O$2,$Q$2)/$Q$2)) -> 4164.8606 | M56: =L56*(1+IF(M$3<=$O$2,$D56,$D56-($D56-$I$49)*MIN(M$3-$O$2,$Q$2)/$Q$2)) -> 4258.3721 | N56: =M56*(1+IF(N$3<=$O$2,$D56,$D56-($D56-$I$49)*MIN(N$3-$O$2,$Q$2)/$Q$2)) -> 4336.3003 | O56: =SUMPRODUCT(E56:N56,1/(1+$F$49)^$E$3:$N$3)*$E$2 -> 11926.702 | P56: =N56*$E$2*(1+$I$49)/($F$49-$I$49)/(1+$F$49)^$N$3 -> 18682.332 | Q56: =O56+P56 -> 30609.034 | R56: =Q56-$G$2+$I$2 -> 26541.234 | S56: =R56/$K$2 -> 203.91237 | T56: =S56-$M$2 -> 27.283602
A57: 7 | B57: =IF(T56>0,B56,D56) -> 0.015625 | C57: =IF(T56>0,D56,C56) -> 0.0390625 | D57: =(B57+C57)/2 -> 0.02734375 | E57: =$C$2*(1+IF(E$3<=$O$2,$D57,$D57-($D57-$I$49)*MIN(E$3-$O$2,$Q$2)/$Q$2)) -> 3225.8594 | F57: =E57*(1+IF(F$3<=$O$2,$D57,$D57-($D57-$I$49)*MIN(F$3-$O$2,$Q$2)/$Q$2)) -> 3314.0665 | G57: =F57*(1+IF(G$3<=$O$2,$D57,$D57-($D57-$I$49)*MIN(G$3-$O$2,$Q$2)/$Q$2)) -> 3404.6855 | H57: =G57*(1+IF(H$3<=$O$2,$D57,$D57-($D57-$I$49)*MIN(H$3-$O$2,$Q$2)/$Q$2)) -> 3497.7823 | I57: =H57*(1+IF(I$3<=$O$2,$D57,$D57-($D57-$I$49)*MIN(I$3-$O$2,$Q$2)/$Q$2)) -> 3593.4248 | J57: =I57*(1+IF(J$3<=$O$2,$D57,$D57-($D57-$I$49)*MIN(J$3-$O$2,$Q$2)/$Q$2)) -> 3685.1829 | K57: =J57*(1+IF(K$3<=$O$2,$D57,$D57-($D57-$I$49)*MIN(K$3-$O$2,$Q$2)/$Q$2)) -> 3772.6185 | L57: =K57*(1+IF(L$3<=$O$2,$D57,$D57-($D57-$I$49)*MIN(L$3-$O$2,$Q$2)/$Q$2)) -> 3855.3049 | M57: =L57*(1+IF(M$3<=$O$2,$D57,$D57-($D57-$I$49)*MIN(M$3-$O$2,$Q$2)/$Q$2)) -> 3932.8302 | N57: =M57*(1+IF(N$3<=$O$2,$D57,$D57-($D57-$I$49)*MIN(N$3-$O$2,$Q$2)/$Q$2)) -> 4004.801 | O57: =SUMPRODUCT(E57:N57,1/(1+$F$49)^$E$3:$N$3)*$E$2 -> 11324.512 | P57: =N57*$E$2*(1+$I$49)/($F$49-$I$49)/(1+$F$49)^$N$3 -> 17254.115 | Q57: =O57+P57 -> 28578.627 | R57: =Q57-$G$2+$I$2 -> 24510.827 | S57: =R57/$K$2 -> 188.31305 | T57: =S57-$M$2 -> 11.684289
A58: 8 | B58: =IF(T57>0,B57,D57) -> 0.015625 | C58: =IF(T57>0,D57,C57) -> 0.02734375 | D58: =(B58+C58)/2 -> 0.021484375 | E58: =$C$2*(1+IF(E$3<=$O$2,$D58,$D58-($D58-$I$49)*MIN(E$3-$O$2,$Q$2)/$Q$2)) -> 3207.4609 | F58: =E58*(1+IF(F$3<=$O$2,$D58,$D58-($D58-$I$49)*MIN(F$3-$O$2,$Q$2)/$Q$2)) -> 3276.3712 | G58: =F58*(1+IF(G$3<=$O$2,$D58,$D58-($D58-$I$49)*MIN(G$3-$O$2,$Q$2)/$Q$2)) -> 3346.762 | H58: =G58*(1+IF(H$3<=$O$2,$D58,$D58-($D58-$I$49)*MIN(H$3-$O$2,$Q$2)/$Q$2)) -> 3418.6651 | I58: =H58*(1+IF(I$3<=$O$2,$D58,$D58-($D58-$I$49)*MIN(I$3-$O$2,$Q$2)/$Q$2)) -> 3492.113 | J58: =I58*(1+IF(J$3<=$O$2,$D58,$D58-($D58-$I$49)*MIN(J$3-$O$2,$Q$2)/$Q$2)) -> 3564.9148 | K58: =J58*(1+IF(K$3<=$O$2,$D58,$D58-($D58-$I$49)*MIN(K$3-$O$2,$Q$2)/$Q$2)) -> 3636.964 | L58: =K58*(1+IF(L$3<=$O$2,$D58,$D58-($D58-$I$49)*MIN(L$3-$O$2,$Q$2)/$Q$2)) -> 3708.153 | M58: =L58*(1+IF(M$3<=$O$2,$D58,$D58-($D58-$I$49)*MIN(M$3-$O$2,$Q$2)/$Q$2)) -> 3778.3738 | N58: =M58*(1+IF(N$3<=$O$2,$D58,$D58-($D58-$I$49)*MIN(N$3-$O$2,$Q$2)/$Q$2)) -> 3847.5181 | O58: =SUMPRODUCT(E58:N58,1/(1+$F$49)^$E$3:$N$3)*$E$2 -> 11035.026 | P58: =N58*$E$2*(1+$I$49)/($F$49-$I$49)/(1+$F$49)^$N$3 -> 16576.483 | Q58: =O58+P58 -> 27611.509 | R58: =Q58-$G$2+$I$2 -> 23543.709 | S58: =R58/$K$2 -> 180.88283 | T58: =S58-$M$2 -> 4.2540641
A59: 9 | B59: =IF(T58>0,B58,D58) -> 0.015625 | C59: =IF(T58>0,D58,C58) -> 0.021484375 | D59: =(B59+C59)/2 -> 0.018554688 | E59: =$C$2*(1+IF(E$3<=$O$2,$D59,$D59-($D59-$I$49)*MIN(E$3-$O$2,$Q$2)/$Q$2)) -> 3198.2617 | F59: =E59*(1+IF(F$3<=$O$2,$D59,$D59-($D59-$I$49)*MIN(F$3-$O$2,$Q$2)/$Q$2)) -> 3257.6045 | G59: =F59*(1+IF(G$3<=$O$2,$D59,$D59-($D59-$I$49)*MIN(G$3-$O$2,$Q$2)/$Q$2)) -> 3318.0483 | H59: =G59*(1+IF(H$3<=$O$2,$D59,$D59-($D59-$I$49)*MIN(H$3-$O$2,$Q$2)/$Q$2)) -> 3379.6136 | I59: =H59*(1+IF(I$3<=$O$2,$D59,$D59-($D59-$I$49)*MIN(I$3-$O$2,$Q$2)/$Q$2)) -> 3442.3213 | J59: =I59*(1+IF(J$3<=$O$2,$D59,$D59-($D59-$I$49)*MIN(J$3-$O$2,$Q$2)/$Q$2)) -> 3506.0172 | K59: =J59*(1+IF(K$3<=$O$2,$D59,$D59-($D59-$I$49)*MIN(K$3-$O$2,$Q$2)/$Q$2)) -> 3570.7131 | L59: =K59*(1+IF(L$3<=$O$2,$D59,$D59-($D59-$I$49)*MIN(L$3-$O$2,$Q$2)/$Q$2)) -> 3636.4209 | M59: =L59*(1+IF(M$3<=$O$2,$D59,$D59-($D59-$I$49)*MIN(M$3-$O$2,$Q$2)/$Q$2)) -> 3703.1526 | N59: =M59*(1+IF(N$3<=$O$2,$D59,$D59-($D59-$I$49)*MIN(N$3-$O$2,$Q$2)/$Q$2)) -> 3770.9203 | O59: =SUMPRODUCT(E59:N59,1/(1+$F$49)^$E$3:$N$3)*$E$2 -> 10893.102 | P59: =N59*$E$2*(1+$I$49)/($F$49-$I$49)/(1+$F$49)^$N$3 -> 16246.473 | Q59: =O59+P59 -> 27139.575 | R59: =Q59-$G$2+$I$2 -> 23071.775 | S59: =R59/$K$2 -> 177.25703 | T59: =S59-$M$2 -> 0.62826363
A60: 10 | B60: =IF(T59>0,B59,D59) -> 0.015625 | C60: =IF(T59>0,D59,C59) -> 0.018554688 | D60: =(B60+C60)/2 -> 0.017089844 | E60: =$C$2*(1+IF(E$3<=$O$2,$D60,$D60-($D60-$I$49)*MIN(E$3-$O$2,$Q$2)/$Q$2)) -> 3193.6621 | F60: =E60*(1+IF(F$3<=$O$2,$D60,$D60-($D60-$I$49)*MIN(F$3-$O$2,$Q$2)/$Q$2)) -> 3248.2413 | G60: =F60*(1+IF(G$3<=$O$2,$D60,$D60-($D60-$I$49)*MIN(G$3-$O$2,$Q$2)/$Q$2)) -> 3303.7532 | H60: =G60*(1+IF(H$3<=$O$2,$D60,$D60-($D60-$I$49)*MIN(H$3-$O$2,$Q$2)/$Q$2)) -> 3360.2139 | I60: =H60*(1+IF(I$3<=$O$2,$D60,$D60-($D60-$I$49)*MIN(I$3-$O$2,$Q$2)/$Q$2)) -> 3417.6394 | J60: =I60*(1+IF(J$3<=$O$2,$D60,$D60-($D60-$I$49)*MIN(J$3-$O$2,$Q$2)/$Q$2)) -> 3476.8735 | K60: =J60*(1+IF(K$3<=$O$2,$D60,$D60-($D60-$I$49)*MIN(K$3-$O$2,$Q$2)/$Q$2)) -> 3537.9757 | L60: =K60*(1+IF(L$3<=$O$2,$D60,$D60-($D60-$I$49)*MIN(L$3-$O$2,$Q$2)/$Q$2)) -> 3601.0081 | M60: =L60*(1+IF(M$3<=$O$2,$D60,$D60-($D60-$I$49)*MIN(M$3-$O$2,$Q$2)/$Q$2)) -> 3666.035 | N60: =M60*(1+IF(N$3<=$O$2,$D60,$D60-($D60-$I$49)*MIN(N$3-$O$2,$Q$2)/$Q$2)) -> 3733.1234 | O60: =SUMPRODUCT(E60:N60,1/(1+$F$49)^$E$3:$N$3)*$E$2 -> 10822.835 | P60: =N60*$E$2*(1+$I$49)/($F$49-$I$49)/(1+$F$49)^$N$3 -> 16083.63 | Q60: =O60+P60 -> 26906.465 | R60: =Q60-$G$2+$I$2 -> 22838.665 | S60: =R60/$K$2 -> 175.46608 | T60: =S60-$M$2 -> -1.1626809
A61: 11 | B61: =IF(T60>0,B60,D60) -> 0.017089844 | C61: =IF(T60>0,D60,C60) -> 0.018554688 | D61: =(B61+C61)/2 -> 0.017822266 | E61: =$C$2*(1+IF(E$3<=$O$2,$D61,$D61-($D61-$I$49)*MIN(E$3-$O$2,$Q$2)/$Q$2)) -> 3195.9619 | F61: =E61*(1+IF(F$3<=$O$2,$D61,$D61-($D61-$I$49)*MIN(F$3-$O$2,$Q$2)/$Q$2)) -> 3252.9212 | G61: =F61*(1+IF(G$3<=$O$2,$D61,$D61-($D61-$I$49)*MIN(G$3-$O$2,$Q$2)/$Q$2)) -> 3310.8956 | H61: =G61*(1+IF(H$3<=$O$2,$D61,$D61-($D61-$I$49)*MIN(H$3-$O$2,$Q$2)/$Q$2)) -> 3369.9033 | I61: =H61*(1+IF(I$3<=$O$2,$D61,$D61-($D61-$I$49)*MIN(I$3-$O$2,$Q$2)/$Q$2)) -> 3429.9626 | J61: =I61*(1+IF(J$3<=$O$2,$D61,$D61-($D61-$I$49)*MIN(J$3-$O$2,$Q$2)/$Q$2)) -> 3491.42 | K61: =J61*(1+IF(K$3<=$O$2,$D61,$D61-($D61-$I$49)*MIN(K$3-$O$2,$Q$2)/$Q$2)) -> 3554.3122 | L61: =K61*(1+IF(L$3<=$O$2,$D61,$D61-($D61-$I$49)*MIN(L$3-$O$2,$Q$2)/$Q$2)) -> 3618.6769 | M61: =L61*(1+IF(M$3<=$O$2,$D61,$D61-($D61-$I$49)*MIN(M$3-$O$2,$Q$2)/$Q$2)) -> 3684.553 | N61: =M61*(1+IF(N$3<=$O$2,$D61,$D61-($D61-$I$49)*MIN(N$3-$O$2,$Q$2)/$Q$2)) -> 3751.9803 | O61: =SUMPRODUCT(E61:N61,1/(1+$F$49)^$E$3:$N$3)*$E$2 -> 10857.911 | P61: =N61*$E$2*(1+$I$49)/($F$49-$I$49)/(1+$F$49)^$N$3 -> 16164.872 | Q61: =O61+P61 -> 27022.783 | R61: =Q61-$G$2+$I$2 -> 22954.983 | S61: =R61/$K$2 -> 176.35974 | T61: =S61-$M$2 -> -0.2690273
A62: 12 | B62: =IF(T61>0,B61,D61) -> 0.017822266 | C62: =IF(T61>0,D61,C61) -> 0.018554688 | D62: =(B62+C62)/2 -> 0.018188477 | E62: =$C$2*(1+IF(E$3<=$O$2,$D62,$D62-($D62-$I$49)*MIN(E$3-$O$2,$Q$2)/$Q$2)) -> 3197.1118 | F62: =E62*(1+IF(F$3<=$O$2,$D62,$D62-($D62-$I$49)*MIN(F$3-$O$2,$Q$2)/$Q$2)) -> 3255.2624 | G62: =F62*(1+IF(G$3<=$O$2,$D62,$D62-($D62-$I$49)*MIN(G$3-$O$2,$Q$2)/$Q$2)) -> 3314.4707 | H62: =G62*(1+IF(H$3<=$O$2,$D62,$D62-($D62-$I$49)*MIN(H$3-$O$2,$Q$2)/$Q$2)) -> 3374.7558 | I62: =H62*(1+IF(I$3<=$O$2,$D62,$D62-($D62-$I$49)*MIN(I$3-$O$2,$Q$2)/$Q$2)) -> 3436.1375 | J62: =I62*(1+IF(J$3<=$O$2,$D62,$D62-($D62-$I$49)*MIN(J$3-$O$2,$Q$2)/$Q$2)) -> 3498.7123 | K62: =J62*(1+IF(K$3<=$O$2,$D62,$D62-($D62-$I$49)*MIN(K$3-$O$2,$Q$2)/$Q$2)) -> 3562.5046 | L62: =K62*(1+IF(L$3<=$O$2,$D62,$D62-($D62-$I$49)*MIN(L$3-$O$2,$Q$2)/$Q$2)) -> 3627.5395 | M62: =L62*(1+IF(M$3<=$O$2,$D62,$D62-($D62-$I$49)*MIN(M$3-$O$2,$Q$2)/$Q$2)) -> 3693.8426 | N62: =M62*(1+IF(N$3<=$O$2,$D62,$D62-($D62-$I$49)*MIN(N$3-$O$2,$Q$2)/$Q$2)) -> 3761.4399 | O62: =SUMPRODUCT(E62:N62,1/(1+$F$49)^$E$3:$N$3)*$E$2 -> 10875.492 | P62: =N62*$E$2*(1+$I$49)/($F$49-$I$49)/(1+$F$49)^$N$3 -> 16205.628 | Q62: =O62+P62 -> 27081.12 | R62: =Q62-$G$2+$I$2 -> 23013.32 | S62: =R62/$K$2 -> 176.80793 | T62: =S62-$M$2 -> 0.17916267
A63: 13 | B63: =IF(T62>0,B62,D62) -> 0.017822266 | C63: =IF(T62>0,D62,C62) -> 0.018188477 | D63: =(B63+C63)/2 -> 0.018005371 | E63: =$C$2*(1+IF(E$3<=$O$2,$D63,$D63-($D63-$I$49)*MIN(E$3-$O$2,$Q$2)/$Q$2)) -> 3196.5369 | F63: =E63*(1+IF(F$3<=$O$2,$D63,$D63-($D63-$I$49)*MIN(F$3-$O$2,$Q$2)/$Q$2)) -> 3254.0917 | G63: =F63*(1+IF(G$3<=$O$2,$D63,$D63-($D63-$I$49)*MIN(G$3-$O$2,$Q$2)/$Q$2)) -> 3312.6828 | H63: =G63*(1+IF(H$3<=$O$2,$D63,$D63-($D63-$I$49)*MIN(H$3-$O$2,$Q$2)/$Q$2)) -> 3372.3289 | I63: =H63*(1+IF(I$3<=$O$2,$D63,$D63-($D63-$I$49)*MIN(I$3-$O$2,$Q$2)/$Q$2)) -> 3433.0489 | J63: =I63*(1+IF(J$3<=$O$2,$D63,$D63-($D63-$I$49)*MIN(J$3-$O$2,$Q$2)/$Q$2)) -> 3495.0646 | K63: =J63*(1+IF(K$3<=$O$2,$D63,$D63-($D63-$I$49)*MIN(K$3-$O$2,$Q$2)/$Q$2)) -> 3558.4064 | L63: =K63*(1+IF(L$3<=$O$2,$D63,$D63-($D63-$I$49)*MIN(L$3-$O$2,$Q$2)/$Q$2)) -> 3623.1059 | M63: =L63*(1+IF(M$3<=$O$2,$D63,$D63-($D63-$I$49)*MIN(M$3-$O$2,$Q$2)/$Q$2)) -> 3689.1952 | N63: =M63*(1+IF(N$3<=$O$2,$D63,$D63-($D63-$I$49)*MIN(N$3-$O$2,$Q$2)/$Q$2)) -> 3756.7075 | O63: =SUMPRODUCT(E63:N63,1/(1+$F$49)^$E$3:$N$3)*$E$2 -> 10866.698 | P63: =N63*$E$2*(1+$I$49)/($F$49-$I$49)/(1+$F$49)^$N$3 -> 16185.239 | Q63: =O63+P63 -> 27051.937 | R63: =Q63-$G$2+$I$2 -> 22984.137 | S63: =R63/$K$2 -> 176.58372 | T63: =S63-$M$2 -> -0.045046086
... A74: 24 | B74: =IF(T73>0,B73,D73) -> 0.018042028 | C74: =IF(T73>0,D73,C73) -> 0.018042207 | D74: =(B74+C74)/2 -> 0.018042117 | E74: =$C$2*(1+IF(E$3<=$O$2,$D74,$D74-($D74-$I$49)*MIN(E$3-$O$2,$Q$2)/$Q$2)) -> 3196.6522 | F74: =E74*(1+IF(F$3<=$O$2,$D74,$D74-($D74-$I$49)*MIN(F$3-$O$2,$Q$2)/$Q$2)) -> 3254.3266 | G74: =F74*(1+IF(G$3<=$O$2,$D74,$D74-($D74-$I$49)*MIN(G$3-$O$2,$Q$2)/$Q$2)) -> 3313.0416 | H74: =G74*(1+IF(H$3<=$O$2,$D74,$D74-($D74-$I$49)*MIN(H$3-$O$2,$Q$2)/$Q$2)) -> 3372.8159 | I74: =H74*(1+IF(I$3<=$O$2,$D74,$D74-($D74-$I$49)*MIN(I$3-$O$2,$Q$2)/$Q$2)) -> 3433.6686 | J74: =I74*(1+IF(J$3<=$O$2,$D74,$D74-($D74-$I$49)*MIN(J$3-$O$2,$Q$2)/$Q$2)) -> 3495.7963 | K74: =J74*(1+IF(K$3<=$O$2,$D74,$D74-($D74-$I$49)*MIN(K$3-$O$2,$Q$2)/$Q$2)) -> 3559.2285 | L74: =K74*(1+IF(L$3<=$O$2,$D74,$D74-($D74-$I$49)*MIN(L$3-$O$2,$Q$2)/$Q$2)) -> 3623.9952 | M74: =L74*(1+IF(M$3<=$O$2,$D74,$D74-($D74-$I$49)*MIN(M$3-$O$2,$Q$2)/$Q$2)) -> 3690.1274 | N74: =M74*(1+IF(N$3<=$O$2,$D74,$D74-($D74-$I$49)*MIN(N$3-$O$2,$Q$2)/$Q$2)) -> 3757.6568 | O74: =SUMPRODUCT(E74:N74,1/(1+$F$49)^$E$3:$N$3)*$E$2 -> 10868.462 | P74: =N74*$E$2*(1+$I$49)/($F$49-$I$49)/(1+$F$49)^$N$3 -> 16189.329 | Q74: =O74+P74 -> 27057.791 | R74: =Q74-$G$2+$I$2 -> 22989.991 | S74: =R74/$K$2 -> 176.6287 | T74: =S74-$M$2 -> -6.9322769e-05
A76: Grid block 3: row 1, column 2 of table A (24 steps) | E76: WACC | F76: =Sensitivity!$B$10 -> 0.071941394 | G76: Terminal growth | I76: =Sensitivity!$D$9 -> 0.0233
A77: Step | B77: Low | C77: High | D77: Mid | E77: Rev Y1 | F77: Rev Y2 | G77: Rev Y3 | H77: Rev Y4 | I77: Rev Y5 | J77: Rev Y6 | K77: Rev Y7 | L77: Rev Y8 | M77: Rev Y9 | N77: Rev Y10 | O77: PV of FCF | P77: PV of TV | Q77: EV | R77: Equity | S77: Per share | T77: Value - price
A78: 1 | B78: -0.5 | C78: 1 | D78: =(B78+C78)/2 -> 0.25 | E78: =$C$2*(1+IF(E$3<=$O$2,$D78,$D78-($D78-$I$76)*MIN(E$3-$O$2,$Q$2)/$Q$2)) -> 3925 | F78: =E78*(1+IF(F$3<=$O$2,$D78,$D78-($D78-$I$76)*MIN(F$3-$O$2,$Q$2)/$Q$2)) -> 4906.25 | G78: =F78*(1+IF(G$3<=$O$2,$D78,$D78-($D78-$I$76)*MIN(G$3-$O$2,$Q$2)/$Q$2)) -> 6132.8125 | H78: =G78*(1+IF(H$3<=$O$2,$D78,$D78-($D78-$I$76)*MIN(H$3-$O$2,$Q$2)/$Q$2)) -> 7666.0156 | I78: =H78*(1+IF(I$3<=$O$2,$D78,$D78-($D78-$I$76)*MIN(I$3-$O$2,$Q$2)/$Q$2)) -> 9582.5195 | J78: =I78*(1+IF(J$3<=$O$2,$D78,$D78-($D78-$I$76)*MIN(J$3-$O$2,$Q$2)/$Q$2)) -> 11543.678 | K78: =J78*(1+IF(K$3<=$O$2,$D78,$D78-($D78-$I$76)*MIN(K$3-$O$2,$Q$2)/$Q$2)) -> 13382.817 | L78: =K78*(1+IF(L$3<=$O$2,$D78,$D78-($D78-$I$76)*MIN(L$3-$O$2,$Q$2)/$Q$2)) -> 14908.19 | M78: =L78*(1+IF(M$3<=$O$2,$D78,$D78-($D78-$I$76)*MIN(M$3-$O$2,$Q$2)/$Q$2)) -> 15931.488 | N78: =M78*(1+IF(N$3<=$O$2,$D78,$D78-($D78-$I$76)*MIN(N$3-$O$2,$Q$2)/$Q$2)) -> 16302.692 | O78: =SUMPRODUCT(E78:N78,1/(1+$F$76)^$E$3:$N$3)*$E$2 -> 30250.637 | P78: =N78*$E$2*(1+$I$76)/($F$76-$I$76)/(1+$F$76)^$N$3 -> 77838.119 | Q78: =O78+P78 -> 108088.76 | R78: =Q78-$G$2+$I$2 -> 104020.96 | S78: =R78/$K$2 -> 799.1776 | T78: =S78-$M$2 -> 622.54883
A79: 2 | B79: =IF(T78>0,B78,D78) -> -0.5 | C79: =IF(T78>0,D78,C78) -> 0.25 | D79: =(B79+C79)/2 -> -0.125 | E79: =$C$2*(1+IF(E$3<=$O$2,$D79,$D79-($D79-$I$76)*MIN(E$3-$O$2,$Q$2)/$Q$2)) -> 2747.5 | F79: =E79*(1+IF(F$3<=$O$2,$D79,$D79-($D79-$I$76)*MIN(F$3-$O$2,$Q$2)/$Q$2)) -> 2404.0625 | G79: =F79*(1+IF(G$3<=$O$2,$D79,$D79-($D79-$I$76)*MIN(G$3-$O$2,$Q$2)/$Q$2)) -> 2103.5547 | H79: =G79*(1+IF(H$3<=$O$2,$D79,$D79-($D79-$I$76)*MIN(H$3-$O$2,$Q$2)/$Q$2)) -> 1840.6104 | I79: =H79*(1+IF(I$3<=$O$2,$D79,$D79-($D79-$I$76)*MIN(I$3-$O$2,$Q$2)/$Q$2)) -> 1610.5341 | J79: =I79*(1+IF(J$3<=$O$2,$D79,$D79-($D79-$I$76)*MIN(J$3-$O$2,$Q$2)/$Q$2)) -> 1456.9857 | K79: =J79*(1+IF(K$3<=$O$2,$D79,$D79-($D79-$I$76)*MIN(K$3-$O$2,$Q$2)/$Q$2)) -> 1361.2909 | L79: =K79*(1+IF(L$3<=$O$2,$D79,$D79-($D79-$I$76)*MIN(L$3-$O$2,$Q$2)/$Q$2)) -> 1312.2572 | M79: =L79*(1+IF(M$3<=$O$2,$D79,$D79-($D79-$I$76)*MIN(M$3-$O$2,$Q$2)/$Q$2)) -> 1303.9113 | N79: =M79*(1+IF(N$3<=$O$2,$D79,$D79-($D79-$I$76)*MIN(N$3-$O$2,$Q$2)/$Q$2)) -> 1334.2924 | O79: =SUMPRODUCT(E79:N79,1/(1+$F$76)^$E$3:$N$3)*$E$2 -> 5823.2534 | P79: =N79*$E$2*(1+$I$76)/($F$76-$I$76)/(1+$F$76)^$N$3 -> 6370.654 | Q79: =O79+P79 -> 12193.907 | R79: =Q79-$G$2+$I$2 -> 8126.1074 | S79: =R79/$K$2 -> 62.43168 | T79: =S79-$M$2 -> -114.19709
A80: 3 | B80: =IF(T79>0,B79,D79) -> -0.125 | C80: =IF(T79>0,D79,C79) -> 0.25 | D80: =(B80+C80)/2 -> 0.0625 | E80: =$C$2*(1+IF(E$3<=$O$2,$D80,$D80-($D80-$I$76)*MIN(E$3-$O$2,$Q$2)/$Q$2)) -> 3336.25 | F80: =E80*(1+IF(F$3<=$O$2,$D80,$D80-($D80-$I$76)*MIN(F$3-$O$2,$Q$2)/$Q$2)) -> 3544.7656 | G80: =F80*(1+IF(G$3<=$O$2,$D80,$D80-($D80-$I$76)*MIN(G$3-$O$2,$Q$2)/$Q$2)) -> 3766.3135 | H80: =G80*(1+IF(H$3<=$O$2,$D80,$D80-($D80-$I$76)*MIN(H$3-$O$2,$Q$2)/$Q$2)) -> 4001.7081 | I80: =H80*(1+IF(I$3<=$O$2,$D80,$D80-($D80-$I$76)*MIN(I$3-$O$2,$Q$2)/$Q$2)) -> 4251.8148 | J80: =I80*(1+IF(J$3<=$O$2,$D80,$D80-($D80-$I$76)*MIN(J$3-$O$2,$Q$2)/$Q$2)) -> 4484.219 | K80: =J80*(1+IF(K$3<=$O$2,$D80,$D80-($D80-$I$76)*MIN(K$3-$O$2,$Q$2)/$Q$2)) -> 4694.1702 | L80: =K80*(1+IF(L$3<=$O$2,$D80,$D80-($D80-$I$76)*MIN(L$3-$O$2,$Q$2)/$Q$2)) -> 4877.1489 | M80: =L80*(1+IF(M$3<=$O$2,$D80,$D80-($D80-$I$76)*MIN(M$3-$O$2,$Q$2)/$Q$2)) -> 5029.0233 | N80: =M80*(1+IF(N$3<=$O$2,$D80,$D80-($D80-$I$76)*MIN(N$3-$O$2,$Q$2)/$Q$2)) -> 5146.1996 | O80: =SUMPRODUCT(E80:N80,1/(1+$F$76)^$E$3:$N$3)*$E$2 -> 13270.326 | P80: =N80*$E$2*(1+$I$76)/($F$76-$I$76)/(1+$F$76)^$N$3 -> 24570.819 | Q80: =O80+P80 -> 37841.144 | R80: =Q80-$G$2+$I$2 -> 33773.344 | S80: =R80/$K$2 -> 259.4756 | T80: =S80-$M$2 -> 82.846838
A81: 4 | B81: =IF(T80>0,B80,D80) -> -0.125 | C81: =IF(T80>0,D80,C80) -> 0.0625 | D81: =(B81+C81)/2 -> -0.03125 | E81: =$C$2*(1+IF(E$3<=$O$2,$D81,$D81-($D81-$I$76)*MIN(E$3-$O$2,$Q$2)/$Q$2)) -> 3041.875 | F81: =E81*(1+IF(F$3<=$O$2,$D81,$D81-($D81-$I$76)*MIN(F$3-$O$2,$Q$2)/$Q$2)) -> 2946.8164 | G81: =F81*(1+IF(G$3<=$O$2,$D81,$D81-($D81-$I$76)*MIN(G$3-$O$2,$Q$2)/$Q$2)) -> 2854.7284 | H81: =G81*(1+IF(H$3<=$O$2,$D81,$D81-($D81-$I$76)*MIN(H$3-$O$2,$Q$2)/$Q$2)) -> 2765.5181 | I81: =H81*(1+IF(I$3<=$O$2,$D81,$D81-($D81-$I$76)*MIN(I$3-$O$2,$Q$2)/$Q$2)) -> 2679.0957 | J81: =I81*(1+IF(J$3<=$O$2,$D81,$D81-($D81-$I$76)*MIN(J$3-$O$2,$Q$2)/$Q$2)) -> 2624.6029 | K81: =J81*(1+IF(K$3<=$O$2,$D81,$D81-($D81-$I$76)*MIN(K$3-$O$2,$Q$2)/$Q$2)) -> 2599.8529 | L81: =K81*(1+IF(L$3<=$O$2,$D81,$D81-($D81-$I$76)*MIN(L$3-$O$2,$Q$2)/$Q$2)) -> 2603.7007 | M81: =L81*(1+IF(M$3<=$O$2,$D81,$D81-($D81-$I$76)*MIN(M$3-$O$2,$Q$2)/$Q$2)) -> 2635.9605 | N81: =M81*(1+IF(N$3<=$O$2,$D81,$D81-($D81-$I$76)*MIN(N$3-$O$2,$Q$2)/$Q$2)) -> 2697.3784 | O81: =SUMPRODUCT(E81:N81,1/(1+$F$76)^$E$3:$N$3)*$E$2 -> 8768.1039 | P81: =N81*$E$2*(1+$I$76)/($F$76-$I$76)/(1+$F$76)^$N$3 -> 12878.785 | Q81: =O81+P81 -> 21646.888 | R81: =Q81-$G$2+$I$2 -> 17579.088 | S81: =R81/$K$2 -> 135.05753 | T81: =S81-$M$2 -> -41.571232
A82: 5 | B82: =IF(T81>0,B81,D81) -> -0.03125 | C82: =IF(T81>0,D81,C81) -> 0.0625 | D82: =(B82+C82)/2 -> 0.015625 | E82: =$C$2*(1+IF(E$3<=$O$2,$D82,$D82-($D82-$I$76)*MIN(E$3-$O$2,$Q$2)/$Q$2)) -> 3189.0625 | F82: =E82*(1+IF(F$3<=$O$2,$D82,$D82-($D82-$I$76)*MIN(F$3-$O$2,$Q$2)/$Q$2)) -> 3238.8916 | G82: =F82*(1+IF(G$3<=$O$2,$D82,$D82-($D82-$I$76)*MIN(G$3-$O$2,$Q$2)/$Q$2)) -> 3289.4993 | H82: =G82*(1+IF(H$3<=$O$2,$D82,$D82-($D82-$I$76)*MIN(H$3-$O$2,$Q$2)/$Q$2)) -> 3340.8977 | I82: =H82*(1+IF(I$3<=$O$2,$D82,$D82-($D82-$I$76)*MIN(I$3-$O$2,$Q$2)/$Q$2)) -> 3393.0992 | J82: =I82*(1+IF(J$3<=$O$2,$D82,$D82-($D82-$I$76)*MIN(J$3-$O$2,$Q$2)/$Q$2)) -> 3451.3248 | K82: =J82*(1+IF(K$3<=$O$2,$D82,$D82-($D82-$I$76)*MIN(K$3-$O$2,$Q$2)/$Q$2)) -> 3515.8473 | L82: =K82*(1+IF(L$3<=$O$2,$D82,$D82-($D82-$I$76)*MIN(L$3-$O$2,$Q$2)/$Q$2)) -> 3586.9729 | M82: =L82*(1+IF(M$3<=$O$2,$D82,$D82-($D82-$I$76)*MIN(M$3-$O$2,$Q$2)/$Q$2)) -> 3665.0434 | N82: =M82*(1+IF(N$3<=$O$2,$D82,$D82-($D82-$I$76)*MIN(N$3-$O$2,$Q$2)/$Q$2)) -> 3750.4389 | O82: =SUMPRODUCT(E82:N82,1/(1+$F$76)^$E$3:$N$3)*$E$2 -> 10783.578 | P82: =N82*$E$2*(1+$I$76)/($F$76-$I$76)/(1+$F$76)^$N$3 -> 17906.681 | Q82: =O82+P82 -> 28690.259 | R82: =Q82-$G$2+$I$2 -> 24622.459 | S82: =R82/$K$2 -> 189.1707 | T82: =S82-$M$2 -> 12.541939
A83: 6 | B83: =IF(T82>0,B82,D82) -> -0.03125 | C83: =IF(T82>0,D82,C82) -> 0.015625 | D83: =(B83+C83)/2 -> -0.0078125 | E83: =$C$2*(1+IF(E$3<=$O$2,$D83,$D83-($D83-$I$76)*MIN(E$3-$O$2,$Q$2)/$Q$2)) -> 3115.4688 | F83: =E83*(1+IF(F$3<=$O$2,$D83,$D83-($D83-$I$76)*MIN(F$3-$O$2,$Q$2)/$Q$2)) -> 3091.1292 | G83: =F83*(1+IF(G$3<=$O$2,$D83,$D83-($D83-$I$76)*MIN(G$3-$O$2,$Q$2)/$Q$2)) -> 3066.9797 | H83: =G83*(1+IF(H$3<=$O$2,$D83,$D83-($D83-$I$76)*MIN(H$3-$O$2,$Q$2)/$Q$2)) -> 3043.0189 | I83: =H83*(1+IF(I$3<=$O$2,$D83,$D83-($D83-$I$76)*MIN(I$3-$O$2,$Q$2)/$Q$2)) -> 3019.2453 | J83: =I83*(1+IF(J$3<=$O$2,$D83,$D83-($D83-$I$76)*MIN(J$3-$O$2,$Q$2)/$Q$2)) -> 3014.4447 | K83: =J83*(1+IF(K$3<=$O$2,$D83,$D83-($D83-$I$76)*MIN(K$3-$O$2,$Q$2)/$Q$2)) -> 3028.4092 | L83: =K83*(1+IF(L$3<=$O$2,$D83,$D83-($D83-$I$76)*MIN(L$3-$O$2,$Q$2)/$Q$2)) -> 3061.2825 | M83: =L83*(1+IF(M$3<=$O$2,$D83,$D83-($D83-$I$76)*MIN(M$3-$O$2,$Q$2)/$Q$2)) -> 3113.5616 | N83: =M83*(1+IF(N$3<=$O$2,$D83,$D83-($D83-$I$76)*MIN(N$3-$O$2,$Q$2)/$Q$2)) -> 3186.1076 | O83: =SUMPRODUCT(E83:N83,1/(1+$F$76)^$E$3:$N$3)*$E$2 -> 9722.6177 | P83: =N83*$E$2*(1+$I$76)/($F$76-$I$76)/(1+$F$76)^$N$3 -> 15212.25 | Q83: =O83+P83 -> 24934.867 | R83: =Q83-$G$2+$I$2 -> 20867.067 | S83: =R83/$K$2 -> 160.31859 | T83: =S83-$M$2 -> -16.310178
A84: 7 | B84: =IF(T83>0,B83,D83) -> -0.0078125 | C84: =IF(T83>0,D83,C83) -> 0.015625 | D84: =(B84+C84)/2 -> 0.00390625 | E84: =$C$2*(1+IF(E$3<=$O$2,$D84,$D84-($D84-$I$76)*MIN(E$3-$O$2,$Q$2)/$Q$2)) -> 3152.2656 | F84: =E84*(1+IF(F$3<=$O$2,$D84,$D84-($D84-$I$76)*MIN(F$3-$O$2,$Q$2)/$Q$2)) -> 3164.5792 | G84: =F84*(1+IF(G$3<=$O$2,$D84,$D84-($D84-$I$76)*MIN(G$3-$O$2,$Q$2)/$Q$2)) -> 3176.9408 | H84: =G84*(1+IF(H$3<=$O$2,$D84,$D84-($D84-$I$76)*MIN(H$3-$O$2,$Q$2)/$Q$2)) -> 3189.3507 | I84: =H84*(1+IF(I$3<=$O$2,$D84,$D84-($D84-$I$76)*MIN(I$3-$O$2,$Q$2)/$Q$2)) -> 3201.8091 | J84: =I84*(1+IF(J$3<=$O$2,$D84,$D84-($D84-$I$76)*MIN(J$3-$O$2,$Q$2)/$Q$2)) -> 3226.7352 | K84: =J84*(1+IF(K$3<=$O$2,$D84,$D84-($D84-$I$76)*MIN(K$3-$O$2,$Q$2)/$Q$2)) -> 3264.371 | L84: =K84*(1+IF(L$3<=$O$2,$D84,$D84-($D84-$I$76)*MIN(L$3-$O$2,$Q$2)/$Q$2)) -> 3315.1075 | M84: =L84*(1+IF(M$3<=$O$2,$D84,$D84-($D84-$I$76)*MIN(M$3-$O$2,$Q$2)/$Q$2)) -> 3379.4911 | N84: =M84*(1+IF(N$3<=$O$2,$D84,$D84-($D84-$I$76)*MIN(N$3-$O$2,$Q$2)/$Q$2)) -> 3458.2332 | O84: =SUMPRODUCT(E84:N84,1/(1+$F$76)^$E$3:$N$3)*$E$2 -> 10239.119 | P84: =N84*$E$2*(1+$I$76)/($F$76-$I$76)/(1+$F$76)^$N$3 -> 16511.529 | Q84: =O84+P84 -> 26750.648 | R84: =Q84-$G$2+$I$2 -> 22682.848 | S84: =R84/$K$2 -> 174.26896 | T84: =S84-$M$2 -> -2.3598039
A85: 8 | B85: =IF(T84>0,B84,D84) -> 0.00390625 | C85: =IF(T84>0,D84,C84) -> 0.015625 | D85: =(B85+C85)/2 -> 0.009765625 | E85: =$C$2*(1+IF(E$3<=$O$2,$D85,$D85-($D85-$I$76)*MIN(E$3-$O$2,$Q$2)/$Q$2)) -> 3170.6641 | F85: =E85*(1+IF(F$3<=$O$2,$D85,$D85-($D85-$I$76)*MIN(F$3-$O$2,$Q$2)/$Q$2)) -> 3201.6276 | G85: =F85*(1+IF(G$3<=$O$2,$D85,$D85-($D85-$I$76)*MIN(G$3-$O$2,$Q$2)/$Q$2)) -> 3232.8935 | H85: =G85*(1+IF(H$3<=$O$2,$D85,$D85-($D85-$I$76)*MIN(H$3-$O$2,$Q$2)/$Q$2)) -> 3264.4647 | I85: =H85*(1+IF(I$3<=$O$2,$D85,$D85-($D85-$I$76)*MIN(I$3-$O$2,$Q$2)/$Q$2)) -> 3296.3442 | J85: =I85*(1+IF(J$3<=$O$2,$D85,$D85-($D85-$I$76)*MIN(J$3-$O$2,$Q$2)/$Q$2)) -> 3337.4579 | K85: =J85*(1+IF(K$3<=$O$2,$D85,$D85-($D85-$I$76)*MIN(K$3-$O$2,$Q$2)/$Q$2)) -> 3388.1184 | L85: =K85*(1+IF(L$3<=$O$2,$D85,$D85-($D85-$I$76)*MIN(L$3-$O$2,$Q$2)/$Q$2)) -> 3448.7191 | M85: =L85*(1+IF(M$3<=$O$2,$D85,$D85-($D85-$I$76)*MIN(M$3-$O$2,$Q$2)/$Q$2)) -> 3519.7391 | N85: =M85*(1+IF(N$3<=$O$2,$D85,$D85-($D85-$I$76)*MIN(N$3-$O$2,$Q$2)/$Q$2)) -> 3601.749 | O85: =SUMPRODUCT(E85:N85,1/(1+$F$76)^$E$3:$N$3)*$E$2 -> 10507.767 | P85: =N85*$E$2*(1+$I$76)/($F$76-$I$76)/(1+$F$76)^$N$3 -> 17196.753 | Q85: =O85+P85 -> 27704.519 | R85: =Q85-$G$2+$I$2 -> 23636.719 | S85: =R85/$K$2 -> 181.59741 | T85: =S85-$M$2 -> 4.9686484
A86: 9 | B86: =IF(T85>0,B85,D85) -> 0.00390625 | C86: =IF(T85>0,D85,C85) -> 0.009765625 | D86: =(B86+C86)/2 -> 0.0068359375 | E86: =$C$2*(1+IF(E$3<=$O$2,$D86,$D86-($D86-$I$76)*MIN(E$3-$O$2,$Q$2)/$Q$2)) -> 3161.4648 | F86: =E86*(1+IF(F$3<=$O$2,$D86,$D86-($D86-$I$76)*MIN(F$3-$O$2,$Q$2)/$Q$2)) -> 3183.0764 | G86: =F86*(1+IF(G$3<=$O$2,$D86,$D86-($D86-$I$76)*MIN(G$3-$O$2,$Q$2)/$Q$2)) -> 3204.8357 | H86: =G86*(1+IF(H$3<=$O$2,$D86,$D86-($D86-$I$76)*MIN(H$3-$O$2,$Q$2)/$Q$2)) -> 3226.7438 | I86: =H86*(1+IF(I$3<=$O$2,$D86,$D86-($D86-$I$76)*MIN(I$3-$O$2,$Q$2)/$Q$2)) -> 3248.8016 | J86: =I86*(1+IF(J$3<=$O$2,$D86,$D86-($D86-$I$76)*MIN(J$3-$O$2,$Q$2)/$Q$2)) -> 3281.7079 | K86: =J86*(1+IF(K$3<=$O$2,$D86,$D86-($D86-$I$76)*MIN(K$3-$O$2,$Q$2)/$Q$2)) -> 3325.7536 | L86: =K86*(1+IF(L$3<=$O$2,$D86,$D86-($D86-$I$76)*MIN(L$3-$O$2,$Q$2)/$Q$2)) -> 3381.3414 | M86: =L86*(1+IF(M$3<=$O$2,$D86,$D86-($D86-$I$76)*MIN(M$3-$O$2,$Q$2)/$Q$2)) -> 3448.9926 | N86: =M86*(1+IF(N$3<=$O$2,$D86,$D86-($D86-$I$76)*MIN(N$3-$O$2,$Q$2)/$Q$2)) -> 3529.3541 | O86: =SUMPRODUCT(E86:N86,1/(1+$F$76)^$E$3:$N$3)*$E$2 -> 10372.558 | P86: =N86*$E$2*(1+$I$76)/($F$76-$I$76)/(1+$F$76)^$N$3 -> 16851.099 | Q86: =O86+P86 -> 27223.658 | R86: =Q86-$G$2+$I$2 -> 23155.858 | S86: =R86/$K$2 -> 177.90303 | T86: =S86-$M$2 -> 1.2742615
A87: 10 | B87: =IF(T86>0,B86,D86) -> 0.00390625 | C87: =IF(T86>0,D86,C86) -> 0.0068359375 | D87: =(B87+C87)/2 -> 0.0053710938 | E87: =$C$2*(1+IF(E$3<=$O$2,$D87,$D87-($D87-$I$76)*MIN(E$3-$O$2,$Q$2)/$Q$2)) -> 3156.8652 | F87: =E87*(1+IF(F$3<=$O$2,$D87,$D87-($D87-$I$76)*MIN(F$3-$O$2,$Q$2)/$Q$2)) -> 3173.8211 | G87: =F87*(1+IF(G$3<=$O$2,$D87,$D87-($D87-$I$76)*MIN(G$3-$O$2,$Q$2)/$Q$2)) -> 3190.8679 | H87: =G87*(1+IF(H$3<=$O$2,$D87,$D87-($D87-$I$76)*MIN(H$3-$O$2,$Q$2)/$Q$2)) -> 3208.0064 | I87: =H87*(1+IF(I$3<=$O$2,$D87,$D87-($D87-$I$76)*MIN(I$3-$O$2,$Q$2)/$Q$2)) -> 3225.2369 | J87: =I87*(1+IF(J$3<=$O$2,$D87,$D87-($D87-$I$76)*MIN(J$3-$O$2,$Q$2)/$Q$2)) -> 3254.1249 | K87: =J87*(1+IF(K$3<=$O$2,$D87,$D87-($D87-$I$76)*MIN(K$3-$O$2,$Q$2)/$Q$2)) -> 3294.9403 | L87: =K87*(1+IF(L$3<=$O$2,$D87,$D87-($D87-$I$76)*MIN(L$3-$O$2,$Q$2)/$Q$2)) -> 3348.0826 | M87: =L87*(1+IF(M$3<=$O$2,$D87,$D87-($D87-$I$76)*MIN(M$3-$O$2,$Q$2)/$Q$2)) -> 3414.0874 | N87: =M87*(1+IF(N$3<=$O$2,$D87,$D87-($D87-$I$76)*MIN(N$3-$O$2,$Q$2)/$Q$2)) -> 3493.6356 | O87: =SUMPRODUCT(E87:N87,1/(1+$F$76)^$E$3:$N$3)*$E$2 -> 10305.619 | P87: =N87*$E$2*(1+$I$76)/($F$76-$I$76)/(1+$F$76)^$N$3 -> 16680.559 | Q87: =O87+P87 -> 26986.179 | R87: =Q87-$G$2+$I$2 -> 22918.379 | S87: =R87/$K$2 -> 176.07851 | T87: =S87-$M$2 -> -0.55025648
A88: 11 | B88: =IF(T87>0,B87,D87) -> 0.0053710938 | C88: =IF(T87>0,D87,C87) -> 0.0068359375 | D88: =(B88+C88)/2 -> 0.0061035156 | E88: =$C$2*(1+IF(E$3<=$O$2,$D88,$D88-($D88-$I$76)*MIN(E$3-$O$2,$Q$2)/$Q$2)) -> 3159.165 | F88: =E88*(1+IF(F$3<=$O$2,$D88,$D88-($D88-$I$76)*MIN(F$3-$O$2,$Q$2)/$Q$2)) -> 3178.4471 | G88: =F88*(1+IF(G$3<=$O$2,$D88,$D88-($D88-$I$76)*MIN(G$3-$O$2,$Q$2)/$Q$2)) -> 3197.8468 | H88: =G88*(1+IF(H$3<=$O$2,$D88,$D88-($D88-$I$76)*MIN(H$3-$O$2,$Q$2)/$Q$2)) -> 3217.3649 | I88: =H88*(1+IF(I$3<=$O$2,$D88,$D88-($D88-$I$76)*MIN(I$3-$O$2,$Q$2)/$Q$2)) -> 3237.0021 | J88: =I88*(1+IF(J$3<=$O$2,$D88,$D88-($D88-$I$76)*MIN(J$3-$O$2,$Q$2)/$Q$2)) -> 3267.8922 | K88: =J88*(1+IF(K$3<=$O$2,$D88,$D88-($D88-$I$76)*MIN(K$3-$O$2,$Q$2)/$Q$2)) -> 3310.3163 | L88: =K88*(1+IF(L$3<=$O$2,$D88,$D88-($D88-$I$76)*MIN(L$3-$O$2,$Q$2)/$Q$2)) -> 3364.6764 | M88: =L88*(1+IF(M$3<=$O$2,$D88,$D88-($D88-$I$76)*MIN(M$3-$O$2,$Q$2)/$Q$2)) -> 3431.5012 | N88: =M88*(1+IF(N$3<=$O$2,$D88,$D88-($D88-$I$76)*MIN(N$3-$O$2,$Q$2)/$Q$2)) -> 3511.4552 | O88: =SUMPRODUCT(E88:N88,1/(1+$F$76)^$E$3:$N$3)*$E$2 -> 10339.034 | P88: =N88*$E$2*(1+$I$76)/($F$76-$I$76)/(1+$F$76)^$N$3 -> 16765.64 | Q88: =O88+P88 -> 27104.674 | R88: =Q88-$G$2+$I$2 -> 23036.874 | S88: =R88/$K$2 -> 176.98889 | T88: =S88-$M$2 -> 0.36012436
A89: 12 | B89: =IF(T88>0,B88,D88) -> 0.0053710938 | C89: =IF(T88>0,D88,C88) -> 0.0061035156 | D89: =(B89+C89)/2 -> 0.0057373047 | E89: =$C$2*(1+IF(E$3<=$O$2,$D89,$D89-($D89-$I$76)*MIN(E$3-$O$2,$Q$2)/$Q$2)) -> 3158.0151 | F89: =E89*(1+IF(F$3<=$O$2,$D89,$D89-($D89-$I$76)*MIN(F$3-$O$2,$Q$2)/$Q$2)) -> 3176.1336 | G89: =F89*(1+IF(G$3<=$O$2,$D89,$D89-($D89-$I$76)*MIN(G$3-$O$2,$Q$2)/$Q$2)) -> 3194.3561 | H89: =G89*(1+IF(H$3<=$O$2,$D89,$D89-($D89-$I$76)*MIN(H$3-$O$2,$Q$2)/$Q$2)) -> 3212.6831 | I89: =H89*(1+IF(I$3<=$O$2,$D89,$D89-($D89-$I$76)*MIN(I$3-$O$2,$Q$2)/$Q$2)) -> 3231.1152 | J89: =I89*(1+IF(J$3<=$O$2,$D89,$D89-($D89-$I$76)*MIN(J$3-$O$2,$Q$2)/$Q$2)) -> 3261.0025 | K89: =J89*(1+IF(K$3<=$O$2,$D89,$D89-($D89-$I$76)*MIN(K$3-$O$2,$Q$2)/$Q$2)) -> 3302.6207 | L89: =K89*(1+IF(L$3<=$O$2,$D89,$D89-($D89-$I$76)*MIN(L$3-$O$2,$Q$2)/$Q$2)) -> 3356.3706 | M89: =L89*(1+IF(M$3<=$O$2,$D89,$D89-($D89-$I$76)*MIN(M$3-$O$2,$Q$2)/$Q$2)) -> 3422.7846 | N89: =M89*(1+IF(N$3<=$O$2,$D89,$D89-($D89-$I$76)*MIN(N$3-$O$2,$Q$2)/$Q$2)) -> 3502.5355 | O89: =SUMPRODUCT(E89:N89,1/(1+$F$76)^$E$3:$N$3)*$E$2 -> 10322.313 | P89: =N89*$E$2*(1+$I$76)/($F$76-$I$76)/(1+$F$76)^$N$3 -> 16723.053 | Q89: =O89+P89 -> 27045.365 | R89: =Q89-$G$2+$I$2 -> 22977.565 | S89: =R89/$K$2 -> 176.53323 | T89: =S89-$M$2 -> -0.09553474
A90: 13 | B90: =IF(T89>0,B89,D89) -> 0.0057373047 | C90: =IF(T89>0,D89,C89) -> 0.0061035156 | D90: =(B90+C90)/2 -> 0.0059204102 | E90: =$C$2*(1+IF(E$3<=$O$2,$D90,$D90-($D90-$I$76)*MIN(E$3-$O$2,$Q$2)/$Q$2)) -> 3158.5901 | F90: =E90*(1+IF(F$3<=$O$2,$D90,$D90-($D90-$I$76)*MIN(F$3-$O$2,$Q$2)/$Q$2)) -> 3177.2902 | G90: =F90*(1+IF(G$3<=$O$2,$D90,$D90-($D90-$I$76)*MIN(G$3-$O$2,$Q$2)/$Q$2)) -> 3196.1011 | H90: =G90*(1+IF(H$3<=$O$2,$D90,$D90-($D90-$I$76)*MIN(H$3-$O$2,$Q$2)/$Q$2)) -> 3215.0233 | I90: =H90*(1+IF(I$3<=$O$2,$D90,$D90-($D90-$I$76)*MIN(I$3-$O$2,$Q$2)/$Q$2)) -> 3234.0576 | J90: =I90*(1+IF(J$3<=$O$2,$D90,$D90-($D90-$I$76)*MIN(J$3-$O$2,$Q$2)/$Q$2)) -> 3264.4459 | K90: =J90*(1+IF(K$3<=$O$2,$D90,$D90-($D90-$I$76)*MIN(K$3-$O$2,$Q$2)/$Q$2)) -> 3306.4666 | L90: =K90*(1+IF(L$3<=$O$2,$D90,$D90-($D90-$I$76)*MIN(L$3-$O$2,$Q$2)/$Q$2)) -> 3360.5213 | M90: =L90*(1+IF(M$3<=$O$2,$D90,$D90-($D90-$I$76)*MIN(M$3-$O$2,$Q$2)/$Q$2)) -> 3427.1405 | N90: =M90*(1+IF(N$3<=$O$2,$D90,$D90-($D90-$I$76)*MIN(N$3-$O$2,$Q$2)/$Q$2)) -> 3506.9929 | O90: =SUMPRODUCT(E90:N90,1/(1+$F$76)^$E$3:$N$3)*$E$2 -> 10330.67 | P90: =N90*$E$2*(1+$I$76)/($F$76-$I$76)/(1+$F$76)^$N$3 -> 16744.334 | Q90: =O90+P90 -> 27075.004 | R90: =Q90-$G$2+$I$2 -> 23007.204 | S90: =R90/$K$2 -> 176.76094 | T90: =S90-$M$2 -> 0.13217753
... A101: 24 | B101: =IF(T100>0,B100,D100) -> 0.0058140159 | C101: =IF(T100>0,D100,C100) -> 0.0058141947 | D101: =(B101+C101)/2 -> 0.0058141053 | E101: =$C$2*(1+IF(E$3<=$O$2,$D101,$D101-($D101-$I$76)*MIN(E$3-$O$2,$Q$2)/$Q$2)) -> 3158.2563 | F101: =E101*(1+IF(F$3<=$O$2,$D101,$D101-($D101-$I$76)*MIN(F$3-$O$2,$Q$2)/$Q$2)) -> 3176.6187 | G101: =F101*(1+IF(G$3<=$O$2,$D101,$D101-($D101-$I$76)*MIN(G$3-$O$2,$Q$2)/$Q$2)) -> 3195.0879 | H101: =G101*(1+IF(H$3<=$O$2,$D101,$D101-($D101-$I$76)*MIN(H$3-$O$2,$Q$2)/$Q$2)) -> 3213.6645 | I101: =H101*(1+IF(I$3<=$O$2,$D101,$D101-($D101-$I$76)*MIN(I$3-$O$2,$Q$2)/$Q$2)) -> 3232.3491 | J101: =I101*(1+IF(J$3<=$O$2,$D101,$D101-($D101-$I$76)*MIN(J$3-$O$2,$Q$2)/$Q$2)) -> 3262.4464 | K101: =J101*(1+IF(K$3<=$O$2,$D101,$D101-($D101-$I$76)*MIN(K$3-$O$2,$Q$2)/$Q$2)) -> 3304.2333 | L101: =K101*(1+IF(L$3<=$O$2,$D101,$D101-($D101-$I$76)*MIN(L$3-$O$2,$Q$2)/$Q$2)) -> 3358.111 | M101: =L101*(1+IF(M$3<=$O$2,$D101,$D101-($D101-$I$76)*MIN(M$3-$O$2,$Q$2)/$Q$2)) -> 3424.611 | N101: =M101*(1+IF(N$3<=$O$2,$D101,$D101-($D101-$I$76)*MIN(N$3-$O$2,$Q$2)/$Q$2)) -> 3504.4045 | O101: =SUMPRODUCT(E101:N101,1/(1+$F$76)^$E$3:$N$3)*$E$2 -> 10325.817 | P101: =N101*$E$2*(1+$I$76)/($F$76-$I$76)/(1+$F$76)^$N$3 -> 16731.976 | Q101: =O101+P101 -> 27057.793 | R101: =Q101-$G$2+$I$2 -> 22989.993 | S101: =R101/$K$2 -> 176.62871 | T101: =S101-$M$2 -> -5.3106385e-05
A103: Grid block 4: row 1, column 3 of table A (24 steps) | E103: WACC | F103: =Sensitivity!$B$10 -> 0.071941394 | G103: Terminal growth | I103: =Sensitivity!$E$9 -> 0.0283
A104: Step | B104: Low | C104: High | D104: Mid | E104: Rev Y1 | F104: Rev Y2 | G104: Rev Y3 | H104: Rev Y4 | I104: Rev Y5 | J104: Rev Y6 | K104: Rev Y7 | L104: Rev Y8 | M104: Rev Y9 | N104: Rev Y10 | O104: PV of FCF | P104: PV of TV | Q104: EV | R104: Equity | S104: Per share | T104: Value - price
A105: 1 | B105: -0.5 | C105: 1 | D105: =(B105+C105)/2 -> 0.25 | E105: =$C$2*(1+IF(E$3<=$O$2,$D105,$D105-($D105-$I$103)*MIN(E$3-$O$2,$Q$2)/$Q$2)) -> 3925 | F105: =E105*(1+IF(F$3<=$O$2,$D105,$D105-($D105-$I$103)*MIN(F$3-$O$2,$Q$2)/$Q$2)) -> 4906.25 | G105: =F105*(1+IF(G$3<=$O$2,$D105,$D105-($D105-$I$103)*MIN(G$3-$O$2,$Q$2)/$Q$2)) -> 6132.8125 | H105: =G105*(1+IF(H$3<=$O$2,$D105,$D105-($D105-$I$103)*MIN(H$3-$O$2,$Q$2)/$Q$2)) -> 7666.0156 | I105: =H105*(1+IF(I$3<=$O$2,$D105,$D105-($D105-$I$103)*MIN(I$3-$O$2,$Q$2)/$Q$2)) -> 9582.5195 | J105: =I105*(1+IF(J$3<=$O$2,$D105,$D105-($D105-$I$103)*MIN(J$3-$O$2,$Q$2)/$Q$2)) -> 11553.26 | K105: =J105*(1+IF(K$3<=$O$2,$D105,$D105-($D105-$I$103)*MIN(K$3-$O$2,$Q$2)/$Q$2)) -> 13417.032 | L105: =K105*(1+IF(L$3<=$O$2,$D105,$D105-($D105-$I$103)*MIN(L$3-$O$2,$Q$2)/$Q$2)) -> 14986.557 | M105: =L105*(1+IF(M$3<=$O$2,$D105,$D105-($D105-$I$103)*MIN(M$3-$O$2,$Q$2)/$Q$2)) -> 16075.18 | N105: =M105*(1+IF(N$3<=$O$2,$D105,$D105-($D105-$I$103)*MIN(N$3-$O$2,$Q$2)/$Q$2)) -> 16530.108 | O105: =SUMPRODUCT(E105:N105,1/(1+$F$103)^$E$3:$N$3)*$E$2 -> 30370.08 | P105: =N105*$E$2*(1+$I$103)/($F$103-$I$103)/(1+$F$103)^$N$3 -> 88396.07 | Q105: =O105+P105 -> 118766.15 | R105: =Q105-$G$2+$I$2 -> 114698.35 | S105: =R105/$K$2 -> 881.21044 | T105: =S105-$M$2 -> 704.58167
A106: 2 | B106: =IF(T105>0,B105,D105) -> -0.5 | C106: =IF(T105>0,D105,C105) -> 0.25 | D106: =(B106+C106)/2 -> -0.125 | E106: =$C$2*(1+IF(E$3<=$O$2,$D106,$D106-($D106-$I$103)*MIN(E$3-$O$2,$Q$2)/$Q$2)) -> 2747.5 | F106: =E106*(1+IF(F$3<=$O$2,$D106,$D106-($D106-$I$103)*MIN(F$3-$O$2,$Q$2)/$Q$2)) -> 2404.0625 | G106: =F106*(1+IF(G$3<=$O$2,$D106,$D106-($D106-$I$103)*MIN(G$3-$O$2,$Q$2)/$Q$2)) -> 2103.5547 | H106: =G106*(1+IF(H$3<=$O$2,$D106,$D106-($D106-$I$103)*MIN(H$3-$O$2,$Q$2)/$Q$2)) -> 1840.6104 | I106: =H106*(1+IF(I$3<=$O$2,$D106,$D106-($D106-$I$103)*MIN(I$3-$O$2,$Q$2)/$Q$2)) -> 1610.5341 | J106: =I106*(1+IF(J$3<=$O$2,$D106,$D106-($D106-$I$103)*MIN(J$3-$O$2,$Q$2)/$Q$2)) -> 1458.5963 | K106: =J106*(1+IF(K$3<=$O$2,$D106,$D106-($D106-$I$103)*MIN(K$3-$O$2,$Q$2)/$Q$2)) -> 1365.7129 | L106: =K106*(1+IF(L$3<=$O$2,$D106,$D106-($D106-$I$103)*MIN(L$3-$O$2,$Q$2)/$Q$2)) -> 1320.617 | M106: =L106*(1+IF(M$3<=$O$2,$D106,$D106-($D106-$I$103)*MIN(M$3-$O$2,$Q$2)/$Q$2)) -> 1317.5004 | N106: =M106*(1+IF(N$3<=$O$2,$D106,$D106-($D106-$I$103)*MIN(N$3-$O$2,$Q$2)/$Q$2)) -> 1354.7856 | O106: =SUMPRODUCT(E106:N106,1/(1+$F$103)^$E$3:$N$3)*$E$2 -> 5835.1092 | P106: =N106*$E$2*(1+$I$103)/($F$103-$I$103)/(1+$F$103)^$N$3 -> 7244.8241 | Q106: =O106+P106 -> 13079.933 | R106: =Q106-$G$2+$I$2 -> 9012.1333 | S106: =R106/$K$2 -> 69.238886 | T106: =S106-$M$2 -> -107.38988
A107: 3 | B107: =IF(T106>0,B106,D106) -> -0.125 | C107: =IF(T106>0,D106,C106) -> 0.25 | D107: =(B107+C107)/2 -> 0.0625 | E107: =$C$2*(1+IF(E$3<=$O$2,$D107,$D107-($D107-$I$103)*MIN(E$3-$O$2,$Q$2)/$Q$2)) -> 3336.25 | F107: =E107*(1+IF(F$3<=$O$2,$D107,$D107-($D107-$I$103)*MIN(F$3-$O$2,$Q$2)/$Q$2)) -> 3544.7656 | G107: =F107*(1+IF(G$3<=$O$2,$D107,$D107-($D107-$I$103)*MIN(G$3-$O$2,$Q$2)/$Q$2)) -> 3766.3135 | H107: =G107*(1+IF(H$3<=$O$2,$D107,$D107-($D107-$I$103)*MIN(H$3-$O$2,$Q$2)/$Q$2)) -> 4001.7081 | I107: =H107*(1+IF(I$3<=$O$2,$D107,$D107-($D107-$I$103)*MIN(I$3-$O$2,$Q$2)/$Q$2)) -> 4251.8148 | J107: =I107*(1+IF(J$3<=$O$2,$D107,$D107-($D107-$I$103)*MIN(J$3-$O$2,$Q$2)/$Q$2)) -> 4488.4708 | K107: =J107*(1+IF(K$3<=$O$2,$D107,$D107-($D107-$I$103)*MIN(K$3-$O$2,$Q$2)/$Q$2)) -> 4707.598 | L107: =K107*(1+IF(L$3<=$O$2,$D107,$D107-($D107-$I$103)*MIN(L$3-$O$2,$Q$2)/$Q$2)) -> 4905.2229 | M107: =L107*(1+IF(M$3<=$O$2,$D107,$D107-($D107-$I$103)*MIN(M$3-$O$2,$Q$2)/$Q$2)) -> 5077.5925 | N107: =M107*(1+IF(N$3<=$O$2,$D107,$D107-($D107-$I$103)*MIN(N$3-$O$2,$Q$2)/$Q$2)) -> 5221.2883 | O107: =SUMPRODUCT(E107:N107,1/(1+$F$103)^$E$3:$N$3)*$E$2 -> 13311.532 | P107: =N107*$E$2*(1+$I$103)/($F$103-$I$103)/(1+$F$103)^$N$3 -> 27921.256 | Q107: =O107+P107 -> 41232.788 | R107: =Q107-$G$2+$I$2 -> 37164.988 | S107: =R107/$K$2 -> 285.53309 | T107: =S107-$M$2 -> 108.90433
A108: 4 | B108: =IF(T107>0,B107,D107) -> -0.125 | C108: =IF(T107>0,D107,C107) -> 0.0625 | D108: =(B108+C108)/2 -> -0.03125 | E108: =$C$2*(1+IF(E$3<=$O$2,$D108,$D108-($D108-$I$103)*MIN(E$3-$O$2,$Q$2)/$Q$2)) -> 3041.875 | F108: =E108*(1+IF(F$3<=$O$2,$D108,$D108-($D108-$I$103)*MIN(F$3-$O$2,$Q$2)/$Q$2)) -> 2946.8164 | G108: =F108*(1+IF(G$3<=$O$2,$D108,$D108-($D108-$I$103)*MIN(G$3-$O$2,$Q$2)/$Q$2)) -> 2854.7284 | H108: =G108*(1+IF(H$3<=$O$2,$D108,$D108-($D108-$I$103)*MIN(H$3-$O$2,$Q$2)/$Q$2)) -> 2765.5181 | I108: =H108*(1+IF(I$3<=$O$2,$D108,$D108-($D108-$I$103)*MIN(I$3-$O$2,$Q$2)/$Q$2)) -> 2679.0957 | J108: =I108*(1+IF(J$3<=$O$2,$D108,$D108-($D108-$I$103)*MIN(J$3-$O$2,$Q$2)/$Q$2)) -> 2627.282 | K108: =J108*(1+IF(K$3<=$O$2,$D108,$D108-($D108-$I$103)*MIN(K$3-$O$2,$Q$2)/$Q$2)) -> 2607.7613 | L108: =K108*(1+IF(L$3<=$O$2,$D108,$D108-($D108-$I$103)*MIN(L$3-$O$2,$Q$2)/$Q$2)) -> 2619.444 | M108: =L108*(1+IF(M$3<=$O$2,$D108,$D108-($D108-$I$103)*MIN(M$3-$O$2,$Q$2)/$Q$2)) -> 2662.3767 | N108: =M108*(1+IF(N$3<=$O$2,$D108,$D108-($D108-$I$103)*MIN(N$3-$O$2,$Q$2)/$Q$2)) -> 2737.722 | O108: =SUMPRODUCT(E108:N108,1/(1+$F$103)^$E$3:$N$3)*$E$2 -> 8790.8057 | P108: =N108*$E$2*(1+$I$103)/($F$103-$I$103)/(1+$F$103)^$N$3 -> 14640.187 | Q108: =O108+P108 -> 23430.992 | R108: =Q108-$G$2+$I$2 -> 19363.192 | S108: =R108/$K$2 -> 148.76454 | T108: =S108-$M$2 -> -27.864227
A109: 5 | B109: =IF(T108>0,B108,D108) -> -0.03125 | C109: =IF(T108>0,D108,C108) -> 0.0625 | D109: =(B109+C109)/2 -> 0.015625 | E109: =$C$2*(1+IF(E$3<=$O$2,$D109,$D109-($D109-$I$103)*MIN(E$3-$O$2,$Q$2)/$Q$2)) -> 3189.0625 | F109: =E109*(1+IF(F$3<=$O$2,$D109,$D109-($D109-$I$103)*MIN(F$3-$O$2,$Q$2)/$Q$2)) -> 3238.8916 | G109: =F109*(1+IF(G$3<=$O$2,$D109,$D109-($D109-$I$103)*MIN(G$3-$O$2,$Q$2)/$Q$2)) -> 3289.4993 | H109: =G109*(1+IF(H$3<=$O$2,$D109,$D109-($D109-$I$103)*MIN(H$3-$O$2,$Q$2)/$Q$2)) -> 3340.8977 | I109: =H109*(1+IF(I$3<=$O$2,$D109,$D109-($D109-$I$103)*MIN(I$3-$O$2,$Q$2)/$Q$2)) -> 3393.0992 | J109: =I109*(1+IF(J$3<=$O$2,$D109,$D109-($D109-$I$103)*MIN(J$3-$O$2,$Q$2)/$Q$2)) -> 3454.7179 | K109: =J109*(1+IF(K$3<=$O$2,$D109,$D109-($D109-$I$103)*MIN(K$3-$O$2,$Q$2)/$Q$2)) -> 3526.2133 | L109: =K109*(1+IF(L$3<=$O$2,$D109,$D109-($D109-$I$103)*MIN(L$3-$O$2,$Q$2)/$Q$2)) -> 3608.1272 | M109: =L109*(1+IF(M$3<=$O$2,$D109,$D109-($D109-$I$103)*MIN(M$3-$O$2,$Q$2)/$Q$2)) -> 3701.0906 | N109: =M109*(1+IF(N$3<=$O$2,$D109,$D109-($D109-$I$103)*MIN(N$3-$O$2,$Q$2)/$Q$2)) -> 3805.8315 | O109: =SUMPRODUCT(E109:N109,1/(1+$F$103)^$E$3:$N$3)*$E$2 -> 10814.35 | P109: =N109*$E$2*(1+$I$103)/($F$103-$I$103)/(1+$F$103)^$N$3 -> 20351.987 | Q109: =O109+P109 -> 31166.337 | R109: =Q109-$G$2+$I$2 -> 27098.537 | S109: =R109/$K$2 -> 208.19405 | T109: =S109-$M$2 -> 31.565282
A110: 6 | B110: =IF(T109>0,B109,D109) -> -0.03125 | C110: =IF(T109>0,D109,C109) -> 0.015625 | D110: =(B110+C110)/2 -> -0.0078125 | E110: =$C$2*(1+IF(E$3<=$O$2,$D110,$D110-($D110-$I$103)*MIN(E$3-$O$2,$Q$2)/$Q$2)) -> 3115.4688 | F110: =E110*(1+IF(F$3<=$O$2,$D110,$D110-($D110-$I$103)*MIN(F$3-$O$2,$Q$2)/$Q$2)) -> 3091.1292 | G110: =F110*(1+IF(G$3<=$O$2,$D110,$D110-($D110-$I$103)*MIN(G$3-$O$2,$Q$2)/$Q$2)) -> 3066.9797 | H110: =G110*(1+IF(H$3<=$O$2,$D110,$D110-($D110-$I$103)*MIN(H$3-$O$2,$Q$2)/$Q$2)) -> 3043.0189 | I110: =H110*(1+IF(I$3<=$O$2,$D110,$D110-($D110-$I$103)*MIN(I$3-$O$2,$Q$2)/$Q$2)) -> 3019.2453 | J110: =I110*(1+IF(J$3<=$O$2,$D110,$D110-($D110-$I$103)*MIN(J$3-$O$2,$Q$2)/$Q$2)) -> 3017.464 | K110: =J110*(1+IF(K$3<=$O$2,$D110,$D110-($D110-$I$103)*MIN(K$3-$O$2,$Q$2)/$Q$2)) -> 3037.4773 | L110: =K110*(1+IF(L$3<=$O$2,$D110,$D110-($D110-$I$103)*MIN(L$3-$O$2,$Q$2)/$Q$2)) -> 3079.5616 | M110: =L110*(1+IF(M$3<=$O$2,$D110,$D110-($D110-$I$103)*MIN(M$3-$O$2,$Q$2)/$Q$2)) -> 3144.471 | N110: =M110*(1+IF(N$3<=$O$2,$D110,$D110-($D110-$I$103)*MIN(N$3-$O$2,$Q$2)/$Q$2)) -> 3233.4596 | O110: =SUMPRODUCT(E110:N110,1/(1+$F$103)^$E$3:$N$3)*$E$2 -> 9749.0905 | P110: =N110*$E$2*(1+$I$103)/($F$103-$I$103)/(1+$F$103)^$N$3 -> 17291.183 | Q110: =O110+P110 -> 27040.273 | R110: =Q110-$G$2+$I$2 -> 22972.473 | S110: =R110/$K$2 -> 176.49411 | T110: =S110-$M$2 -> -0.13465599
A111: 7 | B111: =IF(T110>0,B110,D110) -> -0.0078125 | C111: =IF(T110>0,D110,C110) -> 0.015625 | D111: =(B111+C111)/2 -> 0.00390625 | E111: =$C$2*(1+IF(E$3<=$O$2,$D111,$D111-($D111-$I$103)*MIN(E$3-$O$2,$Q$2)/$Q$2)) -> 3152.2656 | F111: =E111*(1+IF(F$3<=$O$2,$D111,$D111-($D111-$I$103)*MIN(F$3-$O$2,$Q$2)/$Q$2)) -> 3164.5792 | G111: =F111*(1+IF(G$3<=$O$2,$D111,$D111-($D111-$I$103)*MIN(G$3-$O$2,$Q$2)/$Q$2)) -> 3176.9408 | H111: =G111*(1+IF(H$3<=$O$2,$D111,$D111-($D111-$I$103)*MIN(H$3-$O$2,$Q$2)/$Q$2)) -> 3189.3507 | I111: =H111*(1+IF(I$3<=$O$2,$D111,$D111-($D111-$I$103)*MIN(I$3-$O$2,$Q$2)/$Q$2)) -> 3201.8091 | J111: =I111*(1+IF(J$3<=$O$2,$D111,$D111-($D111-$I$103)*MIN(J$3-$O$2,$Q$2)/$Q$2)) -> 3229.937 | K111: =J111*(1+IF(K$3<=$O$2,$D111,$D111-($D111-$I$103)*MIN(K$3-$O$2,$Q$2)/$Q$2)) -> 3274.0701 | L111: =K111*(1+IF(L$3<=$O$2,$D111,$D111-($D111-$I$103)*MIN(L$3-$O$2,$Q$2)/$Q$2)) -> 3334.7795 | M111: =L111*(1+IF(M$3<=$O$2,$D111,$D111-($D111-$I$103)*MIN(M$3-$O$2,$Q$2)/$Q$2)) -> 3412.8842 | N111: =M111*(1+IF(N$3<=$O$2,$D111,$D111-($D111-$I$103)*MIN(N$3-$O$2,$Q$2)/$Q$2)) -> 3509.4688 | O111: =SUMPRODUCT(E111:N111,1/(1+$F$103)^$E$3:$N$3)*$E$2 -> 10267.672 | P111: =N111*$E$2*(1+$I$103)/($F$103-$I$103)/(1+$F$103)^$N$3 -> 18767.164 | Q111: =O111+P111 -> 29034.836 | R111: =Q111-$G$2+$I$2 -> 24967.036 | S111: =R111/$K$2 -> 191.81804 | T111: =S111-$M$2 -> 15.189278
A112: 8 | B112: =IF(T111>0,B111,D111) -> -0.0078125 | C112: =IF(T111>0,D111,C111) -> 0.00390625 | D112: =(B112+C112)/2 -> -0.001953125 | E112: =$C$2*(1+IF(E$3<=$O$2,$D112,$D112-($D112-$I$103)*MIN(E$3-$O$2,$Q$2)/$Q$2)) -> 3133.8672 | F112: =E112*(1+IF(F$3<=$O$2,$D112,$D112-($D112-$I$103)*MIN(F$3-$O$2,$Q$2)/$Q$2)) -> 3127.7464 | G112: =F112*(1+IF(G$3<=$O$2,$D112,$D112-($D112-$I$103)*MIN(G$3-$O$2,$Q$2)/$Q$2)) -> 3121.6375 | H112: =G112*(1+IF(H$3<=$O$2,$D112,$D112-($D112-$I$103)*MIN(H$3-$O$2,$Q$2)/$Q$2)) -> 3115.5405 | I112: =H112*(1+IF(I$3<=$O$2,$D112,$D112-($D112-$I$103)*MIN(I$3-$O$2,$Q$2)/$Q$2)) -> 3109.4555 | J112: =I112*(1+IF(J$3<=$O$2,$D112,$D112-($D112-$I$103)*MIN(J$3-$O$2,$Q$2)/$Q$2)) -> 3122.1965 | K112: =J112*(1+IF(K$3<=$O$2,$D112,$D112-($D112-$I$103)*MIN(K$3-$O$2,$Q$2)/$Q$2)) -> 3153.8809 | L112: =K112*(1+IF(L$3<=$O$2,$D112,$D112-($D112-$I$103)*MIN(L$3-$O$2,$Q$2)/$Q$2)) -> 3204.9698 | M112: =L112*(1+IF(M$3<=$O$2,$D112,$D112-($D112-$I$103)*MIN(M$3-$O$2,$Q$2)/$Q$2)) -> 3276.2784 | N112: =M112*(1+IF(N$3<=$O$2,$D112,$D112-($D112-$I$103)*MIN(N$3-$O$2,$Q$2)/$Q$2)) -> 3368.9971 | O112: =SUMPRODUCT(E112:N112,1/(1+$F$103)^$E$3:$N$3)*$E$2 -> 10004.956 | P112: =N112*$E$2*(1+$I$103)/($F$103-$I$103)/(1+$F$103)^$N$3 -> 18015.981 | Q112: =O112+P112 -> 28020.937 | R112: =Q112-$G$2+$I$2 -> 23953.137 | S112: =R112/$K$2 -> 184.0284 | T112: =S112-$M$2 -> 7.3996361
A113: 9 | B113: =IF(T112>0,B112,D112) -> -0.0078125 | C113: =IF(T112>0,D112,C112) -> -0.001953125 | D113: =(B113+C113)/2 -> -0.0048828125 | E113: =$C$2*(1+IF(E$3<=$O$2,$D113,$D113-($D113-$I$103)*MIN(E$3-$O$2,$Q$2)/$Q$2)) -> 3124.668 | F113: =E113*(1+IF(F$3<=$O$2,$D113,$D113-($D113-$I$103)*MIN(F$3-$O$2,$Q$2)/$Q$2)) -> 3109.4108 | G113: =F113*(1+IF(G$3<=$O$2,$D113,$D113-($D113-$I$103)*MIN(G$3-$O$2,$Q$2)/$Q$2)) -> 3094.2281 | H113: =G113*(1+IF(H$3<=$O$2,$D113,$D113-($D113-$I$103)*MIN(H$3-$O$2,$Q$2)/$Q$2)) -> 3079.1196 | I113: =H113*(1+IF(I$3<=$O$2,$D113,$D113-($D113-$I$103)*MIN(I$3-$O$2,$Q$2)/$Q$2)) -> 3064.0848 | J113: =I113*(1+IF(J$3<=$O$2,$D113,$D113-($D113-$I$103)*MIN(J$3-$O$2,$Q$2)/$Q$2)) -> 3069.4585 | K113: =J113*(1+IF(K$3<=$O$2,$D113,$D113-($D113-$I$103)*MIN(K$3-$O$2,$Q$2)/$Q$2)) -> 3095.2122 | L113: =K113*(1+IF(L$3<=$O$2,$D113,$D113-($D113-$I$103)*MIN(L$3-$O$2,$Q$2)/$Q$2)) -> 3141.7236 | M113: =L113*(1+IF(M$3<=$O$2,$D113,$D113-($D113-$I$103)*MIN(M$3-$O$2,$Q$2)/$Q$2)) -> 3209.7841 | N113: =M113*(1+IF(N$3<=$O$2,$D113,$D113-($D113-$I$103)*MIN(N$3-$O$2,$Q$2)/$Q$2)) -> 3300.621 | O113: =SUMPRODUCT(E113:N113,1/(1+$F$103)^$E$3:$N$3)*$E$2 -> 9876.1777 | P113: =N113*$E$2*(1+$I$103)/($F$103-$I$103)/(1+$F$103)^$N$3 -> 17650.334 | Q113: =O113+P113 -> 27526.511 | R113: =Q113-$G$2+$I$2 -> 23458.711 | S113: =R113/$K$2 -> 180.2298 | T113: =S113-$M$2 -> 3.6010402
A114: 10 | B114: =IF(T113>0,B113,D113) -> -0.0078125 | C114: =IF(T113>0,D113,C113) -> -0.0048828125 | D114: =(B114+C114)/2 -> -0.0063476562 | E114: =$C$2*(1+IF(E$3<=$O$2,$D114,$D114-($D114-$I$103)*MIN(E$3-$O$2,$Q$2)/$Q$2)) -> 3120.0684 | F114: =E114*(1+IF(F$3<=$O$2,$D114,$D114-($D114-$I$103)*MIN(F$3-$O$2,$Q$2)/$Q$2)) -> 3100.2632 | G114: =F114*(1+IF(G$3<=$O$2,$D114,$D114-($D114-$I$103)*MIN(G$3-$O$2,$Q$2)/$Q$2)) -> 3080.5838 | H114: =G114*(1+IF(H$3<=$O$2,$D114,$D114-($D114-$I$103)*MIN(H$3-$O$2,$Q$2)/$Q$2)) -> 3061.0293 | I114: =H114*(1+IF(I$3<=$O$2,$D114,$D114-($D114-$I$103)*MIN(I$3-$O$2,$Q$2)/$Q$2)) -> 3041.599 | J114: =I114*(1+IF(J$3<=$O$2,$D114,$D114-($D114-$I$103)*MIN(J$3-$O$2,$Q$2)/$Q$2)) -> 3043.3688 | K114: =J114*(1+IF(K$3<=$O$2,$D114,$D114-($D114-$I$103)*MIN(K$3-$O$2,$Q$2)/$Q$2)) -> 3066.2288 | L114: =K114*(1+IF(L$3<=$O$2,$D114,$D114-($D114-$I$103)*MIN(L$3-$O$2,$Q$2)/$Q$2)) -> 3110.508 | M114: =L114*(1+IF(M$3<=$O$2,$D114,$D114-($D114-$I$103)*MIN(M$3-$O$2,$Q$2)/$Q$2)) -> 3176.981 | N114: =M114*(1+IF(N$3<=$O$2,$D114,$D114-($D114-$I$103)*MIN(N$3-$O$2,$Q$2)/$Q$2)) -> 3266.8896 | O114: =SUMPRODUCT(E114:N114,1/(1+$F$103)^$E$3:$N$3)*$E$2 -> 9812.424 | P114: =N114*$E$2*(1+$I$103)/($F$103-$I$103)/(1+$F$103)^$N$3 -> 17469.952 | Q114: =O114+P114 -> 27282.376 | R114: =Q114-$G$2+$I$2 -> 23214.576 | S114: =R114/$K$2 -> 178.35415 | T114: =S114-$M$2 -> 1.7253876
A115: 11 | B115: =IF(T114>0,B114,D114) -> -0.0078125 | C115: =IF(T114>0,D114,C114) -> -0.0063476562 | D115: =(B115+C115)/2 -> -0.0070800781 | E115: =$C$2*(1+IF(E$3<=$O$2,$D115,$D115-($D115-$I$103)*MIN(E$3-$O$2,$Q$2)/$Q$2)) -> 3117.7686 | F115: =E115*(1+IF(F$3<=$O$2,$D115,$D115-($D115-$I$103)*MIN(F$3-$O$2,$Q$2)/$Q$2)) -> 3095.6945 | G115: =F115*(1+IF(G$3<=$O$2,$D115,$D115-($D115-$I$103)*MIN(G$3-$O$2,$Q$2)/$Q$2)) -> 3073.7768 | H115: =G115*(1+IF(H$3<=$O$2,$D115,$D115-($D115-$I$103)*MIN(H$3-$O$2,$Q$2)/$Q$2)) -> 3052.0142 | I115: =H115*(1+IF(I$3<=$O$2,$D115,$D115-($D115-$I$103)*MIN(I$3-$O$2,$Q$2)/$Q$2)) -> 3030.4057 | J115: =I115*(1+IF(J$3<=$O$2,$D115,$D115-($D115-$I$103)*MIN(J$3-$O$2,$Q$2)/$Q$2)) -> 3030.3934 | K115: =J115*(1+IF(K$3<=$O$2,$D115,$D115-($D115-$I$103)*MIN(K$3-$O$2,$Q$2)/$Q$2)) -> 3051.8242 | L115: =K115*(1+IF(L$3<=$O$2,$D115,$D115-($D115-$I$103)*MIN(L$3-$O$2,$Q$2)/$Q$2)) -> 3095.0013 | M115: =L115*(1+IF(M$3<=$O$2,$D115,$D115-($D115-$I$103)*MIN(M$3-$O$2,$Q$2)/$Q$2)) -> 3160.6895 | N115: =M115*(1+IF(N$3<=$O$2,$D115,$D115-($D115-$I$103)*MIN(N$3-$O$2,$Q$2)/$Q$2)) -> 3250.137 | O115: =SUMPRODUCT(E115:N115,1/(1+$F$103)^$E$3:$N$3)*$E$2 -> 9780.7049 | P115: =N115*$E$2*(1+$I$103)/($F$103-$I$103)/(1+$F$103)^$N$3 -> 17380.367 | Q115: =O115+P115 -> 27161.072 | R115: =Q115-$G$2+$I$2 -> 23093.272 | S115: =R115/$K$2 -> 177.42219 | T115: =S115-$M$2 -> 0.79342189
A116: 12 | B116: =IF(T115>0,B115,D115) -> -0.0078125 | C116: =IF(T115>0,D115,C115) -> -0.0070800781 | D116: =(B116+C116)/2 -> -0.0074462891 | E116: =$C$2*(1+IF(E$3<=$O$2,$D116,$D116-($D116-$I$103)*MIN(E$3-$O$2,$Q$2)/$Q$2)) -> 3116.6187 | F116: =E116*(1+IF(F$3<=$O$2,$D116,$D116-($D116-$I$103)*MIN(F$3-$O$2,$Q$2)/$Q$2)) -> 3093.4114 | G116: =F116*(1+IF(G$3<=$O$2,$D116,$D116-($D116-$I$103)*MIN(G$3-$O$2,$Q$2)/$Q$2)) -> 3070.377 | H116: =G116*(1+IF(H$3<=$O$2,$D116,$D116-($D116-$I$103)*MIN(H$3-$O$2,$Q$2)/$Q$2)) -> 3047.5141 | I116: =H116*(1+IF(I$3<=$O$2,$D116,$D116-($D116-$I$103)*MIN(I$3-$O$2,$Q$2)/$Q$2)) -> 3024.8214 | J116: =I116*(1+IF(J$3<=$O$2,$D116,$D116-($D116-$I$103)*MIN(J$3-$O$2,$Q$2)/$Q$2)) -> 3023.9229 | K116: =J116*(1+IF(K$3<=$O$2,$D116,$D116-($D116-$I$103)*MIN(K$3-$O$2,$Q$2)/$Q$2)) -> 3044.6435 | L116: =K116*(1+IF(L$3<=$O$2,$D116,$D116-($D116-$I$103)*MIN(L$3-$O$2,$Q$2)/$Q$2)) -> 3087.2731 | M116: =L116*(1+IF(M$3<=$O$2,$D116,$D116-($D116-$I$103)*MIN(M$3-$O$2,$Q$2)/$Q$2)) -> 3152.5712 | N116: =M116*(1+IF(N$3<=$O$2,$D116,$D116-($D116-$I$103)*MIN(N$3-$O$2,$Q$2)/$Q$2)) -> 3241.7889 | O116: =SUMPRODUCT(E116:N116,1/(1+$F$103)^$E$3:$N$3)*$E$2 -> 9764.8846 | P116: =N116*$E$2*(1+$I$103)/($F$103-$I$103)/(1+$F$103)^$N$3 -> 17335.725 | Q116: =O116+P116 -> 27100.609 | R116: =Q116-$G$2+$I$2 -> 23032.809 | S116: =R116/$K$2 -> 176.95766 | T116: =S116-$M$2 -> 0.32889787
A117: 13 | B117: =IF(T116>0,B116,D116) -> -0.0078125 | C117: =IF(T116>0,D116,C116) -> -0.0074462891 | D117: =(B117+C117)/2 -> -0.0076293945 | E117: =$C$2*(1+IF(E$3<=$O$2,$D117,$D117-($D117-$I$103)*MIN(E$3-$O$2,$Q$2)/$Q$2)) -> 3116.0437 | F117: =E117*(1+IF(F$3<=$O$2,$D117,$D117-($D117-$I$103)*MIN(F$3-$O$2,$Q$2)/$Q$2)) -> 3092.2702 | G117: =F117*(1+IF(G$3<=$O$2,$D117,$D117-($D117-$I$103)*MIN(G$3-$O$2,$Q$2)/$Q$2)) -> 3068.678 | H117: =G117*(1+IF(H$3<=$O$2,$D117,$D117-($D117-$I$103)*MIN(H$3-$O$2,$Q$2)/$Q$2)) -> 3045.2659 | I117: =H117*(1+IF(I$3<=$O$2,$D117,$D117-($D117-$I$103)*MIN(I$3-$O$2,$Q$2)/$Q$2)) -> 3022.0323 | J117: =I117*(1+IF(J$3<=$O$2,$D117,$D117-($D117-$I$103)*MIN(J$3-$O$2,$Q$2)/$Q$2)) -> 3020.692 | K117: =J117*(1+IF(K$3<=$O$2,$D117,$D117-($D117-$I$103)*MIN(K$3-$O$2,$Q$2)/$Q$2)) -> 3041.0586 | L117: =K117*(1+IF(L$3<=$O$2,$D117,$D117-($D117-$I$103)*MIN(L$3-$O$2,$Q$2)/$Q$2)) -> 3083.4152 | M117: =L117*(1+IF(M$3<=$O$2,$D117,$D117-($D117-$I$103)*MIN(M$3-$O$2,$Q$2)/$Q$2)) -> 3148.5188 | N117: =M117*(1+IF(N$3<=$O$2,$D117,$D117-($D117-$I$103)*MIN(N$3-$O$2,$Q$2)/$Q$2)) -> 3237.6219 | O117: =SUMPRODUCT(E117:N117,1/(1+$F$103)^$E$3:$N$3)*$E$2 -> 9756.9843 | P117: =N117*$E$2*(1+$I$103)/($F$103-$I$103)/(1+$F$103)^$N$3 -> 17313.441 | Q117: =O117+P117 -> 27070.425 | R117: =Q117-$G$2+$I$2 -> 23002.625 | S117: =R117/$K$2 -> 176.72576 | T117: =S117-$M$2 -> 0.09699978
... A128: 24 | B128: =IF(T127>0,B127,D127) -> -0.0077061057 | C128: =IF(T127>0,D127,C127) -> -0.0077059269 | D128: =(B128+C128)/2 -> -0.0077060163 | E128: =$C$2*(1+IF(E$3<=$O$2,$D128,$D128-($D128-$I$103)*MIN(E$3-$O$2,$Q$2)/$Q$2)) -> 3115.8031 | F128: =E128*(1+IF(F$3<=$O$2,$D128,$D128-($D128-$I$103)*MIN(F$3-$O$2,$Q$2)/$Q$2)) -> 3091.7927 | G128: =F128*(1+IF(G$3<=$O$2,$D128,$D128-($D128-$I$103)*MIN(G$3-$O$2,$Q$2)/$Q$2)) -> 3067.9673 | H128: =G128*(1+IF(H$3<=$O$2,$D128,$D128-($D128-$I$103)*MIN(H$3-$O$2,$Q$2)/$Q$2)) -> 3044.3255 | I128: =H128*(1+IF(I$3<=$O$2,$D128,$D128-($D128-$I$103)*MIN(I$3-$O$2,$Q$2)/$Q$2)) -> 3020.8658 | J128: =I128*(1+IF(J$3<=$O$2,$D128,$D128-($D128-$I$103)*MIN(J$3-$O$2,$Q$2)/$Q$2)) -> 3019.3409 | K128: =J128*(1+IF(K$3<=$O$2,$D128,$D128-($D128-$I$103)*MIN(K$3-$O$2,$Q$2)/$Q$2)) -> 3039.5596 | L128: =K128*(1+IF(L$3<=$O$2,$D128,$D128-($D128-$I$103)*MIN(L$3-$O$2,$Q$2)/$Q$2)) -> 3081.8021 | M128: =L128*(1+IF(M$3<=$O$2,$D128,$D128-($D128-$I$103)*MIN(M$3-$O$2,$Q$2)/$Q$2)) -> 3146.8244 | N128: =M128*(1+IF(N$3<=$O$2,$D128,$D128-($D128-$I$103)*MIN(N$3-$O$2,$Q$2)/$Q$2)) -> 3235.8796 | O128: =SUMPRODUCT(E128:N128,1/(1+$F$103)^$E$3:$N$3)*$E$2 -> 9753.6803 | P128: =N128*$E$2*(1+$I$103)/($F$103-$I$103)/(1+$F$103)^$N$3 -> 17304.124 | Q128: =O128+P128 -> 27057.804 | R128: =Q128-$G$2+$I$2 -> 22990.004 | S128: =R128/$K$2 -> 176.6288 | T128: =S128-$M$2 -> 3.2322733e-05
A130: Grid block 5: row 1, column 4 of table A (24 steps) | E130: WACC | F130: =Sensitivity!$B$10 -> 0.071941394 | G130: Terminal growth | I130: =Sensitivity!$F$9 -> 0.0333
A131: Step | B131: Low | C131: High | D131: Mid | E131: Rev Y1 | F131: Rev Y2 | G131: Rev Y3 | H131: Rev Y4 | I131: Rev Y5 | J131: Rev Y6 | K131: Rev Y7 | L131: Rev Y8 | M131: Rev Y9 | N131: Rev Y10 | O131: PV of FCF | P131: PV of TV | Q131: EV | R131: Equity | S131: Per share | T131: Value - price
A132: 1 | B132: -0.5 | C132: 1 | D132: =(B132+C132)/2 -> 0.25 | E132: =$C$2*(1+IF(E$3<=$O$2,$D132,$D132-($D132-$I$130)*MIN(E$3-$O$2,$Q$2)/$Q$2)) -> 3925 | F132: =E132*(1+IF(F$3<=$O$2,$D132,$D132-($D132-$I$130)*MIN(F$3-$O$2,$Q$2)/$Q$2)) -> 4906.25 | G132: =F132*(1+IF(G$3<=$O$2,$D132,$D132-($D132-$I$130)*MIN(G$3-$O$2,$Q$2)/$Q$2)) -> 6132.8125 | H132: =G132*(1+IF(H$3<=$O$2,$D132,$D132-($D132-$I$130)*MIN(H$3-$O$2,$Q$2)/$Q$2)) -> 7666.0156 | I132: =H132*(1+IF(I$3<=$O$2,$D132,$D132-($D132-$I$130)*MIN(I$3-$O$2,$Q$2)/$Q$2)) -> 9582.5195 | J132: =I132*(1+IF(J$3<=$O$2,$D132,$D132-($D132-$I$130)*MIN(J$3-$O$2,$Q$2)/$Q$2)) -> 11562.843 | K132: =J132*(1+IF(K$3<=$O$2,$D132,$D132-($D132-$I$130)*MIN(K$3-$O$2,$Q$2)/$Q$2)) -> 13451.287 | L132: =K132*(1+IF(L$3<=$O$2,$D132,$D132-($D132-$I$130)*MIN(L$3-$O$2,$Q$2)/$Q$2)) -> 15065.172 | M132: =L132*(1+IF(M$3<=$O$2,$D132,$D132-($D132-$I$130)*MIN(M$3-$O$2,$Q$2)/$Q$2)) -> 16219.767 | N132: =M132*(1+IF(N$3<=$O$2,$D132,$D132-($D132-$I$130)*MIN(N$3-$O$2,$Q$2)/$Q$2)) -> 16759.885 | O132: =SUMPRODUCT(E132:N132,1/(1+$F$130)^$E$3:$N$3)*$E$2 -> 30490.352 | P132: =N132*$E$2*(1+$I$130)/($F$130-$I$130)/(1+$F$130)^$N$3 -> 101714 | Q132: =O132+P132 -> 132204.35 | R132: =Q132-$G$2+$I$2 -> 128136.55 | S132: =R132/$K$2 -> 984.45412 | T132: =S132-$M$2 -> 807.82536
A133: 2 | B133: =IF(T132>0,B132,D132) -> -0.5 | C133: =IF(T132>0,D132,C132) -> 0.25 | D133: =(B133+C133)/2 -> -0.125 | E133: =$C$2*(1+IF(E$3<=$O$2,$D133,$D133-($D133-$I$130)*MIN(E$3-$O$2,$Q$2)/$Q$2)) -> 2747.5 | F133: =E133*(1+IF(F$3<=$O$2,$D133,$D133-($D133-$I$130)*MIN(F$3-$O$2,$Q$2)/$Q$2)) -> 2404.0625 | G133: =F133*(1+IF(G$3<=$O$2,$D133,$D133-($D133-$I$130)*MIN(G$3-$O$2,$Q$2)/$Q$2)) -> 2103.5547 | H133: =G133*(1+IF(H$3<=$O$2,$D133,$D133-($D133-$I$130)*MIN(H$3-$O$2,$Q$2)/$Q$2)) -> 1840.6104 | I133: =H133*(1+IF(I$3<=$O$2,$D133,$D133-($D133-$I$130)*MIN(I$3-$O$2,$Q$2)/$Q$2)) -> 1610.5341 | J133: =I133*(1+IF(J$3<=$O$2,$D133,$D133-($D133-$I$130)*MIN(J$3-$O$2,$Q$2)/$Q$2)) -> 1460.2068 | K133: =J133*(1+IF(K$3<=$O$2,$D133,$D133-($D133-$I$130)*MIN(K$3-$O$2,$Q$2)/$Q$2)) -> 1370.1413 | L133: =K133*(1+IF(L$3<=$O$2,$D133,$D133-($D133-$I$130)*MIN(L$3-$O$2,$Q$2)/$Q$2)) -> 1329.0096 | M133: =L133*(1+IF(M$3<=$O$2,$D133,$D133-($D133-$I$130)*MIN(M$3-$O$2,$Q$2)/$Q$2)) -> 1331.1892 | N133: =M133*(1+IF(N$3<=$O$2,$D133,$D133-($D133-$I$130)*MIN(N$3-$O$2,$Q$2)/$Q$2)) -> 1375.5178 | O133: =SUMPRODUCT(E133:N133,1/(1+$F$130)^$E$3:$N$3)*$E$2 -> 5847.0538 | P133: =N133*$E$2*(1+$I$130)/($F$130-$I$130)/(1+$F$130)^$N$3 -> 8347.8743 | Q133: =O133+P133 -> 14194.928 | R133: =Q133-$G$2+$I$2 -> 10127.128 | S133: =R133/$K$2 -> 77.805225 | T133: =S133-$M$2 -> -98.823539
A134: 3 | B134: =IF(T133>0,B133,D133) -> -0.125 | C134: =IF(T133>0,D133,C133) -> 0.25 | D134: =(B134+C134)/2 -> 0.0625 | E134: =$C$2*(1+IF(E$3<=$O$2,$D134,$D134-($D134-$I$130)*MIN(E$3-$O$2,$Q$2)/$Q$2)) -> 3336.25 | F134: =E134*(1+IF(F$3<=$O$2,$D134,$D134-($D134-$I$130)*MIN(F$3-$O$2,$Q$2)/$Q$2)) -> 3544.7656 | G134: =F134*(1+IF(G$3<=$O$2,$D134,$D134-($D134-$I$130)*MIN(G$3-$O$2,$Q$2)/$Q$2)) -> 3766.3135 | H134: =G134*(1+IF(H$3<=$O$2,$D134,$D134-($D134-$I$130)*MIN(H$3-$O$2,$Q$2)/$Q$2)) -> 4001.7081 | I134: =H134*(1+IF(I$3<=$O$2,$D134,$D134-($D134-$I$130)*MIN(I$3-$O$2,$Q$2)/$Q$2)) -> 4251.8148 | J134: =I134*(1+IF(J$3<=$O$2,$D134,$D134-($D134-$I$130)*MIN(J$3-$O$2,$Q$2)/$Q$2)) -> 4492.7227 | K134: =J134*(1+IF(K$3<=$O$2,$D134,$D134-($D134-$I$130)*MIN(K$3-$O$2,$Q$2)/$Q$2)) -> 4721.0428 | L134: =K134*(1+IF(L$3<=$O$2,$D134,$D134-($D134-$I$130)*MIN(L$3-$O$2,$Q$2)/$Q$2)) -> 4933.3953 | M134: =L134*(1+IF(M$3<=$O$2,$D134,$D134-($D134-$I$130)*MIN(M$3-$O$2,$Q$2)/$Q$2)) -> 5126.4884 | N134: =M134*(1+IF(N$3<=$O$2,$D134,$D134-($D134-$I$130)*MIN(N$3-$O$2,$Q$2)/$Q$2)) -> 5297.2005 | O134: =SUMPRODUCT(E134:N134,1/(1+$F$130)^$E$3:$N$3)*$E$2 -> 13353.035 | P134: =N134*$E$2*(1+$I$130)/($F$130-$I$130)/(1+$F$130)^$N$3 -> 32148.158 | Q134: =O134+P134 -> 45501.194 | R134: =Q134-$G$2+$I$2 -> 41433.394 | S134: =R134/$K$2 -> 318.32663 | T134: =S134-$M$2 -> 141.69786
A135: 4 | B135: =IF(T134>0,B134,D134) -> -0.125 | C135: =IF(T134>0,D134,C134) -> 0.0625 | D135: =(B135+C135)/2 -> -0.03125 | E135: =$C$2*(1+IF(E$3<=$O$2,$D135,$D135-($D135-$I$130)*MIN(E$3-$O$2,$Q$2)/$Q$2)) -> 3041.875 | F135: =E135*(1+IF(F$3<=$O$2,$D135,$D135-($D135-$I$130)*MIN(F$3-$O$2,$Q$2)/$Q$2)) -> 2946.8164 | G135: =F135*(1+IF(G$3<=$O$2,$D135,$D135-($D135-$I$130)*MIN(G$3-$O$2,$Q$2)/$Q$2)) -> 2854.7284 | H135: =G135*(1+IF(H$3<=$O$2,$D135,$D135-($D135-$I$130)*MIN(H$3-$O$2,$Q$2)/$Q$2)) -> 2765.5181 | I135: =H135*(1+IF(I$3<=$O$2,$D135,$D135-($D135-$I$130)*MIN(I$3-$O$2,$Q$2)/$Q$2)) -> 2679.0957 | J135: =I135*(1+IF(J$3<=$O$2,$D135,$D135-($D135-$I$130)*MIN(J$3-$O$2,$Q$2)/$Q$2)) -> 2629.9611 | K135: =J135*(1+IF(K$3<=$O$2,$D135,$D135-($D135-$I$130)*MIN(K$3-$O$2,$Q$2)/$Q$2)) -> 2615.6804 | L135: =K135*(1+IF(L$3<=$O$2,$D135,$D135-($D135-$I$130)*MIN(L$3-$O$2,$Q$2)/$Q$2)) -> 2635.2457 | M135: =L135*(1+IF(M$3<=$O$2,$D135,$D135-($D135-$I$130)*MIN(M$3-$O$2,$Q$2)/$Q$2)) -> 2688.9783 | N135: =M135*(1+IF(N$3<=$O$2,$D135,$D135-($D135-$I$130)*MIN(N$3-$O$2,$Q$2)/$Q$2)) -> 2778.5213 | O135: =SUMPRODUCT(E135:N135,1/(1+$F$130)^$E$3:$N$3)*$E$2 -> 8813.6742 | P135: =N135*$E$2*(1+$I$130)/($F$130-$I$130)/(1+$F$130)^$N$3 -> 16862.557 | Q135: =O135+P135 -> 25676.231 | R135: =Q135-$G$2+$I$2 -> 21608.431 | S135: =R135/$K$2 -> 166.01437 | T135: =S135-$M$2 -> -10.614392
A136: 5 | B136: =IF(T135>0,B135,D135) -> -0.03125 | C136: =IF(T135>0,D135,C135) -> 0.0625 | D136: =(B136+C136)/2 -> 0.015625 | E136: =$C$2*(1+IF(E$3<=$O$2,$D136,$D136-($D136-$I$130)*MIN(E$3-$O$2,$Q$2)/$Q$2)) -> 3189.0625 | F136: =E136*(1+IF(F$3<=$O$2,$D136,$D136-($D136-$I$130)*MIN(F$3-$O$2,$Q$2)/$Q$2)) -> 3238.8916 | G136: =F136*(1+IF(G$3<=$O$2,$D136,$D136-($D136-$I$130)*MIN(G$3-$O$2,$Q$2)/$Q$2)) -> 3289.4993 | H136: =G136*(1+IF(H$3<=$O$2,$D136,$D136-($D136-$I$130)*MIN(H$3-$O$2,$Q$2)/$Q$2)) -> 3340.8977 | I136: =H136*(1+IF(I$3<=$O$2,$D136,$D136-($D136-$I$130)*MIN(I$3-$O$2,$Q$2)/$Q$2)) -> 3393.0992 | J136: =I136*(1+IF(J$3<=$O$2,$D136,$D136-($D136-$I$130)*MIN(J$3-$O$2,$Q$2)/$Q$2)) -> 3458.111 | K136: =J136*(1+IF(K$3<=$O$2,$D136,$D136-($D136-$I$130)*MIN(K$3-$O$2,$Q$2)/$Q$2)) -> 3536.5928 | L136: =K136*(1+IF(L$3<=$O$2,$D136,$D136-($D136-$I$130)*MIN(L$3-$O$2,$Q$2)/$Q$2)) -> 3629.3577 | M136: =L136*(1+IF(M$3<=$O$2,$D136,$D136-($D136-$I$130)*MIN(M$3-$O$2,$Q$2)/$Q$2)) -> 3737.3855 | N136: =M136*(1+IF(N$3<=$O$2,$D136,$D136-($D136-$I$130)*MIN(N$3-$O$2,$Q$2)/$Q$2)) -> 3861.8404 | O136: =SUMPRODUCT(E136:N136,1/(1+$F$130)^$E$3:$N$3)*$E$2 -> 10845.346 | P136: =N136*$E$2*(1+$I$130)/($F$130-$I$130)/(1+$F$130)^$N$3 -> 23437.108 | Q136: =O136+P136 -> 34282.454 | R136: =Q136-$G$2+$I$2 -> 30214.654 | S136: =R136/$K$2 -> 232.13471 | T136: =S136-$M$2 -> 55.505943
A137: 6 | B137: =IF(T136>0,B136,D136) -> -0.03125 | C137: =IF(T136>0,D136,C136) -> 0.015625 | D137: =(B137+C137)/2 -> -0.0078125 | E137: =$C$2*(1+IF(E$3<=$O$2,$D137,$D137-($D137-$I$130)*MIN(E$3-$O$2,$Q$2)/$Q$2)) -> 3115.4688 | F137: =E137*(1+IF(F$3<=$O$2,$D137,$D137-($D137-$I$130)*MIN(F$3-$O$2,$Q$2)/$Q$2)) -> 3091.1292 | G137: =F137*(1+IF(G$3<=$O$2,$D137,$D137-($D137-$I$130)*MIN(G$3-$O$2,$Q$2)/$Q$2)) -> 3066.9797 | H137: =G137*(1+IF(H$3<=$O$2,$D137,$D137-($D137-$I$130)*MIN(H$3-$O$2,$Q$2)/$Q$2)) -> 3043.0189 | I137: =H137*(1+IF(I$3<=$O$2,$D137,$D137-($D137-$I$130)*MIN(I$3-$O$2,$Q$2)/$Q$2)) -> 3019.2453 | J137: =I137*(1+IF(J$3<=$O$2,$D137,$D137-($D137-$I$130)*MIN(J$3-$O$2,$Q$2)/$Q$2)) -> 3020.4832 | K137: =J137*(1+IF(K$3<=$O$2,$D137,$D137-($D137-$I$130)*MIN(K$3-$O$2,$Q$2)/$Q$2)) -> 3046.5576 | L137: =K137*(1+IF(L$3<=$O$2,$D137,$D137-($D137-$I$130)*MIN(L$3-$O$2,$Q$2)/$Q$2)) -> 3097.9073 | M137: =L137*(1+IF(M$3<=$O$2,$D137,$D137-($D137-$I$130)*MIN(M$3-$O$2,$Q$2)/$Q$2)) -> 3175.595 | N137: =M137*(1+IF(N$3<=$O$2,$D137,$D137-($D137-$I$130)*MIN(N$3-$O$2,$Q$2)/$Q$2)) -> 3281.3424 | O137: =SUMPRODUCT(E137:N137,1/(1+$F$130)^$E$3:$N$3)*$E$2 -> 9775.7568 | P137: =N137*$E$2*(1+$I$130)/($F$130-$I$130)/(1+$F$130)^$N$3 -> 19914.125 | Q137: =O137+P137 -> 29689.882 | R137: =Q137-$G$2+$I$2 -> 25622.082 | S137: =R137/$K$2 -> 196.85066 | T137: =S137-$M$2 -> 20.221896
A138: 7 | B138: =IF(T137>0,B137,D137) -> -0.03125 | C138: =IF(T137>0,D137,C137) -> -0.0078125 | D138: =(B138+C138)/2 -> -0.01953125 | E138: =$C$2*(1+IF(E$3<=$O$2,$D138,$D138-($D138-$I$130)*MIN(E$3-$O$2,$Q$2)/$Q$2)) -> 3078.6719 | F138: =E138*(1+IF(F$3<=$O$2,$D138,$D138-($D138-$I$130)*MIN(F$3-$O$2,$Q$2)/$Q$2)) -> 3018.5416 | G138: =F138*(1+IF(G$3<=$O$2,$D138,$D138-($D138-$I$130)*MIN(G$3-$O$2,$Q$2)/$Q$2)) -> 2959.5857 | H138: =G138*(1+IF(H$3<=$O$2,$D138,$D138-($D138-$I$130)*MIN(H$3-$O$2,$Q$2)/$Q$2)) -> 2901.7813 | I138: =H138*(1+IF(I$3<=$O$2,$D138,$D138-($D138-$I$130)*MIN(I$3-$O$2,$Q$2)/$Q$2)) -> 2845.1059 | J138: =I138*(1+IF(J$3<=$O$2,$D138,$D138-($D138-$I$130)*MIN(J$3-$O$2,$Q$2)/$Q$2)) -> 2819.5995 | K138: =J138*(1+IF(K$3<=$O$2,$D138,$D138-($D138-$I$130)*MIN(K$3-$O$2,$Q$2)/$Q$2)) -> 2824.1144 | L138: =K138*(1+IF(L$3<=$O$2,$D138,$D138-($D138-$I$130)*MIN(L$3-$O$2,$Q$2)/$Q$2)) -> 2858.4768 | M138: =L138*(1+IF(M$3<=$O$2,$D138,$D138-($D138-$I$130)*MIN(M$3-$O$2,$Q$2)/$Q$2)) -> 2923.4607 | N138: =M138*(1+IF(N$3<=$O$2,$D138,$D138-($D138-$I$130)*MIN(N$3-$O$2,$Q$2)/$Q$2)) -> 3020.8119 | O138: =SUMPRODUCT(E138:N138,1/(1+$F$130)^$E$3:$N$3)*$E$2 -> 9281.9425 | P138: =N138*$E$2*(1+$I$130)/($F$130-$I$130)/(1+$F$130)^$N$3 -> 18332.993 | Q138: =O138+P138 -> 27614.936 | R138: =Q138-$G$2+$I$2 -> 23547.136 | S138: =R138/$K$2 -> 180.90915 | T138: =S138-$M$2 -> 4.2803897
A139: 8 | B139: =IF(T138>0,B138,D138) -> -0.03125 | C139: =IF(T138>0,D138,C138) -> -0.01953125 | D139: =(B139+C139)/2 -> -0.025390625 | E139: =$C$2*(1+IF(E$3<=$O$2,$D139,$D139-($D139-$I$130)*MIN(E$3-$O$2,$Q$2)/$Q$2)) -> 3060.2734 | F139: =E139*(1+IF(F$3<=$O$2,$D139,$D139-($D139-$I$130)*MIN(F$3-$O$2,$Q$2)/$Q$2)) -> 2982.5712 | G139: =F139*(1+IF(G$3<=$O$2,$D139,$D139-($D139-$I$130)*MIN(G$3-$O$2,$Q$2)/$Q$2)) -> 2906.8418 | H139: =G139*(1+IF(H$3<=$O$2,$D139,$D139-($D139-$I$130)*MIN(H$3-$O$2,$Q$2)/$Q$2)) -> 2833.0353 | I139: =H139*(1+IF(I$3<=$O$2,$D139,$D139-($D139-$I$130)*MIN(I$3-$O$2,$Q$2)/$Q$2)) -> 2761.1028 | J139: =I139*(1+IF(J$3<=$O$2,$D139,$D139-($D139-$I$130)*MIN(J$3-$O$2,$Q$2)/$Q$2)) -> 2723.4068 | K139: =J139*(1+IF(K$3<=$O$2,$D139,$D139-($D139-$I$130)*MIN(K$3-$O$2,$Q$2)/$Q$2)) -> 2718.1932 | L139: =K139*(1+IF(L$3<=$O$2,$D139,$D139-($D139-$I$130)*MIN(L$3-$O$2,$Q$2)/$Q$2)) -> 2744.896 | M139: =L139*(1+IF(M$3<=$O$2,$D139,$D139-($D139-$I$130)*MIN(M$3-$O$2,$Q$2)/$Q$2)) -> 2804.0811 | N139: =M139*(1+IF(N$3<=$O$2,$D139,$D139-($D139-$I$130)*MIN(N$3-$O$2,$Q$2)/$Q$2)) -> 2897.457 | O139: =SUMPRODUCT(E139:N139,1/(1+$F$130)^$E$3:$N$3)*$E$2 -> 9044.6951 | P139: =N139*$E$2*(1+$I$130)/($F$130-$I$130)/(1+$F$130)^$N$3 -> 17584.365 | Q139: =O139+P139 -> 26629.06 | R139: =Q139-$G$2+$I$2 -> 22561.26 | S139: =R139/$K$2 -> 173.33482 | T139: =S139-$M$2 -> -3.2939436
A140: 9 | B140: =IF(T139>0,B139,D139) -> -0.025390625 | C140: =IF(T139>0,D139,C139) -> -0.01953125 | D140: =(B140+C140)/2 -> -0.022460938 | E140: =$C$2*(1+IF(E$3<=$O$2,$D140,$D140-($D140-$I$130)*MIN(E$3-$O$2,$Q$2)/$Q$2)) -> 3069.4727 | F140: =E140*(1+IF(F$3<=$O$2,$D140,$D140-($D140-$I$130)*MIN(F$3-$O$2,$Q$2)/$Q$2)) -> 3000.5294 | G140: =F140*(1+IF(G$3<=$O$2,$D140,$D140-($D140-$I$130)*MIN(G$3-$O$2,$Q$2)/$Q$2)) -> 2933.1347 | H140: =G140*(1+IF(H$3<=$O$2,$D140,$D140-($D140-$I$130)*MIN(H$3-$O$2,$Q$2)/$Q$2)) -> 2867.2538 | I140: =H140*(1+IF(I$3<=$O$2,$D140,$D140-($D140-$I$130)*MIN(I$3-$O$2,$Q$2)/$Q$2)) -> 2802.8526 | J140: =I140*(1+IF(J$3<=$O$2,$D140,$D140-($D140-$I$130)*MIN(J$3-$O$2,$Q$2)/$Q$2)) -> 2771.1558 | K140: =J140*(1+IF(K$3<=$O$2,$D140,$D140-($D140-$I$130)*MIN(K$3-$O$2,$Q$2)/$Q$2)) -> 2770.7219 | L140: =K140*(1+IF(L$3<=$O$2,$D140,$D140-($D140-$I$130)*MIN(L$3-$O$2,$Q$2)/$Q$2)) -> 2801.1878 | M140: =L140*(1+IF(M$3<=$O$2,$D140,$D140-($D140-$I$130)*MIN(M$3-$O$2,$Q$2)/$Q$2)) -> 2863.2279 | N140: =M140*(1+IF(N$3<=$O$2,$D140,$D140-($D140-$I$130)*MIN(N$3-$O$2,$Q$2)/$Q$2)) -> 2958.5734 | O140: =SUMPRODUCT(E140:N140,1/(1+$F$130)^$E$3:$N$3)*$E$2 -> 9162.5306 | P140: =N140*$E$2*(1+$I$130)/($F$130-$I$130)/(1+$F$130)^$N$3 -> 17955.274 | Q140: =O140+P140 -> 27117.805 | R140: =Q140-$G$2+$I$2 -> 23050.005 | S140: =R140/$K$2 -> 177.08977 | T140: =S140-$M$2 -> 0.4610079
A141: 10 | B141: =IF(T140>0,B140,D140) -> -0.025390625 | C141: =IF(T140>0,D140,C140) -> -0.022460938 | D141: =(B141+C141)/2 -> -0.023925781 | E141: =$C$2*(1+IF(E$3<=$O$2,$D141,$D141-($D141-$I$130)*MIN(E$3-$O$2,$Q$2)/$Q$2)) -> 3064.873 | F141: =E141*(1+IF(F$3<=$O$2,$D141,$D141-($D141-$I$130)*MIN(F$3-$O$2,$Q$2)/$Q$2)) -> 2991.5436 | G141: =F141*(1+IF(G$3<=$O$2,$D141,$D141-($D141-$I$130)*MIN(G$3-$O$2,$Q$2)/$Q$2)) -> 2919.9685 | H141: =G141*(1+IF(H$3<=$O$2,$D141,$D141-($D141-$I$130)*MIN(H$3-$O$2,$Q$2)/$Q$2)) -> 2850.106 | I141: =H141*(1+IF(I$3<=$O$2,$D141,$D141-($D141-$I$130)*MIN(I$3-$O$2,$Q$2)/$Q$2)) -> 2781.915 | J141: =I141*(1+IF(J$3<=$O$2,$D141,$D141-($D141-$I$130)*MIN(J$3-$O$2,$Q$2)/$Q$2)) -> 2747.195 | K141: =J141*(1+IF(K$3<=$O$2,$D141,$D141-($D141-$I$130)*MIN(K$3-$O$2,$Q$2)/$Q$2)) -> 2744.3503 | L141: =K141*(1+IF(L$3<=$O$2,$D141,$D141-($D141-$I$130)*MIN(L$3-$O$2,$Q$2)/$Q$2)) -> 2772.9182 | M141: =L141*(1+IF(M$3<=$O$2,$D141,$D141-($D141-$I$130)*MIN(M$3-$O$2,$Q$2)/$Q$2)) -> 2833.5199 | N141: =M141*(1+IF(N$3<=$O$2,$D141,$D141-($D141-$I$130)*MIN(N$3-$O$2,$Q$2)/$Q$2)) -> 2927.8761 | O141: =SUMPRODUCT(E141:N141,1/(1+$F$130)^$E$3:$N$3)*$E$2 -> 9103.4171 | P141: =N141*$E$2*(1+$I$130)/($F$130-$I$130)/(1+$F$130)^$N$3 -> 17768.975 | Q141: =O141+P141 -> 26872.392 | R141: =Q141-$G$2+$I$2 -> 22804.592 | S141: =R141/$K$2 -> 175.2043 | T141: =S141-$M$2 -> -1.4244612
A142: 11 | B142: =IF(T141>0,B141,D141) -> -0.023925781 | C142: =IF(T141>0,D141,C141) -> -0.022460938 | D142: =(B142+C142)/2 -> -0.023193359 | E142: =$C$2*(1+IF(E$3<=$O$2,$D142,$D142-($D142-$I$130)*MIN(E$3-$O$2,$Q$2)/$Q$2)) -> 3067.1729 | F142: =E142*(1+IF(F$3<=$O$2,$D142,$D142-($D142-$I$130)*MIN(F$3-$O$2,$Q$2)/$Q$2)) -> 2996.0348 | G142: =F142*(1+IF(G$3<=$O$2,$D142,$D142-($D142-$I$130)*MIN(G$3-$O$2,$Q$2)/$Q$2)) -> 2926.5467 | H142: =G142*(1+IF(H$3<=$O$2,$D142,$D142-($D142-$I$130)*MIN(H$3-$O$2,$Q$2)/$Q$2)) -> 2858.6702 | I142: =H142*(1+IF(I$3<=$O$2,$D142,$D142-($D142-$I$130)*MIN(I$3-$O$2,$Q$2)/$Q$2)) -> 2792.3681 | J142: =I142*(1+IF(J$3<=$O$2,$D142,$D142-($D142-$I$130)*MIN(J$3-$O$2,$Q$2)/$Q$2)) -> 2759.1537 | K142: =J142*(1+IF(K$3<=$O$2,$D142,$D142-($D142-$I$130)*MIN(K$3-$O$2,$Q$2)/$Q$2)) -> 2757.5092 | L142: =K142*(1+IF(L$3<=$O$2,$D142,$D142-($D142-$I$130)*MIN(L$3-$O$2,$Q$2)/$Q$2)) -> 2787.0219 | M142: =L142*(1+IF(M$3<=$O$2,$D142,$D142-($D142-$I$130)*MIN(M$3-$O$2,$Q$2)/$Q$2)) -> 2848.3401 | N142: =M142*(1+IF(N$3<=$O$2,$D142,$D142-($D142-$I$130)*MIN(N$3-$O$2,$Q$2)/$Q$2)) -> 2943.1898 | O142: =SUMPRODUCT(E142:N142,1/(1+$F$130)^$E$3:$N$3)*$E$2 -> 9132.9247 | P142: =N142*$E$2*(1+$I$130)/($F$130-$I$130)/(1+$F$130)^$N$3 -> 17861.913 | Q142: =O142+P142 -> 26994.837 | R142: =Q142-$G$2+$I$2 -> 22927.037 | S142: =R142/$K$2 -> 176.14503 | T142: =S142-$M$2 -> -0.48373252
A143: 12 | B143: =IF(T142>0,B142,D142) -> -0.023193359 | C143: =IF(T142>0,D142,C142) -> -0.022460938 | D143: =(B143+C143)/2 -> -0.022827148 | E143: =$C$2*(1+IF(E$3<=$O$2,$D143,$D143-($D143-$I$130)*MIN(E$3-$O$2,$Q$2)/$Q$2)) -> 3068.3228 | F143: =E143*(1+IF(F$3<=$O$2,$D143,$D143-($D143-$I$130)*MIN(F$3-$O$2,$Q$2)/$Q$2)) -> 2998.2817 | G143: =F143*(1+IF(G$3<=$O$2,$D143,$D143-($D143-$I$130)*MIN(G$3-$O$2,$Q$2)/$Q$2)) -> 2929.8395 | H143: =G143*(1+IF(H$3<=$O$2,$D143,$D143-($D143-$I$130)*MIN(H$3-$O$2,$Q$2)/$Q$2)) -> 2862.9596 | I143: =H143*(1+IF(I$3<=$O$2,$D143,$D143-($D143-$I$130)*MIN(I$3-$O$2,$Q$2)/$Q$2)) -> 2797.6064 | J143: =I143*(1+IF(J$3<=$O$2,$D143,$D143-($D143-$I$130)*MIN(J$3-$O$2,$Q$2)/$Q$2)) -> 2765.1493 | K143: =J143*(1+IF(K$3<=$O$2,$D143,$D143-($D143-$I$130)*MIN(K$3-$O$2,$Q$2)/$Q$2)) -> 2764.1089 | L143: =K143*(1+IF(L$3<=$O$2,$D143,$D143-($D143-$I$130)*MIN(L$3-$O$2,$Q$2)/$Q$2)) -> 2794.0971 | M143: =L143*(1+IF(M$3<=$O$2,$D143,$D143-($D143-$I$130)*MIN(M$3-$O$2,$Q$2)/$Q$2)) -> 2855.7755 | N143: =M143*(1+IF(N$3<=$O$2,$D143,$D143-($D143-$I$130)*MIN(N$3-$O$2,$Q$2)/$Q$2)) -> 2950.8729 | O143: =SUMPRODUCT(E143:N143,1/(1+$F$130)^$E$3:$N$3)*$E$2 -> 9147.7154 | P143: =N143*$E$2*(1+$I$130)/($F$130-$I$130)/(1+$F$130)^$N$3 -> 17908.54 | Q143: =O143+P143 -> 27056.256 | R143: =Q143-$G$2+$I$2 -> 22988.456 | S143: =R143/$K$2 -> 176.6169 | T143: =S143-$M$2 -> -0.011864722
A144: 13 | B144: =IF(T143>0,B143,D143) -> -0.022827148 | C144: =IF(T143>0,D143,C143) -> -0.022460938 | D144: =(B144+C144)/2 -> -0.022644043 | E144: =$C$2*(1+IF(E$3<=$O$2,$D144,$D144-($D144-$I$130)*MIN(E$3-$O$2,$Q$2)/$Q$2)) -> 3068.8977 | F144: =E144*(1+IF(F$3<=$O$2,$D144,$D144-($D144-$I$130)*MIN(F$3-$O$2,$Q$2)/$Q$2)) -> 2999.4055 | G144: =F144*(1+IF(G$3<=$O$2,$D144,$D144-($D144-$I$130)*MIN(G$3-$O$2,$Q$2)/$Q$2)) -> 2931.4868 | H144: =G144*(1+IF(H$3<=$O$2,$D144,$D144-($D144-$I$130)*MIN(H$3-$O$2,$Q$2)/$Q$2)) -> 2865.1061 | I144: =H144*(1+IF(I$3<=$O$2,$D144,$D144-($D144-$I$130)*MIN(I$3-$O$2,$Q$2)/$Q$2)) -> 2800.2285 | J144: =I144*(1+IF(J$3<=$O$2,$D144,$D144-($D144-$I$130)*MIN(J$3-$O$2,$Q$2)/$Q$2)) -> 2768.1512 | K144: =J144*(1+IF(K$3<=$O$2,$D144,$D144-($D144-$I$130)*MIN(K$3-$O$2,$Q$2)/$Q$2)) -> 2767.4137 | L144: =K144*(1+IF(L$3<=$O$2,$D144,$D144-($D144-$I$130)*MIN(L$3-$O$2,$Q$2)/$Q$2)) -> 2797.6405 | M144: =L144*(1+IF(M$3<=$O$2,$D144,$D144-($D144-$I$130)*MIN(M$3-$O$2,$Q$2)/$Q$2)) -> 2859.4996 | N144: =M144*(1+IF(N$3<=$O$2,$D144,$D144-($D144-$I$130)*MIN(N$3-$O$2,$Q$2)/$Q$2)) -> 2954.721 | O144: =SUMPRODUCT(E144:N144,1/(1+$F$130)^$E$3:$N$3)*$E$2 -> 9155.1199 | P144: =N144*$E$2*(1+$I$130)/($F$130-$I$130)/(1+$F$130)^$N$3 -> 17931.894 | Q144: =O144+P144 -> 27087.014 | R144: =Q144-$G$2+$I$2 -> 23019.214 | S144: =R144/$K$2 -> 176.85321 | T144: =S144-$M$2 -> 0.22444587
... A155: 24 | B155: =IF(T154>0,B154,D154) -> -0.022818029 | C155: =IF(T154>0,D154,C154) -> -0.02281785 | D155: =(B155+C155)/2 -> -0.02281794 | E155: =$C$2*(1+IF(E$3<=$O$2,$D155,$D155-($D155-$I$130)*MIN(E$3-$O$2,$Q$2)/$Q$2)) -> 3068.3517 | F155: =E155*(1+IF(F$3<=$O$2,$D155,$D155-($D155-$I$130)*MIN(F$3-$O$2,$Q$2)/$Q$2)) -> 2998.3382 | G155: =F155*(1+IF(G$3<=$O$2,$D155,$D155-($D155-$I$130)*MIN(G$3-$O$2,$Q$2)/$Q$2)) -> 2929.9223 | H155: =G155*(1+IF(H$3<=$O$2,$D155,$D155-($D155-$I$130)*MIN(H$3-$O$2,$Q$2)/$Q$2)) -> 2863.0675 | I155: =H155*(1+IF(I$3<=$O$2,$D155,$D155-($D155-$I$130)*MIN(I$3-$O$2,$Q$2)/$Q$2)) -> 2797.7382 | J155: =I155*(1+IF(J$3<=$O$2,$D155,$D155-($D155-$I$130)*MIN(J$3-$O$2,$Q$2)/$Q$2)) -> 2765.3003 | K155: =J155*(1+IF(K$3<=$O$2,$D155,$D155-($D155-$I$130)*MIN(K$3-$O$2,$Q$2)/$Q$2)) -> 2764.275 | L155: =K155*(1+IF(L$3<=$O$2,$D155,$D155-($D155-$I$130)*MIN(L$3-$O$2,$Q$2)/$Q$2)) -> 2794.2752 | M155: =L155*(1+IF(M$3<=$O$2,$D155,$D155-($D155-$I$130)*MIN(M$3-$O$2,$Q$2)/$Q$2)) -> 2855.9627 | N155: =M155*(1+IF(N$3<=$O$2,$D155,$D155-($D155-$I$130)*MIN(N$3-$O$2,$Q$2)/$Q$2)) -> 2951.0663 | O155: =SUMPRODUCT(E155:N155,1/(1+$F$130)^$E$3:$N$3)*$E$2 -> 9148.0876 | P155: =N155*$E$2*(1+$I$130)/($F$130-$I$130)/(1+$F$130)^$N$3 -> 17909.714 | Q155: =O155+P155 -> 27057.802 | R155: =Q155-$G$2+$I$2 -> 22990.002 | S155: =R155/$K$2 -> 176.62878 | T155: =S155-$M$2 -> 1.4037738e-05
A157: Grid block 6: row 1, column 5 of table A (24 steps) | E157: WACC | F157: =Sensitivity!$B$10 -> 0.071941394 | G157: Terminal growth | I157: =Sensitivity!$G$9 -> 0.0383
A158: Step | B158: Low | C158: High | D158: Mid | E158: Rev Y1 | F158: Rev Y2 | G158: Rev Y3 | H158: Rev Y4 | I158: Rev Y5 | J158: Rev Y6 | K158: Rev Y7 | L158: Rev Y8 | M158: Rev Y9 | N158: Rev Y10 | O158: PV of FCF | P158: PV of TV | Q158: EV | R158: Equity | S158: Per share | T158: Value - price
A159: 1 | B159: -0.5 | C159: 1 | D159: =(B159+C159)/2 -> 0.25 | E159: =$C$2*(1+IF(E$3<=$O$2,$D159,$D159-($D159-$I$157)*MIN(E$3-$O$2,$Q$2)/$Q$2)) -> 3925 | F159: =E159*(1+IF(F$3<=$O$2,$D159,$D159-($D159-$I$157)*MIN(F$3-$O$2,$Q$2)/$Q$2)) -> 4906.25 | G159: =F159*(1+IF(G$3<=$O$2,$D159,$D159-($D159-$I$157)*MIN(G$3-$O$2,$Q$2)/$Q$2)) -> 6132.8125 | H159: =G159*(1+IF(H$3<=$O$2,$D159,$D159-($D159-$I$157)*MIN(H$3-$O$2,$Q$2)/$Q$2)) -> 7666.0156 | I159: =H159*(1+IF(I$3<=$O$2,$D159,$D159-($D159-$I$157)*MIN(I$3-$O$2,$Q$2)/$Q$2)) -> 9582.5195 | J159: =I159*(1+IF(J$3<=$O$2,$D159,$D159-($D159-$I$157)*MIN(J$3-$O$2,$Q$2)/$Q$2)) -> 11572.426 | K159: =J159*(1+IF(K$3<=$O$2,$D159,$D159-($D159-$I$157)*MIN(K$3-$O$2,$Q$2)/$Q$2)) -> 13485.579 | L159: =K159*(1+IF(L$3<=$O$2,$D159,$D159-($D159-$I$157)*MIN(L$3-$O$2,$Q$2)/$Q$2)) -> 15144.035 | M159: =L159*(1+IF(M$3<=$O$2,$D159,$D159-($D159-$I$157)*MIN(M$3-$O$2,$Q$2)/$Q$2)) -> 16365.25 | N159: =M159*(1+IF(N$3<=$O$2,$D159,$D159-($D159-$I$157)*MIN(N$3-$O$2,$Q$2)/$Q$2)) -> 16992.04 | O159: =SUMPRODUCT(E159:N159,1/(1+$F$157)^$E$3:$N$3)*$E$2 -> 30611.457 | P159: =N159*$E$2*(1+$I$157)/($F$157-$I$157)/(1+$F$157)^$N$3 -> 119022.87 | Q159: =O159+P159 -> 149634.33 | R159: =Q159-$G$2+$I$2 -> 145566.53 | S159: =R159/$K$2 -> 1118.3661 | T159: =S159-$M$2 -> 941.73731
A160: 2 | B160: =IF(T159>0,B159,D159) -> -0.5 | C160: =IF(T159>0,D159,C159) -> 0.25 | D160: =(B160+C160)/2 -> -0.125 | E160: =$C$2*(1+IF(E$3<=$O$2,$D160,$D160-($D160-$I$157)*MIN(E$3-$O$2,$Q$2)/$Q$2)) -> 2747.5 | F160: =E160*(1+IF(F$3<=$O$2,$D160,$D160-($D160-$I$157)*MIN(F$3-$O$2,$Q$2)/$Q$2)) -> 2404.0625 | G160: =F160*(1+IF(G$3<=$O$2,$D160,$D160-($D160-$I$157)*MIN(G$3-$O$2,$Q$2)/$Q$2)) -> 2103.5547 | H160: =G160*(1+IF(H$3<=$O$2,$D160,$D160-($D160-$I$157)*MIN(H$3-$O$2,$Q$2)/$Q$2)) -> 1840.6104 | I160: =H160*(1+IF(I$3<=$O$2,$D160,$D160-($D160-$I$157)*MIN(I$3-$O$2,$Q$2)/$Q$2)) -> 1610.5341 | J160: =I160*(1+IF(J$3<=$O$2,$D160,$D160-($D160-$I$157)*MIN(J$3-$O$2,$Q$2)/$Q$2)) -> 1461.8173 | K160: =J160*(1+IF(K$3<=$O$2,$D160,$D160-($D160-$I$157)*MIN(K$3-$O$2,$Q$2)/$Q$2)) -> 1374.5761 | L160: =K160*(1+IF(L$3<=$O$2,$D160,$D160-($D160-$I$157)*MIN(L$3-$O$2,$Q$2)/$Q$2)) -> 1337.435 | M160: =L160*(1+IF(M$3<=$O$2,$D160,$D160-($D160-$I$157)*MIN(M$3-$O$2,$Q$2)/$Q$2)) -> 1344.9782 | N160: =M160*(1+IF(N$3<=$O$2,$D160,$D160-($D160-$I$157)*MIN(N$3-$O$2,$Q$2)/$Q$2)) -> 1396.4908 | O160: =SUMPRODUCT(E160:N160,1/(1+$F$157)^$E$3:$N$3)*$E$2 -> 5859.0879 | P160: =N160*$E$2*(1+$I$157)/($F$157-$I$157)/(1+$F$157)^$N$3 -> 9781.8952 | Q160: =O160+P160 -> 15640.983 | R160: =Q160-$G$2+$I$2 -> 11573.183 | S160: =R160/$K$2 -> 88.915051 | T160: =S160-$M$2 -> -87.713714
A161: 3 | B161: =IF(T160>0,B160,D160) -> -0.125 | C161: =IF(T160>0,D160,C160) -> 0.25 | D161: =(B161+C161)/2 -> 0.0625 | E161: =$C$2*(1+IF(E$3<=$O$2,$D161,$D161-($D161-$I$157)*MIN(E$3-$O$2,$Q$2)/$Q$2)) -> 3336.25 | F161: =E161*(1+IF(F$3<=$O$2,$D161,$D161-($D161-$I$157)*MIN(F$3-$O$2,$Q$2)/$Q$2)) -> 3544.7656 | G161: =F161*(1+IF(G$3<=$O$2,$D161,$D161-($D161-$I$157)*MIN(G$3-$O$2,$Q$2)/$Q$2)) -> 3766.3135 | H161: =G161*(1+IF(H$3<=$O$2,$D161,$D161-($D161-$I$157)*MIN(H$3-$O$2,$Q$2)/$Q$2)) -> 4001.7081 | I161: =H161*(1+IF(I$3<=$O$2,$D161,$D161-($D161-$I$157)*MIN(I$3-$O$2,$Q$2)/$Q$2)) -> 4251.8148 | J161: =I161*(1+IF(J$3<=$O$2,$D161,$D161-($D161-$I$157)*MIN(J$3-$O$2,$Q$2)/$Q$2)) -> 4496.9745 | K161: =J161*(1+IF(K$3<=$O$2,$D161,$D161-($D161-$I$157)*MIN(K$3-$O$2,$Q$2)/$Q$2)) -> 4734.5047 | L161: =K161*(1+IF(L$3<=$O$2,$D161,$D161-($D161-$I$157)*MIN(L$3-$O$2,$Q$2)/$Q$2)) -> 4961.6662 | M161: =L161*(1+IF(M$3<=$O$2,$D161,$D161-($D161-$I$157)*MIN(M$3-$O$2,$Q$2)/$Q$2)) -> 5175.7125 | N161: =M161*(1+IF(N$3<=$O$2,$D161,$D161-($D161-$I$157)*MIN(N$3-$O$2,$Q$2)/$Q$2)) -> 5373.9423 | O161: =SUMPRODUCT(E161:N161,1/(1+$F$157)^$E$3:$N$3)*$E$2 -> 13394.837 | P161: =N161*$E$2*(1+$I$157)/($F$157-$I$157)/(1+$F$157)^$N$3 -> 37642.452 | Q161: =O161+P161 -> 51037.29 | R161: =Q161-$G$2+$I$2 -> 46969.49 | S161: =R161/$K$2 -> 360.85963 | T161: =S161-$M$2 -> 184.23087
A162: 4 | B162: =IF(T161>0,B161,D161) -> -0.125 | C162: =IF(T161>0,D161,C161) -> 0.0625 | D162: =(B162+C162)/2 -> -0.03125 | E162: =$C$2*(1+IF(E$3<=$O$2,$D162,$D162-($D162-$I$157)*MIN(E$3-$O$2,$Q$2)/$Q$2)) -> 3041.875 | F162: =E162*(1+IF(F$3<=$O$2,$D162,$D162-($D162-$I$157)*MIN(F$3-$O$2,$Q$2)/$Q$2)) -> 2946.8164 | G162: =F162*(1+IF(G$3<=$O$2,$D162,$D162-($D162-$I$157)*MIN(G$3-$O$2,$Q$2)/$Q$2)) -> 2854.7284 | H162: =G162*(1+IF(H$3<=$O$2,$D162,$D162-($D162-$I$157)*MIN(H$3-$O$2,$Q$2)/$Q$2)) -> 2765.5181 | I162: =H162*(1+IF(I$3<=$O$2,$D162,$D162-($D162-$I$157)*MIN(I$3-$O$2,$Q$2)/$Q$2)) -> 2679.0957 | J162: =I162*(1+IF(J$3<=$O$2,$D162,$D162-($D162-$I$157)*MIN(J$3-$O$2,$Q$2)/$Q$2)) -> 2632.6402 | K162: =J162*(1+IF(K$3<=$O$2,$D162,$D162-($D162-$I$157)*MIN(K$3-$O$2,$Q$2)/$Q$2)) -> 2623.6102 | L162: =K162*(1+IF(L$3<=$O$2,$D162,$D162-($D162-$I$157)*MIN(L$3-$O$2,$Q$2)/$Q$2)) -> 2651.1056 | M162: =L162*(1+IF(M$3<=$O$2,$D162,$D162-($D162-$I$157)*MIN(M$3-$O$2,$Q$2)/$Q$2)) -> 2715.7661 | N162: =M162*(1+IF(N$3<=$O$2,$D162,$D162-($D162-$I$157)*MIN(N$3-$O$2,$Q$2)/$Q$2)) -> 2819.78 | O162: =SUMPRODUCT(E162:N162,1/(1+$F$157)^$E$3:$N$3)*$E$2 -> 8836.7104 | P162: =N162*$E$2*(1+$I$157)/($F$157-$I$157)/(1+$F$157)^$N$3 -> 19751.502 | Q162: =O162+P162 -> 28588.213 | R162: =Q162-$G$2+$I$2 -> 24520.413 | S162: =R162/$K$2 -> 188.3867 | T162: =S162-$M$2 -> 11.757934
A163: 5 | B163: =IF(T162>0,B162,D162) -> -0.125 | C163: =IF(T162>0,D162,C162) -> -0.03125 | D163: =(B163+C163)/2 -> -0.078125 | E163: =$C$2*(1+IF(E$3<=$O$2,$D163,$D163-($D163-$I$157)*MIN(E$3-$O$2,$Q$2)/$Q$2)) -> 2894.6875 | F163: =E163*(1+IF(F$3<=$O$2,$D163,$D163-($D163-$I$157)*MIN(F$3-$O$2,$Q$2)/$Q$2)) -> 2668.54 | G163: =F163*(1+IF(G$3<=$O$2,$D163,$D163-($D163-$I$157)*MIN(G$3-$O$2,$Q$2)/$Q$2)) -> 2460.0603 | H163: =G163*(1+IF(H$3<=$O$2,$D163,$D163-($D163-$I$157)*MIN(H$3-$O$2,$Q$2)/$Q$2)) -> 2267.8681 | I163: =H163*(1+IF(I$3<=$O$2,$D163,$D163-($D163-$I$157)*MIN(I$3-$O$2,$Q$2)/$Q$2)) -> 2090.6909 | J163: =I163*(1+IF(J$3<=$O$2,$D163,$D163-($D163-$I$157)*MIN(J$3-$O$2,$Q$2)/$Q$2)) -> 1976.0374 | K163: =J163*(1+IF(K$3<=$O$2,$D163,$D163-($D163-$I$157)*MIN(K$3-$O$2,$Q$2)/$Q$2)) -> 1913.6836 | L163: =K163*(1+IF(L$3<=$O$2,$D163,$D163-($D163-$I$157)*MIN(L$3-$O$2,$Q$2)/$Q$2)) -> 1897.8574 | M163: =L163*(1+IF(M$3<=$O$2,$D163,$D163-($D163-$I$157)*MIN(M$3-$O$2,$Q$2)/$Q$2)) -> 1926.3537 | N163: =M163*(1+IF(N$3<=$O$2,$D163,$D163-($D163-$I$157)*MIN(N$3-$O$2,$Q$2)/$Q$2)) -> 2000.1331 | O163: =SUMPRODUCT(E163:N163,1/(1+$F$157)^$E$3:$N$3)*$E$2 -> 7188.4544 | P163: =N163*$E$2*(1+$I$157)/($F$157-$I$157)/(1+$F$157)^$N$3 -> 14010.183 | Q163: =O163+P163 -> 21198.638 | R163: =Q163-$G$2+$I$2 -> 17130.838 | S163: =R163/$K$2 -> 131.61369 | T163: =S163-$M$2 -> -45.015077
A164: 6 | B164: =IF(T163>0,B163,D163) -> -0.078125 | C164: =IF(T163>0,D163,C163) -> -0.03125 | D164: =(B164+C164)/2 -> -0.0546875 | E164: =$C$2*(1+IF(E$3<=$O$2,$D164,$D164-($D164-$I$157)*MIN(E$3-$O$2,$Q$2)/$Q$2)) -> 2968.2812 | F164: =E164*(1+IF(F$3<=$O$2,$D164,$D164-($D164-$I$157)*MIN(F$3-$O$2,$Q$2)/$Q$2)) -> 2805.9534 | G164: =F164*(1+IF(G$3<=$O$2,$D164,$D164-($D164-$I$157)*MIN(G$3-$O$2,$Q$2)/$Q$2)) -> 2652.5028 | H164: =G164*(1+IF(H$3<=$O$2,$D164,$D164-($D164-$I$157)*MIN(H$3-$O$2,$Q$2)/$Q$2)) -> 2507.444 | I164: =H164*(1+IF(I$3<=$O$2,$D164,$D164-($D164-$I$157)*MIN(I$3-$O$2,$Q$2)/$Q$2)) -> 2370.3182 | J164: =I164*(1+IF(J$3<=$O$2,$D164,$D164-($D164-$I$157)*MIN(J$3-$O$2,$Q$2)/$Q$2)) -> 2284.7734 | K164: =J164*(1+IF(K$3<=$O$2,$D164,$D164-($D164-$I$157)*MIN(K$3-$O$2,$Q$2)/$Q$2)) -> 2244.807 | L164: =K164*(1+IF(L$3<=$O$2,$D164,$D164-($D164-$I$157)*MIN(L$3-$O$2,$Q$2)/$Q$2)) -> 2247.2875 | M164: =L164*(1+IF(M$3<=$O$2,$D164,$D164-($D164-$I$157)*MIN(M$3-$O$2,$Q$2)/$Q$2)) -> 2291.5647 | N164: =M164*(1+IF(N$3<=$O$2,$D164,$D164-($D164-$I$157)*MIN(N$3-$O$2,$Q$2)/$Q$2)) -> 2379.3316 | O164: =SUMPRODUCT(E164:N164,1/(1+$F$157)^$E$3:$N$3)*$E$2 -> 7968.4834 | P164: =N164*$E$2*(1+$I$157)/($F$157-$I$157)/(1+$F$157)^$N$3 -> 16666.327 | Q164: =O164+P164 -> 24634.81 | R164: =Q164-$G$2+$I$2 -> 20567.01 | S164: =R164/$K$2 -> 158.01329 | T164: =S164-$M$2 -> -18.615472
A165: 7 | B165: =IF(T164>0,B164,D164) -> -0.0546875 | C165: =IF(T164>0,D164,C164) -> -0.03125 | D165: =(B165+C165)/2 -> -0.04296875 | E165: =$C$2*(1+IF(E$3<=$O$2,$D165,$D165-($D165-$I$157)*MIN(E$3-$O$2,$Q$2)/$Q$2)) -> 3005.0781 | F165: =E165*(1+IF(F$3<=$O$2,$D165,$D165-($D165-$I$157)*MIN(F$3-$O$2,$Q$2)/$Q$2)) -> 2875.9537 | G165: =F165*(1+IF(G$3<=$O$2,$D165,$D165-($D165-$I$157)*MIN(G$3-$O$2,$Q$2)/$Q$2)) -> 2752.3775 | H165: =G165*(1+IF(H$3<=$O$2,$D165,$D165-($D165-$I$157)*MIN(H$3-$O$2,$Q$2)/$Q$2)) -> 2634.1113 | I165: =H165*(1+IF(I$3<=$O$2,$D165,$D165-($D165-$I$157)*MIN(I$3-$O$2,$Q$2)/$Q$2)) -> 2520.9268 | J165: =I165*(1+IF(J$3<=$O$2,$D165,$D165-($D165-$I$157)*MIN(J$3-$O$2,$Q$2)/$Q$2)) -> 2453.5803 | K165: =J165*(1+IF(K$3<=$O$2,$D165,$D165-($D165-$I$157)*MIN(K$3-$O$2,$Q$2)/$Q$2)) -> 2427.9128 | L165: =K165*(1+IF(L$3<=$O$2,$D165,$D165-($D165-$I$157)*MIN(L$3-$O$2,$Q$2)/$Q$2)) -> 2441.9765 | M165: =L165*(1+IF(M$3<=$O$2,$D165,$D165-($D165-$I$157)*MIN(M$3-$O$2,$Q$2)/$Q$2)) -> 2495.8129 | N165: =M165*(1+IF(N$3<=$O$2,$D165,$D165-($D165-$I$157)*MIN(N$3-$O$2,$Q$2)/$Q$2)) -> 2591.4025 | O165: =SUMPRODUCT(E165:N165,1/(1+$F$157)^$E$3:$N$3)*$E$2 -> 8390.9993 | P165: =N165*$E$2*(1+$I$157)/($F$157-$I$157)/(1+$F$157)^$N$3 -> 18151.804 | Q165: =O165+P165 -> 26542.803 | R165: =Q165-$G$2+$I$2 -> 22475.003 | S165: =R165/$K$2 -> 172.67212 | T165: =S165-$M$2 -> -3.9566443
A166: 8 | B166: =IF(T165>0,B165,D165) -> -0.04296875 | C166: =IF(T165>0,D165,C165) -> -0.03125 | D166: =(B166+C166)/2 -> -0.037109375 | E166: =$C$2*(1+IF(E$3<=$O$2,$D166,$D166-($D166-$I$157)*MIN(E$3-$O$2,$Q$2)/$Q$2)) -> 3023.4766 | F166: =E166*(1+IF(F$3<=$O$2,$D166,$D166-($D166-$I$157)*MIN(F$3-$O$2,$Q$2)/$Q$2)) -> 2911.2772 | G166: =F166*(1+IF(G$3<=$O$2,$D166,$D166-($D166-$I$157)*MIN(G$3-$O$2,$Q$2)/$Q$2)) -> 2803.2416 | H166: =G166*(1+IF(H$3<=$O$2,$D166,$D166-($D166-$I$157)*MIN(H$3-$O$2,$Q$2)/$Q$2)) -> 2699.215 | I166: =H166*(1+IF(I$3<=$O$2,$D166,$D166-($D166-$I$157)*MIN(I$3-$O$2,$Q$2)/$Q$2)) -> 2599.0488 | J166: =I166*(1+IF(J$3<=$O$2,$D166,$D166-($D166-$I$157)*MIN(J$3-$O$2,$Q$2)/$Q$2)) -> 2541.7983 | K166: =J166*(1+IF(K$3<=$O$2,$D166,$D166-($D166-$I$157)*MIN(K$3-$O$2,$Q$2)/$Q$2)) -> 2524.1439 | L166: =K166*(1+IF(L$3<=$O$2,$D166,$D166-($D166-$I$157)*MIN(L$3-$O$2,$Q$2)/$Q$2)) -> 2544.681 | M166: =L166*(1+IF(M$3<=$O$2,$D166,$D166-($D166-$I$157)*MIN(M$3-$O$2,$Q$2)/$Q$2)) -> 2603.7637 | N166: =M166*(1+IF(N$3<=$O$2,$D166,$D166-($D166-$I$157)*MIN(N$3-$O$2,$Q$2)/$Q$2)) -> 2703.4878 | O166: =SUMPRODUCT(E166:N166,1/(1+$F$157)^$E$3:$N$3)*$E$2 -> 8610.8811 | P166: =N166*$E$2*(1+$I$157)/($F$157-$I$157)/(1+$F$157)^$N$3 -> 18936.92 | Q166: =O166+P166 -> 27547.801 | R166: =Q166-$G$2+$I$2 -> 23480.001 | S166: =R166/$K$2 -> 180.39337 | T166: =S166-$M$2 -> 3.7646025
A167: 9 | B167: =IF(T166>0,B166,D166) -> -0.04296875 | C167: =IF(T166>0,D166,C166) -> -0.037109375 | D167: =(B167+C167)/2 -> -0.040039062 | E167: =$C$2*(1+IF(E$3<=$O$2,$D167,$D167-($D167-$I$157)*MIN(E$3-$O$2,$Q$2)/$Q$2)) -> 3014.2773 | F167: =E167*(1+IF(F$3<=$O$2,$D167,$D167-($D167-$I$157)*MIN(F$3-$O$2,$Q$2)/$Q$2)) -> 2893.5885 | G167: =F167*(1+IF(G$3<=$O$2,$D167,$D167-($D167-$I$157)*MIN(G$3-$O$2,$Q$2)/$Q$2)) -> 2777.7319 | H167: =G167*(1+IF(H$3<=$O$2,$D167,$D167-($D167-$I$157)*MIN(H$3-$O$2,$Q$2)/$Q$2)) -> 2666.5142 | I167: =H167*(1+IF(I$3<=$O$2,$D167,$D167-($D167-$I$157)*MIN(I$3-$O$2,$Q$2)/$Q$2)) -> 2559.7494 | J167: =I167*(1+IF(J$3<=$O$2,$D167,$D167-($D167-$I$157)*MIN(J$3-$O$2,$Q$2)/$Q$2)) -> 2497.3651 | K167: =J167*(1+IF(K$3<=$O$2,$D167,$D167-($D167-$I$157)*MIN(K$3-$O$2,$Q$2)/$Q$2)) -> 2475.6295 | L167: =K167*(1+IF(L$3<=$O$2,$D167,$D167-($D167-$I$157)*MIN(L$3-$O$2,$Q$2)/$Q$2)) -> 2492.8707 | M167: =L167*(1+IF(M$3<=$O$2,$D167,$D167-($D167-$I$157)*MIN(M$3-$O$2,$Q$2)/$Q$2)) -> 2549.2898 | N167: =M167*(1+IF(N$3<=$O$2,$D167,$D167-($D167-$I$157)*MIN(N$3-$O$2,$Q$2)/$Q$2)) -> 2646.9276 | O167: =SUMPRODUCT(E167:N167,1/(1+$F$157)^$E$3:$N$3)*$E$2 -> 8500.2062 | P167: =N167*$E$2*(1+$I$157)/($F$157-$I$157)/(1+$F$157)^$N$3 -> 18540.736 | Q167: =O167+P167 -> 27040.942 | R167: =Q167-$G$2+$I$2 -> 22973.142 | S167: =R167/$K$2 -> 176.49925 | T167: =S167-$M$2 -> -0.12951406
A168: 10 | B168: =IF(T167>0,B167,D167) -> -0.040039062 | C168: =IF(T167>0,D167,C167) -> -0.037109375 | D168: =(B168+C168)/2 -> -0.038574219 | E168: =$C$2*(1+IF(E$3<=$O$2,$D168,$D168-($D168-$I$157)*MIN(E$3-$O$2,$Q$2)/$Q$2)) -> 3018.877 | F168: =E168*(1+IF(F$3<=$O$2,$D168,$D168-($D168-$I$157)*MIN(F$3-$O$2,$Q$2)/$Q$2)) -> 2902.4261 | G168: =F168*(1+IF(G$3<=$O$2,$D168,$D168-($D168-$I$157)*MIN(G$3-$O$2,$Q$2)/$Q$2)) -> 2790.4673 | H168: =G168*(1+IF(H$3<=$O$2,$D168,$D168-($D168-$I$157)*MIN(H$3-$O$2,$Q$2)/$Q$2)) -> 2682.8272 | I168: =H168*(1+IF(I$3<=$O$2,$D168,$D168-($D168-$I$157)*MIN(I$3-$O$2,$Q$2)/$Q$2)) -> 2579.3393 | J168: =I168*(1+IF(J$3<=$O$2,$D168,$D168-($D168-$I$157)*MIN(J$3-$O$2,$Q$2)/$Q$2)) -> 2519.5002 | K168: =J168*(1+IF(K$3<=$O$2,$D168,$D168-($D168-$I$157)*MIN(K$3-$O$2,$Q$2)/$Q$2)) -> 2499.7863 | L168: =K168*(1+IF(L$3<=$O$2,$D168,$D168-($D168-$I$157)*MIN(L$3-$O$2,$Q$2)/$Q$2)) -> 2518.6605 | M168: =L168*(1+IF(M$3<=$O$2,$D168,$D168-($D168-$I$157)*MIN(M$3-$O$2,$Q$2)/$Q$2)) -> 2576.4011 | N168: =M168*(1+IF(N$3<=$O$2,$D168,$D168-($D168-$I$157)*MIN(N$3-$O$2,$Q$2)/$Q$2)) -> 2675.0773 | O168: =SUMPRODUCT(E168:N168,1/(1+$F$157)^$E$3:$N$3)*$E$2 -> 8555.3589 | P168: =N168*$E$2*(1+$I$157)/($F$157-$I$157)/(1+$F$157)^$N$3 -> 18737.914 | Q168: =O168+P168 -> 27293.273 | R168: =Q168-$G$2+$I$2 -> 23225.473 | S168: =R168/$K$2 -> 178.43787 | T168: =S168-$M$2 -> 1.8091068
A169: 11 | B169: =IF(T168>0,B168,D168) -> -0.040039062 | C169: =IF(T168>0,D168,C168) -> -0.038574219 | D169: =(B169+C169)/2 -> -0.039306641 | E169: =$C$2*(1+IF(E$3<=$O$2,$D169,$D169-($D169-$I$157)*MIN(E$3-$O$2,$Q$2)/$Q$2)) -> 3016.5771 | F169: =E169*(1+IF(F$3<=$O$2,$D169,$D169-($D169-$I$157)*MIN(F$3-$O$2,$Q$2)/$Q$2)) -> 2898.0056 | G169: =F169*(1+IF(G$3<=$O$2,$D169,$D169-($D169-$I$157)*MIN(G$3-$O$2,$Q$2)/$Q$2)) -> 2784.0948 | H169: =G169*(1+IF(H$3<=$O$2,$D169,$D169-($D169-$I$157)*MIN(H$3-$O$2,$Q$2)/$Q$2)) -> 2674.6614 | I169: =H169*(1+IF(I$3<=$O$2,$D169,$D169-($D169-$I$157)*MIN(I$3-$O$2,$Q$2)/$Q$2)) -> 2569.5294 | J169: =I169*(1+IF(J$3<=$O$2,$D169,$D169-($D169-$I$157)*MIN(J$3-$O$2,$Q$2)/$Q$2)) -> 2508.4123 | K169: =J169*(1+IF(K$3<=$O$2,$D169,$D169-($D169-$I$157)*MIN(K$3-$O$2,$Q$2)/$Q$2)) -> 2487.6829 | L169: =K169*(1+IF(L$3<=$O$2,$D169,$D169-($D169-$I$157)*MIN(L$3-$O$2,$Q$2)/$Q$2)) -> 2505.7368 | M169: =L169*(1+IF(M$3<=$O$2,$D169,$D169-($D169-$I$157)*MIN(M$3-$O$2,$Q$2)/$Q$2)) -> 2562.8142 | N169: =M169*(1+IF(N$3<=$O$2,$D169,$D169-($D169-$I$157)*MIN(N$3-$O$2,$Q$2)/$Q$2)) -> 2660.97 | O169: =SUMPRODUCT(E169:N169,1/(1+$F$157)^$E$3:$N$3)*$E$2 -> 8527.7365 | P169: =N169*$E$2*(1+$I$157)/($F$157-$I$157)/(1+$F$157)^$N$3 -> 18639.098 | Q169: =O169+P169 -> 27166.834 | R169: =Q169-$G$2+$I$2 -> 23099.034 | S169: =R169/$K$2 -> 177.46646 | T169: =S169-$M$2 -> 0.83769504
A170: 12 | B170: =IF(T169>0,B169,D169) -> -0.040039062 | C170: =IF(T169>0,D169,C169) -> -0.039306641 | D170: =(B170+C170)/2 -> -0.039672852 | E170: =$C$2*(1+IF(E$3<=$O$2,$D170,$D170-($D170-$I$157)*MIN(E$3-$O$2,$Q$2)/$Q$2)) -> 3015.4272 | F170: =E170*(1+IF(F$3<=$O$2,$D170,$D170-($D170-$I$157)*MIN(F$3-$O$2,$Q$2)/$Q$2)) -> 2895.7966 | G170: =F170*(1+IF(G$3<=$O$2,$D170,$D170-($D170-$I$157)*MIN(G$3-$O$2,$Q$2)/$Q$2)) -> 2780.9121 | H170: =G170*(1+IF(H$3<=$O$2,$D170,$D170-($D170-$I$157)*MIN(H$3-$O$2,$Q$2)/$Q$2)) -> 2670.5854 | I170: =H170*(1+IF(I$3<=$O$2,$D170,$D170-($D170-$I$157)*MIN(I$3-$O$2,$Q$2)/$Q$2)) -> 2564.6357 | J170: =I170*(1+IF(J$3<=$O$2,$D170,$D170-($D170-$I$157)*MIN(J$3-$O$2,$Q$2)/$Q$2)) -> 2502.8837 | K170: =J170*(1+IF(K$3<=$O$2,$D170,$D170-($D170-$I$157)*MIN(K$3-$O$2,$Q$2)/$Q$2)) -> 2481.6499 | L170: =K170*(1+IF(L$3<=$O$2,$D170,$D170-($D170-$I$157)*MIN(L$3-$O$2,$Q$2)/$Q$2)) -> 2499.2966 | M170: =L170*(1+IF(M$3<=$O$2,$D170,$D170-($D170-$I$157)*MIN(M$3-$O$2,$Q$2)/$Q$2)) -> 2556.0442 | N170: =M170*(1+IF(N$3<=$O$2,$D170,$D170-($D170-$I$157)*MIN(N$3-$O$2,$Q$2)/$Q$2)) -> 2653.9407 | O170: =SUMPRODUCT(E170:N170,1/(1+$F$157)^$E$3:$N$3)*$E$2 -> 8513.9599 | P170: =N170*$E$2*(1+$I$157)/($F$157-$I$157)/(1+$F$157)^$N$3 -> 18589.86 | Q170: =O170+P170 -> 27103.82 | R170: =Q170-$G$2+$I$2 -> 23036.02 | S170: =R170/$K$2 -> 176.98233 | T170: =S170-$M$2 -> 0.35356616
A171: 13 | B171: =IF(T170>0,B170,D170) -> -0.040039062 | C171: =IF(T170>0,D170,C170) -> -0.039672852 | D171: =(B171+C171)/2 -> -0.039855957 | E171: =$C$2*(1+IF(E$3<=$O$2,$D171,$D171-($D171-$I$157)*MIN(E$3-$O$2,$Q$2)/$Q$2)) -> 3014.8523 | F171: =E171*(1+IF(F$3<=$O$2,$D171,$D171-($D171-$I$157)*MIN(F$3-$O$2,$Q$2)/$Q$2)) -> 2894.6925 | G171: =F171*(1+IF(G$3<=$O$2,$D171,$D171-($D171-$I$157)*MIN(G$3-$O$2,$Q$2)/$Q$2)) -> 2779.3217 | H171: =G171*(1+IF(H$3<=$O$2,$D171,$D171-($D171-$I$157)*MIN(H$3-$O$2,$Q$2)/$Q$2)) -> 2668.5492 | I171: =H171*(1+IF(I$3<=$O$2,$D171,$D171-($D171-$I$157)*MIN(I$3-$O$2,$Q$2)/$Q$2)) -> 2562.1916 | J171: =I171*(1+IF(J$3<=$O$2,$D171,$D171-($D171-$I$157)*MIN(J$3-$O$2,$Q$2)/$Q$2)) -> 2500.1231 | K171: =J171*(1+IF(K$3<=$O$2,$D171,$D171-($D171-$I$157)*MIN(K$3-$O$2,$Q$2)/$Q$2)) -> 2478.6381 | L171: =K171*(1+IF(L$3<=$O$2,$D171,$D171-($D171-$I$157)*MIN(L$3-$O$2,$Q$2)/$Q$2)) -> 2496.0818 | M171: =L171*(1+IF(M$3<=$O$2,$D171,$D171-($D171-$I$157)*MIN(M$3-$O$2,$Q$2)/$Q$2)) -> 2552.665 | N171: =M171*(1+IF(N$3<=$O$2,$D171,$D171-($D171-$I$157)*MIN(N$3-$O$2,$Q$2)/$Q$2)) -> 2650.4321 | O171: =SUMPRODUCT(E171:N171,1/(1+$F$157)^$E$3:$N$3)*$E$2 -> 8507.0802 | P171: =N171*$E$2*(1+$I$157)/($F$157-$I$157)/(1+$F$157)^$N$3 -> 18565.284 | Q171: =O171+P171 -> 27072.364 | R171: =Q171-$G$2+$I$2 -> 23004.564 | S171: =R171/$K$2 -> 176.74066 | T171: =S171-$M$2 -> 0.11189509
... A182: 24 | B182: =IF(T181>0,B181,D181) -> -0.039940894 | C182: =IF(T181>0,D181,C181) -> -0.039940715 | D182: =(B182+C182)/2 -> -0.039940804 | E182: =$C$2*(1+IF(E$3<=$O$2,$D182,$D182-($D182-$I$157)*MIN(E$3-$O$2,$Q$2)/$Q$2)) -> 3014.5859 | F182: =E182*(1+IF(F$3<=$O$2,$D182,$D182-($D182-$I$157)*MIN(F$3-$O$2,$Q$2)/$Q$2)) -> 2894.1809 | G182: =F182*(1+IF(G$3<=$O$2,$D182,$D182-($D182-$I$157)*MIN(G$3-$O$2,$Q$2)/$Q$2)) -> 2778.585 | H182: =G182*(1+IF(H$3<=$O$2,$D182,$D182-($D182-$I$157)*MIN(H$3-$O$2,$Q$2)/$Q$2)) -> 2667.6061 | I182: =H182*(1+IF(I$3<=$O$2,$D182,$D182-($D182-$I$157)*MIN(I$3-$O$2,$Q$2)/$Q$2)) -> 2561.0597 | J182: =I182*(1+IF(J$3<=$O$2,$D182,$D182-($D182-$I$157)*MIN(J$3-$O$2,$Q$2)/$Q$2)) -> 2498.8448 | K182: =J182*(1+IF(K$3<=$O$2,$D182,$D182-($D182-$I$157)*MIN(K$3-$O$2,$Q$2)/$Q$2)) -> 2477.2436 | L182: =K182*(1+IF(L$3<=$O$2,$D182,$D182-($D182-$I$157)*MIN(L$3-$O$2,$Q$2)/$Q$2)) -> 2494.5934 | M182: =L182*(1+IF(M$3<=$O$2,$D182,$D182-($D182-$I$157)*MIN(M$3-$O$2,$Q$2)/$Q$2)) -> 2551.1005 | N182: =M182*(1+IF(N$3<=$O$2,$D182,$D182-($D182-$I$157)*MIN(N$3-$O$2,$Q$2)/$Q$2)) -> 2648.8077 | O182: =SUMPRODUCT(E182:N182,1/(1+$F$157)^$E$3:$N$3)*$E$2 -> 8503.8942 | P182: =N182*$E$2*(1+$I$157)/($F$157-$I$157)/(1+$F$157)^$N$3 -> 18553.906 | Q182: =O182+P182 -> 27057.8 | R182: =Q182-$G$2+$I$2 -> 22990 | S182: =R182/$K$2 -> 176.62876 | T182: =S182-$M$2 -> -1.3661323e-06
...

Sheet DCF
B2: Verisk (VRSK): discounted cash flow
B3: Panel A runs the model at the solved growth rate, so it should land on the price. Panel B runs it at your view.
B5: A. At the solved (implied) growth rate
B6: Year | C6: 1 | D6: 2 | E6: 3 | F6: 4 | G6: 5 | H6: 6 | I6: 7 | J6: 8 | K6: 9 | L6: 10
B7: Revenue growth | C7: =IF(C$6<=Inputs!$C$46,Solver!$W$7,Solver!$W$7-(Solver!$W$7-Inputs!$C$37)*MIN(C$6-Inputs!$C$46,Inputs!$C$47)/Inputs!$C$47) -> 0.02636698 | D7: =IF(D$6<=Inputs!$C$46,Solver!$W$7,Solver!$W$7-(Solver!$W$7-Inputs!$C$37)*MIN(D$6-Inputs!$C$46,Inputs!$C$47)/Inputs!$C$47) -> 0.02636698 | E7: =IF(E$6<=Inputs!$C$46,Solver!$W$7,Solver!$W$7-(Solver!$W$7-Inputs!$C$37)*MIN(E$6-Inputs!$C$46,Inputs!$C$47)/Inputs!$C$47) -> 0.02636698 | F7: =IF(F$6<=Inputs!$C$46,Solver!$W$7,Solver!$W$7-(Solver!$W$7-Inputs!$C$37)*MIN(F$6-Inputs!$C$46,Inputs!$C$47)/Inputs!$C$47) -> 0.02636698 | G7: =IF(G$6<=Inputs!$C$46,Solver!$W$7,Solver!$W$7-(Solver!$W$7-Inputs!$C$37)*MIN(G$6-Inputs!$C$46,Inputs!$C$47)/Inputs!$C$47) -> 0.02636698 | H7: =IF(H$6<=Inputs!$C$46,Solver!$W$7,Solver!$W$7-(Solver!$W$7-Inputs!$C$37)*MIN(H$6-Inputs!$C$46,Inputs!$C$47)/Inputs!$C$47) -> 0.026753584 | I7: =IF(I$6<=Inputs!$C$46,Solver!$W$7,Solver!$W$7-(Solver!$W$7-Inputs!$C$37)*MIN(I$6-Inputs!$C$46,Inputs!$C$47)/Inputs!$C$47) -> 0.027140188 | J7: =IF(J$6<=Inputs!$C$46,Solver!$W$7,Solver!$W$7-(Solver!$W$7-Inputs!$C$37)*MIN(J$6-Inputs!$C$46,Inputs!$C$47)/Inputs!$C$47) -> 0.027526792 | ... L7: =IF(L$6<=Inputs!$C$46,Solver!$W$7,Solver!$W$7-(Solver!$W$7-Inputs!$C$37)*MIN(L$6-Inputs!$C$46,Inputs!$C$47)/Inputs!$C$47) -> 0.0283
B8: Revenue ($mm) | C8: =Inputs!$C$12*(1+C7) -> 3222.7923 | D8: =C8*(1+D7) -> 3307.7676 | E8: =D8*(1+E7) -> 3394.9835 | F8: =E8*(1+F7) -> 3484.4989 | G8: =F8*(1+G7) -> 3576.3746 | H8: =G8*(1+H7) -> 3672.0555 | I8: =H8*(1+I7) -> 3771.7157 | J8: =I8*(1+J7) -> 3875.539 | K8: =J8*(1+K7) -> 3983.7184 | L8: =K8*(1+L7) -> 4096.4577
B9: Unlevered free cash flow ($mm) | C9: =C8*Inputs!$C$23 -> 1465.1389 | D9: =D8*Inputs!$C$23 -> 1503.7702 | E9: =E8*Inputs!$C$23 -> 1543.42 | F9: =F8*Inputs!$C$23 -> 1584.1154 | G9: =G8*Inputs!$C$23 -> 1625.8837 | H9: =H8*Inputs!$C$23 -> 1669.3819 | I9: =I8*Inputs!$C$23 -> 1714.6892 | J9: =J8*Inputs!$C$23 -> 1761.8891 | ... L9: =L8*Inputs!$C$23 -> 1862.3227
B10: Discount factor | C10: =1/(1+WACC!$C$35)^C$6 -> 0.92426448 | D10: =1/(1+WACC!$C$35)^D$6 -> 0.85426483 | E10: =1/(1+WACC!$C$35)^E$6 -> 0.78956664 | F10: =1/(1+WACC!$C$35)^F$6 -> 0.7297684 | G10: =1/(1+WACC!$C$35)^G$6 -> 0.67449901 | H10: =1/(1+WACC!$C$35)^H$6 -> 0.62341547 | I10: =1/(1+WACC!$C$35)^I$6 -> 0.57620078 | J10: =1/(1+WACC!$C$35)^J$6 -> 0.53256191 | ... L10: =1/(1+WACC!$C$35)^L$6 -> 0.45494891
B11: Present value ($mm) | C11: =C9*C10 -> 1354.1758 | D11: =D9*D10 -> 1284.6179 | E11: =E9*E10 -> 1218.633 | F11: =F9*F10 -> 1156.0373 | G11: =G9*G10 -> 1096.6569 | H11: =H9*H10 -> 1040.7185 | I11: =I9*I10 -> 988.00528 | J11: =J9*J10 -> 938.31505 | ... L11: =L9*L10 -> 847.26169
B13: Sum of present values, years 1 to 10 | C13: =SUM(C11:L11) -> 10815.881
B14: Terminal value at year 10 | C14: =L9*(1+Inputs!$C$37)/(WACC!$C$35-Inputs!$C$37) -> 35700.534
B15: Present value of terminal value | C15: =C14*L10 -> 16241.919
B16: Enterprise value | C16: =C13+C15 -> 27057.8
B17: Less: debt | C17: =-Inputs!$C$27 -> -4620
B18: Plus: cash | C18: =Inputs!$C$28 -> 552.2
B19: Equity value | C19: =SUM(C16:C18) -> 22990
B20: Shares (mm) | C20: =Inputs!$C$7 -> 130.16
B21: Value per share ($) | C21: =C19/C20 -> 176.62876
B22: Price at the lock ($) | C22: =Inputs!$C$6 -> 176.62876
B23: Value / price - 1 | C23: =C21/C22-1 -> 8.6088914e-12
B24: Terminal value share of enterprise value | C24: =C15/C16 -> 0.60026755
B25: B. At your view of growth (Inputs tab, yellow cell)
B26: Year | C26: 1 | D26: 2 | E26: 3 | F26: 4 | G26: 5 | H26: 6 | I26: 7 | J26: 8 | K26: 9 | L26: 10
B27: Revenue growth | C27: =IF(C$26<=Inputs!$C$46,Inputs!$C$45,Inputs!$C$45-(Inputs!$C$45-Inputs!$C$37)*MIN(C$26-Inputs!$C$46,Inputs!$C$47)/Inputs!$C$47) -> 0.062755445 | D27: =IF(D$26<=Inputs!$C$46,Inputs!$C$45,Inputs!$C$45-(Inputs!$C$45-Inputs!$C$37)*MIN(D$26-Inputs!$C$46,Inputs!$C$47)/Inputs!$C$47) -> 0.062755445 | E27: =IF(E$26<=Inputs!$C$46,Inputs!$C$45,Inputs!$C$45-(Inputs!$C$45-Inputs!$C$37)*MIN(E$26-Inputs!$C$46,Inputs!$C$47)/Inputs!$C$47) -> 0.062755445 | F27: =IF(F$26<=Inputs!$C$46,Inputs!$C$45,Inputs!$C$45-(Inputs!$C$45-Inputs!$C$37)*MIN(F$26-Inputs!$C$46,Inputs!$C$47)/Inputs!$C$47) -> 0.062755445 | G27: =IF(G$26<=Inputs!$C$46,Inputs!$C$45,Inputs!$C$45-(Inputs!$C$45-Inputs!$C$37)*MIN(G$26-Inputs!$C$46,Inputs!$C$47)/Inputs!$C$47) -> 0.062755445 | H27: =IF(H$26<=Inputs!$C$46,Inputs!$C$45,Inputs!$C$45-(Inputs!$C$45-Inputs!$C$37)*MIN(H$26-Inputs!$C$46,Inputs!$C$47)/Inputs!$C$47) -> 0.055864356 | I27: =IF(I$26<=Inputs!$C$46,Inputs!$C$45,Inputs!$C$45-(Inputs!$C$45-Inputs!$C$37)*MIN(I$26-Inputs!$C$46,Inputs!$C$47)/Inputs!$C$47) -> 0.048973267 | J27: =IF(J$26<=Inputs!$C$46,Inputs!$C$45,Inputs!$C$45-(Inputs!$C$45-Inputs!$C$37)*MIN(J$26-Inputs!$C$46,Inputs!$C$47)/Inputs!$C$47) -> 0.042082178 | ... L27: =IF(L$26<=Inputs!$C$46,Inputs!$C$45,Inputs!$C$45-(Inputs!$C$45-Inputs!$C$37)*MIN(L$26-Inputs!$C$46,Inputs!$C$47)/Inputs!$C$47) -> 0.0283
B28: Revenue ($mm) | C28: =Inputs!$C$12*(1+C27) -> 3337.0521 | D28: =C28*(1+D27) -> 3546.4703 | E28: =D28*(1+E27) -> 3769.0306 | F28: =E28*(1+F27) -> 4005.5578 | G28: =F28*(1+G27) -> 4256.9284 | H28: =G28*(1+H27) -> 4494.7389 | I28: =H28*(1+I27) -> 4714.861 | J28: =I28*(1+J27) -> 4913.2726 | K28: =J28*(1+K27) -> 5086.176 | L28: =K28*(1+L27) -> 5230.1148
B29: Unlevered free cash flow ($mm) | C29: =C28*Inputs!$C$23 -> 1517.0834 | D29: =D28*Inputs!$C$23 -> 1612.2886 | E29: =E28*Inputs!$C$23 -> 1713.4685 | F29: =F28*Inputs!$C$23 -> 1820.998 | G29: =G28*Inputs!$C$23 -> 1935.2756 | H29: =H28*Inputs!$C$23 -> 2043.3885 | I29: =I28*Inputs!$C$23 -> 2143.4599 | J29: =J28*Inputs!$C$23 -> 2233.6613 | ... L29: =L28*Inputs!$C$23 -> 2377.7035
B30: Discount factor | C30: =1/(1+WACC!$C$35)^C$26 -> 0.92426448 | D30: =1/(1+WACC!$C$35)^D$26 -> 0.85426483 | E30: =1/(1+WACC!$C$35)^E$26 -> 0.78956664 | F30: =1/(1+WACC!$C$35)^F$26 -> 0.7297684 | G30: =1/(1+WACC!$C$35)^G$26 -> 0.67449901 | H30: =1/(1+WACC!$C$35)^H$26 -> 0.62341547 | I30: =1/(1+WACC!$C$35)^I$26 -> 0.57620078 | J30: =1/(1+WACC!$C$35)^J$26 -> 0.53256191 | ... L30: =1/(1+WACC!$C$35)^L$26 -> 0.45494891
B31: Present value ($mm) | C31: =C29*C30 -> 1402.1863 | D31: =D29*D30 -> 1377.3215 | E31: =E29*E30 -> 1352.8976 | F31: =F29*F30 -> 1328.9068 | G31: =G29*G30 -> 1305.3414 | H31: =H29*H30 -> 1273.88 | I31: =I29*I30 -> 1235.0633 | J31: =J29*J30 -> 1189.563 | ... L31: =L29*L30 -> 1081.7336
B33: Sum of present values, years 1 to 10 | C33: =SUM(C31:L31) -> 12685.056
B34: Terminal value at year 10 | C34: =L29*(1+Inputs!$C$37)/(WACC!$C$35-Inputs!$C$37) -> 45580.33
B35: Present value of terminal value | C35: =C34*L30 -> 20736.722
B36: Enterprise value | C36: =C33+C35 -> 33421.777
B37: Less: debt | C37: =-Inputs!$C$27 -> -4620
B38: Plus: cash | C38: =Inputs!$C$28 -> 552.2
B39: Equity value | C39: =SUM(C36:C38) -> 29353.977
B40: Shares (mm) | C40: =Inputs!$C$7 -> 130.16
B41: Value per share ($) | C41: =C39/C40 -> 225.52226
B42: Price at the lock ($) | C42: =Inputs!$C$6 -> 176.62876
B43: Value / price - 1 | C43: =C41/C42-1 -> 0.27681502
B44: Terminal value share of enterprise value | C44: =C35/C36 -> 0.62045538

Sheet Sensitivity
B2: Verisk (VRSK): sensitivity
B3: Table A re-solves implied growth for each pair of inputs (Solver tab, blocks 2 to 26). Table B values the stock at a growth view.
B5: WACC step | C5: 0.005 | D5: Terminal-growth step | F5: 0.005
B6: Growth-view step | C6: 0.02
B8: A. Implied 5-year growth: WACC (rows) by terminal growth (columns)
C9: =Inputs!$C$37+(0-2)*$F$5 -> 0.0183 | D9: =Inputs!$C$37+(1-2)*$F$5 -> 0.0233 | E9: =Inputs!$C$37+(2-2)*$F$5 -> 0.0283 | F9: =Inputs!$C$37+(3-2)*$F$5 -> 0.0333 | G9: =Inputs!$C$37+(4-2)*$F$5 -> 0.0383
B10: =WACC!$C$35+(0-2)*$C$5 -> 0.071941394 | C10: =Solver!$D$74 -> 0.018042117 | D10: =Solver!$D$101 -> 0.0058141053 | E10: =Solver!$D$128 -> -0.0077060163 | F10: =Solver!$D$155 -> -0.02281794 | G10: =Solver!$D$182 -> -0.039940804 | I10: Centre cell = the base case. Each step changes one input by the step size above.
B11: =WACC!$C$35+(1-2)*$C$5 -> 0.076941394 | C11: =Solver!$D$209 -> 0.033414751 | D11: =Solver!$D$236 -> 0.022205979 | E11: =Solver!$D$263 -> 0.0099221766 | F11: =Solver!$D$290 -> -0.0036592782 | G11: =Solver!$D$317 -> -0.018839329
B12: =WACC!$C$35+(2-2)*$C$5 -> 0.081941394 | C12: =Solver!$D$344 -> 0.047977537 | D12: =Solver!$D$371 -> 0.037626892 | E12: =Solver!$D$398 -> 0.026366979 | F12: =Solver!$D$425 -> 0.014027387 | G12: =Solver!$D$452 -> 0.00038477778
B13: =WACC!$C$35+(3-2)*$C$5 -> 0.086941394 | C13: =Solver!$D$479 -> 0.061852247 | D13: =Solver!$D$506 -> 0.052234381 | E13: =Solver!$D$533 -> 0.04183653 | F13: =Solver!$D$560 -> 0.030525476 | G13: =Solver!$D$587 -> 0.018130094
B14: =WACC!$C$35+(4-2)*$C$5 -> 0.091941394 | C14: =Solver!$D$614 -> 0.075135261 | D14: =Solver!$D$641 -> 0.066150397 | E14: =Solver!$D$668 -> 0.056488544 | F14: =Solver!$D$695 -> 0.046043485 | G14: =Solver!$D$722 -> 0.03468129
B17: B. Value per share: WACC (rows) by your growth view (columns)
C18: =Inputs!$C$45+(0-2)*$C$6 -> 0.022755445 | D18: =Inputs!$C$45+(1-2)*$C$6 -> 0.042755445 | E18: =Inputs!$C$45+(2-2)*$C$6 -> 0.062755445 | F18: =Inputs!$C$45+(3-2)*$C$6 -> 0.082755445 | G18: =Inputs!$C$45+(4-2)*$C$6 -> 0.10275544
B19: =WACC!$C$35+(0-2)*$C$5 -> 0.071941394 | C19: =(SUMPRODUCT($C28:$L28,1/(1+$B19)^$C$27:$L$27)*Inputs!$C$23+$L28*Inputs!$C$23*(1+Inputs!$C$37)/($B19-Inputs!$C$37)/(1+$B19)^$L$27-Inputs!$C$27+Inputs!$C$28)/Inputs!$C$7 -> 218.69989 | D19: =(SUMPRODUCT($C29:$L29,1/(1+$B19)^$C$27:$L$27)*Inputs!$C$23+$L29*Inputs!$C$23*(1+Inputs!$C$37)/($B19-Inputs!$C$37)/(1+$B19)^$L$27-Inputs!$C$27+Inputs!$C$28)/Inputs!$C$7 -> 250.49906 | E19: =(SUMPRODUCT($C30:$L30,1/(1+$B19)^$C$27:$L$27)*Inputs!$C$23+$L30*Inputs!$C$23*(1+Inputs!$C$37)/($B19-Inputs!$C$37)/(1+$B19)^$L$27-Inputs!$C$27+Inputs!$C$28)/Inputs!$C$7 -> 286.01162 | F19: =(SUMPRODUCT($C31:$L31,1/(1+$B19)^$C$27:$L$27)*Inputs!$C$23+$L31*Inputs!$C$23*(1+Inputs!$C$37)/($B19-Inputs!$C$37)/(1+$B19)^$L$27-Inputs!$C$27+Inputs!$C$28)/Inputs!$C$7 -> 325.61377 | G19: =(SUMPRODUCT($C32:$L32,1/(1+$B19)^$C$27:$L$27)*Inputs!$C$23+$L32*Inputs!$C$23*(1+Inputs!$C$37)/($B19-Inputs!$C$37)/(1+$B19)^$L$27-Inputs!$C$27+Inputs!$C$28)/Inputs!$C$7 -> 369.71348 | I19: Compare with the price at the lock: $176.63.
B20: =WACC!$C$35+(1-2)*$C$5 -> 0.076941394 | C20: =(SUMPRODUCT($C28:$L28,1/(1+$B20)^$C$27:$L$27)*Inputs!$C$23+$L28*Inputs!$C$23*(1+Inputs!$C$37)/($B20-Inputs!$C$37)/(1+$B20)^$L$27-Inputs!$C$27+Inputs!$C$28)/Inputs!$C$7 -> 193.10844 | D20: =(SUMPRODUCT($C29:$L29,1/(1+$B20)^$C$27:$L$27)*Inputs!$C$23+$L29*Inputs!$C$23*(1+Inputs!$C$37)/($B20-Inputs!$C$37)/(1+$B20)^$L$27-Inputs!$C$27+Inputs!$C$28)/Inputs!$C$7 -> 221.24757 | E20: =(SUMPRODUCT($C30:$L30,1/(1+$B20)^$C$27:$L$27)*Inputs!$C$23+$L30*Inputs!$C$23*(1+Inputs!$C$37)/($B20-Inputs!$C$37)/(1+$B20)^$L$27-Inputs!$C$27+Inputs!$C$28)/Inputs!$C$7 -> 252.64825 | F20: =(SUMPRODUCT($C31:$L31,1/(1+$B20)^$C$27:$L$27)*Inputs!$C$23+$L31*Inputs!$C$23*(1+Inputs!$C$37)/($B20-Inputs!$C$37)/(1+$B20)^$L$27-Inputs!$C$27+Inputs!$C$28)/Inputs!$C$7 -> 287.63953 | G20: =(SUMPRODUCT($C32:$L32,1/(1+$B20)^$C$27:$L$27)*Inputs!$C$23+$L32*Inputs!$C$23*(1+Inputs!$C$37)/($B20-Inputs!$C$37)/(1+$B20)^$L$27-Inputs!$C$27+Inputs!$C$28)/Inputs!$C$7 -> 326.57814
B21: =WACC!$C$35+(2-2)*$C$5 -> 0.081941394 | C21: =(SUMPRODUCT($C28:$L28,1/(1+$B21)^$C$27:$L$27)*Inputs!$C$23+$L28*Inputs!$C$23*(1+Inputs!$C$37)/($B21-Inputs!$C$37)/(1+$B21)^$L$27-Inputs!$C$27+Inputs!$C$28)/Inputs!$C$7 -> 172.28548 | D21: =(SUMPRODUCT($C29:$L29,1/(1+$B21)^$C$27:$L$27)*Inputs!$C$23+$L29*Inputs!$C$23*(1+Inputs!$C$37)/($B21-Inputs!$C$37)/(1+$B21)^$L$27-Inputs!$C$27+Inputs!$C$28)/Inputs!$C$7 -> 197.45598 | E21: =(SUMPRODUCT($C30:$L30,1/(1+$B21)^$C$27:$L$27)*Inputs!$C$23+$L30*Inputs!$C$23*(1+Inputs!$C$37)/($B21-Inputs!$C$37)/(1+$B21)^$L$27-Inputs!$C$27+Inputs!$C$28)/Inputs!$C$7 -> 225.52226 | F21: =(SUMPRODUCT($C31:$L31,1/(1+$B21)^$C$27:$L$27)*Inputs!$C$23+$L31*Inputs!$C$23*(1+Inputs!$C$37)/($B21-Inputs!$C$37)/(1+$B21)^$L$27-Inputs!$C$27+Inputs!$C$28)/Inputs!$C$7 -> 256.77525 | G21: =(SUMPRODUCT($C32:$L32,1/(1+$B21)^$C$27:$L$27)*Inputs!$C$23+$L32*Inputs!$C$23*(1+Inputs!$C$37)/($B21-Inputs!$C$37)/(1+$B21)^$L$27-Inputs!$C$27+Inputs!$C$28)/Inputs!$C$7 -> 291.53027
B22: =WACC!$C$35+(3-2)*$C$5 -> 0.086941394 | C22: =(SUMPRODUCT($C28:$L28,1/(1+$B22)^$C$27:$L$27)*Inputs!$C$23+$L28*Inputs!$C$23*(1+Inputs!$C$37)/($B22-Inputs!$C$37)/(1+$B22)^$L$27-Inputs!$C$27+Inputs!$C$28)/Inputs!$C$7 -> 155.01134 | D22: =(SUMPRODUCT($C29:$L29,1/(1+$B22)^$C$27:$L$27)*Inputs!$C$23+$L29*Inputs!$C$23*(1+Inputs!$C$37)/($B22-Inputs!$C$37)/(1+$B22)^$L$27-Inputs!$C$27+Inputs!$C$28)/Inputs!$C$7 -> 177.72748 | E22: =(SUMPRODUCT($C30:$L30,1/(1+$B22)^$C$27:$L$27)*Inputs!$C$23+$L30*Inputs!$C$23*(1+Inputs!$C$37)/($B22-Inputs!$C$37)/(1+$B22)^$L$27-Inputs!$C$27+Inputs!$C$28)/Inputs!$C$7 -> 203.03764 | F22: =(SUMPRODUCT($C31:$L31,1/(1+$B22)^$C$27:$L$27)*Inputs!$C$23+$L31*Inputs!$C$23*(1+Inputs!$C$37)/($B22-Inputs!$C$37)/(1+$B22)^$L$27-Inputs!$C$27+Inputs!$C$28)/Inputs!$C$7 -> 231.20132 | G22: =(SUMPRODUCT($C32:$L32,1/(1+$B22)^$C$27:$L$27)*Inputs!$C$23+$L32*Inputs!$C$23*(1+Inputs!$C$37)/($B22-Inputs!$C$37)/(1+$B22)^$L$27-Inputs!$C$27+Inputs!$C$28)/Inputs!$C$7 -> 262.49974
B23: =WACC!$C$35+(4-2)*$C$5 -> 0.091941394 | C23: =(SUMPRODUCT($C28:$L28,1/(1+$B23)^$C$27:$L$27)*Inputs!$C$23+$L28*Inputs!$C$23*(1+Inputs!$C$37)/($B23-Inputs!$C$37)/(1+$B23)^$L$27-Inputs!$C$27+Inputs!$C$28)/Inputs!$C$7 -> 140.44965 | D23: =(SUMPRODUCT($C29:$L29,1/(1+$B23)^$C$27:$L$27)*Inputs!$C$23+$L29*Inputs!$C$23*(1+Inputs!$C$37)/($B23-Inputs!$C$37)/(1+$B23)^$L$27-Inputs!$C$27+Inputs!$C$28)/Inputs!$C$7 -> 161.10425 | E23: =(SUMPRODUCT($C30:$L30,1/(1+$B23)^$C$27:$L$27)*Inputs!$C$23+$L30*Inputs!$C$23*(1+Inputs!$C$37)/($B23-Inputs!$C$37)/(1+$B23)^$L$27-Inputs!$C$27+Inputs!$C$28)/Inputs!$C$7 -> 184.09997 | F23: =(SUMPRODUCT($C31:$L31,1/(1+$B23)^$C$27:$L$27)*Inputs!$C$23+$L31*Inputs!$C$23*(1+Inputs!$C$37)/($B23-Inputs!$C$37)/(1+$B23)^$L$27-Inputs!$C$27+Inputs!$C$28)/Inputs!$C$7 -> 209.67001 | G23: =(SUMPRODUCT($C32:$L32,1/(1+$B23)^$C$27:$L$27)*Inputs!$C$23+$L32*Inputs!$C$23*(1+Inputs!$C$37)/($B23-Inputs!$C$37)/(1+$B23)^$L$27-Inputs!$C$27+Inputs!$C$28)/Inputs!$C$7 -> 238.06704
B26: Helper: revenue paths for each growth view (years 1 to 10)
C27: 1 | D27: 2 | E27: 3 | F27: 4 | G27: 5 | H27: 6 | I27: 7 | J27: 8 | K27: 9 | L27: 10
B28: =C$18 -> 0.022755445 | C28: =Inputs!$C$12*(1+IF(C$27<=Inputs!$C$46,$B28,$B28-($B28-Inputs!$C$37)*MIN(C$27-Inputs!$C$46,Inputs!$C$47)/Inputs!$C$47)) -> 3211.4521 | D28: =C28*(1+IF(D$27<=Inputs!$C$46,$B28,$B28-($B28-Inputs!$C$37)*MIN(D$27-Inputs!$C$46,Inputs!$C$47)/Inputs!$C$47)) -> 3284.5301 | E28: =D28*(1+IF(E$27<=Inputs!$C$46,$B28,$B28-($B28-Inputs!$C$37)*MIN(E$27-Inputs!$C$46,Inputs!$C$47)/Inputs!$C$47)) -> 3359.2711 | F28: =E28*(1+IF(F$27<=Inputs!$C$46,$B28,$B28-($B28-Inputs!$C$37)*MIN(F$27-Inputs!$C$46,Inputs!$C$47)/Inputs!$C$47)) -> 3435.7128 | G28: =F28*(1+IF(G$27<=Inputs!$C$46,$B28,$B28-($B28-Inputs!$C$37)*MIN(G$27-Inputs!$C$46,Inputs!$C$47)/Inputs!$C$47)) -> 3513.8939 | H28: =G28*(1+IF(H$27<=Inputs!$C$46,$B28,$B28-($B28-Inputs!$C$37)*MIN(H$27-Inputs!$C$46,Inputs!$C$47)/Inputs!$C$47)) -> 3597.7508 | I28: =H28*(1+IF(I$27<=Inputs!$C$46,$B28,$B28-($B28-Inputs!$C$37)*MIN(I$27-Inputs!$C$46,Inputs!$C$47)/Inputs!$C$47)) -> 3687.5983 | J28: =I28*(1+IF(J$27<=Inputs!$C$46,$B28,$B28-($B28-Inputs!$C$37)*MIN(J$27-Inputs!$C$46,Inputs!$C$47)/Inputs!$C$47)) -> 3783.7789 | K28: =J28*(1+IF(K$27<=Inputs!$C$46,$B28,$B28-($B28-Inputs!$C$37)*MIN(K$27-Inputs!$C$46,Inputs!$C$47)/Inputs!$C$47)) -> 3886.664 | L28: =K28*(1+IF(L$27<=Inputs!$C$46,$B28,$B28-($B28-Inputs!$C$37)*MIN(L$27-Inputs!$C$46,Inputs!$C$47)/Inputs!$C$47)) -> 3996.6566
B29: =D$18 -> 0.042755445 | C29: =Inputs!$C$12*(1+IF(C$27<=Inputs!$C$46,$B29,$B29-($B29-Inputs!$C$37)*MIN(C$27-Inputs!$C$46,Inputs!$C$47)/Inputs!$C$47)) -> 3274.2521 | D29: =C29*(1+IF(D$27<=Inputs!$C$46,$B29,$B29-($B29-Inputs!$C$37)*MIN(D$27-Inputs!$C$46,Inputs!$C$47)/Inputs!$C$47)) -> 3414.2442 | E29: =D29*(1+IF(E$27<=Inputs!$C$46,$B29,$B29-($B29-Inputs!$C$37)*MIN(E$27-Inputs!$C$46,Inputs!$C$47)/Inputs!$C$47)) -> 3560.2217 | F29: =E29*(1+IF(F$27<=Inputs!$C$46,$B29,$B29-($B29-Inputs!$C$37)*MIN(F$27-Inputs!$C$46,Inputs!$C$47)/Inputs!$C$47)) -> 3712.4406 | G29: =F29*(1+IF(G$27<=Inputs!$C$46,$B29,$B29-($B29-Inputs!$C$37)*MIN(G$27-Inputs!$C$46,Inputs!$C$47)/Inputs!$C$47)) -> 3871.1676 | H29: =G29*(1+IF(H$27<=Inputs!$C$46,$B29,$B29-($B29-Inputs!$C$37)*MIN(H$27-Inputs!$C$46,Inputs!$C$47)/Inputs!$C$47)) -> 4025.4892 | I29: =H29*(1+IF(I$27<=Inputs!$C$46,$B29,$B29-($B29-Inputs!$C$37)*MIN(I$27-Inputs!$C$46,Inputs!$C$47)/Inputs!$C$47)) -> 4174.3247 | J29: =I29*(1+IF(J$27<=Inputs!$C$46,$B29,$B29-($B29-Inputs!$C$37)*MIN(J$27-Inputs!$C$46,Inputs!$C$47)/Inputs!$C$47)) -> 4316.5948 | K29: =J29*(1+IF(K$27<=Inputs!$C$46,$B29,$B29-($B29-Inputs!$C$37)*MIN(K$27-Inputs!$C$46,Inputs!$C$47)/Inputs!$C$47)) -> 4451.2341 | L29: =K29*(1+IF(L$27<=Inputs!$C$46,$B29,$B29-($B29-Inputs!$C$37)*MIN(L$27-Inputs!$C$46,Inputs!$C$47)/Inputs!$C$47)) -> 4577.204
B30: =E$18 -> 0.062755445 | C30: =Inputs!$C$12*(1+IF(C$27<=Inputs!$C$46,$B30,$B30-($B30-Inputs!$C$37)*MIN(C$27-Inputs!$C$46,Inputs!$C$47)/Inputs!$C$47)) -> 3337.0521 | D30: =C30*(1+IF(D$27<=Inputs!$C$46,$B30,$B30-($B30-Inputs!$C$37)*MIN(D$27-Inputs!$C$46,Inputs!$C$47)/Inputs!$C$47)) -> 3546.4703 | E30: =D30*(1+IF(E$27<=Inputs!$C$46,$B30,$B30-($B30-Inputs!$C$37)*MIN(E$27-Inputs!$C$46,Inputs!$C$47)/Inputs!$C$47)) -> 3769.0306 | F30: =E30*(1+IF(F$27<=Inputs!$C$46,$B30,$B30-($B30-Inputs!$C$37)*MIN(F$27-Inputs!$C$46,Inputs!$C$47)/Inputs!$C$47)) -> 4005.5578 | G30: =F30*(1+IF(G$27<=Inputs!$C$46,$B30,$B30-($B30-Inputs!$C$37)*MIN(G$27-Inputs!$C$46,Inputs!$C$47)/Inputs!$C$47)) -> 4256.9284 | H30: =G30*(1+IF(H$27<=Inputs!$C$46,$B30,$B30-($B30-Inputs!$C$37)*MIN(H$27-Inputs!$C$46,Inputs!$C$47)/Inputs!$C$47)) -> 4494.7389 | I30: =H30*(1+IF(I$27<=Inputs!$C$46,$B30,$B30-($B30-Inputs!$C$37)*MIN(I$27-Inputs!$C$46,Inputs!$C$47)/Inputs!$C$47)) -> 4714.861 | J30: =I30*(1+IF(J$27<=Inputs!$C$46,$B30,$B30-($B30-Inputs!$C$37)*MIN(J$27-Inputs!$C$46,Inputs!$C$47)/Inputs!$C$47)) -> 4913.2726 | K30: =J30*(1+IF(K$27<=Inputs!$C$46,$B30,$B30-($B30-Inputs!$C$37)*MIN(K$27-Inputs!$C$46,Inputs!$C$47)/Inputs!$C$47)) -> 5086.176 | L30: =K30*(1+IF(L$27<=Inputs!$C$46,$B30,$B30-($B30-Inputs!$C$37)*MIN(L$27-Inputs!$C$46,Inputs!$C$47)/Inputs!$C$47)) -> 5230.1148
B31: =F$18 -> 0.082755445 | C31: =Inputs!$C$12*(1+IF(C$27<=Inputs!$C$46,$B31,$B31-($B31-Inputs!$C$37)*MIN(C$27-Inputs!$C$46,Inputs!$C$47)/Inputs!$C$47)) -> 3399.8521 | D31: =C31*(1+IF(D$27<=Inputs!$C$46,$B31,$B31-($B31-Inputs!$C$37)*MIN(D$27-Inputs!$C$46,Inputs!$C$47)/Inputs!$C$47)) -> 3681.2084 | E31: =D31*(1+IF(E$27<=Inputs!$C$46,$B31,$B31-($B31-Inputs!$C$37)*MIN(E$27-Inputs!$C$46,Inputs!$C$47)/Inputs!$C$47)) -> 3985.8484 | F31: =E31*(1+IF(F$27<=Inputs!$C$46,$B31,$B31-($B31-Inputs!$C$37)*MIN(F$27-Inputs!$C$46,Inputs!$C$47)/Inputs!$C$47)) -> 4315.6991 | G31: =F31*(1+IF(G$27<=Inputs!$C$46,$B31,$B31-($B31-Inputs!$C$37)*MIN(G$27-Inputs!$C$46,Inputs!$C$47)/Inputs!$C$47)) -> 4672.8467 | H31: =G31*(1+IF(H$27<=Inputs!$C$46,$B31,$B31-($B31-Inputs!$C$37)*MIN(H$27-Inputs!$C$46,Inputs!$C$47)/Inputs!$C$47)) -> 5008.6578 | I31: =H31*(1+IF(I$27<=Inputs!$C$46,$B31,$B31-($B31-Inputs!$C$37)*MIN(I$27-Inputs!$C$46,Inputs!$C$47)/Inputs!$C$47)) -> 5314.052 | J31: =I31*(1+IF(J$27<=Inputs!$C$46,$B31,$B31-($B31-Inputs!$C$37)*MIN(J$27-Inputs!$C$46,Inputs!$C$47)/Inputs!$C$47)) -> 5580.1913 | K31: =J31*(1+IF(K$27<=Inputs!$C$46,$B31,$B31-($B31-Inputs!$C$37)*MIN(K$27-Inputs!$C$46,Inputs!$C$47)/Inputs!$C$47)) -> 5798.8851 | L31: =K31*(1+IF(L$27<=Inputs!$C$46,$B31,$B31-($B31-Inputs!$C$37)*MIN(L$27-Inputs!$C$46,Inputs!$C$47)/Inputs!$C$47)) -> 5962.9935
B32: =G$18 -> 0.10275544 | C32: =Inputs!$C$12*(1+IF(C$27<=Inputs!$C$46,$B32,$B32-($B32-Inputs!$C$37)*MIN(C$27-Inputs!$C$46,Inputs!$C$47)/Inputs!$C$47)) -> 3462.6521 | D32: =C32*(1+IF(D$27<=Inputs!$C$46,$B32,$B32-($B32-Inputs!$C$37)*MIN(D$27-Inputs!$C$46,Inputs!$C$47)/Inputs!$C$47)) -> 3818.4585 | E32: =D32*(1+IF(E$27<=Inputs!$C$46,$B32,$B32-($B32-Inputs!$C$37)*MIN(E$27-Inputs!$C$46,Inputs!$C$47)/Inputs!$C$47)) -> 4210.8259 | F32: =E32*(1+IF(F$27<=Inputs!$C$46,$B32,$B32-($B32-Inputs!$C$37)*MIN(F$27-Inputs!$C$46,Inputs!$C$47)/Inputs!$C$47)) -> 4643.5111 | G32: =F32*(1+IF(G$27<=Inputs!$C$46,$B32,$B32-($B32-Inputs!$C$37)*MIN(G$27-Inputs!$C$46,Inputs!$C$47)/Inputs!$C$47)) -> 5120.6572 | H32: =G32*(1+IF(H$27<=Inputs!$C$46,$B32,$B32-($B32-Inputs!$C$37)*MIN(H$27-Inputs!$C$46,Inputs!$C$47)/Inputs!$C$47)) -> 5570.5804 | I32: =H32*(1+IF(I$27<=Inputs!$C$46,$B32,$B32-($B32-Inputs!$C$37)*MIN(I$27-Inputs!$C$46,Inputs!$C$47)/Inputs!$C$47)) -> 5977.0839 | J32: =I32*(1+IF(J$27<=Inputs!$C$46,$B32,$B32-($B32-Inputs!$C$37)*MIN(J$27-Inputs!$C$46,Inputs!$C$47)/Inputs!$C$47)) -> 6324.2459 | K32: =J32*(1+IF(K$27<=Inputs!$C$46,$B32,$B32-($B32-Inputs!$C$37)*MIN(K$27-Inputs!$C$46,Inputs!$C$47)/Inputs!$C$47)) -> 6597.397 | L32: =K32*(1+IF(L$27<=Inputs!$C$46,$B32,$B32-($B32-Inputs!$C$37)*MIN(L$27-Inputs!$C$46,Inputs!$C$47)/Inputs!$C$47)) -> 6784.1033

Sheet Check
B2: Verisk (VRSK): check against the Python pipeline
B3: Python values are typed in (blue) from the pipeline that runs the site. Each row passes if the two agree within the tolerance.
B5: Item | C5: This workbook | D5: Python pipeline | E5: Difference | F5: Result
B6: Unlevered free-cash-flow margin | C6: =Inputs!$C$23 -> 0.45461783 | D6: 0.45461783 | E6: =C6-D6 -> 4.3949044e-09 | F6: =IF(ABS(E6)<=0.00005,"Pass","Check") -> Pass
B7: Group median unlevered beta | C7: =WACC!$C$12 -> 0.72811666 | D7: 0.72811666 | E7: =C7-D7 -> -1.769097e-09 | F7: =IF(ABS(E7)<=0.0005,"Pass","Check") -> Pass
B8: WACC | C8: =WACC!$C$35 -> 0.081941394 | D8: 0.08194139 | E8: =C8-D8 -> 4.3493295e-09 | F8: =IF(ABS(E8)<=0.00005,"Pass","Check") -> Pass
B9: Terminal growth | C9: =Inputs!$C$37 -> 0.0283 | D9: 0.0283 | E9: =C9-D9 -> 0 | F9: =IF(ABS(E9)<=0.00005,"Pass","Check") -> Pass
B10: Anchor | C10: =Inputs!$C$43 -> 0.062755445 | D10: 0.06275544 | E10: =C10-D10 -> 4.8798554e-09 | F10: =IF(ABS(E10)<=0.00005,"Pass","Check") -> Pass
B11: Implied growth, base case | C11: =Solver!$W$7 -> 0.02636698 | D11: 0.02636698 | E11: =C11-D11 -> -2.4177756e-10 | F11: =IF(ABS(E11)<=0.00005,"Pass","Check") -> Pass
B12: Implied growth, WACC one point higher | C12: =Sensitivity!$E$14 -> 0.056488544 | D12: 0.05648852 | E12: =C12-D12 -> 2.3748856e-08 | F12: =IF(ABS(E12)<=0.0002,"Pass","Check") -> Pass
B13: Value per share at the anchor ($) | C13: =DCF!$C$41 -> 225.52226 | D13: 225.52226 | E13: =C13-D13 -> 9.1549168e-10 | F13: =IF(ABS(E13)<=0.0225522260220916,"Pass","Check") -> Pass
B14: Panel A value minus price ($) | C14: =DCF!$C$21-DCF!$C$22 -> 1.5205615e-09 | D14: 0 | E14: =C14-D14 -> 1.5205615e-09 | F14: =IF(ABS(E14)<=0.01,"Pass","Check") -> Pass | G14: Panel B on the DCF tab uses your view; with the yellow cell at the anchor it matches the pipeline.
B16: Overall | C16: =IF(COUNTIF(F6:F14,"Pass")=9,"All checks pass","Review") -> All checks pass
