Workbook

Sheet Cover
B2: Priced In: Morningstar (MORN)
B3: Reverse DCF, model v1.0. Inputs as of the Oct 13, 2026 close; model locked Oct 14, 2026 (commit 0735af0).
B4: Ratings and indexes | US | reports in USD
B6: The question
B7: What revenue growth over the next five years does today's price imply, and is that more or less than the company has delivered and analysts expect?
B9: Answer
B10: Price at the lock ($) | C10: =Inputs!$C$6 -> 204.47881
B11: Implied 5-year revenue growth | C11: =Solver!$W$7 -> 0.049811827
B12: Anchor (history and analysts) | C12: =Inputs!$C$43 -> 0.082073834
B13: Gap (implied - anchor) | C13: =C11-C12 -> -0.032262007
B14: Verdict | C14: =IF(C13>=Inputs!$C$44,"Expectations too high",IF(C13<=-Inputs!$C$44,"Expectations too low","About right")) -> Expectations too low
B15: WACC | C15: =WACC!$C$34 -> 0.094183338
B16: Terminal growth | C16: =Inputs!$C$37 -> 0.0283
B17: Unlevered free-cash-flow margin | C17: =Inputs!$C$23 -> 0.19976654
B18: Your view of growth (Inputs, yellow) | C18: =Inputs!$C$45 -> 0.082073834
B19: Value per share at your view ($) | C19: =DCF!$C$41 -> 252.16673
B20: Upside or downside at your view | C20: =DCF!$C$43 -> 0.23321697
B25: How to use this file
B26: 1. Change any blue cell on Inputs, History or WACC; everything recalculates, including the solver.
B27: 2. The Solver tab finds implied growth by bisection with formulas, so you never need Goal Seek. 40 steps narrow a 150-point range to well under 0.0001%.
B28: 3. Type your own growth view in the yellow cell on Inputs; DCF panel B and this page show what the stock is worth if you're right.
B29: 4. Check confirms this workbook matches the Python pipeline that runs the site.
B31: Colour key
B32: Typed input with a source | C32: 1234
B33: Formula | C33: =C32*2 -> 2468
B34: Link to another tab | C34: =Inputs!$C$12 -> 2570
B35: Your view (edit this one) | C35: =Inputs!$C$45 -> 0.082073834
B37: Live site
B38: https://claude.ai/artifact/DS3n4CgaKxaSLzkXDsBKuK
B40: Built by Rohan Jayapalan. Not investment advice.

Sheet Inputs
B2: Morningstar (MORN): inputs
B3: Blue cells are typed inputs with a source. Black cells are formulas. Change a blue cell and every tab recalculates.
B5: Market and price
B6: Price per share at the lock ($) | C6: 204.47881 | E6: Market cap divided by shares from Stock Analysis at the Oct 13, 2026 close.
B7: Diluted shares outstanding (mm) | C7: 37.51 | E7: Stock Analysis statistics page, Oct 13, 2026.
B8: Market value of equity ($mm) | C8: =C6*C7 -> 7670 | E8: Price x shares.
B10: Trailing 12 months
B11: Revenue, reported ($mm) | C11: 2570 | E11: Stock Analysis income statement, trailing 12 months.
B12: Revenue used in the model ($mm) | C12: =C11 -> 2570 | E12: Same as reported.
B13: Free cash flow, reported (cash from operations - capex) ($mm) | C13: 497.5 | E13: Stock Analysis cash flow statement, trailing 12 months.
B14: Free cash flow before adjustments ($mm) | C14: =C13 -> 497.5 | E14: Same as reported.
B15: Less: adjustments ($mm) | C15: 0 | E15: None for this company.
B16: Free cash flow used ($mm) | C16: =C14-C15 -> 497.5
B17: Operating income ($mm) | C17: 583.5 | E17: Stock Analysis, trailing 12 months.
B18: Pretax income ($mm) | C18: 562.3 | E18: Stock Analysis, trailing 12 months.
B19: Interest proxy: operating income - pretax, floored at zero ($mm) | C19: =MAX(0,C17-C18) -> 21.2 | E19: Net interest and other non-operating costs. Adding it back (after tax) turns levered FCF into unlevered FCF.
B20: Tax rate | C20: 0.25 | E20: Statutory blend: 25% US (21% federal plus state), 26.5% Canada (federal plus Ontario).
B21: After-tax interest added back ($mm) | C21: =C19*(1-C20) -> 15.9
B22: Unlevered free cash flow ($mm) | C22: =C16+C21 -> 513.4
B23: Unlevered free-cash-flow margin | C23: =C22/C12 -> 0.19976654 | E23: Held flat for all 10 years in the model.
B24: EBITDA ($mm) | C24: 680.1 | E24: Stock Analysis, trailing 12 months.
B26: Balance sheet
B27: Total debt ($mm) | C27: 1900 | E27: Stock Analysis balance sheet, latest quarter.
B28: Cash and equivalents ($mm) | C28: 523.8 | E28: Stock Analysis balance sheet, latest quarter.
B29: Net debt ($mm) | C29: =C27-C28 -> 1376.2
B31: Rates
B32: 10-year US Treasury yield | C32: 0.0521 | E32: US Treasury daily par yield curve, Oct 13, 2026.
B33: 10-year TIPS real yield | C33: 0.0288 | E33: US Treasury daily real yield curve, Oct 13, 2026.
B34: Breakeven inflation | C34: =C32-C33 -> 0.0233 | E34: Nominal minus real: the market's inflation expectation.
B35: Risk-free rate used | C35: =C32 -> 0.0521
B36: Real growth added to inflation | C36: 0.005 | E36: Half a point of long-run real growth.
B37: Terminal growth | C37: =MIN(C34+C36,C35) -> 0.0283 | E37: Capped at the risk-free rate.
B38: Equity risk premium | C38: 0.0423 | E38: Damodaran implied equity risk premium, start of 2026.
B40: Growth anchor and verdict
B41: Past revenue growth (CAGR) | C41: =History!$C$12 -> 0.096047667 | E41: FY2021 to the 12 months ended June 2026
B42: Analysts' revenue growth forecast | C42: 0.0681 | E42: Analysts' 3-year revenue CAGR forecast (stockanalysis)
B43: Anchor (average of the two) | C43: =AVERAGE(C41:C42) -> 0.082073834 | E43: AVERAGE skips the n/a text when history isn't used.
B44: Verdict band (+/-) | C44: 0.03 | E44: Set before any backtest and never changed.
B45: Your view of 5-year revenue growth | C45: 0.082073834 | E45: Type your own view. It starts at the anchor. DCF panel B and the Cover show what the stock is worth at your view.
B46: Years at the solved growth rate | C46: 5 | E46: Model v1.0: 5 years at the growth rate, then a straight-line fade.
B47: Years of fade to terminal growth | C47: 5 | E47: Years 1 to 10 are on the Solver and DCF tabs; years past 10 grow at the terminal rate.

Sheet History
B2: Morningstar (MORN): revenue history
B3: Revenue from Stock Analysis income statements; the window is chosen so acquisitions and disposals don't count as growth.
B5: Fiscal year | C5: FY2021 | D5: FY2022 | E5: FY2023 | F5: FY2024 | G5: FY2025 | H5: TTM Jun-26
B6: Revenue ($mm) | C6: 1699 | D6: 1871 | E6: 2039 | F6: 2275 | G6: 2446 | H6: 2567
B7: Growth on the prior year | D7: =D6/C6-1 -> 0.10123602 | E7: =E6/D6-1 -> 0.089791555 | F7: =F6/E6-1 -> 0.11574301 | G7: =G6/F6-1 -> 0.075164835
B10: History window
B11: Start year | C11: FY2021 | E11: Years from start to TTM | G11: 4.5
B12: Revenue CAGR, start to TTM | C12: =(H6/INDEX(C6:H6,MATCH(C11,C5:H5,0)))^(1/G11)-1 -> 0.096047667 | I12: FY2021 to the 12 months ended June 2026
B15: Free-cash-flow margin history
B16: Fiscal year | C16: 2021 | D16: 2022 | E16: 2023 | F16: 2024 | G16: 2025
B17: (CFO - capex) / revenue | C17: 0.2048 | D17: 0.09 | E17: 0.0968 | F17: 0.1973 | G17: 0.181 | I17: SEC XBRL filings (NetCashProvidedByOperatingActivities, PaymentsToAcquirePropertyPlantAndEquipment, revenue tags).
B18: Plus today's interest add-back | C18: =C17+(Inputs!$C$23-Inputs!$C$16/Inputs!$C$12) -> 0.21098677 | D18: =D17+(Inputs!$C$23-Inputs!$C$16/Inputs!$C$12) -> 0.09618677 | E18: =E17+(Inputs!$C$23-Inputs!$C$16/Inputs!$C$12) -> 0.10298677 | F18: =F17+(Inputs!$C$23-Inputs!$C$16/Inputs!$C$12) -> 0.20348677 | G18: =G17+(Inputs!$C$23-Inputs!$C$16/Inputs!$C$12) -> 0.18718677
B19: Range (the margin slider's shaded zone) | C19: =MIN(C18:G18) -> 0.09618677 | D19: =MAX(C18:G18) -> 0.21098677

Sheet WACC
B2: Morningstar (MORN): cost of capital
B3: Bottom-up beta: the median unlevered beta of the company's group, relevered for this company's debt.
B5: Peer | C5: Raw beta | D5: Debt ($mm) | E5: Equity ($mm) | F5: Tax rate | G5: Unlevered beta
B6: S&P Global (SPGI) | C6: 1.0925017 | D6: 15750 | E6: 120850 | F6: 0.25 | G6: =C6/(1+(1-F6)*D6/E6) -> 0.99522342 | H6: Raw betas: 60 monthly returns to Sep 2026 against the S&P 500 (S&P/TSX for TMX); Cboe uses Stock Analysis's 5-year beta. Debt and equity from Stock Analysis, Oct 13, 2026.
B7: Moody's (MCO) | C7: 1.3479367 | D7: 7620 | E7: 80380 | F7: 0.25 | G7: =C7/(1+(1-F7)*D7/E7) -> 1.2584604
B8: MSCI (MSCI) | C8: 1.2419463 | D8: 6540 | E8: 40770 | F8: 0.25 | G8: =C8/(1+(1-F8)*D8/E8) -> 1.1085748
B9: Morningstar (MORN) | C9: 1.0250328 | D9: 1900 | E9: 7670 | F9: 0.25 | G9: =C9/(1+(1-F9)*D9/E9) -> 0.86443117
B11: Group median unlevered beta | C11: =MEDIAN(G6:G9) -> 1.0518991
B12: Debt ($mm) | C12: =Inputs!$C$27 -> 1900
B13: Market value of equity ($mm) | C13: =Inputs!$C$8 -> 7670
B14: Tax rate | C14: =Inputs!$C$20 -> 0.25
B15: Relevered beta | C15: =WACC!$C$11*(1+(1-WACC!$C$14)*WACC!$C$12/WACC!$C$13) -> 1.2473301 | H15: Hamada: unlevered beta x (1 + (1 - tax) x debt / equity).
B16: Risk-free rate | C16: =Inputs!$C$35 -> 0.0521
B17: Equity risk premium | C17: =Inputs!$C$38 -> 0.0423
B18: Cost of equity | C18: =WACC!$C$16+WACC!$C$15*WACC!$C$17 -> 0.10486207 | H18: CAPM: risk-free + beta x premium.
B20: Debt-to-EBITDA spread table
B21: Debt / EBITDA below | C21: Spread
B22: 1 | C22: 0.01 | H22: Synthetic spread over the risk-free rate by leverage, a simplified version of Damodaran's ratings table; the last row covers anything at 4x or above.
B23: 2 | C23: 0.0125
B24: 3 | C24: 0.016
B25: 4 | C25: 0.02
B26: 99 | C26: 0.0275
B28: Debt / EBITDA | C28: =Inputs!$C$27/Inputs!$C$24 -> 2.7937068
B29: Credit spread | C29: =INDEX(C22:C26,COUNTIF(B22:B26,"<="&WACC!$C$28)+1) -> 0.016 | H29: First row whose limit is above this company's leverage.
B30: Pre-tax cost of debt | C30: =WACC!$C$16+WACC!$C$29 -> 0.0681
B31: After-tax cost of debt | C31: =WACC!$C$30*(1-WACC!$C$14) -> 0.051075
B32: Weight of debt | C32: =WACC!$C$12/(WACC!$C$12+WACC!$C$13) -> 0.1985371 | H32: Market-value weights.
B33: Weight of equity | C33: =1-WACC!$C$32 -> 0.8014629
B34: WACC | C34: =WACC!$C$33*WACC!$C$18+WACC!$C$32*WACC!$C$31 -> 0.094183338

Sheet Solver
A1: Solver: bisection for the growth rate that makes the model equal the price (replaces Goal Seek)
B2: Revenue | C2: =Inputs!$C$12 -> 2570 | D2: Margin | E2: =Inputs!$C$23 -> 0.19976654 | F2: Debt | G2: =Inputs!$C$27 -> 1900 | H2: Cash | I2: =Inputs!$C$28 -> 523.8 | J2: Shares | K2: =Inputs!$C$7 -> 37.51 | L2: Price | M2: =Inputs!$C$6 -> 204.47881 | N2: Years | O2: =Inputs!$C$46 -> 5 | P2: Fade | Q2: =Inputs!$C$47 -> 5
D3: Year | E3: 1 | F3: 2 | G3: 3 | H3: 4 | I3: 5 | J3: 6 | K3: 7 | L3: 8 | M3: 9 | N3: 10
A4: Each row tries the midpoint of the current range. If the value per share is above the price, the answer is lower, so the top of the range moves down; otherwise the bottom moves up.
A6: Base case: model WACC and terminal growth (40 steps) | E6: WACC | F6: =WACC!$C$34 -> 0.094183338 | G6: Terminal growth | I6: =Inputs!$C$37 -> 0.0283 | W6: Implied growth
A7: Step | B7: Low | C7: High | D7: Mid | E7: Rev Y1 | F7: Rev Y2 | G7: Rev Y3 | H7: Rev Y4 | I7: Rev Y5 | J7: Rev Y6 | K7: Rev Y7 | L7: Rev Y8 | M7: Rev Y9 | N7: Rev Y10 | O7: PV of FCF | P7: PV of TV | Q7: EV | R7: Equity | S7: Per share | T7: Value - price | W7: =$D$47 -> 0.049811827
A8: 1 | B8: -0.5 | C8: 1 | D8: =(B8+C8)/2 -> 0.25 | E8: =$C$2*(1+IF(E$3<=$O$2,$D8,$D8-($D8-$I$6)*MIN(E$3-$O$2,$Q$2)/$Q$2)) -> 3212.5 | F8: =E8*(1+IF(F$3<=$O$2,$D8,$D8-($D8-$I$6)*MIN(F$3-$O$2,$Q$2)/$Q$2)) -> 4015.625 | G8: =F8*(1+IF(G$3<=$O$2,$D8,$D8-($D8-$I$6)*MIN(G$3-$O$2,$Q$2)/$Q$2)) -> 5019.5312 | H8: =G8*(1+IF(H$3<=$O$2,$D8,$D8-($D8-$I$6)*MIN(H$3-$O$2,$Q$2)/$Q$2)) -> 6274.4141 | I8: =H8*(1+IF(I$3<=$O$2,$D8,$D8-($D8-$I$6)*MIN(I$3-$O$2,$Q$2)/$Q$2)) -> 7843.0176 | J8: =I8*(1+IF(J$3<=$O$2,$D8,$D8-($D8-$I$6)*MIN(J$3-$O$2,$Q$2)/$Q$2)) -> 9456.0126 | K8: =J8*(1+IF(K$3<=$O$2,$D8,$D8-($D8-$I$6)*MIN(K$3-$O$2,$Q$2)/$Q$2)) -> 10981.457 | L8: =K8*(1+IF(L$3<=$O$2,$D8,$D8-($D8-$I$6)*MIN(L$3-$O$2,$Q$2)/$Q$2)) -> 12266.067 | M8: =L8*(1+IF(M$3<=$O$2,$D8,$D8-($D8-$I$6)*MIN(M$3-$O$2,$Q$2)/$Q$2)) -> 13157.074 | N8: =M8*(1+IF(N$3<=$O$2,$D8,$D8-($D8-$I$6)*MIN(N$3-$O$2,$Q$2)/$Q$2)) -> 13529.42 | O8: =SUMPRODUCT(E8:N8,1/(1+$F$6)^$E$3:$N$3)*$E$2 -> 9625.0081 | P8: =N8*$E$2*(1+$I$6)/($F$6-$I$6)/(1+$F$6)^$N$3 -> 17149.252 | Q8: =O8+P8 -> 26774.26 | R8: =Q8-$G$2+$I$2 -> 25398.06 | S8: =R8/$K$2 -> 677.10104 | T8: =S8-$M$2 -> 472.62224 | W8: =IF(OR(ABS(W7+0.5)<0.000001,ABS(W7-1)<0.000001),"Out of range","Solved") -> Solved
A9: 2 | B9: =IF(T8>0,B8,D8) -> -0.5 | C9: =IF(T8>0,D8,C8) -> 0.25 | D9: =(B9+C9)/2 -> -0.125 | E9: =$C$2*(1+IF(E$3<=$O$2,$D9,$D9-($D9-$I$6)*MIN(E$3-$O$2,$Q$2)/$Q$2)) -> 2248.75 | F9: =E9*(1+IF(F$3<=$O$2,$D9,$D9-($D9-$I$6)*MIN(F$3-$O$2,$Q$2)/$Q$2)) -> 1967.6562 | G9: =F9*(1+IF(G$3<=$O$2,$D9,$D9-($D9-$I$6)*MIN(G$3-$O$2,$Q$2)/$Q$2)) -> 1721.6992 | H9: =G9*(1+IF(H$3<=$O$2,$D9,$D9-($D9-$I$6)*MIN(H$3-$O$2,$Q$2)/$Q$2)) -> 1506.4868 | I9: =H9*(1+IF(I$3<=$O$2,$D9,$D9-($D9-$I$6)*MIN(I$3-$O$2,$Q$2)/$Q$2)) -> 1318.176 | J9: =I9*(1+IF(J$3<=$O$2,$D9,$D9-($D9-$I$6)*MIN(J$3-$O$2,$Q$2)/$Q$2)) -> 1193.8192 | K9: =J9*(1+IF(K$3<=$O$2,$D9,$D9-($D9-$I$6)*MIN(K$3-$O$2,$Q$2)/$Q$2)) -> 1117.7968 | L9: =K9*(1+IF(L$3<=$O$2,$D9,$D9-($D9-$I$6)*MIN(L$3-$O$2,$Q$2)/$Q$2)) -> 1080.8872 | M9: =L9*(1+IF(M$3<=$O$2,$D9,$D9-($D9-$I$6)*MIN(M$3-$O$2,$Q$2)/$Q$2)) -> 1078.3363 | N9: =M9*(1+IF(N$3<=$O$2,$D9,$D9-($D9-$I$6)*MIN(N$3-$O$2,$Q$2)/$Q$2)) -> 1108.8532 | O9: =SUMPRODUCT(E9:N9,1/(1+$F$6)^$E$3:$N$3)*$E$2 -> 1928.1352 | P9: =N9*$E$2*(1+$I$6)/($F$6-$I$6)/(1+$F$6)^$N$3 -> 1405.5298 | Q9: =O9+P9 -> 3333.665 | R9: =Q9-$G$2+$I$2 -> 1957.465 | S9: =R9/$K$2 -> 52.185151 | T9: =S9-$M$2 -> -152.29365
A10: 3 | B10: =IF(T9>0,B9,D9) -> -0.125 | C10: =IF(T9>0,D9,C9) -> 0.25 | D10: =(B10+C10)/2 -> 0.0625 | E10: =$C$2*(1+IF(E$3<=$O$2,$D10,$D10-($D10-$I$6)*MIN(E$3-$O$2,$Q$2)/$Q$2)) -> 2730.625 | F10: =E10*(1+IF(F$3<=$O$2,$D10,$D10-($D10-$I$6)*MIN(F$3-$O$2,$Q$2)/$Q$2)) -> 2901.2891 | G10: =F10*(1+IF(G$3<=$O$2,$D10,$D10-($D10-$I$6)*MIN(G$3-$O$2,$Q$2)/$Q$2)) -> 3082.6196 | H10: =G10*(1+IF(H$3<=$O$2,$D10,$D10-($D10-$I$6)*MIN(H$3-$O$2,$Q$2)/$Q$2)) -> 3275.2834 | I10: =H10*(1+IF(I$3<=$O$2,$D10,$D10-($D10-$I$6)*MIN(I$3-$O$2,$Q$2)/$Q$2)) -> 3479.9886 | J10: =I10*(1+IF(J$3<=$O$2,$D10,$D10-($D10-$I$6)*MIN(J$3-$O$2,$Q$2)/$Q$2)) -> 3673.6847 | K10: =J10*(1+IF(K$3<=$O$2,$D10,$D10-($D10-$I$6)*MIN(K$3-$O$2,$Q$2)/$Q$2)) -> 3853.034 | L10: =K10*(1+IF(L$3<=$O$2,$D10,$D10-($D10-$I$6)*MIN(L$3-$O$2,$Q$2)/$Q$2)) -> 4014.7844 | M10: =L10*(1+IF(M$3<=$O$2,$D10,$D10-($D10-$I$6)*MIN(M$3-$O$2,$Q$2)/$Q$2)) -> 4155.8639 | N10: =M10*(1+IF(N$3<=$O$2,$D10,$D10-($D10-$I$6)*MIN(N$3-$O$2,$Q$2)/$Q$2)) -> 4273.4749 | O10: =SUMPRODUCT(E10:N10,1/(1+$F$6)^$E$3:$N$3)*$E$2 -> 4296.7073 | P10: =N10*$E$2*(1+$I$6)/($F$6-$I$6)/(1+$F$6)^$N$3 -> 5416.8545 | Q10: =O10+P10 -> 9713.5618 | R10: =Q10-$G$2+$I$2 -> 8337.3618 | S10: =R10/$K$2 -> 222.27038 | T10: =S10-$M$2 -> 17.79157
A11: 4 | B11: =IF(T10>0,B10,D10) -> -0.125 | C11: =IF(T10>0,D10,C10) -> 0.0625 | D11: =(B11+C11)/2 -> -0.03125 | E11: =$C$2*(1+IF(E$3<=$O$2,$D11,$D11-($D11-$I$6)*MIN(E$3-$O$2,$Q$2)/$Q$2)) -> 2489.6875 | F11: =E11*(1+IF(F$3<=$O$2,$D11,$D11-($D11-$I$6)*MIN(F$3-$O$2,$Q$2)/$Q$2)) -> 2411.8848 | G11: =F11*(1+IF(G$3<=$O$2,$D11,$D11-($D11-$I$6)*MIN(G$3-$O$2,$Q$2)/$Q$2)) -> 2336.5134 | H11: =G11*(1+IF(H$3<=$O$2,$D11,$D11-($D11-$I$6)*MIN(H$3-$O$2,$Q$2)/$Q$2)) -> 2263.4973 | I11: =H11*(1+IF(I$3<=$O$2,$D11,$D11-($D11-$I$6)*MIN(I$3-$O$2,$Q$2)/$Q$2)) -> 2192.763 | J11: =I11*(1+IF(J$3<=$O$2,$D11,$D11-($D11-$I$6)*MIN(J$3-$O$2,$Q$2)/$Q$2)) -> 2150.355 | K11: =J11*(1+IF(K$3<=$O$2,$D11,$D11-($D11-$I$6)*MIN(K$3-$O$2,$Q$2)/$Q$2)) -> 2134.3779 | L11: =K11*(1+IF(L$3<=$O$2,$D11,$D11-($D11-$I$6)*MIN(L$3-$O$2,$Q$2)/$Q$2)) -> 2143.9399 | M11: =L11*(1+IF(M$3<=$O$2,$D11,$D11-($D11-$I$6)*MIN(M$3-$O$2,$Q$2)/$Q$2)) -> 2179.079 | N11: =M11*(1+IF(N$3<=$O$2,$D11,$D11-($D11-$I$6)*MIN(N$3-$O$2,$Q$2)/$Q$2)) -> 2240.747 | O11: =SUMPRODUCT(E11:N11,1/(1+$F$6)^$E$3:$N$3)*$E$2 -> 2869.4996 | P11: =N11*$E$2*(1+$I$6)/($F$6-$I$6)/(1+$F$6)^$N$3 -> 2840.2648 | Q11: =O11+P11 -> 5709.7644 | R11: =Q11-$G$2+$I$2 -> 4333.5644 | S11: =R11/$K$2 -> 115.53091 | T11: =S11-$M$2 -> -88.947896
A12: 5 | B12: =IF(T11>0,B11,D11) -> -0.03125 | C12: =IF(T11>0,D11,C11) -> 0.0625 | D12: =(B12+C12)/2 -> 0.015625 | E12: =$C$2*(1+IF(E$3<=$O$2,$D12,$D12-($D12-$I$6)*MIN(E$3-$O$2,$Q$2)/$Q$2)) -> 2610.1562 | F12: =E12*(1+IF(F$3<=$O$2,$D12,$D12-($D12-$I$6)*MIN(F$3-$O$2,$Q$2)/$Q$2)) -> 2650.9399 | G12: =F12*(1+IF(G$3<=$O$2,$D12,$D12-($D12-$I$6)*MIN(G$3-$O$2,$Q$2)/$Q$2)) -> 2692.3609 | H12: =G12*(1+IF(H$3<=$O$2,$D12,$D12-($D12-$I$6)*MIN(H$3-$O$2,$Q$2)/$Q$2)) -> 2734.429 | I12: =H12*(1+IF(I$3<=$O$2,$D12,$D12-($D12-$I$6)*MIN(I$3-$O$2,$Q$2)/$Q$2)) -> 2777.1545 | J12: =I12*(1+IF(J$3<=$O$2,$D12,$D12-($D12-$I$6)*MIN(J$3-$O$2,$Q$2)/$Q$2)) -> 2827.5876 | K12: =J12*(1+IF(K$3<=$O$2,$D12,$D12-($D12-$I$6)*MIN(K$3-$O$2,$Q$2)/$Q$2)) -> 2886.1045 | L12: =K12*(1+IF(L$3<=$O$2,$D12,$D12-($D12-$I$6)*MIN(L$3-$O$2,$Q$2)/$Q$2)) -> 2953.1487 | M12: =L12*(1+IF(M$3<=$O$2,$D12,$D12-($D12-$I$6)*MIN(M$3-$O$2,$Q$2)/$Q$2)) -> 3029.2366 | N12: =M12*(1+IF(N$3<=$O$2,$D12,$D12-($D12-$I$6)*MIN(N$3-$O$2,$Q$2)/$Q$2)) -> 3114.964 | O12: =SUMPRODUCT(E12:N12,1/(1+$F$6)^$E$3:$N$3)*$E$2 -> 3509.7463 | P12: =N12*$E$2*(1+$I$6)/($F$6-$I$6)/(1+$F$6)^$N$3 -> 3948.3809 | Q12: =O12+P12 -> 7458.1272 | R12: =Q12-$G$2+$I$2 -> 6081.9272 | S12: =R12/$K$2 -> 162.14149 | T12: =S12-$M$2 -> -42.337318
A13: 6 | B13: =IF(T12>0,B12,D12) -> 0.015625 | C13: =IF(T12>0,D12,C12) -> 0.0625 | D13: =(B13+C13)/2 -> 0.0390625 | E13: =$C$2*(1+IF(E$3<=$O$2,$D13,$D13-($D13-$I$6)*MIN(E$3-$O$2,$Q$2)/$Q$2)) -> 2670.3906 | F13: =E13*(1+IF(F$3<=$O$2,$D13,$D13-($D13-$I$6)*MIN(F$3-$O$2,$Q$2)/$Q$2)) -> 2774.7028 | G13: =F13*(1+IF(G$3<=$O$2,$D13,$D13-($D13-$I$6)*MIN(G$3-$O$2,$Q$2)/$Q$2)) -> 2883.0896 | H13: =G13*(1+IF(H$3<=$O$2,$D13,$D13-($D13-$I$6)*MIN(H$3-$O$2,$Q$2)/$Q$2)) -> 2995.7103 | I13: =H13*(1+IF(I$3<=$O$2,$D13,$D13-($D13-$I$6)*MIN(I$3-$O$2,$Q$2)/$Q$2)) -> 3112.7302 | J13: =I13*(1+IF(J$3<=$O$2,$D13,$D13-($D13-$I$6)*MIN(J$3-$O$2,$Q$2)/$Q$2)) -> 3227.6211 | K13: =J13*(1+IF(K$3<=$O$2,$D13,$D13-($D13-$I$6)*MIN(K$3-$O$2,$Q$2)/$Q$2)) -> 3339.8051 | L13: =K13*(1+IF(L$3<=$O$2,$D13,$D13-($D13-$I$6)*MIN(L$3-$O$2,$Q$2)/$Q$2)) -> 3448.6995 | M13: =L13*(1+IF(M$3<=$O$2,$D13,$D13-($D13-$I$6)*MIN(M$3-$O$2,$Q$2)/$Q$2)) -> 3553.721 | N13: =M13*(1+IF(N$3<=$O$2,$D13,$D13-($D13-$I$6)*MIN(N$3-$O$2,$Q$2)/$Q$2)) -> 3654.2913 | O13: =SUMPRODUCT(E13:N13,1/(1+$F$6)^$E$3:$N$3)*$E$2 -> 3883.06 | P13: =N13*$E$2*(1+$I$6)/($F$6-$I$6)/(1+$F$6)^$N$3 -> 4632.0067 | Q13: =O13+P13 -> 8515.0667 | R13: =Q13-$G$2+$I$2 -> 7138.8667 | S13: =R13/$K$2 -> 190.31903 | T13: =S13-$M$2 -> -14.159779
A14: 7 | B14: =IF(T13>0,B13,D13) -> 0.0390625 | C14: =IF(T13>0,D13,C13) -> 0.0625 | D14: =(B14+C14)/2 -> 0.05078125 | E14: =$C$2*(1+IF(E$3<=$O$2,$D14,$D14-($D14-$I$6)*MIN(E$3-$O$2,$Q$2)/$Q$2)) -> 2700.5078 | F14: =E14*(1+IF(F$3<=$O$2,$D14,$D14-($D14-$I$6)*MIN(F$3-$O$2,$Q$2)/$Q$2)) -> 2837.643 | G14: =F14*(1+IF(G$3<=$O$2,$D14,$D14-($D14-$I$6)*MIN(G$3-$O$2,$Q$2)/$Q$2)) -> 2981.742 | H14: =G14*(1+IF(H$3<=$O$2,$D14,$D14-($D14-$I$6)*MIN(H$3-$O$2,$Q$2)/$Q$2)) -> 3133.1586 | I14: =H14*(1+IF(I$3<=$O$2,$D14,$D14-($D14-$I$6)*MIN(I$3-$O$2,$Q$2)/$Q$2)) -> 3292.2643 | J14: =I14*(1+IF(J$3<=$O$2,$D14,$D14-($D14-$I$6)*MIN(J$3-$O$2,$Q$2)/$Q$2)) -> 3444.6468 | K14: =J14*(1+IF(K$3<=$O$2,$D14,$D14-($D14-$I$6)*MIN(K$3-$O$2,$Q$2)/$Q$2)) -> 3588.5943 | L14: =K14*(1+IF(L$3<=$O$2,$D14,$D14-($D14-$I$6)*MIN(L$3-$O$2,$Q$2)/$Q$2)) -> 3722.4219 | M14: =L14*(1+IF(M$3<=$O$2,$D14,$D14-($D14-$I$6)*MIN(M$3-$O$2,$Q$2)/$Q$2)) -> 3844.5034 | N14: =M14*(1+IF(N$3<=$O$2,$D14,$D14-($D14-$I$6)*MIN(N$3-$O$2,$Q$2)/$Q$2)) -> 3953.3028 | O14: =SUMPRODUCT(E14:N14,1/(1+$F$6)^$E$3:$N$3)*$E$2 -> 4084.5962 | P14: =N14*$E$2*(1+$I$6)/($F$6-$I$6)/(1+$F$6)^$N$3 -> 5011.0196 | Q14: =O14+P14 -> 9095.6158 | R14: =Q14-$G$2+$I$2 -> 7719.4158 | S14: =R14/$K$2 -> 205.79621 | T14: =S14-$M$2 -> 1.317404
A15: 8 | B15: =IF(T14>0,B14,D14) -> 0.0390625 | C15: =IF(T14>0,D14,C14) -> 0.05078125 | D15: =(B15+C15)/2 -> 0.044921875 | E15: =$C$2*(1+IF(E$3<=$O$2,$D15,$D15-($D15-$I$6)*MIN(E$3-$O$2,$Q$2)/$Q$2)) -> 2685.4492 | F15: =E15*(1+IF(F$3<=$O$2,$D15,$D15-($D15-$I$6)*MIN(F$3-$O$2,$Q$2)/$Q$2)) -> 2806.0846 | G15: =F15*(1+IF(G$3<=$O$2,$D15,$D15-($D15-$I$6)*MIN(G$3-$O$2,$Q$2)/$Q$2)) -> 2932.1392 | H15: =G15*(1+IF(H$3<=$O$2,$D15,$D15-($D15-$I$6)*MIN(H$3-$O$2,$Q$2)/$Q$2)) -> 3063.8564 | I15: =H15*(1+IF(I$3<=$O$2,$D15,$D15-($D15-$I$6)*MIN(I$3-$O$2,$Q$2)/$Q$2)) -> 3201.4906 | J15: =I15*(1+IF(J$3<=$O$2,$D15,$D15-($D15-$I$6)*MIN(J$3-$O$2,$Q$2)/$Q$2)) -> 3334.6646 | K15: =J15*(1+IF(K$3<=$O$2,$D15,$D15-($D15-$I$6)*MIN(K$3-$O$2,$Q$2)/$Q$2)) -> 3462.2926 | L15: =K15*(1+IF(L$3<=$O$2,$D15,$D15-($D15-$I$6)*MIN(L$3-$O$2,$Q$2)/$Q$2)) -> 3583.2954 | M15: =L15*(1+IF(M$3<=$O$2,$D15,$D15-($D15-$I$6)*MIN(M$3-$O$2,$Q$2)/$Q$2)) -> 3696.6149 | N15: =M15*(1+IF(N$3<=$O$2,$D15,$D15-($D15-$I$6)*MIN(N$3-$O$2,$Q$2)/$Q$2)) -> 3801.2291 | O15: =SUMPRODUCT(E15:N15,1/(1+$F$6)^$E$3:$N$3)*$E$2 -> 3982.5378 | P15: =N15*$E$2*(1+$I$6)/($F$6-$I$6)/(1+$F$6)^$N$3 -> 4818.2581 | Q15: =O15+P15 -> 8800.7959 | R15: =Q15-$G$2+$I$2 -> 7424.5959 | S15: =R15/$K$2 -> 197.93644 | T15: =S15-$M$2 -> -6.5423651
A16: 9 | B16: =IF(T15>0,B15,D15) -> 0.044921875 | C16: =IF(T15>0,D15,C15) -> 0.05078125 | D16: =(B16+C16)/2 -> 0.047851562 | E16: =$C$2*(1+IF(E$3<=$O$2,$D16,$D16-($D16-$I$6)*MIN(E$3-$O$2,$Q$2)/$Q$2)) -> 2692.9785 | F16: =E16*(1+IF(F$3<=$O$2,$D16,$D16-($D16-$I$6)*MIN(F$3-$O$2,$Q$2)/$Q$2)) -> 2821.8417 | G16: =F16*(1+IF(G$3<=$O$2,$D16,$D16-($D16-$I$6)*MIN(G$3-$O$2,$Q$2)/$Q$2)) -> 2956.8713 | H16: =G16*(1+IF(H$3<=$O$2,$D16,$D16-($D16-$I$6)*MIN(H$3-$O$2,$Q$2)/$Q$2)) -> 3098.3622 | I16: =H16*(1+IF(I$3<=$O$2,$D16,$D16-($D16-$I$6)*MIN(I$3-$O$2,$Q$2)/$Q$2)) -> 3246.6237 | J16: =I16*(1+IF(J$3<=$O$2,$D16,$D16-($D16-$I$6)*MIN(J$3-$O$2,$Q$2)/$Q$2)) -> 3389.2844 | K16: =J16*(1+IF(K$3<=$O$2,$D16,$D16-($D16-$I$6)*MIN(K$3-$O$2,$Q$2)/$Q$2)) -> 3524.9606 | L16: =K16*(1+IF(L$3<=$O$2,$D16,$D16-($D16-$I$6)*MIN(L$3-$O$2,$Q$2)/$Q$2)) -> 3652.2844 | M16: =L16*(1+IF(M$3<=$O$2,$D16,$D16-($D16-$I$6)*MIN(M$3-$O$2,$Q$2)/$Q$2)) -> 3769.9256 | N16: =M16*(1+IF(N$3<=$O$2,$D16,$D16-($D16-$I$6)*MIN(N$3-$O$2,$Q$2)/$Q$2)) -> 3876.6145 | O16: =SUMPRODUCT(E16:N16,1/(1+$F$6)^$E$3:$N$3)*$E$2 -> 4033.2405 | P16: =N16*$E$2*(1+$I$6)/($F$6-$I$6)/(1+$F$6)^$N$3 -> 4913.8131 | Q16: =O16+P16 -> 8947.0536 | R16: =Q16-$G$2+$I$2 -> 7570.8536 | S16: =R16/$K$2 -> 201.83561 | T16: =S16-$M$2 -> -2.6431992
A17: 10 | B17: =IF(T16>0,B16,D16) -> 0.047851562 | C17: =IF(T16>0,D16,C16) -> 0.05078125 | D17: =(B17+C17)/2 -> 0.049316406 | E17: =$C$2*(1+IF(E$3<=$O$2,$D17,$D17-($D17-$I$6)*MIN(E$3-$O$2,$Q$2)/$Q$2)) -> 2696.7432 | F17: =E17*(1+IF(F$3<=$O$2,$D17,$D17-($D17-$I$6)*MIN(F$3-$O$2,$Q$2)/$Q$2)) -> 2829.7368 | G17: =F17*(1+IF(G$3<=$O$2,$D17,$D17-($D17-$I$6)*MIN(G$3-$O$2,$Q$2)/$Q$2)) -> 2969.2893 | H17: =G17*(1+IF(H$3<=$O$2,$D17,$D17-($D17-$I$6)*MIN(H$3-$O$2,$Q$2)/$Q$2)) -> 3115.724 | I17: =H17*(1+IF(I$3<=$O$2,$D17,$D17-($D17-$I$6)*MIN(I$3-$O$2,$Q$2)/$Q$2)) -> 3269.3803 | J17: =I17*(1+IF(J$3<=$O$2,$D17,$D17-($D17-$I$6)*MIN(J$3-$O$2,$Q$2)/$Q$2)) -> 3416.8722 | K17: =J17*(1+IF(K$3<=$O$2,$D17,$D17-($D17-$I$6)*MIN(K$3-$O$2,$Q$2)/$Q$2)) -> 3556.656 | L17: =K17*(1+IF(L$3<=$O$2,$D17,$D17-($D17-$I$6)*MIN(L$3-$O$2,$Q$2)/$Q$2)) -> 3687.2086 | M17: =L17*(1+IF(M$3<=$O$2,$D17,$D17-($D17-$I$6)*MIN(M$3-$O$2,$Q$2)/$Q$2)) -> 3807.0549 | N17: =M17*(1+IF(N$3<=$O$2,$D17,$D17-($D17-$I$6)*MIN(N$3-$O$2,$Q$2)/$Q$2)) -> 3914.7946 | O17: =SUMPRODUCT(E17:N17,1/(1+$F$6)^$E$3:$N$3)*$E$2 -> 4058.8363 | P17: =N17*$E$2*(1+$I$6)/($F$6-$I$6)/(1+$F$6)^$N$3 -> 4962.2084 | Q17: =O17+P17 -> 9021.0446 | R17: =Q17-$G$2+$I$2 -> 7644.8446 | S17: =R17/$K$2 -> 203.80817 | T17: =S17-$M$2 -> -0.67063088
A18: 11 | B18: =IF(T17>0,B17,D17) -> 0.049316406 | C18: =IF(T17>0,D17,C17) -> 0.05078125 | D18: =(B18+C18)/2 -> 0.050048828 | E18: =$C$2*(1+IF(E$3<=$O$2,$D18,$D18-($D18-$I$6)*MIN(E$3-$O$2,$Q$2)/$Q$2)) -> 2698.6255 | F18: =E18*(1+IF(F$3<=$O$2,$D18,$D18-($D18-$I$6)*MIN(F$3-$O$2,$Q$2)/$Q$2)) -> 2833.6885 | G18: =F18*(1+IF(G$3<=$O$2,$D18,$D18-($D18-$I$6)*MIN(G$3-$O$2,$Q$2)/$Q$2)) -> 2975.5113 | H18: =G18*(1+IF(H$3<=$O$2,$D18,$D18-($D18-$I$6)*MIN(H$3-$O$2,$Q$2)/$Q$2)) -> 3124.4322 | I18: =H18*(1+IF(I$3<=$O$2,$D18,$D18-($D18-$I$6)*MIN(I$3-$O$2,$Q$2)/$Q$2)) -> 3280.8063 | J18: =I18*(1+IF(J$3<=$O$2,$D18,$D18-($D18-$I$6)*MIN(J$3-$O$2,$Q$2)/$Q$2)) -> 3430.7361 | K18: =J18*(1+IF(K$3<=$O$2,$D18,$D18-($D18-$I$6)*MIN(K$3-$O$2,$Q$2)/$Q$2)) -> 3572.5946 | L18: =K18*(1+IF(L$3<=$O$2,$D18,$D18-($D18-$I$6)*MIN(L$3-$O$2,$Q$2)/$Q$2)) -> 3704.779 | M18: =L18*(1+IF(M$3<=$O$2,$D18,$D18-($D18-$I$6)*MIN(M$3-$O$2,$Q$2)/$Q$2)) -> 3825.7391 | N18: =M18*(1+IF(N$3<=$O$2,$D18,$D18-($D18-$I$6)*MIN(N$3-$O$2,$Q$2)/$Q$2)) -> 3934.0076 | O18: =SUMPRODUCT(E18:N18,1/(1+$F$6)^$E$3:$N$3)*$E$2 -> 4071.6957 | P18: =N18*$E$2*(1+$I$6)/($F$6-$I$6)/(1+$F$6)^$N$3 -> 4986.5618 | Q18: =O18+P18 -> 9058.2575 | R18: =Q18-$G$2+$I$2 -> 7682.0575 | S18: =R18/$K$2 -> 204.80025 | T18: =S18-$M$2 -> 0.3214465
A19: 12 | B19: =IF(T18>0,B18,D18) -> 0.049316406 | C19: =IF(T18>0,D18,C18) -> 0.050048828 | D19: =(B19+C19)/2 -> 0.049682617 | E19: =$C$2*(1+IF(E$3<=$O$2,$D19,$D19-($D19-$I$6)*MIN(E$3-$O$2,$Q$2)/$Q$2)) -> 2697.6843 | F19: =E19*(1+IF(F$3<=$O$2,$D19,$D19-($D19-$I$6)*MIN(F$3-$O$2,$Q$2)/$Q$2)) -> 2831.7123 | G19: =F19*(1+IF(G$3<=$O$2,$D19,$D19-($D19-$I$6)*MIN(G$3-$O$2,$Q$2)/$Q$2)) -> 2972.3992 | H19: =G19*(1+IF(H$3<=$O$2,$D19,$D19-($D19-$I$6)*MIN(H$3-$O$2,$Q$2)/$Q$2)) -> 3120.0758 | I19: =H19*(1+IF(I$3<=$O$2,$D19,$D19-($D19-$I$6)*MIN(I$3-$O$2,$Q$2)/$Q$2)) -> 3275.0893 | J19: =I19*(1+IF(J$3<=$O$2,$D19,$D19-($D19-$I$6)*MIN(J$3-$O$2,$Q$2)/$Q$2)) -> 3423.7983 | K19: =J19*(1+IF(K$3<=$O$2,$D19,$D19-($D19-$I$6)*MIN(K$3-$O$2,$Q$2)/$Q$2)) -> 3564.6177 | L19: =K19*(1+IF(L$3<=$O$2,$D19,$D19-($D19-$I$6)*MIN(L$3-$O$2,$Q$2)/$Q$2)) -> 3695.9847 | M19: =L19*(1+IF(M$3<=$O$2,$D19,$D19-($D19-$I$6)*MIN(M$3-$O$2,$Q$2)/$Q$2)) -> 3816.3871 | N19: =M19*(1+IF(N$3<=$O$2,$D19,$D19-($D19-$I$6)*MIN(N$3-$O$2,$Q$2)/$Q$2)) -> 3924.3908 | O19: =SUMPRODUCT(E19:N19,1/(1+$F$6)^$E$3:$N$3)*$E$2 -> 4065.2608 | P19: =N19*$E$2*(1+$I$6)/($F$6-$I$6)/(1+$F$6)^$N$3 -> 4974.3721 | Q19: =O19+P19 -> 9039.6329 | R19: =Q19-$G$2+$I$2 -> 7663.4329 | S19: =R19/$K$2 -> 204.30373 | T19: =S19-$M$2 -> -0.17507636
A20: 13 | B20: =IF(T19>0,B19,D19) -> 0.049682617 | C20: =IF(T19>0,D19,C19) -> 0.050048828 | D20: =(B20+C20)/2 -> 0.049865723 | E20: =$C$2*(1+IF(E$3<=$O$2,$D20,$D20-($D20-$I$6)*MIN(E$3-$O$2,$Q$2)/$Q$2)) -> 2698.1549 | F20: =E20*(1+IF(F$3<=$O$2,$D20,$D20-($D20-$I$6)*MIN(F$3-$O$2,$Q$2)/$Q$2)) -> 2832.7004 | G20: =F20*(1+IF(G$3<=$O$2,$D20,$D20-($D20-$I$6)*MIN(G$3-$O$2,$Q$2)/$Q$2)) -> 2973.955 | H20: =G20*(1+IF(H$3<=$O$2,$D20,$D20-($D20-$I$6)*MIN(H$3-$O$2,$Q$2)/$Q$2)) -> 3122.2534 | I20: =H20*(1+IF(I$3<=$O$2,$D20,$D20-($D20-$I$6)*MIN(I$3-$O$2,$Q$2)/$Q$2)) -> 3277.9468 | J20: =I20*(1+IF(J$3<=$O$2,$D20,$D20-($D20-$I$6)*MIN(J$3-$O$2,$Q$2)/$Q$2)) -> 3427.2658 | K20: =J20*(1+IF(K$3<=$O$2,$D20,$D20-($D20-$I$6)*MIN(K$3-$O$2,$Q$2)/$Q$2)) -> 3568.6043 | L20: =K20*(1+IF(L$3<=$O$2,$D20,$D20-($D20-$I$6)*MIN(L$3-$O$2,$Q$2)/$Q$2)) -> 3700.3796 | M20: =L20*(1+IF(M$3<=$O$2,$D20,$D20-($D20-$I$6)*MIN(M$3-$O$2,$Q$2)/$Q$2)) -> 3821.0606 | N20: =M20*(1+IF(N$3<=$O$2,$D20,$D20-($D20-$I$6)*MIN(N$3-$O$2,$Q$2)/$Q$2)) -> 3929.1966 | O20: =SUMPRODUCT(E20:N20,1/(1+$F$6)^$E$3:$N$3)*$E$2 -> 4068.477 | P20: =N20*$E$2*(1+$I$6)/($F$6-$I$6)/(1+$F$6)^$N$3 -> 4980.4637 | Q20: =O20+P20 -> 9048.9406 | R20: =Q20-$G$2+$I$2 -> 7672.7406 | S20: =R20/$K$2 -> 204.55187 | T20: =S20-$M$2 -> 0.073063926
... A47: 40 | B47: =IF(T46>0,B46,D46) -> 0.049811827 | C47: =IF(T46>0,D46,C46) -> 0.049811827 | D47: =(B47+C47)/2 -> 0.049811827 | E47: =$C$2*(1+IF(E$3<=$O$2,$D47,$D47-($D47-$I$6)*MIN(E$3-$O$2,$Q$2)/$Q$2)) -> 2698.0164 | F47: =E47*(1+IF(F$3<=$O$2,$D47,$D47-($D47-$I$6)*MIN(F$3-$O$2,$Q$2)/$Q$2)) -> 2832.4095 | G47: =F47*(1+IF(G$3<=$O$2,$D47,$D47-($D47-$I$6)*MIN(G$3-$O$2,$Q$2)/$Q$2)) -> 2973.497 | H47: =G47*(1+IF(H$3<=$O$2,$D47,$D47-($D47-$I$6)*MIN(H$3-$O$2,$Q$2)/$Q$2)) -> 3121.6123 | I47: =H47*(1+IF(I$3<=$O$2,$D47,$D47-($D47-$I$6)*MIN(I$3-$O$2,$Q$2)/$Q$2)) -> 3277.1055 | J47: =I47*(1+IF(J$3<=$O$2,$D47,$D47-($D47-$I$6)*MIN(J$3-$O$2,$Q$2)/$Q$2)) -> 3426.2448 | K47: =J47*(1+IF(K$3<=$O$2,$D47,$D47-($D47-$I$6)*MIN(K$3-$O$2,$Q$2)/$Q$2)) -> 3567.4304 | L47: =K47*(1+IF(L$3<=$O$2,$D47,$D47-($D47-$I$6)*MIN(L$3-$O$2,$Q$2)/$Q$2)) -> 3699.0855 | M47: =L47*(1+IF(M$3<=$O$2,$D47,$D47-($D47-$I$6)*MIN(M$3-$O$2,$Q$2)/$Q$2)) -> 3819.6844 | N47: =M47*(1+IF(N$3<=$O$2,$D47,$D47-($D47-$I$6)*MIN(N$3-$O$2,$Q$2)/$Q$2)) -> 3927.7815 | O47: =SUMPRODUCT(E47:N47,1/(1+$F$6)^$E$3:$N$3)*$E$2 -> 4067.53 | P47: =N47*$E$2*(1+$I$6)/($F$6-$I$6)/(1+$F$6)^$N$3 -> 4978.67 | Q47: =O47+P47 -> 9046.2 | R47: =Q47-$G$2+$I$2 -> 7670 | S47: =R47/$K$2 -> 204.47881 | T47: =S47-$M$2 -> -1.690637e-09
A49: Grid block 2: row 1, column 1 of table A (24 steps) | E49: WACC | F49: =Sensitivity!$B$10 -> 0.084183338 | G49: Terminal growth | I49: =Sensitivity!$C$9 -> 0.0183
A50: Step | B50: Low | C50: High | D50: Mid | E50: Rev Y1 | F50: Rev Y2 | G50: Rev Y3 | H50: Rev Y4 | I50: Rev Y5 | J50: Rev Y6 | K50: Rev Y7 | L50: Rev Y8 | M50: Rev Y9 | N50: Rev Y10 | O50: PV of FCF | P50: PV of TV | Q50: EV | R50: Equity | S50: Per share | T50: Value - price
A51: 1 | B51: -0.5 | C51: 1 | D51: =(B51+C51)/2 -> 0.25 | E51: =$C$2*(1+IF(E$3<=$O$2,$D51,$D51-($D51-$I$49)*MIN(E$3-$O$2,$Q$2)/$Q$2)) -> 3212.5 | F51: =E51*(1+IF(F$3<=$O$2,$D51,$D51-($D51-$I$49)*MIN(F$3-$O$2,$Q$2)/$Q$2)) -> 4015.625 | G51: =F51*(1+IF(G$3<=$O$2,$D51,$D51-($D51-$I$49)*MIN(G$3-$O$2,$Q$2)/$Q$2)) -> 5019.5312 | H51: =G51*(1+IF(H$3<=$O$2,$D51,$D51-($D51-$I$49)*MIN(H$3-$O$2,$Q$2)/$Q$2)) -> 6274.4141 | I51: =H51*(1+IF(I$3<=$O$2,$D51,$D51-($D51-$I$49)*MIN(I$3-$O$2,$Q$2)/$Q$2)) -> 7843.0176 | J51: =I51*(1+IF(J$3<=$O$2,$D51,$D51-($D51-$I$49)*MIN(J$3-$O$2,$Q$2)/$Q$2)) -> 9440.3265 | K51: =J51*(1+IF(K$3<=$O$2,$D51,$D51-($D51-$I$49)*MIN(K$3-$O$2,$Q$2)/$Q$2)) -> 10925.479 | L51: =K51*(1+IF(L$3<=$O$2,$D51,$D51-($D51-$I$49)*MIN(L$3-$O$2,$Q$2)/$Q$2)) -> 12137.988 | M51: =L51*(1+IF(M$3<=$O$2,$D51,$D51-($D51-$I$49)*MIN(M$3-$O$2,$Q$2)/$Q$2)) -> 12922.588 | N51: =M51*(1+IF(N$3<=$O$2,$D51,$D51-($D51-$I$49)*MIN(N$3-$O$2,$Q$2)/$Q$2)) -> 13159.071 | O51: =SUMPRODUCT(E51:N51,1/(1+$F$49)^$E$3:$N$3)*$E$2 -> 10103.721 | P51: =N51*$E$2*(1+$I$49)/($F$49-$I$49)/(1+$F$49)^$N$3 -> 18105.93 | Q51: =O51+P51 -> 28209.652 | R51: =Q51-$G$2+$I$2 -> 26833.452 | S51: =R51/$K$2 -> 715.36795 | T51: =S51-$M$2 -> 510.88914
A52: 2 | B52: =IF(T51>0,B51,D51) -> -0.5 | C52: =IF(T51>0,D51,C51) -> 0.25 | D52: =(B52+C52)/2 -> -0.125 | E52: =$C$2*(1+IF(E$3<=$O$2,$D52,$D52-($D52-$I$49)*MIN(E$3-$O$2,$Q$2)/$Q$2)) -> 2248.75 | F52: =E52*(1+IF(F$3<=$O$2,$D52,$D52-($D52-$I$49)*MIN(F$3-$O$2,$Q$2)/$Q$2)) -> 1967.6562 | G52: =F52*(1+IF(G$3<=$O$2,$D52,$D52-($D52-$I$49)*MIN(G$3-$O$2,$Q$2)/$Q$2)) -> 1721.6992 | H52: =G52*(1+IF(H$3<=$O$2,$D52,$D52-($D52-$I$49)*MIN(H$3-$O$2,$Q$2)/$Q$2)) -> 1506.4868 | I52: =H52*(1+IF(I$3<=$O$2,$D52,$D52-($D52-$I$49)*MIN(I$3-$O$2,$Q$2)/$Q$2)) -> 1318.176 | J52: =I52*(1+IF(J$3<=$O$2,$D52,$D52-($D52-$I$49)*MIN(J$3-$O$2,$Q$2)/$Q$2)) -> 1191.1829 | K52: =J52*(1+IF(K$3<=$O$2,$D52,$D52-($D52-$I$49)*MIN(K$3-$O$2,$Q$2)/$Q$2)) -> 1110.5636 | L52: =K52*(1+IF(L$3<=$O$2,$D52,$D52-($D52-$I$49)*MIN(L$3-$O$2,$Q$2)/$Q$2)) -> 1067.2294 | M52: =L52*(1+IF(M$3<=$O$2,$D52,$D52-($D52-$I$49)*MIN(M$3-$O$2,$Q$2)/$Q$2)) -> 1056.1729 | N52: =M52*(1+IF(N$3<=$O$2,$D52,$D52-($D52-$I$49)*MIN(N$3-$O$2,$Q$2)/$Q$2)) -> 1075.5009 | O52: =SUMPRODUCT(E52:N52,1/(1+$F$49)^$E$3:$N$3)*$E$2 -> 1994.0849 | P52: =N52*$E$2*(1+$I$49)/($F$49-$I$49)/(1+$F$49)^$N$3 -> 1479.8115 | Q52: =O52+P52 -> 3473.8964 | R52: =Q52-$G$2+$I$2 -> 2097.6964 | S52: =R52/$K$2 -> 55.923658 | T52: =S52-$M$2 -> -148.55515
A53: 3 | B53: =IF(T52>0,B52,D52) -> -0.125 | C53: =IF(T52>0,D52,C52) -> 0.25 | D53: =(B53+C53)/2 -> 0.0625 | E53: =$C$2*(1+IF(E$3<=$O$2,$D53,$D53-($D53-$I$49)*MIN(E$3-$O$2,$Q$2)/$Q$2)) -> 2730.625 | F53: =E53*(1+IF(F$3<=$O$2,$D53,$D53-($D53-$I$49)*MIN(F$3-$O$2,$Q$2)/$Q$2)) -> 2901.2891 | G53: =F53*(1+IF(G$3<=$O$2,$D53,$D53-($D53-$I$49)*MIN(G$3-$O$2,$Q$2)/$Q$2)) -> 3082.6196 | H53: =G53*(1+IF(H$3<=$O$2,$D53,$D53-($D53-$I$49)*MIN(H$3-$O$2,$Q$2)/$Q$2)) -> 3275.2834 | I53: =H53*(1+IF(I$3<=$O$2,$D53,$D53-($D53-$I$49)*MIN(I$3-$O$2,$Q$2)/$Q$2)) -> 3479.9886 | J53: =I53*(1+IF(J$3<=$O$2,$D53,$D53-($D53-$I$49)*MIN(J$3-$O$2,$Q$2)/$Q$2)) -> 3666.7248 | K53: =J53*(1+IF(K$3<=$O$2,$D53,$D53-($D53-$I$49)*MIN(K$3-$O$2,$Q$2)/$Q$2)) -> 3831.0674 | L53: =K53*(1+IF(L$3<=$O$2,$D53,$D53-($D53-$I$49)*MIN(L$3-$O$2,$Q$2)/$Q$2)) -> 3968.9092 | M53: =L53*(1+IF(M$3<=$O$2,$D53,$D53-($D53-$I$49)*MIN(M$3-$O$2,$Q$2)/$Q$2)) -> 4076.6254 | N53: =M53*(1+IF(N$3<=$O$2,$D53,$D53-($D53-$I$49)*MIN(N$3-$O$2,$Q$2)/$Q$2)) -> 4151.2276 | O53: =SUMPRODUCT(E53:N53,1/(1+$F$49)^$E$3:$N$3)*$E$2 -> 4480.9877 | P53: =N53*$E$2*(1+$I$49)/($F$49-$I$49)/(1+$F$49)^$N$3 -> 5711.789 | Q53: =O53+P53 -> 10192.777 | R53: =Q53-$G$2+$I$2 -> 8816.5767 | S53: =R53/$K$2 -> 235.04603 | T53: =S53-$M$2 -> 30.567227
A54: 4 | B54: =IF(T53>0,B53,D53) -> -0.125 | C54: =IF(T53>0,D53,C53) -> 0.0625 | D54: =(B54+C54)/2 -> -0.03125 | E54: =$C$2*(1+IF(E$3<=$O$2,$D54,$D54-($D54-$I$49)*MIN(E$3-$O$2,$Q$2)/$Q$2)) -> 2489.6875 | F54: =E54*(1+IF(F$3<=$O$2,$D54,$D54-($D54-$I$49)*MIN(F$3-$O$2,$Q$2)/$Q$2)) -> 2411.8848 | G54: =F54*(1+IF(G$3<=$O$2,$D54,$D54-($D54-$I$49)*MIN(G$3-$O$2,$Q$2)/$Q$2)) -> 2336.5134 | H54: =G54*(1+IF(H$3<=$O$2,$D54,$D54-($D54-$I$49)*MIN(H$3-$O$2,$Q$2)/$Q$2)) -> 2263.4973 | I54: =H54*(1+IF(I$3<=$O$2,$D54,$D54-($D54-$I$49)*MIN(I$3-$O$2,$Q$2)/$Q$2)) -> 2192.763 | J54: =I54*(1+IF(J$3<=$O$2,$D54,$D54-($D54-$I$49)*MIN(J$3-$O$2,$Q$2)/$Q$2)) -> 2145.9695 | K54: =J54*(1+IF(K$3<=$O$2,$D54,$D54-($D54-$I$49)*MIN(K$3-$O$2,$Q$2)/$Q$2)) -> 2121.441 | L54: =K54*(1+IF(L$3<=$O$2,$D54,$D54-($D54-$I$49)*MIN(L$3-$O$2,$Q$2)/$Q$2)) -> 2118.2164 | M54: =L54*(1+IF(M$3<=$O$2,$D54,$D54-($D54-$I$49)*MIN(M$3-$O$2,$Q$2)/$Q$2)) -> 2135.9883 | N54: =M54*(1+IF(N$3<=$O$2,$D54,$D54-($D54-$I$49)*MIN(N$3-$O$2,$Q$2)/$Q$2)) -> 2175.0769 | O54: =SUMPRODUCT(E54:N54,1/(1+$F$49)^$E$3:$N$3)*$E$2 -> 2980.6328 | P54: =N54*$E$2*(1+$I$49)/($F$49-$I$49)/(1+$F$49)^$N$3 -> 2992.7485 | Q54: =O54+P54 -> 5973.3813 | R54: =Q54-$G$2+$I$2 -> 4597.1813 | S54: =R54/$K$2 -> 122.55882 | T54: =S54-$M$2 -> -81.919988
A55: 5 | B55: =IF(T54>0,B54,D54) -> -0.03125 | C55: =IF(T54>0,D54,C54) -> 0.0625 | D55: =(B55+C55)/2 -> 0.015625 | E55: =$C$2*(1+IF(E$3<=$O$2,$D55,$D55-($D55-$I$49)*MIN(E$3-$O$2,$Q$2)/$Q$2)) -> 2610.1562 | F55: =E55*(1+IF(F$3<=$O$2,$D55,$D55-($D55-$I$49)*MIN(F$3-$O$2,$Q$2)/$Q$2)) -> 2650.9399 | G55: =F55*(1+IF(G$3<=$O$2,$D55,$D55-($D55-$I$49)*MIN(G$3-$O$2,$Q$2)/$Q$2)) -> 2692.3609 | H55: =G55*(1+IF(H$3<=$O$2,$D55,$D55-($D55-$I$49)*MIN(H$3-$O$2,$Q$2)/$Q$2)) -> 2734.429 | I55: =H55*(1+IF(I$3<=$O$2,$D55,$D55-($D55-$I$49)*MIN(I$3-$O$2,$Q$2)/$Q$2)) -> 2777.1545 | J55: =I55*(1+IF(J$3<=$O$2,$D55,$D55-($D55-$I$49)*MIN(J$3-$O$2,$Q$2)/$Q$2)) -> 2822.0333 | K55: =J55*(1+IF(K$3<=$O$2,$D55,$D55-($D55-$I$49)*MIN(K$3-$O$2,$Q$2)/$Q$2)) -> 2869.1471 | L55: =K55*(1+IF(L$3<=$O$2,$D55,$D55-($D55-$I$49)*MIN(L$3-$O$2,$Q$2)/$Q$2)) -> 2918.5825 | M55: =L55*(1+IF(M$3<=$O$2,$D55,$D55-($D55-$I$49)*MIN(M$3-$O$2,$Q$2)/$Q$2)) -> 2970.4312 | N55: =M55*(1+IF(N$3<=$O$2,$D55,$D55-($D55-$I$49)*MIN(N$3-$O$2,$Q$2)/$Q$2)) -> 3024.79 | O55: =SUMPRODUCT(E55:N55,1/(1+$F$49)^$E$3:$N$3)*$E$2 -> 3653.17 | P55: =N55*$E$2*(1+$I$49)/($F$49-$I$49)/(1+$F$49)^$N$3 -> 4161.8924 | Q55: =O55+P55 -> 7815.0624 | R55: =Q55-$G$2+$I$2 -> 6438.8624 | S55: =R55/$K$2 -> 171.65722 | T55: =S55-$M$2 -> -32.821584
A56: 6 | B56: =IF(T55>0,B55,D55) -> 0.015625 | C56: =IF(T55>0,D55,C55) -> 0.0625 | D56: =(B56+C56)/2 -> 0.0390625 | E56: =$C$2*(1+IF(E$3<=$O$2,$D56,$D56-($D56-$I$49)*MIN(E$3-$O$2,$Q$2)/$Q$2)) -> 2670.3906 | F56: =E56*(1+IF(F$3<=$O$2,$D56,$D56-($D56-$I$49)*MIN(F$3-$O$2,$Q$2)/$Q$2)) -> 2774.7028 | G56: =F56*(1+IF(G$3<=$O$2,$D56,$D56-($D56-$I$49)*MIN(G$3-$O$2,$Q$2)/$Q$2)) -> 2883.0896 | H56: =G56*(1+IF(H$3<=$O$2,$D56,$D56-($D56-$I$49)*MIN(H$3-$O$2,$Q$2)/$Q$2)) -> 2995.7103 | I56: =H56*(1+IF(I$3<=$O$2,$D56,$D56-($D56-$I$49)*MIN(I$3-$O$2,$Q$2)/$Q$2)) -> 3112.7302 | J56: =I56*(1+IF(J$3<=$O$2,$D56,$D56-($D56-$I$49)*MIN(J$3-$O$2,$Q$2)/$Q$2)) -> 3221.3956 | K56: =J56*(1+IF(K$3<=$O$2,$D56,$D56-($D56-$I$49)*MIN(K$3-$O$2,$Q$2)/$Q$2)) -> 3320.4777 | L56: =K56*(1+IF(L$3<=$O$2,$D56,$D56-($D56-$I$49)*MIN(L$3-$O$2,$Q$2)/$Q$2)) -> 3408.819 | M56: =L56*(1+IF(M$3<=$O$2,$D56,$D56-($D56-$I$49)*MIN(M$3-$O$2,$Q$2)/$Q$2)) -> 3485.3555 | N56: =M56*(1+IF(N$3<=$O$2,$D56,$D56-($D56-$I$49)*MIN(N$3-$O$2,$Q$2)/$Q$2)) -> 3549.1375 | O56: =SUMPRODUCT(E56:N56,1/(1+$F$49)^$E$3:$N$3)*$E$2 -> 4045.7264 | P56: =N56*$E$2*(1+$I$49)/($F$49-$I$49)/(1+$F$49)^$N$3 -> 4883.3566 | Q56: =O56+P56 -> 8929.083 | R56: =Q56-$G$2+$I$2 -> 7552.883 | S56: =R56/$K$2 -> 201.35652 | T56: =S56-$M$2 -> -3.1222882
A57: 7 | B57: =IF(T56>0,B56,D56) -> 0.0390625 | C57: =IF(T56>0,D56,C56) -> 0.0625 | D57: =(B57+C57)/2 -> 0.05078125 | E57: =$C$2*(1+IF(E$3<=$O$2,$D57,$D57-($D57-$I$49)*MIN(E$3-$O$2,$Q$2)/$Q$2)) -> 2700.5078 | F57: =E57*(1+IF(F$3<=$O$2,$D57,$D57-($D57-$I$49)*MIN(F$3-$O$2,$Q$2)/$Q$2)) -> 2837.643 | G57: =F57*(1+IF(G$3<=$O$2,$D57,$D57-($D57-$I$49)*MIN(G$3-$O$2,$Q$2)/$Q$2)) -> 2981.742 | H57: =G57*(1+IF(H$3<=$O$2,$D57,$D57-($D57-$I$49)*MIN(H$3-$O$2,$Q$2)/$Q$2)) -> 3133.1586 | I57: =H57*(1+IF(I$3<=$O$2,$D57,$D57-($D57-$I$49)*MIN(I$3-$O$2,$Q$2)/$Q$2)) -> 3292.2643 | J57: =I57*(1+IF(J$3<=$O$2,$D57,$D57-($D57-$I$49)*MIN(J$3-$O$2,$Q$2)/$Q$2)) -> 3438.0623 | K57: =J57*(1+IF(K$3<=$O$2,$D57,$D57-($D57-$I$49)*MIN(K$3-$O$2,$Q$2)/$Q$2)) -> 3567.9823 | L57: =K57*(1+IF(L$3<=$O$2,$D57,$D57-($D57-$I$49)*MIN(L$3-$O$2,$Q$2)/$Q$2)) -> 3679.6334 | M57: =L57*(1+IF(M$3<=$O$2,$D57,$D57-($D57-$I$49)*MIN(M$3-$O$2,$Q$2)/$Q$2)) -> 3770.8745 | N57: =M57*(1+IF(N$3<=$O$2,$D57,$D57-($D57-$I$49)*MIN(N$3-$O$2,$Q$2)/$Q$2)) -> 3839.8815 | O57: =SUMPRODUCT(E57:N57,1/(1+$F$49)^$E$3:$N$3)*$E$2 -> 4257.7577 | P57: =N57*$E$2*(1+$I$49)/($F$49-$I$49)/(1+$F$49)^$N$3 -> 5283.3993 | Q57: =O57+P57 -> 9541.157 | R57: =Q57-$G$2+$I$2 -> 8164.957 | S57: =R57/$K$2 -> 217.67414 | T57: =S57-$M$2 -> 13.195335
A58: 8 | B58: =IF(T57>0,B57,D57) -> 0.0390625 | C58: =IF(T57>0,D57,C57) -> 0.05078125 | D58: =(B58+C58)/2 -> 0.044921875 | E58: =$C$2*(1+IF(E$3<=$O$2,$D58,$D58-($D58-$I$49)*MIN(E$3-$O$2,$Q$2)/$Q$2)) -> 2685.4492 | F58: =E58*(1+IF(F$3<=$O$2,$D58,$D58-($D58-$I$49)*MIN(F$3-$O$2,$Q$2)/$Q$2)) -> 2806.0846 | G58: =F58*(1+IF(G$3<=$O$2,$D58,$D58-($D58-$I$49)*MIN(G$3-$O$2,$Q$2)/$Q$2)) -> 2932.1392 | H58: =G58*(1+IF(H$3<=$O$2,$D58,$D58-($D58-$I$49)*MIN(H$3-$O$2,$Q$2)/$Q$2)) -> 3063.8564 | I58: =H58*(1+IF(I$3<=$O$2,$D58,$D58-($D58-$I$49)*MIN(I$3-$O$2,$Q$2)/$Q$2)) -> 3201.4906 | J58: =I58*(1+IF(J$3<=$O$2,$D58,$D58-($D58-$I$49)*MIN(J$3-$O$2,$Q$2)/$Q$2)) -> 3328.2616 | K58: =J58*(1+IF(K$3<=$O$2,$D58,$D58-($D58-$I$49)*MIN(K$3-$O$2,$Q$2)/$Q$2)) -> 3442.3315 | L58: =K58*(1+IF(L$3<=$O$2,$D58,$D58-($D58-$I$49)*MIN(L$3-$O$2,$Q$2)/$Q$2)) -> 3541.9827 | M58: =L58*(1+IF(M$3<=$O$2,$D58,$D58-($D58-$I$49)*MIN(M$3-$O$2,$Q$2)/$Q$2)) -> 3625.6599 | N58: =M58*(1+IF(N$3<=$O$2,$D58,$D58-($D58-$I$49)*MIN(N$3-$O$2,$Q$2)/$Q$2)) -> 3692.0094 | O58: =SUMPRODUCT(E58:N58,1/(1+$F$49)^$E$3:$N$3)*$E$2 -> 4150.3757 | P58: =N58*$E$2*(1+$I$49)/($F$49-$I$49)/(1+$F$49)^$N$3 -> 5079.938 | Q58: =O58+P58 -> 9230.3137 | R58: =Q58-$G$2+$I$2 -> 7854.1137 | S58: =R58/$K$2 -> 209.3872 | T58: =S58-$M$2 -> 4.9083904
A59: 9 | B59: =IF(T58>0,B58,D58) -> 0.0390625 | C59: =IF(T58>0,D58,C58) -> 0.044921875 | D59: =(B59+C59)/2 -> 0.041992188 | E59: =$C$2*(1+IF(E$3<=$O$2,$D59,$D59-($D59-$I$49)*MIN(E$3-$O$2,$Q$2)/$Q$2)) -> 2677.9199 | F59: =E59*(1+IF(F$3<=$O$2,$D59,$D59-($D59-$I$49)*MIN(F$3-$O$2,$Q$2)/$Q$2)) -> 2790.3716 | G59: =F59*(1+IF(G$3<=$O$2,$D59,$D59-($D59-$I$49)*MIN(G$3-$O$2,$Q$2)/$Q$2)) -> 2907.5454 | H59: =G59*(1+IF(H$3<=$O$2,$D59,$D59-($D59-$I$49)*MIN(H$3-$O$2,$Q$2)/$Q$2)) -> 3029.6396 | I59: =H59*(1+IF(I$3<=$O$2,$D59,$D59-($D59-$I$49)*MIN(I$3-$O$2,$Q$2)/$Q$2)) -> 3156.8608 | J59: =I59*(1+IF(J$3<=$O$2,$D59,$D59-($D59-$I$49)*MIN(J$3-$O$2,$Q$2)/$Q$2)) -> 3274.4657 | K59: =J59*(1+IF(K$3<=$O$2,$D59,$D59-($D59-$I$49)*MIN(K$3-$O$2,$Q$2)/$Q$2)) -> 3380.936 | L59: =K59*(1+IF(L$3<=$O$2,$D59,$D59-($D59-$I$49)*MIN(L$3-$O$2,$Q$2)/$Q$2)) -> 3474.8479 | M59: =L59*(1+IF(M$3<=$O$2,$D59,$D59-($D59-$I$49)*MIN(M$3-$O$2,$Q$2)/$Q$2)) -> 3554.9029 | N59: =M59*(1+IF(N$3<=$O$2,$D59,$D59-($D59-$I$49)*MIN(N$3-$O$2,$Q$2)/$Q$2)) -> 3619.9576 | O59: =SUMPRODUCT(E59:N59,1/(1+$F$49)^$E$3:$N$3)*$E$2 -> 4097.7136 | P59: =N59*$E$2*(1+$I$49)/($F$49-$I$49)/(1+$F$49)^$N$3 -> 4980.7999 | Q59: =O59+P59 -> 9078.5135 | R59: =Q59-$G$2+$I$2 -> 7702.3135 | S59: =R59/$K$2 -> 205.34027 | T59: =S59-$M$2 -> 0.86146471
A60: 10 | B60: =IF(T59>0,B59,D59) -> 0.0390625 | C60: =IF(T59>0,D59,C59) -> 0.041992188 | D60: =(B60+C60)/2 -> 0.040527344 | E60: =$C$2*(1+IF(E$3<=$O$2,$D60,$D60-($D60-$I$49)*MIN(E$3-$O$2,$Q$2)/$Q$2)) -> 2674.1553 | F60: =E60*(1+IF(F$3<=$O$2,$D60,$D60-($D60-$I$49)*MIN(F$3-$O$2,$Q$2)/$Q$2)) -> 2782.5317 | G60: =F60*(1+IF(G$3<=$O$2,$D60,$D60-($D60-$I$49)*MIN(G$3-$O$2,$Q$2)/$Q$2)) -> 2895.3003 | H60: =G60*(1+IF(H$3<=$O$2,$D60,$D60-($D60-$I$49)*MIN(H$3-$O$2,$Q$2)/$Q$2)) -> 3012.6391 | I60: =H60*(1+IF(I$3<=$O$2,$D60,$D60-($D60-$I$49)*MIN(I$3-$O$2,$Q$2)/$Q$2)) -> 3134.7334 | J60: =I60*(1+IF(J$3<=$O$2,$D60,$D60-($D60-$I$49)*MIN(J$3-$O$2,$Q$2)/$Q$2)) -> 3247.8405 | K60: =J60*(1+IF(K$3<=$O$2,$D60,$D60-($D60-$I$49)*MIN(K$3-$O$2,$Q$2)/$Q$2)) -> 3350.5905 | L60: =K60*(1+IF(L$3<=$O$2,$D60,$D60-($D60-$I$49)*MIN(L$3-$O$2,$Q$2)/$Q$2)) -> 3441.6961 | M60: =L60*(1+IF(M$3<=$O$2,$D60,$D60-($D60-$I$49)*MIN(M$3-$O$2,$Q$2)/$Q$2)) -> 3519.9791 | N60: =M60*(1+IF(N$3<=$O$2,$D60,$D60-($D60-$I$49)*MIN(N$3-$O$2,$Q$2)/$Q$2)) -> 3584.3948 | O60: =SUMPRODUCT(E60:N60,1/(1+$F$49)^$E$3:$N$3)*$E$2 -> 4071.6362 | P60: =N60*$E$2*(1+$I$49)/($F$49-$I$49)/(1+$F$49)^$N$3 -> 4931.868 | Q60: =O60+P60 -> 9003.5041 | R60: =Q60-$G$2+$I$2 -> 7627.3041 | S60: =R60/$K$2 -> 203.34055 | T60: =S60-$M$2 -> -1.1382531
A61: 11 | B61: =IF(T60>0,B60,D60) -> 0.040527344 | C61: =IF(T60>0,D60,C60) -> 0.041992188 | D61: =(B61+C61)/2 -> 0.041259766 | E61: =$C$2*(1+IF(E$3<=$O$2,$D61,$D61-($D61-$I$49)*MIN(E$3-$O$2,$Q$2)/$Q$2)) -> 2676.0376 | F61: =E61*(1+IF(F$3<=$O$2,$D61,$D61-($D61-$I$49)*MIN(F$3-$O$2,$Q$2)/$Q$2)) -> 2786.4503 | G61: =F61*(1+IF(G$3<=$O$2,$D61,$D61-($D61-$I$49)*MIN(G$3-$O$2,$Q$2)/$Q$2)) -> 2901.4186 | H61: =G61*(1+IF(H$3<=$O$2,$D61,$D61-($D61-$I$49)*MIN(H$3-$O$2,$Q$2)/$Q$2)) -> 3021.1304 | I61: =H61*(1+IF(I$3<=$O$2,$D61,$D61-($D61-$I$49)*MIN(I$3-$O$2,$Q$2)/$Q$2)) -> 3145.7816 | J61: =I61*(1+IF(J$3<=$O$2,$D61,$D61-($D61-$I$49)*MIN(J$3-$O$2,$Q$2)/$Q$2)) -> 3261.1305 | K61: =J61*(1+IF(K$3<=$O$2,$D61,$D61-($D61-$I$49)*MIN(K$3-$O$2,$Q$2)/$Q$2)) -> 3365.734 | L61: =K61*(1+IF(L$3<=$O$2,$D61,$D61-($D61-$I$49)*MIN(L$3-$O$2,$Q$2)/$Q$2)) -> 3458.2376 | M61: =L61*(1+IF(M$3<=$O$2,$D61,$D61-($D61-$I$49)*MIN(M$3-$O$2,$Q$2)/$Q$2)) -> 3537.4034 | N61: =M61*(1+IF(N$3<=$O$2,$D61,$D61-($D61-$I$49)*MIN(N$3-$O$2,$Q$2)/$Q$2)) -> 3602.1379 | O61: =SUMPRODUCT(E61:N61,1/(1+$F$49)^$E$3:$N$3)*$E$2 -> 4084.6539 | P61: =N61*$E$2*(1+$I$49)/($F$49-$I$49)/(1+$F$49)^$N$3 -> 4956.2812 | Q61: =O61+P61 -> 9040.935 | R61: =Q61-$G$2+$I$2 -> 7664.735 | S61: =R61/$K$2 -> 204.33844 | T61: =S61-$M$2 -> -0.14036139
A62: 12 | B62: =IF(T61>0,B61,D61) -> 0.041259766 | C62: =IF(T61>0,D61,C61) -> 0.041992188 | D62: =(B62+C62)/2 -> 0.041625977 | E62: =$C$2*(1+IF(E$3<=$O$2,$D62,$D62-($D62-$I$49)*MIN(E$3-$O$2,$Q$2)/$Q$2)) -> 2676.9788 | F62: =E62*(1+IF(F$3<=$O$2,$D62,$D62-($D62-$I$49)*MIN(F$3-$O$2,$Q$2)/$Q$2)) -> 2788.4106 | G62: =F62*(1+IF(G$3<=$O$2,$D62,$D62-($D62-$I$49)*MIN(G$3-$O$2,$Q$2)/$Q$2)) -> 2904.4809 | H62: =G62*(1+IF(H$3<=$O$2,$D62,$D62-($D62-$I$49)*MIN(H$3-$O$2,$Q$2)/$Q$2)) -> 3025.3828 | I62: =H62*(1+IF(I$3<=$O$2,$D62,$D62-($D62-$I$49)*MIN(I$3-$O$2,$Q$2)/$Q$2)) -> 3151.3173 | J62: =I62*(1+IF(J$3<=$O$2,$D62,$D62-($D62-$I$49)*MIN(J$3-$O$2,$Q$2)/$Q$2)) -> 3267.7924 | K62: =J62*(1+IF(K$3<=$O$2,$D62,$D62-($D62-$I$49)*MIN(K$3-$O$2,$Q$2)/$Q$2)) -> 3373.3277 | L62: =K62*(1+IF(L$3<=$O$2,$D62,$D62-($D62-$I$49)*MIN(L$3-$O$2,$Q$2)/$Q$2)) -> 3466.5341 | M62: =L62*(1+IF(M$3<=$O$2,$D62,$D62-($D62-$I$49)*MIN(M$3-$O$2,$Q$2)/$Q$2)) -> 3546.1437 | N62: =M62*(1+IF(N$3<=$O$2,$D62,$D62-($D62-$I$49)*MIN(N$3-$O$2,$Q$2)/$Q$2)) -> 3611.0381 | O62: =SUMPRODUCT(E62:N62,1/(1+$F$49)^$E$3:$N$3)*$E$2 -> 4091.1785 | P62: =N62*$E$2*(1+$I$49)/($F$49-$I$49)/(1+$F$49)^$N$3 -> 4968.5273 | Q62: =O62+P62 -> 9059.7058 | R62: =Q62-$G$2+$I$2 -> 7683.5058 | S62: =R62/$K$2 -> 204.83886 | T62: =S62-$M$2 -> 0.360059
A63: 13 | B63: =IF(T62>0,B62,D62) -> 0.041259766 | C63: =IF(T62>0,D62,C62) -> 0.041625977 | D63: =(B63+C63)/2 -> 0.041442871 | E63: =$C$2*(1+IF(E$3<=$O$2,$D63,$D63-($D63-$I$49)*MIN(E$3-$O$2,$Q$2)/$Q$2)) -> 2676.5082 | F63: =E63*(1+IF(F$3<=$O$2,$D63,$D63-($D63-$I$49)*MIN(F$3-$O$2,$Q$2)/$Q$2)) -> 2787.4304 | G63: =F63*(1+IF(G$3<=$O$2,$D63,$D63-($D63-$I$49)*MIN(G$3-$O$2,$Q$2)/$Q$2)) -> 2902.9495 | H63: =G63*(1+IF(H$3<=$O$2,$D63,$D63-($D63-$I$49)*MIN(H$3-$O$2,$Q$2)/$Q$2)) -> 3023.256 | I63: =H63*(1+IF(I$3<=$O$2,$D63,$D63-($D63-$I$49)*MIN(I$3-$O$2,$Q$2)/$Q$2)) -> 3148.5485 | J63: =I63*(1+IF(J$3<=$O$2,$D63,$D63-($D63-$I$49)*MIN(J$3-$O$2,$Q$2)/$Q$2)) -> 3264.46 | K63: =J63*(1+IF(K$3<=$O$2,$D63,$D63-($D63-$I$49)*MIN(K$3-$O$2,$Q$2)/$Q$2)) -> 3369.5291 | L63: =K63*(1+IF(L$3<=$O$2,$D63,$D63-($D63-$I$49)*MIN(L$3-$O$2,$Q$2)/$Q$2)) -> 3462.3837 | M63: =L63*(1+IF(M$3<=$O$2,$D63,$D63-($D63-$I$49)*MIN(M$3-$O$2,$Q$2)/$Q$2)) -> 3541.7712 | N63: =M63*(1+IF(N$3<=$O$2,$D63,$D63-($D63-$I$49)*MIN(N$3-$O$2,$Q$2)/$Q$2)) -> 3606.5856 | O63: =SUMPRODUCT(E63:N63,1/(1+$F$49)^$E$3:$N$3)*$E$2 -> 4087.9148 | P63: =N63*$E$2*(1+$I$49)/($F$49-$I$49)/(1+$F$49)^$N$3 -> 4962.401 | Q63: =O63+P63 -> 9050.3158 | R63: =Q63-$G$2+$I$2 -> 7674.1158 | S63: =R63/$K$2 -> 204.58853 | T63: =S63-$M$2 -> 0.10972574
... A74: 24 | B74: =IF(T73>0,B73,D73) -> 0.041362405 | C74: =IF(T73>0,D73,C73) -> 0.041362584 | D74: =(B74+C74)/2 -> 0.041362494 | E74: =$C$2*(1+IF(E$3<=$O$2,$D74,$D74-($D74-$I$49)*MIN(E$3-$O$2,$Q$2)/$Q$2)) -> 2676.3016 | F74: =E74*(1+IF(F$3<=$O$2,$D74,$D74-($D74-$I$49)*MIN(F$3-$O$2,$Q$2)/$Q$2)) -> 2787.0001 | G74: =F74*(1+IF(G$3<=$O$2,$D74,$D74-($D74-$I$49)*MIN(G$3-$O$2,$Q$2)/$Q$2)) -> 2902.2774 | H74: =G74*(1+IF(H$3<=$O$2,$D74,$D74-($D74-$I$49)*MIN(H$3-$O$2,$Q$2)/$Q$2)) -> 3022.3228 | I74: =H74*(1+IF(I$3<=$O$2,$D74,$D74-($D74-$I$49)*MIN(I$3-$O$2,$Q$2)/$Q$2)) -> 3147.3336 | J74: =I74*(1+IF(J$3<=$O$2,$D74,$D74-($D74-$I$49)*MIN(J$3-$O$2,$Q$2)/$Q$2)) -> 3262.9981 | K74: =J74*(1+IF(K$3<=$O$2,$D74,$D74-($D74-$I$49)*MIN(K$3-$O$2,$Q$2)/$Q$2)) -> 3367.8627 | L74: =K74*(1+IF(L$3<=$O$2,$D74,$D74-($D74-$I$49)*MIN(L$3-$O$2,$Q$2)/$Q$2)) -> 3460.5631 | M74: =L74*(1+IF(M$3<=$O$2,$D74,$D74-($D74-$I$49)*MIN(M$3-$O$2,$Q$2)/$Q$2)) -> 3539.8533 | N74: =M74*(1+IF(N$3<=$O$2,$D74,$D74-($D74-$I$49)*MIN(N$3-$O$2,$Q$2)/$Q$2)) -> 3604.6326 | O74: =SUMPRODUCT(E74:N74,1/(1+$F$49)^$E$3:$N$3)*$E$2 -> 4086.4831 | P74: =N74*$E$2*(1+$I$49)/($F$49-$I$49)/(1+$F$49)^$N$3 -> 4959.7138 | Q74: =O74+P74 -> 9046.1968 | R74: =Q74-$G$2+$I$2 -> 7669.9968 | S74: =R74/$K$2 -> 204.47872 | T74: =S74-$M$2 -> -8.4008877e-05
A76: Grid block 3: row 1, column 2 of table A (24 steps) | E76: WACC | F76: =Sensitivity!$B$10 -> 0.084183338 | G76: Terminal growth | I76: =Sensitivity!$D$9 -> 0.0233
A77: Step | B77: Low | C77: High | D77: Mid | E77: Rev Y1 | F77: Rev Y2 | G77: Rev Y3 | H77: Rev Y4 | I77: Rev Y5 | J77: Rev Y6 | K77: Rev Y7 | L77: Rev Y8 | M77: Rev Y9 | N77: Rev Y10 | O77: PV of FCF | P77: PV of TV | Q77: EV | R77: Equity | S77: Per share | T77: Value - price
A78: 1 | B78: -0.5 | C78: 1 | D78: =(B78+C78)/2 -> 0.25 | E78: =$C$2*(1+IF(E$3<=$O$2,$D78,$D78-($D78-$I$76)*MIN(E$3-$O$2,$Q$2)/$Q$2)) -> 3212.5 | F78: =E78*(1+IF(F$3<=$O$2,$D78,$D78-($D78-$I$76)*MIN(F$3-$O$2,$Q$2)/$Q$2)) -> 4015.625 | G78: =F78*(1+IF(G$3<=$O$2,$D78,$D78-($D78-$I$76)*MIN(G$3-$O$2,$Q$2)/$Q$2)) -> 5019.5312 | H78: =G78*(1+IF(H$3<=$O$2,$D78,$D78-($D78-$I$76)*MIN(H$3-$O$2,$Q$2)/$Q$2)) -> 6274.4141 | I78: =H78*(1+IF(I$3<=$O$2,$D78,$D78-($D78-$I$76)*MIN(I$3-$O$2,$Q$2)/$Q$2)) -> 7843.0176 | J78: =I78*(1+IF(J$3<=$O$2,$D78,$D78-($D78-$I$76)*MIN(J$3-$O$2,$Q$2)/$Q$2)) -> 9448.1696 | K78: =J78*(1+IF(K$3<=$O$2,$D78,$D78-($D78-$I$76)*MIN(K$3-$O$2,$Q$2)/$Q$2)) -> 10953.452 | L78: =K78*(1+IF(L$3<=$O$2,$D78,$D78-($D78-$I$76)*MIN(L$3-$O$2,$Q$2)/$Q$2)) -> 12201.926 | M78: =L78*(1+IF(M$3<=$O$2,$D78,$D78-($D78-$I$76)*MIN(M$3-$O$2,$Q$2)/$Q$2)) -> 13039.467 | N78: =M78*(1+IF(N$3<=$O$2,$D78,$D78-($D78-$I$76)*MIN(N$3-$O$2,$Q$2)/$Q$2)) -> 13343.286 | O78: =SUMPRODUCT(E78:N78,1/(1+$F$76)^$E$3:$N$3)*$E$2 -> 10142.23 | P78: =N78*$E$2*(1+$I$76)/($F$76-$I$76)/(1+$F$76)^$N$3 -> 19964.7 | Q78: =O78+P78 -> 30106.929 | R78: =Q78-$G$2+$I$2 -> 28730.729 | S78: =R78/$K$2 -> 765.94853 | T78: =S78-$M$2 -> 561.46972
A79: 2 | B79: =IF(T78>0,B78,D78) -> -0.5 | C79: =IF(T78>0,D78,C78) -> 0.25 | D79: =(B79+C79)/2 -> -0.125 | E79: =$C$2*(1+IF(E$3<=$O$2,$D79,$D79-($D79-$I$76)*MIN(E$3-$O$2,$Q$2)/$Q$2)) -> 2248.75 | F79: =E79*(1+IF(F$3<=$O$2,$D79,$D79-($D79-$I$76)*MIN(F$3-$O$2,$Q$2)/$Q$2)) -> 1967.6562 | G79: =F79*(1+IF(G$3<=$O$2,$D79,$D79-($D79-$I$76)*MIN(G$3-$O$2,$Q$2)/$Q$2)) -> 1721.6992 | H79: =G79*(1+IF(H$3<=$O$2,$D79,$D79-($D79-$I$76)*MIN(H$3-$O$2,$Q$2)/$Q$2)) -> 1506.4868 | I79: =H79*(1+IF(I$3<=$O$2,$D79,$D79-($D79-$I$76)*MIN(I$3-$O$2,$Q$2)/$Q$2)) -> 1318.176 | J79: =I79*(1+IF(J$3<=$O$2,$D79,$D79-($D79-$I$76)*MIN(J$3-$O$2,$Q$2)/$Q$2)) -> 1192.5011 | K79: =J79*(1+IF(K$3<=$O$2,$D79,$D79-($D79-$I$76)*MIN(K$3-$O$2,$Q$2)/$Q$2)) -> 1114.1776 | L79: =K79*(1+IF(L$3<=$O$2,$D79,$D79-($D79-$I$76)*MIN(L$3-$O$2,$Q$2)/$Q$2)) -> 1074.0449 | M79: =L79*(1+IF(M$3<=$O$2,$D79,$D79-($D79-$I$76)*MIN(M$3-$O$2,$Q$2)/$Q$2)) -> 1067.214 | N79: =M79*(1+IF(N$3<=$O$2,$D79,$D79-($D79-$I$76)*MIN(N$3-$O$2,$Q$2)/$Q$2)) -> 1092.0801 | O79: =SUMPRODUCT(E79:N79,1/(1+$F$76)^$E$3:$N$3)*$E$2 -> 1997.9118 | P79: =N79*$E$2*(1+$I$76)/($F$76-$I$76)/(1+$F$76)^$N$3 -> 1634.0091 | Q79: =O79+P79 -> 3631.9209 | R79: =Q79-$G$2+$I$2 -> 2255.7209 | S79: =R79/$K$2 -> 60.13652 | T79: =S79-$M$2 -> -144.34229
A80: 3 | B80: =IF(T79>0,B79,D79) -> -0.125 | C80: =IF(T79>0,D79,C79) -> 0.25 | D80: =(B80+C80)/2 -> 0.0625 | E80: =$C$2*(1+IF(E$3<=$O$2,$D80,$D80-($D80-$I$76)*MIN(E$3-$O$2,$Q$2)/$Q$2)) -> 2730.625 | F80: =E80*(1+IF(F$3<=$O$2,$D80,$D80-($D80-$I$76)*MIN(F$3-$O$2,$Q$2)/$Q$2)) -> 2901.2891 | G80: =F80*(1+IF(G$3<=$O$2,$D80,$D80-($D80-$I$76)*MIN(G$3-$O$2,$Q$2)/$Q$2)) -> 3082.6196 | H80: =G80*(1+IF(H$3<=$O$2,$D80,$D80-($D80-$I$76)*MIN(H$3-$O$2,$Q$2)/$Q$2)) -> 3275.2834 | I80: =H80*(1+IF(I$3<=$O$2,$D80,$D80-($D80-$I$76)*MIN(I$3-$O$2,$Q$2)/$Q$2)) -> 3479.9886 | J80: =I80*(1+IF(J$3<=$O$2,$D80,$D80-($D80-$I$76)*MIN(J$3-$O$2,$Q$2)/$Q$2)) -> 3670.2047 | K80: =J80*(1+IF(K$3<=$O$2,$D80,$D80-($D80-$I$76)*MIN(K$3-$O$2,$Q$2)/$Q$2)) -> 3842.0437 | L80: =K80*(1+IF(L$3<=$O$2,$D80,$D80-($D80-$I$76)*MIN(L$3-$O$2,$Q$2)/$Q$2)) -> 3991.8066 | M80: =L80*(1+IF(M$3<=$O$2,$D80,$D80-($D80-$I$76)*MIN(M$3-$O$2,$Q$2)/$Q$2)) -> 4116.1114 | N80: =M80*(1+IF(N$3<=$O$2,$D80,$D80-($D80-$I$76)*MIN(N$3-$O$2,$Q$2)/$Q$2)) -> 4212.0168 | O80: =SUMPRODUCT(E80:N80,1/(1+$F$76)^$E$3:$N$3)*$E$2 -> 4494.2796 | P80: =N80*$E$2*(1+$I$76)/($F$76-$I$76)/(1+$F$76)^$N$3 -> 6302.1695 | Q80: =O80+P80 -> 10796.449 | R80: =Q80-$G$2+$I$2 -> 9420.2491 | S80: =R80/$K$2 -> 251.13967 | T80: =S80-$M$2 -> 46.660866
A81: 4 | B81: =IF(T80>0,B80,D80) -> -0.125 | C81: =IF(T80>0,D80,C80) -> 0.0625 | D81: =(B81+C81)/2 -> -0.03125 | E81: =$C$2*(1+IF(E$3<=$O$2,$D81,$D81-($D81-$I$76)*MIN(E$3-$O$2,$Q$2)/$Q$2)) -> 2489.6875 | F81: =E81*(1+IF(F$3<=$O$2,$D81,$D81-($D81-$I$76)*MIN(F$3-$O$2,$Q$2)/$Q$2)) -> 2411.8848 | G81: =F81*(1+IF(G$3<=$O$2,$D81,$D81-($D81-$I$76)*MIN(G$3-$O$2,$Q$2)/$Q$2)) -> 2336.5134 | H81: =G81*(1+IF(H$3<=$O$2,$D81,$D81-($D81-$I$76)*MIN(H$3-$O$2,$Q$2)/$Q$2)) -> 2263.4973 | I81: =H81*(1+IF(I$3<=$O$2,$D81,$D81-($D81-$I$76)*MIN(I$3-$O$2,$Q$2)/$Q$2)) -> 2192.763 | J81: =I81*(1+IF(J$3<=$O$2,$D81,$D81-($D81-$I$76)*MIN(J$3-$O$2,$Q$2)/$Q$2)) -> 2148.1622 | K81: =J81*(1+IF(K$3<=$O$2,$D81,$D81-($D81-$I$76)*MIN(K$3-$O$2,$Q$2)/$Q$2)) -> 2127.9051 | L81: =K81*(1+IF(L$3<=$O$2,$D81,$D81-($D81-$I$76)*MIN(L$3-$O$2,$Q$2)/$Q$2)) -> 2131.0544 | M81: =L81*(1+IF(M$3<=$O$2,$D81,$D81-($D81-$I$76)*MIN(M$3-$O$2,$Q$2)/$Q$2)) -> 2157.4581 | N81: =M81*(1+IF(N$3<=$O$2,$D81,$D81-($D81-$I$76)*MIN(N$3-$O$2,$Q$2)/$Q$2)) -> 2207.7269 | O81: =SUMPRODUCT(E81:N81,1/(1+$F$76)^$E$3:$N$3)*$E$2 -> 2987.9579 | P81: =N81*$E$2*(1+$I$76)/($F$76-$I$76)/(1+$F$76)^$N$3 -> 3303.2795 | Q81: =O81+P81 -> 6291.2375 | R81: =Q81-$G$2+$I$2 -> 4915.0375 | S81: =R81/$K$2 -> 131.03272 | T81: =S81-$M$2 -> -73.446082
A82: 5 | B82: =IF(T81>0,B81,D81) -> -0.03125 | C82: =IF(T81>0,D81,C81) -> 0.0625 | D82: =(B82+C82)/2 -> 0.015625 | E82: =$C$2*(1+IF(E$3<=$O$2,$D82,$D82-($D82-$I$76)*MIN(E$3-$O$2,$Q$2)/$Q$2)) -> 2610.1562 | F82: =E82*(1+IF(F$3<=$O$2,$D82,$D82-($D82-$I$76)*MIN(F$3-$O$2,$Q$2)/$Q$2)) -> 2650.9399 | G82: =F82*(1+IF(G$3<=$O$2,$D82,$D82-($D82-$I$76)*MIN(G$3-$O$2,$Q$2)/$Q$2)) -> 2692.3609 | H82: =G82*(1+IF(H$3<=$O$2,$D82,$D82-($D82-$I$76)*MIN(H$3-$O$2,$Q$2)/$Q$2)) -> 2734.429 | I82: =H82*(1+IF(I$3<=$O$2,$D82,$D82-($D82-$I$76)*MIN(I$3-$O$2,$Q$2)/$Q$2)) -> 2777.1545 | J82: =I82*(1+IF(J$3<=$O$2,$D82,$D82-($D82-$I$76)*MIN(J$3-$O$2,$Q$2)/$Q$2)) -> 2824.8104 | K82: =J82*(1+IF(K$3<=$O$2,$D82,$D82-($D82-$I$76)*MIN(K$3-$O$2,$Q$2)/$Q$2)) -> 2877.6203 | L82: =K82*(1+IF(L$3<=$O$2,$D82,$D82-($D82-$I$76)*MIN(L$3-$O$2,$Q$2)/$Q$2)) -> 2935.8345 | M82: =L82*(1+IF(M$3<=$O$2,$D82,$D82-($D82-$I$76)*MIN(M$3-$O$2,$Q$2)/$Q$2)) -> 2999.733 | N82: =M82*(1+IF(N$3<=$O$2,$D82,$D82-($D82-$I$76)*MIN(N$3-$O$2,$Q$2)/$Q$2)) -> 3069.6267 | O82: =SUMPRODUCT(E82:N82,1/(1+$F$76)^$E$3:$N$3)*$E$2 -> 3663.0977 | P82: =N82*$E$2*(1+$I$76)/($F$76-$I$76)/(1+$F$76)^$N$3 -> 4592.8848 | Q82: =O82+P82 -> 8255.9824 | R82: =Q82-$G$2+$I$2 -> 6879.7824 | S82: =R82/$K$2 -> 183.41195 | T82: =S82-$M$2 -> -21.066851
A83: 6 | B83: =IF(T82>0,B82,D82) -> 0.015625 | C83: =IF(T82>0,D82,C82) -> 0.0625 | D83: =(B83+C83)/2 -> 0.0390625 | E83: =$C$2*(1+IF(E$3<=$O$2,$D83,$D83-($D83-$I$76)*MIN(E$3-$O$2,$Q$2)/$Q$2)) -> 2670.3906 | F83: =E83*(1+IF(F$3<=$O$2,$D83,$D83-($D83-$I$76)*MIN(F$3-$O$2,$Q$2)/$Q$2)) -> 2774.7028 | G83: =F83*(1+IF(G$3<=$O$2,$D83,$D83-($D83-$I$76)*MIN(G$3-$O$2,$Q$2)/$Q$2)) -> 2883.0896 | H83: =G83*(1+IF(H$3<=$O$2,$D83,$D83-($D83-$I$76)*MIN(H$3-$O$2,$Q$2)/$Q$2)) -> 2995.7103 | I83: =H83*(1+IF(I$3<=$O$2,$D83,$D83-($D83-$I$76)*MIN(I$3-$O$2,$Q$2)/$Q$2)) -> 3112.7302 | J83: =I83*(1+IF(J$3<=$O$2,$D83,$D83-($D83-$I$76)*MIN(J$3-$O$2,$Q$2)/$Q$2)) -> 3224.5083 | K83: =J83*(1+IF(K$3<=$O$2,$D83,$D83-($D83-$I$76)*MIN(K$3-$O$2,$Q$2)/$Q$2)) -> 3330.1352 | L83: =K83*(1+IF(L$3<=$O$2,$D83,$D83-($D83-$I$76)*MIN(L$3-$O$2,$Q$2)/$Q$2)) -> 3428.7238 | M83: =L83*(1+IF(M$3<=$O$2,$D83,$D83-($D83-$I$76)*MIN(M$3-$O$2,$Q$2)/$Q$2)) -> 3519.4221 | N83: =M83*(1+IF(N$3<=$O$2,$D83,$D83-($D83-$I$76)*MIN(N$3-$O$2,$Q$2)/$Q$2)) -> 3601.4247 | O83: =SUMPRODUCT(E83:N83,1/(1+$F$76)^$E$3:$N$3)*$E$2 -> 4057.2304 | P83: =N83*$E$2*(1+$I$76)/($F$76-$I$76)/(1+$F$76)^$N$3 -> 5388.5798 | Q83: =O83+P83 -> 9445.8102 | R83: =Q83-$G$2+$I$2 -> 8069.6102 | S83: =R83/$K$2 -> 215.13224 | T83: =S83-$M$2 -> 10.653431
A84: 7 | B84: =IF(T83>0,B83,D83) -> 0.015625 | C84: =IF(T83>0,D83,C83) -> 0.0390625 | D84: =(B84+C84)/2 -> 0.02734375 | E84: =$C$2*(1+IF(E$3<=$O$2,$D84,$D84-($D84-$I$76)*MIN(E$3-$O$2,$Q$2)/$Q$2)) -> 2640.2734 | F84: =E84*(1+IF(F$3<=$O$2,$D84,$D84-($D84-$I$76)*MIN(F$3-$O$2,$Q$2)/$Q$2)) -> 2712.4684 | G84: =F84*(1+IF(G$3<=$O$2,$D84,$D84-($D84-$I$76)*MIN(G$3-$O$2,$Q$2)/$Q$2)) -> 2786.6375 | H84: =G84*(1+IF(H$3<=$O$2,$D84,$D84-($D84-$I$76)*MIN(H$3-$O$2,$Q$2)/$Q$2)) -> 2862.8346 | I84: =H84*(1+IF(I$3<=$O$2,$D84,$D84-($D84-$I$76)*MIN(I$3-$O$2,$Q$2)/$Q$2)) -> 2941.1152 | J84: =I84*(1+IF(J$3<=$O$2,$D84,$D84-($D84-$I$76)*MIN(J$3-$O$2,$Q$2)/$Q$2)) -> 3019.1577 | K84: =J84*(1+IF(K$3<=$O$2,$D84,$D84-($D84-$I$76)*MIN(K$3-$O$2,$Q$2)/$Q$2)) -> 3096.8293 | L84: =K84*(1+IF(L$3<=$O$2,$D84,$D84-($D84-$I$76)*MIN(L$3-$O$2,$Q$2)/$Q$2)) -> 3173.9946 | M84: =L84*(1+IF(M$3<=$O$2,$D84,$D84-($D84-$I$76)*MIN(M$3-$O$2,$Q$2)/$Q$2)) -> 3250.5156 | N84: =M84*(1+IF(N$3<=$O$2,$D84,$D84-($D84-$I$76)*MIN(N$3-$O$2,$Q$2)/$Q$2)) -> 3326.2526 | O84: =SUMPRODUCT(E84:N84,1/(1+$F$76)^$E$3:$N$3)*$E$2 -> 3855.0567 | P84: =N84*$E$2*(1+$I$76)/($F$76-$I$76)/(1+$F$76)^$N$3 -> 4976.8575 | Q84: =O84+P84 -> 8831.9142 | R84: =Q84-$G$2+$I$2 -> 7455.7142 | S84: =R84/$K$2 -> 198.76604 | T84: =S84-$M$2 -> -5.7127647
A85: 8 | B85: =IF(T84>0,B84,D84) -> 0.02734375 | C85: =IF(T84>0,D84,C84) -> 0.0390625 | D85: =(B85+C85)/2 -> 0.033203125 | E85: =$C$2*(1+IF(E$3<=$O$2,$D85,$D85-($D85-$I$76)*MIN(E$3-$O$2,$Q$2)/$Q$2)) -> 2655.332 | F85: =E85*(1+IF(F$3<=$O$2,$D85,$D85-($D85-$I$76)*MIN(F$3-$O$2,$Q$2)/$Q$2)) -> 2743.4974 | G85: =F85*(1+IF(G$3<=$O$2,$D85,$D85-($D85-$I$76)*MIN(G$3-$O$2,$Q$2)/$Q$2)) -> 2834.59 | H85: =G85*(1+IF(H$3<=$O$2,$D85,$D85-($D85-$I$76)*MIN(H$3-$O$2,$Q$2)/$Q$2)) -> 2928.7073 | I85: =H85*(1+IF(I$3<=$O$2,$D85,$D85-($D85-$I$76)*MIN(I$3-$O$2,$Q$2)/$Q$2)) -> 3025.9495 | J85: =I85*(1+IF(J$3<=$O$2,$D85,$D85-($D85-$I$76)*MIN(J$3-$O$2,$Q$2)/$Q$2)) -> 3120.4272 | K85: =J85*(1+IF(K$3<=$O$2,$D85,$D85-($D85-$I$76)*MIN(K$3-$O$2,$Q$2)/$Q$2)) -> 3211.6744 | L85: =K85*(1+IF(L$3<=$O$2,$D85,$D85-($D85-$I$76)*MIN(L$3-$O$2,$Q$2)/$Q$2)) -> 3299.2286 | M85: =L85*(1+IF(M$3<=$O$2,$D85,$D85-($D85-$I$76)*MIN(M$3-$O$2,$Q$2)/$Q$2)) -> 3382.6352 | N85: =M85*(1+IF(N$3<=$O$2,$D85,$D85-($D85-$I$76)*MIN(N$3-$O$2,$Q$2)/$Q$2)) -> 3461.4506 | O85: =SUMPRODUCT(E85:N85,1/(1+$F$76)^$E$3:$N$3)*$E$2 -> 3954.8354 | P85: =N85*$E$2*(1+$I$76)/($F$76-$I$76)/(1+$F$76)^$N$3 -> 5179.1455 | Q85: =O85+P85 -> 9133.9809 | R85: =Q85-$G$2+$I$2 -> 7757.7809 | S85: =R85/$K$2 -> 206.81901 | T85: =S85-$M$2 -> 2.3402011
A86: 9 | B86: =IF(T85>0,B85,D85) -> 0.02734375 | C86: =IF(T85>0,D85,C85) -> 0.033203125 | D86: =(B86+C86)/2 -> 0.030273438 | E86: =$C$2*(1+IF(E$3<=$O$2,$D86,$D86-($D86-$I$76)*MIN(E$3-$O$2,$Q$2)/$Q$2)) -> 2647.8027 | F86: =E86*(1+IF(F$3<=$O$2,$D86,$D86-($D86-$I$76)*MIN(F$3-$O$2,$Q$2)/$Q$2)) -> 2727.9608 | G86: =F86*(1+IF(G$3<=$O$2,$D86,$D86-($D86-$I$76)*MIN(G$3-$O$2,$Q$2)/$Q$2)) -> 2810.5456 | H86: =G86*(1+IF(H$3<=$O$2,$D86,$D86-($D86-$I$76)*MIN(H$3-$O$2,$Q$2)/$Q$2)) -> 2895.6305 | I86: =H86*(1+IF(I$3<=$O$2,$D86,$D86-($D86-$I$76)*MIN(I$3-$O$2,$Q$2)/$Q$2)) -> 2983.2911 | J86: =I86*(1+IF(J$3<=$O$2,$D86,$D86-($D86-$I$76)*MIN(J$3-$O$2,$Q$2)/$Q$2)) -> 3069.4449 | K86: =J86*(1+IF(K$3<=$O$2,$D86,$D86-($D86-$I$76)*MIN(K$3-$O$2,$Q$2)/$Q$2)) -> 3153.8057 | L86: =K86*(1+IF(L$3<=$O$2,$D86,$D86-($D86-$I$76)*MIN(L$3-$O$2,$Q$2)/$Q$2)) -> 3236.0865 | M86: =L86*(1+IF(M$3<=$O$2,$D86,$D86-($D86-$I$76)*MIN(M$3-$O$2,$Q$2)/$Q$2)) -> 3316.0006 | N86: =M86*(1+IF(N$3<=$O$2,$D86,$D86-($D86-$I$76)*MIN(N$3-$O$2,$Q$2)/$Q$2)) -> 3393.2635 | O86: =SUMPRODUCT(E86:N86,1/(1+$F$76)^$E$3:$N$3)*$E$2 -> 3904.623 | P86: =N86*$E$2*(1+$I$76)/($F$76-$I$76)/(1+$F$76)^$N$3 -> 5077.1215 | Q86: =O86+P86 -> 8981.7445 | R86: =Q86-$G$2+$I$2 -> 7605.5445 | S86: =R86/$K$2 -> 202.76045 | T86: =S86-$M$2 -> -1.7183557
A87: 10 | B87: =IF(T86>0,B86,D86) -> 0.030273438 | C87: =IF(T86>0,D86,C86) -> 0.033203125 | D87: =(B87+C87)/2 -> 0.031738281 | E87: =$C$2*(1+IF(E$3<=$O$2,$D87,$D87-($D87-$I$76)*MIN(E$3-$O$2,$Q$2)/$Q$2)) -> 2651.5674 | F87: =E87*(1+IF(F$3<=$O$2,$D87,$D87-($D87-$I$76)*MIN(F$3-$O$2,$Q$2)/$Q$2)) -> 2735.7236 | G87: =F87*(1+IF(G$3<=$O$2,$D87,$D87-($D87-$I$76)*MIN(G$3-$O$2,$Q$2)/$Q$2)) -> 2822.5507 | H87: =G87*(1+IF(H$3<=$O$2,$D87,$D87-($D87-$I$76)*MIN(H$3-$O$2,$Q$2)/$Q$2)) -> 2912.1336 | I87: =H87*(1+IF(I$3<=$O$2,$D87,$D87-($D87-$I$76)*MIN(I$3-$O$2,$Q$2)/$Q$2)) -> 3004.5598 | J87: =I87*(1+IF(J$3<=$O$2,$D87,$D87-($D87-$I$76)*MIN(J$3-$O$2,$Q$2)/$Q$2)) -> 3094.8487 | K87: =J87*(1+IF(K$3<=$O$2,$D87,$D87-($D87-$I$76)*MIN(K$3-$O$2,$Q$2)/$Q$2)) -> 3182.6278 | L87: =K87*(1+IF(L$3<=$O$2,$D87,$D87-($D87-$I$76)*MIN(L$3-$O$2,$Q$2)/$Q$2)) -> 3267.5253 | M87: =L87*(1+IF(M$3<=$O$2,$D87,$D87-($D87-$I$76)*MIN(M$3-$O$2,$Q$2)/$Q$2)) -> 3349.1731 | N87: =M87*(1+IF(N$3<=$O$2,$D87,$D87-($D87-$I$76)*MIN(N$3-$O$2,$Q$2)/$Q$2)) -> 3427.2089 | O87: =SUMPRODUCT(E87:N87,1/(1+$F$76)^$E$3:$N$3)*$E$2 -> 3929.6479 | P87: =N87*$E$2*(1+$I$76)/($F$76-$I$76)/(1+$F$76)^$N$3 -> 5127.9119 | Q87: =O87+P87 -> 9057.5598 | R87: =Q87-$G$2+$I$2 -> 7681.3598 | S87: =R87/$K$2 -> 204.78165 | T87: =S87-$M$2 -> 0.3028473
A88: 11 | B88: =IF(T87>0,B87,D87) -> 0.030273438 | C88: =IF(T87>0,D87,C87) -> 0.031738281 | D88: =(B88+C88)/2 -> 0.031005859 | E88: =$C$2*(1+IF(E$3<=$O$2,$D88,$D88-($D88-$I$76)*MIN(E$3-$O$2,$Q$2)/$Q$2)) -> 2649.6851 | F88: =E88*(1+IF(F$3<=$O$2,$D88,$D88-($D88-$I$76)*MIN(F$3-$O$2,$Q$2)/$Q$2)) -> 2731.8408 | G88: =F88*(1+IF(G$3<=$O$2,$D88,$D88-($D88-$I$76)*MIN(G$3-$O$2,$Q$2)/$Q$2)) -> 2816.5439 | H88: =G88*(1+IF(H$3<=$O$2,$D88,$D88-($D88-$I$76)*MIN(H$3-$O$2,$Q$2)/$Q$2)) -> 2903.8733 | I88: =H88*(1+IF(I$3<=$O$2,$D88,$D88-($D88-$I$76)*MIN(I$3-$O$2,$Q$2)/$Q$2)) -> 2993.9103 | J88: =I88*(1+IF(J$3<=$O$2,$D88,$D88-($D88-$I$76)*MIN(J$3-$O$2,$Q$2)/$Q$2)) -> 3082.125 | K88: =J88*(1+IF(K$3<=$O$2,$D88,$D88-($D88-$I$76)*MIN(K$3-$O$2,$Q$2)/$Q$2)) -> 3168.1887 | L88: =K88*(1+IF(L$3<=$O$2,$D88,$D88-($D88-$I$76)*MIN(L$3-$O$2,$Q$2)/$Q$2)) -> 3251.773 | M88: =L88*(1+IF(M$3<=$O$2,$D88,$D88-($D88-$I$76)*MIN(M$3-$O$2,$Q$2)/$Q$2)) -> 3332.5508 | N88: =M88*(1+IF(N$3<=$O$2,$D88,$D88-($D88-$I$76)*MIN(N$3-$O$2,$Q$2)/$Q$2)) -> 3410.1993 | O88: =SUMPRODUCT(E88:N88,1/(1+$F$76)^$E$3:$N$3)*$E$2 -> 3917.1152 | P88: =N88*$E$2*(1+$I$76)/($F$76-$I$76)/(1+$F$76)^$N$3 -> 5102.4615 | Q88: =O88+P88 -> 9019.5767 | R88: =Q88-$G$2+$I$2 -> 7643.3767 | S88: =R88/$K$2 -> 203.76904 | T88: =S88-$M$2 -> -0.7097659
A89: 12 | B89: =IF(T88>0,B88,D88) -> 0.031005859 | C89: =IF(T88>0,D88,C88) -> 0.031738281 | D89: =(B89+C89)/2 -> 0.03137207 | E89: =$C$2*(1+IF(E$3<=$O$2,$D89,$D89-($D89-$I$76)*MIN(E$3-$O$2,$Q$2)/$Q$2)) -> 2650.6262 | F89: =E89*(1+IF(F$3<=$O$2,$D89,$D89-($D89-$I$76)*MIN(F$3-$O$2,$Q$2)/$Q$2)) -> 2733.7819 | G89: =F89*(1+IF(G$3<=$O$2,$D89,$D89-($D89-$I$76)*MIN(G$3-$O$2,$Q$2)/$Q$2)) -> 2819.5462 | H89: =G89*(1+IF(H$3<=$O$2,$D89,$D89-($D89-$I$76)*MIN(H$3-$O$2,$Q$2)/$Q$2)) -> 2908.0013 | I89: =H89*(1+IF(I$3<=$O$2,$D89,$D89-($D89-$I$76)*MIN(I$3-$O$2,$Q$2)/$Q$2)) -> 2999.2313 | J89: =I89*(1+IF(J$3<=$O$2,$D89,$D89-($D89-$I$76)*MIN(J$3-$O$2,$Q$2)/$Q$2)) -> 3088.4814 | K89: =J89*(1+IF(K$3<=$O$2,$D89,$D89-($D89-$I$76)*MIN(K$3-$O$2,$Q$2)/$Q$2)) -> 3175.4012 | L89: =K89*(1+IF(L$3<=$O$2,$D89,$D89-($D89-$I$76)*MIN(L$3-$O$2,$Q$2)/$Q$2)) -> 3259.6409 | M89: =L89*(1+IF(M$3<=$O$2,$D89,$D89-($D89-$I$76)*MIN(M$3-$O$2,$Q$2)/$Q$2)) -> 3340.853 | N89: =M89*(1+IF(N$3<=$O$2,$D89,$D89-($D89-$I$76)*MIN(N$3-$O$2,$Q$2)/$Q$2)) -> 3418.6948 | O89: =SUMPRODUCT(E89:N89,1/(1+$F$76)^$E$3:$N$3)*$E$2 -> 3923.3765 | P89: =N89*$E$2*(1+$I$76)/($F$76-$I$76)/(1+$F$76)^$N$3 -> 5115.1729 | Q89: =O89+P89 -> 9038.5493 | R89: =Q89-$G$2+$I$2 -> 7662.3493 | S89: =R89/$K$2 -> 204.27484 | T89: =S89-$M$2 -> -0.20396312
A90: 13 | B90: =IF(T89>0,B89,D89) -> 0.03137207 | C90: =IF(T89>0,D89,C89) -> 0.031738281 | D90: =(B90+C90)/2 -> 0.031555176 | E90: =$C$2*(1+IF(E$3<=$O$2,$D90,$D90-($D90-$I$76)*MIN(E$3-$O$2,$Q$2)/$Q$2)) -> 2651.0968 | F90: =E90*(1+IF(F$3<=$O$2,$D90,$D90-($D90-$I$76)*MIN(F$3-$O$2,$Q$2)/$Q$2)) -> 2734.7526 | G90: =F90*(1+IF(G$3<=$O$2,$D90,$D90-($D90-$I$76)*MIN(G$3-$O$2,$Q$2)/$Q$2)) -> 2821.0482 | H90: =G90*(1+IF(H$3<=$O$2,$D90,$D90-($D90-$I$76)*MIN(H$3-$O$2,$Q$2)/$Q$2)) -> 2910.0669 | I90: =H90*(1+IF(I$3<=$O$2,$D90,$D90-($D90-$I$76)*MIN(I$3-$O$2,$Q$2)/$Q$2)) -> 3001.8946 | J90: =I90*(1+IF(J$3<=$O$2,$D90,$D90-($D90-$I$76)*MIN(J$3-$O$2,$Q$2)/$Q$2)) -> 3091.6636 | K90: =J90*(1+IF(K$3<=$O$2,$D90,$D90-($D90-$I$76)*MIN(K$3-$O$2,$Q$2)/$Q$2)) -> 3179.0127 | L90: =K90*(1+IF(L$3<=$O$2,$D90,$D90-($D90-$I$76)*MIN(L$3-$O$2,$Q$2)/$Q$2)) -> 3263.5811 | M90: =L90*(1+IF(M$3<=$O$2,$D90,$D90-($D90-$I$76)*MIN(M$3-$O$2,$Q$2)/$Q$2)) -> 3345.0108 | N90: =M90*(1+IF(N$3<=$O$2,$D90,$D90-($D90-$I$76)*MIN(N$3-$O$2,$Q$2)/$Q$2)) -> 3422.9495 | O90: =SUMPRODUCT(E90:N90,1/(1+$F$76)^$E$3:$N$3)*$E$2 -> 3926.5109 | P90: =N90*$E$2*(1+$I$76)/($F$76-$I$76)/(1+$F$76)^$N$3 -> 5121.5389 | Q90: =O90+P90 -> 9048.0498 | R90: =Q90-$G$2+$I$2 -> 7671.8498 | S90: =R90/$K$2 -> 204.52812 | T90: =S90-$M$2 -> 0.049316023
... A101: 24 | B101: =IF(T100>0,B100,D100) -> 0.031519413 | C101: =IF(T100>0,D100,C100) -> 0.031519592 | D101: =(B101+C101)/2 -> 0.031519502 | E101: =$C$2*(1+IF(E$3<=$O$2,$D101,$D101-($D101-$I$76)*MIN(E$3-$O$2,$Q$2)/$Q$2)) -> 2651.0051 | F101: =E101*(1+IF(F$3<=$O$2,$D101,$D101-($D101-$I$76)*MIN(F$3-$O$2,$Q$2)/$Q$2)) -> 2734.5635 | G101: =F101*(1+IF(G$3<=$O$2,$D101,$D101-($D101-$I$76)*MIN(G$3-$O$2,$Q$2)/$Q$2)) -> 2820.7556 | H101: =G101*(1+IF(H$3<=$O$2,$D101,$D101-($D101-$I$76)*MIN(H$3-$O$2,$Q$2)/$Q$2)) -> 2909.6644 | I101: =H101*(1+IF(I$3<=$O$2,$D101,$D101-($D101-$I$76)*MIN(I$3-$O$2,$Q$2)/$Q$2)) -> 3001.3755 | J101: =I101*(1+IF(J$3<=$O$2,$D101,$D101-($D101-$I$76)*MIN(J$3-$O$2,$Q$2)/$Q$2)) -> 3091.0434 | K101: =J101*(1+IF(K$3<=$O$2,$D101,$D101-($D101-$I$76)*MIN(K$3-$O$2,$Q$2)/$Q$2)) -> 3178.3089 | L101: =K101*(1+IF(L$3<=$O$2,$D101,$D101-($D101-$I$76)*MIN(L$3-$O$2,$Q$2)/$Q$2)) -> 3262.8131 | M101: =L101*(1+IF(M$3<=$O$2,$D101,$D101-($D101-$I$76)*MIN(M$3-$O$2,$Q$2)/$Q$2)) -> 3344.2004 | N101: =M101*(1+IF(N$3<=$O$2,$D101,$D101-($D101-$I$76)*MIN(N$3-$O$2,$Q$2)/$Q$2)) -> 3422.1203 | O101: =SUMPRODUCT(E101:N101,1/(1+$F$76)^$E$3:$N$3)*$E$2 -> 3925.9001 | P101: =N101*$E$2*(1+$I$76)/($F$76-$I$76)/(1+$F$76)^$N$3 -> 5120.2981 | Q101: =O101+P101 -> 9046.1982 | R101: =Q101-$G$2+$I$2 -> 7669.9982 | S101: =R101/$K$2 -> 204.47876 | T101: =S101-$M$2 -> -4.8656585e-05
A103: Grid block 4: row 1, column 3 of table A (24 steps) | E103: WACC | F103: =Sensitivity!$B$10 -> 0.084183338 | G103: Terminal growth | I103: =Sensitivity!$E$9 -> 0.0283
A104: Step | B104: Low | C104: High | D104: Mid | E104: Rev Y1 | F104: Rev Y2 | G104: Rev Y3 | H104: Rev Y4 | I104: Rev Y5 | J104: Rev Y6 | K104: Rev Y7 | L104: Rev Y8 | M104: Rev Y9 | N104: Rev Y10 | O104: PV of FCF | P104: PV of TV | Q104: EV | R104: Equity | S104: Per share | T104: Value - price
A105: 1 | B105: -0.5 | C105: 1 | D105: =(B105+C105)/2 -> 0.25 | E105: =$C$2*(1+IF(E$3<=$O$2,$D105,$D105-($D105-$I$103)*MIN(E$3-$O$2,$Q$2)/$Q$2)) -> 3212.5 | F105: =E105*(1+IF(F$3<=$O$2,$D105,$D105-($D105-$I$103)*MIN(F$3-$O$2,$Q$2)/$Q$2)) -> 4015.625 | G105: =F105*(1+IF(G$3<=$O$2,$D105,$D105-($D105-$I$103)*MIN(G$3-$O$2,$Q$2)/$Q$2)) -> 5019.5312 | H105: =G105*(1+IF(H$3<=$O$2,$D105,$D105-($D105-$I$103)*MIN(H$3-$O$2,$Q$2)/$Q$2)) -> 6274.4141 | I105: =H105*(1+IF(I$3<=$O$2,$D105,$D105-($D105-$I$103)*MIN(I$3-$O$2,$Q$2)/$Q$2)) -> 7843.0176 | J105: =I105*(1+IF(J$3<=$O$2,$D105,$D105-($D105-$I$103)*MIN(J$3-$O$2,$Q$2)/$Q$2)) -> 9456.0126 | K105: =J105*(1+IF(K$3<=$O$2,$D105,$D105-($D105-$I$103)*MIN(K$3-$O$2,$Q$2)/$Q$2)) -> 10981.457 | L105: =K105*(1+IF(L$3<=$O$2,$D105,$D105-($D105-$I$103)*MIN(L$3-$O$2,$Q$2)/$Q$2)) -> 12266.067 | M105: =L105*(1+IF(M$3<=$O$2,$D105,$D105-($D105-$I$103)*MIN(M$3-$O$2,$Q$2)/$Q$2)) -> 13157.074 | N105: =M105*(1+IF(N$3<=$O$2,$D105,$D105-($D105-$I$103)*MIN(N$3-$O$2,$Q$2)/$Q$2)) -> 13529.42 | O105: =SUMPRODUCT(E105:N105,1/(1+$F$103)^$E$3:$N$3)*$E$2 -> 10181.004 | P105: =N105*$E$2*(1+$I$103)/($F$103-$I$103)/(1+$F$103)^$N$3 -> 22162.162 | Q105: =O105+P105 -> 32343.166 | R105: =Q105-$G$2+$I$2 -> 30966.966 | S105: =R105/$K$2 -> 825.56561 | T105: =S105-$M$2 -> 621.08681
A106: 2 | B106: =IF(T105>0,B105,D105) -> -0.5 | C106: =IF(T105>0,D105,C105) -> 0.25 | D106: =(B106+C106)/2 -> -0.125 | E106: =$C$2*(1+IF(E$3<=$O$2,$D106,$D106-($D106-$I$103)*MIN(E$3-$O$2,$Q$2)/$Q$2)) -> 2248.75 | F106: =E106*(1+IF(F$3<=$O$2,$D106,$D106-($D106-$I$103)*MIN(F$3-$O$2,$Q$2)/$Q$2)) -> 1967.6562 | G106: =F106*(1+IF(G$3<=$O$2,$D106,$D106-($D106-$I$103)*MIN(G$3-$O$2,$Q$2)/$Q$2)) -> 1721.6992 | H106: =G106*(1+IF(H$3<=$O$2,$D106,$D106-($D106-$I$103)*MIN(H$3-$O$2,$Q$2)/$Q$2)) -> 1506.4868 | I106: =H106*(1+IF(I$3<=$O$2,$D106,$D106-($D106-$I$103)*MIN(I$3-$O$2,$Q$2)/$Q$2)) -> 1318.176 | J106: =I106*(1+IF(J$3<=$O$2,$D106,$D106-($D106-$I$103)*MIN(J$3-$O$2,$Q$2)/$Q$2)) -> 1193.8192 | K106: =J106*(1+IF(K$3<=$O$2,$D106,$D106-($D106-$I$103)*MIN(K$3-$O$2,$Q$2)/$Q$2)) -> 1117.7968 | L106: =K106*(1+IF(L$3<=$O$2,$D106,$D106-($D106-$I$103)*MIN(L$3-$O$2,$Q$2)/$Q$2)) -> 1080.8872 | M106: =L106*(1+IF(M$3<=$O$2,$D106,$D106-($D106-$I$103)*MIN(M$3-$O$2,$Q$2)/$Q$2)) -> 1078.3363 | N106: =M106*(1+IF(N$3<=$O$2,$D106,$D106-($D106-$I$103)*MIN(N$3-$O$2,$Q$2)/$Q$2)) -> 1108.8532 | O106: =SUMPRODUCT(E106:N106,1/(1+$F$103)^$E$3:$N$3)*$E$2 -> 2001.7672 | P106: =N106*$E$2*(1+$I$103)/($F$103-$I$103)/(1+$F$103)^$N$3 -> 1816.3813 | Q106: =O106+P106 -> 3818.1484 | R106: =Q106-$G$2+$I$2 -> 2441.9484 | S106: =R106/$K$2 -> 65.101264 | T106: =S106-$M$2 -> -139.37754
A107: 3 | B107: =IF(T106>0,B106,D106) -> -0.125 | C107: =IF(T106>0,D106,C106) -> 0.25 | D107: =(B107+C107)/2 -> 0.0625 | E107: =$C$2*(1+IF(E$3<=$O$2,$D107,$D107-($D107-$I$103)*MIN(E$3-$O$2,$Q$2)/$Q$2)) -> 2730.625 | F107: =E107*(1+IF(F$3<=$O$2,$D107,$D107-($D107-$I$103)*MIN(F$3-$O$2,$Q$2)/$Q$2)) -> 2901.2891 | G107: =F107*(1+IF(G$3<=$O$2,$D107,$D107-($D107-$I$103)*MIN(G$3-$O$2,$Q$2)/$Q$2)) -> 3082.6196 | H107: =G107*(1+IF(H$3<=$O$2,$D107,$D107-($D107-$I$103)*MIN(H$3-$O$2,$Q$2)/$Q$2)) -> 3275.2834 | I107: =H107*(1+IF(I$3<=$O$2,$D107,$D107-($D107-$I$103)*MIN(I$3-$O$2,$Q$2)/$Q$2)) -> 3479.9886 | J107: =I107*(1+IF(J$3<=$O$2,$D107,$D107-($D107-$I$103)*MIN(J$3-$O$2,$Q$2)/$Q$2)) -> 3673.6847 | K107: =J107*(1+IF(K$3<=$O$2,$D107,$D107-($D107-$I$103)*MIN(K$3-$O$2,$Q$2)/$Q$2)) -> 3853.034 | L107: =K107*(1+IF(L$3<=$O$2,$D107,$D107-($D107-$I$103)*MIN(L$3-$O$2,$Q$2)/$Q$2)) -> 4014.7844 | M107: =L107*(1+IF(M$3<=$O$2,$D107,$D107-($D107-$I$103)*MIN(M$3-$O$2,$Q$2)/$Q$2)) -> 4155.8639 | N107: =M107*(1+IF(N$3<=$O$2,$D107,$D107-($D107-$I$103)*MIN(N$3-$O$2,$Q$2)/$Q$2)) -> 4273.4749 | O107: =SUMPRODUCT(E107:N107,1/(1+$F$103)^$E$3:$N$3)*$E$2 -> 4507.6667 | P107: =N107*$E$2*(1+$I$103)/($F$103-$I$103)/(1+$F$103)^$N$3 -> 7000.259 | Q107: =O107+P107 -> 11507.926 | R107: =Q107-$G$2+$I$2 -> 10131.726 | S107: =R107/$K$2 -> 270.10732 | T107: =S107-$M$2 -> 65.628519
A108: 4 | B108: =IF(T107>0,B107,D107) -> -0.125 | C108: =IF(T107>0,D107,C107) -> 0.0625 | D108: =(B108+C108)/2 -> -0.03125 | E108: =$C$2*(1+IF(E$3<=$O$2,$D108,$D108-($D108-$I$103)*MIN(E$3-$O$2,$Q$2)/$Q$2)) -> 2489.6875 | F108: =E108*(1+IF(F$3<=$O$2,$D108,$D108-($D108-$I$103)*MIN(F$3-$O$2,$Q$2)/$Q$2)) -> 2411.8848 | G108: =F108*(1+IF(G$3<=$O$2,$D108,$D108-($D108-$I$103)*MIN(G$3-$O$2,$Q$2)/$Q$2)) -> 2336.5134 | H108: =G108*(1+IF(H$3<=$O$2,$D108,$D108-($D108-$I$103)*MIN(H$3-$O$2,$Q$2)/$Q$2)) -> 2263.4973 | I108: =H108*(1+IF(I$3<=$O$2,$D108,$D108-($D108-$I$103)*MIN(I$3-$O$2,$Q$2)/$Q$2)) -> 2192.763 | J108: =I108*(1+IF(J$3<=$O$2,$D108,$D108-($D108-$I$103)*MIN(J$3-$O$2,$Q$2)/$Q$2)) -> 2150.355 | K108: =J108*(1+IF(K$3<=$O$2,$D108,$D108-($D108-$I$103)*MIN(K$3-$O$2,$Q$2)/$Q$2)) -> 2134.3779 | L108: =K108*(1+IF(L$3<=$O$2,$D108,$D108-($D108-$I$103)*MIN(L$3-$O$2,$Q$2)/$Q$2)) -> 2143.9399 | M108: =L108*(1+IF(M$3<=$O$2,$D108,$D108-($D108-$I$103)*MIN(M$3-$O$2,$Q$2)/$Q$2)) -> 2179.079 | N108: =M108*(1+IF(N$3<=$O$2,$D108,$D108-($D108-$I$103)*MIN(N$3-$O$2,$Q$2)/$Q$2)) -> 2240.747 | O108: =SUMPRODUCT(E108:N108,1/(1+$F$103)^$E$3:$N$3)*$E$2 -> 2995.3366 | P108: =N108*$E$2*(1+$I$103)/($F$103-$I$103)/(1+$F$103)^$N$3 -> 3670.5046 | Q108: =O108+P108 -> 6665.8412 | R108: =Q108-$G$2+$I$2 -> 5289.6412 | S108: =R108/$K$2 -> 141.01949 | T108: =S108-$M$2 -> -63.459311
A109: 5 | B109: =IF(T108>0,B108,D108) -> -0.03125 | C109: =IF(T108>0,D108,C108) -> 0.0625 | D109: =(B109+C109)/2 -> 0.015625 | E109: =$C$2*(1+IF(E$3<=$O$2,$D109,$D109-($D109-$I$103)*MIN(E$3-$O$2,$Q$2)/$Q$2)) -> 2610.1562 | F109: =E109*(1+IF(F$3<=$O$2,$D109,$D109-($D109-$I$103)*MIN(F$3-$O$2,$Q$2)/$Q$2)) -> 2650.9399 | G109: =F109*(1+IF(G$3<=$O$2,$D109,$D109-($D109-$I$103)*MIN(G$3-$O$2,$Q$2)/$Q$2)) -> 2692.3609 | H109: =G109*(1+IF(H$3<=$O$2,$D109,$D109-($D109-$I$103)*MIN(H$3-$O$2,$Q$2)/$Q$2)) -> 2734.429 | I109: =H109*(1+IF(I$3<=$O$2,$D109,$D109-($D109-$I$103)*MIN(I$3-$O$2,$Q$2)/$Q$2)) -> 2777.1545 | J109: =I109*(1+IF(J$3<=$O$2,$D109,$D109-($D109-$I$103)*MIN(J$3-$O$2,$Q$2)/$Q$2)) -> 2827.5876 | K109: =J109*(1+IF(K$3<=$O$2,$D109,$D109-($D109-$I$103)*MIN(K$3-$O$2,$Q$2)/$Q$2)) -> 2886.1045 | L109: =K109*(1+IF(L$3<=$O$2,$D109,$D109-($D109-$I$103)*MIN(L$3-$O$2,$Q$2)/$Q$2)) -> 2953.1487 | M109: =L109*(1+IF(M$3<=$O$2,$D109,$D109-($D109-$I$103)*MIN(M$3-$O$2,$Q$2)/$Q$2)) -> 3029.2366 | N109: =M109*(1+IF(N$3<=$O$2,$D109,$D109-($D109-$I$103)*MIN(N$3-$O$2,$Q$2)/$Q$2)) -> 3114.964 | O109: =SUMPRODUCT(E109:N109,1/(1+$F$103)^$E$3:$N$3)*$E$2 -> 3673.0971 | P109: =N109*$E$2*(1+$I$103)/($F$103-$I$103)/(1+$F$103)^$N$3 -> 5102.535 | Q109: =O109+P109 -> 8775.6321 | R109: =Q109-$G$2+$I$2 -> 7399.4321 | S109: =R109/$K$2 -> 197.26558 | T109: =S109-$M$2 -> -7.2132211
A110: 6 | B110: =IF(T109>0,B109,D109) -> 0.015625 | C110: =IF(T109>0,D109,C109) -> 0.0625 | D110: =(B110+C110)/2 -> 0.0390625 | E110: =$C$2*(1+IF(E$3<=$O$2,$D110,$D110-($D110-$I$103)*MIN(E$3-$O$2,$Q$2)/$Q$2)) -> 2670.3906 | F110: =E110*(1+IF(F$3<=$O$2,$D110,$D110-($D110-$I$103)*MIN(F$3-$O$2,$Q$2)/$Q$2)) -> 2774.7028 | G110: =F110*(1+IF(G$3<=$O$2,$D110,$D110-($D110-$I$103)*MIN(G$3-$O$2,$Q$2)/$Q$2)) -> 2883.0896 | H110: =G110*(1+IF(H$3<=$O$2,$D110,$D110-($D110-$I$103)*MIN(H$3-$O$2,$Q$2)/$Q$2)) -> 2995.7103 | I110: =H110*(1+IF(I$3<=$O$2,$D110,$D110-($D110-$I$103)*MIN(I$3-$O$2,$Q$2)/$Q$2)) -> 3112.7302 | J110: =I110*(1+IF(J$3<=$O$2,$D110,$D110-($D110-$I$103)*MIN(J$3-$O$2,$Q$2)/$Q$2)) -> 3227.6211 | K110: =J110*(1+IF(K$3<=$O$2,$D110,$D110-($D110-$I$103)*MIN(K$3-$O$2,$Q$2)/$Q$2)) -> 3339.8051 | L110: =K110*(1+IF(L$3<=$O$2,$D110,$D110-($D110-$I$103)*MIN(L$3-$O$2,$Q$2)/$Q$2)) -> 3448.6995 | M110: =L110*(1+IF(M$3<=$O$2,$D110,$D110-($D110-$I$103)*MIN(M$3-$O$2,$Q$2)/$Q$2)) -> 3553.721 | N110: =M110*(1+IF(N$3<=$O$2,$D110,$D110-($D110-$I$103)*MIN(N$3-$O$2,$Q$2)/$Q$2)) -> 3654.2913 | O110: =SUMPRODUCT(E110:N110,1/(1+$F$103)^$E$3:$N$3)*$E$2 -> 4068.8173 | P110: =N110*$E$2*(1+$I$103)/($F$103-$I$103)/(1+$F$103)^$N$3 -> 5985.9918 | Q110: =O110+P110 -> 10054.809 | R110: =Q110-$G$2+$I$2 -> 8678.6091 | S110: =R110/$K$2 -> 231.36788 | T110: =S110-$M$2 -> 26.889072
A111: 7 | B111: =IF(T110>0,B110,D110) -> 0.015625 | C111: =IF(T110>0,D110,C110) -> 0.0390625 | D111: =(B111+C111)/2 -> 0.02734375 | E111: =$C$2*(1+IF(E$3<=$O$2,$D111,$D111-($D111-$I$103)*MIN(E$3-$O$2,$Q$2)/$Q$2)) -> 2640.2734 | F111: =E111*(1+IF(F$3<=$O$2,$D111,$D111-($D111-$I$103)*MIN(F$3-$O$2,$Q$2)/$Q$2)) -> 2712.4684 | G111: =F111*(1+IF(G$3<=$O$2,$D111,$D111-($D111-$I$103)*MIN(G$3-$O$2,$Q$2)/$Q$2)) -> 2786.6375 | H111: =G111*(1+IF(H$3<=$O$2,$D111,$D111-($D111-$I$103)*MIN(H$3-$O$2,$Q$2)/$Q$2)) -> 2862.8346 | I111: =H111*(1+IF(I$3<=$O$2,$D111,$D111-($D111-$I$103)*MIN(I$3-$O$2,$Q$2)/$Q$2)) -> 2941.1152 | J111: =I111*(1+IF(J$3<=$O$2,$D111,$D111-($D111-$I$103)*MIN(J$3-$O$2,$Q$2)/$Q$2)) -> 3022.0988 | K111: =J111*(1+IF(K$3<=$O$2,$D111,$D111-($D111-$I$103)*MIN(K$3-$O$2,$Q$2)/$Q$2)) -> 3105.8903 | L111: =K111*(1+IF(L$3<=$O$2,$D111,$D111-($D111-$I$103)*MIN(L$3-$O$2,$Q$2)/$Q$2)) -> 3192.599 | M111: =L111*(1+IF(M$3<=$O$2,$D111,$D111-($D111-$I$103)*MIN(M$3-$O$2,$Q$2)/$Q$2)) -> 3282.339 | N111: =M111*(1+IF(N$3<=$O$2,$D111,$D111-($D111-$I$103)*MIN(N$3-$O$2,$Q$2)/$Q$2)) -> 3375.2292 | O111: =SUMPRODUCT(E111:N111,1/(1+$F$103)^$E$3:$N$3)*$E$2 -> 3865.8246 | P111: =N111*$E$2*(1+$I$103)/($F$103-$I$103)/(1+$F$103)^$N$3 -> 5528.868 | Q111: =O111+P111 -> 9394.6926 | R111: =Q111-$G$2+$I$2 -> 8018.4926 | S111: =R111/$K$2 -> 213.76946 | T111: =S111-$M$2 -> 9.2906577
A112: 8 | B112: =IF(T111>0,B111,D111) -> 0.015625 | C112: =IF(T111>0,D111,C111) -> 0.02734375 | D112: =(B112+C112)/2 -> 0.021484375 | E112: =$C$2*(1+IF(E$3<=$O$2,$D112,$D112-($D112-$I$103)*MIN(E$3-$O$2,$Q$2)/$Q$2)) -> 2625.2148 | F112: =E112*(1+IF(F$3<=$O$2,$D112,$D112-($D112-$I$103)*MIN(F$3-$O$2,$Q$2)/$Q$2)) -> 2681.6159 | G112: =F112*(1+IF(G$3<=$O$2,$D112,$D112-($D112-$I$103)*MIN(G$3-$O$2,$Q$2)/$Q$2)) -> 2739.2288 | H112: =G112*(1+IF(H$3<=$O$2,$D112,$D112-($D112-$I$103)*MIN(H$3-$O$2,$Q$2)/$Q$2)) -> 2798.0794 | I112: =H112*(1+IF(I$3<=$O$2,$D112,$D112-($D112-$I$103)*MIN(I$3-$O$2,$Q$2)/$Q$2)) -> 2858.1944 | J112: =I112*(1+IF(J$3<=$O$2,$D112,$D112-($D112-$I$103)*MIN(J$3-$O$2,$Q$2)/$Q$2)) -> 2923.497 | K112: =J112*(1+IF(K$3<=$O$2,$D112,$D112-($D112-$I$103)*MIN(K$3-$O$2,$Q$2)/$Q$2)) -> 2994.2767 | L112: =K112*(1+IF(L$3<=$O$2,$D112,$D112-($D112-$I$103)*MIN(L$3-$O$2,$Q$2)/$Q$2)) -> 3070.8516 | M112: =L112*(1+IF(M$3<=$O$2,$D112,$D112-($D112-$I$103)*MIN(M$3-$O$2,$Q$2)/$Q$2)) -> 3153.5707 | N112: =M112*(1+IF(N$3<=$O$2,$D112,$D112-($D112-$I$103)*MIN(N$3-$O$2,$Q$2)/$Q$2)) -> 3242.8168 | O112: =SUMPRODUCT(E112:N112,1/(1+$F$103)^$E$3:$N$3)*$E$2 -> 3768.2088 | P112: =N112*$E$2*(1+$I$103)/($F$103-$I$103)/(1+$F$103)^$N$3 -> 5311.967 | Q112: =O112+P112 -> 9080.1758 | R112: =Q112-$G$2+$I$2 -> 7703.9758 | S112: =R112/$K$2 -> 205.38459 | T112: =S112-$M$2 -> 0.90577984
A113: 9 | B113: =IF(T112>0,B112,D112) -> 0.015625 | C113: =IF(T112>0,D112,C112) -> 0.021484375 | D113: =(B113+C113)/2 -> 0.018554688 | E113: =$C$2*(1+IF(E$3<=$O$2,$D113,$D113-($D113-$I$103)*MIN(E$3-$O$2,$Q$2)/$Q$2)) -> 2617.6855 | F113: =E113*(1+IF(F$3<=$O$2,$D113,$D113-($D113-$I$103)*MIN(F$3-$O$2,$Q$2)/$Q$2)) -> 2666.2559 | G113: =F113*(1+IF(G$3<=$O$2,$D113,$D113-($D113-$I$103)*MIN(G$3-$O$2,$Q$2)/$Q$2)) -> 2715.7274 | H113: =G113*(1+IF(H$3<=$O$2,$D113,$D113-($D113-$I$103)*MIN(H$3-$O$2,$Q$2)/$Q$2)) -> 2766.1169 | I113: =H113*(1+IF(I$3<=$O$2,$D113,$D113-($D113-$I$103)*MIN(I$3-$O$2,$Q$2)/$Q$2)) -> 2817.4413 | J113: =I113*(1+IF(J$3<=$O$2,$D113,$D113-($D113-$I$103)*MIN(J$3-$O$2,$Q$2)/$Q$2)) -> 2875.2095 | K113: =J113*(1+IF(K$3<=$O$2,$D113,$D113-($D113-$I$103)*MIN(K$3-$O$2,$Q$2)/$Q$2)) -> 2939.766 | L113: =K113*(1+IF(L$3<=$O$2,$D113,$D113-($D113-$I$103)*MIN(L$3-$O$2,$Q$2)/$Q$2)) -> 3011.5018 | M113: =L113*(1+IF(M$3<=$O$2,$D113,$D113-($D113-$I$103)*MIN(M$3-$O$2,$Q$2)/$Q$2)) -> 3090.8577 | N113: =M113*(1+IF(N$3<=$O$2,$D113,$D113-($D113-$I$103)*MIN(N$3-$O$2,$Q$2)/$Q$2)) -> 3178.329 | O113: =SUMPRODUCT(E113:N113,1/(1+$F$103)^$E$3:$N$3)*$E$2 -> 3720.3438 | P113: =N113*$E$2*(1+$I$103)/($F$103-$I$103)/(1+$F$103)^$N$3 -> 5206.3313 | Q113: =O113+P113 -> 8926.6751 | R113: =Q113-$G$2+$I$2 -> 7550.4751 | S113: =R113/$K$2 -> 201.29232 | T113: =S113-$M$2 -> -3.1864807
A114: 10 | B114: =IF(T113>0,B113,D113) -> 0.018554688 | C114: =IF(T113>0,D113,C113) -> 0.021484375 | D114: =(B114+C114)/2 -> 0.020019531 | E114: =$C$2*(1+IF(E$3<=$O$2,$D114,$D114-($D114-$I$103)*MIN(E$3-$O$2,$Q$2)/$Q$2)) -> 2621.4502 | F114: =E114*(1+IF(F$3<=$O$2,$D114,$D114-($D114-$I$103)*MIN(F$3-$O$2,$Q$2)/$Q$2)) -> 2673.9304 | G114: =F114*(1+IF(G$3<=$O$2,$D114,$D114-($D114-$I$103)*MIN(G$3-$O$2,$Q$2)/$Q$2)) -> 2727.4612 | H114: =G114*(1+IF(H$3<=$O$2,$D114,$D114-($D114-$I$103)*MIN(H$3-$O$2,$Q$2)/$Q$2)) -> 2782.0637 | I114: =H114*(1+IF(I$3<=$O$2,$D114,$D114-($D114-$I$103)*MIN(I$3-$O$2,$Q$2)/$Q$2)) -> 2837.7593 | J114: =I114*(1+IF(J$3<=$O$2,$D114,$D114-($D114-$I$103)*MIN(J$3-$O$2,$Q$2)/$Q$2)) -> 2899.2695 | K114: =J114*(1+IF(K$3<=$O$2,$D114,$D114-($D114-$I$103)*MIN(K$3-$O$2,$Q$2)/$Q$2)) -> 2966.9145 | L114: =K114*(1+IF(L$3<=$O$2,$D114,$D114-($D114-$I$103)*MIN(L$3-$O$2,$Q$2)/$Q$2)) -> 3041.0512 | M114: =L114*(1+IF(M$3<=$O$2,$D114,$D114-($D114-$I$103)*MIN(M$3-$O$2,$Q$2)/$Q$2)) -> 3122.0767 | N114: =M114*(1+IF(N$3<=$O$2,$D114,$D114-($D114-$I$103)*MIN(N$3-$O$2,$Q$2)/$Q$2)) -> 3210.4314 | O114: =SUMPRODUCT(E114:N114,1/(1+$F$103)^$E$3:$N$3)*$E$2 -> 3744.1986 | P114: =N114*$E$2*(1+$I$103)/($F$103-$I$103)/(1+$F$103)^$N$3 -> 5258.9175 | Q114: =O114+P114 -> 9003.116 | R114: =Q114-$G$2+$I$2 -> 7626.916 | S114: =R114/$K$2 -> 203.33021 | T114: =S114-$M$2 -> -1.1485993
A115: 11 | B115: =IF(T114>0,B114,D114) -> 0.020019531 | C115: =IF(T114>0,D114,C114) -> 0.021484375 | D115: =(B115+C115)/2 -> 0.020751953 | E115: =$C$2*(1+IF(E$3<=$O$2,$D115,$D115-($D115-$I$103)*MIN(E$3-$O$2,$Q$2)/$Q$2)) -> 2623.3325 | F115: =E115*(1+IF(F$3<=$O$2,$D115,$D115-($D115-$I$103)*MIN(F$3-$O$2,$Q$2)/$Q$2)) -> 2677.7718 | G115: =F115*(1+IF(G$3<=$O$2,$D115,$D115-($D115-$I$103)*MIN(G$3-$O$2,$Q$2)/$Q$2)) -> 2733.3408 | H115: =G115*(1+IF(H$3<=$O$2,$D115,$D115-($D115-$I$103)*MIN(H$3-$O$2,$Q$2)/$Q$2)) -> 2790.0629 | I115: =H115*(1+IF(I$3<=$O$2,$D115,$D115-($D115-$I$103)*MIN(I$3-$O$2,$Q$2)/$Q$2)) -> 2847.9622 | J115: =I115*(1+IF(J$3<=$O$2,$D115,$D115-($D115-$I$103)*MIN(J$3-$O$2,$Q$2)/$Q$2)) -> 2911.3623 | K115: =J115*(1+IF(K$3<=$O$2,$D115,$D115-($D115-$I$103)*MIN(K$3-$O$2,$Q$2)/$Q$2)) -> 2980.5688 | L115: =K115*(1+IF(L$3<=$O$2,$D115,$D115-($D115-$I$103)*MIN(L$3-$O$2,$Q$2)/$Q$2)) -> 3055.9199 | M115: =L115*(1+IF(M$3<=$O$2,$D115,$D115-($D115-$I$103)*MIN(M$3-$O$2,$Q$2)/$Q$2)) -> 3137.7892 | N115: =M115*(1+IF(N$3<=$O$2,$D115,$D115-($D115-$I$103)*MIN(N$3-$O$2,$Q$2)/$Q$2)) -> 3226.5886 | O115: =SUMPRODUCT(E115:N115,1/(1+$F$103)^$E$3:$N$3)*$E$2 -> 3756.1842 | P115: =N115*$E$2*(1+$I$103)/($F$103-$I$103)/(1+$F$103)^$N$3 -> 5285.3841 | Q115: =O115+P115 -> 9041.5683 | R115: =Q115-$G$2+$I$2 -> 7665.3683 | S115: =R115/$K$2 -> 204.35533 | T115: =S115-$M$2 -> -0.12347935
A116: 12 | B116: =IF(T115>0,B115,D115) -> 0.020751953 | C116: =IF(T115>0,D115,C115) -> 0.021484375 | D116: =(B116+C116)/2 -> 0.021118164 | E116: =$C$2*(1+IF(E$3<=$O$2,$D116,$D116-($D116-$I$103)*MIN(E$3-$O$2,$Q$2)/$Q$2)) -> 2624.2737 | F116: =E116*(1+IF(F$3<=$O$2,$D116,$D116-($D116-$I$103)*MIN(F$3-$O$2,$Q$2)/$Q$2)) -> 2679.6935 | G116: =F116*(1+IF(G$3<=$O$2,$D116,$D116-($D116-$I$103)*MIN(G$3-$O$2,$Q$2)/$Q$2)) -> 2736.2837 | H116: =G116*(1+IF(H$3<=$O$2,$D116,$D116-($D116-$I$103)*MIN(H$3-$O$2,$Q$2)/$Q$2)) -> 2794.069 | I116: =H116*(1+IF(I$3<=$O$2,$D116,$D116-($D116-$I$103)*MIN(I$3-$O$2,$Q$2)/$Q$2)) -> 2853.0746 | J116: =I116*(1+IF(J$3<=$O$2,$D116,$D116-($D116-$I$103)*MIN(J$3-$O$2,$Q$2)/$Q$2)) -> 2917.4244 | K116: =J116*(1+IF(K$3<=$O$2,$D116,$D116-($D116-$I$103)*MIN(K$3-$O$2,$Q$2)/$Q$2)) -> 2987.416 | L116: =K116*(1+IF(L$3<=$O$2,$D116,$D116-($D116-$I$103)*MIN(L$3-$O$2,$Q$2)/$Q$2)) -> 3063.3778 | M116: =L116*(1+IF(M$3<=$O$2,$D116,$D116-($D116-$I$103)*MIN(M$3-$O$2,$Q$2)/$Q$2)) -> 3145.6713 | N116: =M116*(1+IF(N$3<=$O$2,$D116,$D116-($D116-$I$103)*MIN(N$3-$O$2,$Q$2)/$Q$2)) -> 3234.6938 | O116: =SUMPRODUCT(E116:N116,1/(1+$F$103)^$E$3:$N$3)*$E$2 -> 3762.1916 | P116: =N116*$E$2*(1+$I$103)/($F$103-$I$103)/(1+$F$103)^$N$3 -> 5298.661 | Q116: =O116+P116 -> 9060.8526 | R116: =Q116-$G$2+$I$2 -> 7684.6526 | S116: =R116/$K$2 -> 204.86944 | T116: =S116-$M$2 -> 0.39063191
A117: 13 | B117: =IF(T116>0,B116,D116) -> 0.020751953 | C117: =IF(T116>0,D116,C116) -> 0.021118164 | D117: =(B117+C117)/2 -> 0.020935059 | E117: =$C$2*(1+IF(E$3<=$O$2,$D117,$D117-($D117-$I$103)*MIN(E$3-$O$2,$Q$2)/$Q$2)) -> 2623.8031 | F117: =E117*(1+IF(F$3<=$O$2,$D117,$D117-($D117-$I$103)*MIN(F$3-$O$2,$Q$2)/$Q$2)) -> 2678.7326 | G117: =F117*(1+IF(G$3<=$O$2,$D117,$D117-($D117-$I$103)*MIN(G$3-$O$2,$Q$2)/$Q$2)) -> 2734.812 | H117: =G117*(1+IF(H$3<=$O$2,$D117,$D117-($D117-$I$103)*MIN(H$3-$O$2,$Q$2)/$Q$2)) -> 2792.0654 | I117: =H117*(1+IF(I$3<=$O$2,$D117,$D117-($D117-$I$103)*MIN(I$3-$O$2,$Q$2)/$Q$2)) -> 2850.5175 | J117: =I117*(1+IF(J$3<=$O$2,$D117,$D117-($D117-$I$103)*MIN(J$3-$O$2,$Q$2)/$Q$2)) -> 2914.392 | K117: =J117*(1+IF(K$3<=$O$2,$D117,$D117-($D117-$I$103)*MIN(K$3-$O$2,$Q$2)/$Q$2)) -> 2983.9907 | L117: =K117*(1+IF(L$3<=$O$2,$D117,$D117-($D117-$I$103)*MIN(L$3-$O$2,$Q$2)/$Q$2)) -> 3059.6469 | M117: =L117*(1+IF(M$3<=$O$2,$D117,$D117-($D117-$I$103)*MIN(M$3-$O$2,$Q$2)/$Q$2)) -> 3141.7281 | N117: =M117*(1+IF(N$3<=$O$2,$D117,$D117-($D117-$I$103)*MIN(N$3-$O$2,$Q$2)/$Q$2)) -> 3230.639 | O117: =SUMPRODUCT(E117:N117,1/(1+$F$103)^$E$3:$N$3)*$E$2 -> 3759.1867 | P117: =N117*$E$2*(1+$I$103)/($F$103-$I$103)/(1+$F$103)^$N$3 -> 5292.0189 | Q117: =O117+P117 -> 9051.2056 | R117: =Q117-$G$2+$I$2 -> 7675.0056 | S117: =R117/$K$2 -> 204.61225 | T117: =S117-$M$2 -> 0.13344681
... A128: 24 | B128: =IF(T127>0,B127,D127) -> 0.02083993 | C128: =IF(T127>0,D127,C127) -> 0.020840108 | D128: =(B128+C128)/2 -> 0.020840019 | E128: =$C$2*(1+IF(E$3<=$O$2,$D128,$D128-($D128-$I$103)*MIN(E$3-$O$2,$Q$2)/$Q$2)) -> 2623.5588 | F128: =E128*(1+IF(F$3<=$O$2,$D128,$D128-($D128-$I$103)*MIN(F$3-$O$2,$Q$2)/$Q$2)) -> 2678.2339 | G128: =F128*(1+IF(G$3<=$O$2,$D128,$D128-($D128-$I$103)*MIN(G$3-$O$2,$Q$2)/$Q$2)) -> 2734.0483 | H128: =G128*(1+IF(H$3<=$O$2,$D128,$D128-($D128-$I$103)*MIN(H$3-$O$2,$Q$2)/$Q$2)) -> 2791.0259 | I128: =H128*(1+IF(I$3<=$O$2,$D128,$D128-($D128-$I$103)*MIN(I$3-$O$2,$Q$2)/$Q$2)) -> 2849.191 | J128: =I128*(1+IF(J$3<=$O$2,$D128,$D128-($D128-$I$103)*MIN(J$3-$O$2,$Q$2)/$Q$2)) -> 2912.8191 | K128: =J128*(1+IF(K$3<=$O$2,$D128,$D128-($D128-$I$103)*MIN(K$3-$O$2,$Q$2)/$Q$2)) -> 2982.2142 | L128: =K128*(1+IF(L$3<=$O$2,$D128,$D128-($D128-$I$103)*MIN(L$3-$O$2,$Q$2)/$Q$2)) -> 3057.7119 | M128: =L128*(1+IF(M$3<=$O$2,$D128,$D128-($D128-$I$103)*MIN(M$3-$O$2,$Q$2)/$Q$2)) -> 3139.6831 | N128: =M128*(1+IF(N$3<=$O$2,$D128,$D128-($D128-$I$103)*MIN(N$3-$O$2,$Q$2)/$Q$2)) -> 3228.5361 | O128: =SUMPRODUCT(E128:N128,1/(1+$F$103)^$E$3:$N$3)*$E$2 -> 3757.628 | P128: =N128*$E$2*(1+$I$103)/($F$103-$I$103)/(1+$F$103)^$N$3 -> 5288.5742 | Q128: =O128+P128 -> 9046.2022 | R128: =Q128-$G$2+$I$2 -> 7670.0022 | S128: =R128/$K$2 -> 204.47886 | T128: =S128-$M$2 -> 5.8787648e-05
A130: Grid block 5: row 1, column 4 of table A (24 steps) | E130: WACC | F130: =Sensitivity!$B$10 -> 0.084183338 | G130: Terminal growth | I130: =Sensitivity!$F$9 -> 0.0333
A131: Step | B131: Low | C131: High | D131: Mid | E131: Rev Y1 | F131: Rev Y2 | G131: Rev Y3 | H131: Rev Y4 | I131: Rev Y5 | J131: Rev Y6 | K131: Rev Y7 | L131: Rev Y8 | M131: Rev Y9 | N131: Rev Y10 | O131: PV of FCF | P131: PV of TV | Q131: EV | R131: Equity | S131: Per share | T131: Value - price
A132: 1 | B132: -0.5 | C132: 1 | D132: =(B132+C132)/2 -> 0.25 | E132: =$C$2*(1+IF(E$3<=$O$2,$D132,$D132-($D132-$I$130)*MIN(E$3-$O$2,$Q$2)/$Q$2)) -> 3212.5 | F132: =E132*(1+IF(F$3<=$O$2,$D132,$D132-($D132-$I$130)*MIN(F$3-$O$2,$Q$2)/$Q$2)) -> 4015.625 | G132: =F132*(1+IF(G$3<=$O$2,$D132,$D132-($D132-$I$130)*MIN(G$3-$O$2,$Q$2)/$Q$2)) -> 5019.5312 | H132: =G132*(1+IF(H$3<=$O$2,$D132,$D132-($D132-$I$130)*MIN(H$3-$O$2,$Q$2)/$Q$2)) -> 6274.4141 | I132: =H132*(1+IF(I$3<=$O$2,$D132,$D132-($D132-$I$130)*MIN(I$3-$O$2,$Q$2)/$Q$2)) -> 7843.0176 | J132: =I132*(1+IF(J$3<=$O$2,$D132,$D132-($D132-$I$130)*MIN(J$3-$O$2,$Q$2)/$Q$2)) -> 9463.8556 | K132: =J132*(1+IF(K$3<=$O$2,$D132,$D132-($D132-$I$130)*MIN(K$3-$O$2,$Q$2)/$Q$2)) -> 11009.492 | L132: =K132*(1+IF(L$3<=$O$2,$D132,$D132-($D132-$I$130)*MIN(L$3-$O$2,$Q$2)/$Q$2)) -> 12330.411 | M132: =L132*(1+IF(M$3<=$O$2,$D132,$D132-($D132-$I$130)*MIN(M$3-$O$2,$Q$2)/$Q$2)) -> 13275.414 | N132: =M132*(1+IF(N$3<=$O$2,$D132,$D132-($D132-$I$130)*MIN(N$3-$O$2,$Q$2)/$Q$2)) -> 13717.485 | O132: =SUMPRODUCT(E132:N132,1/(1+$F$130)^$E$3:$N$3)*$E$2 -> 10220.046 | P132: =N132*$E$2*(1+$I$130)/($F$130-$I$130)/(1+$F$130)^$N$3 -> 24798.237 | Q132: =O132+P132 -> 35018.283 | R132: =Q132-$G$2+$I$2 -> 33642.083 | S132: =R132/$K$2 -> 896.88304 | T132: =S132-$M$2 -> 692.40424
A133: 2 | B133: =IF(T132>0,B132,D132) -> -0.5 | C133: =IF(T132>0,D132,C132) -> 0.25 | D133: =(B133+C133)/2 -> -0.125 | E133: =$C$2*(1+IF(E$3<=$O$2,$D133,$D133-($D133-$I$130)*MIN(E$3-$O$2,$Q$2)/$Q$2)) -> 2248.75 | F133: =E133*(1+IF(F$3<=$O$2,$D133,$D133-($D133-$I$130)*MIN(F$3-$O$2,$Q$2)/$Q$2)) -> 1967.6562 | G133: =F133*(1+IF(G$3<=$O$2,$D133,$D133-($D133-$I$130)*MIN(G$3-$O$2,$Q$2)/$Q$2)) -> 1721.6992 | H133: =G133*(1+IF(H$3<=$O$2,$D133,$D133-($D133-$I$130)*MIN(H$3-$O$2,$Q$2)/$Q$2)) -> 1506.4868 | I133: =H133*(1+IF(I$3<=$O$2,$D133,$D133-($D133-$I$130)*MIN(I$3-$O$2,$Q$2)/$Q$2)) -> 1318.176 | J133: =I133*(1+IF(J$3<=$O$2,$D133,$D133-($D133-$I$130)*MIN(J$3-$O$2,$Q$2)/$Q$2)) -> 1195.1374 | K133: =J133*(1+IF(K$3<=$O$2,$D133,$D133-($D133-$I$130)*MIN(K$3-$O$2,$Q$2)/$Q$2)) -> 1121.4213 | L133: =K133*(1+IF(L$3<=$O$2,$D133,$D133-($D133-$I$130)*MIN(L$3-$O$2,$Q$2)/$Q$2)) -> 1087.7563 | M133: =L133*(1+IF(M$3<=$O$2,$D133,$D133-($D133-$I$130)*MIN(M$3-$O$2,$Q$2)/$Q$2)) -> 1089.5402 | N133: =M133*(1+IF(N$3<=$O$2,$D133,$D133-($D133-$I$130)*MIN(N$3-$O$2,$Q$2)/$Q$2)) -> 1125.8219 | O133: =SUMPRODUCT(E133:N133,1/(1+$F$130)^$E$3:$N$3)*$E$2 -> 2005.6512 | P133: =N133*$E$2*(1+$I$130)/($F$130-$I$130)/(1+$F$130)^$N$3 -> 2035.2417 | Q133: =O133+P133 -> 4040.8929 | R133: =Q133-$G$2+$I$2 -> 2664.6929 | S133: =R133/$K$2 -> 71.039533 | T133: =S133-$M$2 -> -133.43927
A134: 3 | B134: =IF(T133>0,B133,D133) -> -0.125 | C134: =IF(T133>0,D133,C133) -> 0.25 | D134: =(B134+C134)/2 -> 0.0625 | E134: =$C$2*(1+IF(E$3<=$O$2,$D134,$D134-($D134-$I$130)*MIN(E$3-$O$2,$Q$2)/$Q$2)) -> 2730.625 | F134: =E134*(1+IF(F$3<=$O$2,$D134,$D134-($D134-$I$130)*MIN(F$3-$O$2,$Q$2)/$Q$2)) -> 2901.2891 | G134: =F134*(1+IF(G$3<=$O$2,$D134,$D134-($D134-$I$130)*MIN(G$3-$O$2,$Q$2)/$Q$2)) -> 3082.6196 | H134: =G134*(1+IF(H$3<=$O$2,$D134,$D134-($D134-$I$130)*MIN(H$3-$O$2,$Q$2)/$Q$2)) -> 3275.2834 | I134: =H134*(1+IF(I$3<=$O$2,$D134,$D134-($D134-$I$130)*MIN(I$3-$O$2,$Q$2)/$Q$2)) -> 3479.9886 | J134: =I134*(1+IF(J$3<=$O$2,$D134,$D134-($D134-$I$130)*MIN(J$3-$O$2,$Q$2)/$Q$2)) -> 3677.1647 | K134: =J134*(1+IF(K$3<=$O$2,$D134,$D134-($D134-$I$130)*MIN(K$3-$O$2,$Q$2)/$Q$2)) -> 3864.0382 | L134: =K134*(1+IF(L$3<=$O$2,$D134,$D134-($D134-$I$130)*MIN(L$3-$O$2,$Q$2)/$Q$2)) -> 4037.8427 | M134: =L134*(1+IF(M$3<=$O$2,$D134,$D134-($D134-$I$130)*MIN(M$3-$O$2,$Q$2)/$Q$2)) -> 4195.8838 | N134: =M134*(1+IF(N$3<=$O$2,$D134,$D134-($D134-$I$130)*MIN(N$3-$O$2,$Q$2)/$Q$2)) -> 4335.6068 | O134: =SUMPRODUCT(E134:N134,1/(1+$F$130)^$E$3:$N$3)*$E$2 -> 4521.1497 | P134: =N134*$E$2*(1+$I$130)/($F$130-$I$130)/(1+$F$130)^$N$3 -> 7837.8362 | Q134: =O134+P134 -> 12358.986 | R134: =Q134-$G$2+$I$2 -> 10982.786 | S134: =R134/$K$2 -> 292.79621 | T134: =S134-$M$2 -> 88.317404
A135: 4 | B135: =IF(T134>0,B134,D134) -> -0.125 | C135: =IF(T134>0,D134,C134) -> 0.0625 | D135: =(B135+C135)/2 -> -0.03125 | E135: =$C$2*(1+IF(E$3<=$O$2,$D135,$D135-($D135-$I$130)*MIN(E$3-$O$2,$Q$2)/$Q$2)) -> 2489.6875 | F135: =E135*(1+IF(F$3<=$O$2,$D135,$D135-($D135-$I$130)*MIN(F$3-$O$2,$Q$2)/$Q$2)) -> 2411.8848 | G135: =F135*(1+IF(G$3<=$O$2,$D135,$D135-($D135-$I$130)*MIN(G$3-$O$2,$Q$2)/$Q$2)) -> 2336.5134 | H135: =G135*(1+IF(H$3<=$O$2,$D135,$D135-($D135-$I$130)*MIN(H$3-$O$2,$Q$2)/$Q$2)) -> 2263.4973 | I135: =H135*(1+IF(I$3<=$O$2,$D135,$D135-($D135-$I$130)*MIN(I$3-$O$2,$Q$2)/$Q$2)) -> 2192.763 | J135: =I135*(1+IF(J$3<=$O$2,$D135,$D135-($D135-$I$130)*MIN(J$3-$O$2,$Q$2)/$Q$2)) -> 2152.5478 | K135: =J135*(1+IF(K$3<=$O$2,$D135,$D135-($D135-$I$130)*MIN(K$3-$O$2,$Q$2)/$Q$2)) -> 2140.8594 | L135: =K135*(1+IF(L$3<=$O$2,$D135,$D135-($D135-$I$130)*MIN(L$3-$O$2,$Q$2)/$Q$2)) -> 2156.8731 | M135: =L135*(1+IF(M$3<=$O$2,$D135,$D135-($D135-$I$130)*MIN(M$3-$O$2,$Q$2)/$Q$2)) -> 2200.8517 | N135: =M135*(1+IF(N$3<=$O$2,$D135,$D135-($D135-$I$130)*MIN(N$3-$O$2,$Q$2)/$Q$2)) -> 2274.1401 | O135: =SUMPRODUCT(E135:N135,1/(1+$F$130)^$E$3:$N$3)*$E$2 -> 3002.7691 | P135: =N135*$E$2*(1+$I$130)/($F$130-$I$130)/(1+$F$130)^$N$3 -> 4111.1517 | Q135: =O135+P135 -> 7113.9208 | R135: =Q135-$G$2+$I$2 -> 5737.7208 | S135: =R135/$K$2 -> 152.9651 | T135: =S135-$M$2 -> -51.513708
A136: 5 | B136: =IF(T135>0,B135,D135) -> -0.03125 | C136: =IF(T135>0,D135,C135) -> 0.0625 | D136: =(B136+C136)/2 -> 0.015625 | E136: =$C$2*(1+IF(E$3<=$O$2,$D136,$D136-($D136-$I$130)*MIN(E$3-$O$2,$Q$2)/$Q$2)) -> 2610.1562 | F136: =E136*(1+IF(F$3<=$O$2,$D136,$D136-($D136-$I$130)*MIN(F$3-$O$2,$Q$2)/$Q$2)) -> 2650.9399 | G136: =F136*(1+IF(G$3<=$O$2,$D136,$D136-($D136-$I$130)*MIN(G$3-$O$2,$Q$2)/$Q$2)) -> 2692.3609 | H136: =G136*(1+IF(H$3<=$O$2,$D136,$D136-($D136-$I$130)*MIN(H$3-$O$2,$Q$2)/$Q$2)) -> 2734.429 | I136: =H136*(1+IF(I$3<=$O$2,$D136,$D136-($D136-$I$130)*MIN(I$3-$O$2,$Q$2)/$Q$2)) -> 2777.1545 | J136: =I136*(1+IF(J$3<=$O$2,$D136,$D136-($D136-$I$130)*MIN(J$3-$O$2,$Q$2)/$Q$2)) -> 2830.3647 | K136: =J136*(1+IF(K$3<=$O$2,$D136,$D136-($D136-$I$130)*MIN(K$3-$O$2,$Q$2)/$Q$2)) -> 2894.5999 | L136: =K136*(1+IF(L$3<=$O$2,$D136,$D136-($D136-$I$130)*MIN(L$3-$O$2,$Q$2)/$Q$2)) -> 2970.5252 | M136: =L136*(1+IF(M$3<=$O$2,$D136,$D136-($D136-$I$130)*MIN(M$3-$O$2,$Q$2)/$Q$2)) -> 3058.9429 | N136: =M136*(1+IF(N$3<=$O$2,$D136,$D136-($D136-$I$130)*MIN(N$3-$O$2,$Q$2)/$Q$2)) -> 3160.8057 | O136: =SUMPRODUCT(E136:N136,1/(1+$F$130)^$E$3:$N$3)*$E$2 -> 3683.1688 | P136: =N136*$E$2*(1+$I$130)/($F$130-$I$130)/(1+$F$130)^$N$3 -> 5714.0508 | Q136: =O136+P136 -> 9397.2196 | R136: =Q136-$G$2+$I$2 -> 8021.0196 | S136: =R136/$K$2 -> 213.83683 | T136: =S136-$M$2 -> 9.3580283
A137: 6 | B137: =IF(T136>0,B136,D136) -> -0.03125 | C137: =IF(T136>0,D136,C136) -> 0.015625 | D137: =(B137+C137)/2 -> -0.0078125 | E137: =$C$2*(1+IF(E$3<=$O$2,$D137,$D137-($D137-$I$130)*MIN(E$3-$O$2,$Q$2)/$Q$2)) -> 2549.9219 | F137: =E137*(1+IF(F$3<=$O$2,$D137,$D137-($D137-$I$130)*MIN(F$3-$O$2,$Q$2)/$Q$2)) -> 2530.0006 | G137: =F137*(1+IF(G$3<=$O$2,$D137,$D137-($D137-$I$130)*MIN(G$3-$O$2,$Q$2)/$Q$2)) -> 2510.235 | H137: =G137*(1+IF(H$3<=$O$2,$D137,$D137-($D137-$I$130)*MIN(H$3-$O$2,$Q$2)/$Q$2)) -> 2490.6238 | I137: =H137*(1+IF(I$3<=$O$2,$D137,$D137-($D137-$I$130)*MIN(I$3-$O$2,$Q$2)/$Q$2)) -> 2471.1658 | J137: =I137*(1+IF(J$3<=$O$2,$D137,$D137-($D137-$I$130)*MIN(J$3-$O$2,$Q$2)/$Q$2)) -> 2472.1789 | K137: =J137*(1+IF(K$3<=$O$2,$D137,$D137-($D137-$I$130)*MIN(K$3-$O$2,$Q$2)/$Q$2)) -> 2493.52 | L137: =K137*(1+IF(L$3<=$O$2,$D137,$D137-($D137-$I$130)*MIN(L$3-$O$2,$Q$2)/$Q$2)) -> 2535.5483 | M137: =L137*(1+IF(M$3<=$O$2,$D137,$D137-($D137-$I$130)*MIN(M$3-$O$2,$Q$2)/$Q$2)) -> 2599.1335 | N137: =M137*(1+IF(N$3<=$O$2,$D137,$D137-($D137-$I$130)*MIN(N$3-$O$2,$Q$2)/$Q$2)) -> 2685.6847 | O137: =SUMPRODUCT(E137:N137,1/(1+$F$130)^$E$3:$N$3)*$E$2 -> 3325.1628 | P137: =N137*$E$2*(1+$I$130)/($F$130-$I$130)/(1+$F$130)^$N$3 -> 4855.1351 | Q137: =O137+P137 -> 8180.2979 | R137: =Q137-$G$2+$I$2 -> 6804.0979 | S137: =R137/$K$2 -> 181.39424 | T137: =S137-$M$2 -> -23.084567
A138: 7 | B138: =IF(T137>0,B137,D137) -> -0.0078125 | C138: =IF(T137>0,D137,C137) -> 0.015625 | D138: =(B138+C138)/2 -> 0.00390625 | E138: =$C$2*(1+IF(E$3<=$O$2,$D138,$D138-($D138-$I$130)*MIN(E$3-$O$2,$Q$2)/$Q$2)) -> 2580.0391 | F138: =E138*(1+IF(F$3<=$O$2,$D138,$D138-($D138-$I$130)*MIN(F$3-$O$2,$Q$2)/$Q$2)) -> 2590.1173 | G138: =F138*(1+IF(G$3<=$O$2,$D138,$D138-($D138-$I$130)*MIN(G$3-$O$2,$Q$2)/$Q$2)) -> 2600.235 | H138: =G138*(1+IF(H$3<=$O$2,$D138,$D138-($D138-$I$130)*MIN(H$3-$O$2,$Q$2)/$Q$2)) -> 2610.3922 | I138: =H138*(1+IF(I$3<=$O$2,$D138,$D138-($D138-$I$130)*MIN(I$3-$O$2,$Q$2)/$Q$2)) -> 2620.589 | J138: =I138*(1+IF(J$3<=$O$2,$D138,$D138-($D138-$I$130)*MIN(J$3-$O$2,$Q$2)/$Q$2)) -> 2646.2315 | K138: =J138*(1+IF(K$3<=$O$2,$D138,$D138-($D138-$I$130)*MIN(K$3-$O$2,$Q$2)/$Q$2)) -> 2687.6814 | L138: =K138*(1+IF(L$3<=$O$2,$D138,$D138-($D138-$I$130)*MIN(L$3-$O$2,$Q$2)/$Q$2)) -> 2745.5807 | M138: =L138*(1+IF(M$3<=$O$2,$D138,$D138-($D138-$I$130)*MIN(M$3-$O$2,$Q$2)/$Q$2)) -> 2820.868 | N138: =M138*(1+IF(N$3<=$O$2,$D138,$D138-($D138-$I$130)*MIN(N$3-$O$2,$Q$2)/$Q$2)) -> 2914.8029 | O138: =SUMPRODUCT(E138:N138,1/(1+$F$130)^$E$3:$N$3)*$E$2 -> 3499.4905 | P138: =N138*$E$2*(1+$I$130)/($F$130-$I$130)/(1+$F$130)^$N$3 -> 5269.3311 | Q138: =O138+P138 -> 8768.8216 | R138: =Q138-$G$2+$I$2 -> 7392.6216 | S138: =R138/$K$2 -> 197.08402 | T138: =S138-$M$2 -> -7.394785
A139: 8 | B139: =IF(T138>0,B138,D138) -> 0.00390625 | C139: =IF(T138>0,D138,C138) -> 0.015625 | D139: =(B139+C139)/2 -> 0.009765625 | E139: =$C$2*(1+IF(E$3<=$O$2,$D139,$D139-($D139-$I$130)*MIN(E$3-$O$2,$Q$2)/$Q$2)) -> 2595.0977 | F139: =E139*(1+IF(F$3<=$O$2,$D139,$D139-($D139-$I$130)*MIN(F$3-$O$2,$Q$2)/$Q$2)) -> 2620.4404 | G139: =F139*(1+IF(G$3<=$O$2,$D139,$D139-($D139-$I$130)*MIN(G$3-$O$2,$Q$2)/$Q$2)) -> 2646.0306 | H139: =G139*(1+IF(H$3<=$O$2,$D139,$D139-($D139-$I$130)*MIN(H$3-$O$2,$Q$2)/$Q$2)) -> 2671.8708 | I139: =H139*(1+IF(I$3<=$O$2,$D139,$D139-($D139-$I$130)*MIN(I$3-$O$2,$Q$2)/$Q$2)) -> 2697.9633 | J139: =I139*(1+IF(J$3<=$O$2,$D139,$D139-($D139-$I$130)*MIN(J$3-$O$2,$Q$2)/$Q$2)) -> 2737.0095 | K139: =J139*(1+IF(K$3<=$O$2,$D139,$D139-($D139-$I$130)*MIN(K$3-$O$2,$Q$2)/$Q$2)) -> 2789.5037 | L139: =K139*(1+IF(L$3<=$O$2,$D139,$D139-($D139-$I$130)*MIN(L$3-$O$2,$Q$2)/$Q$2)) -> 2856.1345 | M139: =L139*(1+IF(M$3<=$O$2,$D139,$D139-($D139-$I$130)*MIN(M$3-$O$2,$Q$2)/$Q$2)) -> 2937.8003 | N139: =M139*(1+IF(N$3<=$O$2,$D139,$D139-($D139-$I$130)*MIN(N$3-$O$2,$Q$2)/$Q$2)) -> 3035.629 | O139: =SUMPRODUCT(E139:N139,1/(1+$F$130)^$E$3:$N$3)*$E$2 -> 3590.1318 | P139: =N139*$E$2*(1+$I$130)/($F$130-$I$130)/(1+$F$130)^$N$3 -> 5487.7585 | Q139: =O139+P139 -> 9077.8903 | R139: =Q139-$G$2+$I$2 -> 7701.6903 | S139: =R139/$K$2 -> 205.32366 | T139: =S139-$M$2 -> 0.84484955
A140: 9 | B140: =IF(T139>0,B139,D139) -> 0.00390625 | C140: =IF(T139>0,D139,C139) -> 0.009765625 | D140: =(B140+C140)/2 -> 0.0068359375 | E140: =$C$2*(1+IF(E$3<=$O$2,$D140,$D140-($D140-$I$130)*MIN(E$3-$O$2,$Q$2)/$Q$2)) -> 2587.5684 | F140: =E140*(1+IF(F$3<=$O$2,$D140,$D140-($D140-$I$130)*MIN(F$3-$O$2,$Q$2)/$Q$2)) -> 2605.2568 | G140: =F140*(1+IF(G$3<=$O$2,$D140,$D140-($D140-$I$130)*MIN(G$3-$O$2,$Q$2)/$Q$2)) -> 2623.0662 | H140: =G140*(1+IF(H$3<=$O$2,$D140,$D140-($D140-$I$130)*MIN(H$3-$O$2,$Q$2)/$Q$2)) -> 2640.9973 | I140: =H140*(1+IF(I$3<=$O$2,$D140,$D140-($D140-$I$130)*MIN(I$3-$O$2,$Q$2)/$Q$2)) -> 2659.051 | J140: =I140*(1+IF(J$3<=$O$2,$D140,$D140-($D140-$I$130)*MIN(J$3-$O$2,$Q$2)/$Q$2)) -> 2691.302 | K140: =J140*(1+IF(K$3<=$O$2,$D140,$D140-($D140-$I$130)*MIN(K$3-$O$2,$Q$2)/$Q$2)) -> 2738.1886 | L140: =K140*(1+IF(L$3<=$O$2,$D140,$D140-($D140-$I$130)*MIN(L$3-$O$2,$Q$2)/$Q$2)) -> 2800.3849 | M140: =L140*(1+IF(M$3<=$O$2,$D140,$D140-($D140-$I$130)*MIN(M$3-$O$2,$Q$2)/$Q$2)) -> 2878.8158 | N140: =M140*(1+IF(N$3<=$O$2,$D140,$D140-($D140-$I$130)*MIN(N$3-$O$2,$Q$2)/$Q$2)) -> 2974.6804 | O140: =SUMPRODUCT(E140:N140,1/(1+$F$130)^$E$3:$N$3)*$E$2 -> 3544.5154 | P140: =N140*$E$2*(1+$I$130)/($F$130-$I$130)/(1+$F$130)^$N$3 -> 5377.5766 | Q140: =O140+P140 -> 8922.0919 | R140: =Q140-$G$2+$I$2 -> 7545.8919 | S140: =R140/$K$2 -> 201.17014 | T140: =S140-$M$2 -> -3.3086666
A141: 10 | B141: =IF(T140>0,B140,D140) -> 0.0068359375 | C141: =IF(T140>0,D140,C140) -> 0.009765625 | D141: =(B141+C141)/2 -> 0.0083007812 | E141: =$C$2*(1+IF(E$3<=$O$2,$D141,$D141-($D141-$I$130)*MIN(E$3-$O$2,$Q$2)/$Q$2)) -> 2591.333 | F141: =E141*(1+IF(F$3<=$O$2,$D141,$D141-($D141-$I$130)*MIN(F$3-$O$2,$Q$2)/$Q$2)) -> 2612.8431 | G141: =F141*(1+IF(G$3<=$O$2,$D141,$D141-($D141-$I$130)*MIN(G$3-$O$2,$Q$2)/$Q$2)) -> 2634.5317 | H141: =G141*(1+IF(H$3<=$O$2,$D141,$D141-($D141-$I$130)*MIN(H$3-$O$2,$Q$2)/$Q$2)) -> 2656.4004 | I141: =H141*(1+IF(I$3<=$O$2,$D141,$D141-($D141-$I$130)*MIN(I$3-$O$2,$Q$2)/$Q$2)) -> 2678.4506 | J141: =I141*(1+IF(J$3<=$O$2,$D141,$D141-($D141-$I$130)*MIN(J$3-$O$2,$Q$2)/$Q$2)) -> 2714.0757 | K141: =J141*(1+IF(K$3<=$O$2,$D141,$D141-($D141-$I$130)*MIN(K$3-$O$2,$Q$2)/$Q$2)) -> 2763.7445 | L141: =K141*(1+IF(L$3<=$O$2,$D141,$D141-($D141-$I$130)*MIN(L$3-$O$2,$Q$2)/$Q$2)) -> 2828.1406 | M141: =L141*(1+IF(M$3<=$O$2,$D141,$D141-($D141-$I$130)*MIN(M$3-$O$2,$Q$2)/$Q$2)) -> 2908.1775 | N141: =M141*(1+IF(N$3<=$O$2,$D141,$D141-($D141-$I$130)*MIN(N$3-$O$2,$Q$2)/$Q$2)) -> 3005.0198 | O141: =SUMPRODUCT(E141:N141,1/(1+$F$130)^$E$3:$N$3)*$E$2 -> 3567.2492 | P141: =N141*$E$2*(1+$I$130)/($F$130-$I$130)/(1+$F$130)^$N$3 -> 5432.4236 | Q141: =O141+P141 -> 8999.6728 | R141: =Q141-$G$2+$I$2 -> 7623.4728 | S141: =R141/$K$2 -> 203.23841 | T141: =S141-$M$2 -> -1.2403945
A142: 11 | B142: =IF(T141>0,B141,D141) -> 0.0083007812 | C142: =IF(T141>0,D141,C141) -> 0.009765625 | D142: =(B142+C142)/2 -> 0.0090332031 | E142: =$C$2*(1+IF(E$3<=$O$2,$D142,$D142-($D142-$I$130)*MIN(E$3-$O$2,$Q$2)/$Q$2)) -> 2593.2153 | F142: =E142*(1+IF(F$3<=$O$2,$D142,$D142-($D142-$I$130)*MIN(F$3-$O$2,$Q$2)/$Q$2)) -> 2616.6404 | G142: =F142*(1+IF(G$3<=$O$2,$D142,$D142-($D142-$I$130)*MIN(G$3-$O$2,$Q$2)/$Q$2)) -> 2640.277 | H142: =G142*(1+IF(H$3<=$O$2,$D142,$D142-($D142-$I$130)*MIN(H$3-$O$2,$Q$2)/$Q$2)) -> 2664.1272 | I142: =H142*(1+IF(I$3<=$O$2,$D142,$D142-($D142-$I$130)*MIN(I$3-$O$2,$Q$2)/$Q$2)) -> 2688.1928 | J142: =I142*(1+IF(J$3<=$O$2,$D142,$D142-($D142-$I$130)*MIN(J$3-$O$2,$Q$2)/$Q$2)) -> 2725.5225 | K142: =J142*(1+IF(K$3<=$O$2,$D142,$D142-($D142-$I$130)*MIN(K$3-$O$2,$Q$2)/$Q$2)) -> 2776.5986 | L142: =K142*(1+IF(L$3<=$O$2,$D142,$D142-($D142-$I$130)*MIN(L$3-$O$2,$Q$2)/$Q$2)) -> 2842.1077 | M142: =L142*(1+IF(M$3<=$O$2,$D142,$D142-($D142-$I$130)*MIN(M$3-$O$2,$Q$2)/$Q$2)) -> 2922.9561 | N142: =M142*(1+IF(N$3<=$O$2,$D142,$D142-($D142-$I$130)*MIN(N$3-$O$2,$Q$2)/$Q$2)) -> 3020.2905 | O142: =SUMPRODUCT(E142:N142,1/(1+$F$130)^$E$3:$N$3)*$E$2 -> 3578.6718 | P142: =N142*$E$2*(1+$I$130)/($F$130-$I$130)/(1+$F$130)^$N$3 -> 5460.0299 | Q142: =O142+P142 -> 9038.7017 | R142: =Q142-$G$2+$I$2 -> 7662.5017 | S142: =R142/$K$2 -> 204.2789 | T142: =S142-$M$2 -> -0.19990169
A143: 12 | B143: =IF(T142>0,B142,D142) -> 0.0090332031 | C143: =IF(T142>0,D142,C142) -> 0.009765625 | D143: =(B143+C143)/2 -> 0.0093994141 | E143: =$C$2*(1+IF(E$3<=$O$2,$D143,$D143-($D143-$I$130)*MIN(E$3-$O$2,$Q$2)/$Q$2)) -> 2594.1565 | F143: =E143*(1+IF(F$3<=$O$2,$D143,$D143-($D143-$I$130)*MIN(F$3-$O$2,$Q$2)/$Q$2)) -> 2618.54 | G143: =F143*(1+IF(G$3<=$O$2,$D143,$D143-($D143-$I$130)*MIN(G$3-$O$2,$Q$2)/$Q$2)) -> 2643.1528 | H143: =G143*(1+IF(H$3<=$O$2,$D143,$D143-($D143-$I$130)*MIN(H$3-$O$2,$Q$2)/$Q$2)) -> 2667.9969 | I143: =H143*(1+IF(I$3<=$O$2,$D143,$D143-($D143-$I$130)*MIN(I$3-$O$2,$Q$2)/$Q$2)) -> 2693.0745 | J143: =I143*(1+IF(J$3<=$O$2,$D143,$D143-($D143-$I$130)*MIN(J$3-$O$2,$Q$2)/$Q$2)) -> 2731.261 | K143: =J143*(1+IF(K$3<=$O$2,$D143,$D143-($D143-$I$130)*MIN(K$3-$O$2,$Q$2)/$Q$2)) -> 2783.0448 | L143: =K143*(1+IF(L$3<=$O$2,$D143,$D143-($D143-$I$130)*MIN(L$3-$O$2,$Q$2)/$Q$2)) -> 2849.1136 | M143: =L143*(1+IF(M$3<=$O$2,$D143,$D143-($D143-$I$130)*MIN(M$3-$O$2,$Q$2)/$Q$2)) -> 2930.37 | N143: =M143*(1+IF(N$3<=$O$2,$D143,$D143-($D143-$I$130)*MIN(N$3-$O$2,$Q$2)/$Q$2)) -> 3027.9513 | O143: =SUMPRODUCT(E143:N143,1/(1+$F$130)^$E$3:$N$3)*$E$2 -> 3584.3971 | P143: =N143*$E$2*(1+$I$130)/($F$130-$I$130)/(1+$F$130)^$N$3 -> 5473.8789 | Q143: =O143+P143 -> 9058.276 | R143: =Q143-$G$2+$I$2 -> 7682.076 | S143: =R143/$K$2 -> 204.80075 | T143: =S143-$M$2 -> 0.32194066
A144: 13 | B144: =IF(T143>0,B143,D143) -> 0.0090332031 | C144: =IF(T143>0,D143,C143) -> 0.0093994141 | D144: =(B144+C144)/2 -> 0.0092163086 | E144: =$C$2*(1+IF(E$3<=$O$2,$D144,$D144-($D144-$I$130)*MIN(E$3-$O$2,$Q$2)/$Q$2)) -> 2593.6859 | F144: =E144*(1+IF(F$3<=$O$2,$D144,$D144-($D144-$I$130)*MIN(F$3-$O$2,$Q$2)/$Q$2)) -> 2617.5901 | G144: =F144*(1+IF(G$3<=$O$2,$D144,$D144-($D144-$I$130)*MIN(G$3-$O$2,$Q$2)/$Q$2)) -> 2641.7146 | H144: =G144*(1+IF(H$3<=$O$2,$D144,$D144-($D144-$I$130)*MIN(H$3-$O$2,$Q$2)/$Q$2)) -> 2666.0615 | I144: =H144*(1+IF(I$3<=$O$2,$D144,$D144-($D144-$I$130)*MIN(I$3-$O$2,$Q$2)/$Q$2)) -> 2690.6327 | J144: =I144*(1+IF(J$3<=$O$2,$D144,$D144-($D144-$I$130)*MIN(J$3-$O$2,$Q$2)/$Q$2)) -> 2728.3905 | K144: =J144*(1+IF(K$3<=$O$2,$D144,$D144-($D144-$I$130)*MIN(K$3-$O$2,$Q$2)/$Q$2)) -> 2779.8201 | L144: =K144*(1+IF(L$3<=$O$2,$D144,$D144-($D144-$I$130)*MIN(L$3-$O$2,$Q$2)/$Q$2)) -> 2845.6088 | M144: =L144*(1+IF(M$3<=$O$2,$D144,$D144-($D144-$I$130)*MIN(M$3-$O$2,$Q$2)/$Q$2)) -> 2926.661 | N144: =M144*(1+IF(N$3<=$O$2,$D144,$D144-($D144-$I$130)*MIN(N$3-$O$2,$Q$2)/$Q$2)) -> 3024.1188 | O144: =SUMPRODUCT(E144:N144,1/(1+$F$130)^$E$3:$N$3)*$E$2 -> 3581.5333 | P144: =N144*$E$2*(1+$I$130)/($F$130-$I$130)/(1+$F$130)^$N$3 -> 5466.9505 | Q144: =O144+P144 -> 9048.4838 | R144: =Q144-$G$2+$I$2 -> 7672.2838 | S144: =R144/$K$2 -> 204.53969 | T144: =S144-$M$2 -> 0.060886287
... A155: 24 | B155: =IF(T154>0,B154,D154) -> 0.0091735721 | C155: =IF(T154>0,D154,C154) -> 0.0091737509 | D155: =(B155+C155)/2 -> 0.0091736615 | E155: =$C$2*(1+IF(E$3<=$O$2,$D155,$D155-($D155-$I$130)*MIN(E$3-$O$2,$Q$2)/$Q$2)) -> 2593.5763 | F155: =E155*(1+IF(F$3<=$O$2,$D155,$D155-($D155-$I$130)*MIN(F$3-$O$2,$Q$2)/$Q$2)) -> 2617.3689 | G155: =F155*(1+IF(G$3<=$O$2,$D155,$D155-($D155-$I$130)*MIN(G$3-$O$2,$Q$2)/$Q$2)) -> 2641.3798 | H155: =G155*(1+IF(H$3<=$O$2,$D155,$D155-($D155-$I$130)*MIN(H$3-$O$2,$Q$2)/$Q$2)) -> 2665.6109 | I155: =H155*(1+IF(I$3<=$O$2,$D155,$D155-($D155-$I$130)*MIN(I$3-$O$2,$Q$2)/$Q$2)) -> 2690.0643 | J155: =I155*(1+IF(J$3<=$O$2,$D155,$D155-($D155-$I$130)*MIN(J$3-$O$2,$Q$2)/$Q$2)) -> 2727.7223 | K155: =J155*(1+IF(K$3<=$O$2,$D155,$D155-($D155-$I$130)*MIN(K$3-$O$2,$Q$2)/$Q$2)) -> 2779.0695 | L155: =K155*(1+IF(L$3<=$O$2,$D155,$D155-($D155-$I$130)*MIN(L$3-$O$2,$Q$2)/$Q$2)) -> 2844.793 | M155: =L155*(1+IF(M$3<=$O$2,$D155,$D155-($D155-$I$130)*MIN(M$3-$O$2,$Q$2)/$Q$2)) -> 2925.7977 | N155: =M155*(1+IF(N$3<=$O$2,$D155,$D155-($D155-$I$130)*MIN(N$3-$O$2,$Q$2)/$Q$2)) -> 3023.2268 | O155: =SUMPRODUCT(E155:N155,1/(1+$F$130)^$E$3:$N$3)*$E$2 -> 3580.8666 | P155: =N155*$E$2*(1+$I$130)/($F$130-$I$130)/(1+$F$130)^$N$3 -> 5465.338 | Q155: =O155+P155 -> 9046.2046 | R155: =Q155-$G$2+$I$2 -> 7670.0046 | S155: =R155/$K$2 -> 204.47893 | T155: =S155-$M$2 -> 0.00012232919
A157: Grid block 6: row 1, column 5 of table A (24 steps) | E157: WACC | F157: =Sensitivity!$B$10 -> 0.084183338 | G157: Terminal growth | I157: =Sensitivity!$G$9 -> 0.0383
A158: Step | B158: Low | C158: High | D158: Mid | E158: Rev Y1 | F158: Rev Y2 | G158: Rev Y3 | H158: Rev Y4 | I158: Rev Y5 | J158: Rev Y6 | K158: Rev Y7 | L158: Rev Y8 | M158: Rev Y9 | N158: Rev Y10 | O158: PV of FCF | P158: PV of TV | Q158: EV | R158: Equity | S158: Per share | T158: Value - price
A159: 1 | B159: -0.5 | C159: 1 | D159: =(B159+C159)/2 -> 0.25 | E159: =$C$2*(1+IF(E$3<=$O$2,$D159,$D159-($D159-$I$157)*MIN(E$3-$O$2,$Q$2)/$Q$2)) -> 3212.5 | F159: =E159*(1+IF(F$3<=$O$2,$D159,$D159-($D159-$I$157)*MIN(F$3-$O$2,$Q$2)/$Q$2)) -> 4015.625 | G159: =F159*(1+IF(G$3<=$O$2,$D159,$D159-($D159-$I$157)*MIN(G$3-$O$2,$Q$2)/$Q$2)) -> 5019.5312 | H159: =G159*(1+IF(H$3<=$O$2,$D159,$D159-($D159-$I$157)*MIN(H$3-$O$2,$Q$2)/$Q$2)) -> 6274.4141 | I159: =H159*(1+IF(I$3<=$O$2,$D159,$D159-($D159-$I$157)*MIN(I$3-$O$2,$Q$2)/$Q$2)) -> 7843.0176 | J159: =I159*(1+IF(J$3<=$O$2,$D159,$D159-($D159-$I$157)*MIN(J$3-$O$2,$Q$2)/$Q$2)) -> 9471.6986 | K159: =J159*(1+IF(K$3<=$O$2,$D159,$D159-($D159-$I$157)*MIN(K$3-$O$2,$Q$2)/$Q$2)) -> 11037.56 | L159: =K159*(1+IF(L$3<=$O$2,$D159,$D159-($D159-$I$157)*MIN(L$3-$O$2,$Q$2)/$Q$2)) -> 12394.959 | M159: =L159*(1+IF(M$3<=$O$2,$D159,$D159-($D159-$I$157)*MIN(M$3-$O$2,$Q$2)/$Q$2)) -> 13394.488 | N159: =M159*(1+IF(N$3<=$O$2,$D159,$D159-($D159-$I$157)*MIN(N$3-$O$2,$Q$2)/$Q$2)) -> 13907.497 | O159: =SUMPRODUCT(E159:N159,1/(1+$F$157)^$E$3:$N$3)*$E$2 -> 10259.357 | P159: =N159*$E$2*(1+$I$157)/($F$157-$I$157)/(1+$F$157)^$N$3 -> 28016.398 | Q159: =O159+P159 -> 38275.755 | R159: =Q159-$G$2+$I$2 -> 36899.555 | S159: =R159/$K$2 -> 983.7258 | T159: =S159-$M$2 -> 779.247
A160: 2 | B160: =IF(T159>0,B159,D159) -> -0.5 | C160: =IF(T159>0,D159,C159) -> 0.25 | D160: =(B160+C160)/2 -> -0.125 | E160: =$C$2*(1+IF(E$3<=$O$2,$D160,$D160-($D160-$I$157)*MIN(E$3-$O$2,$Q$2)/$Q$2)) -> 2248.75 | F160: =E160*(1+IF(F$3<=$O$2,$D160,$D160-($D160-$I$157)*MIN(F$3-$O$2,$Q$2)/$Q$2)) -> 1967.6562 | G160: =F160*(1+IF(G$3<=$O$2,$D160,$D160-($D160-$I$157)*MIN(G$3-$O$2,$Q$2)/$Q$2)) -> 1721.6992 | H160: =G160*(1+IF(H$3<=$O$2,$D160,$D160-($D160-$I$157)*MIN(H$3-$O$2,$Q$2)/$Q$2)) -> 1506.4868 | I160: =H160*(1+IF(I$3<=$O$2,$D160,$D160-($D160-$I$157)*MIN(I$3-$O$2,$Q$2)/$Q$2)) -> 1318.176 | J160: =I160*(1+IF(J$3<=$O$2,$D160,$D160-($D160-$I$157)*MIN(J$3-$O$2,$Q$2)/$Q$2)) -> 1196.4556 | K160: =J160*(1+IF(K$3<=$O$2,$D160,$D160-($D160-$I$157)*MIN(K$3-$O$2,$Q$2)/$Q$2)) -> 1125.0511 | L160: =K160*(1+IF(L$3<=$O$2,$D160,$D160-($D160-$I$157)*MIN(L$3-$O$2,$Q$2)/$Q$2)) -> 1094.6522 | M160: =L160*(1+IF(M$3<=$O$2,$D160,$D160-($D160-$I$157)*MIN(M$3-$O$2,$Q$2)/$Q$2)) -> 1100.8261 | N160: =M160*(1+IF(N$3<=$O$2,$D160,$D160-($D160-$I$157)*MIN(N$3-$O$2,$Q$2)/$Q$2)) -> 1142.9877 | O160: =SUMPRODUCT(E160:N160,1/(1+$F$157)^$E$3:$N$3)*$E$2 -> 2009.5641 | P160: =N160*$E$2*(1+$I$157)/($F$157-$I$157)/(1+$F$157)^$N$3 -> 2302.5278 | Q160: =O160+P160 -> 4312.0919 | R160: =Q160-$G$2+$I$2 -> 2935.8919 | S160: =R160/$K$2 -> 78.269579 | T160: =S160-$M$2 -> -126.20923
A161: 3 | B161: =IF(T160>0,B160,D160) -> -0.125 | C161: =IF(T160>0,D160,C160) -> 0.25 | D161: =(B161+C161)/2 -> 0.0625 | E161: =$C$2*(1+IF(E$3<=$O$2,$D161,$D161-($D161-$I$157)*MIN(E$3-$O$2,$Q$2)/$Q$2)) -> 2730.625 | F161: =E161*(1+IF(F$3<=$O$2,$D161,$D161-($D161-$I$157)*MIN(F$3-$O$2,$Q$2)/$Q$2)) -> 2901.2891 | G161: =F161*(1+IF(G$3<=$O$2,$D161,$D161-($D161-$I$157)*MIN(G$3-$O$2,$Q$2)/$Q$2)) -> 3082.6196 | H161: =G161*(1+IF(H$3<=$O$2,$D161,$D161-($D161-$I$157)*MIN(H$3-$O$2,$Q$2)/$Q$2)) -> 3275.2834 | I161: =H161*(1+IF(I$3<=$O$2,$D161,$D161-($D161-$I$157)*MIN(I$3-$O$2,$Q$2)/$Q$2)) -> 3479.9886 | J161: =I161*(1+IF(J$3<=$O$2,$D161,$D161-($D161-$I$157)*MIN(J$3-$O$2,$Q$2)/$Q$2)) -> 3680.6447 | K161: =J161*(1+IF(K$3<=$O$2,$D161,$D161-($D161-$I$157)*MIN(K$3-$O$2,$Q$2)/$Q$2)) -> 3875.0564 | L161: =K161*(1+IF(L$3<=$O$2,$D161,$D161-($D161-$I$157)*MIN(L$3-$O$2,$Q$2)/$Q$2)) -> 4060.9816 | M161: =L161*(1+IF(M$3<=$O$2,$D161,$D161-($D161-$I$157)*MIN(M$3-$O$2,$Q$2)/$Q$2)) -> 4236.1723 | N161: =M161*(1+IF(N$3<=$O$2,$D161,$D161-($D161-$I$157)*MIN(N$3-$O$2,$Q$2)/$Q$2)) -> 4398.4177 | O161: =SUMPRODUCT(E161:N161,1/(1+$F$157)^$E$3:$N$3)*$E$2 -> 4534.729 | P161: =N161*$E$2*(1+$I$157)/($F$157-$I$157)/(1+$F$157)^$N$3 -> 8860.5316 | Q161: =O161+P161 -> 13395.261 | R161: =Q161-$G$2+$I$2 -> 12019.061 | S161: =R161/$K$2 -> 320.42284 | T161: =S161-$M$2 -> 115.94403
A162: 4 | B162: =IF(T161>0,B161,D161) -> -0.125 | C162: =IF(T161>0,D161,C161) -> 0.0625 | D162: =(B162+C162)/2 -> -0.03125 | E162: =$C$2*(1+IF(E$3<=$O$2,$D162,$D162-($D162-$I$157)*MIN(E$3-$O$2,$Q$2)/$Q$2)) -> 2489.6875 | F162: =E162*(1+IF(F$3<=$O$2,$D162,$D162-($D162-$I$157)*MIN(F$3-$O$2,$Q$2)/$Q$2)) -> 2411.8848 | G162: =F162*(1+IF(G$3<=$O$2,$D162,$D162-($D162-$I$157)*MIN(G$3-$O$2,$Q$2)/$Q$2)) -> 2336.5134 | H162: =G162*(1+IF(H$3<=$O$2,$D162,$D162-($D162-$I$157)*MIN(H$3-$O$2,$Q$2)/$Q$2)) -> 2263.4973 | I162: =H162*(1+IF(I$3<=$O$2,$D162,$D162-($D162-$I$157)*MIN(I$3-$O$2,$Q$2)/$Q$2)) -> 2192.763 | J162: =I162*(1+IF(J$3<=$O$2,$D162,$D162-($D162-$I$157)*MIN(J$3-$O$2,$Q$2)/$Q$2)) -> 2154.7405 | K162: =J162*(1+IF(K$3<=$O$2,$D162,$D162-($D162-$I$157)*MIN(K$3-$O$2,$Q$2)/$Q$2)) -> 2147.3498 | L162: =K162*(1+IF(L$3<=$O$2,$D162,$D162-($D162-$I$157)*MIN(L$3-$O$2,$Q$2)/$Q$2)) -> 2169.854 | M162: =L162*(1+IF(M$3<=$O$2,$D162,$D162-($D162-$I$157)*MIN(M$3-$O$2,$Q$2)/$Q$2)) -> 2222.7767 | N162: =M162*(1+IF(N$3<=$O$2,$D162,$D162-($D162-$I$157)*MIN(N$3-$O$2,$Q$2)/$Q$2)) -> 2307.9091 | O162: =SUMPRODUCT(E162:N162,1/(1+$F$157)^$E$3:$N$3)*$E$2 -> 3010.2557 | P162: =N162*$E$2*(1+$I$157)/($F$157-$I$157)/(1+$F$157)^$N$3 -> 4649.2404 | Q162: =O162+P162 -> 7659.4962 | R162: =Q162-$G$2+$I$2 -> 6283.2962 | S162: =R162/$K$2 -> 167.50989 | T162: =S162-$M$2 -> -36.968911
A163: 5 | B163: =IF(T162>0,B162,D162) -> -0.03125 | C163: =IF(T162>0,D162,C162) -> 0.0625 | D163: =(B163+C163)/2 -> 0.015625 | E163: =$C$2*(1+IF(E$3<=$O$2,$D163,$D163-($D163-$I$157)*MIN(E$3-$O$2,$Q$2)/$Q$2)) -> 2610.1562 | F163: =E163*(1+IF(F$3<=$O$2,$D163,$D163-($D163-$I$157)*MIN(F$3-$O$2,$Q$2)/$Q$2)) -> 2650.9399 | G163: =F163*(1+IF(G$3<=$O$2,$D163,$D163-($D163-$I$157)*MIN(G$3-$O$2,$Q$2)/$Q$2)) -> 2692.3609 | H163: =G163*(1+IF(H$3<=$O$2,$D163,$D163-($D163-$I$157)*MIN(H$3-$O$2,$Q$2)/$Q$2)) -> 2734.429 | I163: =H163*(1+IF(I$3<=$O$2,$D163,$D163-($D163-$I$157)*MIN(I$3-$O$2,$Q$2)/$Q$2)) -> 2777.1545 | J163: =I163*(1+IF(J$3<=$O$2,$D163,$D163-($D163-$I$157)*MIN(J$3-$O$2,$Q$2)/$Q$2)) -> 2833.1419 | K163: =J163*(1+IF(K$3<=$O$2,$D163,$D163-($D163-$I$157)*MIN(K$3-$O$2,$Q$2)/$Q$2)) -> 2903.1063 | L163: =K163*(1+IF(L$3<=$O$2,$D163,$D163-($D163-$I$157)*MIN(L$3-$O$2,$Q$2)/$Q$2)) -> 2987.9641 | M163: =L163*(1+IF(M$3<=$O$2,$D163,$D163-($D163-$I$157)*MIN(M$3-$O$2,$Q$2)/$Q$2)) -> 3088.8528 | N163: =M163*(1+IF(N$3<=$O$2,$D163,$D163-($D163-$I$157)*MIN(N$3-$O$2,$Q$2)/$Q$2)) -> 3207.1558 | O163: =SUMPRODUCT(E163:N163,1/(1+$F$157)^$E$3:$N$3)*$E$2 -> 3693.3132 | P163: =N163*$E$2*(1+$I$157)/($F$157-$I$157)/(1+$F$157)^$N$3 -> 6460.7564 | Q163: =O163+P163 -> 10154.07 | R163: =Q163-$G$2+$I$2 -> 8777.8697 | S163: =R163/$K$2 -> 234.01412 | T163: =S163-$M$2 -> 29.535315
A164: 6 | B164: =IF(T163>0,B163,D163) -> -0.03125 | C164: =IF(T163>0,D163,C163) -> 0.015625 | D164: =(B164+C164)/2 -> -0.0078125 | E164: =$C$2*(1+IF(E$3<=$O$2,$D164,$D164-($D164-$I$157)*MIN(E$3-$O$2,$Q$2)/$Q$2)) -> 2549.9219 | F164: =E164*(1+IF(F$3<=$O$2,$D164,$D164-($D164-$I$157)*MIN(F$3-$O$2,$Q$2)/$Q$2)) -> 2530.0006 | G164: =F164*(1+IF(G$3<=$O$2,$D164,$D164-($D164-$I$157)*MIN(G$3-$O$2,$Q$2)/$Q$2)) -> 2510.235 | H164: =G164*(1+IF(H$3<=$O$2,$D164,$D164-($D164-$I$157)*MIN(H$3-$O$2,$Q$2)/$Q$2)) -> 2490.6238 | I164: =H164*(1+IF(I$3<=$O$2,$D164,$D164-($D164-$I$157)*MIN(I$3-$O$2,$Q$2)/$Q$2)) -> 2471.1658 | J164: =I164*(1+IF(J$3<=$O$2,$D164,$D164-($D164-$I$157)*MIN(J$3-$O$2,$Q$2)/$Q$2)) -> 2474.6501 | K164: =J164*(1+IF(K$3<=$O$2,$D164,$D164-($D164-$I$157)*MIN(K$3-$O$2,$Q$2)/$Q$2)) -> 2500.9618 | L164: =K164*(1+IF(L$3<=$O$2,$D164,$D164-($D164-$I$157)*MIN(L$3-$O$2,$Q$2)/$Q$2)) -> 2550.6184 | M164: =L164*(1+IF(M$3<=$O$2,$D164,$D164-($D164-$I$157)*MIN(M$3-$O$2,$Q$2)/$Q$2)) -> 2624.784 | N164: =M164*(1+IF(N$3<=$O$2,$D164,$D164-($D164-$I$157)*MIN(N$3-$O$2,$Q$2)/$Q$2)) -> 2725.3133 | O164: =SUMPRODUCT(E164:N164,1/(1+$F$157)^$E$3:$N$3)*$E$2 -> 3333.8915 | P164: =N164*$E$2*(1+$I$157)/($F$157-$I$157)/(1+$F$157)^$N$3 -> 5490.0935 | Q164: =O164+P164 -> 8823.985 | R164: =Q164-$G$2+$I$2 -> 7447.785 | S164: =R164/$K$2 -> 198.55465 | T164: =S164-$M$2 -> -5.9241549
A165: 7 | B165: =IF(T164>0,B164,D164) -> -0.0078125 | C165: =IF(T164>0,D164,C164) -> 0.015625 | D165: =(B165+C165)/2 -> 0.00390625 | E165: =$C$2*(1+IF(E$3<=$O$2,$D165,$D165-($D165-$I$157)*MIN(E$3-$O$2,$Q$2)/$Q$2)) -> 2580.0391 | F165: =E165*(1+IF(F$3<=$O$2,$D165,$D165-($D165-$I$157)*MIN(F$3-$O$2,$Q$2)/$Q$2)) -> 2590.1173 | G165: =F165*(1+IF(G$3<=$O$2,$D165,$D165-($D165-$I$157)*MIN(G$3-$O$2,$Q$2)/$Q$2)) -> 2600.235 | H165: =G165*(1+IF(H$3<=$O$2,$D165,$D165-($D165-$I$157)*MIN(H$3-$O$2,$Q$2)/$Q$2)) -> 2610.3922 | I165: =H165*(1+IF(I$3<=$O$2,$D165,$D165-($D165-$I$157)*MIN(I$3-$O$2,$Q$2)/$Q$2)) -> 2620.589 | J165: =I165*(1+IF(J$3<=$O$2,$D165,$D165-($D165-$I$157)*MIN(J$3-$O$2,$Q$2)/$Q$2)) -> 2648.8521 | K165: =J165*(1+IF(K$3<=$O$2,$D165,$D165-($D165-$I$157)*MIN(K$3-$O$2,$Q$2)/$Q$2)) -> 2695.6407 | L165: =K165*(1+IF(L$3<=$O$2,$D165,$D165-($D165-$I$157)*MIN(L$3-$O$2,$Q$2)/$Q$2)) -> 2761.7985 | M165: =L165*(1+IF(M$3<=$O$2,$D165,$D165-($D165-$I$157)*MIN(M$3-$O$2,$Q$2)/$Q$2)) -> 2848.5776 | N165: =M165*(1+IF(N$3<=$O$2,$D165,$D165-($D165-$I$157)*MIN(N$3-$O$2,$Q$2)/$Q$2)) -> 2957.6782 | O165: =SUMPRODUCT(E165:N165,1/(1+$F$157)^$E$3:$N$3)*$E$2 -> 3508.9041 | P165: =N165*$E$2*(1+$I$157)/($F$157-$I$157)/(1+$F$157)^$N$3 -> 5958.1883 | Q165: =O165+P165 -> 9467.0924 | R165: =Q165-$G$2+$I$2 -> 8090.8924 | S165: =R165/$K$2 -> 215.69961 | T165: =S165-$M$2 -> 11.220805
A166: 8 | B166: =IF(T165>0,B165,D165) -> -0.0078125 | C166: =IF(T165>0,D165,C165) -> 0.00390625 | D166: =(B166+C166)/2 -> -0.001953125 | E166: =$C$2*(1+IF(E$3<=$O$2,$D166,$D166-($D166-$I$157)*MIN(E$3-$O$2,$Q$2)/$Q$2)) -> 2564.9805 | F166: =E166*(1+IF(F$3<=$O$2,$D166,$D166-($D166-$I$157)*MIN(F$3-$O$2,$Q$2)/$Q$2)) -> 2559.9707 | G166: =F166*(1+IF(G$3<=$O$2,$D166,$D166-($D166-$I$157)*MIN(G$3-$O$2,$Q$2)/$Q$2)) -> 2554.9708 | H166: =G166*(1+IF(H$3<=$O$2,$D166,$D166-($D166-$I$157)*MIN(H$3-$O$2,$Q$2)/$Q$2)) -> 2549.9806 | I166: =H166*(1+IF(I$3<=$O$2,$D166,$D166-($D166-$I$157)*MIN(I$3-$O$2,$Q$2)/$Q$2)) -> 2545.0002 | J166: =I166*(1+IF(J$3<=$O$2,$D166,$D166-($D166-$I$157)*MIN(J$3-$O$2,$Q$2)/$Q$2)) -> 2560.5183 | K166: =J166*(1+IF(K$3<=$O$2,$D166,$D166-($D166-$I$157)*MIN(K$3-$O$2,$Q$2)/$Q$2)) -> 2596.7449 | L166: =K166*(1+IF(L$3<=$O$2,$D166,$D166-($D166-$I$157)*MIN(L$3-$O$2,$Q$2)/$Q$2)) -> 2654.3894 | M166: =L166*(1+IF(M$3<=$O$2,$D166,$D166-($D166-$I$157)*MIN(M$3-$O$2,$Q$2)/$Q$2)) -> 2734.683 | N166: =M166*(1+IF(N$3<=$O$2,$D166,$D166-($D166-$I$157)*MIN(N$3-$O$2,$Q$2)/$Q$2)) -> 2839.4213 | O166: =SUMPRODUCT(E166:N166,1/(1+$F$157)^$E$3:$N$3)*$E$2 -> 3420.2521 | P166: =N166*$E$2*(1+$I$157)/($F$157-$I$157)/(1+$F$157)^$N$3 -> 5719.9621 | Q166: =O166+P166 -> 9140.2142 | R166: =Q166-$G$2+$I$2 -> 7764.0142 | S166: =R166/$K$2 -> 206.98518 | T166: =S166-$M$2 -> 2.5063766
A167: 9 | B167: =IF(T166>0,B166,D166) -> -0.0078125 | C167: =IF(T166>0,D166,C166) -> -0.001953125 | D167: =(B167+C167)/2 -> -0.0048828125 | E167: =$C$2*(1+IF(E$3<=$O$2,$D167,$D167-($D167-$I$157)*MIN(E$3-$O$2,$Q$2)/$Q$2)) -> 2557.4512 | F167: =E167*(1+IF(F$3<=$O$2,$D167,$D167-($D167-$I$157)*MIN(F$3-$O$2,$Q$2)/$Q$2)) -> 2544.9636 | G167: =F167*(1+IF(G$3<=$O$2,$D167,$D167-($D167-$I$157)*MIN(G$3-$O$2,$Q$2)/$Q$2)) -> 2532.537 | H167: =G167*(1+IF(H$3<=$O$2,$D167,$D167-($D167-$I$157)*MIN(H$3-$O$2,$Q$2)/$Q$2)) -> 2520.1711 | I167: =H167*(1+IF(I$3<=$O$2,$D167,$D167-($D167-$I$157)*MIN(I$3-$O$2,$Q$2)/$Q$2)) -> 2507.8656 | J167: =I167*(1+IF(J$3<=$O$2,$D167,$D167-($D167-$I$157)*MIN(J$3-$O$2,$Q$2)/$Q$2)) -> 2517.2795 | K167: =J167*(1+IF(K$3<=$O$2,$D167,$D167-($D167-$I$157)*MIN(K$3-$O$2,$Q$2)/$Q$2)) -> 2548.4694 | L167: =K167*(1+IF(L$3<=$O$2,$D167,$D167-($D167-$I$157)*MIN(L$3-$O$2,$Q$2)/$Q$2)) -> 2602.0557 | M167: =L167*(1+IF(M$3<=$O$2,$D167,$D167-($D167-$I$157)*MIN(M$3-$O$2,$Q$2)/$Q$2)) -> 2679.2417 | N167: =M167*(1+IF(N$3<=$O$2,$D167,$D167-($D167-$I$157)*MIN(N$3-$O$2,$Q$2)/$Q$2)) -> 2781.8566 | O167: =SUMPRODUCT(E167:N167,1/(1+$F$157)^$E$3:$N$3)*$E$2 -> 3376.7889 | P167: =N167*$E$2*(1+$I$157)/($F$157-$I$157)/(1+$F$157)^$N$3 -> 5603.999 | Q167: =O167+P167 -> 8980.7879 | R167: =Q167-$G$2+$I$2 -> 7604.5879 | S167: =R167/$K$2 -> 202.73495 | T167: =S167-$M$2 -> -1.7438569
A168: 10 | B168: =IF(T167>0,B167,D167) -> -0.0048828125 | C168: =IF(T167>0,D167,C167) -> -0.001953125 | D168: =(B168+C168)/2 -> -0.0034179688 | E168: =$C$2*(1+IF(E$3<=$O$2,$D168,$D168-($D168-$I$157)*MIN(E$3-$O$2,$Q$2)/$Q$2)) -> 2561.2158 | F168: =E168*(1+IF(F$3<=$O$2,$D168,$D168-($D168-$I$157)*MIN(F$3-$O$2,$Q$2)/$Q$2)) -> 2552.4617 | G168: =F168*(1+IF(G$3<=$O$2,$D168,$D168-($D168-$I$157)*MIN(G$3-$O$2,$Q$2)/$Q$2)) -> 2543.7374 | H168: =G168*(1+IF(H$3<=$O$2,$D168,$D168-($D168-$I$157)*MIN(H$3-$O$2,$Q$2)/$Q$2)) -> 2535.043 | I168: =H168*(1+IF(I$3<=$O$2,$D168,$D168-($D168-$I$157)*MIN(I$3-$O$2,$Q$2)/$Q$2)) -> 2526.3783 | J168: =I168*(1+IF(J$3<=$O$2,$D168,$D168-($D168-$I$157)*MIN(J$3-$O$2,$Q$2)/$Q$2)) -> 2538.8223 | K168: =J168*(1+IF(K$3<=$O$2,$D168,$D168-($D168-$I$157)*MIN(K$3-$O$2,$Q$2)/$Q$2)) -> 2572.5105 | L168: =K168*(1+IF(L$3<=$O$2,$D168,$D168-($D168-$I$157)*MIN(L$3-$O$2,$Q$2)/$Q$2)) -> 2628.1097 | M168: =L168*(1+IF(M$3<=$O$2,$D168,$D168-($D168-$I$157)*MIN(M$3-$O$2,$Q$2)/$Q$2)) -> 2706.8384 | N168: =M168*(1+IF(N$3<=$O$2,$D168,$D168-($D168-$I$157)*MIN(N$3-$O$2,$Q$2)/$Q$2)) -> 2810.5103 | O168: =SUMPRODUCT(E168:N168,1/(1+$F$157)^$E$3:$N$3)*$E$2 -> 3398.4494 | P168: =N168*$E$2*(1+$I$157)/($F$157-$I$157)/(1+$F$157)^$N$3 -> 5661.7214 | Q168: =O168+P168 -> 9060.1707 | R168: =Q168-$G$2+$I$2 -> 7683.9707 | S168: =R168/$K$2 -> 204.85126 | T168: =S168-$M$2 -> 0.37245348
A169: 11 | B169: =IF(T168>0,B168,D168) -> -0.0048828125 | C169: =IF(T168>0,D168,C168) -> -0.0034179688 | D169: =(B169+C169)/2 -> -0.0041503906 | E169: =$C$2*(1+IF(E$3<=$O$2,$D169,$D169-($D169-$I$157)*MIN(E$3-$O$2,$Q$2)/$Q$2)) -> 2559.3335 | F169: =E169*(1+IF(F$3<=$O$2,$D169,$D169-($D169-$I$157)*MIN(F$3-$O$2,$Q$2)/$Q$2)) -> 2548.7113 | G169: =F169*(1+IF(G$3<=$O$2,$D169,$D169-($D169-$I$157)*MIN(G$3-$O$2,$Q$2)/$Q$2)) -> 2538.1331 | H169: =G169*(1+IF(H$3<=$O$2,$D169,$D169-($D169-$I$157)*MIN(H$3-$O$2,$Q$2)/$Q$2)) -> 2527.5989 | I169: =H169*(1+IF(I$3<=$O$2,$D169,$D169-($D169-$I$157)*MIN(I$3-$O$2,$Q$2)/$Q$2)) -> 2517.1083 | J169: =I169*(1+IF(J$3<=$O$2,$D169,$D169-($D169-$I$157)*MIN(J$3-$O$2,$Q$2)/$Q$2)) -> 2528.0318 | K169: =J169*(1+IF(K$3<=$O$2,$D169,$D169-($D169-$I$157)*MIN(K$3-$O$2,$Q$2)/$Q$2)) -> 2560.4659 | L169: =K169*(1+IF(L$3<=$O$2,$D169,$D169-($D169-$I$157)*MIN(L$3-$O$2,$Q$2)/$Q$2)) -> 2615.0546 | M169: =L169*(1+IF(M$3<=$O$2,$D169,$D169-($D169-$I$157)*MIN(M$3-$O$2,$Q$2)/$Q$2)) -> 2693.0092 | N169: =M169*(1+IF(N$3<=$O$2,$D169,$D169-($D169-$I$157)*MIN(N$3-$O$2,$Q$2)/$Q$2)) -> 2796.1514 | O169: =SUMPRODUCT(E169:N169,1/(1+$F$157)^$E$3:$N$3)*$E$2 -> 3387.6014 | P169: =N169*$E$2*(1+$I$157)/($F$157-$I$157)/(1+$F$157)^$N$3 -> 5632.7957 | Q169: =O169+P169 -> 9020.397 | R169: =Q169-$G$2+$I$2 -> 7644.197 | S169: =R169/$K$2 -> 203.79091 | T169: =S169-$M$2 -> -0.68789524
A170: 12 | B170: =IF(T169>0,B169,D169) -> -0.0041503906 | C170: =IF(T169>0,D169,C169) -> -0.0034179688 | D170: =(B170+C170)/2 -> -0.0037841797 | E170: =$C$2*(1+IF(E$3<=$O$2,$D170,$D170-($D170-$I$157)*MIN(E$3-$O$2,$Q$2)/$Q$2)) -> 2560.2747 | F170: =E170*(1+IF(F$3<=$O$2,$D170,$D170-($D170-$I$157)*MIN(F$3-$O$2,$Q$2)/$Q$2)) -> 2550.5861 | G170: =F170*(1+IF(G$3<=$O$2,$D170,$D170-($D170-$I$157)*MIN(G$3-$O$2,$Q$2)/$Q$2)) -> 2540.9342 | H170: =G170*(1+IF(H$3<=$O$2,$D170,$D170-($D170-$I$157)*MIN(H$3-$O$2,$Q$2)/$Q$2)) -> 2531.3189 | I170: =H170*(1+IF(I$3<=$O$2,$D170,$D170-($D170-$I$157)*MIN(I$3-$O$2,$Q$2)/$Q$2)) -> 2521.7399 | J170: =I170*(1+IF(J$3<=$O$2,$D170,$D170-($D170-$I$157)*MIN(J$3-$O$2,$Q$2)/$Q$2)) -> 2533.4223 | K170: =J170*(1+IF(K$3<=$O$2,$D170,$D170-($D170-$I$157)*MIN(K$3-$O$2,$Q$2)/$Q$2)) -> 2566.4822 | L170: =K170*(1+IF(L$3<=$O$2,$D170,$D170-($D170-$I$157)*MIN(L$3-$O$2,$Q$2)/$Q$2)) -> 2621.5751 | M170: =L170*(1+IF(M$3<=$O$2,$D170,$D170-($D170-$I$157)*MIN(M$3-$O$2,$Q$2)/$Q$2)) -> 2699.9161 | N170: =M170*(1+IF(N$3<=$O$2,$D170,$D170-($D170-$I$157)*MIN(N$3-$O$2,$Q$2)/$Q$2)) -> 2803.3228 | O170: =SUMPRODUCT(E170:N170,1/(1+$F$157)^$E$3:$N$3)*$E$2 -> 3393.0209 | P170: =N170*$E$2*(1+$I$157)/($F$157-$I$157)/(1+$F$157)^$N$3 -> 5647.2423 | Q170: =O170+P170 -> 9040.2633 | R170: =Q170-$G$2+$I$2 -> 7664.0633 | S170: =R170/$K$2 -> 204.32054 | T170: =S170-$M$2 -> -0.15827027
A171: 13 | B171: =IF(T170>0,B170,D170) -> -0.0037841797 | C171: =IF(T170>0,D170,C170) -> -0.0034179688 | D171: =(B171+C171)/2 -> -0.0036010742 | E171: =$C$2*(1+IF(E$3<=$O$2,$D171,$D171-($D171-$I$157)*MIN(E$3-$O$2,$Q$2)/$Q$2)) -> 2560.7452 | F171: =E171*(1+IF(F$3<=$O$2,$D171,$D171-($D171-$I$157)*MIN(F$3-$O$2,$Q$2)/$Q$2)) -> 2551.5238 | G171: =F171*(1+IF(G$3<=$O$2,$D171,$D171-($D171-$I$157)*MIN(G$3-$O$2,$Q$2)/$Q$2)) -> 2542.3356 | H171: =G171*(1+IF(H$3<=$O$2,$D171,$D171-($D171-$I$157)*MIN(H$3-$O$2,$Q$2)/$Q$2)) -> 2533.1804 | I171: =H171*(1+IF(I$3<=$O$2,$D171,$D171-($D171-$I$157)*MIN(I$3-$O$2,$Q$2)/$Q$2)) -> 2524.0583 | J171: =I171*(1+IF(J$3<=$O$2,$D171,$D171-($D171-$I$157)*MIN(J$3-$O$2,$Q$2)/$Q$2)) -> 2536.1211 | K171: =J171*(1+IF(K$3<=$O$2,$D171,$D171-($D171-$I$157)*MIN(K$3-$O$2,$Q$2)/$Q$2)) -> 2569.4948 | L171: =K171*(1+IF(L$3<=$O$2,$D171,$D171-($D171-$I$157)*MIN(L$3-$O$2,$Q$2)/$Q$2)) -> 2624.8406 | M171: =L171*(1+IF(M$3<=$O$2,$D171,$D171-($D171-$I$157)*MIN(M$3-$O$2,$Q$2)/$Q$2)) -> 2703.3753 | N171: =M171*(1+IF(N$3<=$O$2,$D171,$D171-($D171-$I$157)*MIN(N$3-$O$2,$Q$2)/$Q$2)) -> 2806.9146 | O171: =SUMPRODUCT(E171:N171,1/(1+$F$157)^$E$3:$N$3)*$E$2 -> 3395.734 | P171: =N171*$E$2*(1+$I$157)/($F$157-$I$157)/(1+$F$157)^$N$3 -> 5654.4778 | Q171: =O171+P171 -> 9050.2118 | R171: =Q171-$G$2+$I$2 -> 7674.0118 | S171: =R171/$K$2 -> 204.58576 | T171: =S171-$M$2 -> 0.10695413
... A182: 24 | B182: =IF(T181>0,B181,D181) -> -0.0036749244 | C182: =IF(T181>0,D181,C181) -> -0.0036747456 | D182: =(B182+C182)/2 -> -0.003674835 | E182: =$C$2*(1+IF(E$3<=$O$2,$D182,$D182-($D182-$I$157)*MIN(E$3-$O$2,$Q$2)/$Q$2)) -> 2560.5557 | F182: =E182*(1+IF(F$3<=$O$2,$D182,$D182-($D182-$I$157)*MIN(F$3-$O$2,$Q$2)/$Q$2)) -> 2551.1461 | G182: =F182*(1+IF(G$3<=$O$2,$D182,$D182-($D182-$I$157)*MIN(G$3-$O$2,$Q$2)/$Q$2)) -> 2541.771 | H182: =G182*(1+IF(H$3<=$O$2,$D182,$D182-($D182-$I$157)*MIN(H$3-$O$2,$Q$2)/$Q$2)) -> 2532.4304 | I182: =H182*(1+IF(I$3<=$O$2,$D182,$D182-($D182-$I$157)*MIN(I$3-$O$2,$Q$2)/$Q$2)) -> 2523.1242 | J182: =I182*(1+IF(J$3<=$O$2,$D182,$D182-($D182-$I$157)*MIN(J$3-$O$2,$Q$2)/$Q$2)) -> 2535.0336 | K182: =J182*(1+IF(K$3<=$O$2,$D182,$D182-($D182-$I$157)*MIN(K$3-$O$2,$Q$2)/$Q$2)) -> 2568.2809 | L182: =K182*(1+IF(L$3<=$O$2,$D182,$D182-($D182-$I$157)*MIN(L$3-$O$2,$Q$2)/$Q$2)) -> 2623.5247 | M182: =L182*(1+IF(M$3<=$O$2,$D182,$D182-($D182-$I$157)*MIN(M$3-$O$2,$Q$2)/$Q$2)) -> 2701.9813 | N182: =M182*(1+IF(N$3<=$O$2,$D182,$D182-($D182-$I$157)*MIN(N$3-$O$2,$Q$2)/$Q$2)) -> 2805.4672 | O182: =SUMPRODUCT(E182:N182,1/(1+$F$157)^$E$3:$N$3)*$E$2 -> 3394.6408 | P182: =N182*$E$2*(1+$I$157)/($F$157-$I$157)/(1+$F$157)^$N$3 -> 5651.5622 | Q182: =O182+P182 -> 9046.203 | R182: =Q182-$G$2+$I$2 -> 7670.003 | S182: =R182/$K$2 -> 204.47889 | T182: =S182-$M$2 -> 8.0191548e-05
...

Sheet DCF
B2: Morningstar (MORN): discounted cash flow
B3: Panel A runs the model at the solved growth rate, so it should land on the price. Panel B runs it at your view.
B5: A. At the solved (implied) growth rate
B6: Year | C6: 1 | D6: 2 | E6: 3 | F6: 4 | G6: 5 | H6: 6 | I6: 7 | J6: 8 | K6: 9 | L6: 10
B7: Revenue growth | C7: =IF(C$6<=Inputs!$C$46,Solver!$W$7,Solver!$W$7-(Solver!$W$7-Inputs!$C$37)*MIN(C$6-Inputs!$C$46,Inputs!$C$47)/Inputs!$C$47) -> 0.049811827 | D7: =IF(D$6<=Inputs!$C$46,Solver!$W$7,Solver!$W$7-(Solver!$W$7-Inputs!$C$37)*MIN(D$6-Inputs!$C$46,Inputs!$C$47)/Inputs!$C$47) -> 0.049811827 | E7: =IF(E$6<=Inputs!$C$46,Solver!$W$7,Solver!$W$7-(Solver!$W$7-Inputs!$C$37)*MIN(E$6-Inputs!$C$46,Inputs!$C$47)/Inputs!$C$47) -> 0.049811827 | F7: =IF(F$6<=Inputs!$C$46,Solver!$W$7,Solver!$W$7-(Solver!$W$7-Inputs!$C$37)*MIN(F$6-Inputs!$C$46,Inputs!$C$47)/Inputs!$C$47) -> 0.049811827 | G7: =IF(G$6<=Inputs!$C$46,Solver!$W$7,Solver!$W$7-(Solver!$W$7-Inputs!$C$37)*MIN(G$6-Inputs!$C$46,Inputs!$C$47)/Inputs!$C$47) -> 0.049811827 | H7: =IF(H$6<=Inputs!$C$46,Solver!$W$7,Solver!$W$7-(Solver!$W$7-Inputs!$C$37)*MIN(H$6-Inputs!$C$46,Inputs!$C$47)/Inputs!$C$47) -> 0.045509461 | I7: =IF(I$6<=Inputs!$C$46,Solver!$W$7,Solver!$W$7-(Solver!$W$7-Inputs!$C$37)*MIN(I$6-Inputs!$C$46,Inputs!$C$47)/Inputs!$C$47) -> 0.041207096 | J7: =IF(J$6<=Inputs!$C$46,Solver!$W$7,Solver!$W$7-(Solver!$W$7-Inputs!$C$37)*MIN(J$6-Inputs!$C$46,Inputs!$C$47)/Inputs!$C$47) -> 0.036904731 | ... L7: =IF(L$6<=Inputs!$C$46,Solver!$W$7,Solver!$W$7-(Solver!$W$7-Inputs!$C$37)*MIN(L$6-Inputs!$C$46,Inputs!$C$47)/Inputs!$C$47) -> 0.0283
B8: Revenue ($mm) | C8: =Inputs!$C$12*(1+C7) -> 2698.0164 | D8: =C8*(1+D7) -> 2832.4095 | E8: =D8*(1+E7) -> 2973.497 | F8: =E8*(1+F7) -> 3121.6123 | G8: =F8*(1+G7) -> 3277.1055 | H8: =G8*(1+H7) -> 3426.2448 | I8: =H8*(1+I7) -> 3567.4304 | J8: =I8*(1+J7) -> 3699.0855 | K8: =J8*(1+K7) -> 3819.6844 | L8: =K8*(1+L7) -> 3927.7815
B9: Unlevered free cash flow ($mm) | C9: =C8*Inputs!$C$23 -> 538.97339 | D9: =D8*Inputs!$C$23 -> 565.82064 | E9: =E8*Inputs!$C$23 -> 594.0052 | F9: =F8*Inputs!$C$23 -> 623.59368 | G9: =G8*Inputs!$C$23 -> 654.65602 | H9: =H8*Inputs!$C$23 -> 684.44907 | I9: =I8*Inputs!$C$23 -> 712.65323 | J9: =J8*Inputs!$C$23 -> 738.9535 | ... L9: =L8*Inputs!$C$23 -> 784.63931
B10: Discount factor | C10: =1/(1+WACC!$C$34)^C$6 -> 0.91392362 | D10: =1/(1+WACC!$C$34)^D$6 -> 0.83525639 | E10: =1/(1+WACC!$C$34)^E$6 -> 0.76336054 | F10: =1/(1+WACC!$C$34)^F$6 -> 0.69765323 | G10: =1/(1+WACC!$C$34)^G$6 -> 0.63760177 | H10: =1/(1+WACC!$C$34)^H$6 -> 0.58271932 | I10: =1/(1+WACC!$C$34)^I$6 -> 0.53256095 | J10: =1/(1+WACC!$C$34)^J$6 -> 0.48672004 | ... L10: =1/(1+WACC!$C$34)^L$6 -> 0.40653602
B11: Present value ($mm) | C11: =C9*C10 -> 492.58051 | D11: =D9*D10 -> 472.60531 | E11: =E9*E10 -> 453.44013 | F11: =F9*F10 -> 435.05215 | G11: =G9*G10 -> 417.40984 | H11: =H9*H10 -> 398.8417 | I11: =I9*I10 -> 379.53128 | J11: =J9*J10 -> 359.66347 | ... L11: =L9*L10 -> 318.98414
B13: Sum of present values, years 1 to 10 | C13: =SUM(C11:L11) -> 4067.53
B14: Terminal value at year 10 | C14: =L9*(1+Inputs!$C$37)/(WACC!$C$34-Inputs!$C$37) -> 12246.565
B15: Present value of terminal value | C15: =C14*L10 -> 4978.67
B16: Enterprise value | C16: =C13+C15 -> 9046.2
B17: Less: debt | C17: =-Inputs!$C$27 -> -1900
B18: Plus: cash | C18: =Inputs!$C$28 -> 523.8
B19: Equity value | C19: =SUM(C16:C18) -> 7670
B20: Shares (mm) | C20: =Inputs!$C$7 -> 37.51
B21: Value per share ($) | C21: =C19/C20 -> 204.47881
B22: Price at the lock ($) | C22: =Inputs!$C$6 -> 204.47881
B23: Value / price - 1 | C23: =C21/C22-1 -> -8.2680529e-12
B24: Terminal value share of enterprise value | C24: =C15/C16 -> 0.55036037
B25: B. At your view of growth (Inputs tab, yellow cell)
B26: Year | C26: 1 | D26: 2 | E26: 3 | F26: 4 | G26: 5 | H26: 6 | I26: 7 | J26: 8 | K26: 9 | L26: 10
B27: Revenue growth | C27: =IF(C$26<=Inputs!$C$46,Inputs!$C$45,Inputs!$C$45-(Inputs!$C$45-Inputs!$C$37)*MIN(C$26-Inputs!$C$46,Inputs!$C$47)/Inputs!$C$47) -> 0.082073834 | D27: =IF(D$26<=Inputs!$C$46,Inputs!$C$45,Inputs!$C$45-(Inputs!$C$45-Inputs!$C$37)*MIN(D$26-Inputs!$C$46,Inputs!$C$47)/Inputs!$C$47) -> 0.082073834 | E27: =IF(E$26<=Inputs!$C$46,Inputs!$C$45,Inputs!$C$45-(Inputs!$C$45-Inputs!$C$37)*MIN(E$26-Inputs!$C$46,Inputs!$C$47)/Inputs!$C$47) -> 0.082073834 | F27: =IF(F$26<=Inputs!$C$46,Inputs!$C$45,Inputs!$C$45-(Inputs!$C$45-Inputs!$C$37)*MIN(F$26-Inputs!$C$46,Inputs!$C$47)/Inputs!$C$47) -> 0.082073834 | G27: =IF(G$26<=Inputs!$C$46,Inputs!$C$45,Inputs!$C$45-(Inputs!$C$45-Inputs!$C$37)*MIN(G$26-Inputs!$C$46,Inputs!$C$47)/Inputs!$C$47) -> 0.082073834 | H27: =IF(H$26<=Inputs!$C$46,Inputs!$C$45,Inputs!$C$45-(Inputs!$C$45-Inputs!$C$37)*MIN(H$26-Inputs!$C$46,Inputs!$C$47)/Inputs!$C$47) -> 0.071319067 | I27: =IF(I$26<=Inputs!$C$46,Inputs!$C$45,Inputs!$C$45-(Inputs!$C$45-Inputs!$C$37)*MIN(I$26-Inputs!$C$46,Inputs!$C$47)/Inputs!$C$47) -> 0.0605643 | J27: =IF(J$26<=Inputs!$C$46,Inputs!$C$45,Inputs!$C$45-(Inputs!$C$45-Inputs!$C$37)*MIN(J$26-Inputs!$C$46,Inputs!$C$47)/Inputs!$C$47) -> 0.049809533 | ... L27: =IF(L$26<=Inputs!$C$46,Inputs!$C$45,Inputs!$C$45-(Inputs!$C$45-Inputs!$C$37)*MIN(L$26-Inputs!$C$46,Inputs!$C$47)/Inputs!$C$47) -> 0.0283
B28: Revenue ($mm) | C28: =Inputs!$C$12*(1+C27) -> 2780.9298 | D28: =C28*(1+D27) -> 3009.1713 | E28: =D28*(1+E27) -> 3256.1455 | F28: =E28*(1+F27) -> 3523.3899 | G28: =F28*(1+G27) -> 3812.568 | H28: =G28*(1+H27) -> 4084.4768 | I28: =H28*(1+I27) -> 4331.8503 | J28: =I28*(1+J27) -> 4547.6177 | K28: =J28*(1+K27) -> 4725.2239 | L28: =K28*(1+L27) -> 4858.9477
B29: Unlevered free cash flow ($mm) | C29: =C28*Inputs!$C$23 -> 555.53671 | D29: =D28*Inputs!$C$23 -> 601.13173 | E29: =E28*Inputs!$C$23 -> 650.46892 | F29: =F28*Inputs!$C$23 -> 703.8554 | G29: =G28*Inputs!$C$23 -> 761.62351 | H29: =H28*Inputs!$C$23 -> 815.94179 | I29: =I28*Inputs!$C$23 -> 865.35873 | J29: =J28*Inputs!$C$23 -> 908.46184 | ... L29: =L28*Inputs!$C$23 -> 970.65516
B30: Discount factor | C30: =1/(1+WACC!$C$34)^C$26 -> 0.91392362 | D30: =1/(1+WACC!$C$34)^D$26 -> 0.83525639 | E30: =1/(1+WACC!$C$34)^E$26 -> 0.76336054 | F30: =1/(1+WACC!$C$34)^F$26 -> 0.69765323 | G30: =1/(1+WACC!$C$34)^G$26 -> 0.63760177 | H30: =1/(1+WACC!$C$34)^H$26 -> 0.58271932 | I30: =1/(1+WACC!$C$34)^I$26 -> 0.53256095 | J30: =1/(1+WACC!$C$34)^J$26 -> 0.48672004 | ... L30: =1/(1+WACC!$C$34)^L$26 -> 0.40653602
B31: Present value ($mm) | C31: =C29*C30 -> 507.71812 | D31: =D29*D30 -> 502.09912 | E31: =E29*E30 -> 496.54231 | F31: =F29*F30 -> 491.04699 | G31: =G29*G30 -> 485.6125 | H31: =H29*H30 -> 475.46504 | I31: =I29*I30 -> 460.85627 | J31: =J29*J30 -> 442.16658 | ... L31: =L29*L30 -> 394.60628
B33: Sum of present values, years 1 to 10 | C33: =SUM(C31:L31) -> 4676.002
B34: Terminal value at year 10 | C34: =L29*(1+Inputs!$C$37)/(WACC!$C$34-Inputs!$C$37) -> 15149.881
B35: Present value of terminal value | C35: =C34*L30 -> 6158.9722
B36: Enterprise value | C36: =C33+C35 -> 10834.974
B37: Less: debt | C37: =-Inputs!$C$27 -> -1900
B38: Plus: cash | C38: =Inputs!$C$28 -> 523.8
B39: Equity value | C39: =SUM(C36:C38) -> 9458.7741
B40: Shares (mm) | C40: =Inputs!$C$7 -> 37.51
B41: Value per share ($) | C41: =C39/C40 -> 252.16673
B42: Price at the lock ($) | C42: =Inputs!$C$6 -> 204.47881
B43: Value / price - 1 | C43: =C41/C42-1 -> 0.23321697
B44: Terminal value share of enterprise value | C44: =C35/C36 -> 0.56843441

Sheet Sensitivity
B2: Morningstar (MORN): sensitivity
B3: Table A re-solves implied growth for each pair of inputs (Solver tab, blocks 2 to 26). Table B values the stock at a growth view.
B5: WACC step | C5: 0.005 | D5: Terminal-growth step | F5: 0.005
B6: Growth-view step | C6: 0.02
B8: A. Implied 5-year growth: WACC (rows) by terminal growth (columns)
C9: =Inputs!$C$37+(0-2)*$F$5 -> 0.0183 | D9: =Inputs!$C$37+(1-2)*$F$5 -> 0.0233 | E9: =Inputs!$C$37+(2-2)*$F$5 -> 0.0283 | F9: =Inputs!$C$37+(3-2)*$F$5 -> 0.0333 | G9: =Inputs!$C$37+(4-2)*$F$5 -> 0.0383
B10: =WACC!$C$34+(0-2)*$C$5 -> 0.084183338 | C10: =Solver!$D$74 -> 0.041362494 | D10: =Solver!$D$101 -> 0.031519502 | E10: =Solver!$D$128 -> 0.020840019 | F10: =Solver!$D$155 -> 0.0091736615 | G10: =Solver!$D$182 -> -0.003674835 | I10: Centre cell = the base case. Each step changes one input by the step size above.
B11: =WACC!$C$34+(1-2)*$C$5 -> 0.089183338 | C11: =Solver!$D$209 -> 0.0547553 | D11: =Solver!$D$236 -> 0.045588583 | E11: =Solver!$D$263 -> 0.035700351 | F11: =Solver!$D$290 -> 0.024972051 | G11: =Solver!$D$317 -> 0.013252765
B12: =WACC!$C$34+(2-2)*$C$5 -> 0.094183338 | C12: =Solver!$D$344 -> 0.067600578 | D12: =Solver!$D$371 -> 0.059020728 | E12: =Solver!$D$398 -> 0.04981181 | F12: =Solver!$D$425 -> 0.039878517 | G12: =Solver!$D$452 -> 0.02910158
B13: =WACC!$C$34+(3-2)*$C$5 -> 0.099183338 | C13: =Solver!$D$479 -> 0.079968423 | D13: =Solver!$D$506 -> 0.071902663 | E13: =Solver!$D$533 -> 0.063283473 | F13: =Solver!$D$560 -> 0.054032534 | G13: =Solver!$D$587 -> 0.04405418
B14: =WACC!$C$34+(4-2)*$C$5 -> 0.10418334 | C14: =Solver!$D$614 -> 0.091916591 | D14: =Solver!$D$641 -> 0.084305018 | E14: =Solver!$D$668 -> 0.076202065 | F14: =Solver!$D$695 -> 0.067543536 | G14: =Solver!$D$722 -> 0.058250576
B17: B. Value per share: WACC (rows) by your growth view (columns)
C18: =Inputs!$C$45+(0-2)*$C$6 -> 0.042073834 | D18: =Inputs!$C$45+(1-2)*$C$6 -> 0.062073834 | E18: =Inputs!$C$45+(2-2)*$C$6 -> 0.082073834 | F18: =Inputs!$C$45+(3-2)*$C$6 -> 0.10207383 | G18: =Inputs!$C$45+(4-2)*$C$6 -> 0.12207383
B19: =WACC!$C$34+(0-2)*$C$5 -> 0.084183338 | C19: =(SUMPRODUCT($C28:$L28,1/(1+$B19)^$C$27:$L$27)*Inputs!$C$23+$L28*Inputs!$C$23*(1+Inputs!$C$37)/($B19-Inputs!$C$37)/(1+$B19)^$L$27-Inputs!$C$27+Inputs!$C$28)/Inputs!$C$7 -> 236.07456 | D19: =(SUMPRODUCT($C29:$L29,1/(1+$B19)^$C$27:$L$27)*Inputs!$C$23+$L29*Inputs!$C$23*(1+Inputs!$C$37)/($B19-Inputs!$C$37)/(1+$B19)^$L$27-Inputs!$C$27+Inputs!$C$28)/Inputs!$C$7 -> 269.35836 | E19: =(SUMPRODUCT($C30:$L30,1/(1+$B19)^$C$27:$L$27)*Inputs!$C$23+$L30*Inputs!$C$23*(1+Inputs!$C$37)/($B19-Inputs!$C$37)/(1+$B19)^$L$27-Inputs!$C$27+Inputs!$C$28)/Inputs!$C$7 -> 306.41099 | F19: =(SUMPRODUCT($C31:$L31,1/(1+$B19)^$C$27:$L$27)*Inputs!$C$23+$L31*Inputs!$C$23*(1+Inputs!$C$37)/($B19-Inputs!$C$37)/(1+$B19)^$L$27-Inputs!$C$27+Inputs!$C$28)/Inputs!$C$7 -> 347.60487 | G19: =(SUMPRODUCT($C32:$L32,1/(1+$B19)^$C$27:$L$27)*Inputs!$C$23+$L32*Inputs!$C$23*(1+Inputs!$C$37)/($B19-Inputs!$C$37)/(1+$B19)^$L$27-Inputs!$C$27+Inputs!$C$28)/Inputs!$C$7 -> 393.34322 | I19: Compare with the price at the lock: $204.48.
B20: =WACC!$C$34+(1-2)*$C$5 -> 0.089183338 | C20: =(SUMPRODUCT($C28:$L28,1/(1+$B20)^$C$27:$L$27)*Inputs!$C$23+$L28*Inputs!$C$23*(1+Inputs!$C$37)/($B20-Inputs!$C$37)/(1+$B20)^$L$27-Inputs!$C$27+Inputs!$C$28)/Inputs!$C$7 -> 213.41675 | D20: =(SUMPRODUCT($C29:$L29,1/(1+$B20)^$C$27:$L$27)*Inputs!$C$23+$L29*Inputs!$C$23*(1+Inputs!$C$37)/($B20-Inputs!$C$37)/(1+$B20)^$L$27-Inputs!$C$27+Inputs!$C$28)/Inputs!$C$7 -> 243.53814 | E20: =(SUMPRODUCT($C30:$L30,1/(1+$B20)^$C$27:$L$27)*Inputs!$C$23+$L30*Inputs!$C$23*(1+Inputs!$C$37)/($B20-Inputs!$C$37)/(1+$B20)^$L$27-Inputs!$C$27+Inputs!$C$28)/Inputs!$C$7 -> 277.04619 | F20: =(SUMPRODUCT($C31:$L31,1/(1+$B20)^$C$27:$L$27)*Inputs!$C$23+$L31*Inputs!$C$23*(1+Inputs!$C$37)/($B20-Inputs!$C$37)/(1+$B20)^$L$27-Inputs!$C$27+Inputs!$C$28)/Inputs!$C$7 -> 314.27421 | G20: =(SUMPRODUCT($C32:$L32,1/(1+$B20)^$C$27:$L$27)*Inputs!$C$23+$L32*Inputs!$C$23*(1+Inputs!$C$37)/($B20-Inputs!$C$37)/(1+$B20)^$L$27-Inputs!$C$27+Inputs!$C$28)/Inputs!$C$7 -> 355.58298
B21: =WACC!$C$34+(2-2)*$C$5 -> 0.094183338 | C21: =(SUMPRODUCT($C28:$L28,1/(1+$B21)^$C$27:$L$27)*Inputs!$C$23+$L28*Inputs!$C$23*(1+Inputs!$C$37)/($B21-Inputs!$C$37)/(1+$B21)^$L$27-Inputs!$C$27+Inputs!$C$28)/Inputs!$C$7 -> 194.20402 | D21: =(SUMPRODUCT($C29:$L29,1/(1+$B21)^$C$27:$L$27)*Inputs!$C$23+$L29*Inputs!$C$23*(1+Inputs!$C$37)/($B21-Inputs!$C$37)/(1+$B21)^$L$27-Inputs!$C$27+Inputs!$C$28)/Inputs!$C$7 -> 221.65316 | E21: =(SUMPRODUCT($C30:$L30,1/(1+$B21)^$C$27:$L$27)*Inputs!$C$23+$L30*Inputs!$C$23*(1+Inputs!$C$37)/($B21-Inputs!$C$37)/(1+$B21)^$L$27-Inputs!$C$27+Inputs!$C$28)/Inputs!$C$7 -> 252.16673 | F21: =(SUMPRODUCT($C31:$L31,1/(1+$B21)^$C$27:$L$27)*Inputs!$C$23+$L31*Inputs!$C$23*(1+Inputs!$C$37)/($B21-Inputs!$C$37)/(1+$B21)^$L$27-Inputs!$C$27+Inputs!$C$28)/Inputs!$C$7 -> 286.04512 | G21: =(SUMPRODUCT($C32:$L32,1/(1+$B21)^$C$27:$L$27)*Inputs!$C$23+$L32*Inputs!$C$23*(1+Inputs!$C$37)/($B21-Inputs!$C$37)/(1+$B21)^$L$27-Inputs!$C$27+Inputs!$C$28)/Inputs!$C$7 -> 323.61335
B22: =WACC!$C$34+(3-2)*$C$5 -> 0.099183338 | C22: =(SUMPRODUCT($C28:$L28,1/(1+$B22)^$C$27:$L$27)*Inputs!$C$23+$L28*Inputs!$C$23*(1+Inputs!$C$37)/($B22-Inputs!$C$37)/(1+$B22)^$L$27-Inputs!$C$27+Inputs!$C$28)/Inputs!$C$7 -> 177.70716 | D22: =(SUMPRODUCT($C29:$L29,1/(1+$B22)^$C$27:$L$27)*Inputs!$C$23+$L29*Inputs!$C$23*(1+Inputs!$C$37)/($B22-Inputs!$C$37)/(1+$B22)^$L$27-Inputs!$C$27+Inputs!$C$28)/Inputs!$C$7 -> 202.87018 | E22: =(SUMPRODUCT($C30:$L30,1/(1+$B22)^$C$27:$L$27)*Inputs!$C$23+$L30*Inputs!$C$23*(1+Inputs!$C$37)/($B22-Inputs!$C$37)/(1+$B22)^$L$27-Inputs!$C$27+Inputs!$C$28)/Inputs!$C$7 -> 230.82259 | F22: =(SUMPRODUCT($C31:$L31,1/(1+$B22)^$C$27:$L$27)*Inputs!$C$23+$L31*Inputs!$C$23*(1+Inputs!$C$37)/($B22-Inputs!$C$37)/(1+$B22)^$L$27-Inputs!$C$27+Inputs!$C$28)/Inputs!$C$7 -> 261.83671 | G22: =(SUMPRODUCT($C32:$L32,1/(1+$B22)^$C$27:$L$27)*Inputs!$C$23+$L32*Inputs!$C$23*(1+Inputs!$C$37)/($B22-Inputs!$C$37)/(1+$B22)^$L$27-Inputs!$C$27+Inputs!$C$28)/Inputs!$C$7 -> 296.20713
B23: =WACC!$C$34+(4-2)*$C$5 -> 0.10418334 | C23: =(SUMPRODUCT($C28:$L28,1/(1+$B23)^$C$27:$L$27)*Inputs!$C$23+$L28*Inputs!$C$23*(1+Inputs!$C$37)/($B23-Inputs!$C$37)/(1+$B23)^$L$27-Inputs!$C$27+Inputs!$C$28)/Inputs!$C$7 -> 163.38915 | D23: =(SUMPRODUCT($C29:$L29,1/(1+$B23)^$C$27:$L$27)*Inputs!$C$23+$L29*Inputs!$C$23*(1+Inputs!$C$37)/($B23-Inputs!$C$37)/(1+$B23)^$L$27-Inputs!$C$27+Inputs!$C$28)/Inputs!$C$7 -> 186.57557 | E23: =(SUMPRODUCT($C30:$L30,1/(1+$B23)^$C$27:$L$27)*Inputs!$C$23+$L30*Inputs!$C$23*(1+Inputs!$C$37)/($B23-Inputs!$C$37)/(1+$B23)^$L$27-Inputs!$C$27+Inputs!$C$28)/Inputs!$C$7 -> 212.31416 | F23: =(SUMPRODUCT($C31:$L31,1/(1+$B23)^$C$27:$L$27)*Inputs!$C$23+$L31*Inputs!$C$23*(1+Inputs!$C$37)/($B23-Inputs!$C$37)/(1+$B23)^$L$27-Inputs!$C$27+Inputs!$C$28)/Inputs!$C$7 -> 240.85303 | G23: =(SUMPRODUCT($C32:$L32,1/(1+$B23)^$C$27:$L$27)*Inputs!$C$23+$L32*Inputs!$C$23*(1+Inputs!$C$37)/($B23-Inputs!$C$37)/(1+$B23)^$L$27-Inputs!$C$27+Inputs!$C$28)/Inputs!$C$7 -> 272.4606
B26: Helper: revenue paths for each growth view (years 1 to 10)
C27: 1 | D27: 2 | E27: 3 | F27: 4 | G27: 5 | H27: 6 | I27: 7 | J27: 8 | K27: 9 | L27: 10
B28: =C$18 -> 0.042073834 | C28: =Inputs!$C$12*(1+IF(C$27<=Inputs!$C$46,$B28,$B28-($B28-Inputs!$C$37)*MIN(C$27-Inputs!$C$46,Inputs!$C$47)/Inputs!$C$47)) -> 2678.1298 | D28: =C28*(1+IF(D$27<=Inputs!$C$46,$B28,$B28-($B28-Inputs!$C$37)*MIN(D$27-Inputs!$C$46,Inputs!$C$47)/Inputs!$C$47)) -> 2790.8089 | E28: =D28*(1+IF(E$27<=Inputs!$C$46,$B28,$B28-($B28-Inputs!$C$37)*MIN(E$27-Inputs!$C$46,Inputs!$C$47)/Inputs!$C$47)) -> 2908.229 | F28: =E28*(1+IF(F$27<=Inputs!$C$46,$B28,$B28-($B28-Inputs!$C$37)*MIN(F$27-Inputs!$C$46,Inputs!$C$47)/Inputs!$C$47)) -> 3030.5893 | G28: =F28*(1+IF(G$27<=Inputs!$C$46,$B28,$B28-($B28-Inputs!$C$37)*MIN(G$27-Inputs!$C$46,Inputs!$C$47)/Inputs!$C$47)) -> 3158.0978 | H28: =G28*(1+IF(H$27<=Inputs!$C$46,$B28,$B28-($B28-Inputs!$C$37)*MIN(H$27-Inputs!$C$46,Inputs!$C$47)/Inputs!$C$47)) -> 3282.2713 | I28: =H28*(1+IF(I$27<=Inputs!$C$46,$B28,$B28-($B28-Inputs!$C$37)*MIN(I$27-Inputs!$C$46,Inputs!$C$47)/Inputs!$C$47)) -> 3402.2852 | J28: =I28*(1+IF(J$27<=Inputs!$C$46,$B28,$B28-($B28-Inputs!$C$37)*MIN(J$27-Inputs!$C$46,Inputs!$C$47)/Inputs!$C$47)) -> 3517.3149 | K28: =J28*(1+IF(K$27<=Inputs!$C$46,$B28,$B28-($B28-Inputs!$C$37)*MIN(K$27-Inputs!$C$46,Inputs!$C$47)/Inputs!$C$47)) -> 3626.5443 | L28: =K28*(1+IF(L$27<=Inputs!$C$46,$B28,$B28-($B28-Inputs!$C$37)*MIN(L$27-Inputs!$C$46,Inputs!$C$47)/Inputs!$C$47)) -> 3729.1755
B29: =D$18 -> 0.062073834 | C29: =Inputs!$C$12*(1+IF(C$27<=Inputs!$C$46,$B29,$B29-($B29-Inputs!$C$37)*MIN(C$27-Inputs!$C$46,Inputs!$C$47)/Inputs!$C$47)) -> 2729.5298 | D29: =C29*(1+IF(D$27<=Inputs!$C$46,$B29,$B29-($B29-Inputs!$C$37)*MIN(D$27-Inputs!$C$46,Inputs!$C$47)/Inputs!$C$47)) -> 2898.9621 | E29: =D29*(1+IF(E$27<=Inputs!$C$46,$B29,$B29-($B29-Inputs!$C$37)*MIN(E$27-Inputs!$C$46,Inputs!$C$47)/Inputs!$C$47)) -> 3078.9118 | F29: =E29*(1+IF(F$27<=Inputs!$C$46,$B29,$B29-($B29-Inputs!$C$37)*MIN(F$27-Inputs!$C$46,Inputs!$C$47)/Inputs!$C$47)) -> 3270.0317 | G29: =F29*(1+IF(G$27<=Inputs!$C$46,$B29,$B29-($B29-Inputs!$C$37)*MIN(G$27-Inputs!$C$46,Inputs!$C$47)/Inputs!$C$47)) -> 3473.0151 | H29: =G29*(1+IF(H$27<=Inputs!$C$46,$B29,$B29-($B29-Inputs!$C$37)*MIN(H$27-Inputs!$C$46,Inputs!$C$47)/Inputs!$C$47)) -> 3665.139 | I29: =H29*(1+IF(I$27<=Inputs!$C$46,$B29,$B29-($B29-Inputs!$C$37)*MIN(I$27-Inputs!$C$46,Inputs!$C$47)/Inputs!$C$47)) -> 3843.134 | J29: =I29*(1+IF(J$27<=Inputs!$C$46,$B29,$B29-($B29-Inputs!$C$37)*MIN(J$27-Inputs!$C$46,Inputs!$C$47)/Inputs!$C$47)) -> 4003.8136 | K29: =J29*(1+IF(K$27<=Inputs!$C$46,$B29,$B29-($B29-Inputs!$C$37)*MIN(K$27-Inputs!$C$46,Inputs!$C$47)/Inputs!$C$47)) -> 4144.1663 | L29: =K29*(1+IF(L$27<=Inputs!$C$46,$B29,$B29-($B29-Inputs!$C$37)*MIN(L$27-Inputs!$C$46,Inputs!$C$47)/Inputs!$C$47)) -> 4261.4462
B30: =E$18 -> 0.082073834 | C30: =Inputs!$C$12*(1+IF(C$27<=Inputs!$C$46,$B30,$B30-($B30-Inputs!$C$37)*MIN(C$27-Inputs!$C$46,Inputs!$C$47)/Inputs!$C$47)) -> 2780.9298 | D30: =C30*(1+IF(D$27<=Inputs!$C$46,$B30,$B30-($B30-Inputs!$C$37)*MIN(D$27-Inputs!$C$46,Inputs!$C$47)/Inputs!$C$47)) -> 3009.1713 | E30: =D30*(1+IF(E$27<=Inputs!$C$46,$B30,$B30-($B30-Inputs!$C$37)*MIN(E$27-Inputs!$C$46,Inputs!$C$47)/Inputs!$C$47)) -> 3256.1455 | F30: =E30*(1+IF(F$27<=Inputs!$C$46,$B30,$B30-($B30-Inputs!$C$37)*MIN(F$27-Inputs!$C$46,Inputs!$C$47)/Inputs!$C$47)) -> 3523.3899 | G30: =F30*(1+IF(G$27<=Inputs!$C$46,$B30,$B30-($B30-Inputs!$C$37)*MIN(G$27-Inputs!$C$46,Inputs!$C$47)/Inputs!$C$47)) -> 3812.568 | H30: =G30*(1+IF(H$27<=Inputs!$C$46,$B30,$B30-($B30-Inputs!$C$37)*MIN(H$27-Inputs!$C$46,Inputs!$C$47)/Inputs!$C$47)) -> 4084.4768 | I30: =H30*(1+IF(I$27<=Inputs!$C$46,$B30,$B30-($B30-Inputs!$C$37)*MIN(I$27-Inputs!$C$46,Inputs!$C$47)/Inputs!$C$47)) -> 4331.8503 | J30: =I30*(1+IF(J$27<=Inputs!$C$46,$B30,$B30-($B30-Inputs!$C$37)*MIN(J$27-Inputs!$C$46,Inputs!$C$47)/Inputs!$C$47)) -> 4547.6177 | K30: =J30*(1+IF(K$27<=Inputs!$C$46,$B30,$B30-($B30-Inputs!$C$37)*MIN(K$27-Inputs!$C$46,Inputs!$C$47)/Inputs!$C$47)) -> 4725.2239 | L30: =K30*(1+IF(L$27<=Inputs!$C$46,$B30,$B30-($B30-Inputs!$C$37)*MIN(L$27-Inputs!$C$46,Inputs!$C$47)/Inputs!$C$47)) -> 4858.9477
B31: =F$18 -> 0.10207383 | C31: =Inputs!$C$12*(1+IF(C$27<=Inputs!$C$46,$B31,$B31-($B31-Inputs!$C$37)*MIN(C$27-Inputs!$C$46,Inputs!$C$47)/Inputs!$C$47)) -> 2832.3298 | D31: =C31*(1+IF(D$27<=Inputs!$C$46,$B31,$B31-($B31-Inputs!$C$37)*MIN(D$27-Inputs!$C$46,Inputs!$C$47)/Inputs!$C$47)) -> 3121.4365 | E31: =D31*(1+IF(E$27<=Inputs!$C$46,$B31,$B31-($B31-Inputs!$C$37)*MIN(E$27-Inputs!$C$46,Inputs!$C$47)/Inputs!$C$47)) -> 3440.0535 | F31: =E31*(1+IF(F$27<=Inputs!$C$46,$B31,$B31-($B31-Inputs!$C$37)*MIN(F$27-Inputs!$C$46,Inputs!$C$47)/Inputs!$C$47)) -> 3791.1929 | G31: =F31*(1+IF(G$27<=Inputs!$C$46,$B31,$B31-($B31-Inputs!$C$37)*MIN(G$27-Inputs!$C$46,Inputs!$C$47)/Inputs!$C$47)) -> 4178.1745 | H31: =G31*(1+IF(H$27<=Inputs!$C$46,$B31,$B31-($B31-Inputs!$C$37)*MIN(H$27-Inputs!$C$46,Inputs!$C$47)/Inputs!$C$47)) -> 4543.0089 | I31: =H31*(1+IF(I$27<=Inputs!$C$46,$B31,$B31-($B31-Inputs!$C$37)*MIN(I$27-Inputs!$C$46,Inputs!$C$47)/Inputs!$C$47)) -> 4872.6691 | J31: =I31*(1+IF(J$27<=Inputs!$C$46,$B31,$B31-($B31-Inputs!$C$37)*MIN(J$27-Inputs!$C$46,Inputs!$C$47)/Inputs!$C$47)) -> 5154.3558 | K31: =J31*(1+IF(K$27<=Inputs!$C$46,$B31,$B31-($B31-Inputs!$C$37)*MIN(K$27-Inputs!$C$46,Inputs!$C$47)/Inputs!$C$47)) -> 5376.2754 | L31: =K31*(1+IF(L$27<=Inputs!$C$46,$B31,$B31-($B31-Inputs!$C$37)*MIN(L$27-Inputs!$C$46,Inputs!$C$47)/Inputs!$C$47)) -> 5528.424
B32: =G$18 -> 0.12207383 | C32: =Inputs!$C$12*(1+IF(C$27<=Inputs!$C$46,$B32,$B32-($B32-Inputs!$C$37)*MIN(C$27-Inputs!$C$46,Inputs!$C$47)/Inputs!$C$47)) -> 2883.7298 | D32: =C32*(1+IF(D$27<=Inputs!$C$46,$B32,$B32-($B32-Inputs!$C$37)*MIN(D$27-Inputs!$C$46,Inputs!$C$47)/Inputs!$C$47)) -> 3235.7577 | E32: =D32*(1+IF(E$27<=Inputs!$C$46,$B32,$B32-($B32-Inputs!$C$37)*MIN(E$27-Inputs!$C$46,Inputs!$C$47)/Inputs!$C$47)) -> 3630.759 | F32: =E32*(1+IF(F$27<=Inputs!$C$46,$B32,$B32-($B32-Inputs!$C$37)*MIN(F$27-Inputs!$C$46,Inputs!$C$47)/Inputs!$C$47)) -> 4073.9797 | G32: =F32*(1+IF(G$27<=Inputs!$C$46,$B32,$B32-($B32-Inputs!$C$37)*MIN(G$27-Inputs!$C$46,Inputs!$C$47)/Inputs!$C$47)) -> 4571.306 | H32: =G32*(1+IF(H$27<=Inputs!$C$46,$B32,$B32-($B32-Inputs!$C$37)*MIN(H$27-Inputs!$C$46,Inputs!$C$47)/Inputs!$C$47)) -> 5043.6091 | I32: =H32*(1+IF(I$27<=Inputs!$C$46,$B32,$B32-($B32-Inputs!$C$37)*MIN(I$27-Inputs!$C$46,Inputs!$C$47)/Inputs!$C$47)) -> 5470.1184 | J32: =I32*(1+IF(J$27<=Inputs!$C$46,$B32,$B32-($B32-Inputs!$C$37)*MIN(J$27-Inputs!$C$46,Inputs!$C$47)/Inputs!$C$47)) -> 5830.1043 | K32: =J32*(1+IF(K$27<=Inputs!$C$46,$B32,$B32-($B32-Inputs!$C$37)*MIN(K$27-Inputs!$C$46,Inputs!$C$47)/Inputs!$C$47)) -> 6104.4385 | L32: =K32*(1+IF(L$27<=Inputs!$C$46,$B32,$B32-($B32-Inputs!$C$37)*MIN(L$27-Inputs!$C$46,Inputs!$C$47)/Inputs!$C$47)) -> 6277.1941

Sheet Check
B2: Morningstar (MORN): check against the Python pipeline
B3: Python values are typed in (blue) from the pipeline that runs the site. Each row passes if the two agree within the tolerance.
B5: Item | C5: This workbook | D5: Python pipeline | E5: Difference | F5: Result
B6: Unlevered free-cash-flow margin | C6: =Inputs!$C$23 -> 0.19976654 | D6: 0.19976654 | E6: =C6-D6 -> -3.0350194e-09 | F6: =IF(ABS(E6)<=0.00005,"Pass","Check") -> Pass
B7: Group median unlevered beta | C7: =WACC!$C$11 -> 1.0518991 | D7: 1.0518991 | E7: =C7-D7 -> 8.6848484e-10 | F7: =IF(ABS(E7)<=0.0005,"Pass","Check") -> Pass
B8: WACC | C8: =WACC!$C$34 -> 0.094183338 | D8: 0.09418334 | E8: =C8-D8 -> -2.446156e-09 | F8: =IF(ABS(E8)<=0.00005,"Pass","Check") -> Pass
B9: Terminal growth | C9: =Inputs!$C$37 -> 0.0283 | D9: 0.0283 | E9: =C9-D9 -> 0 | F9: =IF(ABS(E9)<=0.00005,"Pass","Check") -> Pass
B10: Anchor | C10: =Inputs!$C$43 -> 0.082073834 | D10: 0.08207383 | E10: =C10-D10 -> 3.7486065e-09 | F10: =IF(ABS(E10)<=0.00005,"Pass","Check") -> Pass
B11: Implied growth, base case | C11: =Solver!$W$7 -> 0.049811827 | D11: 0.04981183 | E11: =C11-D11 -> -3.4654489e-09 | F11: =IF(ABS(E11)<=0.00005,"Pass","Check") -> Pass
B12: Implied growth, WACC one point higher | C12: =Sensitivity!$E$14 -> 0.076202065 | D12: 0.07620215 | E12: =C12-D12 -> -8.5247421e-08 | F12: =IF(ABS(E12)<=0.0002,"Pass","Check") -> Pass
B13: Value per share at the anchor ($) | C13: =DCF!$C$41 -> 252.16673 | D13: 252.16673 | E13: =C13-D13 -> 1.8595756e-09 | F13: =IF(ABS(E13)<=0.0252166732741859,"Pass","Check") -> Pass
B14: Panel A value minus price ($) | C14: =DCF!$C$21-DCF!$C$22 -> -1.690637e-09 | D14: 0 | E14: =C14-D14 -> -1.690637e-09 | F14: =IF(ABS(E14)<=0.01,"Pass","Check") -> Pass | G14: Panel B on the DCF tab uses your view; with the yellow cell at the anchor it matches the pipeline.
B16: Overall | C16: =IF(COUNTIF(F6:F14,"Pass")=9,"All checks pass","Review") -> All checks pass
