Workbook

Sheet Cover
B2: Priced In: Intercontinental Exchange (ICE)
B3: Reverse DCF, model v1.0. Inputs as of the Oct 13, 2026 close; model locked Oct 14, 2026 (commit 0735af0).
B4: Exchanges | US | reports in USD
B6: The question
B7: What revenue growth over the next five years does today's price imply, and is that more or less than the company has delivered and analysts expect?
B9: Answer
B10: Price at the lock ($) | C10: =Inputs!$C$6 -> 155.80969
B11: Implied 5-year revenue growth | C11: =Solver!$W$7 -> 0.022919701
B12: Anchor (history and analysts) | C12: =Inputs!$C$43 -> 0.0812
B13: Gap (implied - anchor) | C13: =C11-C12 -> -0.058280299
B14: Verdict | C14: =IF(C13>=Inputs!$C$44,"Expectations too high",IF(C13<=-Inputs!$C$44,"Expectations too low","About right")) -> Expectations too low
B15: WACC | C15: =WACC!$C$37 -> 0.077017203
B16: Terminal growth | C16: =Inputs!$C$37 -> 0.0283
B17: Unlevered free-cash-flow margin | C17: =Inputs!$C$23 -> 0.49526515
B18: Your view of growth (Inputs, yellow) | C18: =Inputs!$C$45 -> 0.0812
B19: Value per share at your view ($) | C19: =DCF!$C$41 -> 233.35771
B20: Upside or downside at your view | C20: =DCF!$C$43 -> 0.49770987
B22: Fit flag: History not comparable
B23: Black Knight joined in September 2023, so past growth includes an acquisition.
B25: How to use this file
B26: 1. Change any blue cell on Inputs, History or WACC; everything recalculates, including the solver.
B27: 2. The Solver tab finds implied growth by bisection with formulas, so you never need Goal Seek. 40 steps narrow a 150-point range to well under 0.0001%.
B28: 3. Type your own growth view in the yellow cell on Inputs; DCF panel B and this page show what the stock is worth if you're right.
B29: 4. Check confirms this workbook matches the Python pipeline that runs the site.
B31: Colour key
B32: Typed input with a source | C32: 1234
B33: Formula | C33: =C32*2 -> 2468
B34: Link to another tab | C34: =Inputs!$C$12 -> 10560
B35: Your view (edit this one) | C35: =Inputs!$C$45 -> 0.0812
B37: Live site
B38: https://claude.ai/artifact/DS3n4CgaKxaSLzkXDsBKuK
B40: Built by Rohan Jayapalan. Not investment advice.

Sheet Inputs
B2: Intercontinental Exchange (ICE): inputs
B3: Blue cells are typed inputs with a source. Black cells are formulas. Change a blue cell and every tab recalculates.
B5: Market and price
B6: Price per share at the lock ($) | C6: 155.80969 | E6: Market cap divided by shares from Stock Analysis at the Oct 13, 2026 close.
B7: Diluted shares outstanding (mm) | C7: 561.39 | E7: Stock Analysis statistics page, Oct 13, 2026.
B8: Market value of equity ($mm) | C8: =C6*C7 -> 87470 | E8: Price x shares.
B10: Trailing 12 months
B11: Revenue, reported ($mm) | C11: 10560 | E11: Stock Analysis income statement, trailing 12 months.
B12: Revenue used in the model ($mm) | C12: =C11 -> 10560 | E12: Same as reported.
B13: Free cash flow, reported (cash from operations - capex) ($mm) | C13: 5080 | E13: Stock Analysis cash flow statement, trailing 12 months.
B14: Free cash flow before adjustments ($mm) | C14: =C13 -> 5080 | E14: Same as reported.
B15: Less: adjustments ($mm) | C15: 0 | E15: None for this company.
B16: Free cash flow used ($mm) | C16: =C14-C15 -> 5080
B17: Operating income ($mm) | C17: 5530 | E17: Stock Analysis, trailing 12 months.
B18: Pretax income ($mm) | C18: 5330 | E18: Stock Analysis, trailing 12 months.
B19: Interest proxy: operating income - pretax, floored at zero ($mm) | C19: =MAX(0,C17-C18) -> 200 | E19: Net interest and other non-operating costs. Adding it back (after tax) turns levered FCF into unlevered FCF.
B20: Tax rate | C20: 0.25 | E20: Statutory blend: 25% US (21% federal plus state), 26.5% Canada (federal plus Ontario).
B21: After-tax interest added back ($mm) | C21: =C19*(1-C20) -> 150
B22: Unlevered free cash flow ($mm) | C22: =C16+C21 -> 5230
B23: Unlevered free-cash-flow margin | C23: =C22/C12 -> 0.49526515 | E23: Held flat for all 10 years in the model.
B24: EBITDA ($mm) | C24: 6710 | E24: Stock Analysis, trailing 12 months.
B26: Balance sheet
B27: Total debt ($mm) | C27: 20530 | E27: Stock Analysis balance sheet, latest quarter.
B28: Cash and equivalents ($mm) | C28: 1070 | E28: Stock Analysis balance sheet, latest quarter.
B29: Net debt ($mm) | C29: =C27-C28 -> 19460
B31: Rates
B32: 10-year US Treasury yield | C32: 0.0521 | E32: US Treasury daily par yield curve, Oct 13, 2026.
B33: 10-year TIPS real yield | C33: 0.0288 | E33: US Treasury daily real yield curve, Oct 13, 2026.
B34: Breakeven inflation | C34: =C32-C33 -> 0.0233 | E34: Nominal minus real: the market's inflation expectation.
B35: Risk-free rate used | C35: =C32 -> 0.0521
B36: Real growth added to inflation | C36: 0.005 | E36: Half a point of long-run real growth.
B37: Terminal growth | C37: =MIN(C34+C36,C35) -> 0.0283 | E37: Capped at the risk-free rate.
B38: Equity risk premium | C38: 0.0423 | E38: Damodaran implied equity risk premium, start of 2026.
B40: Growth anchor and verdict
B41: Past revenue growth (CAGR) | C41: n/a | E41: Not used: past growth isn't comparable (see Cover).
B42: Analysts' revenue growth forecast | C42: 0.0812 | E42: Analysts' 3-year revenue CAGR forecast (stockanalysis)
B43: Anchor (average of the two) | C43: =AVERAGE(C41:C42) -> 0.0812 | E43: AVERAGE skips the n/a text when history isn't used.
B44: Verdict band (+/-) | C44: 0.03 | E44: Set before any backtest and never changed.
B45: Your view of 5-year revenue growth | C45: 0.0812 | E45: Type your own view. It starts at the anchor. DCF panel B and the Cover show what the stock is worth at your view.
B46: Years at the solved growth rate | C46: 5 | E46: Model v1.0: 5 years at the growth rate, then a straight-line fade.
B47: Years of fade to terminal growth | C47: 5 | E47: Years 1 to 10 are on the Solver and DCF tabs; years past 10 grow at the terminal rate.

Sheet History
B2: Intercontinental Exchange (ICE): revenue history
B3: Revenue from Stock Analysis income statements; the window is chosen so acquisitions and disposals don't count as growth.
B5: Fiscal year | C5: FY2021 | D5: FY2022 | E5: FY2023 | F5: FY2024 | G5: FY2025 | H5: TTM Jun-26
B6: Revenue ($mm) | C6: 7146 | D6: 7292 | E6: 7988 | F6: 9279 | G6: 9931 | H6: 10558
B7: Growth on the prior year | D7: =D6/C6-1 -> 0.02043101 | E7: =E6/D6-1 -> 0.095447065 | F7: =F6/E6-1 -> 0.16161743 | G7: =G6/F6-1 -> 0.070266192
B8: Source note: net revenue
B10: History window
B11: Not used for this company: Black Knight joined in September 2023, so past growth includes an acquisition.
B15: Free-cash-flow margin history
B16: Fiscal year | C16: 2021 | D16: 2022 | E16: 2023 | F16: 2024 | G16: 2025
B17: (CFO - capex) / revenue | C17: 0.3211 | D17: 0.3455 | E17: 0.3385 | F17: 0.3574 | G17: 0.3393 | I17: SEC XBRL filings (NetCashProvidedByOperatingActivities, PaymentsToAcquirePropertyPlantAndEquipment, revenue tags).
B18: Plus today's interest add-back | C18: =C17+(Inputs!$C$23-Inputs!$C$16/Inputs!$C$12) -> 0.33530455 | D18: =D17+(Inputs!$C$23-Inputs!$C$16/Inputs!$C$12) -> 0.35970455 | E18: =E17+(Inputs!$C$23-Inputs!$C$16/Inputs!$C$12) -> 0.35270455 | F18: =F17+(Inputs!$C$23-Inputs!$C$16/Inputs!$C$12) -> 0.37160455 | G18: =G17+(Inputs!$C$23-Inputs!$C$16/Inputs!$C$12) -> 0.35350455
B19: Range (the margin slider's shaded zone) | C19: =MIN(C18:G18) -> 0.33530455 | D19: =MAX(C18:G18) -> 0.37160455

Sheet WACC
B2: Intercontinental Exchange (ICE): cost of capital
B3: Bottom-up beta: the median unlevered beta of the company's group, relevered for this company's debt.
B5: Peer | C5: Raw beta | D5: Debt ($mm) | E5: Equity ($mm) | F5: Tax rate | G5: Unlevered beta
B6: Intercontinental Exchange (ICE) | C6: 0.93718463 | D6: 20530 | E6: 87470 | F6: 0.25 | G6: =C6/(1+(1-F6)*D6/E6) -> 0.79690417 | H6: Raw betas: 60 monthly returns to Sep 2026 against the S&P 500 (S&P/TSX for TMX); Cboe uses Stock Analysis's 5-year beta. Debt and equity from Stock Analysis, Oct 13, 2026.
B7: CME Group (CME) | C7: 0.23986632 | D7: 3870 | E7: 99970 | F7: 0.25 | G7: =C7/(1+(1-F7)*D7/E7) -> 0.2330986
B8: Nasdaq (NDAQ) | C8: 0.99189493 | D8: 9320 | E8: 52250 | F8: 0.25 | G8: =C8/(1+(1-F8)*D8/E8) -> 0.87485669
B9: Cboe Global Markets (CBOE) | C9: 0.41 | D9: 1580 | E9: 30520 | F9: 0.25 | G9: =C9/(1+(1-F9)*D9/E9) -> 0.39467592
B10: TMX Group (X) | C10: 0.071228248 | D10: 2070 | E10: 15010 | F10: 0.265 | G10: =C10/(1+(1-F10)*D10/E10) -> 0.064672851
B11: Tradeweb (TW) | C11: 0.61179985 | D11: 150.34 | E11: 25740 | F11: 0.25 | G11: =C11/(1+(1-F11)*D11/E11) -> 0.60913153
B12: MarketAxess (MKTX) | C12: 0.79839643 | D12: 178.91 | E12: 5790 | F12: 0.25 | G12: =C12/(1+(1-F12)*D12/E12) -> 0.78031278
B14: Group median unlevered beta | C14: =MEDIAN(G6:G12) -> 0.60913153
B15: Debt ($mm) | C15: =Inputs!$C$27 -> 20530
B16: Market value of equity ($mm) | C16: =Inputs!$C$8 -> 87470
B17: Tax rate | C17: =Inputs!$C$20 -> 0.25
B18: Relevered beta | C18: =WACC!$C$14*(1+(1-WACC!$C$17)*WACC!$C$15/WACC!$C$16) -> 0.71635804 | H18: Hamada: unlevered beta x (1 + (1 - tax) x debt / equity).
B19: Risk-free rate | C19: =Inputs!$C$35 -> 0.0521
B20: Equity risk premium | C20: =Inputs!$C$38 -> 0.0423
B21: Cost of equity | C21: =WACC!$C$19+WACC!$C$18*WACC!$C$20 -> 0.082401945 | H21: CAPM: risk-free + beta x premium.
B23: Debt-to-EBITDA spread table
B24: Debt / EBITDA below | C24: Spread
B25: 1 | C25: 0.01 | H25: Synthetic spread over the risk-free rate by leverage, a simplified version of Damodaran's ratings table; the last row covers anything at 4x or above.
B26: 2 | C26: 0.0125
B27: 3 | C27: 0.016
B28: 4 | C28: 0.02
B29: 99 | C29: 0.0275
B31: Debt / EBITDA | C31: =Inputs!$C$27/Inputs!$C$24 -> 3.0596125
B32: Credit spread | C32: =INDEX(C25:C29,COUNTIF(B25:B29,"<="&WACC!$C$31)+1) -> 0.02 | H32: First row whose limit is above this company's leverage.
B33: Pre-tax cost of debt | C33: =WACC!$C$19+WACC!$C$32 -> 0.0721
B34: After-tax cost of debt | C34: =WACC!$C$33*(1-WACC!$C$17) -> 0.054075
B35: Weight of debt | C35: =WACC!$C$15/(WACC!$C$15+WACC!$C$16) -> 0.19009259 | H35: Market-value weights.
B36: Weight of equity | C36: =1-WACC!$C$35 -> 0.80990741
B37: WACC | C37: =WACC!$C$36*WACC!$C$21+WACC!$C$35*WACC!$C$34 -> 0.077017203

Sheet Solver
A1: Solver: bisection for the growth rate that makes the model equal the price (replaces Goal Seek)
B2: Revenue | C2: =Inputs!$C$12 -> 10560 | D2: Margin | E2: =Inputs!$C$23 -> 0.49526515 | F2: Debt | G2: =Inputs!$C$27 -> 20530 | H2: Cash | I2: =Inputs!$C$28 -> 1070 | J2: Shares | K2: =Inputs!$C$7 -> 561.39 | L2: Price | M2: =Inputs!$C$6 -> 155.80969 | N2: Years | O2: =Inputs!$C$46 -> 5 | P2: Fade | Q2: =Inputs!$C$47 -> 5
D3: Year | E3: 1 | F3: 2 | G3: 3 | H3: 4 | I3: 5 | J3: 6 | K3: 7 | L3: 8 | M3: 9 | N3: 10
A4: Each row tries the midpoint of the current range. If the value per share is above the price, the answer is lower, so the top of the range moves down; otherwise the bottom moves up.
A6: Base case: model WACC and terminal growth (40 steps) | E6: WACC | F6: =WACC!$C$37 -> 0.077017203 | G6: Terminal growth | I6: =Inputs!$C$37 -> 0.0283 | W6: Implied growth
A7: Step | B7: Low | C7: High | D7: Mid | E7: Rev Y1 | F7: Rev Y2 | G7: Rev Y3 | H7: Rev Y4 | I7: Rev Y5 | J7: Rev Y6 | K7: Rev Y7 | L7: Rev Y8 | M7: Rev Y9 | N7: Rev Y10 | O7: PV of FCF | P7: PV of TV | Q7: EV | R7: Equity | S7: Per share | T7: Value - price | W7: =$D$47 -> 0.022919701
A8: 1 | B8: -0.5 | C8: 1 | D8: =(B8+C8)/2 -> 0.25 | E8: =$C$2*(1+IF(E$3<=$O$2,$D8,$D8-($D8-$I$6)*MIN(E$3-$O$2,$Q$2)/$Q$2)) -> 13200 | F8: =E8*(1+IF(F$3<=$O$2,$D8,$D8-($D8-$I$6)*MIN(F$3-$O$2,$Q$2)/$Q$2)) -> 16500 | G8: =F8*(1+IF(G$3<=$O$2,$D8,$D8-($D8-$I$6)*MIN(G$3-$O$2,$Q$2)/$Q$2)) -> 20625 | H8: =G8*(1+IF(H$3<=$O$2,$D8,$D8-($D8-$I$6)*MIN(H$3-$O$2,$Q$2)/$Q$2)) -> 25781.25 | I8: =H8*(1+IF(I$3<=$O$2,$D8,$D8-($D8-$I$6)*MIN(I$3-$O$2,$Q$2)/$Q$2)) -> 32226.562 | J8: =I8*(1+IF(J$3<=$O$2,$D8,$D8-($D8-$I$6)*MIN(J$3-$O$2,$Q$2)/$Q$2)) -> 38854.277 | K8: =J8*(1+IF(K$3<=$O$2,$D8,$D8-($D8-$I$6)*MIN(K$3-$O$2,$Q$2)/$Q$2)) -> 45122.249 | L8: =K8*(1+IF(L$3<=$O$2,$D8,$D8-($D8-$I$6)*MIN(L$3-$O$2,$Q$2)/$Q$2)) -> 50400.65 | M8: =L8*(1+IF(M$3<=$O$2,$D8,$D8-($D8-$I$6)*MIN(M$3-$O$2,$Q$2)/$Q$2)) -> 54061.753 | N8: =M8*(1+IF(N$3<=$O$2,$D8,$D8-($D8-$I$6)*MIN(N$3-$O$2,$Q$2)/$Q$2)) -> 55591.701 | O8: =SUMPRODUCT(E8:N8,1/(1+$F$6)^$E$3:$N$3)*$E$2 -> 108048.66 | P8: =N8*$E$2*(1+$I$6)/($F$6-$I$6)/(1+$F$6)^$N$3 -> 276731.65 | Q8: =O8+P8 -> 384780.31 | R8: =Q8-$G$2+$I$2 -> 365320.31 | S8: =R8/$K$2 -> 650.74246 | T8: =S8-$M$2 -> 494.93277 | W8: =IF(OR(ABS(W7+0.5)<0.000001,ABS(W7-1)<0.000001),"Out of range","Solved") -> Solved
A9: 2 | B9: =IF(T8>0,B8,D8) -> -0.5 | C9: =IF(T8>0,D8,C8) -> 0.25 | D9: =(B9+C9)/2 -> -0.125 | E9: =$C$2*(1+IF(E$3<=$O$2,$D9,$D9-($D9-$I$6)*MIN(E$3-$O$2,$Q$2)/$Q$2)) -> 9240 | F9: =E9*(1+IF(F$3<=$O$2,$D9,$D9-($D9-$I$6)*MIN(F$3-$O$2,$Q$2)/$Q$2)) -> 8085 | G9: =F9*(1+IF(G$3<=$O$2,$D9,$D9-($D9-$I$6)*MIN(G$3-$O$2,$Q$2)/$Q$2)) -> 7074.375 | H9: =G9*(1+IF(H$3<=$O$2,$D9,$D9-($D9-$I$6)*MIN(H$3-$O$2,$Q$2)/$Q$2)) -> 6190.0781 | I9: =H9*(1+IF(I$3<=$O$2,$D9,$D9-($D9-$I$6)*MIN(I$3-$O$2,$Q$2)/$Q$2)) -> 5416.3184 | J9: =I9*(1+IF(J$3<=$O$2,$D9,$D9-($D9-$I$6)*MIN(J$3-$O$2,$Q$2)/$Q$2)) -> 4905.3429 | K9: =J9*(1+IF(K$3<=$O$2,$D9,$D9-($D9-$I$6)*MIN(K$3-$O$2,$Q$2)/$Q$2)) -> 4592.9707 | L9: =K9*(1+IF(L$3<=$O$2,$D9,$D9-($D9-$I$6)*MIN(L$3-$O$2,$Q$2)/$Q$2)) -> 4441.3108 | M9: =L9*(1+IF(M$3<=$O$2,$D9,$D9-($D9-$I$6)*MIN(M$3-$O$2,$Q$2)/$Q$2)) -> 4430.8293 | N9: =M9*(1+IF(N$3<=$O$2,$D9,$D9-($D9-$I$6)*MIN(N$3-$O$2,$Q$2)/$Q$2)) -> 4556.2217 | O9: =SUMPRODUCT(E9:N9,1/(1+$F$6)^$E$3:$N$3)*$E$2 -> 20959.844 | P9: =N9*$E$2*(1+$I$6)/($F$6-$I$6)/(1+$F$6)^$N$3 -> 22680.557 | Q9: =O9+P9 -> 43640.401 | R9: =Q9-$G$2+$I$2 -> 24180.401 | S9: =R9/$K$2 -> 43.072376 | T9: =S9-$M$2 -> -112.73731
A10: 3 | B10: =IF(T9>0,B9,D9) -> -0.125 | C10: =IF(T9>0,D9,C9) -> 0.25 | D10: =(B10+C10)/2 -> 0.0625 | E10: =$C$2*(1+IF(E$3<=$O$2,$D10,$D10-($D10-$I$6)*MIN(E$3-$O$2,$Q$2)/$Q$2)) -> 11220 | F10: =E10*(1+IF(F$3<=$O$2,$D10,$D10-($D10-$I$6)*MIN(F$3-$O$2,$Q$2)/$Q$2)) -> 11921.25 | G10: =F10*(1+IF(G$3<=$O$2,$D10,$D10-($D10-$I$6)*MIN(G$3-$O$2,$Q$2)/$Q$2)) -> 12666.328 | H10: =G10*(1+IF(H$3<=$O$2,$D10,$D10-($D10-$I$6)*MIN(H$3-$O$2,$Q$2)/$Q$2)) -> 13457.974 | I10: =H10*(1+IF(I$3<=$O$2,$D10,$D10-($D10-$I$6)*MIN(I$3-$O$2,$Q$2)/$Q$2)) -> 14299.097 | J10: =I10*(1+IF(J$3<=$O$2,$D10,$D10-($D10-$I$6)*MIN(J$3-$O$2,$Q$2)/$Q$2)) -> 15094.985 | K10: =J10*(1+IF(K$3<=$O$2,$D10,$D10-($D10-$I$6)*MIN(K$3-$O$2,$Q$2)/$Q$2)) -> 15831.922 | L10: =K10*(1+IF(L$3<=$O$2,$D10,$D10-($D10-$I$6)*MIN(L$3-$O$2,$Q$2)/$Q$2)) -> 16496.546 | M10: =L10*(1+IF(M$3<=$O$2,$D10,$D10-($D10-$I$6)*MIN(M$3-$O$2,$Q$2)/$Q$2)) -> 17076.235 | N10: =M10*(1+IF(N$3<=$O$2,$D10,$D10-($D10-$I$6)*MIN(N$3-$O$2,$Q$2)/$Q$2)) -> 17559.492 | O10: =SUMPRODUCT(E10:N10,1/(1+$F$6)^$E$3:$N$3)*$E$2 -> 47557.33 | P10: =N10*$E$2*(1+$I$6)/($F$6-$I$6)/(1+$F$6)^$N$3 -> 87409.938 | Q10: =O10+P10 -> 134967.27 | R10: =Q10-$G$2+$I$2 -> 115507.27 | S10: =R10/$K$2 -> 205.75227 | T10: =S10-$M$2 -> 49.942584
A11: 4 | B11: =IF(T10>0,B10,D10) -> -0.125 | C11: =IF(T10>0,D10,C10) -> 0.0625 | D11: =(B11+C11)/2 -> -0.03125 | E11: =$C$2*(1+IF(E$3<=$O$2,$D11,$D11-($D11-$I$6)*MIN(E$3-$O$2,$Q$2)/$Q$2)) -> 10230 | F11: =E11*(1+IF(F$3<=$O$2,$D11,$D11-($D11-$I$6)*MIN(F$3-$O$2,$Q$2)/$Q$2)) -> 9910.3125 | G11: =F11*(1+IF(G$3<=$O$2,$D11,$D11-($D11-$I$6)*MIN(G$3-$O$2,$Q$2)/$Q$2)) -> 9600.6152 | H11: =G11*(1+IF(H$3<=$O$2,$D11,$D11-($D11-$I$6)*MIN(H$3-$O$2,$Q$2)/$Q$2)) -> 9300.596 | I11: =H11*(1+IF(I$3<=$O$2,$D11,$D11-($D11-$I$6)*MIN(I$3-$O$2,$Q$2)/$Q$2)) -> 9009.9524 | J11: =I11*(1+IF(J$3<=$O$2,$D11,$D11-($D11-$I$6)*MIN(J$3-$O$2,$Q$2)/$Q$2)) -> 8835.6999 | K11: =J11*(1+IF(K$3<=$O$2,$D11,$D11-($D11-$I$6)*MIN(K$3-$O$2,$Q$2)/$Q$2)) -> 8770.0507 | L11: =K11*(1+IF(L$3<=$O$2,$D11,$D11-($D11-$I$6)*MIN(L$3-$O$2,$Q$2)/$Q$2)) -> 8809.3405 | M11: =L11*(1+IF(M$3<=$O$2,$D11,$D11-($D11-$I$6)*MIN(M$3-$O$2,$Q$2)/$Q$2)) -> 8953.7256 | N11: =M11*(1+IF(N$3<=$O$2,$D11,$D11-($D11-$I$6)*MIN(N$3-$O$2,$Q$2)/$Q$2)) -> 9207.116 | O11: =SUMPRODUCT(E11:N11,1/(1+$F$6)^$E$3:$N$3)*$E$2 -> 31487.518 | P11: =N11*$E$2*(1+$I$6)/($F$6-$I$6)/(1+$F$6)^$N$3 -> 45832.387 | Q11: =O11+P11 -> 77319.905 | R11: =Q11-$G$2+$I$2 -> 57859.905 | S11: =R11/$K$2 -> 103.06544 | T11: =S11-$M$2 -> -52.744251
A12: 5 | B12: =IF(T11>0,B11,D11) -> -0.03125 | C12: =IF(T11>0,D11,C11) -> 0.0625 | D12: =(B12+C12)/2 -> 0.015625 | E12: =$C$2*(1+IF(E$3<=$O$2,$D12,$D12-($D12-$I$6)*MIN(E$3-$O$2,$Q$2)/$Q$2)) -> 10725 | F12: =E12*(1+IF(F$3<=$O$2,$D12,$D12-($D12-$I$6)*MIN(F$3-$O$2,$Q$2)/$Q$2)) -> 10892.578 | G12: =F12*(1+IF(G$3<=$O$2,$D12,$D12-($D12-$I$6)*MIN(G$3-$O$2,$Q$2)/$Q$2)) -> 11062.775 | H12: =G12*(1+IF(H$3<=$O$2,$D12,$D12-($D12-$I$6)*MIN(H$3-$O$2,$Q$2)/$Q$2)) -> 11235.631 | I12: =H12*(1+IF(I$3<=$O$2,$D12,$D12-($D12-$I$6)*MIN(I$3-$O$2,$Q$2)/$Q$2)) -> 11411.187 | J12: =I12*(1+IF(J$3<=$O$2,$D12,$D12-($D12-$I$6)*MIN(J$3-$O$2,$Q$2)/$Q$2)) -> 11618.414 | K12: =J12*(1+IF(K$3<=$O$2,$D12,$D12-($D12-$I$6)*MIN(K$3-$O$2,$Q$2)/$Q$2)) -> 11858.857 | L12: =K12*(1+IF(L$3<=$O$2,$D12,$D12-($D12-$I$6)*MIN(L$3-$O$2,$Q$2)/$Q$2)) -> 12134.339 | M12: =L12*(1+IF(M$3<=$O$2,$D12,$D12-($D12-$I$6)*MIN(M$3-$O$2,$Q$2)/$Q$2)) -> 12446.98 | N12: =M12*(1+IF(N$3<=$O$2,$D12,$D12-($D12-$I$6)*MIN(N$3-$O$2,$Q$2)/$Q$2)) -> 12799.23 | O12: =SUMPRODUCT(E12:N12,1/(1+$F$6)^$E$3:$N$3)*$E$2 -> 38684.207 | P12: =N12*$E$2*(1+$I$6)/($F$6-$I$6)/(1+$F$6)^$N$3 -> 63713.68 | Q12: =O12+P12 -> 102397.89 | R12: =Q12-$G$2+$I$2 -> 82937.887 | S12: =R12/$K$2 -> 147.73667 | T12: =S12-$M$2 -> -8.0730203
A13: 6 | B13: =IF(T12>0,B12,D12) -> 0.015625 | C13: =IF(T12>0,D12,C12) -> 0.0625 | D13: =(B13+C13)/2 -> 0.0390625 | E13: =$C$2*(1+IF(E$3<=$O$2,$D13,$D13-($D13-$I$6)*MIN(E$3-$O$2,$Q$2)/$Q$2)) -> 10972.5 | F13: =E13*(1+IF(F$3<=$O$2,$D13,$D13-($D13-$I$6)*MIN(F$3-$O$2,$Q$2)/$Q$2)) -> 11401.113 | G13: =F13*(1+IF(G$3<=$O$2,$D13,$D13-($D13-$I$6)*MIN(G$3-$O$2,$Q$2)/$Q$2)) -> 11846.469 | H13: =G13*(1+IF(H$3<=$O$2,$D13,$D13-($D13-$I$6)*MIN(H$3-$O$2,$Q$2)/$Q$2)) -> 12309.222 | I13: =H13*(1+IF(I$3<=$O$2,$D13,$D13-($D13-$I$6)*MIN(I$3-$O$2,$Q$2)/$Q$2)) -> 12790.051 | J13: =I13*(1+IF(J$3<=$O$2,$D13,$D13-($D13-$I$6)*MIN(J$3-$O$2,$Q$2)/$Q$2)) -> 13262.132 | K13: =J13*(1+IF(K$3<=$O$2,$D13,$D13-($D13-$I$6)*MIN(K$3-$O$2,$Q$2)/$Q$2)) -> 13723.09 | L13: =K13*(1+IF(L$3<=$O$2,$D13,$D13-($D13-$I$6)*MIN(L$3-$O$2,$Q$2)/$Q$2)) -> 14170.532 | M13: =L13*(1+IF(M$3<=$O$2,$D13,$D13-($D13-$I$6)*MIN(M$3-$O$2,$Q$2)/$Q$2)) -> 14602.06 | N13: =M13*(1+IF(N$3<=$O$2,$D13,$D13-($D13-$I$6)*MIN(N$3-$O$2,$Q$2)/$Q$2)) -> 15015.298 | O13: =SUMPRODUCT(E13:N13,1/(1+$F$6)^$E$3:$N$3)*$E$2 -> 42890.144 | P13: =N13*$E$2*(1+$I$6)/($F$6-$I$6)/(1+$F$6)^$N$3 -> 74745.116 | Q13: =O13+P13 -> 117635.26 | R13: =Q13-$G$2+$I$2 -> 98175.26 | S13: =R13/$K$2 -> 174.87889 | T13: =S13-$M$2 -> 19.069203
A14: 7 | B14: =IF(T13>0,B13,D13) -> 0.015625 | C14: =IF(T13>0,D13,C13) -> 0.0390625 | D14: =(B14+C14)/2 -> 0.02734375 | E14: =$C$2*(1+IF(E$3<=$O$2,$D14,$D14-($D14-$I$6)*MIN(E$3-$O$2,$Q$2)/$Q$2)) -> 10848.75 | F14: =E14*(1+IF(F$3<=$O$2,$D14,$D14-($D14-$I$6)*MIN(F$3-$O$2,$Q$2)/$Q$2)) -> 11145.396 | G14: =F14*(1+IF(G$3<=$O$2,$D14,$D14-($D14-$I$6)*MIN(G$3-$O$2,$Q$2)/$Q$2)) -> 11450.152 | H14: =G14*(1+IF(H$3<=$O$2,$D14,$D14-($D14-$I$6)*MIN(H$3-$O$2,$Q$2)/$Q$2)) -> 11763.243 | I14: =H14*(1+IF(I$3<=$O$2,$D14,$D14-($D14-$I$6)*MIN(I$3-$O$2,$Q$2)/$Q$2)) -> 12084.894 | J14: =I14*(1+IF(J$3<=$O$2,$D14,$D14-($D14-$I$6)*MIN(J$3-$O$2,$Q$2)/$Q$2)) -> 12417.651 | K14: =J14*(1+IF(K$3<=$O$2,$D14,$D14-($D14-$I$6)*MIN(K$3-$O$2,$Q$2)/$Q$2)) -> 12761.946 | L14: =K14*(1+IF(L$3<=$O$2,$D14,$D14-($D14-$I$6)*MIN(L$3-$O$2,$Q$2)/$Q$2)) -> 13118.228 | M14: =L14*(1+IF(M$3<=$O$2,$D14,$D14-($D14-$I$6)*MIN(M$3-$O$2,$Q$2)/$Q$2)) -> 13486.965 | N14: =M14*(1+IF(N$3<=$O$2,$D14,$D14-($D14-$I$6)*MIN(N$3-$O$2,$Q$2)/$Q$2)) -> 13868.646 | O14: =SUMPRODUCT(E14:N14,1/(1+$F$6)^$E$3:$N$3)*$E$2 -> 40732.294 | P14: =N14*$E$2*(1+$I$6)/($F$6-$I$6)/(1+$F$6)^$N$3 -> 69037.161 | Q14: =O14+P14 -> 109769.45 | R14: =Q14-$G$2+$I$2 -> 90309.455 | S14: =R14/$K$2 -> 160.86759 | T14: =S14-$M$2 -> 5.0579008
A15: 8 | B15: =IF(T14>0,B14,D14) -> 0.015625 | C15: =IF(T14>0,D14,C14) -> 0.02734375 | D15: =(B15+C15)/2 -> 0.021484375 | E15: =$C$2*(1+IF(E$3<=$O$2,$D15,$D15-($D15-$I$6)*MIN(E$3-$O$2,$Q$2)/$Q$2)) -> 10786.875 | F15: =E15*(1+IF(F$3<=$O$2,$D15,$D15-($D15-$I$6)*MIN(F$3-$O$2,$Q$2)/$Q$2)) -> 11018.624 | G15: =F15*(1+IF(G$3<=$O$2,$D15,$D15-($D15-$I$6)*MIN(G$3-$O$2,$Q$2)/$Q$2)) -> 11255.353 | H15: =G15*(1+IF(H$3<=$O$2,$D15,$D15-($D15-$I$6)*MIN(H$3-$O$2,$Q$2)/$Q$2)) -> 11497.167 | I15: =H15*(1+IF(I$3<=$O$2,$D15,$D15-($D15-$I$6)*MIN(I$3-$O$2,$Q$2)/$Q$2)) -> 11744.176 | J15: =I15*(1+IF(J$3<=$O$2,$D15,$D15-($D15-$I$6)*MIN(J$3-$O$2,$Q$2)/$Q$2)) -> 12012.501 | K15: =J15*(1+IF(K$3<=$O$2,$D15,$D15-($D15-$I$6)*MIN(K$3-$O$2,$Q$2)/$Q$2)) -> 12303.331 | L15: =K15*(1+IF(L$3<=$O$2,$D15,$D15-($D15-$I$6)*MIN(L$3-$O$2,$Q$2)/$Q$2)) -> 12617.974 | M15: =L15*(1+IF(M$3<=$O$2,$D15,$D15-($D15-$I$6)*MIN(M$3-$O$2,$Q$2)/$Q$2)) -> 12957.863 | N15: =M15*(1+IF(N$3<=$O$2,$D15,$D15-($D15-$I$6)*MIN(N$3-$O$2,$Q$2)/$Q$2)) -> 13324.57 | O15: =SUMPRODUCT(E15:N15,1/(1+$F$6)^$E$3:$N$3)*$E$2 -> 39694.865 | P15: =N15*$E$2*(1+$I$6)/($F$6-$I$6)/(1+$F$6)^$N$3 -> 66328.789 | Q15: =O15+P15 -> 106023.65 | R15: =Q15-$G$2+$I$2 -> 86563.653 | S15: =R15/$K$2 -> 154.19522 | T15: =S15-$M$2 -> -1.6144689
A16: 9 | B16: =IF(T15>0,B15,D15) -> 0.021484375 | C16: =IF(T15>0,D15,C15) -> 0.02734375 | D16: =(B16+C16)/2 -> 0.024414062 | E16: =$C$2*(1+IF(E$3<=$O$2,$D16,$D16-($D16-$I$6)*MIN(E$3-$O$2,$Q$2)/$Q$2)) -> 10817.812 | F16: =E16*(1+IF(F$3<=$O$2,$D16,$D16-($D16-$I$6)*MIN(F$3-$O$2,$Q$2)/$Q$2)) -> 11081.919 | G16: =F16*(1+IF(G$3<=$O$2,$D16,$D16-($D16-$I$6)*MIN(G$3-$O$2,$Q$2)/$Q$2)) -> 11352.474 | H16: =G16*(1+IF(H$3<=$O$2,$D16,$D16-($D16-$I$6)*MIN(H$3-$O$2,$Q$2)/$Q$2)) -> 11629.634 | I16: =H16*(1+IF(I$3<=$O$2,$D16,$D16-($D16-$I$6)*MIN(I$3-$O$2,$Q$2)/$Q$2)) -> 11913.561 | J16: =I16*(1+IF(J$3<=$O$2,$D16,$D16-($D16-$I$6)*MIN(J$3-$O$2,$Q$2)/$Q$2)) -> 12213.678 | K16: =J16*(1+IF(K$3<=$O$2,$D16,$D16-($D16-$I$6)*MIN(K$3-$O$2,$Q$2)/$Q$2)) -> 12530.848 | L16: =K16*(1+IF(L$3<=$O$2,$D16,$D16-($D16-$I$6)*MIN(L$3-$O$2,$Q$2)/$Q$2)) -> 12865.994 | M16: =L16*(1+IF(M$3<=$O$2,$D16,$D16-($D16-$I$6)*MIN(M$3-$O$2,$Q$2)/$Q$2)) -> 13220.102 | N16: =M16*(1+IF(N$3<=$O$2,$D16,$D16-($D16-$I$6)*MIN(N$3-$O$2,$Q$2)/$Q$2)) -> 13594.231 | O16: =SUMPRODUCT(E16:N16,1/(1+$F$6)^$E$3:$N$3)*$E$2 -> 40210.192 | P16: =N16*$E$2*(1+$I$6)/($F$6-$I$6)/(1+$F$6)^$N$3 -> 67671.141 | Q16: =O16+P16 -> 107881.33 | R16: =Q16-$G$2+$I$2 -> 88421.333 | S16: =R16/$K$2 -> 157.50429 | T16: =S16-$M$2 -> 1.6946023
A17: 10 | B17: =IF(T16>0,B16,D16) -> 0.021484375 | C17: =IF(T16>0,D16,C16) -> 0.024414062 | D17: =(B17+C17)/2 -> 0.022949219 | E17: =$C$2*(1+IF(E$3<=$O$2,$D17,$D17-($D17-$I$6)*MIN(E$3-$O$2,$Q$2)/$Q$2)) -> 10802.344 | F17: =E17*(1+IF(F$3<=$O$2,$D17,$D17-($D17-$I$6)*MIN(F$3-$O$2,$Q$2)/$Q$2)) -> 11050.249 | G17: =F17*(1+IF(G$3<=$O$2,$D17,$D17-($D17-$I$6)*MIN(G$3-$O$2,$Q$2)/$Q$2)) -> 11303.844 | H17: =G17*(1+IF(H$3<=$O$2,$D17,$D17-($D17-$I$6)*MIN(H$3-$O$2,$Q$2)/$Q$2)) -> 11563.258 | I17: =H17*(1+IF(I$3<=$O$2,$D17,$D17-($D17-$I$6)*MIN(I$3-$O$2,$Q$2)/$Q$2)) -> 11828.626 | J17: =I17*(1+IF(J$3<=$O$2,$D17,$D17-($D17-$I$6)*MIN(J$3-$O$2,$Q$2)/$Q$2)) -> 12112.742 | K17: =J17*(1+IF(K$3<=$O$2,$D17,$D17-($D17-$I$6)*MIN(K$3-$O$2,$Q$2)/$Q$2)) -> 12416.645 | L17: =K17*(1+IF(L$3<=$O$2,$D17,$D17-($D17-$I$6)*MIN(L$3-$O$2,$Q$2)/$Q$2)) -> 12741.461 | M17: =L17*(1+IF(M$3<=$O$2,$D17,$D17-($D17-$I$6)*MIN(M$3-$O$2,$Q$2)/$Q$2)) -> 13088.409 | N17: =M17*(1+IF(N$3<=$O$2,$D17,$D17-($D17-$I$6)*MIN(N$3-$O$2,$Q$2)/$Q$2)) -> 13458.811 | O17: =SUMPRODUCT(E17:N17,1/(1+$F$6)^$E$3:$N$3)*$E$2 -> 39951.686 | P17: =N17*$E$2*(1+$I$6)/($F$6-$I$6)/(1+$F$6)^$N$3 -> 66997.029 | Q17: =O17+P17 -> 106948.72 | R17: =Q17-$G$2+$I$2 -> 87488.715 | S17: =R17/$K$2 -> 155.84302 | T17: =S17-$M$2 -> 0.033336951
A18: 11 | B18: =IF(T17>0,B17,D17) -> 0.021484375 | C18: =IF(T17>0,D17,C17) -> 0.022949219 | D18: =(B18+C18)/2 -> 0.022216797 | E18: =$C$2*(1+IF(E$3<=$O$2,$D18,$D18-($D18-$I$6)*MIN(E$3-$O$2,$Q$2)/$Q$2)) -> 10794.609 | F18: =E18*(1+IF(F$3<=$O$2,$D18,$D18-($D18-$I$6)*MIN(F$3-$O$2,$Q$2)/$Q$2)) -> 11034.431 | G18: =F18*(1+IF(G$3<=$O$2,$D18,$D18-($D18-$I$6)*MIN(G$3-$O$2,$Q$2)/$Q$2)) -> 11279.581 | H18: =G18*(1+IF(H$3<=$O$2,$D18,$D18-($D18-$I$6)*MIN(H$3-$O$2,$Q$2)/$Q$2)) -> 11530.177 | I18: =H18*(1+IF(I$3<=$O$2,$D18,$D18-($D18-$I$6)*MIN(I$3-$O$2,$Q$2)/$Q$2)) -> 11786.34 | J18: =I18*(1+IF(J$3<=$O$2,$D18,$D18-($D18-$I$6)*MIN(J$3-$O$2,$Q$2)/$Q$2)) -> 12062.535 | K18: =J18*(1+IF(K$3<=$O$2,$D18,$D18-($D18-$I$6)*MIN(K$3-$O$2,$Q$2)/$Q$2)) -> 12359.877 | L18: =K18*(1+IF(L$3<=$O$2,$D18,$D18-($D18-$I$6)*MIN(L$3-$O$2,$Q$2)/$Q$2)) -> 12679.587 | M18: =L18*(1+IF(M$3<=$O$2,$D18,$D18-($D18-$I$6)*MIN(M$3-$O$2,$Q$2)/$Q$2)) -> 13022.993 | N18: =M18*(1+IF(N$3<=$O$2,$D18,$D18-($D18-$I$6)*MIN(N$3-$O$2,$Q$2)/$Q$2)) -> 13391.543 | O18: =SUMPRODUCT(E18:N18,1/(1+$F$6)^$E$3:$N$3)*$E$2 -> 39823.066 | P18: =N18*$E$2*(1+$I$6)/($F$6-$I$6)/(1+$F$6)^$N$3 -> 66662.177 | Q18: =O18+P18 -> 106485.24 | R18: =Q18-$G$2+$I$2 -> 87025.243 | S18: =R18/$K$2 -> 155.01744 | T18: =S18-$M$2 -> -0.79224237
A19: 12 | B19: =IF(T18>0,B18,D18) -> 0.022216797 | C19: =IF(T18>0,D18,C18) -> 0.022949219 | D19: =(B19+C19)/2 -> 0.022583008 | E19: =$C$2*(1+IF(E$3<=$O$2,$D19,$D19-($D19-$I$6)*MIN(E$3-$O$2,$Q$2)/$Q$2)) -> 10798.477 | F19: =E19*(1+IF(F$3<=$O$2,$D19,$D19-($D19-$I$6)*MIN(F$3-$O$2,$Q$2)/$Q$2)) -> 11042.339 | G19: =F19*(1+IF(G$3<=$O$2,$D19,$D19-($D19-$I$6)*MIN(G$3-$O$2,$Q$2)/$Q$2)) -> 11291.708 | H19: =G19*(1+IF(H$3<=$O$2,$D19,$D19-($D19-$I$6)*MIN(H$3-$O$2,$Q$2)/$Q$2)) -> 11546.709 | I19: =H19*(1+IF(I$3<=$O$2,$D19,$D19-($D19-$I$6)*MIN(I$3-$O$2,$Q$2)/$Q$2)) -> 11807.468 | J19: =I19*(1+IF(J$3<=$O$2,$D19,$D19-($D19-$I$6)*MIN(J$3-$O$2,$Q$2)/$Q$2)) -> 12087.617 | K19: =J19*(1+IF(K$3<=$O$2,$D19,$D19-($D19-$I$6)*MIN(K$3-$O$2,$Q$2)/$Q$2)) -> 12388.233 | L19: =K19*(1+IF(L$3<=$O$2,$D19,$D19-($D19-$I$6)*MIN(L$3-$O$2,$Q$2)/$Q$2)) -> 12710.491 | M19: =L19*(1+IF(M$3<=$O$2,$D19,$D19-($D19-$I$6)*MIN(M$3-$O$2,$Q$2)/$Q$2)) -> 13055.665 | N19: =M19*(1+IF(N$3<=$O$2,$D19,$D19-($D19-$I$6)*MIN(N$3-$O$2,$Q$2)/$Q$2)) -> 13425.14 | O19: =SUMPRODUCT(E19:N19,1/(1+$F$6)^$E$3:$N$3)*$E$2 -> 39887.324 | P19: =N19*$E$2*(1+$I$6)/($F$6-$I$6)/(1+$F$6)^$N$3 -> 66829.42 | Q19: =O19+P19 -> 106716.74 | R19: =Q19-$G$2+$I$2 -> 87256.743 | S19: =R19/$K$2 -> 155.42981 | T19: =S19-$M$2 -> -0.37987256
A20: 13 | B20: =IF(T19>0,B19,D19) -> 0.022583008 | C20: =IF(T19>0,D19,C19) -> 0.022949219 | D20: =(B20+C20)/2 -> 0.022766113 | E20: =$C$2*(1+IF(E$3<=$O$2,$D20,$D20-($D20-$I$6)*MIN(E$3-$O$2,$Q$2)/$Q$2)) -> 10800.41 | F20: =E20*(1+IF(F$3<=$O$2,$D20,$D20-($D20-$I$6)*MIN(F$3-$O$2,$Q$2)/$Q$2)) -> 11046.294 | G20: =F20*(1+IF(G$3<=$O$2,$D20,$D20-($D20-$I$6)*MIN(G$3-$O$2,$Q$2)/$Q$2)) -> 11297.775 | H20: =G20*(1+IF(H$3<=$O$2,$D20,$D20-($D20-$I$6)*MIN(H$3-$O$2,$Q$2)/$Q$2)) -> 11554.981 | I20: =H20*(1+IF(I$3<=$O$2,$D20,$D20-($D20-$I$6)*MIN(I$3-$O$2,$Q$2)/$Q$2)) -> 11818.043 | J20: =I20*(1+IF(J$3<=$O$2,$D20,$D20-($D20-$I$6)*MIN(J$3-$O$2,$Q$2)/$Q$2)) -> 12100.174 | K20: =J20*(1+IF(K$3<=$O$2,$D20,$D20-($D20-$I$6)*MIN(K$3-$O$2,$Q$2)/$Q$2)) -> 12402.432 | L20: =K20*(1+IF(L$3<=$O$2,$D20,$D20-($D20-$I$6)*MIN(L$3-$O$2,$Q$2)/$Q$2)) -> 12725.968 | M20: =L20*(1+IF(M$3<=$O$2,$D20,$D20-($D20-$I$6)*MIN(M$3-$O$2,$Q$2)/$Q$2)) -> 13072.028 | N20: =M20*(1+IF(N$3<=$O$2,$D20,$D20-($D20-$I$6)*MIN(N$3-$O$2,$Q$2)/$Q$2)) -> 13441.966 | O20: =SUMPRODUCT(E20:N20,1/(1+$F$6)^$E$3:$N$3)*$E$2 -> 39919.492 | P20: =N20*$E$2*(1+$I$6)/($F$6-$I$6)/(1+$F$6)^$N$3 -> 66913.178 | Q20: =O20+P20 -> 106832.67 | R20: =Q20-$G$2+$I$2 -> 87372.67 | S20: =R20/$K$2 -> 155.63631 | T20: =S20-$M$2 -> -0.17337286
... A47: 40 | B47: =IF(T46>0,B46,D46) -> 0.022919701 | C47: =IF(T46>0,D46,C46) -> 0.022919701 | D47: =(B47+C47)/2 -> 0.022919701 | E47: =$C$2*(1+IF(E$3<=$O$2,$D47,$D47-($D47-$I$6)*MIN(E$3-$O$2,$Q$2)/$Q$2)) -> 10802.032 | F47: =E47*(1+IF(F$3<=$O$2,$D47,$D47-($D47-$I$6)*MIN(F$3-$O$2,$Q$2)/$Q$2)) -> 11049.611 | G47: =F47*(1+IF(G$3<=$O$2,$D47,$D47-($D47-$I$6)*MIN(G$3-$O$2,$Q$2)/$Q$2)) -> 11302.865 | H47: =G47*(1+IF(H$3<=$O$2,$D47,$D47-($D47-$I$6)*MIN(H$3-$O$2,$Q$2)/$Q$2)) -> 11561.923 | I47: =H47*(1+IF(I$3<=$O$2,$D47,$D47-($D47-$I$6)*MIN(I$3-$O$2,$Q$2)/$Q$2)) -> 11826.919 | J47: =I47*(1+IF(J$3<=$O$2,$D47,$D47-($D47-$I$6)*MIN(J$3-$O$2,$Q$2)/$Q$2)) -> 12110.715 | K47: =J47*(1+IF(K$3<=$O$2,$D47,$D47-($D47-$I$6)*MIN(K$3-$O$2,$Q$2)/$Q$2)) -> 12414.353 | L47: =K47*(1+IF(L$3<=$O$2,$D47,$D47-($D47-$I$6)*MIN(L$3-$O$2,$Q$2)/$Q$2)) -> 12738.962 | M47: =L47*(1+IF(M$3<=$O$2,$D47,$D47-($D47-$I$6)*MIN(M$3-$O$2,$Q$2)/$Q$2)) -> 13085.767 | N47: =M47*(1+IF(N$3<=$O$2,$D47,$D47-($D47-$I$6)*MIN(N$3-$O$2,$Q$2)/$Q$2)) -> 13456.094 | O47: =SUMPRODUCT(E47:N47,1/(1+$F$6)^$E$3:$N$3)*$E$2 -> 39946.495 | P47: =N47*$E$2*(1+$I$6)/($F$6-$I$6)/(1+$F$6)^$N$3 -> 66983.505 | Q47: =O47+P47 -> 106930 | R47: =Q47-$G$2+$I$2 -> 87470 | S47: =R47/$K$2 -> 155.80969 | T47: =S47-$M$2 -> 1.4248087e-09
A49: Grid block 2: row 1, column 1 of table A (24 steps) | E49: WACC | F49: =Sensitivity!$B$10 -> 0.067017203 | G49: Terminal growth | I49: =Sensitivity!$C$9 -> 0.0183
A50: Step | B50: Low | C50: High | D50: Mid | E50: Rev Y1 | F50: Rev Y2 | G50: Rev Y3 | H50: Rev Y4 | I50: Rev Y5 | J50: Rev Y6 | K50: Rev Y7 | L50: Rev Y8 | M50: Rev Y9 | N50: Rev Y10 | O50: PV of FCF | P50: PV of TV | Q50: EV | R50: Equity | S50: Per share | T50: Value - price
A51: 1 | B51: -0.5 | C51: 1 | D51: =(B51+C51)/2 -> 0.25 | E51: =$C$2*(1+IF(E$3<=$O$2,$D51,$D51-($D51-$I$49)*MIN(E$3-$O$2,$Q$2)/$Q$2)) -> 13200 | F51: =E51*(1+IF(F$3<=$O$2,$D51,$D51-($D51-$I$49)*MIN(F$3-$O$2,$Q$2)/$Q$2)) -> 16500 | G51: =F51*(1+IF(G$3<=$O$2,$D51,$D51-($D51-$I$49)*MIN(G$3-$O$2,$Q$2)/$Q$2)) -> 20625 | H51: =G51*(1+IF(H$3<=$O$2,$D51,$D51-($D51-$I$49)*MIN(H$3-$O$2,$Q$2)/$Q$2)) -> 25781.25 | I51: =H51*(1+IF(I$3<=$O$2,$D51,$D51-($D51-$I$49)*MIN(I$3-$O$2,$Q$2)/$Q$2)) -> 32226.562 | J51: =I51*(1+IF(J$3<=$O$2,$D51,$D51-($D51-$I$49)*MIN(J$3-$O$2,$Q$2)/$Q$2)) -> 38789.824 | K51: =J51*(1+IF(K$3<=$O$2,$D51,$D51-($D51-$I$49)*MIN(K$3-$O$2,$Q$2)/$Q$2)) -> 44892.239 | L51: =K51*(1+IF(L$3<=$O$2,$D51,$D51-($D51-$I$49)*MIN(L$3-$O$2,$Q$2)/$Q$2)) -> 49874.38 | M51: =L51*(1+IF(M$3<=$O$2,$D51,$D51-($D51-$I$49)*MIN(M$3-$O$2,$Q$2)/$Q$2)) -> 53098.26 | N51: =M51*(1+IF(N$3<=$O$2,$D51,$D51-($D51-$I$49)*MIN(N$3-$O$2,$Q$2)/$Q$2)) -> 54069.958 | O51: =SUMPRODUCT(E51:N51,1/(1+$F$49)^$E$3:$N$3)*$E$2 -> 113607.26 | P51: =N51*$E$2*(1+$I$49)/($F$49-$I$49)/(1+$F$49)^$N$3 -> 292599.1 | Q51: =O51+P51 -> 406206.36 | R51: =Q51-$G$2+$I$2 -> 386746.36 | S51: =R51/$K$2 -> 688.90853 | T51: =S51-$M$2 -> 533.09885
A52: 2 | B52: =IF(T51>0,B51,D51) -> -0.5 | C52: =IF(T51>0,D51,C51) -> 0.25 | D52: =(B52+C52)/2 -> -0.125 | E52: =$C$2*(1+IF(E$3<=$O$2,$D52,$D52-($D52-$I$49)*MIN(E$3-$O$2,$Q$2)/$Q$2)) -> 9240 | F52: =E52*(1+IF(F$3<=$O$2,$D52,$D52-($D52-$I$49)*MIN(F$3-$O$2,$Q$2)/$Q$2)) -> 8085 | G52: =F52*(1+IF(G$3<=$O$2,$D52,$D52-($D52-$I$49)*MIN(G$3-$O$2,$Q$2)/$Q$2)) -> 7074.375 | H52: =G52*(1+IF(H$3<=$O$2,$D52,$D52-($D52-$I$49)*MIN(H$3-$O$2,$Q$2)/$Q$2)) -> 6190.0781 | I52: =H52*(1+IF(I$3<=$O$2,$D52,$D52-($D52-$I$49)*MIN(I$3-$O$2,$Q$2)/$Q$2)) -> 5416.3184 | J52: =I52*(1+IF(J$3<=$O$2,$D52,$D52-($D52-$I$49)*MIN(J$3-$O$2,$Q$2)/$Q$2)) -> 4894.5102 | K52: =J52*(1+IF(K$3<=$O$2,$D52,$D52-($D52-$I$49)*MIN(K$3-$O$2,$Q$2)/$Q$2)) -> 4563.2498 | L52: =K52*(1+IF(L$3<=$O$2,$D52,$D52-($D52-$I$49)*MIN(L$3-$O$2,$Q$2)/$Q$2)) -> 4385.1918 | M52: =L52*(1+IF(M$3<=$O$2,$D52,$D52-($D52-$I$49)*MIN(M$3-$O$2,$Q$2)/$Q$2)) -> 4339.7612 | N52: =M52*(1+IF(N$3<=$O$2,$D52,$D52-($D52-$I$49)*MIN(N$3-$O$2,$Q$2)/$Q$2)) -> 4419.1788 | O52: =SUMPRODUCT(E52:N52,1/(1+$F$49)^$E$3:$N$3)*$E$2 -> 21707.788 | P52: =N52*$E$2*(1+$I$49)/($F$49-$I$49)/(1+$F$49)^$N$3 -> 23914.347 | Q52: =O52+P52 -> 45622.136 | R52: =Q52-$G$2+$I$2 -> 26162.136 | S52: =R52/$K$2 -> 46.602426 | T52: =S52-$M$2 -> -109.20726
A53: 3 | B53: =IF(T52>0,B52,D52) -> -0.125 | C53: =IF(T52>0,D52,C52) -> 0.25 | D53: =(B53+C53)/2 -> 0.0625 | E53: =$C$2*(1+IF(E$3<=$O$2,$D53,$D53-($D53-$I$49)*MIN(E$3-$O$2,$Q$2)/$Q$2)) -> 11220 | F53: =E53*(1+IF(F$3<=$O$2,$D53,$D53-($D53-$I$49)*MIN(F$3-$O$2,$Q$2)/$Q$2)) -> 11921.25 | G53: =F53*(1+IF(G$3<=$O$2,$D53,$D53-($D53-$I$49)*MIN(G$3-$O$2,$Q$2)/$Q$2)) -> 12666.328 | H53: =G53*(1+IF(H$3<=$O$2,$D53,$D53-($D53-$I$49)*MIN(H$3-$O$2,$Q$2)/$Q$2)) -> 13457.974 | I53: =H53*(1+IF(I$3<=$O$2,$D53,$D53-($D53-$I$49)*MIN(I$3-$O$2,$Q$2)/$Q$2)) -> 14299.097 | J53: =I53*(1+IF(J$3<=$O$2,$D53,$D53-($D53-$I$49)*MIN(J$3-$O$2,$Q$2)/$Q$2)) -> 15066.387 | K53: =J53*(1+IF(K$3<=$O$2,$D53,$D53-($D53-$I$49)*MIN(K$3-$O$2,$Q$2)/$Q$2)) -> 15741.662 | L53: =K53*(1+IF(L$3<=$O$2,$D53,$D53-($D53-$I$49)*MIN(L$3-$O$2,$Q$2)/$Q$2)) -> 16308.047 | M53: =L53*(1+IF(M$3<=$O$2,$D53,$D53-($D53-$I$49)*MIN(M$3-$O$2,$Q$2)/$Q$2)) -> 16750.647 | N53: =M53*(1+IF(N$3<=$O$2,$D53,$D53-($D53-$I$49)*MIN(N$3-$O$2,$Q$2)/$Q$2)) -> 17057.184 | O53: =SUMPRODUCT(E53:N53,1/(1+$F$49)^$E$3:$N$3)*$E$2 -> 49677.075 | P53: =N53*$E$2*(1+$I$49)/($F$49-$I$49)/(1+$F$49)^$N$3 -> 92304.803 | Q53: =O53+P53 -> 141981.88 | R53: =Q53-$G$2+$I$2 -> 122521.88 | S53: =R53/$K$2 -> 218.24735 | T53: =S53-$M$2 -> 62.437659
A54: 4 | B54: =IF(T53>0,B53,D53) -> -0.125 | C54: =IF(T53>0,D53,C53) -> 0.0625 | D54: =(B54+C54)/2 -> -0.03125 | E54: =$C$2*(1+IF(E$3<=$O$2,$D54,$D54-($D54-$I$49)*MIN(E$3-$O$2,$Q$2)/$Q$2)) -> 10230 | F54: =E54*(1+IF(F$3<=$O$2,$D54,$D54-($D54-$I$49)*MIN(F$3-$O$2,$Q$2)/$Q$2)) -> 9910.3125 | G54: =F54*(1+IF(G$3<=$O$2,$D54,$D54-($D54-$I$49)*MIN(G$3-$O$2,$Q$2)/$Q$2)) -> 9600.6152 | H54: =G54*(1+IF(H$3<=$O$2,$D54,$D54-($D54-$I$49)*MIN(H$3-$O$2,$Q$2)/$Q$2)) -> 9300.596 | I54: =H54*(1+IF(I$3<=$O$2,$D54,$D54-($D54-$I$49)*MIN(I$3-$O$2,$Q$2)/$Q$2)) -> 9009.9524 | J54: =I54*(1+IF(J$3<=$O$2,$D54,$D54-($D54-$I$49)*MIN(J$3-$O$2,$Q$2)/$Q$2)) -> 8817.68 | K54: =J54*(1+IF(K$3<=$O$2,$D54,$D54-($D54-$I$49)*MIN(K$3-$O$2,$Q$2)/$Q$2)) -> 8716.8939 | L54: =K54*(1+IF(L$3<=$O$2,$D54,$D54-($D54-$I$49)*MIN(L$3-$O$2,$Q$2)/$Q$2)) -> 8703.6442 | M54: =L54*(1+IF(M$3<=$O$2,$D54,$D54-($D54-$I$49)*MIN(M$3-$O$2,$Q$2)/$Q$2)) -> 8776.6678 | N54: =M54*(1+IF(N$3<=$O$2,$D54,$D54-($D54-$I$49)*MIN(N$3-$O$2,$Q$2)/$Q$2)) -> 8937.2808 | O54: =SUMPRODUCT(E54:N54,1/(1+$F$49)^$E$3:$N$3)*$E$2 -> 32757.744 | P54: =N54*$E$2*(1+$I$49)/($F$49-$I$49)/(1+$F$49)^$N$3 -> 48364.017 | Q54: =O54+P54 -> 81121.761 | R54: =Q54-$G$2+$I$2 -> 61661.761 | S54: =R54/$K$2 -> 109.83765 | T54: =S54-$M$2 -> -45.972032
A55: 5 | B55: =IF(T54>0,B54,D54) -> -0.03125 | C55: =IF(T54>0,D54,C54) -> 0.0625 | D55: =(B55+C55)/2 -> 0.015625 | E55: =$C$2*(1+IF(E$3<=$O$2,$D55,$D55-($D55-$I$49)*MIN(E$3-$O$2,$Q$2)/$Q$2)) -> 10725 | F55: =E55*(1+IF(F$3<=$O$2,$D55,$D55-($D55-$I$49)*MIN(F$3-$O$2,$Q$2)/$Q$2)) -> 10892.578 | G55: =F55*(1+IF(G$3<=$O$2,$D55,$D55-($D55-$I$49)*MIN(G$3-$O$2,$Q$2)/$Q$2)) -> 11062.775 | H55: =G55*(1+IF(H$3<=$O$2,$D55,$D55-($D55-$I$49)*MIN(H$3-$O$2,$Q$2)/$Q$2)) -> 11235.631 | I55: =H55*(1+IF(I$3<=$O$2,$D55,$D55-($D55-$I$49)*MIN(I$3-$O$2,$Q$2)/$Q$2)) -> 11411.187 | J55: =I55*(1+IF(J$3<=$O$2,$D55,$D55-($D55-$I$49)*MIN(J$3-$O$2,$Q$2)/$Q$2)) -> 11595.592 | K55: =J55*(1+IF(K$3<=$O$2,$D55,$D55-($D55-$I$49)*MIN(K$3-$O$2,$Q$2)/$Q$2)) -> 11789.18 | L55: =K55*(1+IF(L$3<=$O$2,$D55,$D55-($D55-$I$49)*MIN(L$3-$O$2,$Q$2)/$Q$2)) -> 11992.308 | M55: =L55*(1+IF(M$3<=$O$2,$D55,$D55-($D55-$I$49)*MIN(M$3-$O$2,$Q$2)/$Q$2)) -> 12205.351 | N55: =M55*(1+IF(N$3<=$O$2,$D55,$D55-($D55-$I$49)*MIN(N$3-$O$2,$Q$2)/$Q$2)) -> 12428.709 | O55: =SUMPRODUCT(E55:N55,1/(1+$F$49)^$E$3:$N$3)*$E$2 -> 40329.007 | P55: =N55*$E$2*(1+$I$49)/($F$49-$I$49)/(1+$F$49)^$N$3 -> 67257.851 | Q55: =O55+P55 -> 107586.86 | R55: =Q55-$G$2+$I$2 -> 88126.858 | S55: =R55/$K$2 -> 156.97974 | T55: =S55-$M$2 -> 1.1700572
A56: 6 | B56: =IF(T55>0,B55,D55) -> -0.03125 | C56: =IF(T55>0,D55,C55) -> 0.015625 | D56: =(B56+C56)/2 -> -0.0078125 | E56: =$C$2*(1+IF(E$3<=$O$2,$D56,$D56-($D56-$I$49)*MIN(E$3-$O$2,$Q$2)/$Q$2)) -> 10477.5 | F56: =E56*(1+IF(F$3<=$O$2,$D56,$D56-($D56-$I$49)*MIN(F$3-$O$2,$Q$2)/$Q$2)) -> 10395.645 | G56: =F56*(1+IF(G$3<=$O$2,$D56,$D56-($D56-$I$49)*MIN(G$3-$O$2,$Q$2)/$Q$2)) -> 10314.429 | H56: =G56*(1+IF(H$3<=$O$2,$D56,$D56-($D56-$I$49)*MIN(H$3-$O$2,$Q$2)/$Q$2)) -> 10233.847 | I56: =H56*(1+IF(I$3<=$O$2,$D56,$D56-($D56-$I$49)*MIN(I$3-$O$2,$Q$2)/$Q$2)) -> 10153.895 | J56: =I56*(1+IF(J$3<=$O$2,$D56,$D56-($D56-$I$49)*MIN(J$3-$O$2,$Q$2)/$Q$2)) -> 10127.597 | K56: =J56*(1+IF(K$3<=$O$2,$D56,$D56-($D56-$I$49)*MIN(K$3-$O$2,$Q$2)/$Q$2)) -> 10154.257 | L56: =K56*(1+IF(L$3<=$O$2,$D56,$D56-($D56-$I$49)*MIN(L$3-$O$2,$Q$2)/$Q$2)) -> 10234.019 | M56: =L56*(1+IF(M$3<=$O$2,$D56,$D56-($D56-$I$49)*MIN(M$3-$O$2,$Q$2)/$Q$2)) -> 10367.855 | N56: =M56*(1+IF(N$3<=$O$2,$D56,$D56-($D56-$I$49)*MIN(N$3-$O$2,$Q$2)/$Q$2)) -> 10557.586 | O56: =SUMPRODUCT(E56:N56,1/(1+$F$49)^$E$3:$N$3)*$E$2 -> 36342.756 | P56: =N56*$E$2*(1+$I$49)/($F$49-$I$49)/(1+$F$49)^$N$3 -> 57132.286 | Q56: =O56+P56 -> 93475.041 | R56: =Q56-$G$2+$I$2 -> 74015.041 | S56: =R56/$K$2 -> 131.84246 | T56: =S56-$M$2 -> -23.967222
A57: 7 | B57: =IF(T56>0,B56,D56) -> -0.0078125 | C57: =IF(T56>0,D56,C56) -> 0.015625 | D57: =(B57+C57)/2 -> 0.00390625 | E57: =$C$2*(1+IF(E$3<=$O$2,$D57,$D57-($D57-$I$49)*MIN(E$3-$O$2,$Q$2)/$Q$2)) -> 10601.25 | F57: =E57*(1+IF(F$3<=$O$2,$D57,$D57-($D57-$I$49)*MIN(F$3-$O$2,$Q$2)/$Q$2)) -> 10642.661 | G57: =F57*(1+IF(G$3<=$O$2,$D57,$D57-($D57-$I$49)*MIN(G$3-$O$2,$Q$2)/$Q$2)) -> 10684.234 | H57: =G57*(1+IF(H$3<=$O$2,$D57,$D57-($D57-$I$49)*MIN(H$3-$O$2,$Q$2)/$Q$2)) -> 10725.969 | I57: =H57*(1+IF(I$3<=$O$2,$D57,$D57-($D57-$I$49)*MIN(I$3-$O$2,$Q$2)/$Q$2)) -> 10767.868 | J57: =I57*(1+IF(J$3<=$O$2,$D57,$D57-($D57-$I$49)*MIN(J$3-$O$2,$Q$2)/$Q$2)) -> 10840.928 | K57: =J57*(1+IF(K$3<=$O$2,$D57,$D57-($D57-$I$49)*MIN(K$3-$O$2,$Q$2)/$Q$2)) -> 10945.692 | L57: =K57*(1+IF(L$3<=$O$2,$D57,$D57-($D57-$I$49)*MIN(L$3-$O$2,$Q$2)/$Q$2)) -> 11082.978 | M57: =L57*(1+IF(M$3<=$O$2,$D57,$D57-($D57-$I$49)*MIN(M$3-$O$2,$Q$2)/$Q$2)) -> 11253.891 | N57: =M57*(1+IF(N$3<=$O$2,$D57,$D57-($D57-$I$49)*MIN(N$3-$O$2,$Q$2)/$Q$2)) -> 11459.838 | O57: =SUMPRODUCT(E57:N57,1/(1+$F$49)^$E$3:$N$3)*$E$2 -> 38283.186 | P57: =N57*$E$2*(1+$I$49)/($F$49-$I$49)/(1+$F$49)^$N$3 -> 62014.81 | Q57: =O57+P57 -> 100298 | R57: =Q57-$G$2+$I$2 -> 80837.996 | S57: =R57/$K$2 -> 143.99615 | T57: =S57-$M$2 -> -11.813541
A58: 8 | B58: =IF(T57>0,B57,D57) -> 0.00390625 | C58: =IF(T57>0,D57,C57) -> 0.015625 | D58: =(B58+C58)/2 -> 0.009765625 | E58: =$C$2*(1+IF(E$3<=$O$2,$D58,$D58-($D58-$I$49)*MIN(E$3-$O$2,$Q$2)/$Q$2)) -> 10663.125 | F58: =E58*(1+IF(F$3<=$O$2,$D58,$D58-($D58-$I$49)*MIN(F$3-$O$2,$Q$2)/$Q$2)) -> 10767.257 | G58: =F58*(1+IF(G$3<=$O$2,$D58,$D58-($D58-$I$49)*MIN(G$3-$O$2,$Q$2)/$Q$2)) -> 10872.406 | H58: =G58*(1+IF(H$3<=$O$2,$D58,$D58-($D58-$I$49)*MIN(H$3-$O$2,$Q$2)/$Q$2)) -> 10978.582 | I58: =H58*(1+IF(I$3<=$O$2,$D58,$D58-($D58-$I$49)*MIN(I$3-$O$2,$Q$2)/$Q$2)) -> 11085.795 | J58: =I58*(1+IF(J$3<=$O$2,$D58,$D58-($D58-$I$49)*MIN(J$3-$O$2,$Q$2)/$Q$2)) -> 11212.976 | K58: =J58*(1+IF(K$3<=$O$2,$D58,$D58-($D58-$I$49)*MIN(K$3-$O$2,$Q$2)/$Q$2)) -> 11360.756 | L58: =K58*(1+IF(L$3<=$O$2,$D58,$D58-($D58-$I$49)*MIN(L$3-$O$2,$Q$2)/$Q$2)) -> 11529.875 | M58: =L58*(1+IF(M$3<=$O$2,$D58,$D58-($D58-$I$49)*MIN(M$3-$O$2,$Q$2)/$Q$2)) -> 11721.192 | N58: =M58*(1+IF(N$3<=$O$2,$D58,$D58-($D58-$I$49)*MIN(N$3-$O$2,$Q$2)/$Q$2)) -> 11935.69 | O58: =SUMPRODUCT(E58:N58,1/(1+$F$49)^$E$3:$N$3)*$E$2 -> 39292.593 | P58: =N58*$E$2*(1+$I$49)/($F$49-$I$49)/(1+$F$49)^$N$3 -> 64589.882 | Q58: =O58+P58 -> 103882.47 | R58: =Q58-$G$2+$I$2 -> 84422.474 | S58: =R58/$K$2 -> 150.38115 | T58: =S58-$M$2 -> -5.4285357
A59: 9 | B59: =IF(T58>0,B58,D58) -> 0.009765625 | C59: =IF(T58>0,D58,C58) -> 0.015625 | D59: =(B59+C59)/2 -> 0.012695312 | E59: =$C$2*(1+IF(E$3<=$O$2,$D59,$D59-($D59-$I$49)*MIN(E$3-$O$2,$Q$2)/$Q$2)) -> 10694.062 | F59: =E59*(1+IF(F$3<=$O$2,$D59,$D59-($D59-$I$49)*MIN(F$3-$O$2,$Q$2)/$Q$2)) -> 10829.827 | G59: =F59*(1+IF(G$3<=$O$2,$D59,$D59-($D59-$I$49)*MIN(G$3-$O$2,$Q$2)/$Q$2)) -> 10967.315 | H59: =G59*(1+IF(H$3<=$O$2,$D59,$D59-($D59-$I$49)*MIN(H$3-$O$2,$Q$2)/$Q$2)) -> 11106.548 | I59: =H59*(1+IF(I$3<=$O$2,$D59,$D59-($D59-$I$49)*MIN(I$3-$O$2,$Q$2)/$Q$2)) -> 11247.55 | J59: =I59*(1+IF(J$3<=$O$2,$D59,$D59-($D59-$I$49)*MIN(J$3-$O$2,$Q$2)/$Q$2)) -> 11402.949 | K59: =J59*(1+IF(K$3<=$O$2,$D59,$D59-($D59-$I$49)*MIN(K$3-$O$2,$Q$2)/$Q$2)) -> 11573.277 | L59: =K59*(1+IF(L$3<=$O$2,$D59,$D59-($D59-$I$49)*MIN(L$3-$O$2,$Q$2)/$Q$2)) -> 11759.122 | M59: =L59*(1+IF(M$3<=$O$2,$D59,$D59-($D59-$I$49)*MIN(M$3-$O$2,$Q$2)/$Q$2)) -> 11961.132 | N59: =M59*(1+IF(N$3<=$O$2,$D59,$D59-($D59-$I$49)*MIN(N$3-$O$2,$Q$2)/$Q$2)) -> 12180.021 | O59: =SUMPRODUCT(E59:N59,1/(1+$F$49)^$E$3:$N$3)*$E$2 -> 39807.382 | P59: =N59*$E$2*(1+$I$49)/($F$49-$I$49)/(1+$F$49)^$N$3 -> 65912.077 | Q59: =O59+P59 -> 105719.46 | R59: =Q59-$G$2+$I$2 -> 86259.459 | S59: =R59/$K$2 -> 153.65336 | T59: =S59-$M$2 -> -2.1563278
A60: 10 | B60: =IF(T59>0,B59,D59) -> 0.012695312 | C60: =IF(T59>0,D59,C59) -> 0.015625 | D60: =(B60+C60)/2 -> 0.014160156 | E60: =$C$2*(1+IF(E$3<=$O$2,$D60,$D60-($D60-$I$49)*MIN(E$3-$O$2,$Q$2)/$Q$2)) -> 10709.531 | F60: =E60*(1+IF(F$3<=$O$2,$D60,$D60-($D60-$I$49)*MIN(F$3-$O$2,$Q$2)/$Q$2)) -> 10861.18 | G60: =F60*(1+IF(G$3<=$O$2,$D60,$D60-($D60-$I$49)*MIN(G$3-$O$2,$Q$2)/$Q$2)) -> 11014.976 | H60: =G60*(1+IF(H$3<=$O$2,$D60,$D60-($D60-$I$49)*MIN(H$3-$O$2,$Q$2)/$Q$2)) -> 11170.95 | I60: =H60*(1+IF(I$3<=$O$2,$D60,$D60-($D60-$I$49)*MIN(I$3-$O$2,$Q$2)/$Q$2)) -> 11329.132 | J60: =I60*(1+IF(J$3<=$O$2,$D60,$D60-($D60-$I$49)*MIN(J$3-$O$2,$Q$2)/$Q$2)) -> 11498.935 | K60: =J60*(1+IF(K$3<=$O$2,$D60,$D60-($D60-$I$49)*MIN(K$3-$O$2,$Q$2)/$Q$2)) -> 11680.803 | L60: =K60*(1+IF(L$3<=$O$2,$D60,$D60-($D60-$I$49)*MIN(L$3-$O$2,$Q$2)/$Q$2)) -> 11875.219 | M60: =L60*(1+IF(M$3<=$O$2,$D60,$D60-($D60-$I$49)*MIN(M$3-$O$2,$Q$2)/$Q$2)) -> 12082.703 | N60: =M60*(1+IF(N$3<=$O$2,$D60,$D60-($D60-$I$49)*MIN(N$3-$O$2,$Q$2)/$Q$2)) -> 12303.816 | O60: =SUMPRODUCT(E60:N60,1/(1+$F$49)^$E$3:$N$3)*$E$2 -> 40067.335 | P60: =N60*$E$2*(1+$I$49)/($F$49-$I$49)/(1+$F$49)^$N$3 -> 66581.995 | Q60: =O60+P60 -> 106649.33 | R60: =Q60-$G$2+$I$2 -> 87189.329 | S60: =R60/$K$2 -> 155.30973 | T60: =S60-$M$2 -> -0.49995673
A61: 11 | B61: =IF(T60>0,B60,D60) -> 0.014160156 | C61: =IF(T60>0,D60,C60) -> 0.015625 | D61: =(B61+C61)/2 -> 0.014892578 | E61: =$C$2*(1+IF(E$3<=$O$2,$D61,$D61-($D61-$I$49)*MIN(E$3-$O$2,$Q$2)/$Q$2)) -> 10717.266 | F61: =E61*(1+IF(F$3<=$O$2,$D61,$D61-($D61-$I$49)*MIN(F$3-$O$2,$Q$2)/$Q$2)) -> 10876.873 | G61: =F61*(1+IF(G$3<=$O$2,$D61,$D61-($D61-$I$49)*MIN(G$3-$O$2,$Q$2)/$Q$2)) -> 11038.858 | H61: =G61*(1+IF(H$3<=$O$2,$D61,$D61-($D61-$I$49)*MIN(H$3-$O$2,$Q$2)/$Q$2)) -> 11203.255 | I61: =H61*(1+IF(I$3<=$O$2,$D61,$D61-($D61-$I$49)*MIN(I$3-$O$2,$Q$2)/$Q$2)) -> 11370.1 | J61: =I61*(1+IF(J$3<=$O$2,$D61,$D61-($D61-$I$49)*MIN(J$3-$O$2,$Q$2)/$Q$2)) -> 11547.179 | K61: =J61*(1+IF(K$3<=$O$2,$D61,$D61-($D61-$I$49)*MIN(K$3-$O$2,$Q$2)/$Q$2)) -> 11734.885 | L61: =K61*(1+IF(L$3<=$O$2,$D61,$D61-($D61-$I$49)*MIN(L$3-$O$2,$Q$2)/$Q$2)) -> 11933.639 | M61: =L61*(1+IF(M$3<=$O$2,$D61,$D61-($D61-$I$49)*MIN(M$3-$O$2,$Q$2)/$Q$2)) -> 12143.892 | N61: =M61*(1+IF(N$3<=$O$2,$D61,$D61-($D61-$I$49)*MIN(N$3-$O$2,$Q$2)/$Q$2)) -> 12366.125 | O61: =SUMPRODUCT(E61:N61,1/(1+$F$49)^$E$3:$N$3)*$E$2 -> 40197.955 | P61: =N61*$E$2*(1+$I$49)/($F$49-$I$49)/(1+$F$49)^$N$3 -> 66919.178 | Q61: =O61+P61 -> 107117.13 | R61: =Q61-$G$2+$I$2 -> 87657.133 | S61: =R61/$K$2 -> 156.14303 | T61: =S61-$M$2 -> 0.33333868
A62: 12 | B62: =IF(T61>0,B61,D61) -> 0.014160156 | C62: =IF(T61>0,D61,C61) -> 0.014892578 | D62: =(B62+C62)/2 -> 0.014526367 | E62: =$C$2*(1+IF(E$3<=$O$2,$D62,$D62-($D62-$I$49)*MIN(E$3-$O$2,$Q$2)/$Q$2)) -> 10713.398 | F62: =E62*(1+IF(F$3<=$O$2,$D62,$D62-($D62-$I$49)*MIN(F$3-$O$2,$Q$2)/$Q$2)) -> 10869.025 | G62: =F62*(1+IF(G$3<=$O$2,$D62,$D62-($D62-$I$49)*MIN(G$3-$O$2,$Q$2)/$Q$2)) -> 11026.913 | H62: =G62*(1+IF(H$3<=$O$2,$D62,$D62-($D62-$I$49)*MIN(H$3-$O$2,$Q$2)/$Q$2)) -> 11187.094 | I62: =H62*(1+IF(I$3<=$O$2,$D62,$D62-($D62-$I$49)*MIN(I$3-$O$2,$Q$2)/$Q$2)) -> 11349.601 | J62: =I62*(1+IF(J$3<=$O$2,$D62,$D62-($D62-$I$49)*MIN(J$3-$O$2,$Q$2)/$Q$2)) -> 11523.036 | K62: =J62*(1+IF(K$3<=$O$2,$D62,$D62-($D62-$I$49)*MIN(K$3-$O$2,$Q$2)/$Q$2)) -> 11707.817 | L62: =K62*(1+IF(L$3<=$O$2,$D62,$D62-($D62-$I$49)*MIN(L$3-$O$2,$Q$2)/$Q$2)) -> 11904.398 | M62: =L62*(1+IF(M$3<=$O$2,$D62,$D62-($D62-$I$49)*MIN(M$3-$O$2,$Q$2)/$Q$2)) -> 12113.264 | N62: =M62*(1+IF(N$3<=$O$2,$D62,$D62-($D62-$I$49)*MIN(N$3-$O$2,$Q$2)/$Q$2)) -> 12334.936 | O62: =SUMPRODUCT(E62:N62,1/(1+$F$49)^$E$3:$N$3)*$E$2 -> 40132.591 | P62: =N62*$E$2*(1+$I$49)/($F$49-$I$49)/(1+$F$49)^$N$3 -> 66750.4 | Q62: =O62+P62 -> 106882.99 | R62: =Q62-$G$2+$I$2 -> 87422.991 | S62: =R62/$K$2 -> 155.72595 | T62: =S62-$M$2 -> -0.083736139
A63: 13 | B63: =IF(T62>0,B62,D62) -> 0.014526367 | C63: =IF(T62>0,D62,C62) -> 0.014892578 | D63: =(B63+C63)/2 -> 0.014709473 | E63: =$C$2*(1+IF(E$3<=$O$2,$D63,$D63-($D63-$I$49)*MIN(E$3-$O$2,$Q$2)/$Q$2)) -> 10715.332 | F63: =E63*(1+IF(F$3<=$O$2,$D63,$D63-($D63-$I$49)*MIN(F$3-$O$2,$Q$2)/$Q$2)) -> 10872.949 | G63: =F63*(1+IF(G$3<=$O$2,$D63,$D63-($D63-$I$49)*MIN(G$3-$O$2,$Q$2)/$Q$2)) -> 11032.884 | H63: =G63*(1+IF(H$3<=$O$2,$D63,$D63-($D63-$I$49)*MIN(H$3-$O$2,$Q$2)/$Q$2)) -> 11195.172 | I63: =H63*(1+IF(I$3<=$O$2,$D63,$D63-($D63-$I$49)*MIN(I$3-$O$2,$Q$2)/$Q$2)) -> 11359.847 | J63: =I63*(1+IF(J$3<=$O$2,$D63,$D63-($D63-$I$49)*MIN(J$3-$O$2,$Q$2)/$Q$2)) -> 11535.102 | K63: =J63*(1+IF(K$3<=$O$2,$D63,$D63-($D63-$I$49)*MIN(K$3-$O$2,$Q$2)/$Q$2)) -> 11721.344 | L63: =K63*(1+IF(L$3<=$O$2,$D63,$D63-($D63-$I$49)*MIN(L$3-$O$2,$Q$2)/$Q$2)) -> 11919.011 | M63: =L63*(1+IF(M$3<=$O$2,$D63,$D63-($D63-$I$49)*MIN(M$3-$O$2,$Q$2)/$Q$2)) -> 12128.569 | N63: =M63*(1+IF(N$3<=$O$2,$D63,$D63-($D63-$I$49)*MIN(N$3-$O$2,$Q$2)/$Q$2)) -> 12350.522 | O63: =SUMPRODUCT(E63:N63,1/(1+$F$49)^$E$3:$N$3)*$E$2 -> 40165.26 | P63: =N63*$E$2*(1+$I$49)/($F$49-$I$49)/(1+$F$49)^$N$3 -> 66834.742 | Q63: =O63+P63 -> 107000 | R63: =Q63-$G$2+$I$2 -> 87540.002 | S63: =R63/$K$2 -> 155.93438 | T63: =S63-$M$2 -> 0.1246944
... A74: 24 | B74: =IF(T73>0,B73,D73) -> 0.01459986 | C74: =IF(T73>0,D73,C73) -> 0.014600039 | D74: =(B74+C74)/2 -> 0.014599949 | E74: =$C$2*(1+IF(E$3<=$O$2,$D74,$D74-($D74-$I$49)*MIN(E$3-$O$2,$Q$2)/$Q$2)) -> 10714.175 | F74: =E74*(1+IF(F$3<=$O$2,$D74,$D74-($D74-$I$49)*MIN(F$3-$O$2,$Q$2)/$Q$2)) -> 10870.602 | G74: =F74*(1+IF(G$3<=$O$2,$D74,$D74-($D74-$I$49)*MIN(G$3-$O$2,$Q$2)/$Q$2)) -> 11029.312 | H74: =G74*(1+IF(H$3<=$O$2,$D74,$D74-($D74-$I$49)*MIN(H$3-$O$2,$Q$2)/$Q$2)) -> 11190.34 | I74: =H74*(1+IF(I$3<=$O$2,$D74,$D74-($D74-$I$49)*MIN(I$3-$O$2,$Q$2)/$Q$2)) -> 11353.718 | J74: =I74*(1+IF(J$3<=$O$2,$D74,$D74-($D74-$I$49)*MIN(J$3-$O$2,$Q$2)/$Q$2)) -> 11527.883 | K74: =J74*(1+IF(K$3<=$O$2,$D74,$D74-($D74-$I$49)*MIN(K$3-$O$2,$Q$2)/$Q$2)) -> 11713.251 | L74: =K74*(1+IF(L$3<=$O$2,$D74,$D74-($D74-$I$49)*MIN(L$3-$O$2,$Q$2)/$Q$2)) -> 11910.268 | M74: =L74*(1+IF(M$3<=$O$2,$D74,$D74-($D74-$I$49)*MIN(M$3-$O$2,$Q$2)/$Q$2)) -> 12119.412 | N74: =M74*(1+IF(N$3<=$O$2,$D74,$D74-($D74-$I$49)*MIN(N$3-$O$2,$Q$2)/$Q$2)) -> 12341.198 | O74: =SUMPRODUCT(E74:N74,1/(1+$F$49)^$E$3:$N$3)*$E$2 -> 40145.716 | P74: =N74*$E$2*(1+$I$49)/($F$49-$I$49)/(1+$F$49)^$N$3 -> 66784.282 | Q74: =O74+P74 -> 106930 | R74: =Q74-$G$2+$I$2 -> 87469.998 | S74: =R74/$K$2 -> 155.80968 | T74: =S74-$M$2 -> -2.8654616e-06
A76: Grid block 3: row 1, column 2 of table A (24 steps) | E76: WACC | F76: =Sensitivity!$B$10 -> 0.067017203 | G76: Terminal growth | I76: =Sensitivity!$D$9 -> 0.0233
A77: Step | B77: Low | C77: High | D77: Mid | E77: Rev Y1 | F77: Rev Y2 | G77: Rev Y3 | H77: Rev Y4 | I77: Rev Y5 | J77: Rev Y6 | K77: Rev Y7 | L77: Rev Y8 | M77: Rev Y9 | N77: Rev Y10 | O77: PV of FCF | P77: PV of TV | Q77: EV | R77: Equity | S77: Per share | T77: Value - price
A78: 1 | B78: -0.5 | C78: 1 | D78: =(B78+C78)/2 -> 0.25 | E78: =$C$2*(1+IF(E$3<=$O$2,$D78,$D78-($D78-$I$76)*MIN(E$3-$O$2,$Q$2)/$Q$2)) -> 13200 | F78: =E78*(1+IF(F$3<=$O$2,$D78,$D78-($D78-$I$76)*MIN(F$3-$O$2,$Q$2)/$Q$2)) -> 16500 | G78: =F78*(1+IF(G$3<=$O$2,$D78,$D78-($D78-$I$76)*MIN(G$3-$O$2,$Q$2)/$Q$2)) -> 20625 | H78: =G78*(1+IF(H$3<=$O$2,$D78,$D78-($D78-$I$76)*MIN(H$3-$O$2,$Q$2)/$Q$2)) -> 25781.25 | I78: =H78*(1+IF(I$3<=$O$2,$D78,$D78-($D78-$I$76)*MIN(I$3-$O$2,$Q$2)/$Q$2)) -> 32226.562 | J78: =I78*(1+IF(J$3<=$O$2,$D78,$D78-($D78-$I$76)*MIN(J$3-$O$2,$Q$2)/$Q$2)) -> 38822.051 | K78: =J78*(1+IF(K$3<=$O$2,$D78,$D78-($D78-$I$76)*MIN(K$3-$O$2,$Q$2)/$Q$2)) -> 45007.18 | L78: =K78*(1+IF(L$3<=$O$2,$D78,$D78-($D78-$I$76)*MIN(L$3-$O$2,$Q$2)/$Q$2)) -> 50137.098 | M78: =L78*(1+IF(M$3<=$O$2,$D78,$D78-($D78-$I$76)*MIN(M$3-$O$2,$Q$2)/$Q$2)) -> 53578.509 | N78: =M78*(1+IF(N$3<=$O$2,$D78,$D78-($D78-$I$76)*MIN(N$3-$O$2,$Q$2)/$Q$2)) -> 54826.888 | O78: =SUMPRODUCT(E78:N78,1/(1+$F$76)^$E$3:$N$3)*$E$2 -> 114060.29 | P78: =N78*$E$2*(1+$I$76)/($F$76-$I$76)/(1+$F$76)^$N$3 -> 332252.12 | Q78: =O78+P78 -> 446312.41 | R78: =Q78-$G$2+$I$2 -> 426852.41 | S78: =R78/$K$2 -> 760.34916 | T78: =S78-$M$2 -> 604.53947
A79: 2 | B79: =IF(T78>0,B78,D78) -> -0.5 | C79: =IF(T78>0,D78,C78) -> 0.25 | D79: =(B79+C79)/2 -> -0.125 | E79: =$C$2*(1+IF(E$3<=$O$2,$D79,$D79-($D79-$I$76)*MIN(E$3-$O$2,$Q$2)/$Q$2)) -> 9240 | F79: =E79*(1+IF(F$3<=$O$2,$D79,$D79-($D79-$I$76)*MIN(F$3-$O$2,$Q$2)/$Q$2)) -> 8085 | G79: =F79*(1+IF(G$3<=$O$2,$D79,$D79-($D79-$I$76)*MIN(G$3-$O$2,$Q$2)/$Q$2)) -> 7074.375 | H79: =G79*(1+IF(H$3<=$O$2,$D79,$D79-($D79-$I$76)*MIN(H$3-$O$2,$Q$2)/$Q$2)) -> 6190.0781 | I79: =H79*(1+IF(I$3<=$O$2,$D79,$D79-($D79-$I$76)*MIN(I$3-$O$2,$Q$2)/$Q$2)) -> 5416.3184 | J79: =I79*(1+IF(J$3<=$O$2,$D79,$D79-($D79-$I$76)*MIN(J$3-$O$2,$Q$2)/$Q$2)) -> 4899.9266 | K79: =J79*(1+IF(K$3<=$O$2,$D79,$D79-($D79-$I$76)*MIN(K$3-$O$2,$Q$2)/$Q$2)) -> 4578.0994 | L79: =K79*(1+IF(L$3<=$O$2,$D79,$D79-($D79-$I$76)*MIN(L$3-$O$2,$Q$2)/$Q$2)) -> 4413.1963 | M79: =L79*(1+IF(M$3<=$O$2,$D79,$D79-($D79-$I$76)*MIN(M$3-$O$2,$Q$2)/$Q$2)) -> 4385.1283 | N79: =M79*(1+IF(N$3<=$O$2,$D79,$D79-($D79-$I$76)*MIN(N$3-$O$2,$Q$2)/$Q$2)) -> 4487.3018 | O79: =SUMPRODUCT(E79:N79,1/(1+$F$76)^$E$3:$N$3)*$E$2 -> 21752.7 | P79: =N79*$E$2*(1+$I$76)/($F$76-$I$76)/(1+$F$76)^$N$3 -> 27193.146 | Q79: =O79+P79 -> 48945.846 | R79: =Q79-$G$2+$I$2 -> 29485.846 | S79: =R79/$K$2 -> 52.522926 | T79: =S79-$M$2 -> -103.28676
A80: 3 | B80: =IF(T79>0,B79,D79) -> -0.125 | C80: =IF(T79>0,D79,C79) -> 0.25 | D80: =(B80+C80)/2 -> 0.0625 | E80: =$C$2*(1+IF(E$3<=$O$2,$D80,$D80-($D80-$I$76)*MIN(E$3-$O$2,$Q$2)/$Q$2)) -> 11220 | F80: =E80*(1+IF(F$3<=$O$2,$D80,$D80-($D80-$I$76)*MIN(F$3-$O$2,$Q$2)/$Q$2)) -> 11921.25 | G80: =F80*(1+IF(G$3<=$O$2,$D80,$D80-($D80-$I$76)*MIN(G$3-$O$2,$Q$2)/$Q$2)) -> 12666.328 | H80: =G80*(1+IF(H$3<=$O$2,$D80,$D80-($D80-$I$76)*MIN(H$3-$O$2,$Q$2)/$Q$2)) -> 13457.974 | I80: =H80*(1+IF(I$3<=$O$2,$D80,$D80-($D80-$I$76)*MIN(I$3-$O$2,$Q$2)/$Q$2)) -> 14299.097 | J80: =I80*(1+IF(J$3<=$O$2,$D80,$D80-($D80-$I$76)*MIN(J$3-$O$2,$Q$2)/$Q$2)) -> 15080.686 | K80: =J80*(1+IF(K$3<=$O$2,$D80,$D80-($D80-$I$76)*MIN(K$3-$O$2,$Q$2)/$Q$2)) -> 15786.763 | L80: =K80*(1+IF(L$3<=$O$2,$D80,$D80-($D80-$I$76)*MIN(L$3-$O$2,$Q$2)/$Q$2)) -> 16402.131 | M80: =L80*(1+IF(M$3<=$O$2,$D80,$D80-($D80-$I$76)*MIN(M$3-$O$2,$Q$2)/$Q$2)) -> 16912.894 | N80: =M80*(1+IF(N$3<=$O$2,$D80,$D80-($D80-$I$76)*MIN(N$3-$O$2,$Q$2)/$Q$2)) -> 17306.964 | O80: =SUMPRODUCT(E80:N80,1/(1+$F$76)^$E$3:$N$3)*$E$2 -> 49833.277 | P80: =N80*$E$2*(1+$I$76)/($F$76-$I$76)/(1+$F$76)^$N$3 -> 104880.58 | Q80: =O80+P80 -> 154713.85 | R80: =Q80-$G$2+$I$2 -> 135253.85 | S80: =R80/$K$2 -> 240.92672 | T80: =S80-$M$2 -> 85.117036
A81: 4 | B81: =IF(T80>0,B80,D80) -> -0.125 | C81: =IF(T80>0,D80,C80) -> 0.0625 | D81: =(B81+C81)/2 -> -0.03125 | E81: =$C$2*(1+IF(E$3<=$O$2,$D81,$D81-($D81-$I$76)*MIN(E$3-$O$2,$Q$2)/$Q$2)) -> 10230 | F81: =E81*(1+IF(F$3<=$O$2,$D81,$D81-($D81-$I$76)*MIN(F$3-$O$2,$Q$2)/$Q$2)) -> 9910.3125 | G81: =F81*(1+IF(G$3<=$O$2,$D81,$D81-($D81-$I$76)*MIN(G$3-$O$2,$Q$2)/$Q$2)) -> 9600.6152 | H81: =G81*(1+IF(H$3<=$O$2,$D81,$D81-($D81-$I$76)*MIN(H$3-$O$2,$Q$2)/$Q$2)) -> 9300.596 | I81: =H81*(1+IF(I$3<=$O$2,$D81,$D81-($D81-$I$76)*MIN(I$3-$O$2,$Q$2)/$Q$2)) -> 9009.9524 | J81: =I81*(1+IF(J$3<=$O$2,$D81,$D81-($D81-$I$76)*MIN(J$3-$O$2,$Q$2)/$Q$2)) -> 8826.69 | K81: =J81*(1+IF(K$3<=$O$2,$D81,$D81-($D81-$I$76)*MIN(K$3-$O$2,$Q$2)/$Q$2)) -> 8743.4543 | L81: =K81*(1+IF(L$3<=$O$2,$D81,$D81-($D81-$I$76)*MIN(L$3-$O$2,$Q$2)/$Q$2)) -> 8756.3946 | M81: =L81*(1+IF(M$3<=$O$2,$D81,$D81-($D81-$I$76)*MIN(M$3-$O$2,$Q$2)/$Q$2)) -> 8864.8863 | N81: =M81*(1+IF(N$3<=$O$2,$D81,$D81-($D81-$I$76)*MIN(N$3-$O$2,$Q$2)/$Q$2)) -> 9071.4382 | O81: =SUMPRODUCT(E81:N81,1/(1+$F$76)^$E$3:$N$3)*$E$2 -> 32843.772 | P81: =N81*$E$2*(1+$I$76)/($F$76-$I$76)/(1+$F$76)^$N$3 -> 54973.111 | Q81: =O81+P81 -> 87816.883 | R81: =Q81-$G$2+$I$2 -> 68356.883 | S81: =R81/$K$2 -> 121.76363 | T81: =S81-$M$2 -> -34.046059
A82: 5 | B82: =IF(T81>0,B81,D81) -> -0.03125 | C82: =IF(T81>0,D81,C81) -> 0.0625 | D82: =(B82+C82)/2 -> 0.015625 | E82: =$C$2*(1+IF(E$3<=$O$2,$D82,$D82-($D82-$I$76)*MIN(E$3-$O$2,$Q$2)/$Q$2)) -> 10725 | F82: =E82*(1+IF(F$3<=$O$2,$D82,$D82-($D82-$I$76)*MIN(F$3-$O$2,$Q$2)/$Q$2)) -> 10892.578 | G82: =F82*(1+IF(G$3<=$O$2,$D82,$D82-($D82-$I$76)*MIN(G$3-$O$2,$Q$2)/$Q$2)) -> 11062.775 | H82: =G82*(1+IF(H$3<=$O$2,$D82,$D82-($D82-$I$76)*MIN(H$3-$O$2,$Q$2)/$Q$2)) -> 11235.631 | I82: =H82*(1+IF(I$3<=$O$2,$D82,$D82-($D82-$I$76)*MIN(I$3-$O$2,$Q$2)/$Q$2)) -> 11411.187 | J82: =I82*(1+IF(J$3<=$O$2,$D82,$D82-($D82-$I$76)*MIN(J$3-$O$2,$Q$2)/$Q$2)) -> 11607.003 | K82: =J82*(1+IF(K$3<=$O$2,$D82,$D82-($D82-$I$76)*MIN(K$3-$O$2,$Q$2)/$Q$2)) -> 11823.996 | L82: =K82*(1+IF(L$3<=$O$2,$D82,$D82-($D82-$I$76)*MIN(L$3-$O$2,$Q$2)/$Q$2)) -> 12063.196 | M82: =L82*(1+IF(M$3<=$O$2,$D82,$D82-($D82-$I$76)*MIN(M$3-$O$2,$Q$2)/$Q$2)) -> 12325.751 | N82: =M82*(1+IF(N$3<=$O$2,$D82,$D82-($D82-$I$76)*MIN(N$3-$O$2,$Q$2)/$Q$2)) -> 12612.941 | O82: =SUMPRODUCT(E82:N82,1/(1+$F$76)^$E$3:$N$3)*$E$2 -> 40445.638 | P82: =N82*$E$2*(1+$I$76)/($F$76-$I$76)/(1+$F$76)^$N$3 -> 76434.694 | Q82: =O82+P82 -> 116880.33 | R82: =Q82-$G$2+$I$2 -> 97420.332 | S82: =R82/$K$2 -> 173.53414 | T82: =S82-$M$2 -> 17.724455
A83: 6 | B83: =IF(T82>0,B82,D82) -> -0.03125 | C83: =IF(T82>0,D82,C82) -> 0.015625 | D83: =(B83+C83)/2 -> -0.0078125 | E83: =$C$2*(1+IF(E$3<=$O$2,$D83,$D83-($D83-$I$76)*MIN(E$3-$O$2,$Q$2)/$Q$2)) -> 10477.5 | F83: =E83*(1+IF(F$3<=$O$2,$D83,$D83-($D83-$I$76)*MIN(F$3-$O$2,$Q$2)/$Q$2)) -> 10395.645 | G83: =F83*(1+IF(G$3<=$O$2,$D83,$D83-($D83-$I$76)*MIN(G$3-$O$2,$Q$2)/$Q$2)) -> 10314.429 | H83: =G83*(1+IF(H$3<=$O$2,$D83,$D83-($D83-$I$76)*MIN(H$3-$O$2,$Q$2)/$Q$2)) -> 10233.847 | I83: =H83*(1+IF(I$3<=$O$2,$D83,$D83-($D83-$I$76)*MIN(I$3-$O$2,$Q$2)/$Q$2)) -> 10153.895 | J83: =I83*(1+IF(J$3<=$O$2,$D83,$D83-($D83-$I$76)*MIN(J$3-$O$2,$Q$2)/$Q$2)) -> 10137.75 | K83: =J83*(1+IF(K$3<=$O$2,$D83,$D83-($D83-$I$76)*MIN(K$3-$O$2,$Q$2)/$Q$2)) -> 10184.714 | L83: =K83*(1+IF(L$3<=$O$2,$D83,$D83-($D83-$I$76)*MIN(L$3-$O$2,$Q$2)/$Q$2)) -> 10295.269 | M83: =L83*(1+IF(M$3<=$O$2,$D83,$D83-($D83-$I$76)*MIN(M$3-$O$2,$Q$2)/$Q$2)) -> 10471.086 | N83: =M83*(1+IF(N$3<=$O$2,$D83,$D83-($D83-$I$76)*MIN(N$3-$O$2,$Q$2)/$Q$2)) -> 10715.062 | O83: =SUMPRODUCT(E83:N83,1/(1+$F$76)^$E$3:$N$3)*$E$2 -> 36443.083 | P83: =N83*$E$2*(1+$I$76)/($F$76-$I$76)/(1+$F$76)^$N$3 -> 64933.509 | Q83: =O83+P83 -> 101376.59 | R83: =Q83-$G$2+$I$2 -> 81916.592 | S83: =R83/$K$2 -> 145.91744 | T83: =S83-$M$2 -> -9.8922462
A84: 7 | B84: =IF(T83>0,B83,D83) -> -0.0078125 | C84: =IF(T83>0,D83,C83) -> 0.015625 | D84: =(B84+C84)/2 -> 0.00390625 | E84: =$C$2*(1+IF(E$3<=$O$2,$D84,$D84-($D84-$I$76)*MIN(E$3-$O$2,$Q$2)/$Q$2)) -> 10601.25 | F84: =E84*(1+IF(F$3<=$O$2,$D84,$D84-($D84-$I$76)*MIN(F$3-$O$2,$Q$2)/$Q$2)) -> 10642.661 | G84: =F84*(1+IF(G$3<=$O$2,$D84,$D84-($D84-$I$76)*MIN(G$3-$O$2,$Q$2)/$Q$2)) -> 10684.234 | H84: =G84*(1+IF(H$3<=$O$2,$D84,$D84-($D84-$I$76)*MIN(H$3-$O$2,$Q$2)/$Q$2)) -> 10725.969 | I84: =H84*(1+IF(I$3<=$O$2,$D84,$D84-($D84-$I$76)*MIN(I$3-$O$2,$Q$2)/$Q$2)) -> 10767.868 | J84: =I84*(1+IF(J$3<=$O$2,$D84,$D84-($D84-$I$76)*MIN(J$3-$O$2,$Q$2)/$Q$2)) -> 10851.695 | K84: =J84*(1+IF(K$3<=$O$2,$D84,$D84-($D84-$I$76)*MIN(K$3-$O$2,$Q$2)/$Q$2)) -> 10978.267 | L84: =K84*(1+IF(L$3<=$O$2,$D84,$D84-($D84-$I$76)*MIN(L$3-$O$2,$Q$2)/$Q$2)) -> 11148.897 | M84: =L84*(1+IF(M$3<=$O$2,$D84,$D84-($D84-$I$76)*MIN(M$3-$O$2,$Q$2)/$Q$2)) -> 11365.422 | N84: =M84*(1+IF(N$3<=$O$2,$D84,$D84-($D84-$I$76)*MIN(N$3-$O$2,$Q$2)/$Q$2)) -> 11630.237 | O84: =SUMPRODUCT(E84:N84,1/(1+$F$76)^$E$3:$N$3)*$E$2 -> 38391.4 | P84: =N84*$E$2*(1+$I$76)/($F$76-$I$76)/(1+$F$76)^$N$3 -> 70479.484 | Q84: =O84+P84 -> 108870.88 | R84: =Q84-$G$2+$I$2 -> 89410.884 | S84: =R84/$K$2 -> 159.26697 | T84: =S84-$M$2 -> 3.4572825
A85: 8 | B85: =IF(T84>0,B84,D84) -> -0.0078125 | C85: =IF(T84>0,D84,C84) -> 0.00390625 | D85: =(B85+C85)/2 -> -0.001953125 | E85: =$C$2*(1+IF(E$3<=$O$2,$D85,$D85-($D85-$I$76)*MIN(E$3-$O$2,$Q$2)/$Q$2)) -> 10539.375 | F85: =E85*(1+IF(F$3<=$O$2,$D85,$D85-($D85-$I$76)*MIN(F$3-$O$2,$Q$2)/$Q$2)) -> 10518.79 | G85: =F85*(1+IF(G$3<=$O$2,$D85,$D85-($D85-$I$76)*MIN(G$3-$O$2,$Q$2)/$Q$2)) -> 10498.246 | H85: =G85*(1+IF(H$3<=$O$2,$D85,$D85-($D85-$I$76)*MIN(H$3-$O$2,$Q$2)/$Q$2)) -> 10477.741 | I85: =H85*(1+IF(I$3<=$O$2,$D85,$D85-($D85-$I$76)*MIN(I$3-$O$2,$Q$2)/$Q$2)) -> 10457.277 | J85: =I85*(1+IF(J$3<=$O$2,$D85,$D85-($D85-$I$76)*MIN(J$3-$O$2,$Q$2)/$Q$2)) -> 10489.668 | K85: =J85*(1+IF(K$3<=$O$2,$D85,$D85-($D85-$I$76)*MIN(K$3-$O$2,$Q$2)/$Q$2)) -> 10575.14 | L85: =K85*(1+IF(L$3<=$O$2,$D85,$D85-($D85-$I$76)*MIN(L$3-$O$2,$Q$2)/$Q$2)) -> 10714.718 | M85: =L85*(1+IF(M$3<=$O$2,$D85,$D85-($D85-$I$76)*MIN(M$3-$O$2,$Q$2)/$Q$2)) -> 10910.255 | N85: =M85*(1+IF(N$3<=$O$2,$D85,$D85-($D85-$I$76)*MIN(N$3-$O$2,$Q$2)/$Q$2)) -> 11164.464 | O85: =SUMPRODUCT(E85:N85,1/(1+$F$76)^$E$3:$N$3)*$E$2 -> 37404.329 | P85: =N85*$E$2*(1+$I$76)/($F$76-$I$76)/(1+$F$76)^$N$3 -> 67656.893 | Q85: =O85+P85 -> 105061.22 | R85: =Q85-$G$2+$I$2 -> 85601.222 | S85: =R85/$K$2 -> 152.48085 | T85: =S85-$M$2 -> -3.3288405
A86: 9 | B86: =IF(T85>0,B85,D85) -> -0.001953125 | C86: =IF(T85>0,D85,C85) -> 0.00390625 | D86: =(B86+C86)/2 -> 0.0009765625 | E86: =$C$2*(1+IF(E$3<=$O$2,$D86,$D86-($D86-$I$76)*MIN(E$3-$O$2,$Q$2)/$Q$2)) -> 10570.312 | F86: =E86*(1+IF(F$3<=$O$2,$D86,$D86-($D86-$I$76)*MIN(F$3-$O$2,$Q$2)/$Q$2)) -> 10580.635 | G86: =F86*(1+IF(G$3<=$O$2,$D86,$D86-($D86-$I$76)*MIN(G$3-$O$2,$Q$2)/$Q$2)) -> 10590.968 | H86: =G86*(1+IF(H$3<=$O$2,$D86,$D86-($D86-$I$76)*MIN(H$3-$O$2,$Q$2)/$Q$2)) -> 10601.31 | I86: =H86*(1+IF(I$3<=$O$2,$D86,$D86-($D86-$I$76)*MIN(I$3-$O$2,$Q$2)/$Q$2)) -> 10611.663 | J86: =I86*(1+IF(J$3<=$O$2,$D86,$D86-($D86-$I$76)*MIN(J$3-$O$2,$Q$2)/$Q$2)) -> 10669.404 | K86: =J86*(1+IF(K$3<=$O$2,$D86,$D86-($D86-$I$76)*MIN(K$3-$O$2,$Q$2)/$Q$2)) -> 10775.094 | L86: =K86*(1+IF(L$3<=$O$2,$D86,$D86-($D86-$I$76)*MIN(L$3-$O$2,$Q$2)/$Q$2)) -> 10929.939 | M86: =L86*(1+IF(M$3<=$O$2,$D86,$D86-($D86-$I$76)*MIN(M$3-$O$2,$Q$2)/$Q$2)) -> 11135.808 | N86: =M86*(1+IF(N$3<=$O$2,$D86,$D86-($D86-$I$76)*MIN(N$3-$O$2,$Q$2)/$Q$2)) -> 11395.272 | O86: =SUMPRODUCT(E86:N86,1/(1+$F$76)^$E$3:$N$3)*$E$2 -> 37894.596 | P86: =N86*$E$2*(1+$I$76)/($F$76-$I$76)/(1+$F$76)^$N$3 -> 69055.597 | Q86: =O86+P86 -> 106950.19 | R86: =Q86-$G$2+$I$2 -> 87490.193 | S86: =R86/$K$2 -> 155.84566 | T86: =S86-$M$2 -> 0.035969502
A87: 10 | B87: =IF(T86>0,B86,D86) -> -0.001953125 | C87: =IF(T86>0,D86,C86) -> 0.0009765625 | D87: =(B87+C87)/2 -> -0.00048828125 | E87: =$C$2*(1+IF(E$3<=$O$2,$D87,$D87-($D87-$I$76)*MIN(E$3-$O$2,$Q$2)/$Q$2)) -> 10554.844 | F87: =E87*(1+IF(F$3<=$O$2,$D87,$D87-($D87-$I$76)*MIN(F$3-$O$2,$Q$2)/$Q$2)) -> 10549.69 | G87: =F87*(1+IF(G$3<=$O$2,$D87,$D87-($D87-$I$76)*MIN(G$3-$O$2,$Q$2)/$Q$2)) -> 10544.539 | H87: =G87*(1+IF(H$3<=$O$2,$D87,$D87-($D87-$I$76)*MIN(H$3-$O$2,$Q$2)/$Q$2)) -> 10539.39 | I87: =H87*(1+IF(I$3<=$O$2,$D87,$D87-($D87-$I$76)*MIN(I$3-$O$2,$Q$2)/$Q$2)) -> 10534.244 | J87: =I87*(1+IF(J$3<=$O$2,$D87,$D87-($D87-$I$76)*MIN(J$3-$O$2,$Q$2)/$Q$2)) -> 10579.219 | K87: =J87*(1+IF(K$3<=$O$2,$D87,$D87-($D87-$I$76)*MIN(K$3-$O$2,$Q$2)/$Q$2)) -> 10674.717 | L87: =K87*(1+IF(L$3<=$O$2,$D87,$D87-($D87-$I$76)*MIN(L$3-$O$2,$Q$2)/$Q$2)) -> 10821.865 | M87: =L87*(1+IF(M$3<=$O$2,$D87,$D87-($D87-$I$76)*MIN(M$3-$O$2,$Q$2)/$Q$2)) -> 11022.528 | N87: =M87*(1+IF(N$3<=$O$2,$D87,$D87-($D87-$I$76)*MIN(N$3-$O$2,$Q$2)/$Q$2)) -> 11279.353 | O87: =SUMPRODUCT(E87:N87,1/(1+$F$76)^$E$3:$N$3)*$E$2 -> 37648.651 | P87: =N87*$E$2*(1+$I$76)/($F$76-$I$76)/(1+$F$76)^$N$3 -> 68353.121 | Q87: =O87+P87 -> 106001.77 | R87: =Q87-$G$2+$I$2 -> 86541.772 | S87: =R87/$K$2 -> 154.15624 | T87: =S87-$M$2 -> -1.6534465
A88: 11 | B88: =IF(T87>0,B87,D87) -> -0.00048828125 | C88: =IF(T87>0,D87,C87) -> 0.0009765625 | D88: =(B88+C88)/2 -> 0.00024414062 | E88: =$C$2*(1+IF(E$3<=$O$2,$D88,$D88-($D88-$I$76)*MIN(E$3-$O$2,$Q$2)/$Q$2)) -> 10562.578 | F88: =E88*(1+IF(F$3<=$O$2,$D88,$D88-($D88-$I$76)*MIN(F$3-$O$2,$Q$2)/$Q$2)) -> 10565.157 | G88: =F88*(1+IF(G$3<=$O$2,$D88,$D88-($D88-$I$76)*MIN(G$3-$O$2,$Q$2)/$Q$2)) -> 10567.736 | H88: =G88*(1+IF(H$3<=$O$2,$D88,$D88-($D88-$I$76)*MIN(H$3-$O$2,$Q$2)/$Q$2)) -> 10570.316 | I88: =H88*(1+IF(I$3<=$O$2,$D88,$D88-($D88-$I$76)*MIN(I$3-$O$2,$Q$2)/$Q$2)) -> 10572.897 | J88: =I88*(1+IF(J$3<=$O$2,$D88,$D88-($D88-$I$76)*MIN(J$3-$O$2,$Q$2)/$Q$2)) -> 10624.232 | K88: =J88*(1+IF(K$3<=$O$2,$D88,$D88-($D88-$I$76)*MIN(K$3-$O$2,$Q$2)/$Q$2)) -> 10724.806 | L88: =K88*(1+IF(L$3<=$O$2,$D88,$D88-($D88-$I$76)*MIN(L$3-$O$2,$Q$2)/$Q$2)) -> 10875.786 | M88: =L88*(1+IF(M$3<=$O$2,$D88,$D88-($D88-$I$76)*MIN(M$3-$O$2,$Q$2)/$Q$2)) -> 11079.042 | N88: =M88*(1+IF(N$3<=$O$2,$D88,$D88-($D88-$I$76)*MIN(N$3-$O$2,$Q$2)/$Q$2)) -> 11337.183 | O88: =SUMPRODUCT(E88:N88,1/(1+$F$76)^$E$3:$N$3)*$E$2 -> 37771.42 | P88: =N88*$E$2*(1+$I$76)/($F$76-$I$76)/(1+$F$76)^$N$3 -> 68703.575 | Q88: =O88+P88 -> 106474.99 | R88: =Q88-$G$2+$I$2 -> 87014.995 | S88: =R88/$K$2 -> 154.99919 | T88: =S88-$M$2 -> -0.8104977
A89: 12 | B89: =IF(T88>0,B88,D88) -> 0.00024414062 | C89: =IF(T88>0,D88,C88) -> 0.0009765625 | D89: =(B89+C89)/2 -> 0.00061035156 | E89: =$C$2*(1+IF(E$3<=$O$2,$D89,$D89-($D89-$I$76)*MIN(E$3-$O$2,$Q$2)/$Q$2)) -> 10566.445 | F89: =E89*(1+IF(F$3<=$O$2,$D89,$D89-($D89-$I$76)*MIN(F$3-$O$2,$Q$2)/$Q$2)) -> 10572.895 | G89: =F89*(1+IF(G$3<=$O$2,$D89,$D89-($D89-$I$76)*MIN(G$3-$O$2,$Q$2)/$Q$2)) -> 10579.348 | H89: =G89*(1+IF(H$3<=$O$2,$D89,$D89-($D89-$I$76)*MIN(H$3-$O$2,$Q$2)/$Q$2)) -> 10585.805 | I89: =H89*(1+IF(I$3<=$O$2,$D89,$D89-($D89-$I$76)*MIN(I$3-$O$2,$Q$2)/$Q$2)) -> 10592.266 | J89: =I89*(1+IF(J$3<=$O$2,$D89,$D89-($D89-$I$76)*MIN(J$3-$O$2,$Q$2)/$Q$2)) -> 10646.798 | K89: =J89*(1+IF(K$3<=$O$2,$D89,$D89-($D89-$I$76)*MIN(K$3-$O$2,$Q$2)/$Q$2)) -> 10749.925 | L89: =K89*(1+IF(L$3<=$O$2,$D89,$D89-($D89-$I$76)*MIN(L$3-$O$2,$Q$2)/$Q$2)) -> 10902.833 | M89: =L89*(1+IF(M$3<=$O$2,$D89,$D89-($D89-$I$76)*MIN(M$3-$O$2,$Q$2)/$Q$2)) -> 11107.393 | N89: =M89*(1+IF(N$3<=$O$2,$D89,$D89-($D89-$I$76)*MIN(N$3-$O$2,$Q$2)/$Q$2)) -> 11366.195 | O89: =SUMPRODUCT(E89:N89,1/(1+$F$76)^$E$3:$N$3)*$E$2 -> 37832.957 | P89: =N89*$E$2*(1+$I$76)/($F$76-$I$76)/(1+$F$76)^$N$3 -> 68879.389 | Q89: =O89+P89 -> 106712.35 | R89: =Q89-$G$2+$I$2 -> 87252.346 | S89: =R89/$K$2 -> 155.42198 | T89: =S89-$M$2 -> -0.38770471
A90: 13 | B90: =IF(T89>0,B89,D89) -> 0.00061035156 | C90: =IF(T89>0,D89,C89) -> 0.0009765625 | D90: =(B90+C90)/2 -> 0.00079345703 | E90: =$C$2*(1+IF(E$3<=$O$2,$D90,$D90-($D90-$I$76)*MIN(E$3-$O$2,$Q$2)/$Q$2)) -> 10568.379 | F90: =E90*(1+IF(F$3<=$O$2,$D90,$D90-($D90-$I$76)*MIN(F$3-$O$2,$Q$2)/$Q$2)) -> 10576.764 | G90: =F90*(1+IF(G$3<=$O$2,$D90,$D90-($D90-$I$76)*MIN(G$3-$O$2,$Q$2)/$Q$2)) -> 10585.157 | H90: =G90*(1+IF(H$3<=$O$2,$D90,$D90-($D90-$I$76)*MIN(H$3-$O$2,$Q$2)/$Q$2)) -> 10593.556 | I90: =H90*(1+IF(I$3<=$O$2,$D90,$D90-($D90-$I$76)*MIN(I$3-$O$2,$Q$2)/$Q$2)) -> 10601.961 | J90: =I90*(1+IF(J$3<=$O$2,$D90,$D90-($D90-$I$76)*MIN(J$3-$O$2,$Q$2)/$Q$2)) -> 10658.096 | K90: =J90*(1+IF(K$3<=$O$2,$D90,$D90-($D90-$I$76)*MIN(K$3-$O$2,$Q$2)/$Q$2)) -> 10762.503 | L90: =K90*(1+IF(L$3<=$O$2,$D90,$D90-($D90-$I$76)*MIN(L$3-$O$2,$Q$2)/$Q$2)) -> 10916.379 | M90: =L90*(1+IF(M$3<=$O$2,$D90,$D90-($D90-$I$76)*MIN(M$3-$O$2,$Q$2)/$Q$2)) -> 11121.593 | N90: =M90*(1+IF(N$3<=$O$2,$D90,$D90-($D90-$I$76)*MIN(N$3-$O$2,$Q$2)/$Q$2)) -> 11380.726 | O90: =SUMPRODUCT(E90:N90,1/(1+$F$76)^$E$3:$N$3)*$E$2 -> 37863.764 | P90: =N90*$E$2*(1+$I$76)/($F$76-$I$76)/(1+$F$76)^$N$3 -> 68967.444 | Q90: =O90+P90 -> 106831.21 | R90: =Q90-$G$2+$I$2 -> 87371.208 | S90: =R90/$K$2 -> 155.63371 | T90: =S90-$M$2 -> -0.17597786
... A101: 24 | B101: =IF(T100>0,B100,D100) -> 0.00094544888 | C101: =IF(T100>0,D100,C100) -> 0.00094562769 | D101: =(B101+C101)/2 -> 0.00094553828 | E101: =$C$2*(1+IF(E$3<=$O$2,$D101,$D101-($D101-$I$76)*MIN(E$3-$O$2,$Q$2)/$Q$2)) -> 10569.985 | F101: =E101*(1+IF(F$3<=$O$2,$D101,$D101-($D101-$I$76)*MIN(F$3-$O$2,$Q$2)/$Q$2)) -> 10579.979 | G101: =F101*(1+IF(G$3<=$O$2,$D101,$D101-($D101-$I$76)*MIN(G$3-$O$2,$Q$2)/$Q$2)) -> 10589.983 | H101: =G101*(1+IF(H$3<=$O$2,$D101,$D101-($D101-$I$76)*MIN(H$3-$O$2,$Q$2)/$Q$2)) -> 10599.996 | I101: =H101*(1+IF(I$3<=$O$2,$D101,$D101-($D101-$I$76)*MIN(I$3-$O$2,$Q$2)/$Q$2)) -> 10610.019 | J101: =I101*(1+IF(J$3<=$O$2,$D101,$D101-($D101-$I$76)*MIN(J$3-$O$2,$Q$2)/$Q$2)) -> 10667.487 | K101: =J101*(1+IF(K$3<=$O$2,$D101,$D101-($D101-$I$76)*MIN(K$3-$O$2,$Q$2)/$Q$2)) -> 10772.96 | L101: =K101*(1+IF(L$3<=$O$2,$D101,$D101-($D101-$I$76)*MIN(L$3-$O$2,$Q$2)/$Q$2)) -> 10927.641 | M101: =L101*(1+IF(M$3<=$O$2,$D101,$D101-($D101-$I$76)*MIN(M$3-$O$2,$Q$2)/$Q$2)) -> 11133.398 | N101: =M101*(1+IF(N$3<=$O$2,$D101,$D101-($D101-$I$76)*MIN(N$3-$O$2,$Q$2)/$Q$2)) -> 11392.807 | O101: =SUMPRODUCT(E101:N101,1/(1+$F$76)^$E$3:$N$3)*$E$2 -> 37889.371 | P101: =N101*$E$2*(1+$I$76)/($F$76-$I$76)/(1+$F$76)^$N$3 -> 69040.654 | Q101: =O101+P101 -> 106930.02 | R101: =Q101-$G$2+$I$2 -> 87470.024 | S101: =R101/$K$2 -> 155.80973 | T101: =S101-$M$2 -> 4.2974637e-05
A103: Grid block 4: row 1, column 3 of table A (24 steps) | E103: WACC | F103: =Sensitivity!$B$10 -> 0.067017203 | G103: Terminal growth | I103: =Sensitivity!$E$9 -> 0.0283
A104: Step | B104: Low | C104: High | D104: Mid | E104: Rev Y1 | F104: Rev Y2 | G104: Rev Y3 | H104: Rev Y4 | I104: Rev Y5 | J104: Rev Y6 | K104: Rev Y7 | L104: Rev Y8 | M104: Rev Y9 | N104: Rev Y10 | O104: PV of FCF | P104: PV of TV | Q104: EV | R104: Equity | S104: Per share | T104: Value - price
A105: 1 | B105: -0.5 | C105: 1 | D105: =(B105+C105)/2 -> 0.25 | E105: =$C$2*(1+IF(E$3<=$O$2,$D105,$D105-($D105-$I$103)*MIN(E$3-$O$2,$Q$2)/$Q$2)) -> 13200 | F105: =E105*(1+IF(F$3<=$O$2,$D105,$D105-($D105-$I$103)*MIN(F$3-$O$2,$Q$2)/$Q$2)) -> 16500 | G105: =F105*(1+IF(G$3<=$O$2,$D105,$D105-($D105-$I$103)*MIN(G$3-$O$2,$Q$2)/$Q$2)) -> 20625 | H105: =G105*(1+IF(H$3<=$O$2,$D105,$D105-($D105-$I$103)*MIN(H$3-$O$2,$Q$2)/$Q$2)) -> 25781.25 | I105: =H105*(1+IF(I$3<=$O$2,$D105,$D105-($D105-$I$103)*MIN(I$3-$O$2,$Q$2)/$Q$2)) -> 32226.562 | J105: =I105*(1+IF(J$3<=$O$2,$D105,$D105-($D105-$I$103)*MIN(J$3-$O$2,$Q$2)/$Q$2)) -> 38854.277 | K105: =J105*(1+IF(K$3<=$O$2,$D105,$D105-($D105-$I$103)*MIN(K$3-$O$2,$Q$2)/$Q$2)) -> 45122.249 | L105: =K105*(1+IF(L$3<=$O$2,$D105,$D105-($D105-$I$103)*MIN(L$3-$O$2,$Q$2)/$Q$2)) -> 50400.65 | M105: =L105*(1+IF(M$3<=$O$2,$D105,$D105-($D105-$I$103)*MIN(M$3-$O$2,$Q$2)/$Q$2)) -> 54061.753 | N105: =M105*(1+IF(N$3<=$O$2,$D105,$D105-($D105-$I$103)*MIN(N$3-$O$2,$Q$2)/$Q$2)) -> 55591.701 | O105: =SUMPRODUCT(E105:N105,1/(1+$F$103)^$E$3:$N$3)*$E$2 -> 114516.48 | P105: =N105*$E$2*(1+$I$103)/($F$103-$I$103)/(1+$F$103)^$N$3 -> 382251.66 | Q105: =O105+P105 -> 496768.15 | R105: =Q105-$G$2+$I$2 -> 477308.15 | S105: =R105/$K$2 -> 850.22559 | T105: =S105-$M$2 -> 694.41591
A106: 2 | B106: =IF(T105>0,B105,D105) -> -0.5 | C106: =IF(T105>0,D105,C105) -> 0.25 | D106: =(B106+C106)/2 -> -0.125 | E106: =$C$2*(1+IF(E$3<=$O$2,$D106,$D106-($D106-$I$103)*MIN(E$3-$O$2,$Q$2)/$Q$2)) -> 9240 | F106: =E106*(1+IF(F$3<=$O$2,$D106,$D106-($D106-$I$103)*MIN(F$3-$O$2,$Q$2)/$Q$2)) -> 8085 | G106: =F106*(1+IF(G$3<=$O$2,$D106,$D106-($D106-$I$103)*MIN(G$3-$O$2,$Q$2)/$Q$2)) -> 7074.375 | H106: =G106*(1+IF(H$3<=$O$2,$D106,$D106-($D106-$I$103)*MIN(H$3-$O$2,$Q$2)/$Q$2)) -> 6190.0781 | I106: =H106*(1+IF(I$3<=$O$2,$D106,$D106-($D106-$I$103)*MIN(I$3-$O$2,$Q$2)/$Q$2)) -> 5416.3184 | J106: =I106*(1+IF(J$3<=$O$2,$D106,$D106-($D106-$I$103)*MIN(J$3-$O$2,$Q$2)/$Q$2)) -> 4905.3429 | K106: =J106*(1+IF(K$3<=$O$2,$D106,$D106-($D106-$I$103)*MIN(K$3-$O$2,$Q$2)/$Q$2)) -> 4592.9707 | L106: =K106*(1+IF(L$3<=$O$2,$D106,$D106-($D106-$I$103)*MIN(L$3-$O$2,$Q$2)/$Q$2)) -> 4441.3108 | M106: =L106*(1+IF(M$3<=$O$2,$D106,$D106-($D106-$I$103)*MIN(M$3-$O$2,$Q$2)/$Q$2)) -> 4430.8293 | N106: =M106*(1+IF(N$3<=$O$2,$D106,$D106-($D106-$I$103)*MIN(N$3-$O$2,$Q$2)/$Q$2)) -> 4556.2217 | O106: =SUMPRODUCT(E106:N106,1/(1+$F$103)^$E$3:$N$3)*$E$2 -> 21797.95 | P106: =N106*$E$2*(1+$I$103)/($F$103-$I$103)/(1+$F$103)^$N$3 -> 31328.837 | Q106: =O106+P106 -> 53126.787 | R106: =Q106-$G$2+$I$2 -> 33666.787 | S106: =R106/$K$2 -> 59.970407 | T106: =S106-$M$2 -> -95.83928
A107: 3 | B107: =IF(T106>0,B106,D106) -> -0.125 | C107: =IF(T106>0,D106,C106) -> 0.25 | D107: =(B107+C107)/2 -> 0.0625 | E107: =$C$2*(1+IF(E$3<=$O$2,$D107,$D107-($D107-$I$103)*MIN(E$3-$O$2,$Q$2)/$Q$2)) -> 11220 | F107: =E107*(1+IF(F$3<=$O$2,$D107,$D107-($D107-$I$103)*MIN(F$3-$O$2,$Q$2)/$Q$2)) -> 11921.25 | G107: =F107*(1+IF(G$3<=$O$2,$D107,$D107-($D107-$I$103)*MIN(G$3-$O$2,$Q$2)/$Q$2)) -> 12666.328 | H107: =G107*(1+IF(H$3<=$O$2,$D107,$D107-($D107-$I$103)*MIN(H$3-$O$2,$Q$2)/$Q$2)) -> 13457.974 | I107: =H107*(1+IF(I$3<=$O$2,$D107,$D107-($D107-$I$103)*MIN(I$3-$O$2,$Q$2)/$Q$2)) -> 14299.097 | J107: =I107*(1+IF(J$3<=$O$2,$D107,$D107-($D107-$I$103)*MIN(J$3-$O$2,$Q$2)/$Q$2)) -> 15094.985 | K107: =J107*(1+IF(K$3<=$O$2,$D107,$D107-($D107-$I$103)*MIN(K$3-$O$2,$Q$2)/$Q$2)) -> 15831.922 | L107: =K107*(1+IF(L$3<=$O$2,$D107,$D107-($D107-$I$103)*MIN(L$3-$O$2,$Q$2)/$Q$2)) -> 16496.546 | M107: =L107*(1+IF(M$3<=$O$2,$D107,$D107-($D107-$I$103)*MIN(M$3-$O$2,$Q$2)/$Q$2)) -> 17076.235 | N107: =M107*(1+IF(N$3<=$O$2,$D107,$D107-($D107-$I$103)*MIN(N$3-$O$2,$Q$2)/$Q$2)) -> 17559.492 | O107: =SUMPRODUCT(E107:N107,1/(1+$F$103)^$E$3:$N$3)*$E$2 -> 49990.609 | P107: =N107*$E$2*(1+$I$103)/($F$103-$I$103)/(1+$F$103)^$N$3 -> 120740.06 | Q107: =O107+P107 -> 170730.66 | R107: =Q107-$G$2+$I$2 -> 151270.66 | S107: =R107/$K$2 -> 269.45735 | T107: =S107-$M$2 -> 113.64767
A108: 4 | B108: =IF(T107>0,B107,D107) -> -0.125 | C108: =IF(T107>0,D107,C107) -> 0.0625 | D108: =(B108+C108)/2 -> -0.03125 | E108: =$C$2*(1+IF(E$3<=$O$2,$D108,$D108-($D108-$I$103)*MIN(E$3-$O$2,$Q$2)/$Q$2)) -> 10230 | F108: =E108*(1+IF(F$3<=$O$2,$D108,$D108-($D108-$I$103)*MIN(F$3-$O$2,$Q$2)/$Q$2)) -> 9910.3125 | G108: =F108*(1+IF(G$3<=$O$2,$D108,$D108-($D108-$I$103)*MIN(G$3-$O$2,$Q$2)/$Q$2)) -> 9600.6152 | H108: =G108*(1+IF(H$3<=$O$2,$D108,$D108-($D108-$I$103)*MIN(H$3-$O$2,$Q$2)/$Q$2)) -> 9300.596 | I108: =H108*(1+IF(I$3<=$O$2,$D108,$D108-($D108-$I$103)*MIN(I$3-$O$2,$Q$2)/$Q$2)) -> 9009.9524 | J108: =I108*(1+IF(J$3<=$O$2,$D108,$D108-($D108-$I$103)*MIN(J$3-$O$2,$Q$2)/$Q$2)) -> 8835.6999 | K108: =J108*(1+IF(K$3<=$O$2,$D108,$D108-($D108-$I$103)*MIN(K$3-$O$2,$Q$2)/$Q$2)) -> 8770.0507 | L108: =K108*(1+IF(L$3<=$O$2,$D108,$D108-($D108-$I$103)*MIN(L$3-$O$2,$Q$2)/$Q$2)) -> 8809.3405 | M108: =L108*(1+IF(M$3<=$O$2,$D108,$D108-($D108-$I$103)*MIN(M$3-$O$2,$Q$2)/$Q$2)) -> 8953.7256 | N108: =M108*(1+IF(N$3<=$O$2,$D108,$D108-($D108-$I$103)*MIN(N$3-$O$2,$Q$2)/$Q$2)) -> 9207.116 | O108: =SUMPRODUCT(E108:N108,1/(1+$F$103)^$E$3:$N$3)*$E$2 -> 32930.435 | P108: =N108*$E$2*(1+$I$103)/($F$103-$I$103)/(1+$F$103)^$N$3 -> 63308.648 | Q108: =O108+P108 -> 96239.083 | R108: =Q108-$G$2+$I$2 -> 76779.083 | S108: =R108/$K$2 -> 136.76603 | T108: =S108-$M$2 -> -19.043655
A109: 5 | B109: =IF(T108>0,B108,D108) -> -0.03125 | C109: =IF(T108>0,D108,C108) -> 0.0625 | D109: =(B109+C109)/2 -> 0.015625 | E109: =$C$2*(1+IF(E$3<=$O$2,$D109,$D109-($D109-$I$103)*MIN(E$3-$O$2,$Q$2)/$Q$2)) -> 10725 | F109: =E109*(1+IF(F$3<=$O$2,$D109,$D109-($D109-$I$103)*MIN(F$3-$O$2,$Q$2)/$Q$2)) -> 10892.578 | G109: =F109*(1+IF(G$3<=$O$2,$D109,$D109-($D109-$I$103)*MIN(G$3-$O$2,$Q$2)/$Q$2)) -> 11062.775 | H109: =G109*(1+IF(H$3<=$O$2,$D109,$D109-($D109-$I$103)*MIN(H$3-$O$2,$Q$2)/$Q$2)) -> 11235.631 | I109: =H109*(1+IF(I$3<=$O$2,$D109,$D109-($D109-$I$103)*MIN(I$3-$O$2,$Q$2)/$Q$2)) -> 11411.187 | J109: =I109*(1+IF(J$3<=$O$2,$D109,$D109-($D109-$I$103)*MIN(J$3-$O$2,$Q$2)/$Q$2)) -> 11618.414 | K109: =J109*(1+IF(K$3<=$O$2,$D109,$D109-($D109-$I$103)*MIN(K$3-$O$2,$Q$2)/$Q$2)) -> 11858.857 | L109: =K109*(1+IF(L$3<=$O$2,$D109,$D109-($D109-$I$103)*MIN(L$3-$O$2,$Q$2)/$Q$2)) -> 12134.339 | M109: =L109*(1+IF(M$3<=$O$2,$D109,$D109-($D109-$I$103)*MIN(M$3-$O$2,$Q$2)/$Q$2)) -> 12446.98 | N109: =M109*(1+IF(N$3<=$O$2,$D109,$D109-($D109-$I$103)*MIN(N$3-$O$2,$Q$2)/$Q$2)) -> 12799.23 | O109: =SUMPRODUCT(E109:N109,1/(1+$F$103)^$E$3:$N$3)*$E$2 -> 40563.12 | P109: =N109*$E$2*(1+$I$103)/($F$103-$I$103)/(1+$F$103)^$N$3 -> 88008.222 | Q109: =O109+P109 -> 128571.34 | R109: =Q109-$G$2+$I$2 -> 109111.34 | S109: =R109/$K$2 -> 194.35925 | T109: =S109-$M$2 -> 38.549568
A110: 6 | B110: =IF(T109>0,B109,D109) -> -0.03125 | C110: =IF(T109>0,D109,C109) -> 0.015625 | D110: =(B110+C110)/2 -> -0.0078125 | E110: =$C$2*(1+IF(E$3<=$O$2,$D110,$D110-($D110-$I$103)*MIN(E$3-$O$2,$Q$2)/$Q$2)) -> 10477.5 | F110: =E110*(1+IF(F$3<=$O$2,$D110,$D110-($D110-$I$103)*MIN(F$3-$O$2,$Q$2)/$Q$2)) -> 10395.645 | G110: =F110*(1+IF(G$3<=$O$2,$D110,$D110-($D110-$I$103)*MIN(G$3-$O$2,$Q$2)/$Q$2)) -> 10314.429 | H110: =G110*(1+IF(H$3<=$O$2,$D110,$D110-($D110-$I$103)*MIN(H$3-$O$2,$Q$2)/$Q$2)) -> 10233.847 | I110: =H110*(1+IF(I$3<=$O$2,$D110,$D110-($D110-$I$103)*MIN(I$3-$O$2,$Q$2)/$Q$2)) -> 10153.895 | J110: =I110*(1+IF(J$3<=$O$2,$D110,$D110-($D110-$I$103)*MIN(J$3-$O$2,$Q$2)/$Q$2)) -> 10147.904 | K110: =J110*(1+IF(K$3<=$O$2,$D110,$D110-($D110-$I$103)*MIN(K$3-$O$2,$Q$2)/$Q$2)) -> 10215.21 | L110: =K110*(1+IF(L$3<=$O$2,$D110,$D110-($D110-$I$103)*MIN(L$3-$O$2,$Q$2)/$Q$2)) -> 10356.742 | M110: =L110*(1+IF(M$3<=$O$2,$D110,$D110-($D110-$I$103)*MIN(M$3-$O$2,$Q$2)/$Q$2)) -> 10575.036 | N110: =M110*(1+IF(N$3<=$O$2,$D110,$D110-($D110-$I$103)*MIN(N$3-$O$2,$Q$2)/$Q$2)) -> 10874.31 | O110: =SUMPRODUCT(E110:N110,1/(1+$F$103)^$E$3:$N$3)*$E$2 -> 36544.146 | P110: =N110*$E$2*(1+$I$103)/($F$103-$I$103)/(1+$F$103)^$N$3 -> 74772.366 | Q110: =O110+P110 -> 111316.51 | R110: =Q110-$G$2+$I$2 -> 91856.512 | S110: =R110/$K$2 -> 163.62335 | T110: =S110-$M$2 -> 7.8136631
A111: 7 | B111: =IF(T110>0,B110,D110) -> -0.03125 | C111: =IF(T110>0,D110,C110) -> -0.0078125 | D111: =(B111+C111)/2 -> -0.01953125 | E111: =$C$2*(1+IF(E$3<=$O$2,$D111,$D111-($D111-$I$103)*MIN(E$3-$O$2,$Q$2)/$Q$2)) -> 10353.75 | F111: =E111*(1+IF(F$3<=$O$2,$D111,$D111-($D111-$I$103)*MIN(F$3-$O$2,$Q$2)/$Q$2)) -> 10151.528 | G111: =F111*(1+IF(G$3<=$O$2,$D111,$D111-($D111-$I$103)*MIN(G$3-$O$2,$Q$2)/$Q$2)) -> 9953.2563 | H111: =G111*(1+IF(H$3<=$O$2,$D111,$D111-($D111-$I$103)*MIN(H$3-$O$2,$Q$2)/$Q$2)) -> 9758.8567 | I111: =H111*(1+IF(I$3<=$O$2,$D111,$D111-($D111-$I$103)*MIN(I$3-$O$2,$Q$2)/$Q$2)) -> 9568.2541 | J111: =I111*(1+IF(J$3<=$O$2,$D111,$D111-($D111-$I$103)*MIN(J$3-$O$2,$Q$2)/$Q$2)) -> 9472.9064 | K111: =J111*(1+IF(K$3<=$O$2,$D111,$D111-($D111-$I$103)*MIN(K$3-$O$2,$Q$2)/$Q$2)) -> 9469.1291 | L111: =K111*(1+IF(L$3<=$O$2,$D111,$D111-($D111-$I$103)*MIN(L$3-$O$2,$Q$2)/$Q$2)) -> 9555.9373 | M111: =L111*(1+IF(M$3<=$O$2,$D111,$D111-($D111-$I$103)*MIN(M$3-$O$2,$Q$2)/$Q$2)) -> 9734.9559 | N111: =M111*(1+IF(N$3<=$O$2,$D111,$D111-($D111-$I$103)*MIN(N$3-$O$2,$Q$2)/$Q$2)) -> 10010.455 | O111: =SUMPRODUCT(E111:N111,1/(1+$F$103)^$E$3:$N$3)*$E$2 -> 34689.146 | P111: =N111*$E$2*(1+$I$103)/($F$103-$I$103)/(1+$F$103)^$N$3 -> 68832.453 | Q111: =O111+P111 -> 103521.6 | R111: =Q111-$G$2+$I$2 -> 84061.599 | S111: =R111/$K$2 -> 149.73833 | T111: =S111-$M$2 -> -6.0713609
A112: 8 | B112: =IF(T111>0,B111,D111) -> -0.01953125 | C112: =IF(T111>0,D111,C111) -> -0.0078125 | D112: =(B112+C112)/2 -> -0.013671875 | E112: =$C$2*(1+IF(E$3<=$O$2,$D112,$D112-($D112-$I$103)*MIN(E$3-$O$2,$Q$2)/$Q$2)) -> 10415.625 | F112: =E112*(1+IF(F$3<=$O$2,$D112,$D112-($D112-$I$103)*MIN(F$3-$O$2,$Q$2)/$Q$2)) -> 10273.224 | G112: =F112*(1+IF(G$3<=$O$2,$D112,$D112-($D112-$I$103)*MIN(G$3-$O$2,$Q$2)/$Q$2)) -> 10132.77 | H112: =G112*(1+IF(H$3<=$O$2,$D112,$D112-($D112-$I$103)*MIN(H$3-$O$2,$Q$2)/$Q$2)) -> 9994.2357 | I112: =H112*(1+IF(I$3<=$O$2,$D112,$D112-($D112-$I$103)*MIN(I$3-$O$2,$Q$2)/$Q$2)) -> 9857.5957 | J112: =I112*(1+IF(J$3<=$O$2,$D112,$D112-($D112-$I$103)*MIN(J$3-$O$2,$Q$2)/$Q$2)) -> 9805.5723 | K112: =J112*(1+IF(K$3<=$O$2,$D112,$D112-($D112-$I$103)*MIN(K$3-$O$2,$Q$2)/$Q$2)) -> 9836.135 | L112: =K112*(1+IF(L$3<=$O$2,$D112,$D112-($D112-$I$103)*MIN(L$3-$O$2,$Q$2)/$Q$2)) -> 9949.3612 | M112: =L112*(1+IF(M$3<=$O$2,$D112,$D112-($D112-$I$103)*MIN(M$3-$O$2,$Q$2)/$Q$2)) -> 10147.409 | N112: =M112*(1+IF(N$3<=$O$2,$D112,$D112-($D112-$I$103)*MIN(N$3-$O$2,$Q$2)/$Q$2)) -> 10434.581 | O112: =SUMPRODUCT(E112:N112,1/(1+$F$103)^$E$3:$N$3)*$E$2 -> 35604.304 | P112: =N112*$E$2*(1+$I$103)/($F$103-$I$103)/(1+$F$103)^$N$3 -> 71748.767 | Q112: =O112+P112 -> 107353.07 | R112: =Q112-$G$2+$I$2 -> 87893.072 | S112: =R112/$K$2 -> 156.5633 | T112: =S112-$M$2 -> 0.75361436
A113: 9 | B113: =IF(T112>0,B112,D112) -> -0.01953125 | C113: =IF(T112>0,D112,C112) -> -0.013671875 | D113: =(B113+C113)/2 -> -0.016601562 | E113: =$C$2*(1+IF(E$3<=$O$2,$D113,$D113-($D113-$I$103)*MIN(E$3-$O$2,$Q$2)/$Q$2)) -> 10384.688 | F113: =E113*(1+IF(F$3<=$O$2,$D113,$D113-($D113-$I$103)*MIN(F$3-$O$2,$Q$2)/$Q$2)) -> 10212.285 | G113: =F113*(1+IF(G$3<=$O$2,$D113,$D113-($D113-$I$103)*MIN(G$3-$O$2,$Q$2)/$Q$2)) -> 10042.746 | H113: =G113*(1+IF(H$3<=$O$2,$D113,$D113-($D113-$I$103)*MIN(H$3-$O$2,$Q$2)/$Q$2)) -> 9876.0203 | I113: =H113*(1+IF(I$3<=$O$2,$D113,$D113-($D113-$I$103)*MIN(I$3-$O$2,$Q$2)/$Q$2)) -> 9712.0629 | J113: =I113*(1+IF(J$3<=$O$2,$D113,$D113-($D113-$I$103)*MIN(J$3-$O$2,$Q$2)/$Q$2)) -> 9638.0449 | K113: =J113*(1+IF(K$3<=$O$2,$D113,$D113-($D113-$I$103)*MIN(K$3-$O$2,$Q$2)/$Q$2)) -> 9651.1436 | L113: =K113*(1+IF(L$3<=$O$2,$D113,$D113-($D113-$I$103)*MIN(L$3-$O$2,$Q$2)/$Q$2)) -> 9750.9304 | M113: =L113*(1+IF(M$3<=$O$2,$D113,$D113-($D113-$I$103)*MIN(M$3-$O$2,$Q$2)/$Q$2)) -> 9939.3153 | N113: =M113*(1+IF(N$3<=$O$2,$D113,$D113-($D113-$I$103)*MIN(N$3-$O$2,$Q$2)/$Q$2)) -> 10220.598 | O113: =SUMPRODUCT(E113:N113,1/(1+$F$103)^$E$3:$N$3)*$E$2 -> 35143.678 | P113: =N113*$E$2*(1+$I$103)/($F$103-$I$103)/(1+$F$103)^$N$3 -> 70277.407 | Q113: =O113+P113 -> 105421.08 | R113: =Q113-$G$2+$I$2 -> 85961.085 | S113: =R113/$K$2 -> 153.12187 | T113: =S113-$M$2 -> -2.68782
A114: 10 | B114: =IF(T113>0,B113,D113) -> -0.016601562 | C114: =IF(T113>0,D113,C113) -> -0.013671875 | D114: =(B114+C114)/2 -> -0.015136719 | E114: =$C$2*(1+IF(E$3<=$O$2,$D114,$D114-($D114-$I$103)*MIN(E$3-$O$2,$Q$2)/$Q$2)) -> 10400.156 | F114: =E114*(1+IF(F$3<=$O$2,$D114,$D114-($D114-$I$103)*MIN(F$3-$O$2,$Q$2)/$Q$2)) -> 10242.732 | G114: =F114*(1+IF(G$3<=$O$2,$D114,$D114-($D114-$I$103)*MIN(G$3-$O$2,$Q$2)/$Q$2)) -> 10087.691 | H114: =G114*(1+IF(H$3<=$O$2,$D114,$D114-($D114-$I$103)*MIN(H$3-$O$2,$Q$2)/$Q$2)) -> 9934.9961 | I114: =H114*(1+IF(I$3<=$O$2,$D114,$D114-($D114-$I$103)*MIN(I$3-$O$2,$Q$2)/$Q$2)) -> 9784.6129 | J114: =I114*(1+IF(J$3<=$O$2,$D114,$D114-($D114-$I$103)*MIN(J$3-$O$2,$Q$2)/$Q$2)) -> 9721.5082 | K114: =J114*(1+IF(K$3<=$O$2,$D114,$D114-($D114-$I$103)*MIN(K$3-$O$2,$Q$2)/$Q$2)) -> 9743.2647 | L114: =K114*(1+IF(L$3<=$O$2,$D114,$D114-($D114-$I$103)*MIN(L$3-$O$2,$Q$2)/$Q$2)) -> 9849.7129 | M114: =L114*(1+IF(M$3<=$O$2,$D114,$D114-($D114-$I$103)*MIN(M$3-$O$2,$Q$2)/$Q$2)) -> 10042.892 | N114: =M114*(1+IF(N$3<=$O$2,$D114,$D114-($D114-$I$103)*MIN(N$3-$O$2,$Q$2)/$Q$2)) -> 10327.106 | O114: =SUMPRODUCT(E114:N114,1/(1+$F$103)^$E$3:$N$3)*$E$2 -> 35373.225 | P114: =N114*$E$2*(1+$I$103)/($F$103-$I$103)/(1+$F$103)^$N$3 -> 71009.76 | Q114: =O114+P114 -> 106382.99 | R114: =Q114-$G$2+$I$2 -> 86922.985 | S114: =R114/$K$2 -> 154.83529 | T114: =S114-$M$2 -> -0.97439372
A115: 11 | B115: =IF(T114>0,B114,D114) -> -0.015136719 | C115: =IF(T114>0,D114,C114) -> -0.013671875 | D115: =(B115+C115)/2 -> -0.014404297 | E115: =$C$2*(1+IF(E$3<=$O$2,$D115,$D115-($D115-$I$103)*MIN(E$3-$O$2,$Q$2)/$Q$2)) -> 10407.891 | F115: =E115*(1+IF(F$3<=$O$2,$D115,$D115-($D115-$I$103)*MIN(F$3-$O$2,$Q$2)/$Q$2)) -> 10257.972 | G115: =F115*(1+IF(G$3<=$O$2,$D115,$D115-($D115-$I$103)*MIN(G$3-$O$2,$Q$2)/$Q$2)) -> 10110.213 | H115: =G115*(1+IF(H$3<=$O$2,$D115,$D115-($D115-$I$103)*MIN(H$3-$O$2,$Q$2)/$Q$2)) -> 9964.5829 | I115: =H115*(1+IF(I$3<=$O$2,$D115,$D115-($D115-$I$103)*MIN(I$3-$O$2,$Q$2)/$Q$2)) -> 9821.0501 | J115: =I115*(1+IF(J$3<=$O$2,$D115,$D115-($D115-$I$103)*MIN(J$3-$O$2,$Q$2)/$Q$2)) -> 9763.465 | K115: =J115*(1+IF(K$3<=$O$2,$D115,$D115-($D115-$I$103)*MIN(K$3-$O$2,$Q$2)/$Q$2)) -> 9789.6059 | L115: =K115*(1+IF(L$3<=$O$2,$D115,$D115-($D115-$I$103)*MIN(L$3-$O$2,$Q$2)/$Q$2)) -> 9899.4284 | M115: =L115*(1+IF(M$3<=$O$2,$D115,$D115-($D115-$I$103)*MIN(M$3-$O$2,$Q$2)/$Q$2)) -> 10095.033 | N115: =M115*(1+IF(N$3<=$O$2,$D115,$D115-($D115-$I$103)*MIN(N$3-$O$2,$Q$2)/$Q$2)) -> 10380.722 | O115: =SUMPRODUCT(E115:N115,1/(1+$F$103)^$E$3:$N$3)*$E$2 -> 35488.572 | P115: =N115*$E$2*(1+$I$103)/($F$103-$I$103)/(1+$F$103)^$N$3 -> 71378.429 | Q115: =O115+P115 -> 106867 | R115: =Q115-$G$2+$I$2 -> 87407.001 | S115: =R115/$K$2 -> 155.69747 | T115: =S115-$M$2 -> -0.11221923
A116: 12 | B116: =IF(T115>0,B115,D115) -> -0.014404297 | C116: =IF(T115>0,D115,C115) -> -0.013671875 | D116: =(B116+C116)/2 -> -0.014038086 | E116: =$C$2*(1+IF(E$3<=$O$2,$D116,$D116-($D116-$I$103)*MIN(E$3-$O$2,$Q$2)/$Q$2)) -> 10411.758 | F116: =E116*(1+IF(F$3<=$O$2,$D116,$D116-($D116-$I$103)*MIN(F$3-$O$2,$Q$2)/$Q$2)) -> 10265.597 | G116: =F116*(1+IF(G$3<=$O$2,$D116,$D116-($D116-$I$103)*MIN(G$3-$O$2,$Q$2)/$Q$2)) -> 10121.487 | H116: =G116*(1+IF(H$3<=$O$2,$D116,$D116-($D116-$I$103)*MIN(H$3-$O$2,$Q$2)/$Q$2)) -> 9979.401 | I116: =H116*(1+IF(I$3<=$O$2,$D116,$D116-($D116-$I$103)*MIN(I$3-$O$2,$Q$2)/$Q$2)) -> 9839.3093 | J116: =I116*(1+IF(J$3<=$O$2,$D116,$D116-($D116-$I$103)*MIN(J$3-$O$2,$Q$2)/$Q$2)) -> 9784.4998 | K116: =J116*(1+IF(K$3<=$O$2,$D116,$D116-($D116-$I$103)*MIN(K$3-$O$2,$Q$2)/$Q$2)) -> 9812.8469 | L116: =K116*(1+IF(L$3<=$O$2,$D116,$D116-($D116-$I$103)*MIN(L$3-$O$2,$Q$2)/$Q$2)) -> 9924.3676 | M116: =L116*(1+IF(M$3<=$O$2,$D116,$D116-($D116-$I$103)*MIN(M$3-$O$2,$Q$2)/$Q$2)) -> 10121.191 | N116: =M116*(1+IF(N$3<=$O$2,$D116,$D116-($D116-$I$103)*MIN(N$3-$O$2,$Q$2)/$Q$2)) -> 10407.621 | O116: =SUMPRODUCT(E116:N116,1/(1+$F$103)^$E$3:$N$3)*$E$2 -> 35546.39 | P116: =N116*$E$2*(1+$I$103)/($F$103-$I$103)/(1+$F$103)^$N$3 -> 71563.389 | Q116: =O116+P116 -> 107109.78 | R116: =Q116-$G$2+$I$2 -> 87649.779 | S116: =R116/$K$2 -> 156.12993 | T116: =S116-$M$2 -> 0.32023932
A117: 13 | B117: =IF(T116>0,B116,D116) -> -0.014404297 | C117: =IF(T116>0,D116,C116) -> -0.014038086 | D117: =(B117+C117)/2 -> -0.014221191 | E117: =$C$2*(1+IF(E$3<=$O$2,$D117,$D117-($D117-$I$103)*MIN(E$3-$O$2,$Q$2)/$Q$2)) -> 10409.824 | F117: =E117*(1+IF(F$3<=$O$2,$D117,$D117-($D117-$I$103)*MIN(F$3-$O$2,$Q$2)/$Q$2)) -> 10261.784 | G117: =F117*(1+IF(G$3<=$O$2,$D117,$D117-($D117-$I$103)*MIN(G$3-$O$2,$Q$2)/$Q$2)) -> 10115.849 | H117: =G117*(1+IF(H$3<=$O$2,$D117,$D117-($D117-$I$103)*MIN(H$3-$O$2,$Q$2)/$Q$2)) -> 9971.9899 | I117: =H117*(1+IF(I$3<=$O$2,$D117,$D117-($D117-$I$103)*MIN(I$3-$O$2,$Q$2)/$Q$2)) -> 9830.1763 | J117: =I117*(1+IF(J$3<=$O$2,$D117,$D117-($D117-$I$103)*MIN(J$3-$O$2,$Q$2)/$Q$2)) -> 9773.9777 | K117: =J117*(1+IF(K$3<=$O$2,$D117,$D117-($D117-$I$103)*MIN(K$3-$O$2,$Q$2)/$Q$2)) -> 9801.2205 | L117: =K117*(1+IF(L$3<=$O$2,$D117,$D117-($D117-$I$103)*MIN(L$3-$O$2,$Q$2)/$Q$2)) -> 9911.8912 | M117: =L117*(1+IF(M$3<=$O$2,$D117,$D117-($D117-$I$103)*MIN(M$3-$O$2,$Q$2)/$Q$2)) -> 10108.105 | N117: =M117*(1+IF(N$3<=$O$2,$D117,$D117-($D117-$I$103)*MIN(N$3-$O$2,$Q$2)/$Q$2)) -> 10394.164 | O117: =SUMPRODUCT(E117:N117,1/(1+$F$103)^$E$3:$N$3)*$E$2 -> 35517.469 | P117: =N117*$E$2*(1+$I$103)/($F$103-$I$103)/(1+$F$103)^$N$3 -> 71470.857 | Q117: =O117+P117 -> 106988.33 | R117: =Q117-$G$2+$I$2 -> 87528.326 | S117: =R117/$K$2 -> 155.91358 | T117: =S117-$M$2 -> 0.10389559
... A128: 24 | B128: =IF(T127>0,B127,D127) -> -0.014309347 | C128: =IF(T127>0,D127,C127) -> -0.014309168 | D128: =(B128+C128)/2 -> -0.014309257 | E128: =$C$2*(1+IF(E$3<=$O$2,$D128,$D128-($D128-$I$103)*MIN(E$3-$O$2,$Q$2)/$Q$2)) -> 10408.894 | F128: =E128*(1+IF(F$3<=$O$2,$D128,$D128-($D128-$I$103)*MIN(F$3-$O$2,$Q$2)/$Q$2)) -> 10259.951 | G128: =F128*(1+IF(G$3<=$O$2,$D128,$D128-($D128-$I$103)*MIN(G$3-$O$2,$Q$2)/$Q$2)) -> 10113.138 | H128: =G128*(1+IF(H$3<=$O$2,$D128,$D128-($D128-$I$103)*MIN(H$3-$O$2,$Q$2)/$Q$2)) -> 9968.4269 | I128: =H128*(1+IF(I$3<=$O$2,$D128,$D128-($D128-$I$103)*MIN(I$3-$O$2,$Q$2)/$Q$2)) -> 9825.7861 | J128: =I128*(1+IF(J$3<=$O$2,$D128,$D128-($D128-$I$103)*MIN(J$3-$O$2,$Q$2)/$Q$2)) -> 9768.9203 | K128: =J128*(1+IF(K$3<=$O$2,$D128,$D128-($D128-$I$103)*MIN(K$3-$O$2,$Q$2)/$Q$2)) -> 9795.6329 | L128: =K128*(1+IF(L$3<=$O$2,$D128,$D128-($D128-$I$103)*MIN(L$3-$O$2,$Q$2)/$Q$2)) -> 9905.8955 | M128: =L128*(1+IF(M$3<=$O$2,$D128,$D128-($D128-$I$103)*MIN(M$3-$O$2,$Q$2)/$Q$2)) -> 10101.816 | N128: =M128*(1+IF(N$3<=$O$2,$D128,$D128-($D128-$I$103)*MIN(N$3-$O$2,$Q$2)/$Q$2)) -> 10387.697 | O128: =SUMPRODUCT(E128:N128,1/(1+$F$103)^$E$3:$N$3)*$E$2 -> 35503.568 | P128: =N128*$E$2*(1+$I$103)/($F$103-$I$103)/(1+$F$103)^$N$3 -> 71426.39 | Q128: =O128+P128 -> 106929.96 | R128: =Q128-$G$2+$I$2 -> 87469.958 | S128: =R128/$K$2 -> 155.80961 | T128: =S128-$M$2 -> -7.4911114e-05
A130: Grid block 5: row 1, column 4 of table A (24 steps) | E130: WACC | F130: =Sensitivity!$B$10 -> 0.067017203 | G130: Terminal growth | I130: =Sensitivity!$F$9 -> 0.0333
A131: Step | B131: Low | C131: High | D131: Mid | E131: Rev Y1 | F131: Rev Y2 | G131: Rev Y3 | H131: Rev Y4 | I131: Rev Y5 | J131: Rev Y6 | K131: Rev Y7 | L131: Rev Y8 | M131: Rev Y9 | N131: Rev Y10 | O131: PV of FCF | P131: PV of TV | Q131: EV | R131: Equity | S131: Per share | T131: Value - price
A132: 1 | B132: -0.5 | C132: 1 | D132: =(B132+C132)/2 -> 0.25 | E132: =$C$2*(1+IF(E$3<=$O$2,$D132,$D132-($D132-$I$130)*MIN(E$3-$O$2,$Q$2)/$Q$2)) -> 13200 | F132: =E132*(1+IF(F$3<=$O$2,$D132,$D132-($D132-$I$130)*MIN(F$3-$O$2,$Q$2)/$Q$2)) -> 16500 | G132: =F132*(1+IF(G$3<=$O$2,$D132,$D132-($D132-$I$130)*MIN(G$3-$O$2,$Q$2)/$Q$2)) -> 20625 | H132: =G132*(1+IF(H$3<=$O$2,$D132,$D132-($D132-$I$130)*MIN(H$3-$O$2,$Q$2)/$Q$2)) -> 25781.25 | I132: =H132*(1+IF(I$3<=$O$2,$D132,$D132-($D132-$I$130)*MIN(I$3-$O$2,$Q$2)/$Q$2)) -> 32226.562 | J132: =I132*(1+IF(J$3<=$O$2,$D132,$D132-($D132-$I$130)*MIN(J$3-$O$2,$Q$2)/$Q$2)) -> 38886.504 | K132: =J132*(1+IF(K$3<=$O$2,$D132,$D132-($D132-$I$130)*MIN(K$3-$O$2,$Q$2)/$Q$2)) -> 45237.448 | L132: =K132*(1+IF(L$3<=$O$2,$D132,$D132-($D132-$I$130)*MIN(L$3-$O$2,$Q$2)/$Q$2)) -> 50665.037 | M132: =L132*(1+IF(M$3<=$O$2,$D132,$D132-($D132-$I$130)*MIN(M$3-$O$2,$Q$2)/$Q$2)) -> 54548.005 | N132: =M132*(1+IF(N$3<=$O$2,$D132,$D132-($D132-$I$130)*MIN(N$3-$O$2,$Q$2)/$Q$2)) -> 56364.454 | O132: =SUMPRODUCT(E132:N132,1/(1+$F$130)^$E$3:$N$3)*$E$2 -> 114975.84 | P132: =N132*$E$2*(1+$I$130)/($F$130-$I$130)/(1+$F$130)^$N$3 -> 447202.02 | Q132: =O132+P132 -> 562177.86 | R132: =Q132-$G$2+$I$2 -> 542717.86 | S132: =R132/$K$2 -> 966.73945 | T132: =S132-$M$2 -> 810.92977
A133: 2 | B133: =IF(T132>0,B132,D132) -> -0.5 | C133: =IF(T132>0,D132,C132) -> 0.25 | D133: =(B133+C133)/2 -> -0.125 | E133: =$C$2*(1+IF(E$3<=$O$2,$D133,$D133-($D133-$I$130)*MIN(E$3-$O$2,$Q$2)/$Q$2)) -> 9240 | F133: =E133*(1+IF(F$3<=$O$2,$D133,$D133-($D133-$I$130)*MIN(F$3-$O$2,$Q$2)/$Q$2)) -> 8085 | G133: =F133*(1+IF(G$3<=$O$2,$D133,$D133-($D133-$I$130)*MIN(G$3-$O$2,$Q$2)/$Q$2)) -> 7074.375 | H133: =G133*(1+IF(H$3<=$O$2,$D133,$D133-($D133-$I$130)*MIN(H$3-$O$2,$Q$2)/$Q$2)) -> 6190.0781 | I133: =H133*(1+IF(I$3<=$O$2,$D133,$D133-($D133-$I$130)*MIN(I$3-$O$2,$Q$2)/$Q$2)) -> 5416.3184 | J133: =I133*(1+IF(J$3<=$O$2,$D133,$D133-($D133-$I$130)*MIN(J$3-$O$2,$Q$2)/$Q$2)) -> 4910.7592 | K133: =J133*(1+IF(K$3<=$O$2,$D133,$D133-($D133-$I$130)*MIN(K$3-$O$2,$Q$2)/$Q$2)) -> 4607.8636 | L133: =K133*(1+IF(L$3<=$O$2,$D133,$D133-($D133-$I$130)*MIN(L$3-$O$2,$Q$2)/$Q$2)) -> 4469.5355 | M133: =L133*(1+IF(M$3<=$O$2,$D133,$D133-($D133-$I$130)*MIN(M$3-$O$2,$Q$2)/$Q$2)) -> 4476.8655 | N133: =M133*(1+IF(N$3<=$O$2,$D133,$D133-($D133-$I$130)*MIN(N$3-$O$2,$Q$2)/$Q$2)) -> 4625.9452 | O133: =SUMPRODUCT(E133:N133,1/(1+$F$130)^$E$3:$N$3)*$E$2 -> 21843.539 | P133: =N133*$E$2*(1+$I$130)/($F$130-$I$130)/(1+$F$130)^$N$3 -> 36702.778 | Q133: =O133+P133 -> 58546.317 | R133: =Q133-$G$2+$I$2 -> 39086.317 | S133: =R133/$K$2 -> 69.624177 | T133: =S133-$M$2 -> -86.18551
A134: 3 | B134: =IF(T133>0,B133,D133) -> -0.125 | C134: =IF(T133>0,D133,C133) -> 0.25 | D134: =(B134+C134)/2 -> 0.0625 | E134: =$C$2*(1+IF(E$3<=$O$2,$D134,$D134-($D134-$I$130)*MIN(E$3-$O$2,$Q$2)/$Q$2)) -> 11220 | F134: =E134*(1+IF(F$3<=$O$2,$D134,$D134-($D134-$I$130)*MIN(F$3-$O$2,$Q$2)/$Q$2)) -> 11921.25 | G134: =F134*(1+IF(G$3<=$O$2,$D134,$D134-($D134-$I$130)*MIN(G$3-$O$2,$Q$2)/$Q$2)) -> 12666.328 | H134: =G134*(1+IF(H$3<=$O$2,$D134,$D134-($D134-$I$130)*MIN(H$3-$O$2,$Q$2)/$Q$2)) -> 13457.974 | I134: =H134*(1+IF(I$3<=$O$2,$D134,$D134-($D134-$I$130)*MIN(I$3-$O$2,$Q$2)/$Q$2)) -> 14299.097 | J134: =I134*(1+IF(J$3<=$O$2,$D134,$D134-($D134-$I$130)*MIN(J$3-$O$2,$Q$2)/$Q$2)) -> 15109.284 | K134: =J134*(1+IF(K$3<=$O$2,$D134,$D134-($D134-$I$130)*MIN(K$3-$O$2,$Q$2)/$Q$2)) -> 15877.138 | L134: =K134*(1+IF(L$3<=$O$2,$D134,$D134-($D134-$I$130)*MIN(L$3-$O$2,$Q$2)/$Q$2)) -> 16591.291 | M134: =L134*(1+IF(M$3<=$O$2,$D134,$D134-($D134-$I$130)*MIN(M$3-$O$2,$Q$2)/$Q$2)) -> 17240.674 | N134: =M134*(1+IF(N$3<=$O$2,$D134,$D134-($D134-$I$130)*MIN(N$3-$O$2,$Q$2)/$Q$2)) -> 17814.789 | O134: =SUMPRODUCT(E134:N134,1/(1+$F$130)^$E$3:$N$3)*$E$2 -> 50149.076 | P134: =N134*$E$2*(1+$I$130)/($F$130-$I$130)/(1+$F$130)^$N$3 -> 141344.57 | Q134: =O134+P134 -> 191493.65 | R134: =Q134-$G$2+$I$2 -> 172033.65 | S134: =R134/$K$2 -> 306.44231 | T134: =S134-$M$2 -> 150.63262
A135: 4 | B135: =IF(T134>0,B134,D134) -> -0.125 | C135: =IF(T134>0,D134,C134) -> 0.0625 | D135: =(B135+C135)/2 -> -0.03125 | E135: =$C$2*(1+IF(E$3<=$O$2,$D135,$D135-($D135-$I$130)*MIN(E$3-$O$2,$Q$2)/$Q$2)) -> 10230 | F135: =E135*(1+IF(F$3<=$O$2,$D135,$D135-($D135-$I$130)*MIN(F$3-$O$2,$Q$2)/$Q$2)) -> 9910.3125 | G135: =F135*(1+IF(G$3<=$O$2,$D135,$D135-($D135-$I$130)*MIN(G$3-$O$2,$Q$2)/$Q$2)) -> 9600.6152 | H135: =G135*(1+IF(H$3<=$O$2,$D135,$D135-($D135-$I$130)*MIN(H$3-$O$2,$Q$2)/$Q$2)) -> 9300.596 | I135: =H135*(1+IF(I$3<=$O$2,$D135,$D135-($D135-$I$130)*MIN(I$3-$O$2,$Q$2)/$Q$2)) -> 9009.9524 | J135: =I135*(1+IF(J$3<=$O$2,$D135,$D135-($D135-$I$130)*MIN(J$3-$O$2,$Q$2)/$Q$2)) -> 8844.7099 | K135: =J135*(1+IF(K$3<=$O$2,$D135,$D135-($D135-$I$130)*MIN(K$3-$O$2,$Q$2)/$Q$2)) -> 8796.6831 | L135: =K135*(1+IF(L$3<=$O$2,$D135,$D135-($D135-$I$130)*MIN(L$3-$O$2,$Q$2)/$Q$2)) -> 8862.4823 | M135: =L135*(1+IF(M$3<=$O$2,$D135,$D135-($D135-$I$130)*MIN(M$3-$O$2,$Q$2)/$Q$2)) -> 9043.1883 | N135: =M135*(1+IF(N$3<=$O$2,$D135,$D135-($D135-$I$130)*MIN(N$3-$O$2,$Q$2)/$Q$2)) -> 9344.3265 | O135: =SUMPRODUCT(E135:N135,1/(1+$F$130)^$E$3:$N$3)*$E$2 -> 33017.736 | P135: =N135*$E$2*(1+$I$130)/($F$130-$I$130)/(1+$F$130)^$N$3 -> 74138.954 | Q135: =O135+P135 -> 107156.69 | R135: =Q135-$G$2+$I$2 -> 87696.69 | S135: =R135/$K$2 -> 156.21349 | T135: =S135-$M$2 -> 0.40380051
A136: 5 | B136: =IF(T135>0,B135,D135) -> -0.125 | C136: =IF(T135>0,D135,C135) -> -0.03125 | D136: =(B136+C136)/2 -> -0.078125 | E136: =$C$2*(1+IF(E$3<=$O$2,$D136,$D136-($D136-$I$130)*MIN(E$3-$O$2,$Q$2)/$Q$2)) -> 9735 | F136: =E136*(1+IF(F$3<=$O$2,$D136,$D136-($D136-$I$130)*MIN(F$3-$O$2,$Q$2)/$Q$2)) -> 8974.4531 | G136: =F136*(1+IF(G$3<=$O$2,$D136,$D136-($D136-$I$130)*MIN(G$3-$O$2,$Q$2)/$Q$2)) -> 8273.324 | H136: =G136*(1+IF(H$3<=$O$2,$D136,$D136-($D136-$I$130)*MIN(H$3-$O$2,$Q$2)/$Q$2)) -> 7626.9705 | I136: =H136*(1+IF(I$3<=$O$2,$D136,$D136-($D136-$I$130)*MIN(I$3-$O$2,$Q$2)/$Q$2)) -> 7031.1135 | J136: =I136*(1+IF(J$3<=$O$2,$D136,$D136-($D136-$I$130)*MIN(J$3-$O$2,$Q$2)/$Q$2)) -> 6638.4961 | K136: =J136*(1+IF(K$3<=$O$2,$D136,$D136-($D136-$I$130)*MIN(K$3-$O$2,$Q$2)/$Q$2)) -> 6415.7414 | L136: =K136*(1+IF(L$3<=$O$2,$D136,$D136-($D136-$I$130)*MIN(L$3-$O$2,$Q$2)/$Q$2)) -> 6343.4359 | M136: =L136*(1+IF(M$3<=$O$2,$D136,$D136-($D136-$I$130)*MIN(M$3-$O$2,$Q$2)/$Q$2)) -> 6413.3089 | N136: =M136*(1+IF(N$3<=$O$2,$D136,$D136-($D136-$I$130)*MIN(N$3-$O$2,$Q$2)/$Q$2)) -> 6626.8721 | O136: =SUMPRODUCT(E136:N136,1/(1+$F$130)^$E$3:$N$3)*$E$2 -> 26829.962 | P136: =N136*$E$2*(1+$I$130)/($F$130-$I$130)/(1+$F$130)^$N$3 -> 52578.36 | Q136: =O136+P136 -> 79408.322 | R136: =Q136-$G$2+$I$2 -> 59948.322 | S136: =R136/$K$2 -> 106.78552 | T136: =S136-$M$2 -> -49.024169
A137: 6 | B137: =IF(T136>0,B136,D136) -> -0.078125 | C137: =IF(T136>0,D136,C136) -> -0.03125 | D137: =(B137+C137)/2 -> -0.0546875 | E137: =$C$2*(1+IF(E$3<=$O$2,$D137,$D137-($D137-$I$130)*MIN(E$3-$O$2,$Q$2)/$Q$2)) -> 9982.5 | F137: =E137*(1+IF(F$3<=$O$2,$D137,$D137-($D137-$I$130)*MIN(F$3-$O$2,$Q$2)/$Q$2)) -> 9436.582 | G137: =F137*(1+IF(G$3<=$O$2,$D137,$D137-($D137-$I$130)*MIN(G$3-$O$2,$Q$2)/$Q$2)) -> 8920.519 | H137: =G137*(1+IF(H$3<=$O$2,$D137,$D137-($D137-$I$130)*MIN(H$3-$O$2,$Q$2)/$Q$2)) -> 8432.6781 | I137: =H137*(1+IF(I$3<=$O$2,$D137,$D137-($D137-$I$130)*MIN(I$3-$O$2,$Q$2)/$Q$2)) -> 7971.516 | J137: =I137*(1+IF(J$3<=$O$2,$D137,$D137-($D137-$I$130)*MIN(J$3-$O$2,$Q$2)/$Q$2)) -> 7675.8525 | K137: =J137*(1+IF(K$3<=$O$2,$D137,$D137-($D137-$I$130)*MIN(K$3-$O$2,$Q$2)/$Q$2)) -> 7526.2309 | L137: =K137*(1+IF(L$3<=$O$2,$D137,$D137-($D137-$I$130)*MIN(L$3-$O$2,$Q$2)/$Q$2)) -> 7511.9687 | M137: =L137*(1+IF(M$3<=$O$2,$D137,$D137-($D137-$I$130)*MIN(M$3-$O$2,$Q$2)/$Q$2)) -> 7629.9254 | N137: =M137*(1+IF(N$3<=$O$2,$D137,$D137-($D137-$I$130)*MIN(N$3-$O$2,$Q$2)/$Q$2)) -> 7884.0019 | O137: =SUMPRODUCT(E137:N137,1/(1+$F$130)^$E$3:$N$3)*$E$2 -> 29757.677 | P137: =N137*$E$2*(1+$I$130)/($F$130-$I$130)/(1+$F$130)^$N$3 -> 62552.572 | Q137: =O137+P137 -> 92310.249 | R137: =Q137-$G$2+$I$2 -> 72850.249 | S137: =R137/$K$2 -> 129.76763 | T137: =S137-$M$2 -> -26.042058
A138: 7 | B138: =IF(T137>0,B137,D137) -> -0.0546875 | C138: =IF(T137>0,D137,C137) -> -0.03125 | D138: =(B138+C138)/2 -> -0.04296875 | E138: =$C$2*(1+IF(E$3<=$O$2,$D138,$D138-($D138-$I$130)*MIN(E$3-$O$2,$Q$2)/$Q$2)) -> 10106.25 | F138: =E138*(1+IF(F$3<=$O$2,$D138,$D138-($D138-$I$130)*MIN(F$3-$O$2,$Q$2)/$Q$2)) -> 9671.9971 | G138: =F138*(1+IF(G$3<=$O$2,$D138,$D138-($D138-$I$130)*MIN(G$3-$O$2,$Q$2)/$Q$2)) -> 9256.4034 | H138: =G138*(1+IF(H$3<=$O$2,$D138,$D138-($D138-$I$130)*MIN(H$3-$O$2,$Q$2)/$Q$2)) -> 8858.6674 | I138: =H138*(1+IF(I$3<=$O$2,$D138,$D138-($D138-$I$130)*MIN(I$3-$O$2,$Q$2)/$Q$2)) -> 8478.0215 | J138: =I138*(1+IF(J$3<=$O$2,$D138,$D138-($D138-$I$130)*MIN(J$3-$O$2,$Q$2)/$Q$2)) -> 8243.0531 | K138: =J138*(1+IF(K$3<=$O$2,$D138,$D138-($D138-$I$130)*MIN(K$3-$O$2,$Q$2)/$Q$2)) -> 8140.3344 | L138: =K138*(1+IF(L$3<=$O$2,$D138,$D138-($D138-$I$130)*MIN(L$3-$O$2,$Q$2)/$Q$2)) -> 8163.0663 | M138: =L138*(1+IF(M$3<=$O$2,$D138,$D138-($D138-$I$130)*MIN(M$3-$O$2,$Q$2)/$Q$2)) -> 8310.379 | N138: =M138*(1+IF(N$3<=$O$2,$D138,$D138-($D138-$I$130)*MIN(N$3-$O$2,$Q$2)/$Q$2)) -> 8587.1146 | O138: =SUMPRODUCT(E138:N138,1/(1+$F$130)^$E$3:$N$3)*$E$2 -> 31344 | P138: =N138*$E$2*(1+$I$130)/($F$130-$I$130)/(1+$F$130)^$N$3 -> 68131.149 | Q138: =O138+P138 -> 99475.149 | R138: =Q138-$G$2+$I$2 -> 80015.149 | S138: =R138/$K$2 -> 142.53041 | T138: =S138-$M$2 -> -13.279273
A139: 8 | B139: =IF(T138>0,B138,D138) -> -0.04296875 | C139: =IF(T138>0,D138,C138) -> -0.03125 | D139: =(B139+C139)/2 -> -0.037109375 | E139: =$C$2*(1+IF(E$3<=$O$2,$D139,$D139-($D139-$I$130)*MIN(E$3-$O$2,$Q$2)/$Q$2)) -> 10168.125 | F139: =E139*(1+IF(F$3<=$O$2,$D139,$D139-($D139-$I$130)*MIN(F$3-$O$2,$Q$2)/$Q$2)) -> 9790.7922 | G139: =F139*(1+IF(G$3<=$O$2,$D139,$D139-($D139-$I$130)*MIN(G$3-$O$2,$Q$2)/$Q$2)) -> 9427.4621 | H139: =G139*(1+IF(H$3<=$O$2,$D139,$D139-($D139-$I$130)*MIN(H$3-$O$2,$Q$2)/$Q$2)) -> 9077.6148 | I139: =H139*(1+IF(I$3<=$O$2,$D139,$D139-($D139-$I$130)*MIN(I$3-$O$2,$Q$2)/$Q$2)) -> 8740.7502 | J139: =I139*(1+IF(J$3<=$O$2,$D139,$D139-($D139-$I$130)*MIN(J$3-$O$2,$Q$2)/$Q$2)) -> 8539.4726 | K139: =J139*(1+IF(K$3<=$O$2,$D139,$D139-($D139-$I$130)*MIN(K$3-$O$2,$Q$2)/$Q$2)) -> 8463.0817 | L139: =K139*(1+IF(L$3<=$O$2,$D139,$D139-($D139-$I$130)*MIN(L$3-$O$2,$Q$2)/$Q$2)) -> 8506.5502 | M139: =L139*(1+IF(M$3<=$O$2,$D139,$D139-($D139-$I$130)*MIN(M$3-$O$2,$Q$2)/$Q$2)) -> 8670.0301 | N139: =M139*(1+IF(N$3<=$O$2,$D139,$D139-($D139-$I$130)*MIN(N$3-$O$2,$Q$2)/$Q$2)) -> 8958.7421 | O139: =SUMPRODUCT(E139:N139,1/(1+$F$130)^$E$3:$N$3)*$E$2 -> 32169.66 | P139: =N139*$E$2*(1+$I$130)/($F$130-$I$130)/(1+$F$130)^$N$3 -> 71079.684 | Q139: =O139+P139 -> 103249.34 | R139: =Q139-$G$2+$I$2 -> 83789.344 | S139: =R139/$K$2 -> 149.25336 | T139: =S139-$M$2 -> -6.556326
A140: 9 | B140: =IF(T139>0,B139,D139) -> -0.037109375 | C140: =IF(T139>0,D139,C139) -> -0.03125 | D140: =(B140+C140)/2 -> -0.034179688 | E140: =$C$2*(1+IF(E$3<=$O$2,$D140,$D140-($D140-$I$130)*MIN(E$3-$O$2,$Q$2)/$Q$2)) -> 10199.062 | F140: =E140*(1+IF(F$3<=$O$2,$D140,$D140-($D140-$I$130)*MIN(F$3-$O$2,$Q$2)/$Q$2)) -> 9850.4617 | G140: =F140*(1+IF(G$3<=$O$2,$D140,$D140-($D140-$I$130)*MIN(G$3-$O$2,$Q$2)/$Q$2)) -> 9513.776 | H140: =G140*(1+IF(H$3<=$O$2,$D140,$D140-($D140-$I$130)*MIN(H$3-$O$2,$Q$2)/$Q$2)) -> 9188.5981 | I140: =H140*(1+IF(I$3<=$O$2,$D140,$D140-($D140-$I$130)*MIN(I$3-$O$2,$Q$2)/$Q$2)) -> 8874.5347 | J140: =I140*(1+IF(J$3<=$O$2,$D140,$D140-($D140-$I$130)*MIN(J$3-$O$2,$Q$2)/$Q$2)) -> 8690.9761 | K140: =J140*(1+IF(K$3<=$O$2,$D140,$D140-($D140-$I$130)*MIN(K$3-$O$2,$Q$2)/$Q$2)) -> 8628.507 | L140: =K140*(1+IF(L$3<=$O$2,$D140,$D140-($D140-$I$130)*MIN(L$3-$O$2,$Q$2)/$Q$2)) -> 8682.9367 | M140: =L140*(1+IF(M$3<=$O$2,$D140,$D140-($D140-$I$130)*MIN(M$3-$O$2,$Q$2)/$Q$2)) -> 8854.8941 | N140: =M140*(1+IF(N$3<=$O$2,$D140,$D140-($D140-$I$130)*MIN(N$3-$O$2,$Q$2)/$Q$2)) -> 9149.7621 | O140: =SUMPRODUCT(E140:N140,1/(1+$F$130)^$E$3:$N$3)*$E$2 -> 32590.86 | P140: =N140*$E$2*(1+$I$130)/($F$130-$I$130)/(1+$F$130)^$N$3 -> 72595.258 | Q140: =O140+P140 -> 105186.12 | R140: =Q140-$G$2+$I$2 -> 85726.118 | S140: =R140/$K$2 -> 152.70332 | T140: =S140-$M$2 -> -3.1063646
A141: 10 | B141: =IF(T140>0,B140,D140) -> -0.034179688 | C141: =IF(T140>0,D140,C140) -> -0.03125 | D141: =(B141+C141)/2 -> -0.032714844 | E141: =$C$2*(1+IF(E$3<=$O$2,$D141,$D141-($D141-$I$130)*MIN(E$3-$O$2,$Q$2)/$Q$2)) -> 10214.531 | F141: =E141*(1+IF(F$3<=$O$2,$D141,$D141-($D141-$I$130)*MIN(F$3-$O$2,$Q$2)/$Q$2)) -> 9880.3645 | G141: =F141*(1+IF(G$3<=$O$2,$D141,$D141-($D141-$I$130)*MIN(G$3-$O$2,$Q$2)/$Q$2)) -> 9557.1299 | H141: =G141*(1+IF(H$3<=$O$2,$D141,$D141-($D141-$I$130)*MIN(H$3-$O$2,$Q$2)/$Q$2)) -> 9244.4699 | I141: =H141*(1+IF(I$3<=$O$2,$D141,$D141-($D141-$I$130)*MIN(I$3-$O$2,$Q$2)/$Q$2)) -> 8942.0385 | J141: =I141*(1+IF(J$3<=$O$2,$D141,$D141-($D141-$I$130)*MIN(J$3-$O$2,$Q$2)/$Q$2)) -> 8767.5625 | K141: =J141*(1+IF(K$3<=$O$2,$D141,$D141-($D141-$I$130)*MIN(K$3-$O$2,$Q$2)/$Q$2)) -> 8712.2488 | L141: =K141*(1+IF(L$3<=$O$2,$D141,$D141-($D141-$I$130)*MIN(L$3-$O$2,$Q$2)/$Q$2)) -> 8772.3116 | M141: =L141*(1+IF(M$3<=$O$2,$D141,$D141-($D141-$I$130)*MIN(M$3-$O$2,$Q$2)/$Q$2)) -> 8948.609 | N141: =M141*(1+IF(N$3<=$O$2,$D141,$D141-($D141-$I$130)*MIN(N$3-$O$2,$Q$2)/$Q$2)) -> 9246.5977 | O141: =SUMPRODUCT(E141:N141,1/(1+$F$130)^$E$3:$N$3)*$E$2 -> 32803.584 | P141: =N141*$E$2*(1+$I$130)/($F$130-$I$130)/(1+$F$130)^$N$3 -> 73363.563 | Q141: =O141+P141 -> 106167.15 | R141: =Q141-$G$2+$I$2 -> 86707.147 | S141: =R141/$K$2 -> 154.45082 | T141: =S141-$M$2 -> -1.358865
A142: 11 | B142: =IF(T141>0,B141,D141) -> -0.032714844 | C142: =IF(T141>0,D141,C141) -> -0.03125 | D142: =(B142+C142)/2 -> -0.031982422 | E142: =$C$2*(1+IF(E$3<=$O$2,$D142,$D142-($D142-$I$130)*MIN(E$3-$O$2,$Q$2)/$Q$2)) -> 10222.266 | F142: =E142*(1+IF(F$3<=$O$2,$D142,$D142-($D142-$I$130)*MIN(F$3-$O$2,$Q$2)/$Q$2)) -> 9895.3328 | G142: =F142*(1+IF(G$3<=$O$2,$D142,$D142-($D142-$I$130)*MIN(G$3-$O$2,$Q$2)/$Q$2)) -> 9578.8561 | H142: =G142*(1+IF(H$3<=$O$2,$D142,$D142-($D142-$I$130)*MIN(H$3-$O$2,$Q$2)/$Q$2)) -> 9272.5011 | I142: =H142*(1+IF(I$3<=$O$2,$D142,$D142-($D142-$I$130)*MIN(I$3-$O$2,$Q$2)/$Q$2)) -> 8975.944 | J142: =I142*(1+IF(J$3<=$O$2,$D142,$D142-($D142-$I$130)*MIN(J$3-$O$2,$Q$2)/$Q$2)) -> 8806.0659 | K142: =J142*(1+IF(K$3<=$O$2,$D142,$D142-($D142-$I$130)*MIN(K$3-$O$2,$Q$2)/$Q$2)) -> 8754.3791 | L142: =K142*(1+IF(L$3<=$O$2,$D142,$D142-($D142-$I$130)*MIN(L$3-$O$2,$Q$2)/$Q$2)) -> 8817.2971 | M142: =L142*(1+IF(M$3<=$O$2,$D142,$D142-($D142-$I$130)*MIN(M$3-$O$2,$Q$2)/$Q$2)) -> 8995.7902 | N142: =M142*(1+IF(N$3<=$O$2,$D142,$D142-($D142-$I$130)*MIN(N$3-$O$2,$Q$2)/$Q$2)) -> 9295.35 | O142: =SUMPRODUCT(E142:N142,1/(1+$F$130)^$E$3:$N$3)*$E$2 -> 32910.481 | P142: =N142*$E$2*(1+$I$130)/($F$130-$I$130)/(1+$F$130)^$N$3 -> 73750.369 | Q142: =O142+P142 -> 106660.85 | R142: =Q142-$G$2+$I$2 -> 87200.85 | S142: =R142/$K$2 -> 155.33025 | T142: =S142-$M$2 -> -0.47943517
A143: 12 | B143: =IF(T142>0,B142,D142) -> -0.031982422 | C143: =IF(T142>0,D142,C142) -> -0.03125 | D143: =(B143+C143)/2 -> -0.031616211 | E143: =$C$2*(1+IF(E$3<=$O$2,$D143,$D143-($D143-$I$130)*MIN(E$3-$O$2,$Q$2)/$Q$2)) -> 10226.133 | F143: =E143*(1+IF(F$3<=$O$2,$D143,$D143-($D143-$I$130)*MIN(F$3-$O$2,$Q$2)/$Q$2)) -> 9902.8212 | G143: =F143*(1+IF(G$3<=$O$2,$D143,$D143-($D143-$I$130)*MIN(G$3-$O$2,$Q$2)/$Q$2)) -> 9589.7316 | H143: =G143*(1+IF(H$3<=$O$2,$D143,$D143-($D143-$I$130)*MIN(H$3-$O$2,$Q$2)/$Q$2)) -> 9286.5406 | I143: =H143*(1+IF(I$3<=$O$2,$D143,$D143-($D143-$I$130)*MIN(I$3-$O$2,$Q$2)/$Q$2)) -> 8992.9354 | J143: =I143*(1+IF(J$3<=$O$2,$D143,$D143-($D143-$I$130)*MIN(J$3-$O$2,$Q$2)/$Q$2)) -> 8825.3703 | K143: =J143*(1+IF(K$3<=$O$2,$D143,$D143-($D143-$I$130)*MIN(K$3-$O$2,$Q$2)/$Q$2)) -> 8775.5093 | L143: =K143*(1+IF(L$3<=$O$2,$D143,$D143-($D143-$I$130)*MIN(L$3-$O$2,$Q$2)/$Q$2)) -> 8839.8647 | M143: =L143*(1+IF(M$3<=$O$2,$D143,$D143-($D143-$I$130)*MIN(M$3-$O$2,$Q$2)/$Q$2)) -> 9019.4621 | N143: =M143*(1+IF(N$3<=$O$2,$D143,$D143-($D143-$I$130)*MIN(N$3-$O$2,$Q$2)/$Q$2)) -> 9319.8102 | O143: =SUMPRODUCT(E143:N143,1/(1+$F$130)^$E$3:$N$3)*$E$2 -> 32964.063 | P143: =N143*$E$2*(1+$I$130)/($F$130-$I$130)/(1+$F$130)^$N$3 -> 73944.439 | Q143: =O143+P143 -> 106908.5 | R143: =Q143-$G$2+$I$2 -> 87448.502 | S143: =R143/$K$2 -> 155.77139 | T143: =S143-$M$2 -> -0.038293969
A144: 13 | B144: =IF(T143>0,B143,D143) -> -0.031616211 | C144: =IF(T143>0,D143,C143) -> -0.03125 | D144: =(B144+C144)/2 -> -0.031433105 | E144: =$C$2*(1+IF(E$3<=$O$2,$D144,$D144-($D144-$I$130)*MIN(E$3-$O$2,$Q$2)/$Q$2)) -> 10228.066 | F144: =E144*(1+IF(F$3<=$O$2,$D144,$D144-($D144-$I$130)*MIN(F$3-$O$2,$Q$2)/$Q$2)) -> 9906.5665 | G144: =F144*(1+IF(G$3<=$O$2,$D144,$D144-($D144-$I$130)*MIN(G$3-$O$2,$Q$2)/$Q$2)) -> 9595.1724 | H144: =G144*(1+IF(H$3<=$O$2,$D144,$D144-($D144-$I$130)*MIN(H$3-$O$2,$Q$2)/$Q$2)) -> 9293.5663 | I144: =H144*(1+IF(I$3<=$O$2,$D144,$D144-($D144-$I$130)*MIN(I$3-$O$2,$Q$2)/$Q$2)) -> 9001.4407 | J144: =I144*(1+IF(J$3<=$O$2,$D144,$D144-($D144-$I$130)*MIN(J$3-$O$2,$Q$2)/$Q$2)) -> 8835.0357 | K144: =J144*(1+IF(K$3<=$O$2,$D144,$D144-($D144-$I$130)*MIN(K$3-$O$2,$Q$2)/$Q$2)) -> 8786.0908 | L144: =K144*(1+IF(L$3<=$O$2,$D144,$D144-($D144-$I$130)*MIN(L$3-$O$2,$Q$2)/$Q$2)) -> 8851.1672 | M144: =L144*(1+IF(M$3<=$O$2,$D144,$D144-($D144-$I$130)*MIN(M$3-$O$2,$Q$2)/$Q$2)) -> 9031.3184 | N144: =M144*(1+IF(N$3<=$O$2,$D144,$D144-($D144-$I$130)*MIN(N$3-$O$2,$Q$2)/$Q$2)) -> 9332.0613 | O144: =SUMPRODUCT(E144:N144,1/(1+$F$130)^$E$3:$N$3)*$E$2 -> 32990.888 | P144: =N144*$E$2*(1+$I$130)/($F$130-$I$130)/(1+$F$130)^$N$3 -> 74041.641 | Q144: =O144+P144 -> 107032.53 | R144: =Q144-$G$2+$I$2 -> 87572.529 | S144: =R144/$K$2 -> 155.99232 | T144: =S144-$M$2 -> 0.182634
... A155: 24 | B155: =IF(T154>0,B154,D154) -> -0.031584561 | C155: =IF(T154>0,D154,C154) -> -0.031584382 | D155: =(B155+C155)/2 -> -0.031584471 | E155: =$C$2*(1+IF(E$3<=$O$2,$D155,$D155-($D155-$I$130)*MIN(E$3-$O$2,$Q$2)/$Q$2)) -> 10226.468 | F155: =E155*(1+IF(F$3<=$O$2,$D155,$D155-($D155-$I$130)*MIN(F$3-$O$2,$Q$2)/$Q$2)) -> 9903.4704 | G155: =F155*(1+IF(G$3<=$O$2,$D155,$D155-($D155-$I$130)*MIN(G$3-$O$2,$Q$2)/$Q$2)) -> 9590.6745 | H155: =G155*(1+IF(H$3<=$O$2,$D155,$D155-($D155-$I$130)*MIN(H$3-$O$2,$Q$2)/$Q$2)) -> 9287.7581 | I155: =H155*(1+IF(I$3<=$O$2,$D155,$D155-($D155-$I$130)*MIN(I$3-$O$2,$Q$2)/$Q$2)) -> 8994.4092 | J155: =I155*(1+IF(J$3<=$O$2,$D155,$D155-($D155-$I$130)*MIN(J$3-$O$2,$Q$2)/$Q$2)) -> 8827.045 | K155: =J155*(1+IF(K$3<=$O$2,$D155,$D155-($D155-$I$130)*MIN(K$3-$O$2,$Q$2)/$Q$2)) -> 8777.3427 | L155: =K155*(1+IF(L$3<=$O$2,$D155,$D155-($D155-$I$130)*MIN(L$3-$O$2,$Q$2)/$Q$2)) -> 8841.823 | M155: =L155*(1+IF(M$3<=$O$2,$D155,$D155-($D155-$I$130)*MIN(M$3-$O$2,$Q$2)/$Q$2)) -> 9021.5163 | N155: =M155*(1+IF(N$3<=$O$2,$D155,$D155-($D155-$I$130)*MIN(N$3-$O$2,$Q$2)/$Q$2)) -> 9321.9328 | O155: =SUMPRODUCT(E155:N155,1/(1+$F$130)^$E$3:$N$3)*$E$2 -> 32968.712 | P155: =N155*$E$2*(1+$I$130)/($F$130-$I$130)/(1+$F$130)^$N$3 -> 73961.28 | Q155: =O155+P155 -> 106929.99 | R155: =Q155-$G$2+$I$2 -> 87469.991 | S155: =R155/$K$2 -> 155.80967 | T155: =S155-$M$2 -> -1.543104e-05
A157: Grid block 6: row 1, column 5 of table A (24 steps) | E157: WACC | F157: =Sensitivity!$B$10 -> 0.067017203 | G157: Terminal growth | I157: =Sensitivity!$G$9 -> 0.0383
A158: Step | B158: Low | C158: High | D158: Mid | E158: Rev Y1 | F158: Rev Y2 | G158: Rev Y3 | H158: Rev Y4 | I158: Rev Y5 | J158: Rev Y6 | K158: Rev Y7 | L158: Rev Y8 | M158: Rev Y9 | N158: Rev Y10 | O158: PV of FCF | P158: PV of TV | Q158: EV | R158: Equity | S158: Per share | T158: Value - price
A159: 1 | B159: -0.5 | C159: 1 | D159: =(B159+C159)/2 -> 0.25 | E159: =$C$2*(1+IF(E$3<=$O$2,$D159,$D159-($D159-$I$157)*MIN(E$3-$O$2,$Q$2)/$Q$2)) -> 13200 | F159: =E159*(1+IF(F$3<=$O$2,$D159,$D159-($D159-$I$157)*MIN(F$3-$O$2,$Q$2)/$Q$2)) -> 16500 | G159: =F159*(1+IF(G$3<=$O$2,$D159,$D159-($D159-$I$157)*MIN(G$3-$O$2,$Q$2)/$Q$2)) -> 20625 | H159: =G159*(1+IF(H$3<=$O$2,$D159,$D159-($D159-$I$157)*MIN(H$3-$O$2,$Q$2)/$Q$2)) -> 25781.25 | I159: =H159*(1+IF(I$3<=$O$2,$D159,$D159-($D159-$I$157)*MIN(I$3-$O$2,$Q$2)/$Q$2)) -> 32226.562 | J159: =I159*(1+IF(J$3<=$O$2,$D159,$D159-($D159-$I$157)*MIN(J$3-$O$2,$Q$2)/$Q$2)) -> 38918.73 | K159: =J159*(1+IF(K$3<=$O$2,$D159,$D159-($D159-$I$157)*MIN(K$3-$O$2,$Q$2)/$Q$2)) -> 45352.775 | L159: =K159*(1+IF(L$3<=$O$2,$D159,$D159-($D159-$I$157)*MIN(L$3-$O$2,$Q$2)/$Q$2)) -> 50930.259 | M159: =L159*(1+IF(M$3<=$O$2,$D159,$D159-($D159-$I$157)*MIN(M$3-$O$2,$Q$2)/$Q$2)) -> 55037.275 | N159: =M159*(1+IF(N$3<=$O$2,$D159,$D159-($D159-$I$157)*MIN(N$3-$O$2,$Q$2)/$Q$2)) -> 57145.203 | O159: =SUMPRODUCT(E159:N159,1/(1+$F$157)^$E$3:$N$3)*$E$2 -> 115438.4 | P159: =N159*$E$2*(1+$I$157)/($F$157-$I$157)/(1+$F$157)^$N$3 -> 534914.12 | Q159: =O159+P159 -> 650352.52 | R159: =Q159-$G$2+$I$2 -> 630892.52 | S159: =R159/$K$2 -> 1123.8043 | T159: =S159-$M$2 -> 967.99465
A160: 2 | B160: =IF(T159>0,B159,D159) -> -0.5 | C160: =IF(T159>0,D159,C159) -> 0.25 | D160: =(B160+C160)/2 -> -0.125 | E160: =$C$2*(1+IF(E$3<=$O$2,$D160,$D160-($D160-$I$157)*MIN(E$3-$O$2,$Q$2)/$Q$2)) -> 9240 | F160: =E160*(1+IF(F$3<=$O$2,$D160,$D160-($D160-$I$157)*MIN(F$3-$O$2,$Q$2)/$Q$2)) -> 8085 | G160: =F160*(1+IF(G$3<=$O$2,$D160,$D160-($D160-$I$157)*MIN(G$3-$O$2,$Q$2)/$Q$2)) -> 7074.375 | H160: =G160*(1+IF(H$3<=$O$2,$D160,$D160-($D160-$I$157)*MIN(H$3-$O$2,$Q$2)/$Q$2)) -> 6190.0781 | I160: =H160*(1+IF(I$3<=$O$2,$D160,$D160-($D160-$I$157)*MIN(I$3-$O$2,$Q$2)/$Q$2)) -> 5416.3184 | J160: =I160*(1+IF(J$3<=$O$2,$D160,$D160-($D160-$I$157)*MIN(J$3-$O$2,$Q$2)/$Q$2)) -> 4916.1755 | K160: =J160*(1+IF(K$3<=$O$2,$D160,$D160-($D160-$I$157)*MIN(K$3-$O$2,$Q$2)/$Q$2)) -> 4622.7782 | L160: =K160*(1+IF(L$3<=$O$2,$D160,$D160-($D160-$I$157)*MIN(L$3-$O$2,$Q$2)/$Q$2)) -> 4497.8707 | M160: =L160*(1+IF(M$3<=$O$2,$D160,$D160-($D160-$I$157)*MIN(M$3-$O$2,$Q$2)/$Q$2)) -> 4523.2387 | N160: =M160*(1+IF(N$3<=$O$2,$D160,$D160-($D160-$I$157)*MIN(N$3-$O$2,$Q$2)/$Q$2)) -> 4696.4787 | O160: =SUMPRODUCT(E160:N160,1/(1+$F$157)^$E$3:$N$3)*$E$2 -> 21889.471 | P160: =N160*$E$2*(1+$I$157)/($F$157-$I$157)/(1+$F$157)^$N$3 -> 43961.919 | Q160: =O160+P160 -> 65851.39 | R160: =Q160-$G$2+$I$2 -> 46391.39 | S160: =R160/$K$2 -> 82.636651 | T160: =S160-$M$2 -> -73.173036
A161: 3 | B161: =IF(T160>0,B160,D160) -> -0.125 | C161: =IF(T160>0,D160,C160) -> 0.25 | D161: =(B161+C161)/2 -> 0.0625 | E161: =$C$2*(1+IF(E$3<=$O$2,$D161,$D161-($D161-$I$157)*MIN(E$3-$O$2,$Q$2)/$Q$2)) -> 11220 | F161: =E161*(1+IF(F$3<=$O$2,$D161,$D161-($D161-$I$157)*MIN(F$3-$O$2,$Q$2)/$Q$2)) -> 11921.25 | G161: =F161*(1+IF(G$3<=$O$2,$D161,$D161-($D161-$I$157)*MIN(G$3-$O$2,$Q$2)/$Q$2)) -> 12666.328 | H161: =G161*(1+IF(H$3<=$O$2,$D161,$D161-($D161-$I$157)*MIN(H$3-$O$2,$Q$2)/$Q$2)) -> 13457.974 | I161: =H161*(1+IF(I$3<=$O$2,$D161,$D161-($D161-$I$157)*MIN(I$3-$O$2,$Q$2)/$Q$2)) -> 14299.097 | J161: =I161*(1+IF(J$3<=$O$2,$D161,$D161-($D161-$I$157)*MIN(J$3-$O$2,$Q$2)/$Q$2)) -> 15123.583 | K161: =J161*(1+IF(K$3<=$O$2,$D161,$D161-($D161-$I$157)*MIN(K$3-$O$2,$Q$2)/$Q$2)) -> 15922.411 | L161: =K161*(1+IF(L$3<=$O$2,$D161,$D161-($D161-$I$157)*MIN(L$3-$O$2,$Q$2)/$Q$2)) -> 16686.368 | M161: =L161*(1+IF(M$3<=$O$2,$D161,$D161-($D161-$I$157)*MIN(M$3-$O$2,$Q$2)/$Q$2)) -> 17406.218 | N161: =M161*(1+IF(N$3<=$O$2,$D161,$D161-($D161-$I$157)*MIN(N$3-$O$2,$Q$2)/$Q$2)) -> 18072.876 | O161: =SUMPRODUCT(E161:N161,1/(1+$F$157)^$E$3:$N$3)*$E$2 -> 50308.686 | P161: =N161*$E$2*(1+$I$157)/($F$157-$I$157)/(1+$F$157)^$N$3 -> 169173.19 | Q161: =O161+P161 -> 219481.88 | R161: =Q161-$G$2+$I$2 -> 200021.88 | S161: =R161/$K$2 -> 356.29754 | T161: =S161-$M$2 -> 200.48786
A162: 4 | B162: =IF(T161>0,B161,D161) -> -0.125 | C162: =IF(T161>0,D161,C161) -> 0.0625 | D162: =(B162+C162)/2 -> -0.03125 | E162: =$C$2*(1+IF(E$3<=$O$2,$D162,$D162-($D162-$I$157)*MIN(E$3-$O$2,$Q$2)/$Q$2)) -> 10230 | F162: =E162*(1+IF(F$3<=$O$2,$D162,$D162-($D162-$I$157)*MIN(F$3-$O$2,$Q$2)/$Q$2)) -> 9910.3125 | G162: =F162*(1+IF(G$3<=$O$2,$D162,$D162-($D162-$I$157)*MIN(G$3-$O$2,$Q$2)/$Q$2)) -> 9600.6152 | H162: =G162*(1+IF(H$3<=$O$2,$D162,$D162-($D162-$I$157)*MIN(H$3-$O$2,$Q$2)/$Q$2)) -> 9300.596 | I162: =H162*(1+IF(I$3<=$O$2,$D162,$D162-($D162-$I$157)*MIN(I$3-$O$2,$Q$2)/$Q$2)) -> 9009.9524 | J162: =I162*(1+IF(J$3<=$O$2,$D162,$D162-($D162-$I$157)*MIN(J$3-$O$2,$Q$2)/$Q$2)) -> 8853.7198 | K162: =J162*(1+IF(K$3<=$O$2,$D162,$D162-($D162-$I$157)*MIN(K$3-$O$2,$Q$2)/$Q$2)) -> 8823.3515 | L162: =K162*(1+IF(L$3<=$O$2,$D162,$D162-($D162-$I$157)*MIN(L$3-$O$2,$Q$2)/$Q$2)) -> 8915.8203 | M162: =L162*(1+IF(M$3<=$O$2,$D162,$D162-($D162-$I$157)*MIN(M$3-$O$2,$Q$2)/$Q$2)) -> 9133.2771 | N162: =M162*(1+IF(N$3<=$O$2,$D162,$D162-($D162-$I$157)*MIN(N$3-$O$2,$Q$2)/$Q$2)) -> 9483.0816 | O162: =SUMPRODUCT(E162:N162,1/(1+$F$157)^$E$3:$N$3)*$E$2 -> 33105.678 | P162: =N162*$E$2*(1+$I$157)/($F$157-$I$157)/(1+$F$157)^$N$3 -> 88767.455 | Q162: =O162+P162 -> 121873.13 | R162: =Q162-$G$2+$I$2 -> 102413.13 | S162: =R162/$K$2 -> 182.42778 | T162: =S162-$M$2 -> 26.618097
A163: 5 | B163: =IF(T162>0,B162,D162) -> -0.125 | C163: =IF(T162>0,D162,C162) -> -0.03125 | D163: =(B163+C163)/2 -> -0.078125 | E163: =$C$2*(1+IF(E$3<=$O$2,$D163,$D163-($D163-$I$157)*MIN(E$3-$O$2,$Q$2)/$Q$2)) -> 9735 | F163: =E163*(1+IF(F$3<=$O$2,$D163,$D163-($D163-$I$157)*MIN(F$3-$O$2,$Q$2)/$Q$2)) -> 8974.4531 | G163: =F163*(1+IF(G$3<=$O$2,$D163,$D163-($D163-$I$157)*MIN(G$3-$O$2,$Q$2)/$Q$2)) -> 8273.324 | H163: =G163*(1+IF(H$3<=$O$2,$D163,$D163-($D163-$I$157)*MIN(H$3-$O$2,$Q$2)/$Q$2)) -> 7626.9705 | I163: =H163*(1+IF(I$3<=$O$2,$D163,$D163-($D163-$I$157)*MIN(I$3-$O$2,$Q$2)/$Q$2)) -> 7031.1135 | J163: =I163*(1+IF(J$3<=$O$2,$D163,$D163-($D163-$I$157)*MIN(J$3-$O$2,$Q$2)/$Q$2)) -> 6645.5272 | K163: =J163*(1+IF(K$3<=$O$2,$D163,$D163-($D163-$I$157)*MIN(K$3-$O$2,$Q$2)/$Q$2)) -> 6435.8276 | L163: =K163*(1+IF(L$3<=$O$2,$D163,$D163-($D163-$I$157)*MIN(L$3-$O$2,$Q$2)/$Q$2)) -> 6382.6033 | M163: =L163*(1+IF(M$3<=$O$2,$D163,$D163-($D163-$I$157)*MIN(M$3-$O$2,$Q$2)/$Q$2)) -> 6478.4381 | N163: =M163*(1+IF(N$3<=$O$2,$D163,$D163-($D163-$I$157)*MIN(N$3-$O$2,$Q$2)/$Q$2)) -> 6726.5623 | O163: =SUMPRODUCT(E163:N163,1/(1+$F$157)^$E$3:$N$3)*$E$2 -> 26893.984 | P163: =N163*$E$2*(1+$I$157)/($F$157-$I$157)/(1+$F$157)^$N$3 -> 62964.745 | Q163: =O163+P163 -> 89858.729 | R163: =Q163-$G$2+$I$2 -> 70398.729 | S163: =R163/$K$2 -> 125.40075 | T163: =S163-$M$2 -> -30.408933
A164: 6 | B164: =IF(T163>0,B163,D163) -> -0.078125 | C164: =IF(T163>0,D163,C163) -> -0.03125 | D164: =(B164+C164)/2 -> -0.0546875 | E164: =$C$2*(1+IF(E$3<=$O$2,$D164,$D164-($D164-$I$157)*MIN(E$3-$O$2,$Q$2)/$Q$2)) -> 9982.5 | F164: =E164*(1+IF(F$3<=$O$2,$D164,$D164-($D164-$I$157)*MIN(F$3-$O$2,$Q$2)/$Q$2)) -> 9436.582 | G164: =F164*(1+IF(G$3<=$O$2,$D164,$D164-($D164-$I$157)*MIN(G$3-$O$2,$Q$2)/$Q$2)) -> 8920.519 | H164: =G164*(1+IF(H$3<=$O$2,$D164,$D164-($D164-$I$157)*MIN(H$3-$O$2,$Q$2)/$Q$2)) -> 8432.6781 | I164: =H164*(1+IF(I$3<=$O$2,$D164,$D164-($D164-$I$157)*MIN(I$3-$O$2,$Q$2)/$Q$2)) -> 7971.516 | J164: =I164*(1+IF(J$3<=$O$2,$D164,$D164-($D164-$I$157)*MIN(J$3-$O$2,$Q$2)/$Q$2)) -> 7683.824 | K164: =J164*(1+IF(K$3<=$O$2,$D164,$D164-($D164-$I$157)*MIN(K$3-$O$2,$Q$2)/$Q$2)) -> 7549.4147 | L164: =K164*(1+IF(L$3<=$O$2,$D164,$D164-($D164-$I$157)*MIN(L$3-$O$2,$Q$2)/$Q$2)) -> 7557.7568 | M164: =L164*(1+IF(M$3<=$O$2,$D164,$D164-($D164-$I$157)*MIN(M$3-$O$2,$Q$2)/$Q$2)) -> 7706.6635 | N164: =M164*(1+IF(N$3<=$O$2,$D164,$D164-($D164-$I$157)*MIN(N$3-$O$2,$Q$2)/$Q$2)) -> 8001.8287 | O164: =SUMPRODUCT(E164:N164,1/(1+$F$157)^$E$3:$N$3)*$E$2 -> 29832.843 | P164: =N164*$E$2*(1+$I$157)/($F$157-$I$157)/(1+$F$157)^$N$3 -> 74902.02 | Q164: =O164+P164 -> 104734.86 | R164: =Q164-$G$2+$I$2 -> 85274.863 | S164: =R164/$K$2 -> 151.89951 | T164: =S164-$M$2 -> -3.9101811
A165: 7 | B165: =IF(T164>0,B164,D164) -> -0.0546875 | C165: =IF(T164>0,D164,C164) -> -0.03125 | D165: =(B165+C165)/2 -> -0.04296875 | E165: =$C$2*(1+IF(E$3<=$O$2,$D165,$D165-($D165-$I$157)*MIN(E$3-$O$2,$Q$2)/$Q$2)) -> 10106.25 | F165: =E165*(1+IF(F$3<=$O$2,$D165,$D165-($D165-$I$157)*MIN(F$3-$O$2,$Q$2)/$Q$2)) -> 9671.9971 | G165: =F165*(1+IF(G$3<=$O$2,$D165,$D165-($D165-$I$157)*MIN(G$3-$O$2,$Q$2)/$Q$2)) -> 9256.4034 | H165: =G165*(1+IF(H$3<=$O$2,$D165,$D165-($D165-$I$157)*MIN(H$3-$O$2,$Q$2)/$Q$2)) -> 8858.6674 | I165: =H165*(1+IF(I$3<=$O$2,$D165,$D165-($D165-$I$157)*MIN(I$3-$O$2,$Q$2)/$Q$2)) -> 8478.0215 | J165: =I165*(1+IF(J$3<=$O$2,$D165,$D165-($D165-$I$157)*MIN(J$3-$O$2,$Q$2)/$Q$2)) -> 8251.5312 | K165: =J165*(1+IF(K$3<=$O$2,$D165,$D165-($D165-$I$157)*MIN(K$3-$O$2,$Q$2)/$Q$2)) -> 8165.2098 | L165: =K165*(1+IF(L$3<=$O$2,$D165,$D165-($D165-$I$157)*MIN(L$3-$O$2,$Q$2)/$Q$2)) -> 8212.5068 | M165: =L165*(1+IF(M$3<=$O$2,$D165,$D165-($D165-$I$157)*MIN(M$3-$O$2,$Q$2)/$Q$2)) -> 8393.5618 | N165: =M165*(1+IF(N$3<=$O$2,$D165,$D165-($D165-$I$157)*MIN(N$3-$O$2,$Q$2)/$Q$2)) -> 8715.0352 | O165: =SUMPRODUCT(E165:N165,1/(1+$F$157)^$E$3:$N$3)*$E$2 -> 31425.339 | P165: =N165*$E$2*(1+$I$157)/($F$157-$I$157)/(1+$F$157)^$N$3 -> 81578.07 | Q165: =O165+P165 -> 113003.41 | R165: =Q165-$G$2+$I$2 -> 93543.409 | S165: =R165/$K$2 -> 166.62821 | T165: =S165-$M$2 -> 10.818519
A166: 8 | B166: =IF(T165>0,B165,D165) -> -0.0546875 | C166: =IF(T165>0,D165,C165) -> -0.04296875 | D166: =(B166+C166)/2 -> -0.048828125 | E166: =$C$2*(1+IF(E$3<=$O$2,$D166,$D166-($D166-$I$157)*MIN(E$3-$O$2,$Q$2)/$Q$2)) -> 10044.375 | F166: =E166*(1+IF(F$3<=$O$2,$D166,$D166-($D166-$I$157)*MIN(F$3-$O$2,$Q$2)/$Q$2)) -> 9553.927 | G166: =F166*(1+IF(G$3<=$O$2,$D166,$D166-($D166-$I$157)*MIN(G$3-$O$2,$Q$2)/$Q$2)) -> 9087.4267 | H166: =G166*(1+IF(H$3<=$O$2,$D166,$D166-($D166-$I$157)*MIN(H$3-$O$2,$Q$2)/$Q$2)) -> 8643.7047 | I166: =H166*(1+IF(I$3<=$O$2,$D166,$D166-($D166-$I$157)*MIN(I$3-$O$2,$Q$2)/$Q$2)) -> 8221.6488 | J166: =I166*(1+IF(J$3<=$O$2,$D166,$D166-($D166-$I$157)*MIN(J$3-$O$2,$Q$2)/$Q$2)) -> 7963.4684 | K166: =J166*(1+IF(K$3<=$O$2,$D166,$D166-($D166-$I$157)*MIN(K$3-$O$2,$Q$2)/$Q$2)) -> 7852.164 | L166: =K166*(1+IF(L$3<=$O$2,$D166,$D166-($D166-$I$157)*MIN(L$3-$O$2,$Q$2)/$Q$2)) -> 7879.2442 | M166: =L166*(1+IF(M$3<=$O$2,$D166,$D166-($D166-$I$157)*MIN(M$3-$O$2,$Q$2)/$Q$2)) -> 8043.7185 | N166: =M166*(1+IF(N$3<=$O$2,$D166,$D166-($D166-$I$157)*MIN(N$3-$O$2,$Q$2)/$Q$2)) -> 8351.7929 | O166: =SUMPRODUCT(E166:N166,1/(1+$F$157)^$E$3:$N$3)*$E$2 -> 30618.39 | P166: =N166*$E$2*(1+$I$157)/($F$157-$I$157)/(1+$F$157)^$N$3 -> 78177.899 | Q166: =O166+P166 -> 108796.29 | R166: =Q166-$G$2+$I$2 -> 89336.29 | S166: =R166/$K$2 -> 159.13409 | T166: =S166-$M$2 -> 3.3244082
A167: 9 | B167: =IF(T166>0,B166,D166) -> -0.0546875 | C167: =IF(T166>0,D166,C166) -> -0.048828125 | D167: =(B167+C167)/2 -> -0.051757812 | E167: =$C$2*(1+IF(E$3<=$O$2,$D167,$D167-($D167-$I$157)*MIN(E$3-$O$2,$Q$2)/$Q$2)) -> 10013.438 | F167: =E167*(1+IF(F$3<=$O$2,$D167,$D167-($D167-$I$157)*MIN(F$3-$O$2,$Q$2)/$Q$2)) -> 9495.1639 | G167: =F167*(1+IF(G$3<=$O$2,$D167,$D167-($D167-$I$157)*MIN(G$3-$O$2,$Q$2)/$Q$2)) -> 9003.715 | H167: =G167*(1+IF(H$3<=$O$2,$D167,$D167-($D167-$I$157)*MIN(H$3-$O$2,$Q$2)/$Q$2)) -> 8537.7024 | I167: =H167*(1+IF(I$3<=$O$2,$D167,$D167-($D167-$I$157)*MIN(I$3-$O$2,$Q$2)/$Q$2)) -> 8095.8096 | J167: =I167*(1+IF(J$3<=$O$2,$D167,$D167-($D167-$I$157)*MIN(J$3-$O$2,$Q$2)/$Q$2)) -> 7822.6064 | K167: =J167*(1+IF(K$3<=$O$2,$D167,$D167-($D167-$I$157)*MIN(K$3-$O$2,$Q$2)/$Q$2)) -> 7699.5201 | L167: =K167*(1+IF(L$3<=$O$2,$D167,$D167-($D167-$I$157)*MIN(L$3-$O$2,$Q$2)/$Q$2)) -> 7717.0509 | M167: =L167*(1+IF(M$3<=$O$2,$D167,$D167-($D167-$I$157)*MIN(M$3-$O$2,$Q$2)/$Q$2)) -> 7873.6178 | N167: =M167*(1+IF(N$3<=$O$2,$D167,$D167-($D167-$I$157)*MIN(N$3-$O$2,$Q$2)/$Q$2)) -> 8175.1774 | O167: =SUMPRODUCT(E167:N167,1/(1+$F$157)^$E$3:$N$3)*$E$2 -> 30222.976 | P167: =N167*$E$2*(1+$I$157)/($F$157-$I$157)/(1+$F$157)^$N$3 -> 76524.67 | Q167: =O167+P167 -> 106747.65 | R167: =Q167-$G$2+$I$2 -> 87287.646 | S167: =R167/$K$2 -> 155.48486 | T167: =S167-$M$2 -> -0.32482594
A168: 10 | B168: =IF(T167>0,B167,D167) -> -0.051757812 | C168: =IF(T167>0,D167,C167) -> -0.048828125 | D168: =(B168+C168)/2 -> -0.050292969 | E168: =$C$2*(1+IF(E$3<=$O$2,$D168,$D168-($D168-$I$157)*MIN(E$3-$O$2,$Q$2)/$Q$2)) -> 10028.906 | F168: =E168*(1+IF(F$3<=$O$2,$D168,$D168-($D168-$I$157)*MIN(F$3-$O$2,$Q$2)/$Q$2)) -> 9524.5228 | G168: =F168*(1+IF(G$3<=$O$2,$D168,$D168-($D168-$I$157)*MIN(G$3-$O$2,$Q$2)/$Q$2)) -> 9045.5063 | H168: =G168*(1+IF(H$3<=$O$2,$D168,$D168-($D168-$I$157)*MIN(H$3-$O$2,$Q$2)/$Q$2)) -> 8590.5809 | I168: =H168*(1+IF(I$3<=$O$2,$D168,$D168-($D168-$I$157)*MIN(I$3-$O$2,$Q$2)/$Q$2)) -> 8158.5351 | J168: =I168*(1+IF(J$3<=$O$2,$D168,$D168-($D168-$I$157)*MIN(J$3-$O$2,$Q$2)/$Q$2)) -> 7892.7759 | K168: =J168*(1+IF(K$3<=$O$2,$D168,$D168-($D168-$I$157)*MIN(K$3-$O$2,$Q$2)/$Q$2)) -> 7775.5225 | L168: =K168*(1+IF(L$3<=$O$2,$D168,$D168-($D168-$I$157)*MIN(L$3-$O$2,$Q$2)/$Q$2)) -> 7797.7824 | M168: =L168*(1+IF(M$3<=$O$2,$D168,$D168-($D168-$I$157)*MIN(M$3-$O$2,$Q$2)/$Q$2)) -> 7958.2717 | N168: =M168*(1+IF(N$3<=$O$2,$D168,$D168-($D168-$I$157)*MIN(N$3-$O$2,$Q$2)/$Q$2)) -> 8263.0735 | O168: =SUMPRODUCT(E168:N168,1/(1+$F$157)^$E$3:$N$3)*$E$2 -> 30420.019 | P168: =N168*$E$2*(1+$I$157)/($F$157-$I$157)/(1+$F$157)^$N$3 -> 77347.432 | Q168: =O168+P168 -> 107767.45 | R168: =Q168-$G$2+$I$2 -> 88307.45 | S168: =R168/$K$2 -> 157.30143 | T168: =S168-$M$2 -> 1.4917442
A169: 11 | B169: =IF(T168>0,B168,D168) -> -0.051757812 | C169: =IF(T168>0,D168,C168) -> -0.050292969 | D169: =(B169+C169)/2 -> -0.051025391 | E169: =$C$2*(1+IF(E$3<=$O$2,$D169,$D169-($D169-$I$157)*MIN(E$3-$O$2,$Q$2)/$Q$2)) -> 10021.172 | F169: =E169*(1+IF(F$3<=$O$2,$D169,$D169-($D169-$I$157)*MIN(F$3-$O$2,$Q$2)/$Q$2)) -> 9509.8377 | G169: =F169*(1+IF(G$3<=$O$2,$D169,$D169-($D169-$I$157)*MIN(G$3-$O$2,$Q$2)/$Q$2)) -> 9024.5945 | H169: =G169*(1+IF(H$3<=$O$2,$D169,$D169-($D169-$I$157)*MIN(H$3-$O$2,$Q$2)/$Q$2)) -> 8564.111 | I169: =H169*(1+IF(I$3<=$O$2,$D169,$D169-($D169-$I$157)*MIN(I$3-$O$2,$Q$2)/$Q$2)) -> 8127.1239 | J169: =I169*(1+IF(J$3<=$O$2,$D169,$D169-($D169-$I$157)*MIN(J$3-$O$2,$Q$2)/$Q$2)) -> 7857.6259 | K169: =J169*(1+IF(K$3<=$O$2,$D169,$D169-($D169-$I$157)*MIN(K$3-$O$2,$Q$2)/$Q$2)) -> 7737.4417 | L169: =K169*(1+IF(L$3<=$O$2,$D169,$D169-($D169-$I$157)*MIN(L$3-$O$2,$Q$2)/$Q$2)) -> 7757.3257 | M169: =L169*(1+IF(M$3<=$O$2,$D169,$D169-($D169-$I$157)*MIN(M$3-$O$2,$Q$2)/$Q$2)) -> 7915.8461 | N169: =M169*(1+IF(N$3<=$O$2,$D169,$D169-($D169-$I$157)*MIN(N$3-$O$2,$Q$2)/$Q$2)) -> 8219.023 | O169: =SUMPRODUCT(E169:N169,1/(1+$F$157)^$E$3:$N$3)*$E$2 -> 30321.332 | P169: =N169*$E$2*(1+$I$157)/($F$157-$I$157)/(1+$F$157)^$N$3 -> 76935.091 | Q169: =O169+P169 -> 107256.42 | R169: =Q169-$G$2+$I$2 -> 87796.423 | S169: =R169/$K$2 -> 156.39114 | T169: =S169-$M$2 -> 0.58145518
A170: 12 | B170: =IF(T169>0,B169,D169) -> -0.051757812 | C170: =IF(T169>0,D169,C169) -> -0.051025391 | D170: =(B170+C170)/2 -> -0.051391602 | E170: =$C$2*(1+IF(E$3<=$O$2,$D170,$D170-($D170-$I$157)*MIN(E$3-$O$2,$Q$2)/$Q$2)) -> 10017.305 | F170: =E170*(1+IF(F$3<=$O$2,$D170,$D170-($D170-$I$157)*MIN(F$3-$O$2,$Q$2)/$Q$2)) -> 9502.4994 | G170: =F170*(1+IF(G$3<=$O$2,$D170,$D170-($D170-$I$157)*MIN(G$3-$O$2,$Q$2)/$Q$2)) -> 9014.1507 | H170: =G170*(1+IF(H$3<=$O$2,$D170,$D170-($D170-$I$157)*MIN(H$3-$O$2,$Q$2)/$Q$2)) -> 8550.8991 | I170: =H170*(1+IF(I$3<=$O$2,$D170,$D170-($D170-$I$157)*MIN(I$3-$O$2,$Q$2)/$Q$2)) -> 8111.4547 | J170: =I170*(1+IF(J$3<=$O$2,$D170,$D170-($D170-$I$157)*MIN(J$3-$O$2,$Q$2)/$Q$2)) -> 7840.0999 | K170: =J170*(1+IF(K$3<=$O$2,$D170,$D170-($D170-$I$157)*MIN(K$3-$O$2,$Q$2)/$Q$2)) -> 7718.461 | L170: =K170*(1+IF(L$3<=$O$2,$D170,$D170-($D170-$I$157)*MIN(L$3-$O$2,$Q$2)/$Q$2)) -> 7737.1656 | M170: =L170*(1+IF(M$3<=$O$2,$D170,$D170-($D170-$I$157)*MIN(M$3-$O$2,$Q$2)/$Q$2)) -> 7894.7073 | N170: =M170*(1+IF(N$3<=$O$2,$D170,$D170-($D170-$I$157)*MIN(N$3-$O$2,$Q$2)/$Q$2)) -> 8197.0746 | O170: =SUMPRODUCT(E170:N170,1/(1+$F$157)^$E$3:$N$3)*$E$2 -> 30272.112 | P170: =N170*$E$2*(1+$I$157)/($F$157-$I$157)/(1+$F$157)^$N$3 -> 76729.641 | Q170: =O170+P170 -> 107001.75 | R170: =Q170-$G$2+$I$2 -> 87541.754 | S170: =R170/$K$2 -> 155.9375 | T170: =S170-$M$2 -> 0.12781461
A171: 13 | B171: =IF(T170>0,B170,D170) -> -0.051757812 | C171: =IF(T170>0,D170,C170) -> -0.051391602 | D171: =(B171+C171)/2 -> -0.051574707 | E171: =$C$2*(1+IF(E$3<=$O$2,$D171,$D171-($D171-$I$157)*MIN(E$3-$O$2,$Q$2)/$Q$2)) -> 10015.371 | F171: =E171*(1+IF(F$3<=$O$2,$D171,$D171-($D171-$I$157)*MIN(F$3-$O$2,$Q$2)/$Q$2)) -> 9498.8313 | G171: =F171*(1+IF(G$3<=$O$2,$D171,$D171-($D171-$I$157)*MIN(G$3-$O$2,$Q$2)/$Q$2)) -> 9008.9318 | H171: =G171*(1+IF(H$3<=$O$2,$D171,$D171-($D171-$I$157)*MIN(H$3-$O$2,$Q$2)/$Q$2)) -> 8544.2988 | I171: =H171*(1+IF(I$3<=$O$2,$D171,$D171-($D171-$I$157)*MIN(I$3-$O$2,$Q$2)/$Q$2)) -> 8103.6291 | J171: =I171*(1+IF(J$3<=$O$2,$D171,$D171-($D171-$I$157)*MIN(J$3-$O$2,$Q$2)/$Q$2)) -> 7831.3491 | K171: =J171*(1+IF(K$3<=$O$2,$D171,$D171-($D171-$I$157)*MIN(K$3-$O$2,$Q$2)/$Q$2)) -> 7708.9856 | L171: =K171*(1+IF(L$3<=$O$2,$D171,$D171-($D171-$I$157)*MIN(L$3-$O$2,$Q$2)/$Q$2)) -> 7727.1026 | M171: =L171*(1+IF(M$3<=$O$2,$D171,$D171-($D171-$I$157)*MIN(M$3-$O$2,$Q$2)/$Q$2)) -> 7884.1564 | N171: =M171*(1+IF(N$3<=$O$2,$D171,$D171-($D171-$I$157)*MIN(N$3-$O$2,$Q$2)/$Q$2)) -> 8186.1196 | O171: =SUMPRODUCT(E171:N171,1/(1+$F$157)^$E$3:$N$3)*$E$2 -> 30247.534 | P171: =N171*$E$2*(1+$I$157)/($F$157-$I$157)/(1+$F$157)^$N$3 -> 76627.096 | Q171: =O171+P171 -> 106874.63 | R171: =Q171-$G$2+$I$2 -> 87414.63 | S171: =R171/$K$2 -> 155.71106 | T171: =S171-$M$2 -> -0.098630548
... A182: 24 | B182: =IF(T181>0,B181,D181) -> -0.051494956 | C182: =IF(T181>0,D181,C181) -> -0.051494777 | D182: =(B182+C182)/2 -> -0.051494867 | E182: =$C$2*(1+IF(E$3<=$O$2,$D182,$D182-($D182-$I$157)*MIN(E$3-$O$2,$Q$2)/$Q$2)) -> 10016.214 | F182: =E182*(1+IF(F$3<=$O$2,$D182,$D182-($D182-$I$157)*MIN(F$3-$O$2,$Q$2)/$Q$2)) -> 9500.4306 | G182: =F182*(1+IF(G$3<=$O$2,$D182,$D182-($D182-$I$157)*MIN(G$3-$O$2,$Q$2)/$Q$2)) -> 9011.2072 | H182: =G182*(1+IF(H$3<=$O$2,$D182,$D182-($D182-$I$157)*MIN(H$3-$O$2,$Q$2)/$Q$2)) -> 8547.1763 | I182: =H182*(1+IF(I$3<=$O$2,$D182,$D182-($D182-$I$157)*MIN(I$3-$O$2,$Q$2)/$Q$2)) -> 8107.0406 | J182: =I182*(1+IF(J$3<=$O$2,$D182,$D182-($D182-$I$157)*MIN(J$3-$O$2,$Q$2)/$Q$2)) -> 7835.1637 | K182: =J182*(1+IF(K$3<=$O$2,$D182,$D182-($D182-$I$157)*MIN(K$3-$O$2,$Q$2)/$Q$2)) -> 7713.116 | L182: =K182*(1+IF(L$3<=$O$2,$D182,$D182-($D182-$I$157)*MIN(L$3-$O$2,$Q$2)/$Q$2)) -> 7731.4891 | M182: =L182*(1+IF(M$3<=$O$2,$D182,$D182-($D182-$I$157)*MIN(M$3-$O$2,$Q$2)/$Q$2)) -> 7888.7555 | N182: =M182*(1+IF(N$3<=$O$2,$D182,$D182-($D182-$I$157)*MIN(N$3-$O$2,$Q$2)/$Q$2)) -> 8190.8948 | O182: =SUMPRODUCT(E182:N182,1/(1+$F$157)^$E$3:$N$3)*$E$2 -> 30258.248 | P182: =N182*$E$2*(1+$I$157)/($F$157-$I$157)/(1+$F$157)^$N$3 -> 76671.795 | Q182: =O182+P182 -> 106930.04 | R182: =Q182-$G$2+$I$2 -> 87470.043 | S182: =R182/$K$2 -> 155.80976 | T182: =S182-$M$2 -> 7.6775892e-05
...

Sheet DCF
B2: Intercontinental Exchange (ICE): discounted cash flow
B3: Panel A runs the model at the solved growth rate, so it should land on the price. Panel B runs it at your view.
B5: A. At the solved (implied) growth rate
B6: Year | C6: 1 | D6: 2 | E6: 3 | F6: 4 | G6: 5 | H6: 6 | I6: 7 | J6: 8 | K6: 9 | L6: 10
B7: Revenue growth | C7: =IF(C$6<=Inputs!$C$46,Solver!$W$7,Solver!$W$7-(Solver!$W$7-Inputs!$C$37)*MIN(C$6-Inputs!$C$46,Inputs!$C$47)/Inputs!$C$47) -> 0.022919701 | D7: =IF(D$6<=Inputs!$C$46,Solver!$W$7,Solver!$W$7-(Solver!$W$7-Inputs!$C$37)*MIN(D$6-Inputs!$C$46,Inputs!$C$47)/Inputs!$C$47) -> 0.022919701 | E7: =IF(E$6<=Inputs!$C$46,Solver!$W$7,Solver!$W$7-(Solver!$W$7-Inputs!$C$37)*MIN(E$6-Inputs!$C$46,Inputs!$C$47)/Inputs!$C$47) -> 0.022919701 | F7: =IF(F$6<=Inputs!$C$46,Solver!$W$7,Solver!$W$7-(Solver!$W$7-Inputs!$C$37)*MIN(F$6-Inputs!$C$46,Inputs!$C$47)/Inputs!$C$47) -> 0.022919701 | G7: =IF(G$6<=Inputs!$C$46,Solver!$W$7,Solver!$W$7-(Solver!$W$7-Inputs!$C$37)*MIN(G$6-Inputs!$C$46,Inputs!$C$47)/Inputs!$C$47) -> 0.022919701 | H7: =IF(H$6<=Inputs!$C$46,Solver!$W$7,Solver!$W$7-(Solver!$W$7-Inputs!$C$37)*MIN(H$6-Inputs!$C$46,Inputs!$C$47)/Inputs!$C$47) -> 0.023995761 | I7: =IF(I$6<=Inputs!$C$46,Solver!$W$7,Solver!$W$7-(Solver!$W$7-Inputs!$C$37)*MIN(I$6-Inputs!$C$46,Inputs!$C$47)/Inputs!$C$47) -> 0.025071821 | J7: =IF(J$6<=Inputs!$C$46,Solver!$W$7,Solver!$W$7-(Solver!$W$7-Inputs!$C$37)*MIN(J$6-Inputs!$C$46,Inputs!$C$47)/Inputs!$C$47) -> 0.02614788 | ... L7: =IF(L$6<=Inputs!$C$46,Solver!$W$7,Solver!$W$7-(Solver!$W$7-Inputs!$C$37)*MIN(L$6-Inputs!$C$46,Inputs!$C$47)/Inputs!$C$47) -> 0.0283
B8: Revenue ($mm) | C8: =Inputs!$C$12*(1+C7) -> 10802.032 | D8: =C8*(1+D7) -> 11049.611 | E8: =D8*(1+E7) -> 11302.865 | F8: =E8*(1+F7) -> 11561.923 | G8: =F8*(1+G7) -> 11826.919 | H8: =G8*(1+H7) -> 12110.715 | I8: =H8*(1+I7) -> 12414.353 | J8: =I8*(1+J7) -> 12738.962 | K8: =J8*(1+K7) -> 13085.767 | L8: =K8*(1+L7) -> 13456.094
B9: Unlevered free cash flow ($mm) | C9: =C8*Inputs!$C$23 -> 5349.87 | D9: =D8*Inputs!$C$23 -> 5472.4875 | E9: =E8*Inputs!$C$23 -> 5597.9152 | F9: =F8*Inputs!$C$23 -> 5726.2178 | G9: =G8*Inputs!$C$23 -> 5857.461 | H9: =H8*Inputs!$C$23 -> 5998.0152 | I9: =I8*Inputs!$C$23 -> 6148.3964 | J9: =J8*Inputs!$C$23 -> 6309.1639 | ... L9: =L8*Inputs!$C$23 -> 6664.3344
B10: Discount factor | C10: =1/(1+WACC!$C$37)^C$6 -> 0.92849028 | D10: =1/(1+WACC!$C$37)^D$6 -> 0.86209419 | E10: =1/(1+WACC!$C$37)^E$6 -> 0.80044608 | F10: =1/(1+WACC!$C$37)^F$6 -> 0.7432064 | G10: =1/(1+WACC!$C$37)^G$6 -> 0.69005991 | H10: =1/(1+WACC!$C$37)^H$6 -> 0.64071392 | I10: =1/(1+WACC!$C$37)^I$6 -> 0.59489664 | J10: =1/(1+WACC!$C$37)^J$6 -> 0.55235575 | ... L10: =1/(1+WACC!$C$37)^L$6 -> 0.47618268
B11: Present value ($mm) | C11: =C9*C10 -> 4967.3023 | D11: =D9*D10 -> 4717.7997 | E11: =E9*E10 -> 4480.8293 | F11: =F9*F10 -> 4255.7617 | G11: =G9*G10 -> 4041.999 | H11: =H9*H10 -> 3843.0118 | I11: =I9*I10 -> 3657.6604 | J11: =J9*J10 -> 3484.903 | ... L11: =L9*L10 -> 3173.4406
B13: Sum of present values, years 1 to 10 | C13: =SUM(C11:L11) -> 39946.495
B14: Terminal value at year 10 | C14: =L9*(1+Inputs!$C$37)/(WACC!$C$37-Inputs!$C$37) -> 140667.66
B15: Present value of terminal value | C15: =C14*L10 -> 66983.505
B16: Enterprise value | C16: =C13+C15 -> 106930
B17: Less: debt | C17: =-Inputs!$C$27 -> -20530
B18: Plus: cash | C18: =Inputs!$C$28 -> 1070
B19: Equity value | C19: =SUM(C16:C18) -> 87470
B20: Shares (mm) | C20: =Inputs!$C$7 -> 561.39
B21: Value per share ($) | C21: =C19/C20 -> 155.80969
B22: Price at the lock ($) | C22: =Inputs!$C$6 -> 155.80969
B23: Value / price - 1 | C23: =C21/C22-1 -> 9.144685e-12
B24: Terminal value share of enterprise value | C24: =C15/C16 -> 0.62642388
B25: B. At your view of growth (Inputs tab, yellow cell)
B26: Year | C26: 1 | D26: 2 | E26: 3 | F26: 4 | G26: 5 | H26: 6 | I26: 7 | J26: 8 | K26: 9 | L26: 10
B27: Revenue growth | C27: =IF(C$26<=Inputs!$C$46,Inputs!$C$45,Inputs!$C$45-(Inputs!$C$45-Inputs!$C$37)*MIN(C$26-Inputs!$C$46,Inputs!$C$47)/Inputs!$C$47) -> 0.0812 | D27: =IF(D$26<=Inputs!$C$46,Inputs!$C$45,Inputs!$C$45-(Inputs!$C$45-Inputs!$C$37)*MIN(D$26-Inputs!$C$46,Inputs!$C$47)/Inputs!$C$47) -> 0.0812 | E27: =IF(E$26<=Inputs!$C$46,Inputs!$C$45,Inputs!$C$45-(Inputs!$C$45-Inputs!$C$37)*MIN(E$26-Inputs!$C$46,Inputs!$C$47)/Inputs!$C$47) -> 0.0812 | F27: =IF(F$26<=Inputs!$C$46,Inputs!$C$45,Inputs!$C$45-(Inputs!$C$45-Inputs!$C$37)*MIN(F$26-Inputs!$C$46,Inputs!$C$47)/Inputs!$C$47) -> 0.0812 | G27: =IF(G$26<=Inputs!$C$46,Inputs!$C$45,Inputs!$C$45-(Inputs!$C$45-Inputs!$C$37)*MIN(G$26-Inputs!$C$46,Inputs!$C$47)/Inputs!$C$47) -> 0.0812 | H27: =IF(H$26<=Inputs!$C$46,Inputs!$C$45,Inputs!$C$45-(Inputs!$C$45-Inputs!$C$37)*MIN(H$26-Inputs!$C$46,Inputs!$C$47)/Inputs!$C$47) -> 0.07062 | I27: =IF(I$26<=Inputs!$C$46,Inputs!$C$45,Inputs!$C$45-(Inputs!$C$45-Inputs!$C$37)*MIN(I$26-Inputs!$C$46,Inputs!$C$47)/Inputs!$C$47) -> 0.06004 | J27: =IF(J$26<=Inputs!$C$46,Inputs!$C$45,Inputs!$C$45-(Inputs!$C$45-Inputs!$C$37)*MIN(J$26-Inputs!$C$46,Inputs!$C$47)/Inputs!$C$47) -> 0.04946 | ... L27: =IF(L$26<=Inputs!$C$46,Inputs!$C$45,Inputs!$C$45-(Inputs!$C$45-Inputs!$C$37)*MIN(L$26-Inputs!$C$46,Inputs!$C$47)/Inputs!$C$47) -> 0.0283
B28: Revenue ($mm) | C28: =Inputs!$C$12*(1+C27) -> 11417.472 | D28: =C28*(1+D27) -> 12344.571 | E28: =D28*(1+E27) -> 13346.95 | F28: =E28*(1+F27) -> 14430.722 | G28: =F28*(1+G27) -> 15602.497 | H28: =G28*(1+H27) -> 16704.345 | I28: =H28*(1+I27) -> 17707.274 | J28: =I28*(1+J27) -> 18583.076 | K28: =J28*(1+K27) -> 19305.586 | L28: =K28*(1+L27) -> 19851.934
B29: Unlevered free cash flow ($mm) | C29: =C28*Inputs!$C$23 -> 5654.676 | D29: =D28*Inputs!$C$23 -> 6113.8357 | E29: =E28*Inputs!$C$23 -> 6610.2791 | F29: =F28*Inputs!$C$23 -> 7147.0338 | G29: =G28*Inputs!$C$23 -> 7727.373 | H29: =H28*Inputs!$C$23 -> 8273.08 | I29: =I28*Inputs!$C$23 -> 8769.7958 | J29: =J28*Inputs!$C$23 -> 9203.5499 | ... L29: =L28*Inputs!$C$23 -> 9831.971
B30: Discount factor | C30: =1/(1+WACC!$C$37)^C$26 -> 0.92849028 | D30: =1/(1+WACC!$C$37)^D$26 -> 0.86209419 | E30: =1/(1+WACC!$C$37)^E$26 -> 0.80044608 | F30: =1/(1+WACC!$C$37)^F$26 -> 0.7432064 | G30: =1/(1+WACC!$C$37)^G$26 -> 0.69005991 | H30: =1/(1+WACC!$C$37)^H$26 -> 0.64071392 | I30: =1/(1+WACC!$C$37)^I$26 -> 0.59489664 | J30: =1/(1+WACC!$C$37)^J$26 -> 0.55235575 | ... L30: =1/(1+WACC!$C$37)^L$26 -> 0.47618268
B31: Present value ($mm) | C31: =C29*C30 -> 5250.3117 | D31: =D29*D30 -> 5270.7022 | E31: =E29*E30 -> 5291.172 | F31: =F29*F30 -> 5311.7213 | G31: =G29*G30 -> 5332.3503 | H31: =H29*H30 -> 5300.6775 | I31: =I29*I30 -> 5217.1221 | J31: =J29*J30 -> 5083.6337 | ... L31: =L29*L30 -> 4681.8144
B33: Sum of present values, years 1 to 10 | C33: =SUM(C31:L31) -> 51643.127
B34: Terminal value at year 10 | C34: =L29*(1+Inputs!$C$37)/(WACC!$C$37-Inputs!$C$37) -> 207528.66
B35: Present value of terminal value | C35: =C34*L30 -> 98821.555
B36: Enterprise value | C36: =C33+C35 -> 150464.68
B37: Less: debt | C37: =-Inputs!$C$27 -> -20530
B38: Plus: cash | C38: =Inputs!$C$28 -> 1070
B39: Equity value | C39: =SUM(C36:C38) -> 131004.68
B40: Shares (mm) | C40: =Inputs!$C$7 -> 561.39
B41: Value per share ($) | C41: =C39/C40 -> 233.35771
B42: Price at the lock ($) | C42: =Inputs!$C$6 -> 155.80969
B43: Value / price - 1 | C43: =C41/C42-1 -> 0.49770987
B44: Terminal value share of enterprise value | C44: =C35/C36 -> 0.65677575

Sheet Sensitivity
B2: Intercontinental Exchange (ICE): sensitivity
B3: Table A re-solves implied growth for each pair of inputs (Solver tab, blocks 2 to 26). Table B values the stock at a growth view.
B5: WACC step | C5: 0.005 | D5: Terminal-growth step | F5: 0.005
B6: Growth-view step | C6: 0.02
B8: A. Implied 5-year growth: WACC (rows) by terminal growth (columns)
C9: =Inputs!$C$37+(0-2)*$F$5 -> 0.0183 | D9: =Inputs!$C$37+(1-2)*$F$5 -> 0.0233 | E9: =Inputs!$C$37+(2-2)*$F$5 -> 0.0283 | F9: =Inputs!$C$37+(3-2)*$F$5 -> 0.0333 | G9: =Inputs!$C$37+(4-2)*$F$5 -> 0.0383
B10: =WACC!$C$37+(0-2)*$C$5 -> 0.067017203 | C10: =Solver!$D$74 -> 0.014599949 | D10: =Solver!$D$101 -> 0.00094553828 | E10: =Solver!$D$128 -> -0.014309257 | F10: =Solver!$D$155 -> -0.031584471 | G10: =Solver!$D$182 -> -0.051494867 | I10: Centre cell = the base case. Each step changes one input by the step size above.
B11: =WACC!$C$37+(1-2)*$C$5 -> 0.072017203 | C11: =Solver!$D$209 -> 0.031172425 | D11: =Solver!$D$236 -> 0.018761128 | E11: =Solver!$D$263 -> 0.0050446689 | F11: =Solver!$D$290 -> -0.010278791 | G11: =Solver!$D$317 -> -0.027631432
B12: =WACC!$C$37+(2-2)*$C$5 -> 0.077017203 | C12: =Solver!$D$344 -> 0.046768576 | D12: =Solver!$D$371 -> 0.035387248 | E12: =Solver!$D$398 -> 0.022919625 | F12: =Solver!$D$425 -> 0.0091412961 | G12: =Solver!$D$452 -> -0.0062510073
B13: =WACC!$C$37+(3-2)*$C$5 -> 0.082017203 | C13: =Solver!$D$479 -> 0.061546296 | D13: =Solver!$D$506 -> 0.051032573 | E13: =Solver!$D$533 -> 0.039599568 | F13: =Solver!$D$560 -> 0.027075619 | G13: =Solver!$D$587 -> 0.013235241
B14: =WACC!$C$37+(4-2)*$C$5 -> 0.087017203 | C14: =Solver!$D$614 -> 0.07562843 | D14: =Solver!$D$641 -> 0.065855533 | E14: =Solver!$D$668 -> 0.055293888 | F14: =Solver!$D$695 -> 0.043809205 | G14: =Solver!$D$722 -> 0.031228751
B17: B. Value per share: WACC (rows) by your growth view (columns)
C18: =Inputs!$C$45+(0-2)*$C$6 -> 0.0412 | D18: =Inputs!$C$45+(1-2)*$C$6 -> 0.0612 | E18: =Inputs!$C$45+(2-2)*$C$6 -> 0.0812 | F18: =Inputs!$C$45+(3-2)*$C$6 -> 0.1012 | G18: =Inputs!$C$45+(4-2)*$C$6 -> 0.1212
B19: =WACC!$C$37+(0-2)*$C$5 -> 0.067017203 | C19: =(SUMPRODUCT($C28:$L28,1/(1+$B19)^$C$27:$L$27)*Inputs!$C$23+$L28*Inputs!$C$23*(1+Inputs!$C$37)/($B19-Inputs!$C$37)/(1+$B19)^$L$27-Inputs!$C$27+Inputs!$C$28)/Inputs!$C$7 -> 232.89516 | D19: =(SUMPRODUCT($C29:$L29,1/(1+$B19)^$C$27:$L$27)*Inputs!$C$23+$L29*Inputs!$C$23*(1+Inputs!$C$37)/($B19-Inputs!$C$37)/(1+$B19)^$L$27-Inputs!$C$27+Inputs!$C$28)/Inputs!$C$7 -> 267.10068 | E19: =(SUMPRODUCT($C30:$L30,1/(1+$B19)^$C$27:$L$27)*Inputs!$C$23+$L30*Inputs!$C$23*(1+Inputs!$C$37)/($B19-Inputs!$C$37)/(1+$B19)^$L$27-Inputs!$C$27+Inputs!$C$28)/Inputs!$C$7 -> 305.27721 | F19: =(SUMPRODUCT($C31:$L31,1/(1+$B19)^$C$27:$L$27)*Inputs!$C$23+$L31*Inputs!$C$23*(1+Inputs!$C$37)/($B19-Inputs!$C$37)/(1+$B19)^$L$27-Inputs!$C$27+Inputs!$C$28)/Inputs!$C$7 -> 347.82296 | G19: =(SUMPRODUCT($C32:$L32,1/(1+$B19)^$C$27:$L$27)*Inputs!$C$23+$L32*Inputs!$C$23*(1+Inputs!$C$37)/($B19-Inputs!$C$37)/(1+$B19)^$L$27-Inputs!$C$27+Inputs!$C$28)/Inputs!$C$7 -> 395.16934 | I19: Compare with the price at the lock: $155.81.
B20: =WACC!$C$37+(1-2)*$C$5 -> 0.072017203 | C20: =(SUMPRODUCT($C28:$L28,1/(1+$B20)^$C$27:$L$27)*Inputs!$C$23+$L28*Inputs!$C$23*(1+Inputs!$C$37)/($B20-Inputs!$C$37)/(1+$B20)^$L$27-Inputs!$C$27+Inputs!$C$28)/Inputs!$C$7 -> 202.04522 | D20: =(SUMPRODUCT($C29:$L29,1/(1+$B20)^$C$27:$L$27)*Inputs!$C$23+$L29*Inputs!$C$23*(1+Inputs!$C$37)/($B20-Inputs!$C$37)/(1+$B20)^$L$27-Inputs!$C$27+Inputs!$C$28)/Inputs!$C$7 -> 231.89648 | E20: =(SUMPRODUCT($C30:$L30,1/(1+$B20)^$C$27:$L$27)*Inputs!$C$23+$L30*Inputs!$C$23*(1+Inputs!$C$37)/($B20-Inputs!$C$37)/(1+$B20)^$L$27-Inputs!$C$27+Inputs!$C$28)/Inputs!$C$7 -> 265.18874 | F20: =(SUMPRODUCT($C31:$L31,1/(1+$B20)^$C$27:$L$27)*Inputs!$C$23+$L31*Inputs!$C$23*(1+Inputs!$C$37)/($B20-Inputs!$C$37)/(1+$B20)^$L$27-Inputs!$C$27+Inputs!$C$28)/Inputs!$C$7 -> 302.26565 | G20: =(SUMPRODUCT($C32:$L32,1/(1+$B20)^$C$27:$L$27)*Inputs!$C$23+$L32*Inputs!$C$23*(1+Inputs!$C$37)/($B20-Inputs!$C$37)/(1+$B20)^$L$27-Inputs!$C$27+Inputs!$C$28)/Inputs!$C$7 -> 343.49946
B21: =WACC!$C$37+(2-2)*$C$5 -> 0.077017203 | C21: =(SUMPRODUCT($C28:$L28,1/(1+$B21)^$C$27:$L$27)*Inputs!$C$23+$L28*Inputs!$C$23*(1+Inputs!$C$37)/($B21-Inputs!$C$37)/(1+$B21)^$L$27-Inputs!$C$27+Inputs!$C$28)/Inputs!$C$7 -> 177.53351 | D21: =(SUMPRODUCT($C29:$L29,1/(1+$B21)^$C$27:$L$27)*Inputs!$C$23+$L29*Inputs!$C$23*(1+Inputs!$C$37)/($B21-Inputs!$C$37)/(1+$B21)^$L$27-Inputs!$C$27+Inputs!$C$28)/Inputs!$C$7 -> 203.93472 | E21: =(SUMPRODUCT($C30:$L30,1/(1+$B21)^$C$27:$L$27)*Inputs!$C$23+$L30*Inputs!$C$23*(1+Inputs!$C$37)/($B21-Inputs!$C$37)/(1+$B21)^$L$27-Inputs!$C$27+Inputs!$C$28)/Inputs!$C$7 -> 233.35771 | F21: =(SUMPRODUCT($C31:$L31,1/(1+$B21)^$C$27:$L$27)*Inputs!$C$23+$L31*Inputs!$C$23*(1+Inputs!$C$37)/($B21-Inputs!$C$37)/(1+$B21)^$L$27-Inputs!$C$27+Inputs!$C$28)/Inputs!$C$7 -> 266.10303 | G21: =(SUMPRODUCT($C32:$L32,1/(1+$B21)^$C$27:$L$27)*Inputs!$C$23+$L32*Inputs!$C$23*(1+Inputs!$C$37)/($B21-Inputs!$C$37)/(1+$B21)^$L$27-Inputs!$C$27+Inputs!$C$28)/Inputs!$C$7 -> 302.49618
B22: =WACC!$C$37+(3-2)*$C$5 -> 0.082017203 | C22: =(SUMPRODUCT($C28:$L28,1/(1+$B22)^$C$27:$L$27)*Inputs!$C$23+$L28*Inputs!$C$23*(1+Inputs!$C$37)/($B22-Inputs!$C$37)/(1+$B22)^$L$27-Inputs!$C$27+Inputs!$C$28)/Inputs!$C$7 -> 157.58996 | D22: =(SUMPRODUCT($C29:$L29,1/(1+$B22)^$C$27:$L$27)*Inputs!$C$23+$L29*Inputs!$C$23*(1+Inputs!$C$37)/($B22-Inputs!$C$37)/(1+$B22)^$L$27-Inputs!$C$27+Inputs!$C$28)/Inputs!$C$7 -> 181.19252 | E22: =(SUMPRODUCT($C30:$L30,1/(1+$B22)^$C$27:$L$27)*Inputs!$C$23+$L30*Inputs!$C$23*(1+Inputs!$C$37)/($B22-Inputs!$C$37)/(1+$B22)^$L$27-Inputs!$C$27+Inputs!$C$28)/Inputs!$C$7 -> 207.47742 | F22: =(SUMPRODUCT($C31:$L31,1/(1+$B22)^$C$27:$L$27)*Inputs!$C$23+$L31*Inputs!$C$23*(1+Inputs!$C$37)/($B22-Inputs!$C$37)/(1+$B22)^$L$27-Inputs!$C$27+Inputs!$C$28)/Inputs!$C$7 -> 236.71038 | G22: =(SUMPRODUCT($C32:$L32,1/(1+$B22)^$C$27:$L$27)*Inputs!$C$23+$L32*Inputs!$C$23*(1+Inputs!$C$37)/($B22-Inputs!$C$37)/(1+$B22)^$L$27-Inputs!$C$27+Inputs!$C$28)/Inputs!$C$7 -> 269.1791
B23: =WACC!$C$37+(4-2)*$C$5 -> 0.087017203 | C23: =(SUMPRODUCT($C28:$L28,1/(1+$B23)^$C$27:$L$27)*Inputs!$C$23+$L28*Inputs!$C$23*(1+Inputs!$C$37)/($B23-Inputs!$C$37)/(1+$B23)^$L$27-Inputs!$C$27+Inputs!$C$28)/Inputs!$C$7 -> 141.04744 | D23: =(SUMPRODUCT($C29:$L29,1/(1+$B23)^$C$27:$L$27)*Inputs!$C$23+$L29*Inputs!$C$23*(1+Inputs!$C$37)/($B23-Inputs!$C$37)/(1+$B23)^$L$27-Inputs!$C$27+Inputs!$C$28)/Inputs!$C$7 -> 162.33606 | E23: =(SUMPRODUCT($C30:$L30,1/(1+$B23)^$C$27:$L$27)*Inputs!$C$23+$L30*Inputs!$C$23*(1+Inputs!$C$37)/($B23-Inputs!$C$37)/(1+$B23)^$L$27-Inputs!$C$27+Inputs!$C$28)/Inputs!$C$7 -> 186.02694 | F23: =(SUMPRODUCT($C31:$L31,1/(1+$B23)^$C$27:$L$27)*Inputs!$C$23+$L31*Inputs!$C$23*(1+Inputs!$C$37)/($B23-Inputs!$C$37)/(1+$B23)^$L$27-Inputs!$C$27+Inputs!$C$28)/Inputs!$C$7 -> 212.35709 | G23: =(SUMPRODUCT($C32:$L32,1/(1+$B23)^$C$27:$L$27)*Inputs!$C$23+$L32*Inputs!$C$23*(1+Inputs!$C$37)/($B23-Inputs!$C$37)/(1+$B23)^$L$27-Inputs!$C$27+Inputs!$C$28)/Inputs!$C$7 -> 241.58305
B26: Helper: revenue paths for each growth view (years 1 to 10)
C27: 1 | D27: 2 | E27: 3 | F27: 4 | G27: 5 | H27: 6 | I27: 7 | J27: 8 | K27: 9 | L27: 10
B28: =C$18 -> 0.0412 | C28: =Inputs!$C$12*(1+IF(C$27<=Inputs!$C$46,$B28,$B28-($B28-Inputs!$C$37)*MIN(C$27-Inputs!$C$46,Inputs!$C$47)/Inputs!$C$47)) -> 10995.072 | D28: =C28*(1+IF(D$27<=Inputs!$C$46,$B28,$B28-($B28-Inputs!$C$37)*MIN(D$27-Inputs!$C$46,Inputs!$C$47)/Inputs!$C$47)) -> 11448.069 | E28: =D28*(1+IF(E$27<=Inputs!$C$46,$B28,$B28-($B28-Inputs!$C$37)*MIN(E$27-Inputs!$C$46,Inputs!$C$47)/Inputs!$C$47)) -> 11919.729 | F28: =E28*(1+IF(F$27<=Inputs!$C$46,$B28,$B28-($B28-Inputs!$C$37)*MIN(F$27-Inputs!$C$46,Inputs!$C$47)/Inputs!$C$47)) -> 12410.822 | G28: =F28*(1+IF(G$27<=Inputs!$C$46,$B28,$B28-($B28-Inputs!$C$37)*MIN(G$27-Inputs!$C$46,Inputs!$C$47)/Inputs!$C$47)) -> 12922.148 | H28: =G28*(1+IF(H$27<=Inputs!$C$46,$B28,$B28-($B28-Inputs!$C$37)*MIN(H$27-Inputs!$C$46,Inputs!$C$47)/Inputs!$C$47)) -> 13421.201 | I28: =H28*(1+IF(I$27<=Inputs!$C$46,$B28,$B28-($B28-Inputs!$C$37)*MIN(I$27-Inputs!$C$46,Inputs!$C$47)/Inputs!$C$47)) -> 13904.902 | J28: =I28*(1+IF(J$27<=Inputs!$C$46,$B28,$B28-($B28-Inputs!$C$37)*MIN(J$27-Inputs!$C$46,Inputs!$C$47)/Inputs!$C$47)) -> 14370.16 | K28: =J28*(1+IF(K$27<=Inputs!$C$46,$B28,$B28-($B28-Inputs!$C$37)*MIN(K$27-Inputs!$C$46,Inputs!$C$47)/Inputs!$C$47)) -> 14813.91 | L28: =K28*(1+IF(L$27<=Inputs!$C$46,$B28,$B28-($B28-Inputs!$C$37)*MIN(L$27-Inputs!$C$46,Inputs!$C$47)/Inputs!$C$47)) -> 15233.144
B29: =D$18 -> 0.0612 | C29: =Inputs!$C$12*(1+IF(C$27<=Inputs!$C$46,$B29,$B29-($B29-Inputs!$C$37)*MIN(C$27-Inputs!$C$46,Inputs!$C$47)/Inputs!$C$47)) -> 11206.272 | D29: =C29*(1+IF(D$27<=Inputs!$C$46,$B29,$B29-($B29-Inputs!$C$37)*MIN(D$27-Inputs!$C$46,Inputs!$C$47)/Inputs!$C$47)) -> 11892.096 | E29: =D29*(1+IF(E$27<=Inputs!$C$46,$B29,$B29-($B29-Inputs!$C$37)*MIN(E$27-Inputs!$C$46,Inputs!$C$47)/Inputs!$C$47)) -> 12619.892 | F29: =E29*(1+IF(F$27<=Inputs!$C$46,$B29,$B29-($B29-Inputs!$C$37)*MIN(F$27-Inputs!$C$46,Inputs!$C$47)/Inputs!$C$47)) -> 13392.23 | G29: =F29*(1+IF(G$27<=Inputs!$C$46,$B29,$B29-($B29-Inputs!$C$37)*MIN(G$27-Inputs!$C$46,Inputs!$C$47)/Inputs!$C$47)) -> 14211.834 | H29: =G29*(1+IF(H$27<=Inputs!$C$46,$B29,$B29-($B29-Inputs!$C$37)*MIN(H$27-Inputs!$C$46,Inputs!$C$47)/Inputs!$C$47)) -> 14988.084 | I29: =H29*(1+IF(I$27<=Inputs!$C$46,$B29,$B29-($B29-Inputs!$C$37)*MIN(I$27-Inputs!$C$46,Inputs!$C$47)/Inputs!$C$47)) -> 15708.112 | J29: =I29*(1+IF(J$27<=Inputs!$C$46,$B29,$B29-($B29-Inputs!$C$37)*MIN(J$27-Inputs!$C$46,Inputs!$C$47)/Inputs!$C$47)) -> 16359.37 | K29: =J29*(1+IF(K$27<=Inputs!$C$46,$B29,$B29-($B29-Inputs!$C$37)*MIN(K$27-Inputs!$C$46,Inputs!$C$47)/Inputs!$C$47)) -> 16929.985 | L29: =K29*(1+IF(L$27<=Inputs!$C$46,$B29,$B29-($B29-Inputs!$C$37)*MIN(L$27-Inputs!$C$46,Inputs!$C$47)/Inputs!$C$47)) -> 17409.104
B30: =E$18 -> 0.0812 | C30: =Inputs!$C$12*(1+IF(C$27<=Inputs!$C$46,$B30,$B30-($B30-Inputs!$C$37)*MIN(C$27-Inputs!$C$46,Inputs!$C$47)/Inputs!$C$47)) -> 11417.472 | D30: =C30*(1+IF(D$27<=Inputs!$C$46,$B30,$B30-($B30-Inputs!$C$37)*MIN(D$27-Inputs!$C$46,Inputs!$C$47)/Inputs!$C$47)) -> 12344.571 | E30: =D30*(1+IF(E$27<=Inputs!$C$46,$B30,$B30-($B30-Inputs!$C$37)*MIN(E$27-Inputs!$C$46,Inputs!$C$47)/Inputs!$C$47)) -> 13346.95 | F30: =E30*(1+IF(F$27<=Inputs!$C$46,$B30,$B30-($B30-Inputs!$C$37)*MIN(F$27-Inputs!$C$46,Inputs!$C$47)/Inputs!$C$47)) -> 14430.722 | G30: =F30*(1+IF(G$27<=Inputs!$C$46,$B30,$B30-($B30-Inputs!$C$37)*MIN(G$27-Inputs!$C$46,Inputs!$C$47)/Inputs!$C$47)) -> 15602.497 | H30: =G30*(1+IF(H$27<=Inputs!$C$46,$B30,$B30-($B30-Inputs!$C$37)*MIN(H$27-Inputs!$C$46,Inputs!$C$47)/Inputs!$C$47)) -> 16704.345 | I30: =H30*(1+IF(I$27<=Inputs!$C$46,$B30,$B30-($B30-Inputs!$C$37)*MIN(I$27-Inputs!$C$46,Inputs!$C$47)/Inputs!$C$47)) -> 17707.274 | J30: =I30*(1+IF(J$27<=Inputs!$C$46,$B30,$B30-($B30-Inputs!$C$37)*MIN(J$27-Inputs!$C$46,Inputs!$C$47)/Inputs!$C$47)) -> 18583.076 | K30: =J30*(1+IF(K$27<=Inputs!$C$46,$B30,$B30-($B30-Inputs!$C$37)*MIN(K$27-Inputs!$C$46,Inputs!$C$47)/Inputs!$C$47)) -> 19305.586 | L30: =K30*(1+IF(L$27<=Inputs!$C$46,$B30,$B30-($B30-Inputs!$C$37)*MIN(L$27-Inputs!$C$46,Inputs!$C$47)/Inputs!$C$47)) -> 19851.934
B31: =F$18 -> 0.1012 | C31: =Inputs!$C$12*(1+IF(C$27<=Inputs!$C$46,$B31,$B31-($B31-Inputs!$C$37)*MIN(C$27-Inputs!$C$46,Inputs!$C$47)/Inputs!$C$47)) -> 11628.672 | D31: =C31*(1+IF(D$27<=Inputs!$C$46,$B31,$B31-($B31-Inputs!$C$37)*MIN(D$27-Inputs!$C$46,Inputs!$C$47)/Inputs!$C$47)) -> 12805.494 | E31: =D31*(1+IF(E$27<=Inputs!$C$46,$B31,$B31-($B31-Inputs!$C$37)*MIN(E$27-Inputs!$C$46,Inputs!$C$47)/Inputs!$C$47)) -> 14101.41 | F31: =E31*(1+IF(F$27<=Inputs!$C$46,$B31,$B31-($B31-Inputs!$C$37)*MIN(F$27-Inputs!$C$46,Inputs!$C$47)/Inputs!$C$47)) -> 15528.472 | G31: =F31*(1+IF(G$27<=Inputs!$C$46,$B31,$B31-($B31-Inputs!$C$37)*MIN(G$27-Inputs!$C$46,Inputs!$C$47)/Inputs!$C$47)) -> 17099.954 | H31: =G31*(1+IF(H$27<=Inputs!$C$46,$B31,$B31-($B31-Inputs!$C$37)*MIN(H$27-Inputs!$C$46,Inputs!$C$47)/Inputs!$C$47)) -> 18581.152 | I31: =H31*(1+IF(I$27<=Inputs!$C$46,$B31,$B31-($B31-Inputs!$C$37)*MIN(I$27-Inputs!$C$46,Inputs!$C$47)/Inputs!$C$47)) -> 19919.738 | J31: =I31*(1+IF(J$27<=Inputs!$C$46,$B31,$B31-($B31-Inputs!$C$37)*MIN(J$27-Inputs!$C$46,Inputs!$C$47)/Inputs!$C$47)) -> 21064.326 | K31: =J31*(1+IF(K$27<=Inputs!$C$46,$B31,$B31-($B31-Inputs!$C$37)*MIN(K$27-Inputs!$C$46,Inputs!$C$47)/Inputs!$C$47)) -> 21967.564 | L31: =K31*(1+IF(L$27<=Inputs!$C$46,$B31,$B31-($B31-Inputs!$C$37)*MIN(L$27-Inputs!$C$46,Inputs!$C$47)/Inputs!$C$47)) -> 22589.246
B32: =G$18 -> 0.1212 | C32: =Inputs!$C$12*(1+IF(C$27<=Inputs!$C$46,$B32,$B32-($B32-Inputs!$C$37)*MIN(C$27-Inputs!$C$46,Inputs!$C$47)/Inputs!$C$47)) -> 11839.872 | D32: =C32*(1+IF(D$27<=Inputs!$C$46,$B32,$B32-($B32-Inputs!$C$37)*MIN(D$27-Inputs!$C$46,Inputs!$C$47)/Inputs!$C$47)) -> 13274.864 | E32: =D32*(1+IF(E$27<=Inputs!$C$46,$B32,$B32-($B32-Inputs!$C$37)*MIN(E$27-Inputs!$C$46,Inputs!$C$47)/Inputs!$C$47)) -> 14883.778 | F32: =E32*(1+IF(F$27<=Inputs!$C$46,$B32,$B32-($B32-Inputs!$C$37)*MIN(F$27-Inputs!$C$46,Inputs!$C$47)/Inputs!$C$47)) -> 16687.692 | G32: =F32*(1+IF(G$27<=Inputs!$C$46,$B32,$B32-($B32-Inputs!$C$37)*MIN(G$27-Inputs!$C$46,Inputs!$C$47)/Inputs!$C$47)) -> 18710.24 | H32: =G32*(1+IF(H$27<=Inputs!$C$46,$B32,$B32-($B32-Inputs!$C$37)*MIN(H$27-Inputs!$C$46,Inputs!$C$47)/Inputs!$C$47)) -> 20630.285 | I32: =H32*(1+IF(I$27<=Inputs!$C$46,$B32,$B32-($B32-Inputs!$C$37)*MIN(I$27-Inputs!$C$46,Inputs!$C$47)/Inputs!$C$47)) -> 22364.054 | J32: =I32*(1+IF(J$27<=Inputs!$C$46,$B32,$B32-($B32-Inputs!$C$37)*MIN(J$27-Inputs!$C$46,Inputs!$C$47)/Inputs!$C$47)) -> 23828.005 | K32: =J32*(1+IF(K$27<=Inputs!$C$46,$B32,$B32-($B32-Inputs!$C$37)*MIN(K$27-Inputs!$C$46,Inputs!$C$47)/Inputs!$C$47)) -> 24945.062 | L32: =K32*(1+IF(L$27<=Inputs!$C$46,$B32,$B32-($B32-Inputs!$C$37)*MIN(L$27-Inputs!$C$46,Inputs!$C$47)/Inputs!$C$47)) -> 25651.007

Sheet Check
B2: Intercontinental Exchange (ICE): check against the Python pipeline
B3: Python values are typed in (blue) from the pipeline that runs the site. Each row passes if the two agree within the tolerance.
B5: Item | C5: This workbook | D5: Python pipeline | E5: Difference | F5: Result
B6: Unlevered free-cash-flow margin | C6: =Inputs!$C$23 -> 0.49526515 | D6: 0.49526515 | E6: =C6-D6 -> 1.5151515e-09 | F6: =IF(ABS(E6)<=0.00005,"Pass","Check") -> Pass
B7: Group median unlevered beta | C7: =WACC!$C$14 -> 0.60913153 | D7: 0.60913153 | E7: =C7-D7 -> -3.7891912e-13 | F7: =IF(ABS(E7)<=0.0005,"Pass","Check") -> Pass
B8: WACC | C8: =WACC!$C$37 -> 0.077017203 | D8: 0.0770172 | E8: =C8-D8 -> 2.6214128e-09 | F8: =IF(ABS(E8)<=0.00005,"Pass","Check") -> Pass
B9: Terminal growth | C9: =Inputs!$C$37 -> 0.0283 | D9: 0.0283 | E9: =C9-D9 -> 0 | F9: =IF(ABS(E9)<=0.00005,"Pass","Check") -> Pass
B10: Anchor | C10: =Inputs!$C$43 -> 0.0812 | D10: 0.0812 | E10: =C10-D10 -> 0 | F10: =IF(ABS(E10)<=0.00005,"Pass","Check") -> Pass
B11: Implied growth, base case | C11: =Solver!$W$7 -> 0.022919701 | D11: 0.02291971 | E11: =C11-D11 -> -8.8382457e-09 | F11: =IF(ABS(E11)<=0.00005,"Pass","Check") -> Pass
B12: Implied growth, WACC one point higher | C12: =Sensitivity!$E$14 -> 0.055293888 | D12: 0.05529393 | E12: =C12-D12 -> -4.2146378e-08 | F12: =IF(ABS(E12)<=0.0002,"Pass","Check") -> Pass
B13: Value per share at the anchor ($) | C13: =DCF!$C$41 -> 233.35771 | D13: 233.35771 | E13: =C13-D13 -> -2.0651498e-09 | F13: =IF(ABS(E13)<=0.0233357705277935,"Pass","Check") -> Pass
B14: Panel A value minus price ($) | C14: =DCF!$C$21-DCF!$C$22 -> 1.4248371e-09 | D14: 0 | E14: =C14-D14 -> 1.4248371e-09 | F14: =IF(ABS(E14)<=0.01,"Pass","Check") -> Pass | G14: Panel B on the DCF tab uses your view; with the yellow cell at the anchor it matches the pipeline.
B16: Overall | C16: =IF(COUNTIF(F6:F14,"Pass")=9,"All checks pass","Review") -> All checks pass
